Workbook
Name Scenario: Assumptions!$B$3

Sheet Cover
B3: WHOOP Inc.
B4: Private Company Valuation
B5: Investment Committee Memo — Supporting Model
B8: Company: | C8: WHOOP Inc.
B9: Ticker: | C9: Private (Pre-IPO)
B10: Last Round: | C10: Series G — $575M at $10.1B post-money (Mar 31, 2026)
B11: Model Date: | C11: April 16, 2026
B12: Analyst: | C12: Landon Brice
B13: Fiscal Year: | C13: Calendar Year (Jan-Dec)
B14: Currency: | C14: USD ($M unless noted)
B17: Valuation Methods:
B18: 1. Intrinsic DCF (scenario-based + real options)
B19: 2. Trading Comps (three-bucket framework)
B20: 3. Precedent Transactions
B21: 4. Last-Round Implied ($10.1B)
B22: 5. Implied IPO Trading Range (back-solved)
B25: Color Convention:
B26: Hard-coded input
B27: Formula / calculation
B28: Cross-sheet link
B29: Needs verification / FLAGGED_GAP
B32: Source Files:
B33: Valuation Summary (live, scenario-driven)
B34: Active Scenario | C34: =Assumptions!$B$3 -> Base
B36: Base DCF — Enterprise Value | C36: =DCF!C39 -> 9467.9686
B37: + Cash | C37: =DCF!C44 -> 700
B38: − Debt | C38: =DCF!C43 -> -10
B39: = Equity Value | C39: =DCF!C45 -> 10157.969
B40: Per Share (FD) | C40: =DCF!C47 -> 24.775533
B42: Real Options (Expected) | C42: =DCF!C53 -> 2392.5
B43: Total EV (DCF + Options) | C43: =DCF!C54 -> 11860.469
B45: Series G Mark | C45: =DCF!C59 -> 10100
B46: Base DCF vs Series G | C46: =DCF!C60 -> -0.062577364
B47: DCF + Options vs Series G | C47: =DCF!C61 -> 0.17430382
B48: Football Field (multi-method synthesis)
B49: Weighted Average EV | C49: ='Football Field'!D16*1000 -> 8635.452
B50: Per Share (FD) | C50: ='Football Field'!G16 -> 22.745005
B51: vs Series G | C51: ='Football Field'!D18 -> -0.14500475
B53: Model Integrity (Checks tab)
B54: Passing | C54: =Checks!B17 -> 7
B55: Warning | C55: =Checks!B18 -> 2
B56: Failing | C56: =Checks!B19 -> 0
B57: Overall | C57: =Checks!B20 -> WARN
B59: Framing Decision — Base Case vs Real Options
B60: Base DCF reflects WHOOP's subscription-driven unit economics if executed (terminal EBITDA ~33%, GM 76%). The bucket-3 weight (30-40% per methodology) is expressed via the 4.5x exit multiple (50% compressed from B3 ~9x), NOT via P&L margin compression. Real options ($2.4B) capture the platform-becoming-true scenarios (healthcare reimbursement, B2B clinical, women's health) on top of base case execution. By construction these are separate value sources — base case = 'WHOOP executes its current plan'; options = 'WHOOP earns the bucket-3 narrative'.
B61: Memo conclusion: Base DCF $9.5B (-6% vs mark) anchors fair value. Multi-method football field $8.6B (-14% vs mark) shows comps undershoot before growth premium. DCF + Real Options $11.9B (+18% vs mark) shows where Series G investors are positioned IF they credit bucket-3 thesis. Series G is paying for growth + optionality, not static comp value.

Sheet Assumptions
A1: WHOOP — Master Assumptions
A3: Scenario: | B3: Base | C3: Select Bear / Base / Bull — drives Active column F throughout the model. Other tabs reference Active values only.
A5: ID | B5: Assumption | C5: Bear | D5: Base | E5: Bull | F5: Active | G5: Tier | H5: Status | I5: Notes
A7: Section 1: Revenue & Growth
A8: R3a | B8: 2025 Beginning Members (M) | C8: 1.5 | D8: 1.3 | E8: 1.1 | F8: =IF($B$3="Bear",C8,IF($B$3="Bull",E8,D8)) -> 1.3 | G8: Tier 3 | H8: High | I8: Back-solved to reconcile avg×ARPU ≈ $650M base. Bear slower decel; bull faster acquisition.
A9: R3b | B9: 2025 Ending Members (M) | C9: 2.3 | D9: 2.5 | E9: 2.7 | F9: =IF($B$3="Bear",C9,IF($B$3="Bull",E9,D9)) -> 2.5 | G9: Tier 1 | H9: Critical | I9: Series G press release: 2.5M+ paying members
A10: R3 | B10: 2025 Average Members (M) — DERIVED | C10: =(C8+C9)/2 -> 1.9 | D10: =(D8+D9)/2 -> 1.9 | E10: =(E8+E9)/2 -> 1.9 | F10: =IF($B$3="Bear",C10,IF($B$3="Bull",E10,D10)) -> 1.9 | G10: Derived | H10: Critical | I10: Per methodology: ARPU applies to AVERAGE members during period, NOT year-end.
A11: R4 | B11: 2025 Blended ARPU ($/yr) | C11: 300 | D11: 338 | E11: 375 | F11: =IF($B$3="Bear",C11,IF($B$3="Bull",E11,D11)) -> 338 | G11: Tier 3 | H11: Critical | I11: v2 build per CLAUDE.md rebuild directives ($300/$338/$375). Single-line; 5-component decomposition deferred to ARPU tab.
A12: R1 | B12: 2025 Recognized Revenue ($M) — DERIVED | C12: =C10*C11 -> 570 | D12: =D10*D11 -> 642.2 | E12: =E10*E11 -> 712.5 | F12: =IF($B$3="Bear",C12,IF($B$3="Bull",E12,D12)) -> 642.2 | G12: Derived | H12: Critical | I12: DERIVED: Avg Members × Blended ARPU. Target ~$650M base. Methodology consistency check: must reconcile within ±5%.
A13: R2 | B13: 2025 Bookings Run-Rate ($M) | C13: 1100 | D13: 1100 | E13: 1100 | F13: =IF($B$3="Bear",C13,IF($B$3="Bull",E13,D13)) -> 1100 | G13: Tier 1 | H13: Locked | I13: Series G press release; CEO statement (Dec 2025 exit rate × 12)
A14: R5 | B14: Subscription Revenue % | C14: 0.8 | D14: 0.85 | E14: 0.88 | F14: =IF($B$3="Bear",C14,IF($B$3="Bull",E14,D14)) -> 0.85 | G14: Tier 2 | H14: High | I14: Sacra/BMCT: ~80-88% range
A15: R6 | B15: 2025 YoY Subscription Growth | C15: 1.03 | D15: 1.03 | E15: 1.03 | F15: =IF($B$3="Bear",C15,IF($B$3="Bull",E15,D15)) -> 1.03 | G15: Tier 1 | H15: Locked | I15: Series G press release: 103%
A16: R7 | B16: Phase 1 Revenue Growth (2026-27) | C16: 0.5 | D16: 0.7 | E16: 0.9 | F16: =IF($B$3="Bear",C16,IF($B$3="Bull",E16,D16)) -> 0.7 | G16: Tier 3 | H16: Critical | I16: Peer trajectories; Series G deployment & WHOOP 5.0 cycle
A17: R8 | B17: Phase 2 Revenue Growth (2028-30) | C17: 0.15 | D17: 0.25 | E17: 0.4 | F17: =IF($B$3="Bear",C17,IF($B$3="Bull",E17,D17)) -> 0.25 | G17: Tier 3 | H17: Critical | I17: Deceleration shape: Dexcom (bull) / Netflix (base) / Peloton (bear)
A18: R9 | B18: Phase 3 Revenue Growth (2031-33) | C18: 0.05 | D18: 0.12 | E18: 0.2 | F18: =IF($B$3="Bear",C18,IF($B$3="Bull",E18,D18)) -> 0.12 | G18: Tier 3 | H18: High | I18: TAM ceiling; healthcare attach resolution
A19: R10a | B19: Year-1 Cohort Annual Churn | C19: 0.3 | D19: 0.22 | E19: 0.15 | F19: =IF($B$3="Bear",C19,IF($B$3="Bull",E19,D19)) -> 0.22 | G19: Tier 3 | H19: Critical | I19: Highest churn ("try and quit"). Will drive Members tab cohort engine.
A20: R10b | B20: Year-2 Cohort Annual Churn | C20: 0.18 | D20: 0.14 | E20: 0.1 | F20: =IF($B$3="Bear",C20,IF($B$3="Bull",E20,D20)) -> 0.14 | G20: Tier 3 | H20: Critical | I20: Stabilizing cohort
A21: R10c | B21: Year-3+ Cohort Annual Churn | C21: 0.12 | D21: 0.08 | E21: 0.05 | F21: =IF($B$3="Bear",C21,IF($B$3="Bull",E21,D21)) -> 0.08 | G21: Tier 3 | H21: Critical | I21: Retained core; very sticky power users
A22: R11 | B22: International Revenue % | C22: 0.35 | D22: 0.43 | E22: 0.55 | F22: =IF($B$3="Bear",C22,IF($B$3="Bull",E22,D22)) -> 0.43 | G22: Tier 2 | H22: High | I22: Stress-tested: 40-45% base; NYT DealBook source ambiguous on "new sales" vs total
A23: R12 | B23: B2B Unite Revenue % | C23: 0.12 | D23: 0.18 | E23: 0.25 | F23: =IF($B$3="Bear",C23,IF($B$3="Bull",E23,D23)) -> 0.18 | G23: Tier 2 | H23: Medium | I23: Sacra/BMCT: ~20% recurring revenue; growing rapidly
A24: R14 | B24: Advanced Labs Attach Rate | C24: 0.03 | D24: 0.1 | E24: 0.25 | F24: =IF($B$3="Bear",C24,IF($B$3="Bull",E24,D24)) -> 0.1 | G24: Tier 3 | H24: Critical | I24: BUCKET-3 THESIS VARIABLE. Bear/Base/Bull per methodology Sec 3. Single most important ARPU assumption — swings $80/member.
... A28: R19 | B28: Deferred Revenue Adjustment (% of bookings) | C28: -0.1 | D28: -0.08 | E28: -0.05 | F28: =IF($B$3="Bear",C28,IF($B$3="Bull",E28,D28)) -> -0.08 | G28: Tier 3 | H28: Medium | I28: Drag during growth (recognized < booked); ASC 606. Approaches 0 at steady state.
A30: Section 2: Cost Structure & Margins
A31: C1 | B31: Hardware BOM per Device ($) | C31: 100 | D31: 80 | E31: 60 | F31: =IF($B$3="Bear",C31,IF($B$3="Bull",E31,D31)) -> 80 | G31: Tier 3 | H31: Critical | I31: Est. $50-80 at scale; 2016 BOM was $250-300 per Contrary Research
A32: C2 | B32: Loaded Hardware Cost per Acquisition ($) | C32: 150 | D32: 120 | E32: 90 | F32: =IF($B$3="Bear",C32,IF($B$3="Bull",E32,D32)) -> 120 | G32: Tier 3 | H32: Critical | I32: C1 + assembly, ship, warranty, returns. Drives unit economics.
A33: C4 | B33: Subscription Delivery Cost (% of sub rev) | C33: 0.15 | D33: 0.1 | E33: 0.08 | F33: =IF($B$3="Bear",C33,IF($B$3="Bull",E33,D33)) -> 0.1 | G33: Tier 3 | H33: High | I33: Infra + support; AWS/GCP benchmarks; declining at scale
A34: C5 | B34: Subscription Gross Margin (standalone) | C34: 0.72 | D34: 0.78 | E34: 0.83 | F34: =IF($B$3="Bear",C34,IF($B$3="Bull",E34,D34)) -> 0.78 | G34: Tier 3 | H34: Critical | I34: Peer: pure SaaS ~80%, Dexcom ~64% (incl consumables). WHOOP higher quality recurring.
A35: C6 | B35: Hardware Gross Margin (standalone) | C35: -0.1 | D35: -0.02 | E35: 0.05 | F35: =IF($B$3="Bear",C35,IF($B$3="Bull",E35,D35)) -> -0.02 | G35: Tier 3 | H35: Critical | I35: Subsidized at acquisition; Peloton HW GM trajectory: -18% to +14%
A36: C7a | B36: Blended GM Phase 1 (2026-27) | C36: 0.56 | D36: 0.6 | E36: 0.64 | F36: =IF($B$3="Bear",C36,IF($B$3="Bull",E36,D36)) -> 0.6 | G36: Tier 3 | H36: Critical | I36: Derived prior; lower in growth years (more hardware drag)
A37: C7b | B37: Blended GM Phase 2 (2028-30) | C37: 0.63 | D37: 0.67 | E37: 0.72 | F37: =IF($B$3="Bear",C37,IF($B$3="Bull",E37,D37)) -> 0.67 | G37: Tier 3 | H37: High | I37: Margin expansion as growth decelerates
A38: C7c | B38: Blended GM Terminal | C38: 0.72 | D38: 0.76 | E38: 0.8 | F38: =IF($B$3="Bear",C38,IF($B$3="Bull",E38,D38)) -> 0.76 | G38: Tier 3 | H38: High | I38: Peer terminal: Dexcom 60%, Spotify 32%; software-heavy mix at scale
A39: C8a | B39: R&D % of Revenue (current) | C39: 0.25 | D39: 0.22 | E39: 0.2 | F39: =IF($B$3="Bear",C39,IF($B$3="Bull",E39,D39)) -> 0.22 | G39: Tier 3 | H39: High | I39: Peers: Dexcom 13%, Garmin 16%, growth SaaS 20-30%
A40: C8b | B40: R&D % of Revenue (terminal) | C40: 0.12 | D40: 0.15 | E40: 0.18 | F40: =IF($B$3="Bear",C40,IF($B$3="Bull",E40,D40)) -> 0.15 | G40: Tier 3 | H40: Medium | I40: Peer steady-state
A41: C9 | B41: S&M % of Revenue (current) | C41: 0.35 | D41: 0.3 | E41: 0.25 | F41: =IF($B$3="Bear",C41,IF($B$3="Bull",E41,D41)) -> 0.3 | G41: Tier 3 | H41: Critical | I41: Peloton peak 28.4% FY22, current 16.9% FY25. Bear = stuck high.
A42: C9a | B42: Paid CAC per Gross Add ($) | C42: 220 | D42: 175 | E42: 130 | F42: =IF($B$3="Bear",C42,IF($B$3="Bull",E42,D42)) -> 175 | G42: Tier 3 | H42: Critical | I42: 30-50% of first-year ARPU. S&M consistency check on Checks tab.
... A53: C12 | B53: D&A % of Revenue | C53: 0.045 | D53: 0.035 | E53: 0.025 | F53: =IF($B$3="Bear",C53,IF($B$3="Bull",E53,D53)) -> 0.035 | G53: Tier 2 | H53: Medium | I53: D&A trails CapEx (~4% of rev) as PP&E ramps. Lower in bull (asset-light scale economies). Used in FCF tab to compute NOPAT → UFCF bridge.
A54: Section 3: Capital Structure & Cap Table (incl. cash yield)
A55: S1 | B55: Fully Diluted Shares Outstanding (M) | C55: 420 | D55: 410 | E55: 400 | F55: =IF($B$3="Bear",C55,IF($B$3="Bull",E55,D55)) -> 410 | G55: Tier 3 | H55: Critical | I55: 361.2M common + ~50M option pool est. Pitchbook auth pref 537.9M, outs 361.2M.
A56: S2 | B56: Series G Price per Share ($) | C56: 28 | D56: 28 | E56: 28 | F56: =IF($B$3="Bear",C56,IF($B$3="Bull",E56,D56)) -> 28 | G56: Tier 2 | H56: High | I56: Pitchbook Series G data; back-solve from $575M raise / shares issued
A57: S3 | B57: Liquidation Preference Type | C57: Participating | D57: 1x non-participating | E57: 1x non-participating | F57: =IF($B$3="Bear",C57,IF($B$3="Bull",E57,D57)) -> 1x non-participating | G57: Tier 2 | H57: Locked | I57: Pitchbook: 1x non-participating pari passu. Bear assumes participating ratchet.
A58: S4 | B58: Total Liquidation Preference ($M) | C58: 1400 | D58: 1400 | E58: 1400 | F58: =IF($B$3="Bear",C58,IF($B$3="Bull",E58,D58)) -> 1400 | G58: Tier 2 | H58: High | I58: Sum of preferred raises: ~$1.4B aggregate (Series A through G)
A59: S7 | B59: Option Pool Size (% of FD shares) | C59: 0.15 | D59: 0.12 | E59: 0.1 | F59: =IF($B$3="Bear",C59,IF($B$3="Bull",E59,D59)) -> 0.12 | G59: Tier 3 | H59: High | I59: Typical 10-15% pre-IPO; 600-person hiring surge implies aggressive granting
A60: S8 | B60: Founder Ownership Ahmed (% FD) | C60: 0.1 | D60: 0.14 | E60: 0.18 | F60: =IF($B$3="Bear",C60,IF($B$3="Bull",E60,D60)) -> 0.14 | G60: Tier 3 | H60: Medium | I60: 12-18% est. across 7 rounds + pool refreshes; possibly lower with secondaries
A61: S9 | B61: DLOM (Discount for Lack of Marketability) | C61: 0.3 | D61: 0.22 | E61: 0.15 | F61: =IF($B$3="Bear",C61,IF($B$3="Bull",E61,D61)) -> 0.22 | G61: Tier 2 | H61: High | I61: Oura tender 25%; EquityZen avg 13-29%; Hiive 39-51% deeper discount
A62: S10 | B62: Debt on Balance Sheet ($M) | C62: 50 | D62: 10 | E62: 0 | F62: =IF($B$3="Bear",C62,IF($B$3="Bull",E62,D62)) -> 10 | G62: Tier 2 | H62: Low | I62: Likely minimal/zero; Pitchbook shows $10.13M debt round Mar 2024
A63: S11 | B63: Cash post Series G ($M) | C63: 500 | D63: 700 | E63: 850 | F63: =IF($B$3="Bear",C63,IF($B$3="Bull",E63,D63)) -> 700 | G63: Tier 3 | H63: Medium | I63: Back-solve: $575M raise + operating cash flow positive entering 2026
A64: S12 | B64: EV-to-Equity Bridge ($M) — DERIVED | C64: =C63-C62 -> 450 | D64: =D63-D62 -> 690 | E64: =E63-E62 -> 850 | F64: =IF($B$3="Bear",C64,IF($B$3="Bull",E64,D64)) -> 690 | G64: Derived | H64: High | I64: Cash − Debt: add to EV to bridge to equity value
A65: S15 | B65: Series F Ratchet / IPO Provisions | C65: Live | D65: Likely extinguished | E65: Extinguished | F65: =IF($B$3="Bear",C65,IF($B$3="Bull",E65,D65)) -> Likely extinguished | G65: Tier 3 | H65: High | I65: Likely extinguished at Series G close; SoftBank notably absent from Series G syndicate
A66: S16 | B66: Dual-Class Share Structure (IPO) | C66: Single class | D66: Dual class | E66: Dual class | F66: =IF($B$3="Bear",C66,IF($B$3="Bull",E66,D66)) -> Dual class | G66: Tier 3 | H66: Medium | I66: Common for founder-led tech IPOs (Meta, Snap, Airbnb); not disclosed
A67: C18 | B67: Cash money-market yield (interest income on idle balance) | C67: 0.025 | D67: 0.035 | E67: 0.045 | F67: =IF($B$3="Bear",C67,IF($B$3="Bull",E67,D67)) -> 0.035 | G67: Tier 2 | H67: Medium | I67: Yield on idle Series G cash. Apply to PRIOR-YEAR ending cash balance to avoid circularity (no feedback into current year cash).
A68: Section 4: WACC / Discount Rate (Damodaran Apr 2026)
A69: D1 | B69: Risk-Free Rate (10yr UST) | C69: 0.043 | D69: 0.043 | E69: 0.043 | F69: =IF($B$3="Bear",C69,IF($B$3="Bull",E69,D69)) -> 0.043 | G69: Tier 1 | H69: Locked | I69: Fed H.15, Apr 14 2026: 4.26%; rounded 4.3%
A70: D2 | B70: Equity Risk Premium | C70: 0.045 | D70: 0.045 | E70: 0.045 | F70: =IF($B$3="Bear",C70,IF($B$3="Bull",E70,D70)) -> 0.045 | G70: Tier 1 | H70: Point Est. | I70: Damodaran 4.23% (Jan 2026); Kroll 5.0%; midpoint 4.5%
A71: D3 | B71: Unlevered Beta (bucket-weighted) | C71: 0.85 | D71: 0.83 | E71: 0.81 | F71: =IF($B$3="Bear",C71,IF($B$3="Bull",E71,D71)) -> 0.83 | G71: Tier 1 | H71: Sensitivity | I71: Damodaran sector: Healthcare 0.83, Electronics 0.83. Bucket-weighted.
A72: D4 | B72: Size Premium | C72: 0.0081 | D72: 0.0081 | E72: 0.0081 | F72: =IF($B$3="Bear",C72,IF($B$3="Bull",E72,D72)) -> 0.0081 | G72: Tier 2 | H72: Point Est. | I72: Kroll CRSP Decile 3 ($7.3-13.5B): 0.81%
A73: D5 | B73: Company-Specific Risk Premium (CSRP) | C73: 0.03 | D73: 0.02 | E73: 0.01 | F73: =IF($B$3="Bear",C73,IF($B$3="Bull",E73,D73)) -> 0.02 | G73: Tier 3 | H73: Sensitivity | I73: Pre-IPO execution risk + private illiquidity; 1-3% range
A74: D8 | B74: Implied Cost of Equity / WACC — DERIVED | C74: =C69+C70*C71+C72+C73 -> 0.11935 | D74: =D69+D70*D71+D72+D73 -> 0.10845 | E74: =E69+E70*E71+E72+E73 -> 0.09755 | F74: =IF($B$3="Bear",C74,IF($B$3="Bull",E74,D74)) -> 0.10845 | G74: Derived | H74: Critical
A76: Section 5: Terminal Value
A77: D9 | B77: Terminal Method (primary) | C77: Exit Multiple | D77: Exit Multiple | E77: Exit Multiple | F77: =IF($B$3="Bear",C77,IF($B$3="Bull",E77,D77)) -> Exit Multiple | G77: Design | H77: Locked | I77: Primary: EV/Revenue exit multiple; cross-check: Gordon Growth
A78: D11 | B78: Terminal EV/Revenue Multiple | C78: 3.5 | D78: 4.5 | E78: 6 | F78: =IF($B$3="Bear",C78,IF($B$3="Bull",E78,D78)) -> 4.5 | G78: Tier 3 | H78: Critical | I78: Compressed 40-60% from current comps; reflects terminal growth 10-15%
A79: D12 | B79: Terminal EV/EBITDA Multiple | C79: 12 | D79: 15 | E79: 18 | F79: =IF($B$3="Bear",C79,IF($B$3="Bull",E79,D79)) -> 15 | G79: Tier 3 | H79: High | I79: Cross-check only; more stable than revenue multiple at maturity
A80: D13 | B80: Perpetuity Growth Rate (Gordon) | C80: 0.025 | D80: 0.03 | E80: 0.035 | F80: =IF($B$3="Bear",C80,IF($B$3="Bull",E80,D80)) -> 0.03 | G80: Tier 2 | H80: Critical | I80: GDP growth + inflation; cannot exceed WACC
A81: D28 | B81: Multiple Compression Factor | C81: 0.4 | D81: 0.5 | E81: 0.6 | F81: =IF($B$3="Bear",C81,IF($B$3="Bull",E81,D81)) -> 0.5 | G81: Tier 3 | H81: High | I81: Terminal multiples 40-60% lower than current comps. Applied to derive D11.
A83: Section 6: Comp Bucket Weighting — THIS IS THE THESIS
A84: V11a | B84: Bucket 1 Weight (Consumer Hardware — Garmin) | C84: 0.4 | D84: 0.2 | E84: 0.1 | F84: =IF($B$3="Bear",C84,IF($B$3="Bull",E84,D84)) -> 0.2 | G84: Design | H84: Critical | I84: Higher = more bearish (WHOOP as hardware company)
A85: V11b | B85: Bucket 2 Weight (Consumer Subscription — PTON/SPOT) | C85: 0.4 | D85: 0.4 | E85: 0.3 | F85: =IF($B$3="Bear",C85,IF($B$3="Bull",E85,D85)) -> 0.4 | G85: Design | H85: Critical | I85: Peloton-Spotify range disaggregated; where does WHOOP sit?
A86: V11c | B86: Bucket 3 Weight (Health Data — DXCM/RMD/MASI/IRTC) | C86: 0.2 | D86: 0.4 | E86: 0.6 | F86: =IF($B$3="Bear",C86,IF($B$3="Bull",E86,D86)) -> 0.4 | G86: Design | H86: Critical | I86: Higher = healthcare thesis is believed; Series G implied ~70%
A87: V11_chk | B87: Bucket Weights Sum (must = 100%) | C87: =C84+C85+C86 -> 1 | D87: =D84+D85+D86 -> 1 | E87: =E84+E85+E86 -> 1 | F87: =IF($B$3="Bear",C87,IF($B$3="Bull",E87,D87)) -> 1 | G87: Derived | H87: Check | I87: Sanity check: bucket weights must sum to 100%
A89: Section 7: IPO Trading Range & Discount Framework
A90: I1 | B90: IPO Timing (months from Series G) | C90: 18 | D90: 15 | E90: 12 | F90: =IF($B$3="Bear",C90,IF($B$3="Bull",E90,D90)) -> 15 | G90: Tier 2 | H90: High | I90: Q2 2027 - Q1 2028; "last private round" per Ahmed
A91: I2 | B91: IPO Pricing Discount (to Stage 1 fair value) | C91: 0.25 | D91: 0.2 | E91: 0.15 | F91: =IF($B$3="Bear",C91,IF($B$3="Bull",E91,D91)) -> 0.2 | G91: Tier 2 | H91: Critical | I91: Loughran/Ritter IPO pricing studies; 15-25% standard
A92: I3 | B92: Illiquidity / Timing Discount (private vs. IPO) | C92: 0.15 | D92: 0.1 | E92: 0.05 | F92: =IF($B$3="Bear",C92,IF($B$3="Bull",E92,D92)) -> 0.1 | G92: Tier 2 | H92: High | I92: Oura tender 25%; Hiive 39-51%; pre-IPO DLOM shrinkage near window
A93: I4 | B93: Series G Investor Required IRR | C93: 0.3 | D93: 0.25 | E93: 0.2 | F93: =IF($B$3="Bear",C93,IF($B$3="Bull",E93,D93)) -> 0.25 | G93: Tier 3 | H93: Medium | I93: Late-stage growth equity return expectations (3-5yr hold)
A94: I5 | B94: Implied Stage 1 Public Fair Value ($M) — DERIVED | C94: =10100/(1-C92)/(1-C91) -> 15843.137 | D94: =10100/(1-D92)/(1-D91) -> 14027.778 | E94: =10100/(1-E92)/(1-E91) -> 12507.74 | F94: =IF($B$3="Bear",C94,IF($B$3="Bull",E94,D94)) -> 14027.778 | G94: Derived | H94: Critical | I94: Back-solve: $10.1B / (1-illiquidity) / (1-IPO discount) → $13-15B target
A96: Section 8: Precedent Transactions
A97: P1 | B97: Deal Inclusion Window | C97: Last 5 years | D97: Last 5 years | E97: Last 5 years | F97: =IF($B$3="Bear",C97,IF($B$3="Bull",E97,D97)) -> Last 5 years | G97: Design | H97: Locked | I97: 2021-2026 with 3-year primary focus
A98: P3 | B98: Deal Size Threshold ($M EV) | C98: 500 | D98: 500 | E98: 500 | F98: =IF($B$3="Bear",C98,IF($B$3="Bull",E98,D98)) -> 500 | G98: Design | H98: Locked | I98: Below this, synergy math distorts multiples
A99: P5 | B99: Multiple Extraction Method | C99: EV/LTM Rev | D99: EV/LTM Rev | E99: EV/LTM Rev | F99: =IF($B$3="Bear",C99,IF($B$3="Bull",E99,D99)) -> EV/LTM Rev | G99: Design | H99: Locked | I99: EV / LTM revenue at announcement; NTM where available
A100: P_b1 | B100: Bucket 1 Precedent Multiple (median) | C100: 1 | D100: 1.5 | E100: 2.5 | F100: =IF($B$3="Bear",C100,IF($B$3="Bull",E100,D100)) -> 1.5 | G100: Tier 2 | H100: High | I100: Fitbit/Google ~1.3x; Garmin tuck-ins; mostly distressed exits
A101: P_b2 | B101: Bucket 2 Precedent Multiple (median) | C101: 0.8 | D101: 1.5 | E101: 3 | F101: =IF($B$3="Bear",C101,IF($B$3="Bull",E101,D101)) -> 1.5 | G101: Tier 2 | H101: High | I101: Peloton/Precor; connected fitness all value-destructive
A102: P_b3 | B102: Bucket 3 Precedent Multiple (median) | C102: 6 | D102: 8 | E102: 10 | F102: =IF($B$3="Bear",C102,IF($B$3="Bull",E102,D102)) -> 8 | G102: Tier 2 | H102: High | I102: Per research/precedent-transactions.md: B3 medtech 6.6-10.1x range
A104: Section 9: Real Options — moved to RealOptions tab (additive, never in DCF base case)
A105: Real-option probabilities (D19-D23) live on the RealOptions tab — cluster-modeled (correlated success / mixed / failure), additive to base DCF EV. See methodology Sec 4.
A107: Legend & Conventions
A108: Blue text | B108: Hard-coded input
A109: Black text | B109: Formula / derived calculation
A110: Green text | B110: Cross-sheet link (wired when other tabs are built)
A111: Yellow fill | B111: FLAGGED_GAP — unsourced critical, needs verification
A112: Active col | B112: Picks Bear/Base/Bull per scenario selector at $B$3
A114: Section 10: Gross Adds Derivation Drivers
A115: Gross Adds = (Prior-Yr Rev × S&M%) / Blended CAC. Saturation modeled via CAC inflation only (single mechanism). TAM is a diagnostic check on Members tab — flagged if penetration exceeds 40%. Blended CAC = total S&M / gross adds (incl. paid + brand + athlete partnerships; excl. hardware subsidy which is in COGS).
A117: GA1 | B117: S&M % of Prior-Yr Revenue — Phase 1 (2026-27) | C117: 0.28 | D117: 0.3 | E117: 0.32 | F117: =IF($B$3="Bear",C117,IF($B$3="Bull",E117,D117)) -> 0.3 | G117: Tier 2 | H117: Critical | I117: Series G deployment phase. ~30% base ties to 2025 calibration ($195M / $650M).
A118: GA2 | B118: S&M % of Prior-Yr Revenue — Phase 2 (2028-30) | C118: 0.22 | D118: 0.24 | E118: 0.26 | F118: =IF($B$3="Bear",C118,IF($B$3="Bull",E118,D118)) -> 0.24 | G118: Tier 2 | H118: High | I118: Post-IPO normalization; public-market margin pressure.
A119: GA3 | B119: S&M % of Prior-Yr Revenue — Phase 3 (2031-33) | C119: 0.18 | D119: 0.19 | E119: 0.2 | F119: =IF($B$3="Bear",C119,IF($B$3="Bull",E119,D119)) -> 0.19 | G119: Tier 2 | H119: Medium | I119: Mature subscription steady-state.
A121: GA4 | B121: 2026 Starting Blended CAC ($) | C121: 250 | D121: 200 | E121: 150 | F121: =IF($B$3="Bear",C121,IF($B$3="Bull",E121,D121)) -> 200 | G121: Tier 3 | H121: Critical | I121: Total S&M / gross adds. Includes paid + brand + athlete partnerships. Excludes hardware subsidy (in COGS). 2025 anchor: ~$130. PLACEHOLDER — validate against research base.
A122: GA5 | B122: Annual Blended CAC Inflation Rate | C122: 0.12 | D122: 0.08 | E122: 0.05 | F122: =IF($B$3="Bear",C122,IF($B$3="Bull",E122,D122)) -> 0.08 | G122: Tier 3 | H122: Critical | I122: YoY blended CAC growth. Sole saturation mechanism (TAM curve removed to avoid double-counting). 8% base = brand cost drift + mid-cycle marginal acquisition cost rise. Peloton peaked ~25%/yr.
A123: GA6 | B123: TAM — Global Paying Subscribers (M) | C123: 12 | D123: 25 | E123: 45 | F123: =IF($B$3="Bear",C123,IF($B$3="Bull",E123,D123)) -> 25 | G123: Tier 1 | H123: Critical | I123: Diagnostic ceiling, not a damping multiplier. Penetration% shown on Members row 49; flag if >40%. Bear: consumer-fitness only. Base: + international + partial Labs scaling. Bull: full health-data platform.
A126: Section 11: ARPU Decomposition Drivers
A127: Build: Sub ARPU (tier-mix-driven) + Labs (attach × price × tests) + Accessories + BP/Healthspan (attach × price). Sums to Blended ARPU on ARPU tab. Replaces single-line $338 anchor (R4) with derived value; consistency check on ARPU tab flags if 2025 derived ≠ R4 within ±5%.
A129: -- Subscription ARPU --
...

Sheet Members
A1: WHOOP — Member Cohort Engine
A2: Members in millions; cohort engine drives revenue. 2025 beginning treated as Y3+ legacy block (simplification — see note).
B5: Units | C5: 2024 | D5: 2025 | E5: 2026 | F5: 2027 | G5: 2028 | H5: 2029 | I5: 2030 | J5: 2031 | K5: 2032 | L5: 2033
C6: Historical | D6: Historical | E6: Phase 1 | F6: Phase 1 | G6: Phase 2 | H6: Phase 2 | I6: Phase 2 | J6: Phase 3 | K6: Phase 3 | L6: Phase 3
A8: 1. Beginning Members (start of year)
A9: Beginning Members (total) | B9: M | C9: 0.7 | D9: =Assumptions!$F$8 -> 1.3 | E9: =D34 -> 2.5 | F9: =E34 -> 2.9099858 | G9: =F34 -> 3.7413302 | H9: =G34 -> 4.4065901 | I9: =H34 -> 5.222723 | J9: =I34 -> 6.1448459 | K9: =J34 -> 6.8029328 | L9: =K34 -> 7.5677286
A10: of which: Year-1 cohort | B10: M | C10: 0.5 | D10: 0 | E10: =D31 -> 1.304 | F10: =E31 -> 0.79254581 | G10: =F31 -> 1.2361269 | H10: =G31 -> 1.1747152 | I10: =H31 -> 1.3909709 | J10: =I31 -> 1.5896534 | K10: =J31 -> 1.4373234 | L10: =K31 -> 1.5846515
A11: of which: Year-2 cohort | B11: M | C11: 0.15 | D11: 0 | E11: =D26 -> 0 | F11: =E26 -> 1.01712 | G11: =F26 -> 0.61818573 | H11: =G26 -> 0.96417899 | I11: =H26 -> 0.91627784 | J11: =I26 -> 1.0849573 | K11: =J26 -> 1.2399297 | L11: =K26 -> 1.1211123
A12: of which: Year-3+ cohort | B12: M | C12: 0.05 | D12: =Assumptions!$F$8 -> 1.3 | E12: =D28 -> 1.196 | F12: =E28 -> 1.10032 | G12: =F28 -> 1.8870176 | H12: =G28 -> 2.2676959 | I12: =H28 -> 2.9154742 | J12: =I28 -> 3.4702352 | K12: =J28 -> 4.1256797 | L12: =K28 -> 4.8619648
A14: 2. Churn Rates (cohort-aged, from Assumptions)
A15: Year-1 churn rate | B15: % | C15: =Assumptions!$F$19 -> 0.22 | D15: =Assumptions!$F$19 -> 0.22 | E15: =Assumptions!$F$19 -> 0.22 | F15: =Assumptions!$F$19 -> 0.22 | G15: =Assumptions!$F$19 -> 0.22 | H15: =Assumptions!$F$19 -> 0.22 | I15: =Assumptions!$F$19 -> 0.22 | J15: =Assumptions!$F$19 -> 0.22 | ... L15: =Assumptions!$F$19 -> 0.22
A16: Year-2 churn rate | B16: % | C16: =Assumptions!$F$20 -> 0.14 | D16: =Assumptions!$F$20 -> 0.14 | E16: =Assumptions!$F$20 -> 0.14 | F16: =Assumptions!$F$20 -> 0.14 | G16: =Assumptions!$F$20 -> 0.14 | H16: =Assumptions!$F$20 -> 0.14 | I16: =Assumptions!$F$20 -> 0.14 | J16: =Assumptions!$F$20 -> 0.14 | ... L16: =Assumptions!$F$20 -> 0.14
A17: Year-3+ churn rate | B17: % | C17: =Assumptions!$F$21 -> 0.08 | D17: =Assumptions!$F$21 -> 0.08 | E17: =Assumptions!$F$21 -> 0.08 | F17: =Assumptions!$F$21 -> 0.08 | G17: =Assumptions!$F$21 -> 0.08 | H17: =Assumptions!$F$21 -> 0.08 | I17: =Assumptions!$F$21 -> 0.08 | J17: =Assumptions!$F$21 -> 0.08 | ... L17: =Assumptions!$F$21 -> 0.08
A19: 3. Churned Members
A20: Y1 churned | B20: M | C20: =C10*C15 -> 0.11 | D20: =D10*D15 -> 0 | E20: =E10*E15 -> 0.28688 | F20: =F10*F15 -> 0.17436008 | G20: =G10*G15 -> 0.27194792 | H20: =H10*H15 -> 0.25843734 | I20: =I10*I15 -> 0.30601361 | J20: =J10*J15 -> 0.34972375 | ... L20: =L10*L15 -> 0.34862333
A21: Y2 churned | B21: M | C21: =C11*C16 -> 0.021 | D21: =D11*D16 -> 0 | E21: =E11*E16 -> 0 | F21: =F11*F16 -> 0.1423968 | G21: =G11*G16 -> 0.086546003 | H21: =H11*H16 -> 0.13498506 | I21: =I11*I16 -> 0.1282789 | J21: =J11*J16 -> 0.15189403 | ... L21: =L11*L16 -> 0.15695572
A22: Y3+ churned | B22: M | C22: =C12*C17 -> 0.004 | D22: =D12*D17 -> 0.104 | E22: =E12*E17 -> 0.09568 | F22: =F12*F17 -> 0.0880256 | G22: =G12*G17 -> 0.15096141 | H22: =H12*H17 -> 0.18141567 | I22: =I12*I17 -> 0.23323793 | J22: =J12*J17 -> 0.27761881 | ... L22: =L12*L17 -> 0.38895719
A23: Total churned | B23: M | C23: =SUM(C20:C22) -> 0.135 | D23: =SUM(D20:D22) -> 0.104 | E23: =SUM(E20:E22) -> 0.38256 | F23: =SUM(F20:F22) -> 0.40478248 | G23: =SUM(G20:G22) -> 0.50945533 | H23: =SUM(H20:H22) -> 0.57483807 | I23: =SUM(I20:I22) -> 0.66753044 | J23: =SUM(J20:J22) -> 0.77923659 | ... L23: =SUM(L20:L22) -> 0.89453623
A25: 4. Surviving Members (end of year, before new adds)
A26: Y1 survivors | B26: M | C26: =C10-C20 -> 0.39 | D26: =D10-D20 -> 0 | E26: =E10-E20 -> 1.01712 | F26: =F10-F20 -> 0.61818573 | G26: =G10-G20 -> 0.96417899 | H26: =H10-H20 -> 0.91627784 | I26: =I10-I20 -> 1.0849573 | J26: =J10-J20 -> 1.2399297 | ... L26: =L10-L20 -> 1.2360282
A27: Y2 survivors | B27: M | C27: =C11-C21 -> 0.129 | D27: =D11-D21 -> 0 | E27: =E11-E21 -> 0 | F27: =F11-F21 -> 0.8747232 | G27: =G11-G21 -> 0.53163973 | H27: =H11-H21 -> 0.82919393 | I27: =I11-I21 -> 0.78799894 | J27: =J11-J21 -> 0.93306331 | ... L27: =L11-L21 -> 0.96415655
A28: Y3+ end state (incl. Y2 graduates) | B28: M | C28: =C12-C22+C27 -> 0.175 | D28: =D12-D22+D27 -> 1.196 | E28: =E12-E22+E27 -> 1.10032 | F28: =F12-F22+F27 -> 1.8870176 | G28: =G12-G22+G27 -> 2.2676959 | H28: =H12-H22+H27 -> 2.9154742 | I28: =I12-I22+I27 -> 3.4702352 | J28: =J12-J22+J27 -> 4.1256797 | ... L28: =L12-L22+L27 -> 5.4371642
A30: 5. New Members (Gross Adds — input per year)
A31: Gross Adds | B31: M | C31: 0.6 | D31: =Assumptions!$F$9-D28 -> 1.304 | E31: =E51 -> 0.79254581 | F31: =F51 -> 1.2361269 | G31: =G51 -> 1.1747152 | H31: =H51 -> 1.3909709 | I31: =I51 -> 1.5896534 | J31: =J51 -> 1.4373234 | K31: =K51 -> 1.5846515 | L31: =L51 -> 1.7033124
A33: 6. Ending & Average Members
A34: Ending Members | B34: M | C34: =C26+C28+C31 -> 1.165 | D34: =D26+D28+D31 -> 2.5 | E34: =E26+E28+E31 -> 2.9099858 | F34: =F26+F28+F31 -> 3.7413302 | G34: =G26+G28+G31 -> 4.4065901 | H34: =H26+H28+H31 -> 5.222723 | I34: =I26+I28+I31 -> 6.1448459 | J34: =J26+J28+J31 -> 6.8029328 | ... L34: =L26+L28+L31 -> 8.3765048
A35: Average Members | B35: M | C35: =(C9+C34)/2 -> 0.9325 | D35: =(D9+D34)/2 -> 1.9 | E35: =(E9+E34)/2 -> 2.7049929 | F35: =(F9+F34)/2 -> 3.325658 | G35: =(G9+G34)/2 -> 4.0739602 | H35: =(H9+H34)/2 -> 4.8146565 | I35: =(I9+I34)/2 -> 5.6837844 | J35: =(J9+J34)/2 -> 6.4738894 | ... L35: =(L9+L34)/2 -> 7.9721167
A37: 7. Diagnostics (output, not input)
A38: Net Adds (Gross - Churned) | B38: M | C38: =C31-C23 -> 0.465 | D38: =D31-D23 -> 1.2 | E38: =E31-E23 -> 0.40998581 | F38: =F31-F23 -> 0.83134443 | G38: =G31-G23 -> 0.66525985 | H38: =H31-H23 -> 0.81613287 | I38: =I31-I23 -> 0.92212298 | J38: =J31-J23 -> 0.65808683 | ... L38: =L31-L23 -> 0.80877619
A39: Net Member Growth % | B39: % | D39: =D34/C34-1 -> 1.1459227 | E39: =E34/D34-1 -> 0.16399433 | F39: =F34/E34-1 -> 0.28568676 | G39: =G34/F34-1 -> 0.17781372 | H39: =H34/G34-1 -> 0.18520735 | I39: =I34/H34-1 -> 0.17655981 | J39: =J34/I34-1 -> 0.10709574 | K39: =K34/J34-1 -> 0.11242149 | L39: =L34/K34-1 -> 0.10687172
A40: Blended Annual Churn Rate (output) | B40: % | C40: =IFERROR(C23/C9,0) -> 0.19285714 | D40: =IFERROR(D23/D9,0) -> 0.08 | E40: =IFERROR(E23/E9,0) -> 0.153024 | F40: =IFERROR(F23/F9,0) -> 0.13910119 | G40: =IFERROR(G23/G9,0) -> 0.13616957 | H40: =IFERROR(H23/H9,0) -> 0.13044964 | I40: =IFERROR(I23/I9,0) -> 0.12781272 | J40: =IFERROR(J23/J9,0) -> 0.12681141 | ... L40: =IFERROR(L23/L9,0) -> 0.11820406
A41: 2025 ending vs Assumptions R3b (consistency) | B41: % | D41: =D34/Assumptions!$F$9-1 -> 0
A43: NOTE: 2025 beginning is treated as Y3+ legacy block (simplification). Replace with audited cohort splits when S-1 data is available. 2024 column is historical reference; engine fully runs 2025 onwards.
A45: 8. Gross Adds Build (DERIVED — S&M / CAC, with TAM diagnostic)
A46: Phase (1=2026-27, 2=2028-30, 3=2031-33) | B46: # | C46: Hist | D46: Hist | E46: 1 | F46: 1 | G46: 2 | H46: 2 | I46: 2 | J46: 3 | K46: 3 | L46: 3
A47: S&M Budget ($M, % × prior-yr revenue) | B47: $M | D47: 195 | E47: ='Revenue Build'!D20*CHOOSE(E46,Assumptions!$F$117,Assumptions!$F$118,Assumptions!$F$119) -> 158.50916 | F47: ='Revenue Build'!E20*CHOOSE(F46,Assumptions!$F$117,Assumptions!$F$118,Assumptions!$F$119) -> 267.00341 | G47: ='Revenue Build'!F20*CHOOSE(G46,Assumptions!$F$117,Assumptions!$F$118,Assumptions!$F$119) -> 274.03756 | H47: ='Revenue Build'!G20*CHOOSE(H46,Assumptions!$F$117,Assumptions!$F$118,Assumptions!$F$119) -> 350.44456 | I47: ='Revenue Build'!H20*CHOOSE(I46,Assumptions!$F$117,Assumptions!$F$118,Assumptions!$F$119) -> 432.54118 | J47: ='Revenue Build'!I20*CHOOSE(J46,Assumptions!$F$117,Assumptions!$F$118,Assumptions!$F$119) -> 422.37993 | K47: ='Revenue Build'!J20*CHOOSE(K46,Assumptions!$F$117,Assumptions!$F$118,Assumptions!$F$119) -> 502.92855 | L47: ='Revenue Build'!K20*CHOOSE(L46,Assumptions!$F$117,Assumptions!$F$118,Assumptions!$F$119) -> 583.83563
A48: Blended CAC ($) | B48: $ | D48: 130 | E48: =Assumptions!$F$121 -> 200 | F48: =E48*(1+Assumptions!$F$122) -> 216 | G48: =F48*(1+Assumptions!$F$122) -> 233.28 | H48: =G48*(1+Assumptions!$F$122) -> 251.9424 | I48: =H48*(1+Assumptions!$F$122) -> 272.09779 | J48: =I48*(1+Assumptions!$F$122) -> 293.86562 | K48: =J48*(1+Assumptions!$F$122) -> 317.37486 | L48: =K48*(1+Assumptions!$F$122) -> 342.76485
A49: Unconstrained Gross Adds (M) = S&M / CAC | B49: M | D49: =D47/D48 -> 1.5 | E49: =E47/E48 -> 0.79254581 | F49: =F47/F48 -> 1.2361269 | G49: =G47/G48 -> 1.1747152 | H49: =H47/H48 -> 1.3909709 | I49: =I47/I48 -> 1.5896534 | J49: =J47/J48 -> 1.4373234 | K49: =K47/K48 -> 1.5846515 | L49: =L47/L48 -> 1.7033124
A50: TAM Penetration % (diagnostic — flag if >40%) | B50: % | D50: n/a | E50: =D34/Assumptions!$F$123 -> 0.1 | F50: =E34/Assumptions!$F$123 -> 0.11639943 | G50: =F34/Assumptions!$F$123 -> 0.14965321 | H50: =G34/Assumptions!$F$123 -> 0.1762636 | I50: =H34/Assumptions!$F$123 -> 0.20890892 | J50: =I34/Assumptions!$F$123 -> 0.24579384 | K50: =J34/Assumptions!$F$123 -> 0.27211731 | L50: =K34/Assumptions!$F$123 -> 0.30270914
A51: Final Gross Adds (M) | B51: M | D51: =D49 -> 1.5 | E51: =E49 -> 0.79254581 | F51: =F49 -> 1.2361269 | G51: =G49 -> 1.1747152 | H51: =H49 -> 1.3909709 | I51: =I49 -> 1.5896534 | J51: =J49 -> 1.4373234 | K51: =K49 -> 1.5846515 | L51: =L49 -> 1.7033124

Sheet ARPU
A1: ARPU Decomposition (5 components per Methodology Sec 3)
A2: Driven from Assumptions Section 11. Sub ARPU = tier-mix × disclosed prices + monthly premium. Labs = attach × price × tests/yr (with 2025 launch-year scaling). Accessories = baseline × (1+inflation). BP/Healthspan = attach × price (paid add-on layer). Sums to Blended ARPU on row 32; consistency check vs. Assumptions R4 below.
A5: Year | B5: Unit | C5: 2024 | D5: 2025 | E5: 2026 | F5: 2027 | G5: 2028 | H5: 2029 | I5: 2030 | J5: 2031 | K5: 2032 | L5: 2033
A7: 1. Subscription ARPU (tier-mix-driven)
A8: Tier mix: % WHOOP One | B8: % | D8: =Assumptions!$F$130 -> 0.3 | E8: =MAX(0,D8-Assumptions!$F$134) -> 0.285 | F8: =MAX(0,E8-Assumptions!$F$134) -> 0.27 | G8: =MAX(0,F8-Assumptions!$F$134) -> 0.255 | H8: =MAX(0,G8-Assumptions!$F$134) -> 0.24 | I8: =MAX(0,H8-Assumptions!$F$134) -> 0.225 | J8: =MAX(0,I8-Assumptions!$F$134) -> 0.21 | K8: =MAX(0,J8-Assumptions!$F$134) -> 0.195 | L8: =MAX(0,K8-Assumptions!$F$134) -> 0.18
A9: Tier mix: % WHOOP Peak | B9: % | D9: =Assumptions!$F$131 -> 0.45 | E9: =D9+Assumptions!$F$134*0.5 -> 0.4575 | F9: =E9+Assumptions!$F$134*0.5 -> 0.465 | G9: =F9+Assumptions!$F$134*0.5 -> 0.4725 | H9: =G9+Assumptions!$F$134*0.5 -> 0.48 | I9: =H9+Assumptions!$F$134*0.5 -> 0.4875 | J9: =I9+Assumptions!$F$134*0.5 -> 0.495 | K9: =J9+Assumptions!$F$134*0.5 -> 0.5025 | L9: =K9+Assumptions!$F$134*0.5 -> 0.51
A10: Tier mix: % WHOOP Life | B10: % | D10: =Assumptions!$F$132 -> 0.25 | E10: =1-E8-E9 -> 0.2575 | F10: =1-F8-F9 -> 0.265 | G10: =1-G8-G9 -> 0.2725 | H10: =1-H8-H9 -> 0.28 | I10: =1-I8-I9 -> 0.2875 | J10: =1-J8-J9 -> 0.295 | K10: =1-K8-K9 -> 0.3025 | L10: =1-L8-L9 -> 0.31
A11: Sub ARPU before monthly premium | B11: $/yr | D11: =D8*199+D9*239+D10*359 -> 257 | E11: =E8*199+E9*239+E10*359 -> 258.5 | F11: =F8*199+F9*239+F10*359 -> 260 | G11: =G8*199+G9*239+G10*359 -> 261.5 | H11: =H8*199+H9*239+H10*359 -> 263 | I11: =I8*199+I9*239+I10*359 -> 264.5 | J11: =J8*199+J9*239+J10*359 -> 266 | K11: =K8*199+K9*239+K10*359 -> 267.5 | L11: =L8*199+L9*239+L10*359 -> 269
A12: Monthly-payer premium ($14 × monthly share) | B12: $/yr | D12: =Assumptions!$F$133*14 -> 1.68 | E12: =Assumptions!$F$133*14 -> 1.68 | F12: =Assumptions!$F$133*14 -> 1.68 | G12: =Assumptions!$F$133*14 -> 1.68 | H12: =Assumptions!$F$133*14 -> 1.68 | I12: =Assumptions!$F$133*14 -> 1.68 | J12: =Assumptions!$F$133*14 -> 1.68 | K12: =Assumptions!$F$133*14 -> 1.68 | L12: =Assumptions!$F$133*14 -> 1.68
A13: Sub ARPU (final) | B13: $/yr | D13: =D11+D12 -> 258.68 | E13: =(E11+E12)*(1+Assumptions!$F$26)^(E$5-$D$5) -> 267.9854 | F13: =(F11+F12)*(1+Assumptions!$F$26)^(F$5-$D$5) -> 277.61631 | G13: =(G11+G12)*(1+Assumptions!$F$26)^(G$5-$D$5) -> 287.58389 | H13: =(H11+H12)*(1+Assumptions!$F$26)^(H$5-$D$5) -> 297.89967 | I13: =(I11+I12)*(1+Assumptions!$F$26)^(I$5-$D$5) -> 308.57557 | J13: =(J11+J12)*(1+Assumptions!$F$26)^(J$5-$D$5) -> 319.62392 | K13: =(K11+K12)*(1+Assumptions!$F$26)^(K$5-$D$5) -> 331.05745 | L13: =(L11+L12)*(1+Assumptions!$F$26)^(L$5-$D$5) -> 342.88933
A15: 2. Advanced Labs ARPU (THE bucket-3 swing variable)
A16: Labs attach % | B16: % | D16: =Assumptions!$F$137*0.5 -> 0.05 | E16: =Assumptions!$F$137 -> 0.1 | F16: =E16*(1+Assumptions!$F$140) -> 0.109 | G16: =F16*(1+Assumptions!$F$140) -> 0.11881 | H16: =G16*(1+Assumptions!$F$140) -> 0.1295029 | I16: =H16*(1+Assumptions!$F$140) -> 0.14115816 | J16: =I16*(1+Assumptions!$F$140) -> 0.1538624 | K16: =J16*(1+Assumptions!$F$140) -> 0.16771001 | L16: =K16*(1+Assumptions!$F$140) -> 0.18280391
A17: Avg test price | B17: $ | D17: =Assumptions!$F$138 -> 250 | E17: =Assumptions!$F$138 -> 250 | F17: =E17 -> 250 | G17: =F17 -> 250 | H17: =G17 -> 250 | I17: =H17 -> 250 | J17: =I17 -> 250 | K17: =J17 -> 250 | L17: =K17 -> 250
A18: Tests per attached member | B18: tests/yr | D18: =Assumptions!$F$139 -> 1.5 | E18: =Assumptions!$F$139 -> 1.5 | F18: =E18 -> 1.5 | G18: =F18 -> 1.5 | H18: =G18 -> 1.5 | I18: =H18 -> 1.5 | J18: =I18 -> 1.5 | K18: =J18 -> 1.5 | L18: =K18 -> 1.5
A19: Launch-year scaling (2025 partial) | B19: factor | D19: 0.075 | E19: 1 | F19: 1 | G19: 1 | H19: 1 | I19: 1 | J19: 1 | K19: 1 | L19: 1
A20: Labs ARPU (attach × price × tests) | B20: $/yr | D20: =D16*D17*D18*D19 -> 1.40625 | E20: =E16*E17*E18*E19 -> 37.5 | F20: =F16*F17*F18*F19 -> 40.875 | G20: =G16*G17*G18*G19 -> 44.55375 | H20: =H16*H17*H18*H19 -> 48.563588 | I20: =I16*I17*I18*I19 -> 52.93431 | J20: =J16*J17*J18*J19 -> 57.698398 | K20: =K16*K17*K18*K19 -> 62.891254 | L20: =L16*L17*L18*L19 -> 68.551467
A22: 3. Accessories ARPU
A23: Accessories ARPU | B23: $/yr | D23: =Assumptions!$F$143 -> 18 | E23: =D23*(1+Assumptions!$F$144) -> 18.54 | F23: =E23*(1+Assumptions!$F$144) -> 19.0962 | G23: =F23*(1+Assumptions!$F$144) -> 19.669086 | H23: =G23*(1+Assumptions!$F$144) -> 20.259159 | I23: =H23*(1+Assumptions!$F$144) -> 20.866933 | J23: =I23*(1+Assumptions!$F$144) -> 21.492941 | K23: =J23*(1+Assumptions!$F$144) -> 22.13773 | L23: =K23*(1+Assumptions!$F$144) -> 22.801861
A25: 4. BP/Healthspan ARPU (paid add-on layer)
A26: BP/Healthspan attach % | B26: % | D26: 0 | E26: =Assumptions!$F$147 -> 0.05 | F26: =E26*(1+Assumptions!$F$149) -> 0.0575 | G26: =F26*(1+Assumptions!$F$149) -> 0.066125 | H26: =G26*(1+Assumptions!$F$149) -> 0.07604375 | I26: =H26*(1+Assumptions!$F$149) -> 0.087450312 | J26: =I26*(1+Assumptions!$F$149) -> 0.10056786 | K26: =J26*(1+Assumptions!$F$149) -> 0.11565304 | L26: =K26*(1+Assumptions!$F$149) -> 0.13300099
A27: BP/Healthspan add-on price | B27: $ | D27: 0 | E27: =Assumptions!$F$148 -> 100 | F27: =E27 -> 100 | G27: =F27 -> 100 | H27: =G27 -> 100 | I27: =H27 -> 100 | J27: =I27 -> 100 | K27: =J27 -> 100 | L27: =K27 -> 100
A28: BP/Healthspan ARPU | B28: $/yr | D28: =D26*D27 -> 0 | E28: =E26*E27 -> 5 | F28: =F26*F27 -> 5.75 | G28: =G26*G27 -> 6.6125 | H28: =H26*H27 -> 7.604375 | I28: =I26*I27 -> 8.7450312 | J28: =J26*J27 -> 10.056786 | K28: =K26*K27 -> 11.565304 | L28: =L26*L27 -> 13.300099
A30: 5. BLENDED ARPU (DERIVED)
A31: Sub ARPU | B31: $/yr | D31: =D13 -> 258.68 | E31: =E13 -> 267.9854 | F31: =F13 -> 277.61631 | G31: =G13 -> 287.58389 | H31: =H13 -> 297.89967 | I31: =I13 -> 308.57557 | J31: =J13 -> 319.62392 | K31: =K13 -> 331.05745 | L31: =L13 -> 342.88933
A32: + Labs ARPU | B32: $/yr | D32: =D20 -> 1.40625 | E32: =E20 -> 37.5 | F32: =F20 -> 40.875 | G32: =G20 -> 44.55375 | H32: =H20 -> 48.563588 | I32: =I20 -> 52.93431 | J32: =J20 -> 57.698398 | K32: =K20 -> 62.891254 | L32: =L20 -> 68.551467
A33: + Accessories ARPU | B33: $/yr | D33: =D23 -> 18 | E33: =E23 -> 18.54 | F33: =F23 -> 19.0962 | G33: =G23 -> 19.669086 | H33: =H23 -> 20.259159 | I33: =I23 -> 20.866933 | J33: =J23 -> 21.492941 | K33: =K23 -> 22.13773 | L33: =L23 -> 22.801861
A34: + BP/Healthspan ARPU | B34: $/yr | D34: =D28 -> 0 | E34: =E28 -> 5 | F34: =F28 -> 5.75 | G34: =G28 -> 6.6125 | H34: =H28 -> 7.604375 | I34: =I28 -> 8.7450312 | J34: =J28 -> 10.056786 | K34: =K28 -> 11.565304 | L34: =L28 -> 13.300099
A35: = Blended ARPU | B35: $/yr | D35: =SUM(D31:D34) -> 278.08625 | E35: =SUM(E31:E34) -> 329.0254 | F35: =SUM(F31:F34) -> 343.33751 | G35: =SUM(G31:G34) -> 358.41923 | H35: =SUM(H31:H34) -> 374.32679 | I35: =SUM(I31:I34) -> 391.12185 | J35: =SUM(J31:J34) -> 408.87204 | K35: =SUM(K31:K34) -> 427.65173 | L35: =SUM(L31:L34) -> 447.54275
A37: Consistency Check (vs. Assumptions R4 anchor)
A38: R4 anchor (2025 single-line ARPU) | B38: $/yr | D38: =Assumptions!$F$11 -> 338
A39: Derived (2025 sum of components) | B39: $/yr | D39: =D35 -> 278.08625
A40: Variance | B40: % | D40: =(D39-D38)/D38 -> -0.17725962
A41: Status | D41: =IF(ABS(D40)<=0.05,"✓ within ±5%","⚠ outside ±5% — reconcile R4 vs. component build") -> ⚠ outside ±5% — reconcile R4 vs. component build

Sheet Revenue Build
A1: WHOOP — Revenue Build-Up
A2: $M unless noted; Calendar Year
B5: Units | C5: 2024 | D5: 2025 | E5: 2026 | F5: 2027 | G5: 2028 | H5: 2029 | I5: 2030 | J5: 2031 | K5: 2032 | L5: 2033
C6: Historical | D6: Historical | E6: Phase 1 | F6: Phase 1 | G6: Phase 2 | H6: Phase 2 | I6: Phase 2 | J6: Phase 3 | K6: Phase 3 | L6: Phase 3
A8: 1. Member Economics (linked from Members tab)
A9: Beginning Members | B9: M | C9: =Members!C9 -> 0.7 | D9: =Members!D9 -> 1.3 | E9: =Members!E9 -> 2.5 | F9: =Members!F9 -> 2.9099858 | G9: =Members!G9 -> 3.7413302 | H9: =Members!H9 -> 4.4065901 | I9: =Members!I9 -> 5.222723 | J9: =Members!J9 -> 6.1448459 | ... L9: =Members!L9 -> 7.5677286
A10: Gross Adds | B10: M | C10: =Members!C31 -> 0.6 | D10: =Members!D31 -> 1.304 | E10: =Members!E31 -> 0.79254581 | F10: =Members!F31 -> 1.2361269 | G10: =Members!G31 -> 1.1747152 | H10: =Members!H31 -> 1.3909709 | I10: =Members!I31 -> 1.5896534 | J10: =Members!J31 -> 1.4373234 | ... L10: =Members!L31 -> 1.7033124
A11: Churned Members | B11: M | C11: =Members!C23 -> 0.135 | D11: =Members!D23 -> 0.104 | E11: =Members!E23 -> 0.38256 | F11: =Members!F23 -> 0.40478248 | G11: =Members!G23 -> 0.50945533 | H11: =Members!H23 -> 0.57483807 | I11: =Members!I23 -> 0.66753044 | J11: =Members!J23 -> 0.77923659 | ... L11: =Members!L23 -> 0.89453623
A12: Ending Members | B12: M | C12: =Members!C34 -> 1.165 | D12: =Members!D34 -> 2.5 | E12: =Members!E34 -> 2.9099858 | F12: =Members!F34 -> 3.7413302 | G12: =Members!G34 -> 4.4065901 | H12: =Members!H34 -> 5.222723 | I12: =Members!I34 -> 6.1448459 | J12: =Members!J34 -> 6.8029328 | ... L12: =Members!L34 -> 8.3765048
A13: Avg Members | B13: M | C13: =Members!C35 -> 0.9325 | D13: =Members!D35 -> 1.9 | E13: =Members!E35 -> 2.7049929 | F13: =Members!F35 -> 3.325658 | G13: =Members!G35 -> 4.0739602 | H13: =Members!H35 -> 4.8146565 | I13: =Members!I35 -> 5.6837844 | J13: =Members!J35 -> 6.4738894 | ... L13: =Members!L35 -> 7.9721167
A14: Blended Annual Churn (output) | B14: % | C14: =IFERROR(Members!C23/Members!C9, 0) -> 0.19285714 | D14: =IFERROR(Members!D23/Members!D9, 0) -> 0.08 | E14: =IFERROR(Members!E23/Members!E9, 0) -> 0.153024 | F14: =IFERROR(Members!F23/Members!F9, 0) -> 0.13910119 | G14: =IFERROR(Members!G23/Members!G9, 0) -> 0.13616957 | H14: =IFERROR(Members!H23/Members!H9, 0) -> 0.13044964 | I14: =IFERROR(Members!I23/Members!I9, 0) -> 0.12781272 | J14: =IFERROR(Members!J23/Members!J9, 0) -> 0.12681141 | ... L14: =IFERROR(Members!L23/Members!L9, 0) -> 0.11820406
A16: 2. ARPU (linked from ARPU tab)
A17: Blended ARPU | B17: $/yr | C17: =ARPU!C35 -> 0 | D17: =ARPU!D35 -> 278.08625 | E17: =ARPU!E35 -> 329.0254 | F17: =ARPU!F35 -> 343.33751 | G17: =ARPU!G35 -> 358.41923 | H17: =ARPU!H35 -> 374.32679 | I17: =ARPU!I35 -> 391.12185 | J17: =ARPU!J35 -> 408.87204 | ... L17: =ARPU!L35 -> 447.54275
A19: 3. Revenue Build
A20: Recognized Revenue (Total) | B20: $M | C20: =C13*C17 -> 0 | D20: =D13*D17 -> 528.36388 | E20: =E13*E17 -> 890.01137 | F20: =F13*F17 -> 1141.8232 | G20: =G13*G17 -> 1460.1857 | H20: =H13*H17 -> 1802.2549 | I20: =I13*I17 -> 2223.0523 | J20: =J13*J17 -> 2646.9924 | ... L20: =L13*L17 -> 3567.863
A21: Memo: Δ Deferred Rev Balance (flows to NWC, not P&L) | B21: $M | C21: =C20*Assumptions!$F$28 -> 0 | D21: =D20*Assumptions!$F$28 -> -42.26911 | E21: =E20*Assumptions!$F$28 -> -71.20091 | F21: =F20*Assumptions!$F$28 -> -91.345852 | G21: =G20*Assumptions!$F$28 -> -116.81485 | H21: =H20*Assumptions!$F$28 -> -144.18039 | I21: =I20*Assumptions!$F$28 -> -177.84418 | J21: =J20*Assumptions!$F$28 -> -211.75939 | ... L21: =L20*Assumptions!$F$28 -> -285.42904
A22: YoY Revenue Growth | B22: % | D22: =D20/C20-1 -> #DIV/0! | E22: =E20/D20-1 -> 0.68446674 | F22: =F20/E20-1 -> 0.28293097 | G22: =G20/F20-1 -> 0.27881945 | H22: =H20/G20-1 -> 0.23426424 | I22: =I20/H20-1 -> 0.23348381 | J22: =J20/I20-1 -> 0.19070181 | K22: =K20/J20-1 -> 0.16087192 | L22: =L20/K20-1 -> 0.16110415
A24: 4. Bookings Reconciliation
A25: Implied Bookings (End × ARPU) | B25: $M | C25: =C12*C17 -> 0 | D25: =D12*D17 -> 695.21563 | E25: =E12*E17 -> 957.45925 | F25: =F12*F17 -> 1284.539 | G25: =G12*G17 -> 1579.4066 | H25: =H12*H17 -> 1955.0051 | I25: =I12*I17 -> 2403.3835 | J25: =J12*J17 -> 2781.529 | ... L25: =L12*L17 -> 3748.844
A26: Bookings/Revenue Ratio | B26: x | C26: =IFERROR(C25/C20, 0) -> 0 | D26: =IFERROR(D25/D20, 0) -> 1.3157895 | E26: =IFERROR(E25/E20, 0) -> 1.0757832 | F26: =IFERROR(F25/F20, 0) -> 1.1249895 | G26: =IFERROR(G25/G20, 0) -> 1.0816478 | H26: =IFERROR(H25/H20, 0) -> 1.084755 | I26: =IFERROR(I25/I20, 0) -> 1.0811187 | J26: =IFERROR(J25/J20, 0) -> 1.0508262 | ... L26: =IFERROR(L25/L20, 0) -> 1.0507253
A27: 2025 Recognized vs Assumptions R1 (consistency) | B27: % | D27: =D20/Assumptions!$F$12-1 -> -0.17725962
A29: 5. Revenue by Component (feeds COGS on P&L)
A30: Subscription Revenue | B30: $M | C30: =C13*ARPU!C31 -> 0 | D30: =D13*ARPU!D31 -> 491.492 | E30: =E13*ARPU!E31 -> 724.89861 | F30: =F13*ARPU!F31 -> 923.25692 | G30: =G13*ARPU!G31 -> 1171.6053 | H30: =H13*ARPU!H31 -> 1434.2846 | I30: =I13*ARPU!I31 -> 1753.877 | J30: =J13*ARPU!J31 -> 2069.2099 | ... L30: =L13*ARPU!L31 -> 2733.5537
A31: Labs Revenue | B31: $M | C31: =C13*ARPU!C32 -> 0 | D31: =D13*ARPU!D32 -> 2.671875 | E31: =E13*ARPU!E32 -> 101.43723 | F31: =F13*ARPU!F32 -> 135.93627 | G31: =G13*ARPU!G32 -> 181.5102 | H31: =H13*ARPU!H32 -> 233.81699 | I31: =I13*ARPU!I32 -> 300.86721 | J31: =J13*ARPU!J32 -> 373.53305 | ... L31: =L13*ARPU!L32 -> 546.50029
A32: Accessories Revenue | B32: $M | C32: =C13*ARPU!C33 -> 0 | D32: =D13*ARPU!D33 -> 34.2 | E32: =E13*ARPU!E33 -> 50.150568 | F32: =F13*ARPU!F33 -> 63.507431 | G32: =G13*ARPU!G33 -> 80.131073 | H32: =H13*ARPU!H33 -> 97.54089 | I32: =I13*ARPU!I33 -> 118.60315 | J32: =J13*ARPU!J33 -> 139.14292 | ... L32: =L13*ARPU!L33 -> 181.7791
A33: BP/Healthspan Revenue | B33: $M | C33: =C13*ARPU!C34 -> 0 | D33: =D13*ARPU!D34 -> 0 | E33: =E13*ARPU!E34 -> 13.524965 | F33: =F13*ARPU!F34 -> 19.122534 | G33: =G13*ARPU!G34 -> 26.939062 | H33: =H13*ARPU!H34 -> 36.612454 | I33: =I13*ARPU!I34 -> 49.704873 | J33: =J13*ARPU!J34 -> 65.106519 | ... L33: =L13*ARPU!L34 -> 106.02994
A34: Memo: Components Sum | B34: $M | C34: =SUM(C30:C33) -> 0 | D34: =SUM(D30:D33) -> 528.36388 | E34: =SUM(E30:E33) -> 890.01137 | F34: =SUM(F30:F33) -> 1141.8232 | G34: =SUM(G30:G33) -> 1460.1857 | H34: =SUM(H30:H33) -> 1802.2549 | I34: =SUM(I30:I33) -> 2223.0523 | J34: =SUM(J30:J33) -> 2646.9924 | ... L34: =SUM(L30:L33) -> 3567.863
A35: Memo: Reconciliation vs row 19 | B35: % | C35: =IFERROR((C34-C20)/C20, 0) -> 0 | D35: =IFERROR((D34-D20)/D20, 0) -> 0 | E35: =IFERROR((E34-E20)/E20, 0) -> -1.2773639e-16 | F35: =IFERROR((F34-F20)/F20, 0) -> -1.9913213e-16 | G35: =IFERROR((G34-G20)/G20, 0) -> 1.5571559e-16 | H35: =IFERROR((H34-H20)/H20, 0) -> -2.5232132e-16 | I35: =IFERROR((I34-I20)/I20, 0) -> 0 | J35: =IFERROR((J34-J20)/J20, 0) -> 0 | ... L35: =IFERROR((L34-L20)/L20, 0) -> 1.274565e-16

Sheet P&L
A1: WHOOP — Projected Income Statement
A2: $M; Calendar Year; Scenario per Assumptions toggle
A3: Calibration items: see notes on F31 (2027 dip), L23 (S&M architecture). Margin tapers and NOL wired; refer to CalibrationLog for status.
B5: Units | C5: 2024 | D5: 2025 | E5: 2026 | F5: 2027 | G5: 2028 | H5: 2029 | I5: 2030 | J5: 2031 | K5: 2032 | L5: 2033
A7: Revenue
A8: Total Revenue | B8: $M | C8: ='Revenue Build'!C20 -> 0 | D8: ='Revenue Build'!D20 -> 528.36388 | E8: ='Revenue Build'!E20 -> 890.01137 | F8: ='Revenue Build'!F20 -> 1141.8232 | G8: ='Revenue Build'!G20 -> 1460.1857 | H8: ='Revenue Build'!H20 -> 1802.2549 | I8: ='Revenue Build'!I20 -> 2223.0523 | J8: ='Revenue Build'!J20 -> 2646.9924 | ... L8: ='Revenue Build'!L20 -> 3567.863 | M8: ← From Revenue Build tab
A9: YoY Growth | B9: % | D9: =IFERROR(D8/C8-1,0) -> 0 | E9: =E8/D8-1 -> 0.68446674 | F9: =F8/E8-1 -> 0.28293097 | G9: =G8/F8-1 -> 0.27881945 | H9: =H8/G8-1 -> 0.23426424 | I9: =I8/H8-1 -> 0.23348381 | J9: =J8/I8-1 -> 0.19070181 | K9: =K8/J8-1 -> 0.16087192 | L9: =L8/K8-1 -> 0.16110415
A11: Cost of Revenue
A12: Subscription COGS (% of sub rev) | B12: $M | D12: =('Revenue Build'!D30 + 'Revenue Build'!D32 + 'Revenue Build'!D33) * Assumptions!$F$33 -> 52.5692 | E12: =('Revenue Build'!E30 + 'Revenue Build'!E32 + 'Revenue Build'!E33) * Assumptions!$F$33 -> 78.857414 | F12: =('Revenue Build'!F30 + 'Revenue Build'!F32 + 'Revenue Build'!F33) * Assumptions!$F$33 -> 100.58869 | G12: =('Revenue Build'!G30 + 'Revenue Build'!G32 + 'Revenue Build'!G33) * Assumptions!$F$33 -> 127.86755 | H12: =('Revenue Build'!H30 + 'Revenue Build'!H32 + 'Revenue Build'!H33) * Assumptions!$F$33 -> 156.84379 | I12: =('Revenue Build'!I30 + 'Revenue Build'!I32 + 'Revenue Build'!I33) * Assumptions!$F$33 -> 192.21851 | J12: =('Revenue Build'!J30 + 'Revenue Build'!J32 + 'Revenue Build'!J33) * Assumptions!$F$33 -> 227.34593 | K12: =('Revenue Build'!K30 + 'Revenue Build'!K32 + 'Revenue Build'!K33) * Assumptions!$F$33 -> 262.09247 | L12: =('Revenue Build'!L30 + 'Revenue Build'!L32 + 'Revenue Build'!L33) * Assumptions!$F$33 -> 302.13628
A13: Hardware COGS (gross adds × loaded cost) | B13: $M | D13: =Members!D31 * Assumptions!$F$32 -> 156.48 | E13: =Members!E31 * Assumptions!$F$32 -> 95.105497 | F13: =Members!F31 * Assumptions!$F$32 -> 148.33523 | G13: =Members!G31 * Assumptions!$F$32 -> 140.96582 | H13: =Members!H31 * Assumptions!$F$32 -> 166.91651 | I13: =Members!I31 * Assumptions!$F$32 -> 190.75841 | J13: =Members!J31 * Assumptions!$F$32 -> 172.47881 | K13: =Members!K31 * Assumptions!$F$32 -> 190.15818 | L13: =Members!L31 * Assumptions!$F$32 -> 204.39749
A14: Total COGS | B14: $M | D14: =D12+D13+D19 -> 210.78592 | E14: =E12+E13+E19 -> 239.89711 | F14: =F12+F13+F19 -> 337.28249 | G14: =G12+G13+G19 -> 386.815 | H14: =H12+H13+H19 -> 475.74135 | I14: =I12+I13+I19 -> 578.5406 | J14: =J12+J13+J19 -> 642.62122 | K14: =K12+K13+K19 -> 745.98204 | L14: =L12+L13+L19 -> 861.75896
A15: Gross Profit | B15: $M | D15: =D8-D14 -> 317.57796 | E15: =E8-E14 -> 650.11426 | F15: =F8-F14 -> 804.54066 | G15: =G8-G14 -> 1073.3707 | H15: =H8-H14 -> 1326.5136 | I15: =I8-I14 -> 1644.5117 | J15: =J8-J14 -> 2004.3712 | K15: =K8-K14 -> 2326.8371 | L15: =L8-L14 -> 2706.1041
A16: Gross Margin | B16: % | D16: =D15/D8 -> 0.60105918 | E16: =E15/E8 -> 0.73045613 | F16: =F15/F8 -> 0.70461057 | G16: =G15/G8 -> 0.73509191 | H16: =H15/H8 -> 0.73602993 | I16: =I15/I8 -> 0.73975394 | J16: =J15/J8 -> 0.75722589 | K16: =K15/K8 -> 0.75723204 | L16: =L15/L8 -> 0.75846636
A17: Subscription GM | B17: % | D17: =IFERROR(('Revenue Build'!D30+'Revenue Build'!D32+'Revenue Build'!D33-D12)/('Revenue Build'!D30+'Revenue Build'!D32+'Revenue Build'!D33),0) -> 0.9 | E17: =IFERROR(('Revenue Build'!E30+'Revenue Build'!E32+'Revenue Build'!E33-E12)/('Revenue Build'!E30+'Revenue Build'!E32+'Revenue Build'!E33),0) -> 0.9 | F17: =IFERROR(('Revenue Build'!F30+'Revenue Build'!F32+'Revenue Build'!F33-F12)/('Revenue Build'!F30+'Revenue Build'!F32+'Revenue Build'!F33),0) -> 0.9 | G17: =IFERROR(('Revenue Build'!G30+'Revenue Build'!G32+'Revenue Build'!G33-G12)/('Revenue Build'!G30+'Revenue Build'!G32+'Revenue Build'!G33),0) -> 0.9 | H17: =IFERROR(('Revenue Build'!H30+'Revenue Build'!H32+'Revenue Build'!H33-H12)/('Revenue Build'!H30+'Revenue Build'!H32+'Revenue Build'!H33),0) -> 0.9 | I17: =IFERROR(('Revenue Build'!I30+'Revenue Build'!I32+'Revenue Build'!I33-I12)/('Revenue Build'!I30+'Revenue Build'!I32+'Revenue Build'!I33),0) -> 0.9 | J17: =IFERROR(('Revenue Build'!J30+'Revenue Build'!J32+'Revenue Build'!J33-J12)/('Revenue Build'!J30+'Revenue Build'!J32+'Revenue Build'!J33),0) -> 0.9 | K17: =IFERROR(('Revenue Build'!K30+'Revenue Build'!K32+'Revenue Build'!K33-K12)/('Revenue Build'!K30+'Revenue Build'!K32+'Revenue Build'!K33),0) -> 0.9 | L17: =IFERROR(('Revenue Build'!L30+'Revenue Build'!L32+'Revenue Build'!L33-L12)/('Revenue Build'!L30+'Revenue Build'!L32+'Revenue Build'!L33),0) -> 0.9 | M17: ← From Assumptions C2
A18: Hardware Margin $ memo (negative = device subsidy, see Sec 6) | B18: $M | D18: n/m | E18: =Members!E31 * ARPU!E33 - E13 -> -80.411698 | F18: =Members!F31 * ARPU!F33 - F13 -> -124.7299 | G18: =Members!G31 * ARPU!G33 - G13 -> -117.86025 | H18: =Members!H31 * ARPU!H33 - H13 -> -138.73661 | I18: =Members!I31 * ARPU!I33 - I13 -> -157.58722 | J18: =Members!J31 * ARPU!J33 - J13 -> -141.5865 | K18: =Members!K31 * ARPU!K33 - K13 -> -155.07759 | L18: =Members!L31 * ARPU!L33 - L13 -> -165.5588 | M18: ← From Assumptions C3
A19: Labs COGS (% of Labs rev) | B19: $M | D19: ='Revenue Build'!D31 * Assumptions!$F$51 -> 1.7367188 | E19: ='Revenue Build'!E31 * Assumptions!$F$51 -> 65.934202 | F19: ='Revenue Build'!F31 * Assumptions!$F$51 -> 88.358577 | G19: ='Revenue Build'!G31 * Assumptions!$F$51 -> 117.98163 | H19: ='Revenue Build'!H31 * Assumptions!$F$51 -> 151.98105 | I19: ='Revenue Build'!I31 * Assumptions!$F$51 -> 195.56369 | J19: ='Revenue Build'!J31 * Assumptions!$F$51 -> 242.79648 | K19: ='Revenue Build'!K31 * Assumptions!$F$51 -> 293.7314 | L19: ='Revenue Build'!L31 * Assumptions!$F$51 -> 355.22519
A20: Operating Expenses
A21: R&D | B21: $M | D21: =D8*Assumptions!$F$39 -> 116.24005 | E21: =E8*(Assumptions!$F$39 + (Assumptions!$F$40-Assumptions!$F$39)*(E$5-2026)/7) -> 195.8025 | F21: =F8*(Assumptions!$F$39 + (Assumptions!$F$40-Assumptions!$F$39)*(F$5-2026)/7) -> 239.78286 | G21: =G8*(Assumptions!$F$39 + (Assumptions!$F$40-Assumptions!$F$39)*(G$5-2026)/7) -> 292.03713 | H21: =H8*(Assumptions!$F$39 + (Assumptions!$F$40-Assumptions!$F$39)*(H$5-2026)/7) -> 342.42844 | I21: =I8*(Assumptions!$F$39 + (Assumptions!$F$40-Assumptions!$F$39)*(I$5-2026)/7) -> 400.14941 | J21: =J8*(Assumptions!$F$39 + (Assumptions!$F$40-Assumptions!$F$39)*(J$5-2026)/7) -> 449.9887 | K21: =K8*(Assumptions!$F$39 + (Assumptions!$F$40-Assumptions!$F$39)*(K$5-2026)/7) -> 491.65106 | L21: =L8*(Assumptions!$F$39 + (Assumptions!$F$40-Assumptions!$F$39)*(L$5-2026)/7) -> 535.17946
A22: R&D % Revenue | B22: % | D22: =D21/D8 -> 0.22 | E22: =E21/E8 -> 0.22 | F22: =F21/F8 -> 0.21 | G22: =G21/G8 -> 0.2 | H22: =H21/H8 -> 0.19 | I22: =I21/I8 -> 0.18 | J22: =J21/J8 -> 0.17 | K22: =K21/K8 -> 0.16 | L22: =L21/L8 -> 0.15 | M22: ← From Assumptions C7/C8
A23: Sales & Marketing | B23: $M | D23: =D8*Assumptions!$F$41 -> 158.50916 | E23: =Members!E47 -> 158.50916 | F23: =Members!F47 -> 267.00341 | G23: =Members!G47 -> 274.03756 | H23: =Members!H47 -> 350.44456 | I23: =Members!I47 -> 432.54118 | J23: =Members!J47 -> 422.37993 | K23: =Members!K47 -> 502.92855 | L23: =Members!L47 -> 583.83563
A24: S&M % Revenue | B24: % | D24: =D23/D8 -> 0.3 | E24: =E23/E8 -> 0.17809791 | F24: =F23/F8 -> 0.23383955 | G24: =G23/G8 -> 0.18767309 | H24: =H23/H8 -> 0.19444783 | I24: =I23/I8 -> 0.19457086 | J24: =J23/J8 -> 0.15956976 | K24: =K23/K8 -> 0.16367008 | L24: =L23/L8 -> 0.16363734 | M24: ← From Assumptions C9/C10
A25: General & Administrative | B25: $M | D25: =D8*Assumptions!$F$45 -> 79.254581 | E25: =E8*(Assumptions!$F$45 + (Assumptions!$F$46-Assumptions!$F$45)*(E$5-2026)/7) -> 133.50171 | F25: =F8*(Assumptions!$F$45 + (Assumptions!$F$46-Assumptions!$F$45)*(F$5-2026)/7) -> 164.74877 | G25: =G8*(Assumptions!$F$45 + (Assumptions!$F$46-Assumptions!$F$45)*(G$5-2026)/7) -> 202.34001 | H25: =H8*(Assumptions!$F$45 + (Assumptions!$F$46-Assumptions!$F$45)*(H$5-2026)/7) -> 239.44244 | I25: =I8*(Assumptions!$F$45 + (Assumptions!$F$46-Assumptions!$F$45)*(I$5-2026)/7) -> 282.64522 | J25: =J8*(Assumptions!$F$45 + (Assumptions!$F$46-Assumptions!$F$45)*(J$5-2026)/7) -> 321.4205 | K25: =K8*(Assumptions!$F$45 + (Assumptions!$F$46-Assumptions!$F$45)*(K$5-2026)/7) -> 355.56907 | L25: =L8*(Assumptions!$F$45 + (Assumptions!$F$46-Assumptions!$F$45)*(L$5-2026)/7) -> 392.46494
A26: G&A % Revenue | B26: % | D26: =D25/D8 -> 0.15 | E26: =E25/E8 -> 0.15 | F26: =F25/F8 -> 0.14428571 | G26: =G25/G8 -> 0.13857143 | H26: =H25/H8 -> 0.13285714 | I26: =I25/I8 -> 0.12714286 | J26: =J25/J8 -> 0.12142857 | K26: =K25/K8 -> 0.11571429 | L26: =L25/L8 -> 0.11 | M26: ← From Assumptions C11/C12
A27: Stock-Based Compensation | B27: $M | D27: =D8*Assumptions!$F$47 -> 73.970943 | E27: =E8*(Assumptions!$F$47 + (Assumptions!$F$48-Assumptions!$F$47)*(E$5-2026)/7) -> 124.60159 | F27: =F8*(Assumptions!$F$47 + (Assumptions!$F$48-Assumptions!$F$47)*(F$5-2026)/7) -> 150.06819 | G27: =G8*(Assumptions!$F$47 + (Assumptions!$F$48-Assumptions!$F$47)*(G$5-2026)/7) -> 179.39424 | H27: =H8*(Assumptions!$F$47 + (Assumptions!$F$48-Assumptions!$F$47)*(H$5-2026)/7) -> 205.97199 | I27: =I8*(Assumptions!$F$47 + (Assumptions!$F$48-Assumptions!$F$47)*(I$5-2026)/7) -> 235.00838 | J27: =J8*(Assumptions!$F$47 + (Assumptions!$F$48-Assumptions!$F$47)*(J$5-2026)/7) -> 257.1364 | K27: =K8*(Assumptions!$F$47 + (Assumptions!$F$48-Assumptions!$F$47)*(K$5-2026)/7) -> 272.16398 | L27: =L8*(Assumptions!$F$47 + (Assumptions!$F$48-Assumptions!$F$47)*(L$5-2026)/7) -> 285.42904
A28: SBC % Revenue | B28: % | D28: =D27/D8 -> 0.14 | E28: =E27/E8 -> 0.14 | F28: =F27/F8 -> 0.13142857 | G28: =G27/G8 -> 0.12285714 | H28: =H27/H8 -> 0.11428571 | I28: =I27/I8 -> 0.10571429 | J28: =J27/J8 -> 0.097142857 | K28: =K27/K8 -> 0.088571429 | L28: =L27/L8 -> 0.08 | M28: ← From Assumptions C13
A29: Total OpEx | B29: $M | D29: =D21+D23+D25+D27 -> 427.97474 | E29: =E21+E23+E25+E27 -> 612.41496 | F29: =F21+F23+F25+F27 -> 821.60323 | G29: =G21+G23+G25+G27 -> 947.80894 | H29: =H21+H23+H25+H27 -> 1138.2874 | I29: =I21+I23+I25+I27 -> 1350.3442 | J29: =J21+J23+J25+J27 -> 1450.9255 | K29: =K21+K23+K25+K27 -> 1622.3127 | L29: =L21+L23+L25+L27 -> 1796.9091
A31: Profitability
A32: EBITDA | B32: $M | D32: =D15-D29+D27 -> -36.42584 | E32: =E15-E29+E27 -> 162.30089 | F32: =F15-F29+F27 -> 133.00562 | G32: =G15-G29+G27 -> 304.95596 | H32: =H15-H29+H27 -> 394.19815 | I32: =I15-I29+I27 -> 529.17586 | J32: =J15-J29+J27 -> 810.58201 | K32: =K15-K29+K27 -> 976.6884 | L32: =L15-L29+L27 -> 1194.6241
A33: EBITDA Margin | B33: % | D33: =D32/D8 -> -0.068940822 | E33: =E32/E8 -> 0.18235822 | F33: =F32/F8 -> 0.1164853 | G33: =G32/G8 -> 0.20884739 | H33: =H32/H8 -> 0.21872496 | I33: =I32/I8 -> 0.23804022 | J33: =J32/J8 -> 0.30622756 | K33: =K32/K8 -> 0.31784767 | L33: =L32/L8 -> 0.33482901
A34: EBIT / Operating Income | B34: $M | D34: =D15-D29 -> -110.39678 | E34: =E15-E29 -> 37.699297 | F34: =F15-F29 -> -17.06257 | G34: =G15-G29 -> 125.56172 | H34: =H15-H29 -> 188.22615 | I34: =I15-I29 -> 294.16748 | J34: =J15-J29 -> 553.44561 | K34: =K15-K29 -> 704.52442 | L34: =L15-L29 -> 909.19502
A35: Operating Margin | B35: % | D35: =D34/D8 -> -0.20894082 | E35: =E34/E8 -> 0.042358219 | F35: =F34/F8 -> -0.014943268 | G35: =G34/G8 -> 0.085990243 | H35: =H34/H8 -> 0.10443925 | I35: =I34/I8 -> 0.13232594 | J35: =J34/J8 -> 0.2090847 | K35: =K34/K8 -> 0.22927624 | L35: =L34/L8 -> 0.25482901
A36: Rule of 40 Score | B36: # | D36: =(D9+D33)*100 -> -6.8940822 | E36: =(E9+E33)*100 -> 86.682496 | F36: =(F9+F33)*100 -> 39.941627 | G36: =(G9+G33)*100 -> 48.766684 | H36: =(H9+H33)*100 -> 45.29892 | I36: =(I9+I33)*100 -> 47.152403 | J36: =(J9+J33)*100 -> 49.692937 | K36: =(K9+K33)*100 -> 47.871959 | L36: =(L9+L33)*100 -> 49.593317 | M36: = Revenue Growth % + EBITDA Margin %
A38: Below the Line
A39: Interest Income / (Expense) | B39: $M | D39: ='WC & Cash'!$D$12*Assumptions!$F$67 -> 2.625 | E39: =('WC & Cash'!D33 + 'WC & Cash'!E13*0.5)*Assumptions!$F$67 -> 20.573467 | F39: ='WC & Cash'!E33*Assumptions!$F$67 -> 35.925826 | G39: ='WC & Cash'!F33*Assumptions!$F$67 -> 40.890032 | H39: ='WC & Cash'!G33*Assumptions!$F$67 -> 49.026588 | I39: ='WC & Cash'!H33*Assumptions!$F$67 -> 59.833222 | J39: ='WC & Cash'!I33*Assumptions!$F$67 -> 74.772358 | K39: ='WC & Cash'!J33*Assumptions!$F$67 -> 95.051872 | L39: ='WC & Cash'!K33*Assumptions!$F$67 -> 120.5887
A40: Pre-Tax Income | B40: $M | D40: =D34+D39 -> -107.77178 | E40: =E34+E39 -> 58.272764 | F40: =F34+F39 -> 18.863256 | G40: =G34+G39 -> 166.45175 | H40: =H34+H39 -> 237.25274 | I40: =I34+I39 -> 354.0007 | J40: =J34+J39 -> 628.21797 | K40: =K34+K39 -> 799.57629 | L40: =L34+L39 -> 1029.7837
A41: Taxes | B41: $M | D41: =MAX(0, D40-D48)*Assumptions!$F$52 -> 0 | E41: =MAX(0, E40-E48)*Assumptions!$F$52 -> 2.6805471 | F41: =MAX(0, F40-F48)*Assumptions!$F$52 -> 0.8677098 | G41: =MAX(0, G40-G48)*Assumptions!$F$52 -> 27.689421 | H41: =MAX(0, H40-H48)*Assumptions!$F$52 -> 54.56813 | I41: =MAX(0, I40-I48)*Assumptions!$F$52 -> 81.420161 | J41: =MAX(0, J40-J48)*Assumptions!$F$52 -> 144.49013 | K41: =MAX(0, K40-K48)*Assumptions!$F$52 -> 183.90255 | L41: =MAX(0, L40-L48)*Assumptions!$F$52 -> 236.85026
A42: Net Income | B42: $M | D42: =D40-D41 -> -107.77178 | E42: =E40-E41 -> 55.592217 | F42: =F40-F41 -> 17.995547 | G42: =G40-G41 -> 138.76233 | H42: =H40-H41 -> 182.68461 | I42: =I40-I41 -> 272.58054 | J42: =J40-J41 -> 483.72784 | K42: =K40-K41 -> 615.67375 | L42: =L40-L41 -> 792.93347
A43: Net Margin | B43: % | D43: =D42/D8 -> -0.20397266 | E43: =E42/E8 -> 0.062462366 | F43: =F42/F8 -> 0.015760362 | G43: =G42/G8 -> 0.095030608 | H43: =H42/H8 -> 0.10136447 | I43: =I42/I8 -> 0.12261544 | J43: =J42/J8 -> 0.18274621 | K43: =K42/K8 -> 0.20036121 | L43: =L42/L8 -> 0.22224325
A45: NOL Carryforward Schedule (post-TCJA, 80% utilization cap)
A46: Beginning NOL Balance | B46: $M | C46: 0 | D46: =C49 -> 0 | E46: =D49 -> 107.77178 | F46: =E49 -> 61.153572 | G46: =F49 -> 46.062966 | H46: =G49 -> 0 | I46: =H49 -> 0 | J46: =I49 -> 0 | K46: =J49 -> 0 | L46: =K49 -> 0
A47: + Current Year Loss Added (if pretax < 0) | B47: $M | C47: 0 | D47: =MAX(0,-D40) -> 107.77178 | E47: =MAX(0,-E40) -> 0 | F47: =MAX(0,-F40) -> 0 | G47: =MAX(0,-G40) -> 0 | H47: =MAX(0,-H40) -> 0 | I47: =MAX(0,-I40) -> 0 | J47: =MAX(0,-J40) -> 0 | K47: =MAX(0,-K40) -> 0 | L47: =MAX(0,-L40) -> 0
A48: − NOL Utilized Against Current Income | B48: $M | C48: 0 | D48: =MIN(D46, MAX(0,D40)*0.8) -> 0 | E48: =MIN(E46, MAX(0,E40)*0.8) -> 46.618211 | F48: =MIN(F46, MAX(0,F40)*0.8) -> 15.090605 | G48: =MIN(G46, MAX(0,G40)*0.8) -> 46.062966 | H48: =MIN(H46, MAX(0,H40)*0.8) -> 0 | I48: =MIN(I46, MAX(0,I40)*0.8) -> 0 | J48: =MIN(J46, MAX(0,J40)*0.8) -> 0 | K48: =MIN(K46, MAX(0,K40)*0.8) -> 0 | L48: =MIN(L46, MAX(0,L40)*0.8) -> 0
A49: Ending NOL Balance | B49: $M | C49: =C46+C47-C48 -> 0 | D49: =D46+D47-D48 -> 107.77178 | E49: =E46+E47-E48 -> 61.153572 | F49: =F46+F47-F48 -> 46.062966 | G49: =G46+G47-G48 -> 0 | H49: =H46+H47-H48 -> 0 | I49: =I46+I47-I48 -> 0 | J49: =J46+J47-J48 -> 0 | ... L49: =L46+L47-L48 -> 0

Sheet FCF
A1: WHOOP — FCF
A2: Free cash flow build. ΔNWC sourced from WC & Cash tab (detailed deferred-rev schedule).
B5: Units | C5: 2024 | D5: 2025 | E5: 2026 | F5: 2027 | G5: 2028 | H5: 2029 | I5: 2030 | J5: 2031 | K5: 2032 | L5: 2033
C6: Historical | D6: Historical | E6: Phase 1 | F6: Phase 1 | G6: Phase 2 | H6: Phase 2 | I6: Phase 2 | J6: Phase 3 | K6: Phase 3 | L6: Phase 3
A8: 1. EBIT to NOPAT
A9: EBIT | B9: $M | D9: ='P&L'!D34 -> -110.39678 | E9: ='P&L'!E34 -> 37.699297 | F9: ='P&L'!F34 -> -17.06257 | G9: ='P&L'!G34 -> 125.56172 | H9: ='P&L'!H34 -> 188.22615 | I9: ='P&L'!I34 -> 294.16748 | J9: ='P&L'!J34 -> 553.44561 | K9: ='P&L'!K34 -> 704.52442 | L9: ='P&L'!L34 -> 909.19502 | M9: = P&L EBIT (row 33)
A10: Less: Cash taxes on EBIT | B10: $M | D10: ='P&L'!D41 -> 0 | E10: ='P&L'!E41 -> 2.6805471 | F10: ='P&L'!F41 -> 0.8677098 | G10: ='P&L'!G41 -> 27.689421 | H10: ='P&L'!H41 -> 54.56813 | I10: ='P&L'!I41 -> 81.420161 | J10: ='P&L'!J41 -> 144.49013 | K10: ='P&L'!K41 -> 183.90255 | L10: ='P&L'!L41 -> 236.85026 | M10: = P&L Cash Taxes (row 40), tax-affected at effective rate
A11: NOPAT | B11: $M | D11: =D9-D10 -> -110.39678 | E11: =E9-E10 -> 35.01875 | F11: =F9-F10 -> -17.93028 | G11: =G9-G10 -> 97.872299 | H11: =H9-H10 -> 133.65802 | I11: =I9-I10 -> 212.74732 | J11: =J9-J10 -> 408.95548 | K11: =K9-K10 -> 520.62187 | L11: =L9-L10 -> 672.34476 | M11: = EBIT − Cash Taxes
A13: 2. NOPAT to Unlevered FCF
A14: Plus: D&A | B14: $M | D14: ='P&L'!D8*Assumptions!$F$53 -> 18.492736 | E14: ='P&L'!E8*Assumptions!$F$53 -> 31.150398 | F14: ='P&L'!F8*Assumptions!$F$53 -> 39.96381 | G14: ='P&L'!G8*Assumptions!$F$53 -> 51.106498 | H14: ='P&L'!H8*Assumptions!$F$53 -> 63.078923 | I14: ='P&L'!I8*Assumptions!$F$53 -> 77.80683 | J14: ='P&L'!J8*Assumptions!$F$53 -> 92.644733 | K14: ='P&L'!K8*Assumptions!$F$53 -> 107.54867 | L14: ='P&L'!L8*Assumptions!$F$53 -> 124.87521 | M14: = Revenue × D&A % (Assumptions F52)
A15: Less: CapEx | B15: $M | D15: =-'P&L'!D8*Assumptions!$F$49 -> -21.134555 | E15: =-'P&L'!E8*Assumptions!$F$49 -> -35.600455 | F15: =-'P&L'!F8*Assumptions!$F$49 -> -45.672926 | G15: =-'P&L'!G8*Assumptions!$F$49 -> -58.407426 | H15: =-'P&L'!H8*Assumptions!$F$49 -> -72.090197 | I15: =-'P&L'!I8*Assumptions!$F$49 -> -88.922091 | J15: =-'P&L'!J8*Assumptions!$F$49 -> -105.87969 | K15: =-'P&L'!K8*Assumptions!$F$49 -> -122.91277 | L15: =-'P&L'!L8*Assumptions!$F$49 -> -142.71452 | M15: = −(Revenue × CapEx %) (Assumptions F48)
A16: Less: Change in NWC | B16: $M | D16: ='WC & Cash'!D26 -> 338.35194 | E16: ='WC & Cash'!E26 -> 120.57015 | F16: ='WC & Cash'!F26 -> 165.47383 | G16: ='WC & Cash'!G26 -> 141.90166 | H16: ='WC & Cash'!H26 -> 184.11422 | I16: ='WC & Cash'!I26 -> 225.20042 | J16: ='WC & Cash'!J26 -> 183.69416 | K16: ='WC & Cash'!K26 -> 224.36592 | L16: ='WC & Cash'!L26 -> 253.26978 | M16: = From WC & Cash tab (Section 3, Total ΔNWC)
A17: Note: SBC is REAL COST in P&L — do NOT add back | M17: Per methodology Sec 6 — SBC stays in P&L as cash-equivalent expense
A18: Unlevered Free Cash Flow | B18: $M | D18: =D11+D14+D15+D16 -> 225.31334 | E18: =E11+E14+E15+E16 -> 151.13884 | F18: =F11+F14+F15+F16 -> 141.83444 | G18: =G11+G14+G15+G16 -> 232.47303 | H18: =H11+H14+H15+H16 -> 308.76097 | I18: =I11+I14+I15+I16 -> 426.83248 | J18: =J11+J14+J15+J16 -> 579.41467 | K18: =K11+K14+K15+K16 -> 729.6237 | L18: =L11+L14+L15+L16 -> 907.77523 | M18: = NOPAT + D&A + CapEx + ΔNWC
A20: 3. FCF Diagnostics
A21: FCF Margin % | B21: % | D21: =IFERROR(D18/'P&L'!D8,0) -> 0.42643593 | E21: =IFERROR(E18/'P&L'!E8,0) -> 0.16981675 | F21: =IFERROR(F18/'P&L'!F8,0) -> 0.12421752 | G21: =IFERROR(G18/'P&L'!G8,0) -> 0.15920786 | H21: =IFERROR(H18/'P&L'!H8,0) -> 0.17131925 | I21: =IFERROR(I18/'P&L'!I8,0) -> 0.1920029 | J21: =IFERROR(J18/'P&L'!J8,0) -> 0.21889548 | K21: =IFERROR(K18/'P&L'!K8,0) -> 0.2374444 | L21: =IFERROR(L18/'P&L'!L8,0) -> 0.25443107 | M21: FCF / Revenue
A22: Rule of 40 (Growth + FCF Margin) | B22: % | E22: =IFERROR(('P&L'!E8/'P&L'!D8-1)*100 + E21*100,0) -> 85.428349 | F22: =IFERROR(('P&L'!F8/'P&L'!E8-1)*100 + F21*100,0) -> 40.714849 | G22: =IFERROR(('P&L'!G8/'P&L'!F8-1)*100 + G21*100,0) -> 43.802731 | H22: =IFERROR(('P&L'!H8/'P&L'!G8-1)*100 + H21*100,0) -> 40.558349 | I22: =IFERROR(('P&L'!I8/'P&L'!H8-1)*100 + I21*100,0) -> 42.54867 | J22: =IFERROR(('P&L'!J8/'P&L'!I8-1)*100 + J21*100,0) -> 40.959729 | K22: =IFERROR(('P&L'!K8/'P&L'!J8-1)*100 + K21*100,0) -> 39.831633 | L22: =IFERROR(('P&L'!L8/'P&L'!K8-1)*100 + L21*100,0) -> 41.553523 | M22: Revenue Growth % + FCF Margin %

Sheet WC & Cash
A1: WHOOP — Working Capital & Cash Roll-Forward
A2: $M; pre-IPO (no debt service / dividends / buybacks). Replaces FCF-tab ΔNWC plug with explicit WC build.
A3: Detailed WC schedule wired into FCF tab as of this session. DCF EV impact: +$813M.
B5: Units | C5: 2024 | D5: 2025 | E5: 2026 | F5: 2027 | G5: 2028 | H5: 2029 | I5: 2030 | J5: 2031 | K5: 2032 | L5: 2033
A7: 1. Drivers
A8: Avg months remaining on annual sub (deferred rev) | B8: mo | D8: 6
A9: Inventory days (gross adds device cost) | B9: days | D9: 45
A10: Accounts payable days (% of total COGS) | B10: days | D10: 18
A11: Other NWC (% of revenue) | B11: % | D11: 0.015
A12: Pre-existing cash balance (start 2025) | B12: $M | D12: 75
A13: Series G proceeds (closed Mar 2026) | B13: $M | D13: 0 | E13: 575
A15: 2. Working Capital Balances (Liabilities = Source / Assets = Use)
A16: Deferred Revenue (= End Members × ARPU × mo/12) | B16: $M | C16: 0 | D16: =Members!D34*ARPU!D35*$D$8/12 -> 347.60781 | E16: =Members!E34*ARPU!E35*$D$8/12 -> 478.72962 | F16: =Members!F34*ARPU!F35*$D$8/12 -> 642.26951 | G16: =Members!G34*ARPU!G35*$D$8/12 -> 789.70331 | H16: =Members!H34*ARPU!H35*$D$8/12 -> 977.50257 | I16: =Members!I34*ARPU!I35*$D$8/12 -> 1201.6917 | J16: =Members!J34*ARPU!J35*$D$8/12 -> 1390.7645 | K16: =Members!K34*ARPU!K35*$D$8/12 -> 1618.1761 | L16: =Members!L34*ARPU!L35*$D$8/12 -> 1874.422
A17: Inventory (= ~45 days of NEXT-yr hardware COGS) | B17: $M | C17: 0 | D17: ='P&L'!E13*$D$9/365 -> 11.725335 | E17: ='P&L'!F13*$D$9/365 -> 18.287905 | F17: ='P&L'!G13*$D$9/365 -> 17.379348 | G17: ='P&L'!H13*$D$9/365 -> 20.578748 | H17: ='P&L'!I13*$D$9/365 -> 23.51816 | I17: ='P&L'!J13*$D$9/365 -> 21.264511 | J17: ='P&L'!K13*$D$9/365 -> 23.444159 | K17: ='P&L'!L13*$D$9/365 -> 25.199691 | L17: =K17*1.05 -> 26.459675
A18: Accounts Payable (= ~18 days of total COGS) | B18: $M | C18: 0 | D18: ='P&L'!D14*$D$10/365 -> 10.394922 | E18: ='P&L'!E14*$D$10/365 -> 11.830543 | F18: ='P&L'!F14*$D$10/365 -> 16.633109 | G18: ='P&L'!G14*$D$10/365 -> 19.075808 | H18: ='P&L'!H14*$D$10/365 -> 23.461217 | I18: ='P&L'!I14*$D$10/365 -> 28.530769 | J18: ='P&L'!J14*$D$10/365 -> 31.69091 | K18: ='P&L'!K14*$D$10/365 -> 36.788156 | L18: ='P&L'!L14*$D$10/365 -> 42.497702
A19: Other NWC (= 1.5% of revenue) | B19: $M | C19: 0 | D19: ='P&L'!D8*$D$11 -> 7.9254581 | E19: ='P&L'!E8*$D$11 -> 13.350171 | F19: ='P&L'!F8*$D$11 -> 17.127347 | G19: ='P&L'!G8*$D$11 -> 21.902785 | H19: ='P&L'!H8*$D$11 -> 27.033824 | I19: ='P&L'!I8*$D$11 -> 33.345784 | J19: ='P&L'!J8*$D$11 -> 39.704886 | K19: ='P&L'!K8*$D$11 -> 46.092287 | L19: ='P&L'!L8*$D$11 -> 53.517946
A21: 3. Change in WC (positive = cash source)
A22: Δ Deferred Revenue (liability ↑ = source) | B22: $M | D22: =D16-C16 -> 347.60781 | E22: =E16-D16 -> 131.12181 | F22: =F16-E16 -> 163.53989 | G22: =G16-F16 -> 147.4338 | H22: =H16-G16 -> 187.79926 | I22: =I16-H16 -> 224.18918 | J22: =J16-I16 -> 189.07276 | K22: =K16-J16 -> 227.41161 | L22: =L16-K16 -> 256.24588
A23: Δ Inventory (asset ↑ = use) | B23: $M | D23: =-(D17-C17) -> -11.725335 | E23: =-(E17-D17) -> -6.5625696 | F23: =-(F17-E17) -> 0.90855709 | G23: =-(G17-F17) -> -3.1994004 | H23: =-(H17-G17) -> -2.9394119 | I23: =-(I17-H17) -> 2.2536492 | J23: =-(J17-I17) -> -2.179648 | K23: =-(K17-J17) -> -1.7555317 | L23: =-(L17-K17) -> -1.2599845
A24: Δ Accounts Payable (liability ↑ = source) | B24: $M | D24: =D18-C18 -> 10.394922 | E24: =E18-D18 -> 1.4356206 | F24: =F18-E18 -> 4.8025667 | G24: =G18-F18 -> 2.4426989 | H24: =H18-G18 -> 4.3854093 | I24: =I18-H18 -> 5.0695521 | J24: =J18-I18 -> 3.1601402 | K24: =K18-J18 -> 5.0972459 | L24: =L18-K18 -> 5.7095465
A25: Δ Other NWC (asset ↑ = use) | B25: $M | D25: =-(D19-C19) -> -7.9254581 | E25: =-(E19-D19) -> -5.4247125 | F25: =-(F19-E19) -> -3.7771767 | G25: =-(G19-F19) -> -4.7754376 | H25: =-(H19-G19) -> -5.1310392 | I25: =-(I19-H19) -> -6.3119601 | J25: =-(J19-I19) -> -6.3591015 | K25: =-(K19-J19) -> -6.3874013 | L25: =-(L19-K19) -> -7.4256588
A26: Total Δ NWC (cash impact) | B26: $M | D26: =SUM(D22:D25) -> 338.35194 | E26: =SUM(E22:E25) -> 120.57015 | F26: =SUM(F22:F25) -> 165.47383 | G26: =SUM(G22:G25) -> 141.90166 | H26: =SUM(H22:H25) -> 184.11422 | I26: =SUM(I22:I25) -> 225.20042 | J26: =SUM(J22:J25) -> 183.69416 | K26: =SUM(K22:K25) -> 224.36592 | L26: =SUM(L22:L25) -> 253.26978
A28: 4. Cash Roll-Forward (pre-IPO; no debt service / dividends / buybacks)
A29: Beginning Cash | B29: $M | D29: =$D$12 -> 75 | E29: =D33 -> 300.31334 | F29: =E33 -> 1026.4522 | G29: =F33 -> 1168.2866 | H29: =G33 -> 1400.7597 | I29: =H33 -> 1709.5206 | J29: =I33 -> 2136.3531 | K29: =J33 -> 2715.7678 | L29: =K33 -> 3445.3915
A30: + Series G proceeds | B30: $M | D30: =$D$13 -> 0 | E30: =$E$13 -> 575
A31: + Unlevered Free Cash Flow (FCF tab) | B31: $M | D31: =FCF!D18 -> 225.31334 | E31: =FCF!E18 -> 151.13884 | F31: =FCF!F18 -> 141.83444 | G31: =FCF!G18 -> 232.47303 | H31: =FCF!H18 -> 308.76097 | I31: =FCF!I18 -> 426.83248 | J31: =FCF!J18 -> 579.41467 | K31: =FCF!K18 -> 729.6237 | L31: =FCF!L18 -> 907.77523
A33: Ending Cash | B33: $M | D33: =D29+D30+D31 -> 300.31334 | E33: =E29+E30+E31 -> 1026.4522 | F33: =F29+F31 -> 1168.2866 | G33: =G29+G31 -> 1400.7597 | H33: =H29+H31 -> 1709.5206 | I33: =I29+I31 -> 2136.3531 | J33: =J29+J31 -> 2715.7678 | K33: =K29+K31 -> 3445.3915 | L33: =L29+L31 -> 4353.1667
A40: Beginning Cash | B40: $M | D40: =$D$12 -> 75 | E40: =D44 -> 300.31334 | F40: =E44 -> 1026.4522 | G40: =F44 -> 1168.2866 | H40: =G44 -> 1400.7597 | I40: =H44 -> 1709.5206 | J40: =I44 -> 2136.3531 | K40: =J44 -> 2715.7678 | L40: =K44 -> 3445.3915
A41: + Series G proceeds | B41: $M | D41: =$D$13 -> 0 | E41: =$E$13 -> 575
A42: + UFCF rebuilt: NOPAT + D&A + CapEx + DETAILED ΔNWC | B42: $M | D42: =FCF!D11+FCF!D14+FCF!D15+D26 -> 225.31334 | E42: =FCF!E11+FCF!E14+FCF!E15+E26 -> 151.13884 | F42: =FCF!F11+FCF!F14+FCF!F15+F26 -> 141.83444 | G42: =FCF!G11+FCF!G14+FCF!G15+G26 -> 232.47303 | H42: =FCF!H11+FCF!H14+FCF!H15+H26 -> 308.76097 | I42: =FCF!I11+FCF!I14+FCF!I15+I26 -> 426.83248 | J42: =FCF!J11+FCF!J14+FCF!J15+J26 -> 579.41467 | K42: =FCF!K11+FCF!K14+FCF!K15+K26 -> 729.6237 | L42: =FCF!L11+FCF!L14+FCF!L15+L26 -> 907.77523
A44: Ending Cash | B44: $M | D44: =D40+D41+D42 -> 300.31334 | E44: =E40+E41+E42 -> 1026.4522 | F44: =F40+F42 -> 1168.2866 | G44: =G40+G42 -> 1400.7597 | H44: =H40+H42 -> 1709.5206 | I44: =I40+I42 -> 2136.3531 | J44: =J40+J42 -> 2715.7678 | K44: =K40+K42 -> 3445.3915 | L44: =L40+L42 -> 4353.1667

Sheet DCF
A1: WHOOP — Discounted Cash Flow
A2: $M; Calendar Year; Base case below — see Sensitivity tab for ranges
A3: ⚠ Integrity flags: TV divergence 30% (>25% threshold), TV % EV 78% (>75% threshold) — both improved materially after WC wiring. See notes on C30, C33
B5: Units | C5: 2025 | D5: 2026 | E5: 2027 | F5: 2028 | G5: 2029 | H5: 2030 | I5: 2031 | J5: 2032 | K5: 2033
A7: 1. Cash Flow & Discounting
A8: Revenue (memo) | B8: $M | C8: ='P&L'!D8 -> 528.36388 | D8: ='P&L'!E8 -> 890.01137 | E8: ='P&L'!F8 -> 1141.8232 | F8: ='P&L'!G8 -> 1460.1857 | G8: ='P&L'!H8 -> 1802.2549 | H8: ='P&L'!I8 -> 2223.0523 | I8: ='P&L'!J8 -> 2646.9924 | J8: ='P&L'!K8 -> 3072.8191 | K8: ='P&L'!L8 -> 3567.863 | M8: ← From P&L tab
A9: Unlevered Free Cash Flow | B9: $M | C9: =FCF!D18 -> 225.31334 | D9: =FCF!E18 -> 151.13884 | E9: =FCF!F18 -> 141.83444 | F9: =FCF!G18 -> 232.47303 | G9: =FCF!H18 -> 308.76097 | H9: =FCF!I18 -> 426.83248 | I9: =FCF!J18 -> 579.41467 | J9: =FCF!K18 -> 729.6237 | K9: =FCF!L18 -> 907.77523 | M9: ← From FCF tab (single source of truth)
A10: FCF Margin % | B10: % | C10: =IFERROR(C9/C8,0) -> 0.42643593 | D10: =IFERROR(D9/D8,0) -> 0.16981675 | E10: =IFERROR(E9/E8,0) -> 0.12421752 | F10: =IFERROR(F9/F8,0) -> 0.15920786 | G10: =IFERROR(G9/G8,0) -> 0.17131925 | H10: =IFERROR(H9/H8,0) -> 0.1920029 | I10: =IFERROR(I9/I8,0) -> 0.21889548 | J10: =IFERROR(J9/J8,0) -> 0.2374444 | K10: =IFERROR(K9/K8,0) -> 0.25443107
A12: WACC | B12: % | C12: n/a | D12: =Assumptions!$F$74 -> 0.10845 | E12: =Assumptions!$F$74 -> 0.10845 | F12: =Assumptions!$F$74 -> 0.10845 | G12: =Assumptions!$F$74 -> 0.10845 | H12: =Assumptions!$F$74 -> 0.10845 | I12: =Assumptions!$F$74 -> 0.10845 | J12: =Assumptions!$F$74 -> 0.10845 | K12: =Assumptions!$F$74 -> 0.10845 | M12: ← Assumptions F73
A13: Discount Period (mid-year) | B13: yrs | C13: n/a | D13: 0.5 | E13: 1.5 | F13: 2.5 | G13: 3.5 | H13: 4.5 | I13: 5.5 | J13: 6.5 | K13: 7.5 | M13: Mid-year convention
A14: Discount Factor | B14: x | C14: n/a | D14: =1/(1+D12)^D13 -> 0.94982139 | E14: =1/(1+E12)^E13 -> 0.85689151 | F14: =1/(1+F12)^F13 -> 0.77305382 | G14: =1/(1+G12)^G13 -> 0.69741876 | H14: =1/(1+H12)^H13 -> 0.62918378 | I14: =1/(1+I12)^I13 -> 0.56762486 | J14: =1/(1+J12)^J13 -> 0.51208883 | K14: =1/(1+K12)^K13 -> 0.4619864
A15: PV of Unlevered FCF | B15: $M | C15: n/a | D15: =D9*D14 -> 143.5549 | E15: =E9*E14 -> 121.53672 | F15: =F9*F14 -> 179.71417 | G15: =G9*G14 -> 215.33569 | H15: =H9*H14 -> 268.55607 | I15: =I9*I14 -> 328.89017 | J15: =J9*J14 -> 373.63215 | K15: =K9*K14 -> 419.37981 | M15: = UFCF / (1+WACC)^period
A18: Discounting
A19: WACC | B19: % | L19: ← From Assumptions D1-D5
A20: Discount Period | B20: # | L20: Mid-year convention
A21: Discount Factor | B21: x
A22: PV of FCF | B22: $M
A24: 2. Terminal Value
A25: Terminal Year Revenue | B25: $M | C25: =K8 -> 3567.863
A26: Terminal Year EBITDA | B26: $M | C26: ='P&L'!L32 -> 1194.6241
A27: Terminal Year FCF | B27: $M | C27: =K9 -> 907.77523
A28: Exit Multiple (EV/Revenue) | B28: x | C28: =Assumptions!$F$78 -> 4.5 | L28: ← From Assumptions D10
A29: Terminal Value (Exit Multiple) | B29: $M | C29: =C25*C28 -> 16055.384
A30: Terminal Value (Gordon Growth) | B30: $M | C30: =C27*(1+Assumptions!$F$80)/(D12-Assumptions!$F$80) -> 11918.528 | L30: =FCF * (1+g) / (WACC - g) -> #NAME?
A31: TV Method Divergence | B31: % | C31: =ABS(C29-C30)/((C29+C30)/2) -> 0.2957653 | L31: If >25%, an assumption is inconsistent
A32: Selected Terminal Value | B32: $M | C32: =C29 -> 16055.384
A33: PV of Terminal Value | B33: $M | C33: =C32*K14 -> 7417.3689
A34: TV as % of Total EV | B34: % | C34: =C33/(C33+SUM(D15:K15)) -> 0.78341714 | L34: If >75%, explicit forecast doing too little
A36: 3. Enterprise Value Summary
A37: Sum of PV of FCFs (2026-2033) | B37: $M | C37: =SUM(D15:K15) -> 2050.5997
A38: PV of Terminal Value | B38: $M | C38: =C33 -> 7417.3689
A39: Enterprise Value (DCF Base) | B39: $M | C39: =C37+C38 -> 9467.9686
A41: 4. Equity Bridge
A42: Enterprise Value | B42: $M | C42: =C39 -> 9467.9686
A43: Less: Debt | B43: $M | C43: =-Assumptions!$F$62 -> -10 | L43: ~$0 (minimal)
A44: Plus: Cash | B44: $M | C44: =Assumptions!$F$63 -> 700 | L44: $600-800M est. post-Series G
A45: Equity Value | B45: $M | C45: =C42+C43+C44 -> 10157.969
A46: Fully Diluted Shares (M) | B46: M | C46: =Assumptions!$F$55 -> 410 | L46: ~900M (PremierAlts est.)
A47: Equity Value per Share | B47: $/sh | C47: =C45/C46 -> 24.775533
A49: 5. Real Options (Additive)
A50: Correlated Success EV | B50: $M | C50: =RealOptions!E5*1000 -> 990 | L50: ← Probability × Payoff from Assumptions
A51: Mixed Outcomes EV | B51: $M | C51: =RealOptions!E6*1000 -> 1125
A52: Correlated Failure EV | B52: $M | C52: =RealOptions!E7*1000 -> 277.5
A53: Expected Option Value | B53: $M | C53: =C50+C51+C52 -> 2392.5
A54: Total EV (DCF + Options) | B54: $M | C54: =C39+C53 -> 11860.469
A56: 6. Scenario Comparison vs Series G — Framing
A57: DCF Base Case EV | B57: $M | C57: =C39 -> 9467.9686
A58: DCF + Options EV | B58: $M | C58: =C54 -> 11860.469
A59: Series G Mark | B59: $M | C59: 10100 | L59: 10100
A60: DCF Premium / (Discount) to Series G | B60: % | C60: =C57/C59-1 -> -0.062577364 | M60: Base case = 'WHOOP executes plan'
A61: DCF + Options Premium / (Discount) to Series G | B61: % | C61: =C58/C59-1 -> 0.17430382 | M61: Options = 'WHOOP earns bucket-3 narrative'

Sheet RealOptions
A1: WHOOP — Real Options
A2: Cluster framework: correlated outcomes, additive to DCF base case. NEVER embedded in DCF.
A4: Cluster | B4: Description | C4: Value ($B) | D4: Probability | E4: Weighted Value ($B)
A5: Correlated success | B5: Healthcare reimbursement + B2B clinical + Women's health all execute | C5: 5.5 | D5: 0.18 | E5: =C5*D5 -> 0.99
A6: Mixed outcomes | B6: Geographic expansion works; healthcare stalls partially | C6: 2.5 | D6: 0.45 | E6: =C6*D6 -> 1.125
A7: Correlated failure | B7: Healthcare thesis stalls; related options fail together | C7: 0.75 | D7: 0.37 | E7: =C7*D7 -> 0.2775
A8: Probability sum (must = 100%) | D8: =SUM(D5:D7) -> 1
A9: Total Real Option Value (additive to DCF) | E9: =SUM(E5:E7) -> 2.3925
A11: Individual Option Probabilities (reference, not additive)
A12: Healthcare reimbursement | B12: 20-30% — upgraded by CMS Innovation Center selection (Apr 2026)
A13: International expansion | B13: 40-60% — note ~60% of sales already intl, partially in base
A14: B2B enterprise / clinical | B14: 25-40% — Unite already ~20% of recurring, partially in base
A15: Women's health / fertility | B15: 30-50% — 150% YoY women membership growth
A16: Noninvasive glucose monitoring | B16: 3-7% — deliberately conservative; hardest unsolved problem
A18: Probability Justification — Honest Read
A19: Cluster probabilities (D5:D7) are methodology-anchored priors, NOT derived from individual option probabilities. Methodology Sec 4 specifies ranges: success 15-20%, mixed 40-50%, failure 30-40%. Our picks (18% / 45% / 37%) are midpoint judgments within those ranges.
A20: Individual option probabilities (rows 12-16) have research justification but are NOT mathematically connected to cluster probabilities. They serve as a sanity check that the cluster framing is reasonable, not as inputs to the cluster math.
A21: Sensitivity: at methodology's stated probability ranges, option value spans $1.5-3.5B (vs. our $2.4B central case). Each 5pp shift in success cluster probability moves option value ~$275M.
A22: MEMO IMPLICATION: Real option value of $2.4B is the highest-leverage, lowest-rigor input in the model. The +18% premium of DCF+Options vs Series G hinges on these probabilities. If cluster probs shift toward bear (10/40/50), DCF+Options drops to ~$10.5B — essentially in line with Series G mark, no premium.

Sheet Comps
A1: WHOOP — Comparable Company Analysis
A2: As of April 16, 2026; All USD. Comp data is PLACEHOLDER — verify against current SEC filings / market data before relying on output.
A4: Company | B4: Ticker | C4: Bucket | D4: Mkt Cap ($B) | E4: EV ($B) | F4: LTM Rev ($B) | G4: EV/Rev LTM | H4: EV/Rev NTM | I4: EV/EBITDA | J4: Gross Margin | K4: Op Margin | L4: Rev Growth | M4: Rule of 40 | N4: Growth-Adj Mult
D5: $B | E5: $B | F5: $B | G5: x | H5: x | I5: x | J5: % | K5: % | L5: % | M5: # | N5: x ÷ %
A7: Bucket 1: Consumer Hardware
A8: Garmin | B8: GRMN | C8: B1 | D8: 51.2 | E8: 48.6 | F8: 7.25 | G8: =E8/F8 -> 6.7034483 | H8: 6.2 | I8: 22.9 | J8: 0.587 | K8: 0.259 | L8: 0.15 | M8: =(L8 + K8)*100 -> 40.9 | N8: =IFERROR(G8/(L8*100), 0) -> 0.44689655
A10: Bucket 2: Consumer Subscription Hybrid
A11: Peloton | B11: PTON | C11: B2 | D11: 2.1 | E11: 2.8 | F11: 2.49 | G11: =E11/F11 -> 1.124498 | H11: 1.2 | I11: 16.4 | J11: 0.509 | K11: -0.014 | L11: -0.08 | M11: =(L11 + K11)*100 -> -9.4 | N11: =IFERROR(G11/(L11*100), 0) -> -0.14056225
A12: Spotify | B12: SPOT | C12: B2 | D12: 109.3 | E12: 102.6 | F12: 20.2 | G12: =E12/F12 -> 5.0792079 | H12: 4.5 | I12: 38.8 | J12: 0.32 | K12: 0.128 | L12: 0.1 | M12: =(L12 + K12)*100 -> 22.8 | N12: =IFERROR(G12/(L12*100), 0) -> 0.50792079
A14: Bucket 3: Health Data / Medical Device
A15: Dexcom | B15: DXCM | C15: B3 | D15: 23.7 | E15: 23.1 | F15: 4.66 | G15: =E15/F15 -> 4.9570815 | H15: 4.4 | I15: 19.8 | J15: 0.6 | K15: 0.2 | L15: 0.16 | M15: =(L15 + K15)*100 -> 36 | N15: =IFERROR(G15/(L15*100), 0) -> 0.3098176
A16: ResMed | B16: RMD | C16: B3 | D16: 33.2 | E16: 32.6 | F16: 5.4 | G16: =E16/F16 -> 6.037037 | H16: 5.5 | I16: 16.1 | J16: 0.594 | K16: 0.328 | L16: 0.1 | M16: =(L16 + K16)*100 -> 42.8 | N16: =IFERROR(G16/(L16*100), 0) -> 0.6037037
A17: Masimo | B17: MASI | C17: B3 | D17: 9.3 | E17: 9.7 | F17: 1.52 | G17: =E17/F17 -> 6.3815789 | H17: 6 | I17: 28.2 | J17: 0.63 | K17: 0.275 | L17: 0.09 | M17: =(L17 + K17)*100 -> 36.5 | N17: =IFERROR(G17/(L17*100), 0) -> 0.70906433
A18: iRhythm | B18: IRTC | C18: B3 | D18: 4 | E18: 4.2 | F18: 0.75 | G18: =E18/F18 -> 5.6 | H18: 4.8 | I18: 60.5 | J18: 0.706 | K18: -0.077 | L18: 0.26 | M18: =(L18 + K18)*100 -> 18.3 | N18: =IFERROR(G18/(L18*100), 0) -> 0.21538462
A21: Bucket Summary Statistics
A22: Bucket | G22: EV/Rev LTM | H22: EV/Rev NTM | J22: Gross Margin | L22: Rev Growth | M22: Rule of 40 | N22: Growth-Adj Mult
A23: B1: Hardware | G23: =G8 -> 6.7034483 | H23: =H8 -> 6.2 | I23: =I8 -> 22.9 | J23: =J8 -> 0.587 | L23: =L8 -> 0.15 | M23: =M8 -> 40.9 | N23: =N8 -> 0.44689655
A24: B2: Subscription (Peloton) | G24: =G11 -> 1.124498 | H24: =H11 -> 1.2 | I24: =I11 -> 16.4 | J24: =J11 -> 0.509 | L24: =L11 -> -0.08 | M24: =M11 -> -9.4 | N24: =N11 -> -0.14056225
A25: B2: Subscription (Spotify) | G25: =G12 -> 5.0792079 | H25: =H12 -> 4.5 | I25: =I12 -> 38.8 | J25: =J12 -> 0.32 | L25: =L12 -> 0.1 | M25: =M12 -> 22.8 | N25: =N12 -> 0.50792079
A26: B3: Health Data (Median) | G26: =MEDIAN(G15:G18) -> 5.8185185 | H26: =MEDIAN(H15:H18) -> 5.15 | I26: =MEDIAN(I15:I18) -> 24 | J26: =MEDIAN(J15:J18) -> 0.615 | L26: =MEDIAN(L15:L18) -> 0.13 | M26: =MEDIAN(M15:M18) -> 36.25 | N26: =MEDIAN(N15:N18) -> 0.45676065
A27: B3: Health Data (Range) | G27: =MIN(G15:G18) & "-" & MAX(G15:G18) & "x" -> 4.95708154506438-6.38157894736842x | H27: =MIN(H15:H18) & "-" & MAX(H15:H18) & "x" -> 4.4-6x
A30: Implied WHOOP Valuation by Bucket Weighting
A31: Scenario | B31: B1 Wt | C31: B2 Wt | D31: B3 Wt | E31: B1 Mult | F31: B2 Mult | G31: B3 Mult | H31: Blended | I31: Impl. EV ($B) | J31: vs. $10.1B
A32: Bear | B32: 0.4 | C32: 0.4 | D32: 0.2 | E32: =$G$23 -> 6.7034483 | F32: =$G$24 -> 1.124498 | G32: =$G$26 -> 5.8185185 | H32: =B32*E32 + C32*F32 + D32*G32 -> 4.2948822 | I32: =H32 * $C$44 / 1000 -> 4.7243704 | J32: =I32*1000/10100 - 1 -> -0.53224055
A33: Base | B33: 0.2 | C33: 0.4 | D33: 0.4 | E33: =$G$23 -> 6.7034483 | F33: =AVERAGE($G$24,$G$25) -> 3.101853 | G33: =$G$26 -> 5.8185185 | H33: =B33*E33 + C33*F33 + D33*G33 -> 4.9088382 | I33: =H33 * $C$44 / 1000 -> 5.3997221 | J33: =I33*1000/10100 - 1 -> -0.46537405
A34: Bull | B34: 0.1 | C34: 0.3 | D34: 0.6 | E34: =$G$23 -> 6.7034483 | F34: =$G$25 -> 5.0792079 | G34: =$G$26 -> 5.8185185 | H34: =B34*E34 + C34*F34 + D34*G34 -> 5.6852183 | I34: =H34 * $C$44 / 1000 -> 6.2537401 | J34: =I34*1000/10100 - 1 -> -0.38081781
A35: Series G Implied | B35: 0.05 | C35: 0.25 | D35: 0.7 | E35: =$G$23 -> 6.7034483 | F35: =$G$25 -> 5.0792079 | G35: =$G$26 -> 5.8185185 | H35: =B35*E35 + C35*F35 + D35*G35 -> 5.6779374 | I35: =H35 * $C$44 / 1000 -> 6.2457311 | J35: =I35*1000/10100 - 1 -> -0.38161078
A37: Note: Blended = (B1Wt × B1Mult) + (B2Wt × B2Mult) + (B3Wt × B3Mult). Implied EV = Blended × 2025 Revenue. vs $10.1B = Implied/Series G mark − 1.
A38: Revenue base: $528M (2025 recognized, from Revenue Build D19). Bookings basis would use $1,100M; methodology Sec 3 says use recognized for comp multiples.
A40: WHOOP Revenue Base for Implied Valuation
A41: 2025 Recognized (model) | B41: ='Revenue Build'!D20 -> 528.36388
A42: 2025 Bookings (methodology proxy) | B42: 1100
A43: 2026 Forecast (NTM) | B43: ='Revenue Build'!E20 -> 890.01137
A44: Active denominator | B44: Bookings | C44: =IF($B$44="Recognized",B41,IF($B$44="Bookings",B42,IF($B$44="NTM",B43,B42))) -> 1100
A46: Dual Back-Solve (Methodology Sec 5 — the central analytical move)
A47: Series G implied multiple (naive) | B47: =10100/$C$44 -> 9.1818182
A48: B3 multiple needed (B1=20%, B2=40%, B3=40% per methodology) | B48: =IFERROR((B47 - 0.2*G23 - 0.4*AVERAGE(G24,G25))/0.4, 0) -> 16.500968
A49: → Premium over B3 median (5.8x) | B49: =IFERROR(B48/G26 - 1, 0) -> 1.8359398
A50: WHOOP growth-adjusted multiple (current) | B50: =B47/100 -> 0.091818182
A51: Bucket-3 median growth-adjusted | B51: =N26 -> 0.45676065
A52: WHOOP vs B3 (growth-adjusted ratio) | B52: =IFERROR(B50/B51, 0) -> 0.20102034
A53: READ: Naive comps say WHOOP needs B3 multiple of 16.5x (vs actual 5.8x median, +184%) to justify Series G — unrealistic. Growth-adjusted says WHOOP at 0.09 is at 20% of B3's growth-adj multiple (0.46) — cheap given growth profile. The dual back-solve resolves: Series G is paying for growth, not just bucket-3 mix.
A55: Key Findings (carry to memo)
A56: 1. Naive comp comparison FAILS to defend Series G. At methodology base bucket weights (20/40/40), would need bucket-3 multiple of 16.5x — nearly 3x current B3 median (5.8x). Means Series G is not defensible on static comp math.
A57: 2. Growth-adjusted comparison RESOLVES the gap. WHOOP at 0.09 growth-adj multiple is at 20% of B3 median (0.46). On a per-unit-of-growth basis, WHOOP is cheap — implying Series G investors are paying for the growth profile, not bucket-3 narrative alone.
A58: 3. Implied EV from bucket-blended comps: Bear $4.7B, Base $5.4B, Bull $6.3B (using $1.1B bookings denominator). All well below Series G $10.1B — confirms growth premium is the gap, not 'wrong bucket weighting'.
A59: 4. Comp data is PLACEHOLDER — refresh with Q1 2026 SEC filings / Bloomberg before relying on output for memo.

Sheet Precedents
A1: WHOOP — Precedent Transactions
A2: 2020-2026; $500M+ EV preferred; All USD
A4: Acquirer / Target | B4: Date | C4: EV ($B) | D4: LTM Rev ($B) | E4: EV/Rev | F4: Regime | G4: Bucket | H4: Strategic Rationale
A5: Google / Fitbit | B5: Jan 2021 | C5: 2.1 | D5: 1.43 | E5: 1.5 | F5: ZIRP-peak | G5: B1 | H5: Wearable data acquisition; failed sub pivot
A6: Lululemon / Mirror | B6: Jul 2020 | C6: 0.5 | D6: 0.17 | E6: 2.9 | F6: ZIRP-peak | G6: B2 | H6: Connected fitness content; 89% write-off
A7: Teladoc / Livongo | B7: Oct 2020 | C7: 18.5 | D7: 0.29 | E7: 63.8 | F7: ZIRP-peak | G7: Cross | H7: Digital health mega-deal; massive write-down
A8: Microsoft / Nuance | B8: Mar 2022 | C8: 19.7 | D8: 1.48 | E8: 13.3 | F8: Transition | G8: Cross | H8: Healthcare AI voice/NLP platform
A9: Masimo / Sound United | B9: Apr 2022 | C9: 1.03 | D9: 0.9 | E9: 1.1 | F9: Transition | G9: B1 | H9: Consumer audio pivot; $675M value destruction
A10: CVS / Signify Health | B10: Sep 2022 | C10: 8 | D10: 0.77 | E10: 10.4 | F10: Transition | G10: B3 | H10: Home health + value-based care platform
A11: Amazon / One Medical | B11: Feb 2023 | C11: 3.9 | D11: 1.1 | E11: 3.5 | F11: Transition | G11: Cross | H11: Primary care distribution; strategic access play
A12: J&J / Shockwave Medical | B12: May 2024 | C12: 13.1 | D12: 0.73 | E12: 17.9 | F12: Current | G12: B3 | H12: OUTLIER: IVL synergies drove 2x+ peer median
A13: BSci / Axonics | B13: Nov 2024 | C13: 3.7 | D13: 0.37 | E13: 10.1 | F13: Current | G13: B3 | H13: Neuromodulation bolt-on
A14: Stryker / Inari Medical | B14: Feb 2025 | C14: 4.9 | D14: 0.6 | E14: 8.1 | F14: Current | G14: B3 | H14: Venous thromboembolism devices
A15: Danaher / Masimo | B15: Feb 2026 | C15: 9.9 | D15: 1.51 | E15: 6.6 | F15: Current | G15: B3 | H15: Patient monitoring platform; pending close
A18: Summary by Regime & Bucket
A19: Current-regime B3 medtech: 6.6-10.1x (median ~8.5x)
A20: Connected fitness deals: uniformly value-destructive
A21: Implied WHOOP range: $5-8B (control premium embedded; Series G is minority)

Sheet Cap Table
A1: WHOOP — Cap Table & Waterfall
A2: Sources: Pitchbook + Cap IQ; BUILD WATERFALL FORMULAS
A4: Round | B4: Date | C4: Amount ($M) | D4: Post-Money ($B) | E4: Price/Share ($) | F4: Shares (M) | G4: Ownership % | H4: Pref Terms | I4: Lead Investor(s)
A5: Seed | B5: 2012 | C5: 1 | H5: 1x non-part. | I5: DraftKings founders
A6: Series A | B6: Sep 2014 | C6: 4 | H6: 1x non-part. | I6: Accomplice, Mousse Partners
A7: Series B | B7: Sep 2016 | C7: 12 | H7: 1x non-part. | I7: Foundry Group
A8: Series C | B8: Oct 2018 | C8: 55 | D8: 0.43 | H8: 1x non-part. | I8: IVP
A9: Series D | B9: Oct 2020 | C9: 100 | D9: 1.2 | H9: 1x non-part. | I9: IVP
A10: Series E | B10: Aug 2021 | C10: 200 | D10: 2.4 | H10: 1x non-part. | I10: SoftBank Vision Fund 2
A11: Series F | B11: Aug 2021 | C11: 200 | D11: 3.6 | E11: 4.76 | H11: 1x non-part. | I11: SoftBank Vision Fund 2
A12: Mezz/Bridge | B12: 2022-2024 | C12: 46 | H12: Various | I12: 5 interim rounds (VC + debt)
A13: Series G | B13: Mar 2026 | C13: 575 | D13: 10.1 | E13: 11.23 | G13: 0.057 | H13: 1x non-part. | I13: Collaborative Fund
A15: Total Equity Raised: | C15: 1030
A17: Key Metrics
A18: Authorized Preferred Shares | C18: 537.9M | E18: Pitchbook
A19: Outstanding Common Shares | C19: 361.2M | E19: Pitchbook
A20: Fully Diluted Shares (est.) | C20: ~900M | E20: PremierAlts/Forge
A21: Option Pool (est.) | C21: ~10-15% of FD | E21: Inferred from gap; FLAGGED_GAP
A22: All Preferences | C22: 1x non-participating pari passu | E22: Pitchbook
A23: Total Liquidation Preference | C23: ~$1.03B (floor) | E23: Sum of equity raised × 1x
A26: Waterfall at Exit Scenarios (BUILD FORMULAS)
C27: Bear ($5B) | E27: Base ($10B) | G27: Bull ($20B)
A28: Total Exit Proceeds
A29: Less: Liquidation Preferences
A30: Remaining for Pro-Rata
A31: Preferred Conversion Check (convert or take pref?)
A32: Common Share Proceeds
A33: Common Value per Share
A34: Preferred Value per Share
A35: Founder Equity Value (est. 12-18% FD)

Sheet Football Field
A1: WHOOP — Valuation Football Field
A2: Multi-method synthesis. Each method shown with low/base/high EV. Per-share converts via Assumptions F62 (debt), F63 (cash), F55 (FD shares).
A4: Method | B4: Source | C4: Low EV ($B) | D4: Base EV ($B) | E4: High EV ($B) | F4: Low $/sh | G4: Base $/sh | H4: High $/sh | I4: Weight | J4: Wtd Base | K4: Note
A6: 1. Intrinsic DCF (base case, no options) | B6: Sensitivity Grid 1 | C6: =Sensitivity!B44 -> 6.3895032 | D6: =Sensitivity!C44 -> 9.4650065 | E6: =Sensitivity!D44 -> 13.142741 | F6: =(C6*1000 - Assumptions!$F$62 + Assumptions!$F$63)/Assumptions!$F$55 -> 17.267081 | G6: =(D6*1000 - Assumptions!$F$62 + Assumptions!$F$63)/Assumptions!$F$55 -> 24.768309 | H6: =(E6*1000 - Assumptions!$F$62 + Assumptions!$F$63)/Assumptions!$F$55 -> 33.738393 | I6: 0.4 | J6: =D6*I6 -> 3.7860026 | K6: Primary fundamental method. WACC × Exit Mult range.
A7: 1b. DCF + Real Options (probability-wtd) | B7: DCF C53 | C7: =C6 + RealOptions!E7 -> 6.6670032 | D7: =DCF!C54/1000 -> 11.860469 | E7: =E6 + RealOptions!E5 -> 14.132741 | F7: =(C7*1000 - Assumptions!$F$62 + Assumptions!$F$63)/Assumptions!$F$55 -> 17.94391 | G7: =(D7*1000 - Assumptions!$F$62 + Assumptions!$F$63)/Assumptions!$F$55 -> 30.610899 | H7: =(E7*1000 - Assumptions!$F$62 + Assumptions!$F$63)/Assumptions!$F$55 -> 36.153028 | K7: Cluster-modeled options (success/mixed/failure). Additive to DCF.
A8: 2. Trading Comps (bucket-weighted, naive) | B8: Comps I32:I34 | C8: =Comps!I32 -> 4.7243704 | D8: =Comps!I33 -> 5.3997221 | E8: =Comps!I34 -> 6.2537401 | F8: =(C8*1000 - Assumptions!$F$62 + Assumptions!$F$63)/Assumptions!$F$55 -> 13.205782 | G8: =(D8*1000 - Assumptions!$F$62 + Assumptions!$F$63)/Assumptions!$F$55 -> 14.852981 | H8: =(E8*1000 - Assumptions!$F$62 + Assumptions!$F$63)/Assumptions!$F$55 -> 16.935952 | I8: 0.2 | J8: =D8*I8 -> 1.0799444 | K8: Naive comp comparison — fails to defend Series G mark.
A9: 2b. Comps applied to FORWARD revenue (NTM 2026) | B9: Bucket-blended × NTM Rev | C9: =Comps!H32 * 'Revenue Build'!$E$20 / 1000 -> 3.822494 | D9: =Comps!H33 * 'Revenue Build'!$E$20 / 1000 -> 4.3689219 | E9: =Comps!H34 * 'Revenue Build'!$E$20 / 1000 -> 5.059909 | F9: =(C9*1000 - Assumptions!$F$62 + Assumptions!$F$63)/Assumptions!$F$55 -> 11.006083 | G9: =(D9*1000 - Assumptions!$F$62 + Assumptions!$F$63)/Assumptions!$F$55 -> 12.338834 | H9: =(E9*1000 - Assumptions!$F$62 + Assumptions!$F$63)/Assumptions!$F$55 -> 14.024168 | I9: 0.15 | J9: =D9*I9 -> 0.65533828 | K9: Comps applied to NTM revenue — captures near-term scaling. Diagnostic shows WHOOP valued reasonably on forward basis.
A10: 3. Precedent Transactions | B10: Not yet populated | C10: n/a | D10: n/a | E10: n/a | K10: Skipped per session decision. 5-10% memo weight max per methodology.
A11: 4. Last-Round Implied (Series G) | B11: DCF C58 | C11: =DCF!C59/1000 -> 10.1 | D11: =DCF!C59/1000 -> 10.1 | E11: =DCF!C59/1000 -> 10.1 | F11: =(C11*1000 - Assumptions!$F$62 + Assumptions!$F$63)/Assumptions!$F$55 -> 26.317073 | G11: =(D11*1000 - Assumptions!$F$62 + Assumptions!$F$63)/Assumptions!$F$55 -> 26.317073 | H11: =(E11*1000 - Assumptions!$F$62 + Assumptions!$F$63)/Assumptions!$F$55 -> 26.317073 | I11: 0.1 | J11: =D11*I11 -> 1.01 | K11: Anchor only — single point. Market datapoint, not derived value.
A12: 5. Implied IPO Trading Range | B12: Assumptions C94/D94/E94 | C12: =Assumptions!E94/1000 -> 12.50774 | D12: =Assumptions!D94/1000 -> 14.027778 | E12: =Assumptions!C94/1000 -> 15.843137 | F12: =(C12*1000 - Assumptions!$F$62 + Assumptions!$F$63)/Assumptions!$F$55 -> 32.18961 | G12: =(D12*1000 - Assumptions!$F$62 + Assumptions!$F$63)/Assumptions!$F$55 -> 35.897019 | H12: =(E12*1000 - Assumptions!$F$62 + Assumptions!$F$63)/Assumptions!$F$55 -> 40.324725 | I12: 0.15 | J12: =D12*I12 -> 2.1041667 | K12: Back-solve: $10.1B ÷ (1−illiquidity) ÷ (1−IPO discount). Bull = lower discounts, lower implied; Bear = higher discounts, higher implied.
A14: Weight Check | I14: =I6+I8+I9+I11+I12 -> 1
A16: Weighted Average EV | D16: =J6+J8+J9+J11+J12 -> 8.635452 | G16: =(D16*1000 - Assumptions!$F$62 + Assumptions!$F$63)/Assumptions!$F$55 -> 22.745005 | K16: = Σ(weight × base EV) per method
A17: Series G Mark | D17: =DCF!C59/1000 -> 10.1 | G17: =(D17*1000 - Assumptions!$F$62 + Assumptions!$F$63)/Assumptions!$F$55 -> 26.317073
A18: Premium / (Discount) to Series G | D18: =D16/D17 - 1 -> -0.14500475 | G18: =G16/G17 - 1 -> -0.13573198 | K18: Positive = methods support a higher mark; negative = Series G is rich.
A20: Method Range Summary
A21: Lowest method base | B21: =INDEX($A$6:$A$12, MATCH(MIN(D6,D8,D9,D11,D12), D6:D12, 0)) -> 2b. Comps applied to FORWARD revenue (NTM 2026) | D21: =MIN(D6,D8,D9,D11,D12) -> 4.3689219 | G21: =(D21*1000 - Assumptions!$F$62 + Assumptions!$F$63)/Assumptions!$F$55 -> 12.338834
A22: Highest method base | B22: =INDEX($A$6:$A$12, MATCH(MAX(D6,D8,D9,D11,D12), D6:D12, 0)) -> 5. Implied IPO Trading Range | D22: =MAX(D6,D8,D9,D11,D12) -> 14.027778 | G22: =(D22*1000 - Assumptions!$F$62 + Assumptions!$F$63)/Assumptions!$F$55 -> 35.897019
A23: Range across methods | D23: =D22-D21 -> 9.6588559 | G23: =G22-G21 -> 23.558185
A25: Memo Read
A26: Multi-method synthesis lands at $8.6B / $22.75 per share, ~14% below Series G $10.1B / $26.32. Methods range $4.4B (forward comps) to $14.0B (IPO range). DCF is the analytical anchor at $9.5B; comps applied to either current or forward revenue undershoot Series G materially — confirming Series G investors are paying a growth premium not captured in static comp math. Real options ($2.4B additive to DCF) bridge most of the gap. IPO range implies $13-15B which is consistent with Series G investors targeting 25%+ IRR over a 15-month hold to IPO.
A29: Chart Data (helper table for visual)
A30: Method | B30: Low (offset) | C30: Range (visible bar) | D30: Base marker | E30: Series G ref
A31: 1. Intrinsic DCF | B31: =C6 -> 6.3895032 | C31: =E6-C6 -> 6.7532382 | D31: =D6 -> 9.4650065 | E31: 10.1
A32: 1b. DCF + Options | B32: =C7 -> 6.6670032 | C32: =E7-C7 -> 7.4657382 | D32: =D7 -> 11.860469 | E32: 10.1
A33: 2. Comps (LTM) | B33: =C8 -> 4.7243704 | C33: =E8-C8 -> 1.5293697 | D33: =D8 -> 5.3997221 | E33: 10.1
A34: 2b. Comps (NTM) | B34: =C9 -> 3.822494 | C34: =E9-C9 -> 1.2374149 | D34: =D9 -> 4.3689219 | E34: 10.1
A35: 4. Last-Round Implied | B35: =C11 -> 10.1 | C35: 0.001 | D35: =D11 -> 10.1 | E35: 10.1
A36: 5. IPO Range | B36: =C12 -> 12.50774 | C36: =E12-C12 -> 3.3353973 | D36: =D12 -> 14.027778 | E36: 10.1
A37: Weighted Avg | B37: =D16 -> 8.635452 | C37: 0.001 | D37: =D16 -> 8.635452 | E37: 10.1

Sheet Scenarios
A1: WHOOP — Scenario Summary
A2: Scenario EV by method; weight sensitivity grid. Populate after DCF + Comps are wired.
A4: Method | B4: Bear ($B) | C4: Base ($B) | D4: Bull ($B) | E4: Notes
A5: 1. Intrinsic DCF (base) | E5: Link from DCF tab
A6: + Real Options | E6: Link from RealOptions tab
A7: 2. Trading Comps (3-bucket) | E7: Link from Comps tab
A8: 3. Precedent Transactions | E8: Link from Precedents tab
A9: 4. Last-Round Implied | E9: Series G mark = $10.1B (constant)
A10: 5. Implied IPO Trading Range | E10: Link from Assumptions I5
A12: Probability Weight Sensitivity
A13: Weight Scheme | B13: Bear Wt | C13: Base Wt | D13: Bull Wt | E13: Weighted EV ($B)
A14: Pessimistic | B14: 0.35 | C14: 0.5 | D14: 0.15
A15: Neutral (base) | B15: 0.25 | C15: 0.5 | D15: 0.25
A16: Optimistic | B16: 0.15 | C16: 0.55 | D16: 0.3

Sheet Sensitivity
A1: WHOOP — Sensitivity Analysis
A2: Base case anchored: WACC 10.85%, Exit Mult 4.5x, Terminal Growth 3.0%, CSRP 2.0% → EV $9.54B / Equity $10.23B / $24.95 per share. Yellow cell = base case.
A4: Grid 1: WACC × Exit Multiple → Enterprise Value ($B)
A5: WACC ↓ / Exit Mult (EV/Rev) → | B5: 3 | C5: 3.5 | D5: 4 | E5: 4.5 | F5: 5 | G5: 5.5 | H5: 6
A6: 0.0935 | B6: {=(SUMPRODUCT(DCF!$D$9:$K$9, 1/(1+$A6)^DCF!$D$13:$K$13) + DCF!$K$8*B$5/(1+$A6)^DCF!$K$13)/1000} -> 7.6676858 | C6: {=(SUMPRODUCT(DCF!$D$9:$K$9, 1/(1+$A6)^DCF!$D$13:$K$13) + DCF!$K$8*C$5/(1+$A6)^DCF!$K$13)/1000} -> 8.5801951 | D6: {=(SUMPRODUCT(DCF!$D$9:$K$9, 1/(1+$A6)^DCF!$D$13:$K$13) + DCF!$K$8*D$5/(1+$A6)^DCF!$K$13)/1000} -> 9.4927043 | E6: {=(SUMPRODUCT(DCF!$D$9:$K$9, 1/(1+$A6)^DCF!$D$13:$K$13) + DCF!$K$8*E$5/(1+$A6)^DCF!$K$13)/1000} -> 10.405214 | F6: {=(SUMPRODUCT(DCF!$D$9:$K$9, 1/(1+$A6)^DCF!$D$13:$K$13) + DCF!$K$8*F$5/(1+$A6)^DCF!$K$13)/1000} -> 11.317723 | G6: {=(SUMPRODUCT(DCF!$D$9:$K$9, 1/(1+$A6)^DCF!$D$13:$K$13) + DCF!$K$8*G$5/(1+$A6)^DCF!$K$13)/1000} -> 12.230232 | H6: {=(SUMPRODUCT(DCF!$D$9:$K$9, 1/(1+$A6)^DCF!$D$13:$K$13) + DCF!$K$8*H$5/(1+$A6)^DCF!$K$13)/1000} -> 13.142741
A7: 0.0985 | B7: {=(SUMPRODUCT(DCF!$D$9:$K$9, 1/(1+$A7)^DCF!$D$13:$K$13) + DCF!$K$8*B$5/(1+$A7)^DCF!$K$13)/1000} -> 7.4345371 | C7: {=(SUMPRODUCT(DCF!$D$9:$K$9, 1/(1+$A7)^DCF!$D$13:$K$13) + DCF!$K$8*C$5/(1+$A7)^DCF!$K$13)/1000} -> 8.3163526 | D7: {=(SUMPRODUCT(DCF!$D$9:$K$9, 1/(1+$A7)^DCF!$D$13:$K$13) + DCF!$K$8*D$5/(1+$A7)^DCF!$K$13)/1000} -> 9.1981681 | E7: {=(SUMPRODUCT(DCF!$D$9:$K$9, 1/(1+$A7)^DCF!$D$13:$K$13) + DCF!$K$8*E$5/(1+$A7)^DCF!$K$13)/1000} -> 10.079984 | F7: {=(SUMPRODUCT(DCF!$D$9:$K$9, 1/(1+$A7)^DCF!$D$13:$K$13) + DCF!$K$8*F$5/(1+$A7)^DCF!$K$13)/1000} -> 10.961799 | G7: {=(SUMPRODUCT(DCF!$D$9:$K$9, 1/(1+$A7)^DCF!$D$13:$K$13) + DCF!$K$8*G$5/(1+$A7)^DCF!$K$13)/1000} -> 11.843615 | H7: {=(SUMPRODUCT(DCF!$D$9:$K$9, 1/(1+$A7)^DCF!$D$13:$K$13) + DCF!$K$8*H$5/(1+$A7)^DCF!$K$13)/1000} -> 12.72543
A8: 0.1035 | B8: {=(SUMPRODUCT(DCF!$D$9:$K$9, 1/(1+$A8)^DCF!$D$13:$K$13) + DCF!$K$8*B$5/(1+$A8)^DCF!$K$13)/1000} -> 7.2098876 | C8: {=(SUMPRODUCT(DCF!$D$9:$K$9, 1/(1+$A8)^DCF!$D$13:$K$13) + DCF!$K$8*C$5/(1+$A8)^DCF!$K$13)/1000} -> 8.0621742 | D8: {=(SUMPRODUCT(DCF!$D$9:$K$9, 1/(1+$A8)^DCF!$D$13:$K$13) + DCF!$K$8*D$5/(1+$A8)^DCF!$K$13)/1000} -> 8.9144607 | E8: {=(SUMPRODUCT(DCF!$D$9:$K$9, 1/(1+$A8)^DCF!$D$13:$K$13) + DCF!$K$8*E$5/(1+$A8)^DCF!$K$13)/1000} -> 9.7667473 | F8: {=(SUMPRODUCT(DCF!$D$9:$K$9, 1/(1+$A8)^DCF!$D$13:$K$13) + DCF!$K$8*F$5/(1+$A8)^DCF!$K$13)/1000} -> 10.619034 | G8: {=(SUMPRODUCT(DCF!$D$9:$K$9, 1/(1+$A8)^DCF!$D$13:$K$13) + DCF!$K$8*G$5/(1+$A8)^DCF!$K$13)/1000} -> 11.47132 | H8: {=(SUMPRODUCT(DCF!$D$9:$K$9, 1/(1+$A8)^DCF!$D$13:$K$13) + DCF!$K$8*H$5/(1+$A8)^DCF!$K$13)/1000} -> 12.323607
A9: 0.1085 | B9: {=(SUMPRODUCT(DCF!$D$9:$K$9, 1/(1+$A9)^DCF!$D$13:$K$13) + DCF!$K$8*B$5/(1+$A9)^DCF!$K$13)/1000} -> 6.9933865 | C9: {=(SUMPRODUCT(DCF!$D$9:$K$9, 1/(1+$A9)^DCF!$D$13:$K$13) + DCF!$K$8*C$5/(1+$A9)^DCF!$K$13)/1000} -> 7.8172599 | D9: {=(SUMPRODUCT(DCF!$D$9:$K$9, 1/(1+$A9)^DCF!$D$13:$K$13) + DCF!$K$8*D$5/(1+$A9)^DCF!$K$13)/1000} -> 8.6411332 | E9: {=(SUMPRODUCT(DCF!$D$9:$K$9, 1/(1+$A9)^DCF!$D$13:$K$13) + DCF!$K$8*E$5/(1+$A9)^DCF!$K$13)/1000} -> 9.4650065 | F9: {=(SUMPRODUCT(DCF!$D$9:$K$9, 1/(1+$A9)^DCF!$D$13:$K$13) + DCF!$K$8*F$5/(1+$A9)^DCF!$K$13)/1000} -> 10.28888 | G9: {=(SUMPRODUCT(DCF!$D$9:$K$9, 1/(1+$A9)^DCF!$D$13:$K$13) + DCF!$K$8*G$5/(1+$A9)^DCF!$K$13)/1000} -> 11.112753 | H9: {=(SUMPRODUCT(DCF!$D$9:$K$9, 1/(1+$A9)^DCF!$D$13:$K$13) + DCF!$K$8*H$5/(1+$A9)^DCF!$K$13)/1000} -> 11.936627
A10: 0.1135 | B10: {=(SUMPRODUCT(DCF!$D$9:$K$9, 1/(1+$A10)^DCF!$D$13:$K$13) + DCF!$K$8*B$5/(1+$A10)^DCF!$K$13)/1000} -> 6.7846993 | C10: {=(SUMPRODUCT(DCF!$D$9:$K$9, 1/(1+$A10)^DCF!$D$13:$K$13) + DCF!$K$8*C$5/(1+$A10)^DCF!$K$13)/1000} -> 7.5812282 | D10: {=(SUMPRODUCT(DCF!$D$9:$K$9, 1/(1+$A10)^DCF!$D$13:$K$13) + DCF!$K$8*D$5/(1+$A10)^DCF!$K$13)/1000} -> 8.377757 | E10: {=(SUMPRODUCT(DCF!$D$9:$K$9, 1/(1+$A10)^DCF!$D$13:$K$13) + DCF!$K$8*E$5/(1+$A10)^DCF!$K$13)/1000} -> 9.1742859 | F10: {=(SUMPRODUCT(DCF!$D$9:$K$9, 1/(1+$A10)^DCF!$D$13:$K$13) + DCF!$K$8*F$5/(1+$A10)^DCF!$K$13)/1000} -> 9.9708148 | G10: {=(SUMPRODUCT(DCF!$D$9:$K$9, 1/(1+$A10)^DCF!$D$13:$K$13) + DCF!$K$8*G$5/(1+$A10)^DCF!$K$13)/1000} -> 10.767344 | H10: {=(SUMPRODUCT(DCF!$D$9:$K$9, 1/(1+$A10)^DCF!$D$13:$K$13) + DCF!$K$8*H$5/(1+$A10)^DCF!$K$13)/1000} -> 11.563872
A11: 0.1185 | B11: {=(SUMPRODUCT(DCF!$D$9:$K$9, 1/(1+$A11)^DCF!$D$13:$K$13) + DCF!$K$8*B$5/(1+$A11)^DCF!$K$13)/1000} -> 6.5835065 | C11: {=(SUMPRODUCT(DCF!$D$9:$K$9, 1/(1+$A11)^DCF!$D$13:$K$13) + DCF!$K$8*C$5/(1+$A11)^DCF!$K$13)/1000} -> 7.3537149 | D11: {=(SUMPRODUCT(DCF!$D$9:$K$9, 1/(1+$A11)^DCF!$D$13:$K$13) + DCF!$K$8*D$5/(1+$A11)^DCF!$K$13)/1000} -> 8.1239233 | E11: {=(SUMPRODUCT(DCF!$D$9:$K$9, 1/(1+$A11)^DCF!$D$13:$K$13) + DCF!$K$8*E$5/(1+$A11)^DCF!$K$13)/1000} -> 8.8941318 | F11: {=(SUMPRODUCT(DCF!$D$9:$K$9, 1/(1+$A11)^DCF!$D$13:$K$13) + DCF!$K$8*F$5/(1+$A11)^DCF!$K$13)/1000} -> 9.6643402 | G11: {=(SUMPRODUCT(DCF!$D$9:$K$9, 1/(1+$A11)^DCF!$D$13:$K$13) + DCF!$K$8*G$5/(1+$A11)^DCF!$K$13)/1000} -> 10.434549 | H11: {=(SUMPRODUCT(DCF!$D$9:$K$9, 1/(1+$A11)^DCF!$D$13:$K$13) + DCF!$K$8*H$5/(1+$A11)^DCF!$K$13)/1000} -> 11.204757
A12: 0.1235 | B12: {=(SUMPRODUCT(DCF!$D$9:$K$9, 1/(1+$A12)^DCF!$D$13:$K$13) + DCF!$K$8*B$5/(1+$A12)^DCF!$K$13)/1000} -> 6.3895032 | C12: {=(SUMPRODUCT(DCF!$D$9:$K$9, 1/(1+$A12)^DCF!$D$13:$K$13) + DCF!$K$8*C$5/(1+$A12)^DCF!$K$13)/1000} -> 7.1343725 | D12: {=(SUMPRODUCT(DCF!$D$9:$K$9, 1/(1+$A12)^DCF!$D$13:$K$13) + DCF!$K$8*D$5/(1+$A12)^DCF!$K$13)/1000} -> 7.8792419 | E12: {=(SUMPRODUCT(DCF!$D$9:$K$9, 1/(1+$A12)^DCF!$D$13:$K$13) + DCF!$K$8*E$5/(1+$A12)^DCF!$K$13)/1000} -> 8.6241112 | F12: {=(SUMPRODUCT(DCF!$D$9:$K$9, 1/(1+$A12)^DCF!$D$13:$K$13) + DCF!$K$8*F$5/(1+$A12)^DCF!$K$13)/1000} -> 9.3689806 | G12: {=(SUMPRODUCT(DCF!$D$9:$K$9, 1/(1+$A12)^DCF!$D$13:$K$13) + DCF!$K$8*G$5/(1+$A12)^DCF!$K$13)/1000} -> 10.11385 | H12: {=(SUMPRODUCT(DCF!$D$9:$K$9, 1/(1+$A12)^DCF!$D$13:$K$13) + DCF!$K$8*H$5/(1+$A12)^DCF!$K$13)/1000} -> 10.858719
A15: Grid 2: WACC × Terminal Growth (Gordon Method) → Enterprise Value ($B)
A16: WACC ↓ / Terminal Growth → | B16: 0.015 | C16: 0.02 | D16: 0.025 | E16: 0.03 | F16: 0.035 | G16: 0.04 | H16: 0.045
A17: 0.0935 | B17: {=(SUMPRODUCT(DCF!$D$9:$K$9, 1/(1+$A17)^DCF!$D$13:$K$13) + DCF!$K$9*(1+B$16)/($A17-B$16)/(1+$A17)^DCF!$K$13)/1000} -> 8.1965353 | C17: {=(SUMPRODUCT(DCF!$D$9:$K$9, 1/(1+$A17)^DCF!$D$13:$K$13) + DCF!$K$9*(1+C$16)/($A17-C$16)/(1+$A17)^DCF!$K$13)/1000} -> 8.6365521 | D17: {=(SUMPRODUCT(DCF!$D$9:$K$9, 1/(1+$A17)^DCF!$D$13:$K$13) + DCF!$K$9*(1+D$16)/($A17-D$16)/(1+$A17)^DCF!$K$13)/1000} -> 9.1408049 | E17: {=(SUMPRODUCT(DCF!$D$9:$K$9, 1/(1+$A17)^DCF!$D$13:$K$13) + DCF!$K$9*(1+E$16)/($A17-E$16)/(1+$A17)^DCF!$K$13)/1000} -> 9.7244675 | F17: {=(SUMPRODUCT(DCF!$D$9:$K$9, 1/(1+$A17)^DCF!$D$13:$K$13) + DCF!$K$9*(1+F$16)/($A17-F$16)/(1+$A17)^DCF!$K$13)/1000} -> 10.407902 | G17: {=(SUMPRODUCT(DCF!$D$9:$K$9, 1/(1+$A17)^DCF!$D$13:$K$13) + DCF!$K$9*(1+G$16)/($A17-G$16)/(1+$A17)^DCF!$K$13)/1000} -> 11.21908 | H17: {=(SUMPRODUCT(DCF!$D$9:$K$9, 1/(1+$A17)^DCF!$D$13:$K$13) + DCF!$K$9*(1+H$16)/($A17-H$16)/(1+$A17)^DCF!$K$13)/1000} -> 12.197512
A18: 0.0985 | B18: {=(SUMPRODUCT(DCF!$D$9:$K$9, 1/(1+$A18)^DCF!$D$13:$K$13) + DCF!$K$9*(1+B$16)/($A18-B$16)/(1+$A18)^DCF!$K$13)/1000} -> 7.5981755 | C18: {=(SUMPRODUCT(DCF!$D$9:$K$9, 1/(1+$A18)^DCF!$D$13:$K$13) + DCF!$K$9*(1+C$16)/($A18-C$16)/(1+$A18)^DCF!$K$13)/1000} -> 7.9741789 | D18: {=(SUMPRODUCT(DCF!$D$9:$K$9, 1/(1+$A18)^DCF!$D$13:$K$13) + DCF!$K$9*(1+D$16)/($A18-D$16)/(1+$A18)^DCF!$K$13)/1000} -> 8.4013393 | E18: {=(SUMPRODUCT(DCF!$D$9:$K$9, 1/(1+$A18)^DCF!$D$13:$K$13) + DCF!$K$9*(1+E$16)/($A18-E$16)/(1+$A18)^DCF!$K$13)/1000} -> 8.8908588 | F18: {=(SUMPRODUCT(DCF!$D$9:$K$9, 1/(1+$A18)^DCF!$D$13:$K$13) + DCF!$K$9*(1+F$16)/($A18-F$16)/(1+$A18)^DCF!$K$13)/1000} -> 9.457468 | G18: {=(SUMPRODUCT(DCF!$D$9:$K$9, 1/(1+$A18)^DCF!$D$13:$K$13) + DCF!$K$9*(1+G$16)/($A18-G$16)/(1+$A18)^DCF!$K$13)/1000} -> 10.120934 | H18: {=(SUMPRODUCT(DCF!$D$9:$K$9, 1/(1+$A18)^DCF!$D$13:$K$13) + DCF!$K$9*(1+H$16)/($A18-H$16)/(1+$A18)^DCF!$K$13)/1000} -> 10.908411
A19: 0.1035 | B19: {=(SUMPRODUCT(DCF!$D$9:$K$9, 1/(1+$A19)^DCF!$D$13:$K$13) + DCF!$K$9*(1+B$16)/($A19-B$16)/(1+$A19)^DCF!$K$13)/1000} -> 7.0702001 | C19: {=(SUMPRODUCT(DCF!$D$9:$K$9, 1/(1+$A19)^DCF!$D$13:$K$13) + DCF!$K$9*(1+C$16)/($A19-C$16)/(1+$A19)^DCF!$K$13)/1000} -> 7.3940161 | D19: {=(SUMPRODUCT(DCF!$D$9:$K$9, 1/(1+$A19)^DCF!$D$13:$K$13) + DCF!$K$9*(1+D$16)/($A19-D$16)/(1+$A19)^DCF!$K$13)/1000} -> 7.7590826 | E19: {=(SUMPRODUCT(DCF!$D$9:$K$9, 1/(1+$A19)^DCF!$D$13:$K$13) + DCF!$K$9*(1+E$16)/($A19-E$16)/(1+$A19)^DCF!$K$13)/1000} -> 8.1738181 | F19: {=(SUMPRODUCT(DCF!$D$9:$K$9, 1/(1+$A19)^DCF!$D$13:$K$13) + DCF!$K$9*(1+F$16)/($A19-F$16)/(1+$A19)^DCF!$K$13)/1000} -> 8.6490988 | G19: {=(SUMPRODUCT(DCF!$D$9:$K$9, 1/(1+$A19)^DCF!$D$13:$K$13) + DCF!$K$9*(1+G$16)/($A19-G$16)/(1+$A19)^DCF!$K$13)/1000} -> 9.1992269 | H19: {=(SUMPRODUCT(DCF!$D$9:$K$9, 1/(1+$A19)^DCF!$D$13:$K$13) + DCF!$K$9*(1+H$16)/($A19-H$16)/(1+$A19)^DCF!$K$13)/1000} -> 9.8433941
A20: 0.1085 | B20: {=(SUMPRODUCT(DCF!$D$9:$K$9, 1/(1+$A20)^DCF!$D$13:$K$13) + DCF!$K$9*(1+B$16)/($A20-B$16)/(1+$A20)^DCF!$K$13)/1000} -> 6.6012323 | C20: {=(SUMPRODUCT(DCF!$D$9:$K$9, 1/(1+$A20)^DCF!$D$13:$K$13) + DCF!$K$9*(1+C$16)/($A20-C$16)/(1+$A20)^DCF!$K$13)/1000} -> 6.8820416 | D20: {=(SUMPRODUCT(DCF!$D$9:$K$9, 1/(1+$A20)^DCF!$D$13:$K$13) + DCF!$K$9*(1+D$16)/($A20-D$16)/(1+$A20)^DCF!$K$13)/1000} -> 7.1964807 | E20: {=(SUMPRODUCT(DCF!$D$9:$K$9, 1/(1+$A20)^DCF!$D$13:$K$13) + DCF!$K$9*(1+E$16)/($A20-E$16)/(1+$A20)^DCF!$K$13)/1000} -> 7.5509758 | F20: {=(SUMPRODUCT(DCF!$D$9:$K$9, 1/(1+$A20)^DCF!$D$13:$K$13) + DCF!$K$9*(1+F$16)/($A20-F$16)/(1+$A20)^DCF!$K$13)/1000} -> 7.9537014 | G20: {=(SUMPRODUCT(DCF!$D$9:$K$9, 1/(1+$A20)^DCF!$D$13:$K$13) + DCF!$K$9*(1+G$16)/($A20-G$16)/(1+$A20)^DCF!$K$13)/1000} -> 8.4152191 | H20: {=(SUMPRODUCT(DCF!$D$9:$K$9, 1/(1+$A20)^DCF!$D$13:$K$13) + DCF!$K$9*(1+H$16)/($A20-H$16)/(1+$A20)^DCF!$K$13)/1000} -> 8.9494168
A21: 0.1135 | B21: {=(SUMPRODUCT(DCF!$D$9:$K$9, 1/(1+$A21)^DCF!$D$13:$K$13) + DCF!$K$9*(1+B$16)/($A21-B$16)/(1+$A21)^DCF!$K$13)/1000} -> 6.1822087 | C21: {=(SUMPRODUCT(DCF!$D$9:$K$9, 1/(1+$A21)^DCF!$D$13:$K$13) + DCF!$K$9*(1+C$16)/($A21-C$16)/(1+$A21)^DCF!$K$13)/1000} -> 6.4272358 | D21: {=(SUMPRODUCT(DCF!$D$9:$K$9, 1/(1+$A21)^DCF!$D$13:$K$13) + DCF!$K$9*(1+D$16)/($A21-D$16)/(1+$A21)^DCF!$K$13)/1000} -> 6.6999495 | E21: {=(SUMPRODUCT(DCF!$D$9:$K$9, 1/(1+$A21)^DCF!$D$13:$K$13) + DCF!$K$9*(1+E$16)/($A21-E$16)/(1+$A21)^DCF!$K$13)/1000} -> 7.0053236 | F21: {=(SUMPRODUCT(DCF!$D$9:$K$9, 1/(1+$A21)^DCF!$D$13:$K$13) + DCF!$K$9*(1+F$16)/($A21-F$16)/(1+$A21)^DCF!$K$13)/1000} -> 7.3495988 | G21: {=(SUMPRODUCT(DCF!$D$9:$K$9, 1/(1+$A21)^DCF!$D$13:$K$13) + DCF!$K$9*(1+G$16)/($A21-G$16)/(1+$A21)^DCF!$K$13)/1000} -> 7.7407142 | H21: {=(SUMPRODUCT(DCF!$D$9:$K$9, 1/(1+$A21)^DCF!$D$13:$K$13) + DCF!$K$9*(1+H$16)/($A21-H$16)/(1+$A21)^DCF!$K$13)/1000} -> 8.1889267
A22: 0.1185 | B22: {=(SUMPRODUCT(DCF!$D$9:$K$9, 1/(1+$A22)^DCF!$D$13:$K$13) + DCF!$K$9*(1+B$16)/($A22-B$16)/(1+$A22)^DCF!$K$13)/1000} -> 5.8058198 | C22: {=(SUMPRODUCT(DCF!$D$9:$K$9, 1/(1+$A22)^DCF!$D$13:$K$13) + DCF!$K$9*(1+C$16)/($A22-C$16)/(1+$A22)^DCF!$K$13)/1000} -> 6.0208195 | D22: {=(SUMPRODUCT(DCF!$D$9:$K$9, 1/(1+$A22)^DCF!$D$13:$K$13) + DCF!$K$9*(1+D$16)/($A22-D$16)/(1+$A22)^DCF!$K$13)/1000} -> 6.2588138 | E22: {=(SUMPRODUCT(DCF!$D$9:$K$9, 1/(1+$A22)^DCF!$D$13:$K$13) + DCF!$K$9*(1+E$16)/($A22-E$16)/(1+$A22)^DCF!$K$13)/1000} -> 6.5237001 | F22: {=(SUMPRODUCT(DCF!$D$9:$K$9, 1/(1+$A22)^DCF!$D$13:$K$13) + DCF!$K$9*(1+F$16)/($A22-F$16)/(1+$A22)^DCF!$K$13)/1000} -> 6.8203094 | G22: {=(SUMPRODUCT(DCF!$D$9:$K$9, 1/(1+$A22)^DCF!$D$13:$K$13) + DCF!$K$9*(1+G$16)/($A22-G$16)/(1+$A22)^DCF!$K$13)/1000} -> 7.1547032 | H22: {=(SUMPRODUCT(DCF!$D$9:$K$9, 1/(1+$A22)^DCF!$D$13:$K$13) + DCF!$K$9*(1+H$16)/($A22-H$16)/(1+$A22)^DCF!$K$13)/1000} -> 7.5345928
A23: 0.1235 | B23: {=(SUMPRODUCT(DCF!$D$9:$K$9, 1/(1+$A23)^DCF!$D$13:$K$13) + DCF!$K$9*(1+B$16)/($A23-B$16)/(1+$A23)^DCF!$K$13)/1000} -> 5.466106 | C23: {=(SUMPRODUCT(DCF!$D$9:$K$9, 1/(1+$A23)^DCF!$D$13:$K$13) + DCF!$K$9*(1+C$16)/($A23-C$16)/(1+$A23)^DCF!$K$13)/1000} -> 5.6557125 | D23: {=(SUMPRODUCT(DCF!$D$9:$K$9, 1/(1+$A23)^DCF!$D$13:$K$13) + DCF!$K$9*(1+D$16)/($A23-D$16)/(1+$A23)^DCF!$K$13)/1000} -> 5.8645684 | E23: {=(SUMPRODUCT(DCF!$D$9:$K$9, 1/(1+$A23)^DCF!$D$13:$K$13) + DCF!$K$9*(1+E$16)/($A23-E$16)/(1+$A23)^DCF!$K$13)/1000} -> 6.0957619 | F23: {=(SUMPRODUCT(DCF!$D$9:$K$9, 1/(1+$A23)^DCF!$D$13:$K$13) + DCF!$K$9*(1+F$16)/($A23-F$16)/(1+$A23)^DCF!$K$13)/1000} -> 6.3530789 | G23: {=(SUMPRODUCT(DCF!$D$9:$K$9, 1/(1+$A23)^DCF!$D$13:$K$13) + DCF!$K$9*(1+G$16)/($A23-G$16)/(1+$A23)^DCF!$K$13)/1000} -> 6.6412122 | H23: {=(SUMPRODUCT(DCF!$D$9:$K$9, 1/(1+$A23)^DCF!$D$13:$K$13) + DCF!$K$9*(1+H$16)/($A23-H$16)/(1+$A23)^DCF!$K$13)/1000} -> 6.9660505
A26: Grid 3: Beta × CSRP → Resulting WACC (per methodology Sec 8)
A27: Beta ↓ / CSRP → | B27: 0.01 | C27: 0.015 | D27: 0.02 | E27: 0.025 | F27: 0.03
A28: 0.7 | B28: =Assumptions!$F$69 + Assumptions!$F$70*$A28 + Assumptions!$F$72 + B$27 -> 0.0926 | C28: =Assumptions!$F$69 + Assumptions!$F$70*$A28 + Assumptions!$F$72 + C$27 -> 0.0976 | D28: =Assumptions!$F$69 + Assumptions!$F$70*$A28 + Assumptions!$F$72 + D$27 -> 0.1026 | E28: =Assumptions!$F$69 + Assumptions!$F$70*$A28 + Assumptions!$F$72 + E$27 -> 0.1076 | F28: =Assumptions!$F$69 + Assumptions!$F$70*$A28 + Assumptions!$F$72 + F$27 -> 0.1126
A29: 0.83 | B29: =Assumptions!$F$69 + Assumptions!$F$70*$A29 + Assumptions!$F$72 + B$27 -> 0.09845 | C29: =Assumptions!$F$69 + Assumptions!$F$70*$A29 + Assumptions!$F$72 + C$27 -> 0.10345 | D29: =Assumptions!$F$69 + Assumptions!$F$70*$A29 + Assumptions!$F$72 + D$27 -> 0.10845 | E29: =Assumptions!$F$69 + Assumptions!$F$70*$A29 + Assumptions!$F$72 + E$27 -> 0.11345 | F29: =Assumptions!$F$69 + Assumptions!$F$70*$A29 + Assumptions!$F$72 + F$27 -> 0.11845
A30: 1 | B30: =Assumptions!$F$69 + Assumptions!$F$70*$A30 + Assumptions!$F$72 + B$27 -> 0.1061 | C30: =Assumptions!$F$69 + Assumptions!$F$70*$A30 + Assumptions!$F$72 + C$27 -> 0.1111 | D30: =Assumptions!$F$69 + Assumptions!$F$70*$A30 + Assumptions!$F$72 + D$27 -> 0.1161 | E30: =Assumptions!$F$69 + Assumptions!$F$70*$A30 + Assumptions!$F$72 + E$27 -> 0.1211 | F30: =Assumptions!$F$69 + Assumptions!$F$70*$A30 + Assumptions!$F$72 + F$27 -> 0.1261
A31: 1.2 | B31: =Assumptions!$F$69 + Assumptions!$F$70*$A31 + Assumptions!$F$72 + B$27 -> 0.1151 | C31: =Assumptions!$F$69 + Assumptions!$F$70*$A31 + Assumptions!$F$72 + C$27 -> 0.1201 | D31: =Assumptions!$F$69 + Assumptions!$F$70*$A31 + Assumptions!$F$72 + D$27 -> 0.1251 | E31: =Assumptions!$F$69 + Assumptions!$F$70*$A31 + Assumptions!$F$72 + E$27 -> 0.1301 | F31: =Assumptions!$F$69 + Assumptions!$F$70*$A31 + Assumptions!$F$72 + F$27 -> 0.1351
A32: 1.4 | B32: =Assumptions!$F$69 + Assumptions!$F$70*$A32 + Assumptions!$F$72 + B$27 -> 0.1241 | C32: =Assumptions!$F$69 + Assumptions!$F$70*$A32 + Assumptions!$F$72 + C$27 -> 0.1291 | D32: =Assumptions!$F$69 + Assumptions!$F$70*$A32 + Assumptions!$F$72 + D$27 -> 0.1341 | E32: =Assumptions!$F$69 + Assumptions!$F$70*$A32 + Assumptions!$F$72 + E$27 -> 0.1391 | F32: =Assumptions!$F$69 + Assumptions!$F$70*$A32 + Assumptions!$F$72 + F$27 -> 0.1441
A34: Grid 3b: Same Beta × CSRP applied to DCF → EV ($B) at base 4.5x exit
A35: Beta ↓ / CSRP → | B35: 0.01 | C35: 0.015 | D35: 0.02 | E35: 0.025 | F35: 0.03
A36: 0.7 | B36: {=(SUMPRODUCT(DCF!$D$9:$K$9, 1/(1+(Assumptions!$F$69+Assumptions!$F$70*$A36+Assumptions!$F$72+B$35))^DCF!$D$13:$K$13) + DCF!$K$8*Assumptions!$F$78/(1+(Assumptions!$F$69+Assumptions!$F$70*$A36+Assumptions!$F$72+B$35))^DCF!$K$13)/1000} -> 10.465069 | C36: {=(SUMPRODUCT(DCF!$D$9:$K$9, 1/(1+(Assumptions!$F$69+Assumptions!$F$70*$A36+Assumptions!$F$72+C$35))^DCF!$D$13:$K$13) + DCF!$K$8*Assumptions!$F$78/(1+(Assumptions!$F$69+Assumptions!$F$70*$A36+Assumptions!$F$72+C$35))^DCF!$K$13)/1000} -> 10.137625 | D36: {=(SUMPRODUCT(DCF!$D$9:$K$9, 1/(1+(Assumptions!$F$69+Assumptions!$F$70*$A36+Assumptions!$F$72+D$35))^DCF!$D$13:$K$13) + DCF!$K$8*Assumptions!$F$78/(1+(Assumptions!$F$69+Assumptions!$F$70*$A36+Assumptions!$F$72+D$35))^DCF!$K$13)/1000} -> 9.8222673 | E36: {=(SUMPRODUCT(DCF!$D$9:$K$9, 1/(1+(Assumptions!$F$69+Assumptions!$F$70*$A36+Assumptions!$F$72+E$35))^DCF!$D$13:$K$13) + DCF!$K$8*Assumptions!$F$78/(1+(Assumptions!$F$69+Assumptions!$F$70*$A36+Assumptions!$F$72+E$35))^DCF!$K$13)/1000} -> 9.5184931 | F36: {=(SUMPRODUCT(DCF!$D$9:$K$9, 1/(1+(Assumptions!$F$69+Assumptions!$F$70*$A36+Assumptions!$F$72+F$35))^DCF!$D$13:$K$13) + DCF!$K$8*Assumptions!$F$78/(1+(Assumptions!$F$69+Assumptions!$F$70*$A36+Assumptions!$F$72+F$35))^DCF!$K$13)/1000} -> 9.2258229
A37: 0.83 | B37: {=(SUMPRODUCT(DCF!$D$9:$K$9, 1/(1+(Assumptions!$F$69+Assumptions!$F$70*$A37+Assumptions!$F$72+B$35))^DCF!$D$13:$K$13) + DCF!$K$8*Assumptions!$F$78/(1+(Assumptions!$F$69+Assumptions!$F$70*$A37+Assumptions!$F$72+B$35))^DCF!$K$13)/1000} -> 10.083176 | C37: {=(SUMPRODUCT(DCF!$D$9:$K$9, 1/(1+(Assumptions!$F$69+Assumptions!$F$70*$A37+Assumptions!$F$72+C$35))^DCF!$D$13:$K$13) + DCF!$K$8*Assumptions!$F$78/(1+(Assumptions!$F$69+Assumptions!$F$70*$A37+Assumptions!$F$72+C$35))^DCF!$K$13)/1000} -> 9.769822 | D37: {=(SUMPRODUCT(DCF!$D$9:$K$9, 1/(1+(Assumptions!$F$69+Assumptions!$F$70*$A37+Assumptions!$F$72+D$35))^DCF!$D$13:$K$13) + DCF!$K$8*Assumptions!$F$78/(1+(Assumptions!$F$69+Assumptions!$F$70*$A37+Assumptions!$F$72+D$35))^DCF!$K$13)/1000} -> 9.4679686 | E37: {=(SUMPRODUCT(DCF!$D$9:$K$9, 1/(1+(Assumptions!$F$69+Assumptions!$F$70*$A37+Assumptions!$F$72+E$35))^DCF!$D$13:$K$13) + DCF!$K$8*Assumptions!$F$78/(1+(Assumptions!$F$69+Assumptions!$F$70*$A37+Assumptions!$F$72+E$35))^DCF!$K$13)/1000} -> 9.17714 | F37: {=(SUMPRODUCT(DCF!$D$9:$K$9, 1/(1+(Assumptions!$F$69+Assumptions!$F$70*$A37+Assumptions!$F$72+F$35))^DCF!$D$13:$K$13) + DCF!$K$8*Assumptions!$F$78/(1+(Assumptions!$F$69+Assumptions!$F$70*$A37+Assumptions!$F$72+F$35))^DCF!$K$13)/1000} -> 8.8968824
A38: 1 | B38: {=(SUMPRODUCT(DCF!$D$9:$K$9, 1/(1+(Assumptions!$F$69+Assumptions!$F$70*$A38+Assumptions!$F$72+B$35))^DCF!$D$13:$K$13) + DCF!$K$8*Assumptions!$F$78/(1+(Assumptions!$F$69+Assumptions!$F$70*$A38+Assumptions!$F$72+B$35))^DCF!$K$13)/1000} -> 9.6084381 | C38: {=(SUMPRODUCT(DCF!$D$9:$K$9, 1/(1+(Assumptions!$F$69+Assumptions!$F$70*$A38+Assumptions!$F$72+C$35))^DCF!$D$13:$K$13) + DCF!$K$8*Assumptions!$F$78/(1+(Assumptions!$F$69+Assumptions!$F$70*$A38+Assumptions!$F$72+C$35))^DCF!$K$13)/1000} -> 9.3124857 | D38: {=(SUMPRODUCT(DCF!$D$9:$K$9, 1/(1+(Assumptions!$F$69+Assumptions!$F$70*$A38+Assumptions!$F$72+D$35))^DCF!$D$13:$K$13) + DCF!$K$8*Assumptions!$F$78/(1+(Assumptions!$F$69+Assumptions!$F$70*$A38+Assumptions!$F$72+D$35))^DCF!$K$13)/1000} -> 9.0273149 | E38: {=(SUMPRODUCT(DCF!$D$9:$K$9, 1/(1+(Assumptions!$F$69+Assumptions!$F$70*$A38+Assumptions!$F$72+E$35))^DCF!$D$13:$K$13) + DCF!$K$8*Assumptions!$F$78/(1+(Assumptions!$F$69+Assumptions!$F$70*$A38+Assumptions!$F$72+E$35))^DCF!$K$13)/1000} -> 8.752483 | F38: {=(SUMPRODUCT(DCF!$D$9:$K$9, 1/(1+(Assumptions!$F$69+Assumptions!$F$70*$A38+Assumptions!$F$72+F$35))^DCF!$D$13:$K$13) + DCF!$K$8*Assumptions!$F$78/(1+(Assumptions!$F$69+Assumptions!$F$70*$A38+Assumptions!$F$72+F$35))^DCF!$K$13)/1000} -> 8.4875674
A39: 1.2 | B39: {=(SUMPRODUCT(DCF!$D$9:$K$9, 1/(1+(Assumptions!$F$69+Assumptions!$F$70*$A39+Assumptions!$F$72+B$35))^DCF!$D$13:$K$13) + DCF!$K$8*Assumptions!$F$78/(1+(Assumptions!$F$69+Assumptions!$F$70*$A39+Assumptions!$F$72+B$35))^DCF!$K$13)/1000} -> 9.0835081 | C39: {=(SUMPRODUCT(DCF!$D$9:$K$9, 1/(1+(Assumptions!$F$69+Assumptions!$F$70*$A39+Assumptions!$F$72+C$35))^DCF!$D$13:$K$13) + DCF!$K$8*Assumptions!$F$78/(1+(Assumptions!$F$69+Assumptions!$F$70*$A39+Assumptions!$F$72+C$35))^DCF!$K$13)/1000} -> 8.8066428 | D39: {=(SUMPRODUCT(DCF!$D$9:$K$9, 1/(1+(Assumptions!$F$69+Assumptions!$F$70*$A39+Assumptions!$F$72+D$35))^DCF!$D$13:$K$13) + DCF!$K$8*Assumptions!$F$78/(1+(Assumptions!$F$69+Assumptions!$F$70*$A39+Assumptions!$F$72+D$35))^DCF!$K$13)/1000} -> 8.5397768 | E39: {=(SUMPRODUCT(DCF!$D$9:$K$9, 1/(1+(Assumptions!$F$69+Assumptions!$F$70*$A39+Assumptions!$F$72+E$35))^DCF!$D$13:$K$13) + DCF!$K$8*Assumptions!$F$78/(1+(Assumptions!$F$69+Assumptions!$F$70*$A39+Assumptions!$F$72+E$35))^DCF!$K$13)/1000} -> 8.2825029 | F39: {=(SUMPRODUCT(DCF!$D$9:$K$9, 1/(1+(Assumptions!$F$69+Assumptions!$F$70*$A39+Assumptions!$F$72+F$35))^DCF!$D$13:$K$13) + DCF!$K$8*Assumptions!$F$78/(1+(Assumptions!$F$69+Assumptions!$F$70*$A39+Assumptions!$F$72+F$35))^DCF!$K$13)/1000} -> 8.0344321
A40: 1.4 | B40: {=(SUMPRODUCT(DCF!$D$9:$K$9, 1/(1+(Assumptions!$F$69+Assumptions!$F$70*$A40+Assumptions!$F$72+B$35))^DCF!$D$13:$K$13) + DCF!$K$8*Assumptions!$F$78/(1+(Assumptions!$F$69+Assumptions!$F$70*$A40+Assumptions!$F$72+B$35))^DCF!$K$13)/1000} -> 8.5923699 | C40: {=(SUMPRODUCT(DCF!$D$9:$K$9, 1/(1+(Assumptions!$F$69+Assumptions!$F$70*$A40+Assumptions!$F$72+C$35))^DCF!$D$13:$K$13) + DCF!$K$8*Assumptions!$F$78/(1+(Assumptions!$F$69+Assumptions!$F$70*$A40+Assumptions!$F$72+C$35))^DCF!$K$13)/1000} -> 8.3332092 | D40: {=(SUMPRODUCT(DCF!$D$9:$K$9, 1/(1+(Assumptions!$F$69+Assumptions!$F$70*$A40+Assumptions!$F$72+D$35))^DCF!$D$13:$K$13) + DCF!$K$8*Assumptions!$F$78/(1+(Assumptions!$F$69+Assumptions!$F$70*$A40+Assumptions!$F$72+D$35))^DCF!$K$13)/1000} -> 8.0833281 | E40: {=(SUMPRODUCT(DCF!$D$9:$K$9, 1/(1+(Assumptions!$F$69+Assumptions!$F$70*$A40+Assumptions!$F$72+E$35))^DCF!$D$13:$K$13) + DCF!$K$8*Assumptions!$F$78/(1+(Assumptions!$F$69+Assumptions!$F$70*$A40+Assumptions!$F$72+E$35))^DCF!$K$13)/1000} -> 7.8423516 | F40: {=(SUMPRODUCT(DCF!$D$9:$K$9, 1/(1+(Assumptions!$F$69+Assumptions!$F$70*$A40+Assumptions!$F$72+F$35))^DCF!$D$13:$K$13) + DCF!$K$8*Assumptions!$F$78/(1+(Assumptions!$F$69+Assumptions!$F$70*$A40+Assumptions!$F$72+F$35))^DCF!$K$13)/1000} -> 7.6099217
A42: Summary — Equity Value per Share Range
A43: Method | B43: Low EV ($B) | C43: Base EV ($B) | D43: High EV ($B) | E43: Per Share Range ($)
A44: Grid 1: WACC × Exit Multiple | B44: =MIN(B6:H12) -> 6.3895032 | C44: =E9 -> 9.4650065 | D44: =MAX(B6:H12) -> 13.142741 | E44: =ROUND((B44*1000-Assumptions!$F$62+Assumptions!$F$63)/Assumptions!$F$55,1) & " — " & ROUND((D44*1000-Assumptions!$F$62+Assumptions!$F$63)/Assumptions!$F$55,1) -> 17.3 — 33.7
A45: Grid 2: WACC × Terminal Growth (Gordon) | B45: =MIN(B17:H23) -> 5.466106 | C45: =E20 -> 7.5509758 | D45: =MAX(B17:H23) -> 12.197512 | E45: =ROUND((B45*1000-Assumptions!$F$62+Assumptions!$F$63)/Assumptions!$F$55,1) & " — " & ROUND((D45*1000-Assumptions!$F$62+Assumptions!$F$63)/Assumptions!$F$55,1) -> 15 — 31.4
A46: Grid 3b: Beta × CSRP → EV | B46: =MIN(B36:F40) -> 7.6099217 | C46: =D37 -> 9.4679686 | D46: =MAX(B36:F40) -> 10.465069 | E46: =ROUND((B46*1000-Assumptions!$F$62+Assumptions!$F$63)/Assumptions!$F$55,1) & " — " & ROUND((D46*1000-Assumptions!$F$62+Assumptions!$F$63)/Assumptions!$F$55,1) -> 20.2 — 27.2
A48: Series G mark $10.1B = $24.63 implied per share. Base DCF base case = $24.95 (-1.3% premium).

Sheet Checks
A1: WHOOP — Diagnostic Checks
A2: Automated integrity checks per methodology Sec 9. ANY red FAIL must be resolved before output is trusted.
A4: Check | B4: Computed | C4: Threshold | D4: Status | E4: Notes
A5: 1. Members × ARPU ≈ Revenue (2025) | B5: =ABS(Members!D35*ARPU!D35/'Revenue Build'!D20-1) -> 0 | C5: <5% | D5: =IF(B5<0.05,"PASS","FAIL") -> PASS | E5: Avg members × blended ARPU should reconcile to consumer revenue
A6: 2. S&M coverage: Members.S&M$ ≤ P&L.S&M (2026) | B6: =ABS('P&L'!E23-Members!E47) -> 0 | C6: <$1M | D6: =IF(B6<1,"PASS","FAIL") -> PASS | E6: P&L S&M = Members.row 46 (single source); should match exactly
A7: 3. Comp bucket weights sum = 100% | B7: =Assumptions!$F$87 -> 1 | C7: =100% | D7: =IF(ABS(B7-1)<0.001,"PASS","FAIL") -> PASS | E7: B1+B2+B3 weights must total 1.0
A8: 4. TV < 75% of total EV (DCF) | B8: =DCF!C34 -> 0.78341714 | C8: <75% | D8: =IF(B8<0.75,"PASS",IF(B8<0.8,"WARN","FAIL")) -> WARN | E8: Methodology Sec 4: TV >75% means explicit forecast doing too little
A9: 5. Exit Multiple ↔ Gordon TV divergence | B9: =DCF!C31 -> 0.2957653 | C9: <25% | D9: =IF(B9<0.25,"PASS",IF(B9<0.35,"WARN","FAIL")) -> WARN | E9: Methodology Sec 4: divergence >25% means assumption inconsistency
A10: 6. Real options probability sum = 100% | B10: =RealOptions!D8 -> 1 | C10: =100% | D10: =IF(ABS(B10-1)<0.001,"PASS","FAIL") -> PASS | E10: Cluster probabilities (success/mixed/failure) must sum to 1.0
A11: 7. WACC > Perpetuity growth (Gordon validity) | B11: =Assumptions!$F$74-Assumptions!$F$80 -> 0.07845 | C11: >0% | D11: =IF(B11>0,"PASS","FAIL") -> PASS | E11: Required for Gordon Growth perpetuity to converge; safer if >3pp
A12: 8. Gross adds vs historical peak (any year) | B12: =MAX(Members!E31:L31)/Members!D31 -> 1.3062212 | C12: <2.0x | D12: =IF(B12<2,"PASS",IF(B12<3,"WARN","FAIL")) -> PASS | E12: Methodology Sec 9: peak gross adds shouldn't exceed 2x base year
A13: 9. Rule of 40 ≥ 20 by Phase 3 | B13: =MIN(FCF!J22:L22) -> 39.831633 | C13: ≥20 | D13: =IF(B13>=20,"PASS","FAIL") -> PASS | E13: Min Rule of 40 across 2031-2033 forecast
A15: Summary
A16: Total checks | B16: =COUNTA(D5:D13) -> 9
A17: Passing | B17: =COUNTIF(D5:D13,"PASS") -> 7
A18: Warning | B18: =COUNTIF(D5:D13,"WARN") -> 2
A19: Failing | B19: =COUNTIF(D5:D13,"FAIL") -> 0
A20: Overall | B20: =IF(B19>0,"FAIL",IF(B18>0,"WARN","PASS")) -> WARN

Sheet Sources
A1: Research File Index
A3: File | B3: Contents | C3: Session
A4: research/whoop-research-brief.md | B4: Structured research brief | C4: S0
A5: research/whoop-pitchbook-data.md | B5: Pitchbook: cap table, funding, financials | C5: S1
A6: research/whoop-capiq-data.md | B6: Cap IQ: dilution waterfall, investors | C6: S1
A7: research/oura-pitchbook-data.md | B7: Oura private comp profile ($11B) | C7: S1
A8: research/peloton-10k-analysis.md | B8: Peloton deep dive (revenue, margins, subs) | C8: S1
A9: research/web-research-sweep.md | B9: Market data, Forge, Garmin, Strava | C9: S1
A10: research/revenue-bookings-reconciliation.md | B10: $1.1B bookings vs revenue, ARPU, churn grids | C10: S1
A11: research/investor-deep-research.md | B11: Series G investor analysis | C11: S1
A12: research/stress-test-international-revenue.md | B12: 60% intl claim verification | C12: S1
A13: research/stress-test-revenue-reconciliation.md | B13: Revenue stress test (base: $650M) | C13: S1
A14: research/comp-dexcom-dxcm.md | B14: Dexcom 10-K (5yr financials) | C14: S2
... A26: research/precedent-transactions.md | B26: 14 deals, 3-bucket M&A analysis | C26: S2
A28: Web Sources (this build)
A29: Source | B29: Used For | C29: URL / Reference | D29: Date Accessed
A30: BusinessWire (WHOOP press release) | B30: Advanced Labs pricing: $199/$349/$599 (1/2/4 tests/yr); 350K waitlist on launch | C30: businesswire.com/news/home/20250930178710/ | D30: Sept 30, 2025 launch
A31: Boston Globe | B31: Women's blood test add-on $299; 150% YoY women membership growth; staff +75% | C31: bostonglobe.com/2026/03/10/business/whoop-299-blood-testing-service-women/ | D31: 46092
A32: WHOOP Membership page | B32: Tier pricing: One ~$199, Peak ~$239-279, Life ~$359; BP & Healthspan bundled in Peak/Life | C32: whoop.com/us/en/membership/ | D32: 46113
A33: WHOOP BP Insights page | B33: BP Insights bundled in Peak & Life (NOT separate paid feature) | C33: whoop.com/us/en/thelocker/blood-pressure-insights/ | D33: 46113
A34: Bloomberg | B34: May 2025 hardware launch: WHOOP 5.0 + WHOOP MG (medical grade); subscription from $199 | C34: bloomberg.com/news/features/2025-05-08/review-whoop-5-0-whoop-mg | D34: 45785
A35: TechCrunch | B35: Function Health $500/yr quarterly (comp price point); Fountain Life $20K/yr | C35: techcrunch.com/2025/09/30/whoop-opens-its-blood-testing-service/ | D35: 45930

Sheet CalibrationLog
A1: WHOOP Valuation — Calibration & Open Items Log
A2: Items deferred for next session. Each is non-blocking but should be addressed before relying on numbers for IC/memo. Sorted by priority.
A4: Tab | B4: Cell / Area | C4: Issue | D4: Suggested fix | E4: Priority | F4: Status
A5: DCF | B5: C30 | C5: TV divergence 55% (Exit Mult $16.1B vs Gordon $9.1B); methodology threshold 25% | D5: Lower exit mult to ~3.0x for Gordon equivalence, OR accept divergence as bull bias on terminal multiple compression | E5: High | F5: Open
A6: DCF | B6: C33 | C6: TV is 85% of total EV; methodology threshold 75%; explicit forecast doing only 15% of work | D6: Tighten R&D/G&A tapers (raises FCF in forecast period), OR extend horizon from 8 to 10 years | E6: High | F6: Open
A7: P&L | B7: L31 | C7: Margin tapers calibrated against bucket-3 peer benchmarks. R&D scenarios spread (Bear 12% / Base 15% / Bull 18%) reflect platform thesis. G&A 13/11/9 per Dexcom/ResMed anchors. SBC restructured: now interpolates from F47 (current) to F48 (terminal), 14%→8% Base. Terminal EBITDA: 36% → 33%. | D7: DONE — Assumptions C40/D40/E40 (R&D), C46/D46/E46 (G&A), C47-E47 (SBC current), C48-E48 (SBC terminal, NEW row inserted). P&L row 26 SBC formula updated to interpolate. | E7: Done | F7: RESOLVED
A8: P&L | B8: D38 | C8: Interest income wired — prior-yr cash × yield (Assumptions F66, 3.5% base). 2026-2033 NI uplift ~$300M cumulative. Non-circular: does NOT flow into UFCF. | D8: DONE — P&L D38:L38 wired to WC & Cash row 32 × Assumptions F66 | E8: Done | F8: RESOLVED
A9: P&L | B9: F31 | C9: 2027 EBITDA margin dips 22→12% from gross adds bulge (1.24M units → hardware COGS spike) | D9: Smooth Members E50:F50 to even gross adds across Phase 1, OR accept as Phase 1 deployment shape | E9: Medium | F9: Open
A10: P&L | B10: L23 | C10: S&M as % current revenue runs 16-20% vs methodology stated 30% | D10: Architecture-driven gap from prior-yr-rev basis. Either restate methodology, OR raise Members S&M phase % inputs | E10: Medium | F10: Open
A11: P&L | B11: D40 | C11: NOL carryforward wired — P&L rows 44-48. Begin/Add/Util/End schedule with 80% TCJA utilization cap. Self-balancing: any future losses auto-flow to NOL pool. | D11: DONE — P&L D40:L40 tax formula updated to MAX(0, Pretax − NOL_Util) × 23%. 2026/2027 NI uplift modest (~$14M, $7M) at current pretax. | E11: Done | F11: RESOLVED
A12: Revenue Build | B12: Row 19 | C12: $528M 2025 revenue vs $650M methodology target; gap is Unite B2B + Coach | D12: Add Unite B2B as separate revenue line on Revenue Build (Path C). $80-120M anchor. | E12: Medium | F12: Open
A13: ARPU | B13: D34 | C13: Derived ARPU $278 vs methodology anchor $338 (-17.7% gap) | D13: Largely resolved by Unite B2B path above. Revisit anchor language in methodology after. | E13: Low | F13: Linked
A14: FCF | B14: L17 | C14: FCF margin 19% in 2033, ~5pp below methodology terminal prior of 25-28% | D14: Will resolve when EBITDA tapers tightened (linked to L31). Or lower CapEx % from 4% to 3%. | E14: Low | F14: Linked
A16: Open Tabs / Builds Pending
A17: Balance Sheet | C17: Not yet built. Unlocks interest income wiring, NWC validation, cash build through forecast. | E17: Next
A18: Sensitivity | C18: Three grids built and live: WACC × Exit Mult, WACC × Terminal Growth (Gordon), Beta × CSRP → EV. Per-share range $14.8-33.7 across method combinations. | E18: Done | F18: RESOLVED
A19: Football Field | C19: Multi-method synthesis live with chart visualization. 5 methods wired to live sources. Weighted avg $8.6B / $22.75 per share, ~14.5% below Series G. Range bar chart added at A29 helper table; Series G $10.1B reference line overlay. Methods range $4.4B (forward comps) to $14.0B (IPO range). | D19: DONE — Football Field tab fully wired. All cells formula-driven from DCF / Sensitivity / Comps / Assumptions / RealOptions. | E19: Done | F19: RESOLVED
A20: Comps | C20: Three-bucket framework wired. Per-comp data placeholder (verify vs SEC/Bloomberg). Bucket summary stats (median + range), implied valuation table by scenario, dual back-solve (naive vs growth-adjusted) all live. Implied EVs: Bear $4.7B, Base $5.4B, Bull $6.3B vs Series G $10.1B. | D20: DONE — Comps tab fully wired. Data placeholder; refresh with current trading multiples before relying on output. | E20: Done | F20: WIRED (data needs refresh)
A21: Precedents | C21: Tab exists; needs deals populated per Assumptions Sec 8. | E21: Later
A22: ΔNWC | B22: FCF row 15 | C22: FCF tab now uses detailed WC schedule (was 8% plug). DCF EV +$813M to $9.54B; per share +$1.98 to $24.95. | D22: DONE — FCF!D15:L15 wired to 'WC & Cash'!D25:L25 | E22: High | F22: RESOLVED
A23: Framing | B23: Cover B56:B58, DCF A55 | C23: Discussed and decided: bucket-3 weight is expressed via 4.5x exit multiple (50% compressed from B3 ~9x), NOT via P&L margin compression. Base case 33% terminal EBITDA reflects WHOOP's natural subscription economics if executed. Real options carry the bucket-3-becoming-true upside as separate value source. No double-counting risk verified. | D23: DONE — Framing documented on Cover B56:B58 and DCF A55. Base case held; options held. No further OpEx changes. | E23: Done | F23: RESOLVED
A24: Real Options | B24: RealOptions C5:D7 | C24: Cluster probabilities (18/45/37) and values ($5.5/$2.5/$0.75B) are methodology-anchored priors, NOT derived from research. Highest-leverage, lowest-rigor input. $2.4B option value swings $1.5-3.5B across reasonable probability ranges. The +18% premium of DCF+Options to Series G is sensitive to this judgment. | D24: Acknowledged in memo as judgment input. Notes added to RealOptions C5:D7 and A18:A22. No model change; flagged for memo discussion of sensitivity. | E24: Memo flag | F24: DOCUMENTED
