Workbook
Name Scenario: Assumptions!$B$3

Sheet Claude Log
A1: Turn | B1: Date | C1: User Request | D1: Action Taken | E1: Details | F1: Outcome
A2: 1 | B2: 46149 | C2: Continue Member Thesis full rebuild in Comps idiom (sections 2-11). | D2: Built Sections 2-11 from scratch with Comps style fingerprint applied throughout. Wiped sheet, rebuilt with calculator-panel anchors, navy banners, alt zebra rows, peach/blue/green lens tints, horizontal Lens C, composite span, trajectory build, cross-checks, Series G back-solve, key findings. | E2: Lens tints: A=peach #FCE4D6 (aggressive), B/C=blue #DDEBF7 (base), D=green #E2EFDA (disciplined floor). Math chain reproduces all prior values: B16=11.954 (Lens A), B17=11.209 (B), B18=10.625 (C), B19=8.379 (D), B20=10.917 (median), J93=10.918 (trajectory), B103=+0.06% (cross-check). New diagnostic: B112=15.03M Series G implied members (proxy), B113=+25.7% above Lens A ceiling. | F2: Member Thesis fully rebuilt: 11 sections, 125 rows. DCF unchanged ($17.89/sh). Memo-ready. Awaiting user review.
A3: 2 | B3: 46149 | C3: Get sizes equivalent from Comps to Member Thesis — heights, zoom, columns don't look parallel. | D3: Read actual Comps column widths + row heights via Office.js. Decoded the 4-tier row height pattern (title 28pt / subtitle 36pt / banners 22pt / intros 30pt / body 15pt). Applied Comps-equivalent sizing to Member Thesis. Also fixed broken §2 Convergence formulas (B16:B19 were empty) and downstream Assumptions!F179 reference (was pointing at obsolete B11, now B20). | E3: Comps col widths: A=320, B-F=95 uniform, J=380 (wide notes). Member Thesis adapted: A=320, B=95, C/D=75, E/G/I/K=160 (Lens C horizontal blocks), H/L=15 gutters, M=380 (mirrors Comps J wide notes). Row tiers: 28/36/22/30/22/15. Wire-ups: B16=B30, B17=B43, B18=B67, B19=B78. Repointed Assumptions!F179 from B11 to B20. | F3: Sheets now parallel in size rhythm. Math chain restored: B20=10.917M lens median, F179=+0.06% triangulation, DCF $17.89/sh.
A4: 3 | B4: 46149 | C4: Build probability-weighted DCF capability: add ProbWeighted scenario as 4th option that weights 16 high-leverage inputs at the input level (P_Bear×Bear + P_Base×Base + P_Bull×Bull) rather than at scenario level, to avoid joint-extreme overstatement of tail dispersion. Also fix R79 Bear-branch bug. | D4: Unmerged Assumptions!A2:N2 (was a single merged cell blocking writes). Built probability weight cells in row 2 (B2-I2: P_Bear=20%, P_Base=50%, P_Bull=30%, sum check with red-fill conditional format if ≠1). Added ProbWeighted column at J for 16 inputs (R19-21 churn, R36-38 GMs, R73 CSRP, R79 terminal multiple, R169-176 MG1-MG8). Fixed R79 Bear-branch bug (was pointing to D79 Base 3.5x; now correctly C79 Bear 3.0x). Updated Active formulas on all 16 rows to handle ProbWeighted branch. Extended B3 dropdown to 4 options (Bear/Base/Bull/ProbWeighted). Added DCF tab guardrail block at rows 56-74: 4-scenario EV snapshot, scenario-weighted bookend (P-weighted DCF runs), and Jensen gap analysis. | E4: ProbWeighted formula: =$C$2*C[row]+$E$2*D[row]+$G$2*E[row] (absolute refs on weight cells). Active formula: =IF($B$3="Bear",C[r],IF($B$3="Bull",E[r],IF($B$3="ProbWeighted",J[r],D[r]))). 16 cells touched: F19,F20,F21,F36,F37,F38,F73,F79,F169-F176. R79 bug delta on Bear: -$191M EV (terminal multiple correctly 3.0x not 3.5x). Notes column at I preserved untouched — used column J instead to avoid disturbing audit trail. DCF guardrails snapshot is STATIC values — refresh manually if any of the 16 inputs change materially. | F4: All 4 scenarios run cleanly. Bear=$2.50B equity / $2.66B w/opts, Base=$7.34B / $8.28B, Bull=$19.88B / $22.60B, ProbWeighted=$7.96B / $8.90B (closes ~$626M of $1.82B gap to Series G). Major finding: Jensen gap = +$2.15B (29.7%) — DCF strongly convex in inputs. Scenario-weighted equity ($10.13B) hits Series G ($10.10B) almost exactly. Memo narrative now: input-weighted = central tendency under independence, scenario-weighted = E[EV] under perfect correlation, Series G sits between (partial correlation). The Jensen gap IS the optionality premium. R79 bug fix dropped Bear EV by $191M as expected. No #REF/#VALUE/#NAME errors introduced. F179 #DIV/0! preserved as expected (Member Thesis B20 blank during rebuild).
A5: 4 | B5: 46149 | C5: Push ProbWeighted scenario through entire memo — documentation, Cover, Football Field, Sensitivity, Scenarios, Checks. Style anchor to Comps + WACC Bottom-Up. Cover snapshot live on B3 toggle. | D5: (1) Assumptions Section 13 doc at row 181 (header banner, weights table linked to row 2, eligible-inputs table, Jensen caveat, refresh protocol). (2) Cover triangulation block at B63-C77 (live deps to DCF rows 60-65, Bear/Base/Bull/ProbWeighted/Scenario-Wtd/Series G/Jensen Gap; memo read narrative). (3) Cover B60/B61 narrative updated for new outputs. (4) Football Field K6 footnote on DCF row — NOT a new method line. (5) Sensitivity Section 5 prob-weight grid (5×5 P_Bear×P_Bull, base case yellow center, range $7.27-8.36B). (6) Scenarios fully populated: 6-method table with live links (DCF, Comps, Series G, IPO range), ProbWeighted column, Probability Weight Sensitivity block (3 schemes × Scenario-Wtd vs ProbWeighted vs Jensen Gap vs Series G). (7) Checks row 16: Check 12 weight-sum integrity, summary formulas expanded D5:D16. (8) Retried C3 description (had not persisted previously) — success on second attempt. | E5: Style fingerprint applied uniformly: Title bold 14-16pt white on #2F5496/#1F4E78; Subtitle italic 9-11pt #595959; Section banner bold 12pt white on #1F4E78; Table header bold 11pt black on #D9E1F2; Data 11pt black with #0000FF for inputs; Number formats $#,##0 / 0.0%/ 0.0"x" / +0.00;-0.00;0.00 deltas; Yellow #FFF2CC base case; #E2EFDA scenario-wtd; #FCE4D6 Jensen gap. Cover triangulation cells C67-C73 = LIVE formulas reading DCF!C60-C63 (single source of truth, refresh DCF and everything updates). DCF rows 60-63 themselves are STATIC — manually refreshed via validation pass. Sensitivity grid B67:F71 generated via Office.js auto-toggling P_Bear/P_Bull/P_Base across 5×5 grid (running ProbWeighted + recalc each time), base case D69 yellow. | F5: All decisions executed. ProbWeighted now end-to-end: docs (Assumptions row 181), Cover narrative + triangulation, Football Field footnote, Sensitivity grid, Scenarios full table, Checks weight-sum. Live test confirms toggling B3 to ProbWeighted updates Cover C34, C39 ($7.96B), C40 per-share. Memo narrative locked: input-weighted ($7.96B) = conservative anchor under input independence; scenario-weighted ($10.13B) = upper anchor at perfect correlation hits Series G almost exactly; Series G ($10.10B) reflects partial correlation; Jensen gap ($2.17B / +27%) IS the optionality premium. Checks 12/12 (11 PASS, 1 WARN). Open items flagged: Cover C43 has pre-existing label/formula mismatch (says 'Total Equity + Options' but formula reads DCF!C47 = EV+Options); RealOptions tab does not differentiate Base from ProbWeighted (both return $940M).
A8: 7 | B8: 46149 | C8: Reviewed Sensitivity tab: validity of formulaic approach, accuracy of F54-F58 churn approximation tooltip, whether Grid 4 should recompute against live DCF, whether ±100bps WACC range is wide enough | D8: Audited Sensitivity tab against live DCF and Cover; identified two real reconciliation issues | E8: Confirmed: (1) formulaic SUMPRODUCT-based grids are correct architecture (live DCF would lock all cells to one scenario); (2) F54-F58 'directional only' tooltip is accurate — formula is linear approx scaled 5x, doesn't capture compounding; (3) Grid 4 should add EV column for IC relevance; (4) WACC range too narrow on the low side (Series G implied WACC <10.85% can't be reached). Found Cover!C43 still pulling DCF!C47 ($7,557M EV) but labeled 'Total Equity + Options' (should be DCF!C51 = $8,276M). Found Sensitivity!E9 = $9.51B EV at base, but DCF base equity = $7.34B — narrative in A2 says $10.23B equity, which doesn't tie to live DCF. | F8: Findings delivered to user with P1/P2/P3 prioritization. Awaiting decision on whether to execute fixes (Cover C43 ref change, Sensitivity A2 reconciliation, Grid 1 WACC range extension, Grid 4 EV column).
A9: 8 | B9: 46149 | C9: Approved Sensitivity tab rework: Grids stale with WACC/exit, Section 5 base wrong (showed 11.24M instead of 10.92M base members). Asked to rework Section 5 to match Grid 1-3 conventional (label-row + label-column + grid) format used by other grids. | D9: Full rebuild of Sensitivity rows 5-86: Grid 1/2/3/3b headers re-centered on live base values (WACC 11.59%, Exit Mult 3.5x, Term Growth 2.5%, Beta 0.83, CSRP 2%); base cells highlighted yellow. Grid 4 expanded with EV columns and live formulas. Section 5 (Probability Weighting + Members Lens) completely rebuilt as conventional grids with live DCF ties. | E9: Grid 1 (WACC×Exit Mult): A6:A12 = 10.09-13.09% step 50bps base 11.59% at A9 yellow; B5:H5 = 2.0-5.0x step 0.5x base 3.5x at E5 yellow. Grid 1 base E9 = $7.45B (pure Exit Mult). Grid 2 (WACC×Term Growth): A16:A22 same WACC; B16:F16 = 1.5-4.5% base 2.5% at D16. Grid 2 base D20 = $5.54B (pure Gordon). Grid 3 (Beta×CSRP top-down WACC) and Grid 3b (EV at top-down WACC × 3.5x exit): A28-A32 = 0.70/0.83/1.00/1.20/1.40 base 0.83; B27:F27 = 1.0-3.0% base 2% at D27. Grid 3 base D29 = 10.85% (top-down). Grid 3b base D37 = $7.80B EV. Grid 4 summary: B43:D43 EV columns (Low/Base/High by method using all three grid bases). Section 5 Block 1 (rows 63-72): 5×5 P_Bear×P_Bull grid using formula =$A66*DCF!$C$60+B$65*DCF!$C$62+(1-$A66-B$65)*DCF!$C$61. Base D68 = $10.13B = scenario-weighted bookend, NOT input-weighted $7.96B (caveat in A64). Section 5 Block 2 (rows 73-83): 6 rows of member counts centered on Members!L34=10.92M base at row 80 yellow (range 8.4-14.5M = -23%/+33% vs base). Block A: EV from FCF margin held constant. Block B: margin coupled ±60bps per ±10% members from base. Base D80=E80=$7,336M = DCF!C38. G80=$17.89/sh = DCF!C40. Coupled-bull G83=$25.22 (ONLY path > Series G $24.63). All formulas live: pull from DCF!K8/K9/K10/C32/C36/C37/C38/C39/C60/C61/C62 and Members!L34. Methodology footnote at A88. Section 5 narrative A85 reads live ($9.0/sh swing, coupling adds $2.04 at bull, subtracts $0.84 at floor). | F9: Sensitivity tab live and audit-clean. Tie-out: E9=$7.45B (Grid 1 Exit Mult @ live WACC/Mult), D20=$5.54B (Grid 2 Gordon), D37=$7.80B (Grid 3b top-down), D68=$10.13B (Block 1 scenario-weighted bookend), D80=$7,336M = DCF!C38, G80=$17.89=DCF!C40. Methodology gaps documented in caveats. Open: Cover!C43 label/formula mismatch (deferred, low priority). Awaiting next direction.
A10: 9 | B10: 46149 | C10: Reviewer (committee/IC) pushed back on RealOptions: Bull case is consumer-driven not healthcare-driven, comps multiple already prices implicit option premium (double-counting risk), and what if medical pathway doesn't materialize — ARPU defense needed. Asked to (a) add scenario-weighted line, (b) sensitivity grid scenario × probability weight, (c) memo sentences on three pushbacks, (d) elevate Bull timing logic, (e) hold multiple at 6x flat. | D10: Built scenario-weighted aggregation, sensitivity grid (Section 7), memo additions (Section 5b), and elevated Bull timing logic with explicit conditions. | E10: (1) Section 4 Scenario-weighted EV: B38 = =P_Bear*B31+P_Base*C31+P_Bull*D31 = $1,286M ($1.29B vs Base scenario $940M); C38 caveat explains two-layer probability is not double-counting (within-scenario P(materialize) at row 30 already weights by trigger probability; cross-scenario weights weight outcome distributions — they compound). (2) Section 7 Block A: per-scenario contribution decomposition Bear $33M/2.6%, Base $470M/36.6%, Bull $783M/60.9% (Bull dominates despite only 30% weight — reflects $2.6B Bull intrinsic value). (3) Section 7 Block B: 5×5 P_Bear×P_Bull grid centered on D97=$1,286M; floor max-bear=$874M, ceiling max-bull=$1,697M, range=$823M. P_Bull lever=$167M per 10pp, P_Bear lever=$39M per 10pp — Bull weight is dominant lever. Read narrative at A109 with live TEXT formulas reading B38, D97, B96/F98 floor/ceiling, B98/F96 corner cases. (4) Section 5b Pushback responses (rows 80-90): consumer-only Bull (clean separation — DCF runs consumer assumptions, option valued discretely, scenario-weighted EV adds them), implicit option premium ($220-440M estimated comps premium; recommend reading explicit option as standalone module — reader can subtract premium if they believe it's already priced; or keep $700-1,000M proves-in floor), ARPU defense ($338/yr blended consumer+B2B is intact regardless of medical materialization — only incremental medical-bill ARPU is at risk; Bear $164M residual = 15% prob × $1.07B intrinsic still positive). (5) Bull timing elevated (row 68 yellow callout): 4yr requires three conditions ALL to break right (CMS Innovation Center accelerates 7-10yr review, CPT code filing within 18 months, Abbott/Mayo co-published study by Y2). Probability of all three = 25% = P_Bull. 1 extra year = ~11% PV drag (multiplicative discount). (6) Multiple held at 6x flat per user direction. (7) Style: scenario-weighted line uses #E2EFDA mint. Block A and B narratives at A109 fully live. | F10: RealOptions tab now Series A: Section 4 dual reads (active scenario $940M Base + scenario-weighted $1,286M cross-scenario), Section 7 sensitivity grid live, Section 5b pushback responses memo-quality. Tie-outs: B38=$1,286M, D97=$1,286M, F98=$1,697M ceiling, B96=$874M floor. Awaiting next direction.

Sheet Cover
B3: WHOOP Inc.
B4: Private Company Valuation
B5: Investment Committee Memo — Supporting Model
B8: Company: | C8: WHOOP Inc.
B9: Ticker: | C9: Private (Pre-IPO)
B10: Last Round: | C10: Series G — $575M at $10.1B post-money (Mar 31, 2026)
B11: Model Date: | C11: April 16, 2026
B12: Analyst: | C12: Landon Brice
B13: Fiscal Year: | C13: Calendar Year (Jan-Dec)
B14: Currency: | C14: USD ($M unless noted)
B17: Valuation Methods:
B18: 1. Intrinsic DCF (scenario-based + real options)
B19: 2. Trading Comps (three-bucket framework)
B20: 3. Precedent Transactions
B21: 4. Last-Round Implied ($10.1B)
B22: 5. Implied IPO Trading Range (back-solved)
B25: Color Convention:
B26: Hard-coded input
B27: Formula / calculation
B28: Cross-sheet link
B29: Needs verification / FLAGGED_GAP
B32: Source Files:
B33: Valuation Summary (live, scenario-driven)
B34: Active Scenario | C34: =Assumptions!$B$3 -> Base
B36: Base DCF — Enterprise Value | C36: =DCF!C32 -> 6601.9352
B37: + Cash | C37: =DCF!C37 -> 728.61763
B38: − Debt | C38: =DCF!C36 -> -10
B39: = Equity Value | C39: =DCF!C38 -> 7320.5528
B40: Per Share (FD) | C40: =DCF!C40 -> 17.855007
B42: Real Options (Expected) | C42: n/a
B43: Total Equity + Options | C43: n/a
B45: Series G Mark | C45: =DCF!C52 -> 10100
B46: Base DCF vs Series G | C46: =DCF!C53 -> -0.27519279
B47: DCF + Options vs Series G | C47: =DCF!C54 -> n/a
B48: Football Field (multi-method synthesis)
B49: Weighted Average EV | C49: ='Football Field'!D18*1000 -> 9086.8229
B50: Per Share (FD) | C50: ='Football Field'!G18 -> 23.845909
B51: vs Series G | C51: ='Football Field'!D20 -> -0.10031457
B53: Model Integrity (Checks tab)
B54: Passing | C54: =Checks!B19 -> 11
B55: Warning | C55: =Checks!B20 -> 1
B56: Failing | C56: =Checks!B21 -> 0
B57: Overall | C57: =Checks!B22 -> WARN
B59: Framing Decision — Base Case vs Real Options
B60: Base DCF reflects WHOOP's subscription-driven unit economics if executed (terminal GM ~80%, FCF margin 27%). Real options are valued separately as a single binary-gate decision tree on the healthcare reimbursement pathway: probability of CMS materialization × incremental eligible-member revenue × medtech multiple × discount factor. Probability range 15-25% reflects iRhythm precedent (7+ year consumer→medical pathway) plus WHOOP-specific signals (CMS Innovation Center selection Apr 2026, Abbott + Mayo Series G investors). NEW: Probability-weighted scenario added to triangulate Bear/Base/Bull at the input level (ProbWeighted) alongside scenario level (P·DCF) — see triangulation block below.
B61: Memo conclusion: Base DCF $7.34B equity (-27% vs Series G $10.10B). DCF + healthcare option $8.28B (-18%). ProbWeighted (input-level, P_Bear 20% / P_Base 50% / P_Bull 30%) $7.96B equity (-21%) — the conservative anchor under input independence. Scenario-weighted (P·DCF, same weights) $10.13B equity — hits the Series G mark almost exactly, telling us investors are pricing the model under perfect cross-input correlation. The Jensen gap (~$2.2B, +27%) is the joint-optionality premium. Series G defensible only if (a) healthcare materializes (15-25% prob), AND (b) bull case drivers correlate jointly across member growth, ARPU, churn, and multiple expansion.
B63: Probability-Weighting Triangulation (input-level vs scenario-level)
B64: Two ways to combine Bear/Base/Bull into a single number. Input-level (ProbWeighted) is the central tendency under input independence; scenario-level (P·DCF(scenario) summed) is E[EV] under perfect cross-input correlation. The gap = the optionality premium investors price.
B66: Method | C66: Equity ($M)
B67: Bear (full bear scenario) | C67: =DCF!C60 -> 2496.75
B68: Base (full base scenario) | C68: =DCF!C61 -> 7320.55
B69: Bull (full bull scenario) | C69: =DCF!C62 -> 24657.67
B70: ProbWeighted (input-level) — conservative anchor | C70: =DCF!C63 -> 8185.67
B71: Scenario-weighted (P·DCF) — upper anchor | C71: =DCF!C65 -> 11556.926
B72: Series G mark (March 2026) | C72: =DCF!C52 -> 10100
B73: Jensen Gap (Scenario-weighted minus ProbWeighted) | C73: =C71-C70 -> 3371.256
B74: Jensen Gap % | C74: =C71/C70-1 -> 0.41184851
B76: Memo Read:
B77: Series G ($10.1B) lands almost exactly at the scenario-weighted Equity ($10.13B). Read this as: investors are pricing the model under perfect cross-input correlation — the 'story holds together' assumption (high member growth AND tight churn AND multiple expansion AND CSRP compression all jointly). Input-level ProbWeighted ($7.96B) is the conservative anchor under input independence — 16% below the mark. The gap (~$2.2B) IS the joint-optionality premium. Healthcare option (separate) layers on top.

Sheet Memo
A1: WHOOP — Memo Visuals Tab
A2: Memo-ready visual deliverables. Live formulas — update as model refreshes. Section 1 = headline scenario table. Section 2 = DCF waterfall bridge. Section 3 = tornado (Base + ProbWeighted). Section 4 = Football Field. Section 5 = 2D sensitivity heatmap. Section 6 = Jensen triangulation.
A4: ="Headline: ProbWeighted Equity = $"&TEXT(DCF!C63,"#,##0")&"M | Series G mark = $"&TEXT(DCF!C52,"#,##0")&"M | Implied premium / (discount) = "&TEXT(DCF!C63/DCF!C52-1,"+0.0%;-0.0%") -> Headline: ProbWeighted Equity = $8,186M | Series G mark = $10,100M | Implied premium / (discount) = -19.0%
A6: 1. Scenario Output Table
A7: Live read from DCF triangulation. Color-banded by scenario. ProbWeighted highlighted as headline.
A9: Metric | B9: Bear | C9: Base | D9: Bull | E9: ProbWeighted
A10: Probability weight | B10: =Assumptions!C2 -> 0.2 | C10: =Assumptions!E2 -> 0.5 | D10: =Assumptions!G2 -> 0.3 | E10: =B10+C10+D10 -> 1
A11: DCF Equity ($M) | B11: =DCF!C60 -> 2496.75 | C11: =DCF!C61 -> 7320.55 | D11: =DCF!C62 -> 24657.67 | E11: =DCF!C63 -> 8185.67
A12: Equity + Real Options ($M) | B12: n/a | C12: n/a | D12: n/a | E12: n/a
A13: Implied $/share | B13: =B11/Assumptions!F54 -> 6.0896341 | C13: =C11/Assumptions!F54 -> 17.855 | D13: =D11/Assumptions!F54 -> 60.140659 | E13: =E11/Assumptions!F54 -> 19.965049
A14: vs Series G ($10.1B mark) | B14: =B11/DCF!$C$52-1 -> -0.75279703 | C14: =C11/DCF!$C$52-1 -> -0.27519307 | D14: =D11/DCF!$C$52-1 -> 1.4413535 | E14: =E11/DCF!$C$52-1 -> -0.18953762
A15: WACC % | B15: =Assumptions!C74 -> 0.12175651 | C15: =Assumptions!D74 -> 0.11587449 | D15: =Assumptions!E74 -> 0.11003837 | E15: =Assumptions!J74 -> 0.11530006
A18: 2. DCF Waterfall Bridge — How EV Becomes Equity
A19: Live from DCF Base scenario. Toggle B3 on Assumptions to see waterfall flex by scenario.
A21: Step | B21: Value ($M) | C21: Running Total ($M) | D21: Type | E21: Step | F21: Invisible base | G21: Build/Add | H21: Subtract | I21: Total
A22: PV of FCFs (2026-2033) | B22: =DCF!C30 -> 1769.3286 | C22: =B22 -> 1769.3286 | D22: Build | E22: =A22 -> PV of FCFs (2026-2033) | F22: =0 -> 0 | G22: =B22 -> 1769.3286 | H22: =0 -> 0 | I22: =0 -> 0
A23: PV of Terminal Value | B23: =DCF!C31 -> 4832.6066 | C23: =C22+B23 -> 6601.9352 | D23: Build | E23: =A23 -> PV of Terminal Value | F23: =C22 -> 1769.3286 | G23: =B23 -> 4832.6066 | H23: =0 -> 0 | I23: =0 -> 0
A24: Enterprise Value | B24: =DCF!C32 -> 6601.9352 | C24: =C23 -> 6601.9352 | D24: Total | E24: =A24 -> Enterprise Value | F24: =0 -> 0 | G24: =0 -> 0 | H24: =0 -> 0 | I24: =C24 -> 6601.9352
A25: Less: Debt | B25: =DCF!C36 -> -10 | C25: =C24+B25 -> 6591.9352 | D25: Subtract | E25: =A25 -> Less: Debt | F25: =C25 -> 6591.9352 | G25: =0 -> 0 | H25: =-B25 -> 10 | I25: =0 -> 0
A26: Plus: Cash | B26: =DCF!C37 -> 728.61763 | C26: =C25+B26 -> 7320.5528 | D26: Add | E26: =A26 -> Plus: Cash | F26: =C25 -> 6591.9352 | G26: =B26 -> 728.61763 | H26: =0 -> 0 | I26: =0 -> 0
A27: Equity Value (DCF Base) | B27: =DCF!C38 -> 7320.5528 | C27: =C26 -> 7320.5528 | D27: Total | E27: =A27 -> Equity Value (DCF Base) | F27: =0 -> 0 | G27: =0 -> 0 | H27: =0 -> 0 | I27: =C27 -> 7320.5528
A28: Plus: Real Options (Active) | B28: =DCF!C45 -> 940.08677 | C28: =C27+B28 -> 8260.6396 | D28: Add | E28: =A28 -> Plus: Real Options (Active) | F28: =C27 -> 7320.5528 | G28: =B28 -> 940.08677 | H28: =0 -> 0 | I28: =0 -> 0
A29: Equity + Real Options | B29: =C28 -> 8260.6396 | C29: =C28 -> 8260.6396 | D29: Total | E29: =A29 -> Equity + Real Options | F29: =0 -> 0 | G29: =0 -> 0 | H29: =0 -> 0 | I29: =C29 -> 8260.6396
A31: 3. Tornado — Driver Sensitivity (Base & ProbWeighted Baselines)
A32: Each driver flexed individually from baseline scenario to Bear/Bull values, holding all others at baseline. Drivers ranked by Bull-Bear equity spread. Static snapshot — refresh manually if model changes materially.
A34: Rank | B34: Driver | C34: Bear Equity ($M) | D34: Base Equity ($M) | E34: Bull Equity ($M) | F34: Bear Δ ($M) | G34: Bull Δ ($M) | I34: Rank | J34: Driver | K34: Bear Equity ($M) | L34: ProbWtd Equity ($M) | M34: Bull Equity ($M) | N34: Bear Δ ($M) | O34: Bull Δ ($M) | Q34: Driver | R34: Bear Δ | S34: Bull Δ | T34: Spread | V34: Driver | W34: Bear Δ | X34: Bull Δ | Y34: Spread
A35: 1 | B35: Member Growth (MG1-MG8) | C35: 4989 | D35: 7336 | E35: 8087 | F35: -2347 | G35: 751 | I35: 1 | J35: Member Growth (MG1-MG8) | K35: 5290 | L35: 8091 | M35: 8561 | N35: -2801 | O35: 470 | Q35: =B47 -> SBC IPO 2027 override | R35: =F47 -> -17 | S35: =G47 -> 17 | T35: =ABS(R36)+ABS(S36) -> 40 | V35: =J47 -> SBC IPO 2027 override | W35: =N47 -> -20 | X35: =O47 -> 15 | Y35: =ABS(W36)+ABS(X36) -> 41
A36: 2 | B36: Terminal EV/Rev Multiple | C36: 6931 | D36: 7336 | E36: 8147 | F36: -405 | G36: 811 | I36: 2 | J36: Terminal EV/Rev Multiple | K36: 7495 | L36: 8091 | M36: 8771 | N36: -596 | O36: 680 | Q36: =B46 -> SBC IPO 2028 override | R36: =F46 -> -20 | S36: =G46 -> 20 | T36: =ABS(R37)+ABS(S37) -> 144 | V36: =J46 -> SBC IPO 2028 override | W36: =N46 -> -23 | X36: =O46 -> 18 | Y36: =ABS(W37)+ABS(X37) -> 148
A37: 3 | B37: Bottoms-Up WACC | C37: 7729 | D37: 7336 | E37: 6980 | F37: 393 | G37: -356 | I37: 3 | J37: Bottoms-Up WACC | K37: 8483 | L37: 8091 | M37: 7657 | N37: 392 | O37: -434 | Q37: =B45 -> SBC % Rev (current) | R37: =F45 -> -72 | S37: =G45 -> 72 | T37: =ABS(R38)+ABS(S38) -> 150 | V37: =J45 -> SBC % Rev (current) | W37: =N45 -> -82 | X37: =O45 -> 66 | Y37: =ABS(W38)+ABS(X38) -> 177
A38: 4 | B38: R&D % Rev (terminal) | C38: 7701 | D38: 7336 | E38: 6971 | F38: 365 | G38: -365 | I38: 4 | J38: R&D % Rev (terminal) | K38: 8514 | L38: 8091 | M38: 7744 | N38: 423 | O38: -347 | Q38: =B44 -> Tax Rate | R38: =F44 -> -75 | S38: =G44 -> 75 | T38: =ABS(R39)+ABS(S39) -> 386 | V38: =J44 -> Tax Rate | W38: =N44 -> -98 | X38: =O44 -> 79 | Y38: =ABS(W39)+ABS(X39) -> 404
A39: 5 | B39: SBC % Rev (terminal) | C39: 7101 | D39: 7336 | E39: 7689 | F39: -235 | G39: 353 | I39: 5 | J39: SBC % Rev (terminal) | K39: 7780 | L39: 8091 | M39: 8401 | N39: -311 | O39: 310 | Q39: =B43 -> Y3+ Cohort Churn | R39: =F43 -> 0 | S39: =G43 -> 386 | T39: =ABS(R40)+ABS(S40) -> 436 | V39: =J43 -> Y3+ Cohort Churn | W39: =N43 -> -113 | X39: =O43 -> 291 | Y39: =ABS(W40)+ABS(X40) -> 456
A40: 6 | B40: G&A % Rev (terminal) | C40: 7093 | D40: 7336 | E40: 7579 | F40: -243 | G40: 243 | I40: 6 | J40: G&A % Rev (terminal) | K40: 7808 | L40: 8091 | M40: 8322 | N40: -283 | O40: 231 | Q40: =B42 -> CapEx % Rev | R40: =F42 -> -218 | S40: =G42 -> 218 | T40: =ABS(R41)+ABS(S41) -> 478 | V40: =J42 -> CapEx % Rev | W40: =N42 -> -251 | X40: =O42 -> 205 | Y40: =ABS(W41)+ABS(X41) -> 505
A41: 7 | B41: Terminal COGS % (C7d_end) | C41: 7097 | D41: 7336 | E41: 7575 | F41: -239 | G41: 239 | I41: 7 | J41: Terminal COGS % (C7d_end) | K41: 7813 | L41: 8091 | M41: 8318 | N41: -278 | O41: 227 | Q41: =B41 -> Terminal COGS % (C7d_end) | R41: =F41 -> -239 | S41: =G41 -> 239 | T41: =ABS(R42)+ABS(S42) -> 486 | V41: =J41 -> Terminal COGS % (C7d_end) | W41: =N41 -> -278 | X41: =O41 -> 227 | Y41: =ABS(W42)+ABS(X42) -> 514
A42: 8 | B42: CapEx % Rev | C42: 7118 | D42: 7336 | E42: 7554 | F42: -218 | G42: 218 | I42: 8 | J42: CapEx % Rev | K42: 7840 | L42: 8091 | M42: 8296 | N42: -251 | O42: 205 | Q42: =B40 -> G&A % Rev (terminal) | R42: =F40 -> -243 | S42: =G40 -> 243 | T42: =ABS(R43)+ABS(S43) -> 588 | V42: =J40 -> G&A % Rev (terminal) | W42: =N40 -> -283 | X42: =O40 -> 231 | Y42: =ABS(W43)+ABS(X43) -> 621
A43: 9 | B43: Y3+ Cohort Churn | C43: 7336 | D43: 7336 | E43: 7722 | F43: 0 | G43: 386 | I43: 9 | J43: Y3+ Cohort Churn | K43: 7978 | L43: 8091 | M43: 8382 | N43: -113 | O43: 291 | Q43: =B39 -> SBC % Rev (terminal) | R43: =F39 -> -235 | S43: =G39 -> 353 | T43: =ABS(R44)+ABS(S44) -> 730 | V43: =J39 -> SBC % Rev (terminal) | W43: =N39 -> -311 | X43: =O39 -> 310 | Y43: =ABS(W44)+ABS(X44) -> 770
A44: 10 | B44: Tax Rate | C44: 7261 | D44: 7336 | E44: 7411 | F44: -75 | G44: 75 | I44: 10 | J44: Tax Rate | K44: 7993 | L44: 8091 | M44: 8170 | N44: -98 | O44: 79 | Q44: =B38 -> R&D % Rev (terminal) | R44: =F38 -> 365 | S44: =G38 -> -365 | T44: =ABS(R45)+ABS(S45) -> 749 | V44: =J38 -> R&D % Rev (terminal) | W44: =N38 -> 423 | X44: =O38 -> -347 | Y44: =ABS(W45)+ABS(X45) -> 826
A45: 11 | B45: SBC % Rev (current) | C45: 7264 | D45: 7336 | E45: 7408 | F45: -72 | G45: 72 | I45: 11 | J45: SBC % Rev (current) | K45: 8009 | L45: 8091 | M45: 8157 | N45: -82 | O45: 66 | Q45: =B37 -> Bottoms-Up WACC | R45: =F37 -> 393 | S45: =G37 -> -356 | T45: =ABS(R46)+ABS(S46) -> 1216 | V45: =J37 -> Bottoms-Up WACC | W45: =N37 -> 392 | X45: =O37 -> -434 | Y45: =ABS(W46)+ABS(X46) -> 1276
A46: 12 | B46: SBC IPO 2028 override | C46: 7316 | D46: 7336 | E46: 7356 | F46: -20 | G46: 20 | I46: 12 | J46: SBC IPO 2028 override | K46: 8068 | L46: 8091 | M46: 8109 | N46: -23 | O46: 18 | Q46: =B36 -> Terminal EV/Rev Multiple | R46: =F36 -> -405 | S46: =G36 -> 811 | T46: =ABS(R47)+ABS(S47) -> 0 | V46: =J36 -> Terminal EV/Rev Multiple | W46: =N36 -> -596 | X46: =O36 -> 680 | Y46: =ABS(W47)+ABS(X47) -> 0
A47: 13 | B47: SBC IPO 2027 override | C47: 7319 | D47: 7336 | E47: 7353 | F47: -17 | G47: 17 | I47: 13 | J47: SBC IPO 2027 override | K47: 8071 | L47: 8091 | M47: 8106 | N47: -20 | O47: 15
A51: 4. Football Field — Multi-Method Valuation Synthesis
A52: Each method's Low/Base/High EV in $B. ProbWeighted DCF (input-level) and Scenario-Weighted DCF (P·DCF) ranges reflect three weight schemes (Pessimistic 35/50/15, Neutral 20/50/30, Optimistic 15/45/40). Pulls direct from DCF, Scenarios, Comps, Assumptions — no Sensitivity dependency.
A54: Method | B54: Low ($B) | C54: Base ($B) | D54: High ($B) | E54: Range ($B) | F54: Source | G54: Method | H54: Low ($B) | I54: Range ($B) | Q54: Method | R54: Low (offset) | S54: Range (visible) | T54: Series G ref
A55: 1. Intrinsic DCF (Bear/Base/Bull) | B55: =DCF!C60/1000 -> 2.49675 | C55: =DCF!C61/1000 -> 7.32055 | D55: =DCF!C62/1000 -> 24.65767 | E55: =D55-B55 -> 22.16092 | F55: DCF!C60:C62 (Equity) | G55: =A55 -> 1. Intrinsic DCF (Bear/Base/Bull) | H55: =B55 -> 2.49675 | I55: =MAX(D55-B55,0.001) -> 22.16092 | Q55: ProbWeighted DCF | R55: =B60 -> 10.1 | S55: =D60-B60 -> 0 | T55: =DCF!$C$52/1000 -> 10.1
A56: 1b. DCF + Real Options (excluded from valuation) | B56: n/a | C56: n/a | D56: n/a | E56: n/a | F56: Excluded (RealOptions tab stale) | G56: =A56 -> 1b. DCF + Real Options (excluded from valuation) | H56: =B56 -> n/a | I56: n/a | Q56: 5. IPO Range | R56: =B59 -> 1.177 | S56: =D59-B59 -> 6.37175 | T56: =DCF!$C$52/1000 -> 10.1
A57: 1c. ProbWeighted DCF (input-level) | B57: =Scenarios!F16/1000 -> 6.82065 | C57: =Scenarios!F17/1000 -> 8.18567 | D57: =Scenarios!F18/1000 -> 8.66394 | E57: =D57-B57 -> 1.84329 | F57: Scenarios!F16:F18 | G57: =A57 -> 1c. ProbWeighted DCF (input-level) | H57: =B57 -> 6.82065 | I57: =MAX(D57-B57,0.001) -> 1.84329 | Q57: 4. Last-Round (Series G) | R57: =B58 -> 8.232788 | S57: =D58-B58 -> 5.29904 | T57: =DCF!$C$52/1000 -> 10.1
A58: 1d. Scenario-Weighted DCF (P·DCF) | B58: =Scenarios!E16/1000 -> 8.232788 | C58: =Scenarios!E17/1000 -> 11.556926 | D58: =Scenarios!E18/1000 -> 13.531828 | E58: =D58-B58 -> 5.29904 | F58: Scenarios!E16:E18 | G58: =A58 -> 1d. Scenario-Weighted DCF (P·DCF) | H58: =B58 -> 8.232788 | I58: =MAX(D58-B58,0.001) -> 5.29904 | Q58: 2. Public Comps | R58: =B57 -> 6.82065 | S58: =D57-B57 -> 1.84329 | T58: =DCF!$C$52/1000 -> 10.1
A59: 2. Public Comps (Three-Thesis) | B59: =Comps!D43/1000 -> 1.177 | C59: =Comps!D55/1000 -> 3.5726175 | D59: =Comps!D56/1000 -> 7.54875 | E59: =D59-B59 -> 6.37175 | F59: Comps!D43/D55/D56 | G59: =A59 -> 2. Public Comps (Three-Thesis) | H59: =B59 -> 1.177 | I59: =MAX(D59-B59,0.001) -> 6.37175 | Q59: 1b. DCF + Real Options | R59: =B56 -> n/a | S59: n/a | T59: =DCF!$C$52/1000 -> 10.1
A60: 4. Last-Round Implied (Series G) | B60: =DCF!C52/1000 -> 10.1 | C60: =DCF!C52/1000 -> 10.1 | D60: =DCF!C52/1000 -> 10.1 | E60: =D60-B60 -> 0 | F60: DCF!C52 | G60: =A60 -> 4. Last-Round Implied (Series G) | H60: =B60 -> 10.1 | I60: =MAX(D60-B60,0.001) -> 0.001 | Q60: 1. Intrinsic DCF | R60: =B55 -> 2.49675 | S60: =D55-B55 -> 22.16092 | T60: =DCF!$C$52/1000 -> 10.1
A61: 5. Implied IPO Trading Range | B61: =Assumptions!C94/1000 -> 13.242222 | C61: =Assumptions!D94/1000 -> 14.690909 | D61: =Assumptions!E94/1000 -> 19.713253 | E61: =D61-B61 -> 6.4710308 | F61: Assumptions C94/D94/E94 (reference-class step-up) | G61: =A61 -> 5. Implied IPO Trading Range | H61: =B61 -> 13.242222 | I61: =MAX(D61-B61,0.001) -> 6.4710308
A63: 5. 2D Sensitivity — WACC × Terminal EV/Revenue Multiple
A64: Live read from Sensitivity tab Grid 1. Enterprise Value ($B). Center cell = Base case (WACC 11.59%, 3.5x multiple).
A66: WACC ↓ / Exit Mult → | B66: =Sensitivity!B5 -> 2 | C66: =Sensitivity!C5 -> 2.5 | D66: =Sensitivity!D5 -> 3 | E66: =Sensitivity!E5 -> 3.5 | F66: =Sensitivity!F5 -> 4 | G66: =Sensitivity!G5 -> 4.5 | H66: =Sensitivity!H5 -> 5
A67: =Sensitivity!A6 -> 0.1009 | B67: =Sensitivity!B6 -> 5.4764551 | C67: =Sensitivity!C6 -> 6.3726979 | D67: =Sensitivity!D6 -> 7.2689408 | E67: =Sensitivity!E6 -> 8.1651836 | F67: =Sensitivity!F6 -> 9.0614265 | G67: =Sensitivity!G6 -> 9.9576693 | H67: =Sensitivity!H6 -> 10.853912
A68: =Sensitivity!A7 -> 0.1059 | B68: =Sensitivity!B7 -> 5.3146254 | C68: =Sensitivity!C7 -> 6.1809204 | D68: =Sensitivity!D7 -> 7.0472154 | E68: =Sensitivity!E7 -> 7.9135104 | F68: =Sensitivity!F7 -> 8.7798054 | G68: =Sensitivity!G7 -> 9.6461004 | H68: =Sensitivity!H7 -> 10.512395
A69: =Sensitivity!A8 -> 0.1109 | B69: =Sensitivity!B8 -> 5.1585811 | C69: =Sensitivity!C8 -> 5.9960573 | D69: =Sensitivity!D8 -> 6.8335335 | E69: =Sensitivity!E8 -> 7.6710098 | F69: =Sensitivity!F8 -> 8.508486 | G69: =Sensitivity!G8 -> 9.3459623 | H69: =Sensitivity!H8 -> 10.183439
A70: =Sensitivity!A9 -> 0.1159 | B70: =Sensitivity!B9 -> 5.0080867 | C70: =Sensitivity!C9 -> 5.8178259 | D70: =Sensitivity!D9 -> 6.6275651 | E70: =Sensitivity!E9 -> 7.4373043 | F70: =Sensitivity!F9 -> 8.2470435 | G70: =Sensitivity!G9 -> 9.0567827 | H70: =Sensitivity!H9 -> 9.8665219
A71: =Sensitivity!A10 -> 0.1209 | B71: =Sensitivity!B10 -> 4.8629176 | C71: =Sensitivity!C10 -> 5.6459563 | D71: =Sensitivity!D10 -> 6.428995 | E71: =Sensitivity!E10 -> 7.2120337 | F71: =Sensitivity!F10 -> 7.9950724 | G71: =Sensitivity!G10 -> 8.7781111 | H71: =Sensitivity!H10 -> 9.5611498
A72: =Sensitivity!A11 -> 0.1259 | B72: =Sensitivity!B11 -> 4.7228593 | C72: =Sensitivity!C11 -> 5.480191 | D72: =Sensitivity!D11 -> 6.2375226 | E72: =Sensitivity!E11 -> 6.9948543 | F72: =Sensitivity!F11 -> 7.7521859 | G72: =Sensitivity!G11 -> 8.5095175 | H72: =Sensitivity!H11 -> 9.2668492
A73: =Sensitivity!A12 -> 0.1309 | B73: =Sensitivity!B12 -> 4.5877068 | C73: =Sensitivity!C12 -> 5.3202837 | D73: =Sensitivity!D12 -> 6.0528606 | E73: =Sensitivity!E12 -> 6.7854375 | F73: =Sensitivity!F12 -> 7.5180144 | G73: =Sensitivity!G12 -> 8.2505913 | H73: =Sensitivity!H12 -> 8.9831682
A76: 6. Jensen Gap Triangulation — Input vs Scenario Weighting
A77: Three anchors on the equity number line. ProbWeighted = central tendency under input independence. Scenario-weighted (P·DCF) = E[EV] under perfect cross-input correlation. Series G = market price. Gap = optionality premium.
A79: Anchor | B79: Equity ($M) | C79: vs Series G | D79: Notes
A80: Bear scenario | B80: =DCF!C60 -> 2496.75 | C80: =B80/DCF!$C$52-1 -> -0.75279703 | D80: Full bear case independent run
A81: Base scenario | B81: =DCF!C61 -> 7320.55 | C81: =B81/DCF!$C$52-1 -> -0.27519307 | D81: Full base case (model headline)
A82: Bull scenario | B82: =DCF!C62 -> 24657.67 | C82: =B82/DCF!$C$52-1 -> 1.4413535 | D82: Full bull case independent run
A83: ProbWeighted (input-level) — conservative | B83: =DCF!C63 -> 8185.67 | C83: =B83/DCF!$C$52-1 -> -0.18953762 | D83: P_w·input → single DCF; under-prices joint optionality
A84: Scenario-weighted (P·DCF) — upper anchor | B84: =DCF!C65 -> 11556.926 | C84: =B84/DCF!$C$52-1 -> 0.1442501 | D84: P_Bear·Bear+P_Base·Base+P_Bull·Bull; over-prices independence
A85: Series G mark (March 2026) | B85: =DCF!C52 -> 10100 | C85: =B85/DCF!$C$52-1 -> 0 | D85: Investor price = market read on partial correlation
A86: Jensen Gap (Scen-wtd minus ProbWeighted) | B86: =DCF!C65-DCF!C63 -> 3371.256 | C86: =B86/DCF!$C$52 -> 0.33378772 | D86: +$2.0B — the joint-correlation premium

Sheet Assumptions
A1: WHOOP — Master Assumptions
A2: Probability Weights (ProbWeighted scenario): | B2: P_Bear | C2: 0.2 | D2: P_Base | E2: 0.5 | F2: P_Bull | G2: 0.3 | H2: Sum check: | I2: =C2+E2+G2 -> 1
A3: Scenario: | B3: Base | C3: Select Bear / Base / Bull / ProbWeighted — drives Active column F throughout the model. ProbWeighted = P_Bear×Bear + P_Base×Base + P_Bull×Bull on 16 high-leverage inputs (see row 2 weights, Section 13 doc at row 181).
A5: ID | B5: Assumption | C5: Bear | D5: Base | E5: Bull | F5: Active | G5: Tier | H5: Status | I5: Notes | J5: ProbWeighted
A7: Section 1: Revenue & Growth
A8: R3a | B8: 2025 Beginning Members (M) | C8: 1.5 | D8: 1.3 | E8: 1.1 | F8: =IF($B$3="Bear",C8,IF($B$3="Bull",E8,D8)) -> 1.3 | G8: Tier 3 | H8: High | I8: Back-solved to reconcile avg×ARPU ≈ $650M base. Bear slower decel; bull faster acquisition.
A9: R3b | B9: 2025 Ending Members (M) | C9: 2.3 | D9: 2.5 | E9: 2.7 | F9: =IF($B$3="Bear",C9,IF($B$3="Bull",E9,D9)) -> 2.5 | G9: Tier 1 | H9: Critical | I9: Series G press release: 2.5M+ paying members
A10: R3 | B10: 2025 Average Members (M) — DERIVED | C10: =(C8+C9)/2 -> 1.9 | D10: =(D8+D9)/2 -> 1.9 | E10: =(E8+E9)/2 -> 1.9 | F10: =IF($B$3="Bear",C10,IF($B$3="Bull",E10,D10)) -> 1.9 | G10: Derived | H10: Critical | I10: Per methodology: ARPU applies to AVERAGE members during period, NOT year-end.
A11: R4 | B11: 2025 Blended ARPU ($/yr) | C11: 270 | D11: =ARPU!D10 -> 274 | E11: 340 | F11: =IF($B$3="Bear",C11,IF($B$3="Bull",E11,D11)) -> 274 | G11: Tier 3 | H11: Critical | I11: Base linked to ARPU!D10 = $274 (year-specific bottoms-up: consumer 80% × $278 + Unite 20% × $260). 2026 steps to $307 (mature build w/ Labs + BP at 5% attach). Bear/Bull still hardcoded $ overrides — TODO: rebuild from tier-mix scenarios. See ARPU tab.
A12: R1 | B12: 2025 Recognized Revenue ($M) — DERIVED | C12: =C10*C11 -> 513 | D12: =D10*D11 -> 520.6 | E12: =E10*E11 -> 646 | F12: =IF($B$3="Bear",C12,IF($B$3="Bull",E12,D12)) -> 520.6 | G12: Derived | H12: Critical | I12: DERIVED: Avg Members × Blended ARPU. 2025 reconciles to $1.1B Series G run-rate as Dec exit-rate annualized, NOT full-year recognized. Gap = ramp through year (free-hardware pivot 9/2025). Memo material.
A13: R2 | B13: 2025 Bookings Run-Rate ($M) | C13: 1100 | D13: 1100 | E13: 1100 | F13: =IF($B$3="Bear",C13,IF($B$3="Bull",E13,D13)) -> 1100 | G13: Tier 1 | H13: Locked | I13: Series G press release; CEO statement (Dec 2025 exit-rate × 12). NOT full-year recognized — see I12 reconciliation note.
A14: R5 | B14: Subscription Revenue % | C14: 0.8 | D14: 0.85 | E14: 0.88 | F14: =IF($B$3="Bear",C14,IF($B$3="Bull",E14,D14)) -> 0.85 | G14: Tier 2 | H14: High | I14: Sacra/BMCT: ~80-88% range
A15: R6 | B15: 2025 YoY Subscription Growth | C15: 1.03 | D15: 1.03 | E15: 1.03 | F15: =IF($B$3="Bear",C15,IF($B$3="Bull",E15,D15)) -> 1.03 | G15: Tier 1 | H15: Locked | I15: Series G press release: 103%
A16: R7 | B16: Phase 1 Revenue Growth (2026-27) | C16: 0.5 | D16: 0.7 | E16: 0.9 | F16: =IF($B$3="Bear",C16,IF($B$3="Bull",E16,D16)) -> 0.7 | G16: Tier 3 | H16: Critical | I16: Peer trajectories; Series G deployment & WHOOP 5.0 cycle
A17: R8 | B17: Phase 2 Revenue Growth (2028-30) | C17: 0.15 | D17: 0.25 | E17: 0.4 | F17: =IF($B$3="Bear",C17,IF($B$3="Bull",E17,D17)) -> 0.25 | G17: Tier 3 | H17: Critical | I17: Deceleration shape: Dexcom (bull) / Netflix (base) / Peloton (bear)
A18: R9 | B18: Phase 3 Revenue Growth (2031-33) | C18: 0.05 | D18: 0.12 | E18: 0.2 | F18: =IF($B$3="Bear",C18,IF($B$3="Bull",E18,D18)) -> 0.12 | G18: Tier 3 | H18: High | I18: TAM ceiling; healthcare attach resolution
A19: R10a | B19: Year-1 Cohort Annual Churn | C19: 0.3 | D19: 0.22 | E19: 0.15 | F19: =IF($B$3="Bear",C19,IF($B$3="Bull",E19,D19)) -> 0.22 | G19: Tier 3 | H19: Critical | I19: Highest churn ("try and quit"). Will drive Members tab cohort engine.
A20: R10b | B20: Year-2 Cohort Annual Churn | C20: 0.18 | D20: 0.15 | E20: 0.1 | F20: =IF($B$3="Bear",C20,IF($B$3="Bull",E20,D20)) -> 0.15 | G20: Tier 3 | H20: Critical | I20: Stabilizing cohort
A21: R10c | B21: Year-3+ Cohort Annual Churn | C21: 0.12 | D21: 0.12 | E21: 0.05 | F21: =IF($B$3="Bear",C21,IF($B$3="Bull",E21,IF($B$3="ProbWeighted",J21,D21))) -> 0.12 | G21: Tier 3 | H21: Critical | I21: Retained core; very sticky power users | J21: =$C$2*C21+$E$2*D21+$G$2*E21 -> 0.099
A22: R12 | B22: B2B Unite Revenue % | C22: 0.12 | D22: 0.18 | E22: 0.25 | F22: =IF($B$3="Bear",C22,IF($B$3="Bull",E22,D22)) -> 0.18 | G22: Tier 2 | H22: Medium | I22: Sacra/BMCT: ~20% recurring revenue; growing rapidly
A23: R14 | B23: Advanced Labs Attach Rate | C23: 0.03 | D23: 0.1 | E23: 0.25 | F23: =IF($B$3="Bear",C23,IF($B$3="Bull",E23,D23)) -> 0.1 | G23: Tier 3 | H23: Critical | I23: BUCKET-3 THESIS VARIABLE. Bear/Base/Bull per methodology Sec 3. Single most important ARPU assumption — swings $80/member.
A24: R15 | B24: Labs Avg Test Price ($) | C24: 250 | D24: 300 | E24: 350 | F24: =IF($B$3="Bear",C24,IF($B$3="Bull",E24,D24)) -> 300 | G24: Tier 3 | H24: High | I24: WHOOP Advanced Labs site: $199-$599. Methodology base: $300.
A25: R16 | B25: Annual Price Inflation | C25: 0.02 | D25: 0.03 | E25: 0.04 | F25: =IF($B$3="Bear",C25,IF($B$3="Bull",E25,D25)) -> 0.03 | G25: Tier 3 | H25: Medium | I25: CPI + premium brand pricing power
A26: R18 | B26: 2026 Gross Adds (M) | C26: 1.5 | D26: 1.9 | E26: 2.3 | F26: =IF($B$3="Bear",C26,IF($B$3="Bull",E26,D26)) -> 1.9 | G26: Tier 3 | H26: Critical | I26: Methodology priors: 1.8-2.0M base. Members tab will use this; per-year gross adds modeled there. CAC × this = S&M consistency check.
A27: R19 | B27: Deferred Revenue Adjustment (% of bookings) | C27: -0.1 | D27: -0.08 | E27: -0.05 | F27: =IF($B$3="Bear",C27,IF($B$3="Bull",E27,D27)) -> -0.08 | G27: Tier 3 | H27: Medium | I27: Drag during growth (recognized < booked); ASC 606. Approaches 0 at steady state.
A29: Section 2: Cost Structure & Margins
A30: C1 | B30: Hardware BOM per Device ($) | C30: 100 | D30: 80 | E30: 60 | F30: =IF($B$3="Bear",C30,IF($B$3="Bull",E30,D30)) -> 80 | G30: Tier 3 | H30: Critical | I30: Est. $50-80 at scale; 2016 BOM was $250-300 per Contrary Research
A31: C2 | B31: Loaded Hardware Cost per Acquisition ($) | C31: 150 | D31: 120 | E31: 90 | F31: =IF($B$3="Bear",C31,IF($B$3="Bull",E31,D31)) -> 120 | G31: Tier 3 | H31: Critical | I31: C1 + assembly, ship, warranty, returns. Drives unit economics.
A32: C4 | B32: Subscription Delivery Cost (% of sub rev) | C32: 0.15 | D32: 0.1 | E32: 0.08 | F32: =IF($B$3="Bear",C32,IF($B$3="Bull",E32,D32)) -> 0.1 | G32: Tier 3 | H32: High | I32: Infra + support; AWS/GCP benchmarks; declining at scale
A33: C5 | B33: Subscription Gross Margin (standalone) | C33: 0.72 | D33: 0.78 | E33: 0.83 | F33: =IF($B$3="Bear",C33,IF($B$3="Bull",E33,D33)) -> 0.78 | G33: Tier 3 | H33: Critical | I33: Peer: pure SaaS ~80%, Dexcom ~64% (incl consumables). WHOOP higher quality recurring.
A34: C6 | B34: Hardware Gross Margin (standalone) | C34: -0.1 | D34: -0.02 | E34: 0.05 | F34: =IF($B$3="Bear",C34,IF($B$3="Bull",E34,D34)) -> -0.02 | G34: Tier 3 | H34: Critical | I34: Subsidized at acquisition; Peloton HW GM trajectory: -18% to +14%
A35: C7a | B35: Blended GM Phase 1 (2026-27) | C35: 0.56 | D35: 0.6 | E35: 0.64 | F35: =IF($B$3="Bear",C35,IF($B$3="Bull",E35,D35)) -> 0.6 | G35: Tier 3 | H35: High | I35: Phase 1 blended GM (legacy decomposed framework, pre-collapse to C7d). No longer drives the model post-ARPU simplification — retained for reference only.
A36: C7b | B36: Blended GM Phase 2 (2028-30) | C36: 0.63 | D36: 0.67 | E36: 0.72 | F36: =IF($B$3="Bear",C36,IF($B$3="Bull",E36,D36)) -> 0.67 | G36: Tier 3 | H36: High | I36: Margin expansion as growth decelerates
A37: C7c | B37: Blended GM Terminal | C37: 0.72 | D37: 0.76 | E37: 0.8 | F37: =IF($B$3="Bear",C37,IF($B$3="Bull",E37,D37)) -> 0.76 | G37: Tier 3 | H37: High | I37: Peer terminal: Dexcom 60%, Spotify 32%; software-heavy mix at scale
A38: C8a | B38: R&D % of Revenue (current) | C38: 0.25 | D38: 0.22 | E38: 0.2 | F38: =IF($B$3="Bear",C38,IF($B$3="Bull",E38,D38)) -> 0.22 | G38: Tier 3 | H38: High | I38: Peers: Dexcom 13%, Garmin 16%, growth SaaS 20-30%
A39: C8b | B39: R&D % of Revenue (terminal) | C39: 0.13 | D39: 0.16 | E39: 0.19 | F39: =IF($B$3="Bear",C39,IF($B$3="Bull",E39,IF($B$3="ProbWeighted",J39,D39))) -> 0.16 | G39: Tier 3 | H39: Medium | I39: Peer steady-state | J39: =$C$2*C39+$E$2*D39+$G$2*E39 -> 0.163
A40: C9 | B40: S&M % of Revenue (current) | C40: 0.35 | D40: 0.3 | E40: 0.25 | F40: =IF($B$3="Bear",C40,IF($B$3="Bull",E40,D40)) -> 0.3 | G40: Tier 3 | H40: Critical | I40: Peloton peak 28.4% FY22, current 16.9% FY25. Bear = stuck high.
A41: C9a | B41: Paid CAC per Gross Add ($) | C41: 220 | D41: 175 | E41: 130 | F41: =IF($B$3="Bear",C41,IF($B$3="Bull",E41,D41)) -> 175 | G41: Tier 3 | H41: Critical | I41: 30-50% of first-year ARPU. S&M consistency check on Checks tab.
A42: C9b | B42: Athlete/Brand Spend ($M/yr) | C42: 100 | D42: 60 | E42: 30 | F42: =IF($B$3="Bear",C42,IF($B$3="Bull",E42,D42)) -> 60 | G42: Tier 3 | H42: High | I42: Press, endorsement deals; non-paid S&M floor
A43: C9t | B43: x | C43: 0.2 | D43: 0.17 | E43: 0.15 | F43: =IF($B$3="Bear",C43,IF($B$3="Bull",E43,D43)) -> 0.17 | G43: Tier 3 | H43: High | I43: Peer steady-state: Garmin SG&A 14-19%
A44: C10 | B44: G&A % of Revenue (current) | C44: 0.18 | D44: 0.15 | E44: 0.12 | F44: =IF($B$3="Bear",C44,IF($B$3="Bull",E44,D44)) -> 0.15 | G44: Tier 3 | H44: Medium | I44: IPO step-up 200-300bps in 2027-28 (SOX, IR, legal)
A45: C10t | B45: G&A % of Revenue (terminal) | C45: 0.13 | D45: 0.11 | E45: 0.09 | F45: =IF($B$3="Bear",C45,IF($B$3="Bull",E45,IF($B$3="ProbWeighted",J45,D45))) -> 0.11 | G45: Tier 3 | H45: Medium | I45: Peer steady-state | J45: =$C$2*C45+$E$2*D45+$G$2*E45 -> 0.108
A46: C11a | B46: SBC % of Revenue (current, 2026 pre-IPO peak) | C46: 0.16 | D46: 0.14 | E46: 0.12 | F46: =IF($B$3="Bear",C46,IF($B$3="Bull",E46,IF($B$3="ProbWeighted",J46,D46))) -> 0.14 | G46: Tier 3 | H46: High | I46: Peloton: 9.2% FY25; pre-IPO typically higher. SBC is REAL COST in FCF. | J46: =$C$2*C46+$E$2*D46+$G$2*E46 -> 0.138
A47: C11b | B47: SBC % of Revenue (terminal, 2033 post-IPO normalized) | C47: 0.13 | D47: 0.11 | E47: 0.08 | F47: =IF($B$3="Bear",C47,IF($B$3="Bull",E47,IF($B$3="ProbWeighted",J47,D47))) -> 0.11 | G47: Tier 3 | H47: High | I47: Methodology Sec 6: SBC normalizes to 6-10% post-IPO. Linear taper from F47 (current) to F48 (terminal) by 2033. | J47: =$C$2*C47+$E$2*D47+$G$2*E47 -> 0.105
A48: C13 | B48: CapEx % of Revenue | C48: 0.05 | D48: 0.04 | E48: 0.03 | F48: =IF($B$3="Bear",C48,IF($B$3="Bull",E48,IF($B$3="ProbWeighted",J48,D48))) -> 0.04 | G48: Tier 3 | H48: Medium | I48: Asset-light; contract manufacturing | J48: =$C$2*C48+$E$2*D48+$G$2*E48 -> 0.039
A49: C16 | B49: NWC % of Incremental Revenue | C49: -0.05 | D49: -0.08 | E49: -0.1 | F49: =IF($B$3="Bear",C49,IF($B$3="Bull",E49,D49)) -> -0.08 | G49: Tier 3 | H49: High | I49: Negative = WC benefit (deferred rev > inventory drag during growth)
A50: C17 | B50: Advanced Labs COGS % | C50: 0.7 | D50: 0.65 | E50: 0.6 | F50: =IF($B$3="Bear",C50,IF($B$3="Bull",E50,D50)) -> 0.65 | G50: Tier 3 | H50: High | I50: Quest/Labcorp panel margins ~30-40%; bucket-3 sensitivity
A51: C15 | B51: Tax Rate (effective) | C51: 0.25 | D51: 0.23 | E51: 0.21 | F51: =IF($B$3="Bear",C51,IF($B$3="Bull",E51,IF($B$3="ProbWeighted",J51,D51))) -> 0.23 | G51: Tier 2 | H51: Medium | I51: US statutory; intl mix-shift lowers over time | J51: =$C$2*C51+$E$2*D51+$G$2*E51 -> 0.228
A52: C12 | B52: D&A % of Revenue | C52: 0.045 | D52: 0.035 | E52: 0.025 | F52: =IF($B$3="Bear",C52,IF($B$3="Bull",E52,D52)) -> 0.035 | G52: Tier 2 | H52: Medium | I52: Capex amortization; lower in mature stages as growth slows. Restored after styling pass clobbered row.
A53: Section 3: Capital Structure & Cap Table (incl. cash yield)
A54: S1 | B54: Fully Diluted Shares Outstanding (M) | C54: 420 | D54: 410 | E54: 400 | F54: =IF($B$3="Bear",C54,IF($B$3="Bull",E54,D54)) -> 410 | G54: Tier 3 | H54: Critical | I54: 361.2M common + ~50M option pool est. Pitchbook auth pref 537.9M, outs 361.2M.
A55: S2 | B55: Series G Price per Share ($) | C55: 28 | D55: 28 | E55: 28 | F55: =IF($B$3="Bear",C55,IF($B$3="Bull",E55,D55)) -> 28 | G55: Tier 2 | H55: High | I55: Pitchbook Series G data; back-solve from $575M raise / shares issued
A56: S3 | B56: Liquidation Preference Type | C56: Participating | D56: 1x non-participating | E56: 1x non-participating | F56: =IF($B$3="Bear",C56,IF($B$3="Bull",E56,D56)) -> 1x non-participating | G56: Tier 2 | H56: Locked | I56: Pitchbook: 1x non-participating pari passu. Bear assumes participating ratchet.
A57: S4 | B57: Total Liquidation Preference ($M) | C57: 1400 | D57: 1400 | E57: 1400 | F57: =IF($B$3="Bear",C57,IF($B$3="Bull",E57,D57)) -> 1400 | G57: Tier 2 | H57: High | I57: Sum of preferred raises: ~$1.4B aggregate (Series A through G)
A58: S7 | B58: Option Pool Size (% of FD shares) | C58: 0.15 | D58: 0.12 | E58: 0.1 | F58: =IF($B$3="Bear",C58,IF($B$3="Bull",E58,D58)) -> 0.12 | G58: Tier 3 | H58: High | I58: Typical 10-15% pre-IPO; 600-person hiring surge implies aggressive granting
A59: S8 | B59: Founder Ownership Ahmed (% FD) | C59: 0.1 | D59: 0.14 | E59: 0.18 | F59: =IF($B$3="Bear",C59,IF($B$3="Bull",E59,D59)) -> 0.14 | G59: Tier 3 | H59: Medium | I59: 12-18% est. across 7 rounds + pool refreshes; possibly lower with secondaries
A60: S9 | B60: DLOM (Discount for Lack of Marketability) | C60: 0.3 | D60: 0.22 | E60: 0.15 | F60: =IF($B$3="Bear",C60,IF($B$3="Bull",E60,D60)) -> 0.22 | G60: Tier 2 | H60: High | I60: Oura tender 25%; EquityZen avg 13-29%; Hiive 39-51% deeper discount
A61: S10 | B61: Debt on Balance Sheet ($M) | C61: 50 | D61: 10 | E61: 0 | F61: =IF($B$3="Bear",C61,IF($B$3="Bull",E61,D61)) -> 10 | G61: Tier 2 | H61: Low | I61: Likely minimal/zero; Pitchbook shows $10.13M debt round Mar 2024
A62: S11 | B62: Cash post Series G ($M) | C62: 500 | D62: 700 | E62: 850 | F62: =IF($B$3="Bear",C62,IF($B$3="Bull",E62,D62)) -> 700 | G62: Tier 3 | H62: Medium | I62: Back-solve: $575M raise + operating cash flow positive entering 2026
A63: S12 | B63: EV-to-Equity Bridge ($M) — DERIVED | C63: =C62-C61 -> 450 | D63: =D62-D61 -> 690 | E63: =E62-E61 -> 850 | F63: =IF($B$3="Bear",C63,IF($B$3="Bull",E63,D63)) -> 690 | G63: Derived | H63: High | I63: Cash − Debt: add to EV to bridge to equity value
A64: S15 | B64: Series F Ratchet / IPO Provisions | C64: Live | D64: Likely extinguished | E64: Extinguished | F64: =IF($B$3="Bear",C64,IF($B$3="Bull",E64,D64)) -> Likely extinguished | G64: Tier 3 | H64: High | I64: Likely extinguished at Series G close; SoftBank notably absent from Series G syndicate
A65: S16
A66: C18 | B66: Cash money-market yield (interest income on idle balance) | C66: 0.025 | D66: 0.035 | E66: 0.045 | F66: =IF($B$3="Bear",C66,IF($B$3="Bull",E66,D66)) -> 0.035 | G66: Tier 2 | H66: Medium | I66: Yield on idle Series G cash. Apply to PRIOR-YEAR ending cash balance to avoid circularity (no feedback into current year cash).
A67: Section 4: WACC / Discount Rate (Damodaran Apr 2026)
A68: D1 | B68: Risk-Free Rate (10yr UST) | C68: 0.043 | D68: 0.043 | E68: 0.043 | F68: =IF($B$3="Bear",C68,IF($B$3="Bull",E68,D68)) -> 0.043 | G68: Tier 1 | H68: Locked | I68: Fed H.15, Apr 14 2026: 4.26%; rounded 4.3%
A69: D2 | B69: Equity Risk Premium | C69: 0.045 | D69: 0.045 | E69: 0.045 | F69: =IF($B$3="Bear",C69,IF($B$3="Bull",E69,D69)) -> 0.045 | G69: Tier 1 | H69: Point Est. | I69: Damodaran 4.23% (Jan 2026); Kroll 5.0%; midpoint 4.5%
A70: D3 | B70: Unlevered Beta (bucket-weighted) | C70: 0.85 | D70: 0.83 | E70: 0.81 | F70: =IF($B$3="Bear",C70,IF($B$3="Bull",E70,D70)) -> 0.83 | G70: Tier 1 | H70: Sensitivity | I70: Damodaran sector: Healthcare 0.83, Electronics 0.83. Bucket-weighted.
A71: D4 | B71: Size Premium | C71: 0.0081 | D71: 0.0081 | E71: 0.0081 | F71: =IF($B$3="Bear",C71,IF($B$3="Bull",E71,D71)) -> 0.0081 | G71: Tier 2 | H71: Point Est. | I71: Kroll CRSP Decile 3 ($7.3-13.5B): 0.81%
A72: D5 | B72: Company-Specific Risk Premium (CSRP) | C72: 0.03 | D72: 0.02 | E72: 0.01 | F72: =IF($B$3="Bear",C72,IF($B$3="Bull",E72,D72)) -> 0.02 | G72: Tier 3 | H72: Sensitivity | I72: Pre-IPO execution risk + private illiquidity; 1-3% range
A73: D8 | B73: Implied Cost of Equity / WACC — DERIVED | C73: =C68+C69*C70+C71+C72 -> 0.11935 | D73: =D68+D69*D70+D71+D72 -> 0.10845 | E73: =E68+E69*E70+E71+E72 -> 0.09755 | F73: =IF($B$3="Bear",C73,IF($B$3="Bull",E73,IF($B$3="ProbWeighted",J73,D73))) -> 0.10845 | G73: Derived | H73: Critical
B74: Bottoms Up WACC | C74: ='WACC Bottom-Up'!E106 -> 0.12175651 | D74: 0.11587449 | E74: ='WACC Bottom-Up'!G106 -> 0.11003837 | F74: =IF($B$3="Bear",C74,IF($B$3="Bull",E74,IF($B$3="ProbWeighted",J74,D74))) -> 0.11587449 | J74: =$C$2*C74+$E$2*D74+$G$2*E74 -> 0.11530006
A75: Section 5: Terminal Value
A76: D9 | B76: Terminal Method (primary) | C76: Exit Multiple | D76: Exit Multiple | E76: Exit Multiple | F76: =IF($B$3="Bear",C76,IF($B$3="Bull",E76,D76)) -> Exit Multiple | G76: Design | H76: Locked | I76: Primary: EV/Revenue exit multiple; cross-check: Gordon Growth
A77: D11 | B77: Terminal EV/Revenue Multiple | C77: 3 | D77: 3.5 | E77: 4.5 | F77: =IF($B$3="Bear",C77,IF($B$3="Bull",E77,IF($B$3="ProbWeighted",J77,D77))) -> 3.5 | G77: Tier 3 | H77: Critical | I77: Compressed 40-60% from current comps; reflects terminal growth 10-15% | J77: =$C$2*C77+$E$2*D77+$G$2*E77 -> 3.7
A78: D12 | B78: Terminal EV/EBITDA Multiple | C78: 12 | D78: 15 | E78: 18 | F78: =IF($B$3="Bear",C78,IF($B$3="Bull",E78,D78)) -> 15 | G78: Tier 3 | H78: High | I78: Cross-check only; more stable than revenue multiple at maturity
A79: D13 | B79: Perpetuity Growth Rate (Gordon) | C79: 0.025 | D79: 0.03 | E79: 0.035 | F79: =IF($B$3="Bear",C79,IF($B$3="Bull",E79,D79)) -> 0.03 | G79: Tier 2 | H79: Critical | I79: GDP growth + inflation; cannot exceed WACC
A80: D28 | B80: Multiple Compression Factor | C80: 0.4 | D80: 0.5 | E80: 0.6 | F80: =IF($B$3="Bear",C80,IF($B$3="Bull",E80,D80)) -> 0.5 | G80: Tier 3 | H80: High | I80: Terminal multiples 40-60% lower than current comps. Applied to derive D11.
A82: Section 6: Comp Bucket Weighting — THIS IS THE THESIS
A83: V11a | B83: Bucket 1 Weight (Consumer Hardware — Garmin) | C83: 0.4 | D83: 0.2 | E83: 0.1 | F83: =IF($B$3="Bear",C83,IF($B$3="Bull",E83,D83)) -> 0.2 | G83: Design | H83: Critical | I83: Higher = more bearish (WHOOP as hardware company)
A84: V11b | B84: Bucket 2 Weight (Consumer Subscription — PTON/SPOT) | C84: 0.4 | D84: 0.4 | E84: 0.3 | F84: =IF($B$3="Bear",C84,IF($B$3="Bull",E84,D84)) -> 0.4 | G84: Design | H84: Critical | I84: Peloton-Spotify range disaggregated; where does WHOOP sit?
A85: V11c | B85: Bucket 3 Weight (Health Data — DXCM/RMD/MASI/IRTC) | C85: 0.2 | D85: 0.4 | E85: 0.6 | F85: =IF($B$3="Bear",C85,IF($B$3="Bull",E85,D85)) -> 0.4 | G85: Design | H85: Critical | I85: Higher = healthcare thesis is believed; Series G implied ~70%
A86: V11_chk | B86: Bucket Weights Sum (must = 100%) | C86: =C83+C84+C85 -> 1 | D86: =D83+D84+D85 -> 1 | E86: =E83+E84+E85 -> 1 | F86: =IF($B$3="Bear",C86,IF($B$3="Bull",E86,D86)) -> 1 | G86: Derived | H86: Check | I86: Sanity check: bucket weights must sum to 100%
A88: Section 7: IPO Trading Range & Discount Framework
A89: I1 | B89: IPO Timing (months from Series G) | C89: 18 | D89: 15 | E89: 12 | F89: =IF($B$3="Bear",C89,IF($B$3="Bull",E89,D89)) -> 15 | G89: Tier 2 | H89: High | I89: Q2 2027 - Q1 2028; "last private round" per Ahmed
A90: I2 | B90: IPO Pricing Discount (to Stage 1 fair value) | C90: 0.25 | D90: 0.2 | E90: 0.15 | F90: =IF($B$3="Bear",C90,IF($B$3="Bull",E90,D90)) -> 0.2 | G90: Tier 2 | H90: Critical | I90: Loughran/Ritter IPO pricing studies; 15-25% standard
A91: I3
A92: I4 | B92: Series G Investor Required IRR | C92: 0.3 | D92: 0.25 | E92: 0.2 | F92: =IF($B$3="Bear",C92,IF($B$3="Bull",E92,D92)) -> 0.25 | G92: Tier 3 | H92: Medium | I92: Late-stage growth equity return expectations (3-5yr hold)
A93: I5a | B93: Implied Stage 1 Public Fair Value ($M) — IRR Backsolve (DEPRECATED, replaced by row 94) | F93: =IF($B$3="Bear",C93,IF($B$3="Bull",E93,D93)) -> 0 | G93: Derived | H93: Critical | I93: Back-solve: $10.1B / (1-illiquidity) / (1-IPO discount) → $13-15B target
A94: I5b | B94: Implied IPO Range ($M) — Reference Class Step-Up (live) | C94: ='Football Field'!D61*1000 -> 13242.222 | D94: ='Football Field'!D62*1000 -> 14690.909 | E94: ='Football Field'!D63*1000 -> 19713.253 | F94: =IF($B$3="Bear",C94,IF($B$3="Bull",E94,D94)) -> 14690.909 | G94: Derived | H94: Critical
A95: Section 8: Precedent Transactions
A96: P1 | B96: Deal Inclusion Window | C96: Last 5 years | D96: Last 5 years | E96: Last 5 years | F96: =IF($B$3="Bear",C96,IF($B$3="Bull",E96,D96)) -> Last 5 years | G96: Design | H96: Locked | I96: 2021-2026 with 3-year primary focus
A97: P3 | B97: Deal Size Threshold ($M EV) | C97: 500 | D97: 500 | E97: 500 | F97: =IF($B$3="Bear",C97,IF($B$3="Bull",E97,D97)) -> 500 | G97: Design | H97: Locked | I97: Below this, synergy math distorts multiples
A98: P5 | B98: Multiple Extraction Method | C98: EV/LTM Rev | D98: EV/LTM Rev | E98: EV/LTM Rev | F98: =IF($B$3="Bear",C98,IF($B$3="Bull",E98,D98)) -> EV/LTM Rev | G98: Design | H98: Locked | I98: EV / LTM revenue at announcement; NTM where available
A99: P_b1 | B99: Bucket 1 Precedent Multiple (median) | C99: 1 | D99: 1.5 | E99: 2.5 | F99: =IF($B$3="Bear",C99,IF($B$3="Bull",E99,D99)) -> 1.5 | G99: Tier 2 | H99: High | I99: Fitbit/Google ~1.3x; Garmin tuck-ins; mostly distressed exits
A100: P_b2 | B100: Bucket 2 Precedent Multiple (median) | C100: 0.8 | D100: 1.5 | E100: 3 | F100: =IF($B$3="Bear",C100,IF($B$3="Bull",E100,D100)) -> 1.5 | G100: Tier 2 | H100: High | I100: Peloton/Precor; connected fitness all value-destructive
A101: P_b3 | B101: Bucket 3 Precedent Multiple (median) | C101: 6 | D101: 8 | E101: 10 | F101: =IF($B$3="Bear",C101,IF($B$3="Bull",E101,D101)) -> 8 | G101: Tier 2 | H101: High | I101: Per research/precedent-transactions.md: B3 medtech 6.6-10.1x range
A103: Section 9: Real Options — see rows 154-161 (binary-gate redesign, supersedes cluster framework)
A104: Healthcare reimbursement pathway is the only separately-valued real option. International, B2B, women's health, glucose moved to base case sensitivities or dropped. Inputs: RO1 (probability), RO2 (eligibility %), RO3 (payer ARPU), RO4 (multiple), RO5 (years). See RealOptions tab Section 5 for full justification.
A106: Legend & Conventions
A107: Blue text | B107: Hard-coded input
...

Sheet Member Thesis
A1: WHOOP — Member Trajectory Triangulation (Four-Lens Framework)
A2: Four independent lenses converge on a 2033 ending member range. Each lens uses a different methodology; convergence is emergent, not curve-fit. Median feeds Trajectory Build (Oura-shape calibrated). Triangulation distance vs live model = audit check (±15% target).
A4: 1. Member Anchors
H5: Bull 18.0M decomposition
A6: 2025E starting members (M) | B6: 2.5
A7: ARPU ($/yr) | B7: =Assumptions!F11 -> 274 | H7: Channel | I7: 2033 Members | J7: Anchor
A8: Series G post-money valuation ($M) | B8: 1100 | H8: Consumer-only ceiling | I8: 12.0M | J8: Median of Apple Watch / Oura / Garmin lenses (consumer-organic)
A9: Series G implied $/share ($) | B9: 24.63 | H9: Clinical channel pull | I9: 4.5M | J9: RPM-eligible Medicare population (~30M) × ~15% WHOOP capture rate
A10: DCF base $/share (live model) | B10: =DCF!C40 -> 17.855007 | H10: Employer health plans | I10: 1.5M | J10: Corporate wellness scaling; Aetna pilot trajectory
H11: Total Bull | I11: 18.0M | J11: Reflects healthcare-driven TAM expansion
A12: 2. Convergence Summary
A13: Each lens uses an independent methodology. Convergence is emergent, not curve-fit. Median feeds Trajectory Build. ✓ = within ±15% of median; ⚠ = 15-25%; ✗ = >25%. | M13: Methodology
M14: TAM 25M × 6%/yr growth × 30% terminal share. Apple-style category-defining product precedent.
A15: Lens | B15: 2033 End (M) | C15: Δ vs Median | D15: Status | M15: Peloton Connected Fitness subs IPO+10 hypothetical × free-hardware advantage × ARPU drag.
A16: Lens A — TAM × Terminal Share | B16: =B30 -> 11.953861 | C16: =B16/$B$20-1 -> 0.094960645 | D16: =IF(ABS(C16)<=0.15,"✓",IF(ABS(C16)<=0.25,"⚠","✗")) -> ✓ | M16: Median of three independently-derived comp endpoints (Apple Watch shape / Oura forward-extrap / Garmin timeline-compressed).
A17: Lens B — Peloton Stage-Shifted Comp | B17: =B43 -> 11.20932 | C17: =B17/$B$20-1 -> 0.026761539 | D17: =IF(ABS(C17)<=0.15,"✓",IF(ABS(C17)<=0.25,"⚠","✗")) -> ✓ | M17: Cumulative S&M $ ÷ weighted CAC, less churn drag. Capital-bounded floor.
A18: Lens C — Apple/Oura/Garmin Triangulation | B18: =B67 -> 10.625 | C18: =B18/$B$20-1 -> -0.026761539 | D18: =IF(ABS(C18)<=0.15,"✓",IF(ABS(C18)<=0.25,"⚠","✗")) -> ✓ | M18: COV across the four lenses; flags whether triangulation is tight enough to feed Trajectory Build.
A19: Lens D — SAM/SOM Bottoms-Up | B19: =B78 -> 8.379 | C19: =B19/$B$20-1 -> -0.2324927 | D19: =IF(ABS(C19)<=0.15,"✓",IF(ABS(C19)<=0.25,"⚠","✗")) -> ⚠
A20: → Median across lenses | B20: =MEDIAN(B16:B19) -> 10.91716 | C20: =STDEV(B16:B19)/B20 -> 0.14115473 | D20: =IF(C20<0.1,"✓ tight",IF(C20<0.2,"⚠ wide","✗ diverge")) -> ⚠ wide
A22: 3. Lens A — TAM × Terminal Share
A23: Lens character — aggressive, assumption-heavy
A24: Premium continuous physiological monitoring at $200-400/yr WTP. Apple-at-30%-smartphone-share precedent supports 25-45% terminal share for category-defining product. Highest output of the four lenses — most upside-leaning by construction.
A26: Input | B26: Value | C26: Note | D26: Source
A27: TAM 2025 (M) | B27: 25 | C27: Premium continuous monitoring; ~130M US adults × $200-400/yr WTP filter ≈ 20-30M globally. | D27: mHealth Intelligence (2023). Oura+WHOOP combined ~4.5M paying 2025 = ~18% penetration of WTP filter.
A28: TAM growth rate (%/yr) | B28: 0.06 | C28: Conservative vs broader wearable CAGR 12-16%. | D28: MarketsandMarkets ($84.5B→$176.8B, 15.9% CAGR). Grand View Research ($92.9B→$230B by 2033, 12.1% CAGR).
A29: Terminal share 2033 (%) | B29: 0.3 | C29: Apple precedent: 30% global smartphone share. WHOOP at 25-30% in defined WTP TAM defensible. | D29: IDC: Oura already >80% smart ring share (2024). Apple smartphone share precedent for category-defining products.
A30: → Implied 2033 ending (M) | B30: =B27*((1+B28)^8)*B29 -> 11.953861 | C30: = TAM 2025 × (1 + growth)⁸ × terminal share | D30: TAM 2033 = 25 × 1.06⁸ ≈ 39.8M.
A32: 4. Lens B — Peloton Stage-Shifted Comp
A33: Lens character — base, structural analogue
A34: WHOOP at 2.5M pre-IPO ≈ Peloton at IPO+2 (~2.6M CF subs end-2020). WHOOP 2033 ≈ Peloton IPO+10 hypothetical extrapolation, adjusted for free-hardware advantage and ARPU drag. | M34: Source
M35: Peloton 10-K FY2019.
A36: Input | B36: Value | C36: Note | M36: Peloton 10-K FY2021.
A37: Peloton CF subs at IPO (Sep 2019) | B37: 0.563 | C37: 10-K FY2019 disclosed Connected Fitness Subscribers. | M37: Peloton 10-K FY2023.
A38: Peloton CF subs IPO+2 (FY2021) | B38: 2.49 | C38: Peak; aligns roughly with WHOOP 2025 anchor of 2.5M. | M38: Spec: extrapolated curve.
A39: Peloton CF peak (FY2023) | B39: 3.08 | C39: Peloton stalled ~3M post-COVID unwind — not a clean 8yr extrapolation, useful floor. | M39: Industry data on hardware-cost elasticity in subscription conversion.
A40: Stage-shifted base case 8yr ahead (M) | B40: 10.7 | C40: Hypothetical Peloton trajectory absent COVID unwind: 4x stage-2 base. Industry S-curve anchored. | M40: Peloton ARPU/churn comp; WHOOP retention disclosure.
A41: Free-hardware acquisition advantage (×) | B41: 1.08 | C41: WHOOP $0 hw vs Peloton $2k bike unlocks step-fn in trial-to-paid; +5-10% sustained gross adds. | M41: = 10.7 × 1.08 × 0.97 = 11.21M.
A42: Lower ARPU drag (marketing capacity, ×) | B42: 0.97 | C42: WHOOP $307 ARPU vs Peloton $500: less CAC headroom but offset by lower churn (12% vs 24%).
A43: → Implied 2033 ending (M) | B43: =B40*B41*B42 -> 11.20932 | C43: = stage-shifted base × free-hw advantage × ARPU drag
A45: 5. Lens C — Comps Triangulation
A46: Lens character — base, methodologically strongest (3 independent paths converge within 3%)
A47: Three independently-derived 2033 endpoints, each using a different analytical method. Apple Watch shape-projects from a smaller scale-anchored base. Oura forward-extrapolates from current trajectory. Garmin compresses a 12-year timeline to 8 years. Convergence is emergent, not curve-fit.
A49: 5a. Apple Watch — Shape Projection | E49: 5b. Oura — Forward Extrapolation | I49: 5c. Garmin — Timeline Compression
A50: Stage-shift WHOOP 2.5M to AW 2017 (10M base), apply AW 8yr multiple, TAM-adjust. | E50: Forward-extrapolate WHOOP 2M anchor with Oura-style decel curve (50/40/30/22/17/13/10/8% YoY). | I50: Compress Garmin's 12yr to ~8yr (digital CAC), TAM-expand, premium-tier offset.
A52: Input | B52: Value | C52: Note | E52: Input | F52: Value | G52: Note | I52: Input | J52: Value | K52: Note
A53: AW base 2017 (M) | B53: 10 | C53: Counterpoint Research / analyst consensus. | E53: WHOOP 2025 anchor (M) | F53: 2 | G53: Conservative; Series G implies 2.4-2.5M. | I53: Garmin yrs to stable wearable subs | J53: 12 | K53: Garmin Fitness segment scale (2008-2020).
A54: AW base 2025 (M) | B54: 170 | C54: Counterpoint/IDC midpoint of 150-200M cumulative shipments through 2025. | E54: 8yr compounded multiple | F54: =(1.5)*(1.4)*(1.3)*(1.22)*(1.17)*(1.13)*(1.1)*(1.08) -> 5.2312229 | G54: = ∏(1+rates) for the 8 YoY values (50/40/30/22/17/13/10/8%). | I54: Garmin terminal premium subs (M) | J54: 10 | K54: Mid-tier wearables active subs base.
A55: 8yr growth multiple | B55: =B54/B53 -> 17 | C55: = 170 / 10 = 17x. | I55: Compression factor (digital-native) | J55: 0.8 | K55: $0 hardware + mandatory sub vs. $300-900 upfront. 80% of Garmin timeline.
A56: WHOOP 2025 anchor (M) | B56: 2.5 | C56: Stage-matched to AW 2017 (4x scale). | I56: TAM expansion factor (2025→2033) | J56: 1.2 | K56: Wearable TAM grows ~20% over 8yrs.
A57: Raw projected 2033 (M) | B57: =B56*B55 -> 42.5 | C57: WHOOP × AW multiple. | I57: Premium-tier offset (subset adj) | J57: 0.9 | K57: Narrower TAM offset by higher retention. 90% of Garmin terminal.
A58: TAM adjustment | B58: 4 | C58: AW 50% buyers vs WHOOP 5-7%; offset for stickiness.
A60: → Apple endpoint (M) | B60: =B57/B58 -> 10.625 | C60: = raw ÷ TAM adj | E60: → Oura endpoint (M) | F60: =F53*F54 -> 10.462446 | G60: = anchor × 8yr mult | I60: → Garmin endpoint (M) | J60: =J54*J56*J57 -> 10.8 | K60: = terminal × TAM × offset
A62: 5d. Lens C Synthesis
A64: Method | B64: Apple | C64: Oura | D64: Garmin | E64: Median | F64: Range
A65: 2033 Endpoint (M) | B65: =B60 -> 10.625 | C65: =F60 -> 10.462446 | D65: =J60 -> 10.8 | E65: =MEDIAN(B65:D65) -> 10.625 | F65: =MAX(B65:D65)-MIN(B65:D65) -> 0.33755425
A67: → Lens C endpoint (M) | B67: =E65 -> 10.625 | C67: = median of 3 methods. Range 0.34M (±3%); convergence is emergent.
A69: 6. Lens D — SAM/SOM Bottoms-Up
A70: Lens character — disciplined floor, most defensible
A71: TAM → SAM → SOM stack. Most conservative lens (8.39M) by design — disciplined market sizing without comp-borrowed shape assumptions. Acts as floor of the four-lens range, not point estimate.
A73: Input | B73: Value | C73: Note | M73: Source
A74: Global TAM — health-conscious consumers (M) | B74: 3500 | C74: Global adults w/ disposable income + health interest. | M74: Pew Research / McKinsey wellness reports.
A75: SAM — premium continuous-biometric subscribers | B75: 245 | C75: Variable + brand allocated. P1 ~$200, P2 ~$240, P3 ~$300; weighted by gross-adds shape. | M75: 7% TAM penetration. Excludes occasional users; targets WTP $25+/mo.
A76: SOM share — WHOOP capture | B76: 0.15 | C76: Steady-state blended; cohort mix shifts to Y3+ over time. | M76: Premium positioning between AW (volume) and Oura (style/wellness).
A77: Maturity factor — 2033 penetration of theoretical max | B77: 0.228 | C77: Approx midpoint 2.5M start → ~11M end. Penetration ramps; 2033 ~23% of full saturation (2040+). | M77: Theoretical max 36.75M (SAM × SOM share) — long-term ceiling, not 2033 expectation.
A78: → Lens D bottoms-up endpoint (M) | B78: =B75*B76*B77 -> 8.379 | C78: = SAM × SOM share × maturity factor. Conservative by construction — floor of the four-lens range. | M78: = 245 × 15% × 22.8% = 8.379M.
A80: 7. Composite Span (across all four lenses)
A82: Lowest defensible (Lens D — SAM/SOM floor) | B82: =MIN(B16:B19) -> 8.379 | C82: Disciplined bottoms-up; comp-shape free.
A83: Highest defensible (Lens A — TAM × share) | B83: =MAX(B16:B19) -> 11.953861 | C83: Top-down; assumption-heavy ceiling.
A84: Most defensible base (lens median) | B84: =B20 -> 10.91716 | C84: Trajectory Build is calibrated to land here.
A85: Span (range across lenses) | B85: =B83-B82 -> 3.5748606 | C85: Span 3.6M = Lens D floor to Lens A ceiling.
A87: 8. Trajectory Build — Oura-Shape Calibrated to Lens Median
A88: Anchors: 2.5M start (2025) → lens median (B20). Shape borrowed from Oura forward-extrapolation (5b): aggressive Y1–2 reflecting unconverted-demand punch (free hardware + GLP-1/CGM/employer wellness tailwinds), decelerating to single-digits as TAM saturates. Per-year rate scaled by k so compounded endpoint matches lens median.
A90: Year | B90: 2025E | C90: 2026E | D90: 2027E | E90: 2028E | F90: 2029E | G90: 2030E | H90: 2031E | I90: 2032E | J90: 2033E | K90: CAGR
A91: Raw Oura shape (%) | C91: 0.5 | D91: 0.38 | E91: 0.26 | F91: 0.19 | G91: 0.14 | H91: 0.11 | I91: 0.08 | J91: 0.06
A92: Calibration multiplier k | B92: 0.9781 | C92: Hardcoded multiplier on raw growth rates so compounded endpoint = lens median
A93: Members (M), end of year | B93: 2.5 | C93: =B93*(1+C$91*$B$92) -> 3.722625 | D93: =C93*(1+D$91*$B$92) -> 5.1062428 | E93: =D93*(1+E$91*$B$92) -> 6.404791 | F93: =E93*(1+F$91*$B$92) -> 7.595051 | G93: =F93*(1+G$91*$B$92) -> 8.6350717 | H93: =G93*(1+H$91*$B$92) -> 9.5641277 | I93: =H93*(1+I$91*$B$92) -> 10.312502 | J93: =I93*(1+J$91*$B$92) -> 10.917701 | K93: =(J93/B93)^(1/8)-1 -> 0.20233059
A94: Calibrated YoY % | C94: =C93/B93-1 -> 0.48905 | D94: =D93/C93-1 -> 0.371678 | E94: =E93/D93-1 -> 0.254306 | F94: =F93/E93-1 -> 0.185839 | G94: =G93/F93-1 -> 0.136934 | H94: =H93/G93-1 -> 0.107591 | I94: =I93/H93-1 -> 0.078248 | J94: =J93/I93-1 -> 0.058686
A96: 9. Cross-Checks vs Live Model
A97: Audit chain: lens median → trajectory build → live Assumptions Base → DCF. Distance metric should be <±15% to confirm triangulation holds.
A99: Cross-check | B99: Members (M) | C99: Note
A100: Live Base (Assumptions!F178) | B100: =Assumptions!F176 -> 10.924108 | C100: Live model Base scenario, compounded ending.
A101: Lens median (B20) | B101: =B20 -> 10.91716 | C101: Triangulated four-lens median — the target.
A102: Trajectory build endpoint (J93) | B102: =J93 -> 10.917701 | C102: Calibrated endpoint (k=0.9781).
A103: → Distance (Live vs Triangulation) | B103: =B100/B101-1 -> 0.00063643908 | C103: ✓ Triangulated within tolerance (target: ±15%).
A105: 10. Series G Back-Solve Diagnostic
A106: What member trajectory does Series G $24.63/sh imply? Compare to four-lens triangulation to see how far above the lens range Series G prices.
A108: Metric | B108: Value | C108: Note
A109: Series G $/sh | B109: =B9 -> 24.63 | C109: From Member Anchors (B9).
A110: DCF base $/sh (lens median trajectory) | B110: =B10 -> 17.855007 | C110: From Member Anchors (B10) — live link to DCF C40.
A111: Series G premium to DCF base | B111: =B109/B110-1 -> 0.379445 | C111: Series G prices in members beyond the lens range OR upside on margins / pricing / multiples.
A112: Implied 2033 members at Series G (proxy) | B112: =B101*(B109/B110) -> 15.059622 | C112: First-order linear scaling: lens median × (Series G / DCF). Approximate — ignores nonlinearity in margin/scale.
A113: → Implied vs Lens A ceiling (max defensible) | B113: =B112/B83-1 -> 0.2598124 | C113: If positive: Series G prices in members beyond what any lens defends.
A115: 11. Key Findings (carry to memo)
A117: 1. Four lenses converge tightly (median 10.92M, COV 14%). Three of four lenses sit within ±3% of the median; only Lens D's bottoms-up SAM/SOM (8.38M) drags the range. Convergence is emergent — each lens uses an independent methodology, none is calibrated to the others.
A118: 2. Lens C (comps triangulation) is the methodologically strongest single lens. Three sub-methods (Apple Watch shape projection, Oura forward extrapolation, Garmin timeline compression) land within 0.34M (±3%) of each other — the tightest internal consistency of any lens.
A119: 3. Lens D anchors the bear floor at 8.38M. Disciplined bottoms-up sizing (TAM→SAM→SOM) without comp-borrowed shape. The 14% COV across lenses is wide because Lens D pulls down — not because the upside lenses disagree.
A120: 4. Trajectory build calibrates exactly to lens median. Oura-shape decel curve scaled by k=0.9781 lands the 8-year compounded endpoint at 10.92M. Implied CAGR 20.2% — aggressive Y1–2 (49%/37%) easing to single-digits Y6–8.
A121: 5. Live model Base scenario reproduces the lens median within 0.06%. Assumptions D169:D176 retuned to (49%/37%/25%/19%/14%/11%/8%/6%) — the trajectory the model now uses is the trajectory the four lenses triangulate to.
A122: 6. Series G implies ~15.0M members (proxy, linear scaling) — 26% above Lens A's most aggressive defensible ceiling (11.95M). Series G is not pricing in even the most upside-leaning lens; the gap to the comp set requires upside on margins, pricing, OR member count beyond what any methodology defends.
A123: 7. Verdict: Member triangulation supports DCF base $17.89/sh. Series G $24.63/sh requires multiple things to break right simultaneously — not a binary member-count argument, but stacked margin + multiple + member upside relative to lens median.
...

Sheet Members
A1: WHOOP — Member Cohort Engine
A2: Members in millions; cohort engine drives revenue. 2025 beginning treated as Y3+ legacy block (simplification — see note).
B5: Units | C5: 2024 | D5: 2025 | E5: 2026 | F5: 2027 | G5: 2028 | H5: 2029 | I5: 2030 | J5: 2031 | K5: 2032 | L5: 2033
C6: Historical | D6: Historical | E6: Phase 1 | F6: Phase 1 | G6: Phase 2 | H6: Phase 2 | I6: Phase 2 | J6: Phase 3 | K6: Phase 3 | L6: Phase 3
A8: 1. Beginning Members (start of year)
A9: Beginning Members (total) | B9: M | C9: 0.7 | D9: =Assumptions!$F$8 -> 1.3 | E9: =D34 -> 2.5 | F9: =E34 -> 3.7225 | G9: =F34 -> 5.10727 | H9: =G34 -> 6.4045166 | I9: =H34 -> 7.5957567 | J9: =I34 -> 8.6363753 | K9: =J34 -> 9.5691039 | L9: =K34 -> 10.315494
A10: of which: Year-1 cohort | B10: M | C10: 0.5 | D10: 0 | E10: =D31 -> 1.356 | F10: =E31 -> 1.6581 | G10: =F31 -> 2.0290104 | H10: =G31 -> 2.1518196 | I10: =H31 -> 2.2224429 | J10: =I31 -> 2.2247063 | K10: =J31 -> 2.2435694 | L10: =K31 -> 2.1710976
A11: of which: Year-2 cohort | B11: M | C11: 0.15 | D11: 0 | E11: =D26 -> 0 | F11: =E26 -> 1.05768 | G11: =F26 -> 1.293318 | H11: =G26 -> 1.5826281 | I11: =H26 -> 1.6784193 | J11: =I26 -> 1.7335054 | K11: =J26 -> 1.7352709 | L11: =K26 -> 1.7499841
A12: of which: Year-3+ cohort | B12: M | C12: 0.05 | D12: =Assumptions!$F$8 -> 1.3 | E12: =D28 -> 1.144 | F12: =E28 -> 1.00672 | G12: =F28 -> 1.7849416 | H12: =G28 -> 2.6700689 | I12: =H28 -> 3.6948945 | J12: =I28 -> 4.6781636 | K12: =J28 -> 5.5902636 | L12: =K28 -> 6.3944122
A14: 2. Churn Rates (cohort-aged, from Assumptions)
A15: Year-1 churn rate | B15: % | C15: =Assumptions!$F$19 -> 0.22 | D15: =Assumptions!$F$19 -> 0.22 | E15: =Assumptions!$F$19 -> 0.22 | F15: =Assumptions!$F$19 -> 0.22 | G15: =Assumptions!$F$19 -> 0.22 | H15: =Assumptions!$F$19 -> 0.22 | I15: =Assumptions!$F$19 -> 0.22 | J15: =Assumptions!$F$19 -> 0.22 | ... L15: =Assumptions!$F$19 -> 0.22
A16: Year-2 churn rate | B16: % | C16: =Assumptions!$F$20 -> 0.15 | D16: =Assumptions!$F$20 -> 0.15 | E16: =Assumptions!$F$20 -> 0.15 | F16: =Assumptions!$F$20 -> 0.15 | G16: =Assumptions!$F$20 -> 0.15 | H16: =Assumptions!$F$20 -> 0.15 | I16: =Assumptions!$F$20 -> 0.15 | J16: =Assumptions!$F$20 -> 0.15 | ... L16: =Assumptions!$F$20 -> 0.15
A17: Year-3+ churn rate | B17: % | C17: =Assumptions!$F$21 -> 0.12 | D17: =Assumptions!$F$21 -> 0.12 | E17: =Assumptions!$F$21 -> 0.12 | F17: =Assumptions!$F$21 -> 0.12 | G17: =Assumptions!$F$21 -> 0.12 | H17: =Assumptions!$F$21 -> 0.12 | I17: =Assumptions!$F$21 -> 0.12 | J17: =Assumptions!$F$21 -> 0.12 | ... L17: =Assumptions!$F$21 -> 0.12
A19: 3. Churned Members
A20: Y1 churned | B20: M | C20: =C10*C15 -> 0.11 | D20: =D10*D15 -> 0 | E20: =E10*E15 -> 0.29832 | F20: =F10*F15 -> 0.364782 | G20: =G10*G15 -> 0.44638229 | H20: =H10*H15 -> 0.4734003 | I20: =I10*I15 -> 0.48893743 | J20: =J10*J15 -> 0.48943539 | ... L20: =L10*L15 -> 0.47764148
A21: Y2 churned | B21: M | C21: =C11*C16 -> 0.0225 | D21: =D11*D16 -> 0 | E21: =E11*E16 -> 0 | F21: =F11*F16 -> 0.158652 | G21: =G11*G16 -> 0.1939977 | H21: =H11*H16 -> 0.23739422 | I21: =I11*I16 -> 0.25176289 | J21: =J11*J16 -> 0.26002582 | ... L21: =L11*L16 -> 0.26249762
A22: Y3+ churned | B22: M | C22: =C12*C17 -> 0.006 | D22: =D12*D17 -> 0.156 | E22: =E12*E17 -> 0.13728 | F22: =F12*F17 -> 0.1208064 | G22: =G12*G17 -> 0.21419299 | H22: =H12*H17 -> 0.32040827 | I22: =I12*I17 -> 0.44338734 | J22: =J12*J17 -> 0.56137963 | ... L22: =L12*L17 -> 0.76732947
A23: Total churned | B23: M | C23: =SUM(C20:C22) -> 0.1385 | D23: =SUM(D20:D22) -> 0.156 | E23: =SUM(E20:E22) -> 0.4356 | F23: =SUM(F20:F22) -> 0.6442404 | G23: =SUM(G20:G22) -> 0.85457298 | H23: =SUM(H20:H22) -> 1.0312028 | I23: =SUM(I20:I22) -> 1.1840877 | J23: =SUM(J20:J22) -> 1.3108408 | ... L23: =SUM(L20:L22) -> 1.5074686
A25: 4. Surviving Members (end of year, before new adds)
A26: Y1 survivors | B26: M | C26: =C10-C20 -> 0.39 | D26: =D10-D20 -> 0 | E26: =E10-E20 -> 1.05768 | F26: =F10-F20 -> 1.293318 | G26: =G10-G20 -> 1.5826281 | H26: =H10-H20 -> 1.6784193 | I26: =I10-I20 -> 1.7335054 | J26: =J10-J20 -> 1.7352709 | ... L26: =L10-L20 -> 1.6934562
A27: Y2 survivors | B27: M | C27: =C11-C21 -> 0.1275 | D27: =D11-D21 -> 0 | E27: =E11-E21 -> 0 | F27: =F11-F21 -> 0.899028 | G27: =G11-G21 -> 1.0993203 | H27: =H11-H21 -> 1.3452339 | I27: =I11-I21 -> 1.4266564 | J27: =J11-J21 -> 1.4734796 | ... L27: =L11-L21 -> 1.4874865
A28: Y3+ end state (incl. Y2 graduates) | B28: M | C28: =C12-C22+C27 -> 0.1715 | D28: =D12-D22+D27 -> 1.144 | E28: =E12-E22+E27 -> 1.00672 | F28: =F12-F22+F27 -> 1.7849416 | G28: =G12-G22+G27 -> 2.6700689 | H28: =H12-H22+H27 -> 3.6948945 | I28: =I12-I22+I27 -> 4.6781636 | J28: =J12-J22+J27 -> 5.5902636 | ... L28: =L12-L22+L27 -> 7.1145693
A30: 5. New Members (Gross Adds — DERIVED via membership identity)
A31: Gross Adds (= Δ Ending + Total Churned) | B31: M | C31: 0.6 | D31: =Assumptions!$F$9-D28 -> 1.356 | E31: =E34-E9+E23 -> 1.6581 | F31: =F34-F9+F23 -> 2.0290104 | G31: =G34-G9+G23 -> 2.1518196 | H31: =H34-H9+H23 -> 2.2224429 | I31: =I34-I9+I23 -> 2.2247063 | J31: =J34-J9+J23 -> 2.2435694 | K31: =K34-K9+K23 -> 2.1710976 | L31: =L34-L9+L23 -> 2.1160827
A33: 6. Ending & Average Members
A34: Ending Members | B34: M | C34: =C26+C28+C31 -> 1.1615 | D34: =D26+D28+D31 -> 2.5 | E34: =MIN(D34*(1+Assumptions!$F$167),0.45*Assumptions!$F$122) -> 3.7225 | F34: =MIN(E34*(1+Assumptions!$F$168),0.45*Assumptions!$F$122) -> 5.10727 | G34: =MIN(F34*(1+Assumptions!$F$169),0.45*Assumptions!$F$122) -> 6.4045166 | H34: =MIN(G34*(1+Assumptions!$F$170),0.45*Assumptions!$F$122) -> 7.5957567 | I34: =MIN(H34*(1+Assumptions!$F$171),0.45*Assumptions!$F$122) -> 8.6363753 | J34: =MIN(I34*(1+Assumptions!$F$172),0.45*Assumptions!$F$122) -> 9.5691039 | K34: =MIN(J34*(1+Assumptions!$F$173),0.45*Assumptions!$F$122) -> 10.315494 | L34: =MIN(K34*(1+Assumptions!$F$174),0.45*Assumptions!$F$122) -> 10.924108
A35: Average Members | B35: M | C35: =(C9+C34)/2 -> 0.93075 | D35: =(D9+D34)/2 -> 1.9 | E35: =(E9+E34)/2 -> 3.11125 | F35: =(F9+F34)/2 -> 4.414885 | G35: =(G9+G34)/2 -> 5.7558933 | H35: =(H9+H34)/2 -> 7.0001366 | I35: =(I9+I34)/2 -> 8.116066 | J35: =(J9+J34)/2 -> 9.1027396 | ... L35: =(L9+L34)/2 -> 10.619801
A37: 7. Diagnostics (output, not input)
A38: Net Adds (Gross - Churned) | B38: M | C38: =C31-C23 -> 0.4615 | D38: =D31-D23 -> 1.2 | E38: =E31-E23 -> 1.2225 | F38: =F31-F23 -> 1.38477 | G38: =G31-G23 -> 1.2972466 | H38: =H31-H23 -> 1.1912401 | I38: =I31-I23 -> 1.0406187 | J38: =J31-J23 -> 0.93272854 | ... L38: =L31-L23 -> 0.60861414
A39: Net Member Growth % | B39: % | D39: =D34/C34-1 -> 1.1523892 | E39: =E34/D34-1 -> 0.489 | F39: =F34/E34-1 -> 0.372 | G39: =G34/F34-1 -> 0.254 | H39: =H34/G34-1 -> 0.186 | I39: =I34/H34-1 -> 0.137 | J39: =J34/I34-1 -> 0.108 | K39: =K34/J34-1 -> 0.078 | L39: =L34/K34-1 -> 0.059
A40: Blended Annual Churn Rate (output) | B40: % | C40: =IFERROR(C23/C9,0) -> 0.19785714 | D40: =IFERROR(D23/D9,0) -> 0.12 | E40: =IFERROR(E23/E9,0) -> 0.17424 | F40: =IFERROR(F23/F9,0) -> 0.1730666 | G40: =IFERROR(G23/G9,0) -> 0.16732481 | H40: =IFERROR(H23/H9,0) -> 0.16101181 | I40: =IFERROR(I23/I9,0) -> 0.15588805 | J40: =IFERROR(J23/J9,0) -> 0.15178136 | ... L40: =IFERROR(L23/L9,0) -> 0.14613634
A41: 2025 ending vs Assumptions R3b (consistency) | B41: % | D41: =D34/Assumptions!$F$9-1 -> 0
A44: 8. S&M Build (Variable + Brand decomposition; member-anchored)
A45: Framework: Total S&M = (Gross Adds × Variable CAC) + Brand $. P&L pulls Total. Brand split exposes true variable acquisition economics. | B45: # | C45: Hist | D45: Hist | E45: Adds→S&M | F45: Adds→S&M | G45: Rev→Adds | H45: Rev→Adds | I45: Rev→Adds | J45: Rev→Adds | K45: Rev→Adds | L45: Rev→Adds
A46: Total S&M $ (= Variable + Brand) [P&L feeder] | B46: $M | D46: 195 | E46: =E53+E54 -> 288.715 | F46: =F53+F54 -> 394.03074 | G46: =G53+G54 -> 463.04359 | H46: =H53+H54 -> 524.55937 | I46: =I53+I54 -> 575.33016 | J46: =J53+J54 -> 628.91598 | K46: =K53+K54 -> 666.90625 | L46: =L53+L54 -> 707.43056
A47: Variable CAC $ (paid acquisition only, excl. brand) | B47: $ | D47: 130 | E47: =Assumptions!$F$120 + (Assumptions!$F$121-Assumptions!$F$120)*(E$5-2026)/7 -> 150 | F47: =Assumptions!$F$120 + (Assumptions!$F$121-Assumptions!$F$120)*(F$5-2026)/7 -> 153.71429 | G47: =Assumptions!$F$120 + (Assumptions!$F$121-Assumptions!$F$120)*(G$5-2026)/7 -> 157.42857 | H47: =Assumptions!$F$120 + (Assumptions!$F$121-Assumptions!$F$120)*(H$5-2026)/7 -> 161.14286 | I47: =Assumptions!$F$120 + (Assumptions!$F$121-Assumptions!$F$120)*(I$5-2026)/7 -> 164.85714 | J47: =Assumptions!$F$120 + (Assumptions!$F$121-Assumptions!$F$120)*(J$5-2026)/7 -> 168.57143 | K47: =Assumptions!$F$120 + (Assumptions!$F$121-Assumptions!$F$120)*(K$5-2026)/7 -> 172.28571 | L47: =Assumptions!$F$120 + (Assumptions!$F$121-Assumptions!$F$120)*(L$5-2026)/7 -> 176
A48: Memo: Total S&M ÷ CAC (legacy diagnostic) | B48: M | D48: =D46/D47 -> 1.5 | E48: =E46/E47 -> 1.9247667 | F48: =F46/F47 -> 2.563397 | G48: =G46/G47 -> 2.9412932 | H48: =H46/H47 -> 3.2552443 | I48: =I46/I47 -> 3.489871 | J48: =J46/J47 -> 3.7308575 | K48: =K46/K47 -> 3.8709318 | L48: =L46/L47 -> 4.0194918
A49: TAM Penetration % (diagnostic — flag if >40%) | B49: % | D49: n/a | E49: =D34/Assumptions!$F$122 -> 0.1 | F49: =E34/Assumptions!$F$122 -> 0.1489 | G49: =F34/Assumptions!$F$122 -> 0.2042908 | H49: =G34/Assumptions!$F$122 -> 0.25618066 | I49: =H34/Assumptions!$F$122 -> 0.30383027 | J49: =I34/Assumptions!$F$122 -> 0.34545501 | K49: =J34/Assumptions!$F$122 -> 0.38276415 | L49: =K34/Assumptions!$F$122 -> 0.41261976
A50: Final Gross Adds (= row 31, derived) | B50: M | D50: =D48 -> 1.5 | E50: =E31 -> 1.6581 | F50: =F31 -> 2.0290104 | G50: =G31 -> 2.1518196 | H50: =H31 -> 2.2224429 | I50: =I31 -> 2.2247063 | J50: =J31 -> 2.2435694 | K50: =K31 -> 2.1710976 | L50: =L31 -> 2.1160827
A51: Implied S&M % of prior-yr revenue (diagnostic by phase) | B51: % | E51: =E46/'Revenue Build'!D20 -> 0.55458125 | F51: =F46/'Revenue Build'!E20 -> 0.44875305 | G51: =G46/'Revenue Build'!F20 -> 0.36080909 | H51: =H46/'Revenue Build'!G20 -> 0.3043825 | I51: =I46/'Revenue Build'!H20 -> 0.26650856 | J51: =J46/'Revenue Build'!I20 -> 0.24395536 | K51: =K46/'Revenue Build'!J20 -> 0.22393334 | L51: =L46/'Revenue Build'!K20 -> 0.21114746
A52: Memo: 2027→2028 implied step (informational) | B52: pp | G52: =(G46/'Revenue Build'!F20)-F51 -> -0.087943954
A53: Variable S&M $ (= Gross Adds × Variable CAC) | B53: $M | E53: =E50*E47 -> 248.715 | F53: =F50*F47 -> 311.88788 | G53: =G50*G47 -> 338.75788 | H53: =H50*H47 -> 358.13079 | I53: =I50*I47 -> 366.75873 | J53: =J50*J47 -> 378.20169 | K53: =K50*K47 -> 374.04911 | L53: =L50*L47 -> 372.43056
A54: Brand S&M $ (= linearly interp Assumptions!F124→F125) | B54: $M | E54: =Assumptions!$F$123+(Assumptions!$F$124-Assumptions!$F$123)*(E$5-2026)/7 -> 40 | F54: =Assumptions!$F$123+(Assumptions!$F$124-Assumptions!$F$123)*(F$5-2026)/7 -> 82.142857 | G54: =Assumptions!$F$123+(Assumptions!$F$124-Assumptions!$F$123)*(G$5-2026)/7 -> 124.28571 | H54: =Assumptions!$F$123+(Assumptions!$F$124-Assumptions!$F$123)*(H$5-2026)/7 -> 166.42857 | I54: =Assumptions!$F$123+(Assumptions!$F$124-Assumptions!$F$123)*(I$5-2026)/7 -> 208.57143 | J54: =Assumptions!$F$123+(Assumptions!$F$124-Assumptions!$F$123)*(J$5-2026)/7 -> 250.71429 | K54: =Assumptions!$F$123+(Assumptions!$F$124-Assumptions!$F$123)*(K$5-2026)/7 -> 292.85714 | L54: =Assumptions!$F$123+(Assumptions!$F$124-Assumptions!$F$123)*(L$5-2026)/7 -> 335
A55: All-in CAC $ (= Total S&M / Gross Adds) [diagnostic] | B55: $ | E55: =E46/E50 -> 174.124 | F55: =F46/F50 -> 194.19848 | G55: =G46/G50 -> 215.187 | H55: =H46/H50 -> 236.02828 | I55: =I46/I50 -> 258.60948 | J55: =J46/J50 -> 280.31938 | K55: =K46/K50 -> 307.17469 | L55: =L46/L50 -> 334.31139
A56: LTV $ (= ARPU × GM% / blended churn) | B56: $ | E56: =Assumptions!$F$11*Assumptions!$F$35/Members!E40 -> 943.52617 | F56: =Assumptions!$F$11*Assumptions!$F$35/Members!F40 -> 949.92335 | G56: =Assumptions!$F$11*Assumptions!$F$36/Members!G40 -> 1097.1475 | H56: =Assumptions!$F$11*Assumptions!$F$36/Members!H40 -> 1140.1648 | I56: =Assumptions!$F$11*Assumptions!$F$36/Members!I40 -> 1177.64 | J56: =Assumptions!$F$11*Assumptions!$F$37/Members!J40 -> 1371.9734 | K56: =Assumptions!$F$11*Assumptions!$F$37/Members!K40 -> 1398.6521 | L56: =Assumptions!$F$11*Assumptions!$F$37/Members!L40 -> 1424.9707
A57: LTV / All-in CAC (≥3x healthy, <2x flag) | B57: x | E57: =E56/E55 -> 5.4187027 | F57: =F56/F55 -> 4.8915076 | G57: =G56/G55 -> 5.0985772 | H57: =H56/H55 -> 4.8306281 | I57: =I56/I55 -> 4.5537387 | J57: =J56/J55 -> 4.8943224 | K57: =K56/K55 -> 4.5532791 | L57: =L56/L55 -> 4.2624053
A58: LTV / Variable CAC (≥5x healthy, what acquisition really earns) | B58: x | E58: =E56/E47 -> 6.2901745 | F58: =F56/F47 -> 6.1797988 | G58: =G56/G47 -> 6.9691766 | H58: =H56/H47 -> 7.075491 | I58: =I56/I47 -> 7.1433969 | J58: =J56/J47 -> 8.1388254 | K58: =K56/K47 -> 8.1182129 | L58: =L56/L47 -> 8.0964242
A59: 9. Guardrails (Layer 5: phase-aware bands & coherence) | M59: Notes
A60: Implied S&M % within band (P1 35-55%, P2 20-30%, P3 12-18%) | B60: ✓/⚠/✗ | E60: =IF(E$5<=2027,IF(AND(E51>=0.35,E51<=0.55),"✓",IF(AND(E51>=0.3,E51<=0.6),"⚠","✗")),IF(E$5<=2030,IF(AND(E51>=0.2,E51<=0.3),"✓",IF(AND(E51>=0.17,E51<=0.33),"⚠","✗")),IF(AND(E51>=0.12,E51<=0.18),"✓",IF(AND(E51>=0.1,E51<=0.2),"⚠","✗")))) -> ⚠ | F60: =IF(F$5<=2027,IF(AND(F51>=0.35,F51<=0.55),"✓",IF(AND(F51>=0.3,F51<=0.6),"⚠","✗")),IF(F$5<=2030,IF(AND(F51>=0.2,F51<=0.3),"✓",IF(AND(F51>=0.17,F51<=0.33),"⚠","✗")),IF(AND(F51>=0.12,F51<=0.18),"✓",IF(AND(F51>=0.1,F51<=0.2),"⚠","✗")))) -> ✓ | G60: =IF(G$5<=2027,IF(AND(G51>=0.35,G51<=0.55),"✓",IF(AND(G51>=0.3,G51<=0.6),"⚠","✗")),IF(G$5<=2030,IF(AND(G51>=0.2,G51<=0.3),"✓",IF(AND(G51>=0.17,G51<=0.33),"⚠","✗")),IF(AND(G51>=0.12,G51<=0.18),"✓",IF(AND(G51>=0.1,G51<=0.2),"⚠","✗")))) -> ✗ | H60: =IF(H$5<=2027,IF(AND(H51>=0.35,H51<=0.55),"✓",IF(AND(H51>=0.3,H51<=0.6),"⚠","✗")),IF(H$5<=2030,IF(AND(H51>=0.2,H51<=0.3),"✓",IF(AND(H51>=0.17,H51<=0.33),"⚠","✗")),IF(AND(H51>=0.12,H51<=0.18),"✓",IF(AND(H51>=0.1,H51<=0.2),"⚠","✗")))) -> ⚠ | I60: =IF(I$5<=2027,IF(AND(I51>=0.35,I51<=0.55),"✓",IF(AND(I51>=0.3,I51<=0.6),"⚠","✗")),IF(I$5<=2030,IF(AND(I51>=0.2,I51<=0.3),"✓",IF(AND(I51>=0.17,I51<=0.33),"⚠","✗")),IF(AND(I51>=0.12,I51<=0.18),"✓",IF(AND(I51>=0.1,I51<=0.2),"⚠","✗")))) -> ✓ | J60: =IF(J$5<=2027,IF(AND(J51>=0.35,J51<=0.55),"✓",IF(AND(J51>=0.3,J51<=0.6),"⚠","✗")),IF(J$5<=2030,IF(AND(J51>=0.2,J51<=0.3),"✓",IF(AND(J51>=0.17,J51<=0.33),"⚠","✗")),IF(AND(J51>=0.12,J51<=0.18),"✓",IF(AND(J51>=0.1,J51<=0.2),"⚠","✗")))) -> ✗ | K60: =IF(K$5<=2027,IF(AND(K51>=0.35,K51<=0.55),"✓",IF(AND(K51>=0.3,K51<=0.6),"⚠","✗")),IF(K$5<=2030,IF(AND(K51>=0.2,K51<=0.3),"✓",IF(AND(K51>=0.17,K51<=0.33),"⚠","✗")),IF(AND(K51>=0.12,K51<=0.18),"✓",IF(AND(K51>=0.1,K51<=0.2),"⚠","✗")))) -> ✗ | L60: =IF(L$5<=2027,IF(AND(L51>=0.35,L51<=0.55),"✓",IF(AND(L51>=0.3,L51<=0.6),"⚠","✗")),IF(L$5<=2030,IF(AND(L51>=0.2,L51<=0.3),"✓",IF(AND(L51>=0.17,L51<=0.33),"⚠","✗")),IF(AND(L51>=0.12,L51<=0.18),"✓",IF(AND(L51>=0.1,L51<=0.2),"⚠","✗")))) -> ✗ | M60: 2030 ✗ accepted as P2/P3 transition flag — model is authentically between regimes; not a band-design fix. 2033 ⚠ resolved by Brand $ bump to $130M terminal.
A61: Variable CAC ≤ 50% × ARPU | B61: ✓/⚠/✗ | E61: =IF(E47<=0.5*ARPU!E$10,"✓",IF(E47<=0.6*ARPU!E$10,"⚠","✗")) -> ⚠ | F61: =IF(F47<=0.5*ARPU!F$10,"✓",IF(F47<=0.6*ARPU!F$10,"⚠","✗")) -> ⚠ | G61: =IF(G47<=0.5*ARPU!G$10,"✓",IF(G47<=0.6*ARPU!G$10,"⚠","✗")) -> ⚠ | H61: =IF(H47<=0.5*ARPU!H$10,"✓",IF(H47<=0.6*ARPU!H$10,"⚠","✗")) -> ⚠ | I61: =IF(I47<=0.5*ARPU!I$10,"✓",IF(I47<=0.6*ARPU!I$10,"⚠","✗")) -> ⚠ | J61: =IF(J47<=0.5*ARPU!J$10,"✓",IF(J47<=0.6*ARPU!J$10,"⚠","✗")) -> ⚠ | K61: =IF(K47<=0.5*ARPU!K$10,"✓",IF(K47<=0.6*ARPU!K$10,"⚠","✗")) -> ⚠ | L61: =IF(L47<=0.5*ARPU!L$10,"✓",IF(L47<=0.6*ARPU!L$10,"⚠","✗")) -> ⚠
A62: LTV / All-in CAC ≥ 3.0x | B62: ✓/⚠/✗ | E62: =IF(E57>=3,"✓",IF(E57>=2,"⚠","✗")) -> ✓ | F62: =IF(F57>=3,"✓",IF(F57>=2,"⚠","✗")) -> ✓ | G62: =IF(G57>=3,"✓",IF(G57>=2,"⚠","✗")) -> ✓ | H62: =IF(H57>=3,"✓",IF(H57>=2,"⚠","✗")) -> ✓ | I62: =IF(I57>=3,"✓",IF(I57>=2,"⚠","✗")) -> ✓ | J62: =IF(J57>=3,"✓",IF(J57>=2,"⚠","✗")) -> ✓ | K62: =IF(K57>=3,"✓",IF(K57>=2,"⚠","✗")) -> ✓ | L62: =IF(L57>=3,"✓",IF(L57>=2,"⚠","✗")) -> ✓
A63: LTV / Variable CAC ≥ 5.0x | B63: ✓/⚠/✗ | E63: =IF(E58>=5,"✓",IF(E58>=3,"⚠","✗")) -> ✓ | F63: =IF(F58>=5,"✓",IF(F58>=3,"⚠","✗")) -> ✓ | G63: =IF(G58>=5,"✓",IF(G58>=3,"⚠","✗")) -> ✓ | H63: =IF(H58>=5,"✓",IF(H58>=3,"⚠","✗")) -> ✓ | I63: =IF(I58>=5,"✓",IF(I58>=3,"⚠","✗")) -> ✓ | J63: =IF(J58>=5,"✓",IF(J58>=3,"⚠","✗")) -> ✓ | K63: =IF(K58>=5,"✓",IF(K58>=3,"⚠","✗")) -> ✓ | L63: =IF(L58>=5,"✓",IF(L58>=3,"⚠","✗")) -> ✓
A64: TAM penetration ≤ 45% (hard-cap if breached) | B64: ✓/⚠/✗ | E64: =IF(E49<=0.45,"✓",IF(E49<=0.55,"⚠","✗")) -> ✓ | F64: =IF(F49<=0.45,"✓",IF(F49<=0.55,"⚠","✗")) -> ✓ | G64: =IF(G49<=0.45,"✓",IF(G49<=0.55,"⚠","✗")) -> ✓ | H64: =IF(H49<=0.45,"✓",IF(H49<=0.55,"⚠","✗")) -> ✓ | I64: =IF(I49<=0.45,"✓",IF(I49<=0.55,"⚠","✗")) -> ✓ | J64: =IF(J49<=0.45,"✓",IF(J49<=0.55,"⚠","✗")) -> ✓ | K64: =IF(K49<=0.45,"✓",IF(K49<=0.55,"⚠","✗")) -> ✓ | L64: =IF(L49<=0.45,"✓",IF(L49<=0.55,"⚠","✗")) -> ✓
A65: Capital coherence: 2026-27 cumul. S&M ≤ $700M Series G | B65: ✓/⚠/✗ | E65: =IF(E46+F46<=700,"✓",IF(E46+F46<=800,"⚠","✗")) -> ✓
A66: Roll-up status (worst across rows 61-65) | B66: ✓/⚠/✗ | E66: =IF(COUNTIF(E60:E64,"✗")>0,"✗",IF(COUNTIF(E60:E64,"⚠")>0,"⚠","✓")) -> ⚠ | F66: =IF(COUNTIF(F60:F64,"✗")>0,"✗",IF(COUNTIF(F60:F64,"⚠")>0,"⚠","✓")) -> ⚠ | G66: =IF(COUNTIF(G60:G64,"✗")>0,"✗",IF(COUNTIF(G60:G64,"⚠")>0,"⚠","✓")) -> ✗ | H66: =IF(COUNTIF(H60:H64,"✗")>0,"✗",IF(COUNTIF(H60:H64,"⚠")>0,"⚠","✓")) -> ⚠ | I66: =IF(COUNTIF(I60:I64,"✗")>0,"✗",IF(COUNTIF(I60:I64,"⚠")>0,"⚠","✓")) -> ⚠ | J66: =IF(COUNTIF(J60:J64,"✗")>0,"✗",IF(COUNTIF(J60:J64,"⚠")>0,"⚠","✓")) -> ✗ | K66: =IF(COUNTIF(K60:K64,"✗")>0,"✗",IF(COUNTIF(K60:K64,"⚠")>0,"⚠","✓")) -> ✗ | L66: =IF(COUNTIF(L60:L64,"✗")>0,"✗",IF(COUNTIF(L60:L64,"⚠")>0,"⚠","✓")) -> ✗
A67: Triangulation flag (vs Member Thesis median) | B67: Δ% | E67: =IF(ABS(Assumptions!$F$177)<=0.15,"✓ triang.",IF(ABS(Assumptions!$F$177)<=0.25,"⚠ wide","✗ diverged")) -> ✓ triang.
A75: Member Trajectory by Scenario — 2025 to 2033
A76: Ending members (millions). Base case ties live to Members!D34:L34; Bear/Bull computed from scenario-specific YoY trajectories.
A78: Scenario | C78: 2025 | D78: 2026 | E78: 2027 | F78: 2028 | G78: 2029 | H78: 2030 | I78: 2031 | J78: 2032 | K78: 2033 | L78: 2033 Endpoint
A79: Bear | B79: Plateau | C79: 2.5 | D79: =C79*1.32 -> 3.3 | E79: =D79*1.22 -> 4.026 | F79: =E79*1.15 -> 4.6299 | G79: =F79*1.1 -> 5.09289 | H79: =G79*1.07 -> 5.4493923 | I79: =H79*1.05 -> 5.7218619 | J79: =I79*1.03 -> 5.8935178 | K79: =J79*1.02 -> 6.0113881 | L79: =K79&"M" -> 6.011388127899M
A80: Base | B80: Durable | C80: =D34 -> 2.5 | D80: =E34 -> 3.7225 | E80: =F34 -> 5.10727 | F80: =G34 -> 6.4045166 | G80: =H34 -> 7.5957567 | H80: =I34 -> 8.6363753 | I80: =J34 -> 9.5691039 | J80: =K34 -> 10.315494 | K80: =L34 -> 10.924108 | L80: =ROUND(K80,1)&"M" -> 10.9M
A81: Bull | B81: Platform | C81: 2.5 | D81: =C81*1.6 -> 4 | E81: =D81*1.5 -> 6 | F81: =E81*1.4 -> 8.4 | G81: =F81*1.28 -> 10.752 | H81: =G81*1.18 -> 12.68736 | I81: =H81*1.13 -> 14.336717 | J81: =I81*1.09 -> 15.627021 | K81: =J81*1.06 -> 16.564643 | L81: =ROUND(K81,1)&"M" -> 16.6M
B84: 2025 | C84: 2026 | D84: 2027 | E84: 2028 | F84: 2029 | G84: 2030 | H84: 2031 | I84: 2032 | J84: 2033
A85: Bear | B85: 2.5 | C85: 3.3 | D85: 4.03 | E85: 4.63 | F85: 5.09 | G85: 5.45 | H85: 5.72 | I85: 5.89 | J85: 6.01
A86: Base | B86: =D34 -> 2.5 | C86: =E34 -> 3.7225 | D86: =F34 -> 5.10727 | E86: =G34 -> 6.4045166 | F86: =H34 -> 7.5957567 | G86: =I34 -> 8.6363753 | H86: =J34 -> 9.5691039 | I86: =K34 -> 10.315494 | J86: =L34 -> 10.924108
A87: Bull | B87: 2.5 | C87: 4 | D87: 6 | E87: 8.4 | F87: 10.75 | G87: 12.69 | H87: 14.34 | I87: 15.63 | J87: 16.56
H114: chart

Sheet ARPU
A1: ARPU — Single-Line Blended Driver (collapsed from 5-component build)
A2: Active driver: ARPU tab bottoms-up build. 2025 driver = D32 (year-specific implied: partial Labs, no BP). 2026 driver = D33 (mature build: full Labs + BP at 5% attach). 2027+ grows at R4g. Assumptions!F11 reads from D10. Consistency check at row 38 verifies Members × ARPU ≈ Methodology rev anchor.
A5: Year | B5: Unit | C5: 2024 | D5: 2025 | E5: 2026 | F5: 2027 | G5: 2028 | H5: 2029 | I5: 2030 | J5: 2031 | K5: 2032 | L5: 2033
A7: Blended ARPU (driver)
A8: 2025 Anchor (Assumptions R4) | B8: $/yr | D8: =D20 -> 274
A9: Annual growth rate (Assumptions R4g) | B9: % | D9: =Assumptions!$F$149 -> 0.03
A10: Blended ARPU | B10: $/yr | C10: 0 | D10: =D8 -> 274 | E10: =D10*(1+$D$9) -> 282.22 | F10: =E10*(1+$D$9) -> 290.6866 | G10: =F10*(1+$D$9) -> 299.4072 | H10: =G10*(1+$D$9) -> 308.38941 | I10: =H10*(1+$D$9) -> 317.6411 | J10: =I10*(1+$D$9) -> 327.17033 | K10: =J10*(1+$D$9) -> 336.98544 | L10: =K10*(1+$D$9) -> 347.095
A13: ARPU Justification
A14: Bottom-up reconciliation showing how blended ARPU reflects consumer + B2B mix. Numbers below are reference; active driver is Section 1 R4 above.
A16: Consumer per-member ARPU components:
A17: Subscription tier-weighted average | B17: $/yr | D17: =258 -> 258 | E17: Tier mix 30/45/25 × $199/$239/$359 = $257; +$1.68 monthly premium
A18: Labs ARPU now estimation | B18: $/yr | D18: 15
A19: Accessories ARPU | B19: $/yr | D19: 1
A20: Consumer ARPU (2025) | B20: $/yr | D20: =SUM(D17:D19) -> 274
A22: B2B Unite per-seat:
A23: Per-seat employer-rate ARPU | B23: $/yr | D23: 260 | E23: B2B health platforms with bundled hardware: $200-350; standalone software: $100-180. Estimate $260 mid-range.
A25: Mix assumption (% of paying members):
A26: Consumer share | B26: % | D26: 0.8 | E26: BMCT estimate: Unite ~20% of recurring revenue
A27: Unite share | B27: % | D27: 0.2
A28: Mix sum check | D28: =D26+D27 -> 1 | E28: Must = 100%
A30: Component | B30: Contribution | C30: Anchor / Justification
A31: Inflation baseline | B31: 0.03 | C31: CPI+ baseline; consistent with Base
A32: Tier-mix shift to Peak/Life | B32: 0.01 | C32: Healthcare-positioning brand effect drives consumer trade-up; Spotify Family/Premium analog
A33: Labs / BP-Healthspan attach growth | B33: 0.01 | C33: Premium feature monetization; clinical anchor justifies adoption (BP launched Jan 2026)
A34: B2B Unite share growth | B34: 0.003 | C34: Enterprise health platform scales from 20% → 30% of base; per-seat pricing 4-7x consumer
A35: Payer-paid revenue uplift | B35: 0.007 | C35: Direct healthcare reimbursement contribution; weighted across eligible-member share × payer ARPU lift
A36: Total Bull | B36: 0.06
A38: Consistency Check: Members × ARPU = Revenue
A39: 2025 Avg Members × Blended ARPU | B39: $M | D39: =Assumptions!D10*D20 -> 520.6
A45: Scenario ARPU Build — Asymmetric Growth Discipline
A46: Bear/Base anchored to inflation only; Bull lifts only because healthcare reimbursement materializes (ARPU = consequence of scenario, not independent dial).
A48: Scenario | B48: Growth | C48: 2025 ARPU | D48: 2033 ARPU | E48: $/Month '33 | F48: Δ vs CPI
A49: Bear | B49: =Assumptions!C149 -> 0.025 | C49: =ARPU!D8 -> 274 | D49: =C49*(1+B49)^8 -> 333.84239 | E49: =D49/12 -> 27.820199 | F49: =B49-3% -> -0.005
A50: Base | B50: =Assumptions!D149 -> 0.03 | C50: =ARPU!D8 -> 274 | D50: =C50*(1+B50)^8 -> 347.095 | E50: =D50/12 -> 28.924584 | F50: =B50-3% -> 0
A51: Bull | B51: =Assumptions!E149 -> 0.06 | C51: =ARPU!D8 -> 274 | D51: =C51*(1+B51)^8 -> 436.71437 | E51: =D51/12 -> 36.392864 | F51: =B51-3% -> 0.03
A54: Bull Decomposition — 6.0% = Sum of Five Anchored Mechanisms
A55: Bull ARPU growth is the CONSEQUENCE of healthcare reimbursement materialization, not an independent dial. Each component anchored to a commercial mechanism.
A57: Component | B57: Contribution | C57: Justification
A58: Inflation baseline | B58: =B31 -> 0.03 | C58: CPI+ baseline; consistent with Base case anchor
A59: Tier-mix shift to Peak / Life | B59: =B32 -> 0.01 | C59: Healthcare-positioning brand effect drives consumer trade-up (Spotify Family/Premium analog)
A60: Labs / BP-Healthspan attach growth | B60: =B33 -> 0.01 | C60: Premium feature monetization (BP launched Jan 2026; clinical anchor justifies adoption)
A61: B2B Unite share growth | B61: =B34 -> 0.003 | C61: Enterprise platform scales from 20% → 30% of base; per-seat pricing 4-7x consumer
A62: Payer-paid revenue uplift | B62: =B35 -> 0.007 | C62: Direct reimbursement contribution (eligible-member share × payer ARPU lift)
A63: Total Bull ARPU Growth | B63: =SUM(B58:B62) -> 0.06 | C63: Matches Bull driver (Assumptions!E149) — mechanism-by-mechanism reconciliation
A65: Sanity Check — $437 Bull Endpoint vs Reference Points
A66: Bull 2033 ARPU of $437/yr = $36.39/month. Sits between current Peak ($33) and Life ($49) consumer tiers.
A68: Reference Point | B68: $/Month | C68: $/Year | D68: vs Bull | E68: Comment
A69: WHOOP One (current) | B69: 30 | C69: =B69*12 -> 360 | D69: =C69/$D$51-1 -> -0.17566258 | E69: Entry tier; Bull implies 21% lift over 8 years
A70: WHOOP Peak (current mid-tier) | B70: 33 | C70: =B70*12 -> 396 | D70: =C70/$D$51-1 -> -0.093228836 | E70: Bull endpoint implies durable mix shift toward Peak/Life
A71: WHOOP Life (current top tier) | B71: 49 | C71: =B71*12 -> 588 | D71: =C71/$D$51-1 -> 0.34641779 | E71: Already exceeds Bull — plausible if Life mix grows materially
A72: Peloton All-Access | B72: 44 | C72: =B72*12 -> 528 | D72: =C72/$D$51-1 -> 0.20902822 | E72: Connected-fitness benchmark — exceeds Bull endpoint
A73: Oura Ring (membership) | B73: 5.99 | C73: =B73*12 -> 71.88 | D73: =C73/$D$51-1 -> -0.83540729 | E73: Pure software — bounds the floor, not a direct comp
A74: Bull 2033 ARPU (model) | B74: =$D$51/12 -> 36.392864 | C74: =$D$51 -> 436.71437 | D74: — | E74: Between Peak and Life tiers; achievable via healthcare uplift

Sheet Revenue Build
A1: WHOOP — Revenue Build-Up
A2: $M unless noted; Calendar Year
B5: Units | C5: 2024 | D5: 2025 | E5: 2026 | F5: 2027 | G5: 2028 | H5: 2029 | I5: 2030 | J5: 2031 | K5: 2032 | L5: 2033
C6: Historical | D6: Historical | E6: Phase 1 | F6: Phase 1 | G6: Phase 2 | H6: Phase 2 | I6: Phase 2 | J6: Phase 3 | K6: Phase 3 | L6: Phase 3
A8: 1. Member Economics (linked from Members tab)
A9: Beginning Members | B9: M | C9: =Members!C9 -> 0.7 | D9: =Members!D9 -> 1.3 | E9: =Members!E9 -> 2.5 | F9: =Members!F9 -> 3.7225 | G9: =Members!G9 -> 5.10727 | H9: =Members!H9 -> 6.4045166 | I9: =Members!I9 -> 7.5957567 | J9: =Members!J9 -> 8.6363753 | ... L9: =Members!L9 -> 10.315494
A10: Gross Adds | B10: M | C10: =Members!C31 -> 0.6 | D10: =Members!D31 -> 1.356 | E10: =Members!E31 -> 1.6581 | F10: =Members!F31 -> 2.0290104 | G10: =Members!G31 -> 2.1518196 | H10: =Members!H31 -> 2.2224429 | I10: =Members!I31 -> 2.2247063 | J10: =Members!J31 -> 2.2435694 | ... L10: =Members!L31 -> 2.1160827
A11: Churned Members | B11: M | C11: =Members!C23 -> 0.1385 | D11: =Members!D23 -> 0.156 | E11: =Members!E23 -> 0.4356 | F11: =Members!F23 -> 0.6442404 | G11: =Members!G23 -> 0.85457298 | H11: =Members!H23 -> 1.0312028 | I11: =Members!I23 -> 1.1840877 | J11: =Members!J23 -> 1.3108408 | ... L11: =Members!L23 -> 1.5074686
A12: Ending Members | B12: M | C12: =Members!C34 -> 1.1615 | D12: =Members!D34 -> 2.5 | E12: =Members!E34 -> 3.7225 | F12: =Members!F34 -> 5.10727 | G12: =Members!G34 -> 6.4045166 | H12: =Members!H34 -> 7.5957567 | I12: =Members!I34 -> 8.6363753 | J12: =Members!J34 -> 9.5691039 | ... L12: =Members!L34 -> 10.924108
A13: Avg Members | B13: M | C13: =Members!C35 -> 0.93075 | D13: =Members!D35 -> 1.9 | E13: =Members!E35 -> 3.11125 | F13: =Members!F35 -> 4.414885 | G13: =Members!G35 -> 5.7558933 | H13: =Members!H35 -> 7.0001366 | I13: =Members!I35 -> 8.116066 | J13: =Members!J35 -> 9.1027396 | ... L13: =Members!L35 -> 10.619801
A14: Blended Annual Churn (output) | B14: % | C14: =IFERROR(Members!C23/Members!C9, 0) -> 0.19785714 | D14: =IFERROR(Members!D23/Members!D9, 0) -> 0.12 | E14: =IFERROR(Members!E23/Members!E9, 0) -> 0.17424 | F14: =IFERROR(Members!F23/Members!F9, 0) -> 0.1730666 | G14: =IFERROR(Members!G23/Members!G9, 0) -> 0.16732481 | H14: =IFERROR(Members!H23/Members!H9, 0) -> 0.16101181 | I14: =IFERROR(Members!I23/Members!I9, 0) -> 0.15588805 | J14: =IFERROR(Members!J23/Members!J9, 0) -> 0.15178136 | ... L14: =IFERROR(Members!L23/Members!L9, 0) -> 0.14613634
A16: 2. ARPU (linked from ARPU tab)
A17: Blended ARPU | B17: $/yr | C17: =ARPU!C10 -> 0 | D17: =ARPU!D10 -> 274 | E17: =ARPU!E10 -> 282.22 | F17: =ARPU!F10 -> 290.6866 | G17: =ARPU!G10 -> 299.4072 | H17: =ARPU!H10 -> 308.38941 | I17: =ARPU!I10 -> 317.6411 | J17: =ARPU!J10 -> 327.17033 | ... L17: =ARPU!L10 -> 347.095
A19: 3. Revenue Build
A20: Recognized Revenue (Total) | B20: $M | C20: =C13*C17 -> 0 | D20: =D13*D17 -> 520.6 | E20: =E13*E17 -> 878.05698 | F20: =F13*F17 -> 1283.3479 | G20: =G13*G17 -> 1723.3559 | H20: =H13*H17 -> 2158.768 | I20: =I13*I17 -> 2577.9961 | J20: =J13*J17 -> 2978.1463 | ... L20: =L13*L17 -> 3686.0799
A21: Memo: Δ Deferred Rev Balance (flows to NWC, not P&L) | B21: $M | C21: =C20*Assumptions!$F$27 -> 0 | D21: =D20*Assumptions!$F$27 -> -41.648 | E21: =E20*Assumptions!$F$27 -> -70.244558 | F21: =F20*Assumptions!$F$27 -> -102.66783 | G21: =G20*Assumptions!$F$27 -> -137.86847 | H21: =H20*Assumptions!$F$27 -> -172.70144 | I21: =I20*Assumptions!$F$27 -> -206.23969 | J21: =J20*Assumptions!$F$27 -> -238.2517 | ... L21: =L20*Assumptions!$F$27 -> -294.88639
A22: YoY Revenue Growth | B22: % | D22: =IFERROR(D20/C20-1,0) -> 0 | E22: =E20/D20-1 -> 0.686625 | F22: =F20/E20-1 -> 0.46157703 | G22: =G20/F20-1 -> 0.34285946 | H22: =H20/G20-1 -> 0.25265365 | I22: =I20/H20-1 -> 0.19419783 | J22: =J20/I20-1 -> 0.15521754 | K22: =K20/J20-1 -> 0.12499844 | L22: =L20/K20-1 -> 0.10018771
A24: 4. Bookings Reconciliation
A25: Implied Bookings (End × ARPU) | B25: $M | C25: =C12*C17 -> 0 | D25: =D12*D17 -> 685 | E25: =E12*E17 -> 1050.5639 | F25: =F12*F17 -> 1484.615 | G25: =G12*G17 -> 1917.5584 | H25: =H12*H17 -> 2342.4509 | I25: =I12*I17 -> 2743.2677 | J25: =J12*J17 -> 3130.7269 | ... L25: =L12*L17 -> 3791.7033
A26: Bookings/Revenue Ratio (memo: Ending × ARPU vs Avg × ARPU) | B26: x | C26: =IFERROR(C25/C20, 0) -> 0 | D26: =IFERROR(D25/D20, 0) -> 1.3157895 | E26: =IFERROR(E25/E20, 0) -> 1.1964644 | F26: =IFERROR(F25/F20, 0) -> 1.1568297 | G26: =IFERROR(G25/G20, 0) -> 1.1126886 | H26: =IFERROR(H25/H20, 0) -> 1.0850869 | I26: =IFERROR(I25/I20, 0) -> 1.0641086 | J26: =IFERROR(J25/J20, 0) -> 1.0512334 | ... L26: =IFERROR(L25/L20, 0) -> 1.0286547
A27: 2025 Recognized vs Assumptions F12 (consistency) | B27: % | D27: =D20/Assumptions!$F$12-1 -> 0

Sheet P&L
A1: WHOOP — Projected Income Statement
A2: $M; Calendar Year; Scenario per Assumptions toggle
A3: Calibration items: see notes on F31 (2027 dip), L23 (S&M architecture). Margin tapers and NOL wired; refer to CalibrationLog for status.
B5: Units | C5: 2024 | D5: 2025 | E5: 2026 | F5: 2027 | G5: 2028 | H5: 2029 | I5: 2030 | J5: 2031 | K5: 2032 | L5: 2033
A7: Revenue
A8: Total Revenue | B8: $M | C8: ='Revenue Build'!C20 -> 0 | D8: ='Revenue Build'!D20 -> 520.6 | E8: ='Revenue Build'!E20 -> 878.05698 | F8: ='Revenue Build'!F20 -> 1283.3479 | G8: ='Revenue Build'!G20 -> 1723.3559 | H8: ='Revenue Build'!H20 -> 2158.768 | I8: ='Revenue Build'!I20 -> 2577.9961 | J8: ='Revenue Build'!J20 -> 2978.1463 | ... L8: ='Revenue Build'!L20 -> 3686.0799 | M8: ← From Revenue Build tab
A9: YoY Growth | B9: % | D9: =IFERROR(D8/C8-1,0) -> 0 | E9: =E8/D8-1 -> 0.686625 | F9: =F8/E8-1 -> 0.46157703 | G9: =G8/F8-1 -> 0.34285946 | H9: =H8/G8-1 -> 0.25265365 | I9: =I8/H8-1 -> 0.19419783 | J9: =J8/I8-1 -> 0.15521754 | K9: =K8/J8-1 -> 0.12499844 | L9: =L8/K8-1 -> 0.10018771
A11: Cost of Revenue
A12: Total COGS (Blended COGS% × Revenue, linearly interpolated) | B12: $M | D12: =D8*0.4 -> 208.24 | E12: =E8*(Assumptions!$F$150 + (Assumptions!$F$151-Assumptions!$F$150)*(E$5-2026)/7) -> 219.51424 | F12: =F8*(Assumptions!$F$150 + (Assumptions!$F$151-Assumptions!$F$150)*(F$5-2026)/7) -> 311.67021 | G12: =G8*(Assumptions!$F$150 + (Assumptions!$F$151-Assumptions!$F$150)*(G$5-2026)/7) -> 406.2196 | H12: =H8*(Assumptions!$F$150 + (Assumptions!$F$151-Assumptions!$F$150)*(H$5-2026)/7) -> 493.43269 | I12: =I8*(Assumptions!$F$150 + (Assumptions!$F$151-Assumptions!$F$150)*(I$5-2026)/7) -> 570.84199 | J12: =J8*(Assumptions!$F$150 + (Assumptions!$F$151-Assumptions!$F$150)*(J$5-2026)/7) -> 638.17421 | K12: =K8*(Assumptions!$F$150 + (Assumptions!$F$151-Assumptions!$F$150)*(K$5-2026)/7) -> 694.01349 | L12: =L8*(Assumptions!$F$150 + (Assumptions!$F$151-Assumptions!$F$150)*(L$5-2026)/7) -> 737.21597
A13: Hardware COGS (MEMO ONLY — embedded in blended COGS%; used for WC inventory only) | B13: $M | D13: =Members!D31 * Assumptions!$F$31 -> 162.72 | E13: =Members!E31 * Assumptions!$F$31 -> 198.972 | F13: =Members!F31 * Assumptions!$F$31 -> 243.48125 | G13: =Members!G31 * Assumptions!$F$31 -> 258.21835 | H13: =Members!H31 * Assumptions!$F$31 -> 266.69314 | I13: =Members!I31 * Assumptions!$F$31 -> 266.96476 | J13: =Members!J31 * Assumptions!$F$31 -> 269.22832 | K13: =Members!K31 * Assumptions!$F$31 -> 260.53172 | L13: =Members!L31 * Assumptions!$F$31 -> 253.92992
A14: Total COGS (= row 12) | B14: $M | D14: =D12 -> 208.24 | E14: =E12 -> 219.51424 | F14: =F12 -> 311.67021 | G14: =G12 -> 406.2196 | H14: =H12 -> 493.43269 | I14: =I12 -> 570.84199 | J14: =J12 -> 638.17421 | K14: =K12 -> 694.01349 | L14: =L12 -> 737.21597
A15: Gross Profit | B15: $M | D15: =D8-D12 -> 312.36 | E15: =E8-E12 -> 658.54273 | F15: =F8-F12 -> 971.6777 | G15: =G8-G12 -> 1317.1363 | H15: =H8-H12 -> 1665.3353 | I15: =I8-I12 -> 2007.1541 | J15: =J8-J12 -> 2339.9721 | K15: =K8-K12 -> 2656.3965 | L15: =L8-L12 -> 2948.8639
A16: Gross Margin | B16: % | D16: =D15/D8 -> 0.6 | E16: =E15/E8 -> 0.75 | F16: =F15/F8 -> 0.75714286 | G16: =G15/G8 -> 0.76428571 | H16: =H15/H8 -> 0.77142857 | I16: =I15/I8 -> 0.77857143 | J16: =J15/J8 -> 0.78571429 | K16: =K15/K8 -> 0.79285714 | L16: =L15/L8 -> 0.8
A20: Operating Expenses
A21: R&D | B21: $M | D21: =D8*Assumptions!$F$38 -> 114.532 | E21: =E8*(Assumptions!$F$38 + (Assumptions!$F$39-Assumptions!$F$38)*(E$5-2026)/7) -> 193.17253 | F21: =F8*(Assumptions!$F$38 + (Assumptions!$F$39-Assumptions!$F$38)*(F$5-2026)/7) -> 271.33642 | G21: =G8*(Assumptions!$F$38 + (Assumptions!$F$39-Assumptions!$F$38)*(G$5-2026)/7) -> 349.59505 | H21: =H8*(Assumptions!$F$38 + (Assumptions!$F$39-Assumptions!$F$38)*(H$5-2026)/7) -> 419.41779 | I21: =I8*(Assumptions!$F$38 + (Assumptions!$F$39-Assumptions!$F$38)*(I$5-2026)/7) -> 478.7707 | J21: =J8*(Assumptions!$F$38 + (Assumptions!$F$39-Assumptions!$F$38)*(J$5-2026)/7) -> 527.55735 | K21: =K8*(Assumptions!$F$38 + (Assumptions!$F$39-Assumptions!$F$38)*(K$5-2026)/7) -> 564.78339 | L21: =L8*(Assumptions!$F$38 + (Assumptions!$F$39-Assumptions!$F$38)*(L$5-2026)/7) -> 589.77278
A22: R&D % Revenue | B22: % | D22: =D21/D8 -> 0.22 | E22: =E21/E8 -> 0.22 | F22: =F21/F8 -> 0.21142857 | G22: =G21/G8 -> 0.20285714 | H22: =H21/H8 -> 0.19428571 | I22: =I21/I8 -> 0.18571429 | J22: =J21/J8 -> 0.17714286 | K22: =K21/K8 -> 0.16857143 | L22: =L21/L8 -> 0.16 | M22: ← From Assumptions C7/C8
A23: Sales & Marketing | B23: $M | D23: =D8*Assumptions!$F$40 -> 156.18 | E23: =Members!E46 -> 288.715 | F23: =Members!F46 -> 394.03074 | G23: =Members!G46 -> 463.04359 | H23: =Members!H46 -> 524.55937 | I23: =Members!I46 -> 575.33016 | J23: =Members!J46 -> 628.91598 | K23: =Members!K46 -> 666.90625 | L23: =Members!L46 -> 707.43056
A24: S&M % Revenue | B24: % | D24: =D23/D8 -> 0.3 | E24: =E23/E8 -> 0.32881124 | F24: =F23/F8 -> 0.30703345 | G24: =G23/G8 -> 0.26868716 | H24: =H23/H8 -> 0.24299015 | I24: =I23/I8 -> 0.22316952 | J24: =J23/J8 -> 0.21117699 | K24: =K23/K8 -> 0.19905213 | L24: =L23/L8 -> 0.19191949 | M24: ← From Assumptions C9/C10
A25: General & Administrative | B25: $M | D25: =D8*Assumptions!$F$44 -> 78.09 | E25: =E8*(Assumptions!$F$44 + (Assumptions!$F$45-Assumptions!$F$44)*(E$5-2026)/7) -> 131.70855 | F25: =F8*(Assumptions!$F$44 + (Assumptions!$F$45-Assumptions!$F$44)*(F$5-2026)/7) -> 185.16877 | G25: =G8*(Assumptions!$F$44 + (Assumptions!$F$45-Assumptions!$F$44)*(G$5-2026)/7) -> 238.80789 | H25: =H8*(Assumptions!$F$44 + (Assumptions!$F$45-Assumptions!$F$44)*(H$5-2026)/7) -> 286.80775 | I25: =I8*(Assumptions!$F$44 + (Assumptions!$F$45-Assumptions!$F$44)*(I$5-2026)/7) -> 327.77379 | J25: =J8*(Assumptions!$F$44 + (Assumptions!$F$45-Assumptions!$F$44)*(J$5-2026)/7) -> 361.63205 | K25: =K8*(Assumptions!$F$44 + (Assumptions!$F$45-Assumptions!$F$44)*(K$5-2026)/7) -> 387.6903 | L25: =L8*(Assumptions!$F$44 + (Assumptions!$F$45-Assumptions!$F$44)*(L$5-2026)/7) -> 405.46879
A26: G&A % Revenue | B26: % | D26: =D25/D8 -> 0.15 | E26: =E25/E8 -> 0.15 | F26: =F25/F8 -> 0.14428571 | G26: =G25/G8 -> 0.13857143 | H26: =H25/H8 -> 0.13285714 | I26: =I25/I8 -> 0.12714286 | J26: =J25/J8 -> 0.12142857 | K26: =K25/K8 -> 0.11571429 | L26: =L25/L8 -> 0.11 | M26: ← From Assumptions C11/C12
A27: Stock-Based Compensation | B27: $M | D27: =D8*Assumptions!$F$46 -> 72.884 | E27: =E8*(Assumptions!$F$46 + (Assumptions!$F$47-Assumptions!$F$46)*(E$5-2026)/7) -> 122.92798 | F27: =F8*Assumptions!$F$162 -> 218.16914 | G27: =G8*Assumptions!$F$163 -> 258.50338 | H27: =H8*(Assumptions!$F$46 + (Assumptions!$F$47-Assumptions!$F$46)*(H$5-2026)/7) -> 274.47194 | I27: =I8*(Assumptions!$F$46 + (Assumptions!$F$47-Assumptions!$F$46)*(I$5-2026)/7) -> 316.72524 | J27: =J8*(Assumptions!$F$46 + (Assumptions!$F$47-Assumptions!$F$46)*(J$5-2026)/7) -> 353.12306 | K27: =K8*(Assumptions!$F$46 + (Assumptions!$F$47-Assumptions!$F$46)*(K$5-2026)/7) -> 382.904 | L27: =L8*(Assumptions!$F$46 + (Assumptions!$F$47-Assumptions!$F$46)*(L$5-2026)/7) -> 405.46879
A28: SBC % Revenue | B28: % | D28: =D27/D8 -> 0.14 | E28: =E27/E8 -> 0.14 | F28: =F27/F8 -> 0.17 | G28: =G27/G8 -> 0.15 | H28: =H27/H8 -> 0.12714286 | I28: =I27/I8 -> 0.12285714 | J28: =J27/J8 -> 0.11857143 | K28: =K27/K8 -> 0.11428571 | L28: =L27/L8 -> 0.11 | M28: ← From Assumptions C13
A29: Total OpEx | B29: $M | D29: =D21+D23+D25+D27 -> 421.686 | E29: =E21+E23+E25+E27 -> 736.52406 | F29: =F21+F23+F25+F27 -> 1068.7051 | G29: =G21+G23+G25+G27 -> 1309.9499 | H29: =H21+H23+H25+H27 -> 1505.2568 | I29: =I21+I23+I25+I27 -> 1698.5999 | J29: =J21+J23+J25+J27 -> 1871.2284 | K29: =K21+K23+K25+K27 -> 2002.2839 | L29: =L21+L23+L25+L27 -> 2108.1409
A31: Profitability
A32: EBITDA | B32: $M | D32: =D15-D29+D27 -> -36.442 | E32: =E15-E29+E27 -> 44.946651 | F32: =F15-F29+F27 -> 121.14178 | G32: =G15-G29+G27 -> 265.68975 | H32: =H15-H29+H27 -> 434.55043 | I32: =I15-I29+I27 -> 625.27946 | J32: =J15-J29+J27 -> 821.86672 | K32: =K15-K29+K27 -> 1037.0165 | L32: =L15-L29+L27 -> 1246.1918
A33: EBITDA Margin | B33: % | D33: =D32/D8 -> -0.07 | E33: =E32/E8 -> 0.051188763 | F33: =F32/F8 -> 0.094395117 | G33: =G32/G8 -> 0.15416999 | H33: =H32/H8 -> 0.20129557 | I33: =I32/I8 -> 0.24254476 | J33: =J32/J8 -> 0.27596587 | K33: =K32/K8 -> 0.3095193 | L33: =L32/L8 -> 0.33808051
A34: EBIT / Operating Income | B34: $M | D34: =D15-D29 -> -109.326 | E34: =E15-E29 -> -77.981326 | F34: =F15-F29 -> -97.027368 | G34: =G15-G29 -> 7.1863685 | H34: =H15-H29 -> 160.0785 | I34: =I15-I29 -> 308.55422 | J34: =J15-J29 -> 468.74366 | K34: =K15-K29 -> 654.11254 | L34: =L15-L29 -> 840.72299
A35: Operating Margin | B35: % | D35: =D34/D8 -> -0.21 | E35: =E34/E8 -> -0.088811237 | F35: =F34/F8 -> -0.075604883 | G35: =G34/G8 -> 0.0041699852 | H35: =H34/H8 -> 0.074152708 | I35: =I34/I8 -> 0.11968762 | J35: =J34/J8 -> 0.15739444 | K35: =K34/K8 -> 0.19523358 | L35: =L34/L8 -> 0.22808051
A36: Rule of 40 Score | B36: # | D36: =(D9+D33)*100 -> -7 | E36: =(E9+E33)*100 -> 73.781376 | F36: =(F9+F33)*100 -> 55.597215 | G36: =(G9+G33)*100 -> 49.702945 | H36: =(H9+H33)*100 -> 45.394921 | I36: =(I9+I33)*100 -> 43.67426 | J36: =(J9+J33)*100 -> 43.11834 | K36: =(K9+K33)*100 -> 43.451774 | L36: =(L9+L33)*100 -> 43.826822 | M36: = Revenue Growth % + EBITDA Margin %
A38: Below the Line
A39: Interest Income / (Expense) | B39: $M | D39: ='WC & Cash'!$D$12*Assumptions!$F$66 -> 2.625 | E39: =('WC & Cash'!D34 + 'WC & Cash'!E14*0.5)*Assumptions!$F$66 -> 12.28502 | F39: ='WC & Cash'!E34*Assumptions!$F$66 -> 25.501617 | G39: ='WC & Cash'!F34*Assumptions!$F$66 -> 29.35966 | H39: ='WC & Cash'!G34*Assumptions!$F$66 -> 36.722888 | I39: ='WC & Cash'!H34*Assumptions!$F$66 -> 48.98739 | J39: ='WC & Cash'!I34*Assumptions!$F$66 -> 63.836293 | K39: ='WC & Cash'!J34*Assumptions!$F$66 -> 82.158077 | L39: ='WC & Cash'!K34*Assumptions!$F$66 -> 104.51342
A40: Pre-Tax Income | B40: $M | D40: =D34+D39 -> -106.701 | E40: =E34+E39 -> -65.696306 | F40: =F34+F39 -> -71.525751 | G40: =G34+G39 -> 36.546029 | H40: =H34+H39 -> 196.80138 | I40: =I34+I39 -> 357.54161 | J40: =J34+J39 -> 532.57995 | K40: =K34+K39 -> 736.27061 | L40: =L34+L39 -> 945.23641
A41: Taxes | B41: $M | D41: =MAX(0, D40-D48)*Assumptions!$F$51 -> 0 | E41: =MAX(0, E40-E48)*Assumptions!$F$51 -> 0 | F41: =MAX(0, F40-F48)*Assumptions!$F$51 -> 0 | G41: =MAX(0, G40-G48)*Assumptions!$F$51 -> 1.6811173 | H41: =MAX(0, H40-H48)*Assumptions!$F$51 -> 9.0528636 | I41: =MAX(0, I40-I48)*Assumptions!$F$51 -> 69.068191 | J41: =MAX(0, J40-J48)*Assumptions!$F$51 -> 122.49339 | K41: =MAX(0, K40-K48)*Assumptions!$F$51 -> 169.34224 | L41: =MAX(0, L40-L48)*Assumptions!$F$51 -> 217.40437
A42: Net Income | B42: $M | D42: =D40-D41 -> -106.701 | E42: =E40-E41 -> -65.696306 | F42: =F40-F41 -> -71.525751 | G42: =G40-G41 -> 34.864911 | H42: =H40-H41 -> 187.74852 | I42: =I40-I41 -> 288.47342 | J42: =J40-J41 -> 410.08656 | K42: =K40-K41 -> 566.92837 | L42: =L40-L41 -> 727.83203
A43: Net Margin | B43: % | D43: =D42/D8 -> -0.20495774 | E43: =E42/E8 -> -0.074820095 | F43: =F42/F8 -> -0.055733718 | G43: =G42/G8 -> 0.020230825 | H43: =H42/H8 -> 0.086970215 | I43: =I42/I8 -> 0.11189831 | J43: =J42/J8 -> 0.1376986 | K43: =K42/K8 -> 0.16921164 | L43: =L42/L8 -> 0.19745422
A45: NOL Carryforward Schedule (post-TCJA, 80% utilization cap)
A46: Beginning NOL Balance | B46: $M | C46: 0 | D46: =C49 -> 0 | E46: =D49 -> 106.701 | F46: =E49 -> 172.39731 | G46: =F49 -> 243.92306 | H46: =G49 -> 214.68623 | I46: =H49 -> 57.245127 | J46: =I49 -> 0 | K46: =J49 -> 0 | L46: =K49 -> 0
A47: + Current Year Loss Added (if pretax < 0) | B47: $M | C47: 0 | D47: =MAX(0,-D40) -> 106.701 | E47: =MAX(0,-E40) -> 65.696306 | F47: =MAX(0,-F40) -> 71.525751 | G47: =MAX(0,-G40) -> 0 | H47: =MAX(0,-H40) -> 0 | I47: =MAX(0,-I40) -> 0 | J47: =MAX(0,-J40) -> 0 | K47: =MAX(0,-K40) -> 0 | L47: =MAX(0,-L40) -> 0
A48: − NOL Utilized Against Current Income | B48: $M | C48: 0 | D48: =MIN(D46, MAX(0,D40)*0.8) -> 0 | E48: =MIN(E46, MAX(0,E40)*0.8) -> 0 | F48: =MIN(F46, MAX(0,F40)*0.8) -> 0 | G48: =MIN(G46, MAX(0,G40)*0.8) -> 29.236823 | H48: =MIN(H46, MAX(0,H40)*0.8) -> 157.44111 | I48: =MIN(I46, MAX(0,I40)*0.8) -> 57.245127 | J48: =MIN(J46, MAX(0,J40)*0.8) -> 0 | K48: =MIN(K46, MAX(0,K40)*0.8) -> 0 | L48: =MIN(L46, MAX(0,L40)*0.8) -> 0
A49: Ending NOL Balance | B49: $M | C49: =C46+C47-C48 -> 0 | D49: =D46+D47-D48 -> 106.701 | E49: =E46+E47-E48 -> 172.39731 | F49: =F46+F47-F48 -> 243.92306 | G49: =G46+G47-G48 -> 214.68623 | H49: =H46+H47-H48 -> 57.245127 | I49: =I46+I47-I48 -> 0 | J49: =J46+J47-J48 -> 0 | ... L49: =L46+L47-L48 -> 0

Sheet FCF
A1: WHOOP — FCF
A2: Free cash flow build. ΔNWC sourced from WC & Cash tab (detailed deferred-rev schedule).
B5: Units | C5: 2024 | D5: 2025 | E5: 2026 | F5: 2027 | G5: 2028 | H5: 2029 | I5: 2030 | J5: 2031 | K5: 2032 | L5: 2033
C6: Historical | D6: Historical | E6: Phase 1 | F6: Phase 1 | G6: Phase 2 | H6: Phase 2 | I6: Phase 2 | J6: Phase 3 | K6: Phase 3 | L6: Phase 3
A8: 1. EBIT to NOPAT
A9: EBIT | B9: $M | D9: ='P&L'!D34 -> -109.326 | E9: ='P&L'!E34 -> -77.981326 | F9: ='P&L'!F34 -> -97.027368 | G9: ='P&L'!G34 -> 7.1863685 | H9: ='P&L'!H34 -> 160.0785 | I9: ='P&L'!I34 -> 308.55422 | J9: ='P&L'!J34 -> 468.74366 | K9: ='P&L'!K34 -> 654.11254 | L9: ='P&L'!L34 -> 840.72299 | M9: = P&L EBIT (row 33)
A10: Less: Cash taxes on EBIT | B10: $M | D10: ='P&L'!D41 -> 0 | E10: ='P&L'!E41 -> 0 | F10: ='P&L'!F41 -> 0 | G10: ='P&L'!G41 -> 1.6811173 | H10: ='P&L'!H41 -> 9.0528636 | I10: ='P&L'!I41 -> 69.068191 | J10: ='P&L'!J41 -> 122.49339 | K10: ='P&L'!K41 -> 169.34224 | L10: ='P&L'!L41 -> 217.40437 | M10: = P&L Cash Taxes (row 40), tax-affected at effective rate
A11: NOPAT | B11: $M | D11: =D9-D10 -> -109.326 | E11: =E9-E10 -> -77.981326 | F11: =F9-F10 -> -97.027368 | G11: =G9-G10 -> 5.5052512 | H11: =H9-H10 -> 151.02563 | I11: =I9-I10 -> 239.48603 | J11: =J9-J10 -> 346.25027 | K11: =K9-K10 -> 484.7703 | L11: =L9-L10 -> 623.31861 | M11: = EBIT − Cash Taxes
A13: 2. NOPAT to Unlevered FCF
A14: Plus: D&A | B14: $M | D14: ='P&L'!D8*Assumptions!$F$52 -> 18.221 | E14: ='P&L'!E8*Assumptions!$F$52 -> 30.731994 | F14: ='P&L'!F8*Assumptions!$F$52 -> 44.917177 | G14: ='P&L'!G8*Assumptions!$F$52 -> 60.317456 | H14: ='P&L'!H8*Assumptions!$F$52 -> 75.556881 | I14: ='P&L'!I8*Assumptions!$F$52 -> 90.229864 | J14: ='P&L'!J8*Assumptions!$F$52 -> 104.23512 | K14: ='P&L'!K8*Assumptions!$F$52 -> 117.26435 | L14: ='P&L'!L8*Assumptions!$F$52 -> 129.0128 | M14: = Revenue × D&A % (Assumptions F52)
A15: Less: CapEx | B15: $M | D15: =-'P&L'!D8*Assumptions!$F$48 -> -20.824 | E15: =-'P&L'!E8*Assumptions!$F$48 -> -35.122279 | F15: =-'P&L'!F8*Assumptions!$F$48 -> -51.333916 | G15: =-'P&L'!G8*Assumptions!$F$48 -> -68.934235 | H15: =-'P&L'!H8*Assumptions!$F$48 -> -86.350721 | I15: =-'P&L'!I8*Assumptions!$F$48 -> -103.11984 | J15: =-'P&L'!J8*Assumptions!$F$48 -> -119.12585 | K15: =-'P&L'!K8*Assumptions!$F$48 -> -134.0164 | L15: =-'P&L'!L8*Assumptions!$F$48 -> -147.44319 | M15: = −(Revenue × CapEx %) (Assumptions F48)
A16: Less: Change in NWC | B16: $M | D16: ='WC & Cash'!D27 -> 100.42958 | E16: ='WC & Cash'!E27 -> 172.48867 | F16: ='WC & Cash'!F27 -> 213.67391 | G16: ='WC & Cash'!G27 -> 213.48946 | H16: ='WC & Cash'!H27 -> 210.18254 | I16: ='WC & Cash'!I27 -> 197.65834 | J16: ='WC & Cash'!J27 -> 192.11999 | K16: ='WC & Cash'!K27 -> 170.70588 | L16: ='WC & Cash'!L27 -> 153.2962 | M16: = From WC & Cash tab (Section 3, Total ΔNWC)
A17: Note: SBC is REAL COST in P&L — do NOT add back | M17: Per methodology Sec 6 — SBC stays in P&L as cash-equivalent expense
A18: Unlevered Free Cash Flow | B18: $M | D18: =D11+D14+D15+D16 -> -11.499425 | E18: =E11+E14+E15+E16 -> 90.117058 | F18: =F11+F14+F15+F16 -> 110.2298 | G18: =G11+G14+G15+G16 -> 210.37793 | H18: =H11+H14+H15+H16 -> 350.41433 | I18: =I11+I14+I15+I16 -> 424.25439 | J18: =J11+J14+J15+J16 -> 523.47953 | K18: =K11+K14+K15+K16 -> 638.72413 | L18: =L11+L14+L15+L16 -> 758.18441 | M18: = NOPAT + D&A + CapEx + ΔNWC
A20: 3. FCF Diagnostics
A21: FCF Margin % | B21: % | D21: =IFERROR(D18/'P&L'!D8,0) -> -0.022088791 | E21: =IFERROR(E18/'P&L'!E8,0) -> 0.10263236 | F21: =IFERROR(F18/'P&L'!F8,0) -> 0.085892378 | G21: =IFERROR(G18/'P&L'!G8,0) -> 0.12207457 | H21: =IFERROR(H18/'P&L'!H8,0) -> 0.16232144 | I21: =IFERROR(I18/'P&L'!I8,0) -> 0.16456751 | J21: =IFERROR(J18/'P&L'!J8,0) -> 0.17577361 | K21: =IFERROR(K18/'P&L'!K8,0) -> 0.19064059 | L21: =IFERROR(L18/'P&L'!L8,0) -> 0.20568855 | M21: FCF / Revenue
A22: Rule of 40 (Growth + FCF Margin) | B22: % | E22: =IFERROR(('P&L'!E8/'P&L'!D8-1)*100 + E21*100,0) -> 78.925736 | F22: =IFERROR(('P&L'!F8/'P&L'!E8-1)*100 + F21*100,0) -> 54.746941 | G22: =IFERROR(('P&L'!G8/'P&L'!F8-1)*100 + G21*100,0) -> 46.493403 | H22: =IFERROR(('P&L'!H8/'P&L'!G8-1)*100 + H21*100,0) -> 41.497509 | I22: =IFERROR(('P&L'!I8/'P&L'!H8-1)*100 + I21*100,0) -> 35.876534 | J22: =IFERROR(('P&L'!J8/'P&L'!I8-1)*100 + J21*100,0) -> 33.099115 | K22: =IFERROR(('P&L'!K8/'P&L'!J8-1)*100 + K21*100,0) -> 31.563903 | L22: =IFERROR(('P&L'!L8/'P&L'!K8-1)*100 + L21*100,0) -> 30.587626 | M22: Revenue Growth % + FCF Margin %

Sheet WC & Cash
A1: WHOOP — Working Capital & Cash Roll-Forward
A2: $M; pre-IPO (no debt service / dividends / buybacks). Replaces FCF-tab ΔNWC plug with explicit WC build.
A3: Detailed WC schedule wired into FCF tab as of this session. DCF EV impact: +$813M.
B5: Units | C5: 2024 | D5: 2025 | E5: 2026 | F5: 2027 | G5: 2028 | H5: 2029 | I5: 2030 | J5: 2031 | K5: 2032 | L5: 2033
A7: 1. Drivers
A8: Avg months remaining on annual sub (deferred rev) | B8: mo | D8: 6
A9: Inventory days (gross adds device cost) | B9: days | D9: 45
A10: Accounts payable days (% of total COGS) | B10: days | D10: 18
A11: Other NWC (% of revenue) | B11: % | D11: 0.015
A12: Pre-existing cash balance (start 2025) | B12: $M | D12: 75
A13: 2024 Deferred Revenue Balance | B13: $M | D13: 220
A14: Series G proceeds (closed Mar 2026) | B14: $M | D14: 0 | E14: 575
A16: 2. Working Capital Balances (Liabilities = Source / Assets = Use)
A17: Deferred Revenue (= End Members × ARPU × mo/12) | B17: $M | C17: =D13 -> 220 | D17: =Members!D34*ARPU!D10*$D$8/12 -> 342.5 | E17: =Members!E34*ARPU!E10*$D$8/12 -> 525.28197 | F17: =Members!F34*ARPU!F10*$D$8/12 -> 742.30748 | G17: =Members!G34*ARPU!G10*$D$8/12 -> 958.77918 | H17: =Members!H34*ARPU!H10*$D$8/12 -> 1171.2255 | I17: =Members!I34*ARPU!I10*$D$8/12 -> 1371.6339 | J17: =Members!J34*ARPU!J10*$D$8/12 -> 1565.3634 | K17: =Members!K34*ARPU!K10*$D$8/12 -> 1738.0856 | L17: =Members!L34*ARPU!L10*$D$8/12 -> 1895.8517
A18: Inventory (= ~45 days of NEXT-yr hardware COGS) | B18: $M | C18: 0 | D18: ='P&L'!E13*$D$9/365 -> 24.530795 | E18: ='P&L'!F13*$D$9/365 -> 30.018236 | F18: ='P&L'!G13*$D$9/365 -> 31.835139 | G18: ='P&L'!H13*$D$9/365 -> 32.879977 | H18: ='P&L'!I13*$D$9/365 -> 32.913463 | I18: ='P&L'!J13*$D$9/365 -> 33.192533 | J18: ='P&L'!K13*$D$9/365 -> 32.120348 | K18: ='P&L'!L13*$D$9/365 -> 31.306429 | L18: =K18*1.05 -> 32.871751
A19: Accounts Payable (= ~18 days of total COGS) | B19: $M | C19: 0 | D19: ='P&L'!D14*$D$10/365 -> 10.26937 | E19: ='P&L'!E14*$D$10/365 -> 10.82536 | F19: ='P&L'!F14*$D$10/365 -> 15.370038 | G19: ='P&L'!G14*$D$10/365 -> 20.032747 | H19: ='P&L'!H14*$D$10/365 -> 24.333667 | I19: ='P&L'!I14*$D$10/365 -> 28.151112 | J19: ='P&L'!J14*$D$10/365 -> 31.471605 | K19: ='P&L'!K14*$D$10/365 -> 34.225323 | L19: ='P&L'!L14*$D$10/365 -> 36.355856
A20: Other NWC (= 1.5% of revenue) | B20: $M | C20: 0 | D20: ='P&L'!D8*$D$11 -> 7.809 | E20: ='P&L'!E8*$D$11 -> 13.170855 | F20: ='P&L'!F8*$D$11 -> 19.250219 | G20: ='P&L'!G8*$D$11 -> 25.850338 | H20: ='P&L'!H8*$D$11 -> 32.38152 | I20: ='P&L'!I8*$D$11 -> 38.669942 | J20: ='P&L'!J8*$D$11 -> 44.672195 | K20: ='P&L'!K8*$D$11 -> 50.256149 | L20: ='P&L'!L8*$D$11 -> 55.291198
A22: 3. Change in WC (positive = cash source)
A23: Δ Deferred Revenue (liability ↑ = source) | B23: $M | D23: =D17-C17 -> 122.5 | E23: =E17-D17 -> 182.78197 | F23: =F17-E17 -> 217.0255 | G23: =G17-F17 -> 216.47171 | H23: =H17-G17 -> 212.44629 | I23: =I17-H17 -> 200.40839 | J23: =J17-I17 -> 193.72957 | K23: =K17-J17 -> 172.7222 | L23: =L17-K17 -> 157.76603
A24: Δ Inventory (asset ↑ = use) | B24: $M | D24: =-(D18-C18) -> -24.530795 | E24: =-(E18-D18) -> -5.4874415 | F24: =-(F18-E18) -> -1.8169026 | G24: =-(G18-F18) -> -1.0448381 | H24: =-(H18-G18) -> -0.033486728 | I24: =-(I18-H18) -> -0.27906968 | J24: =-(J18-I18) -> 1.0721847 | K24: =-(K18-J18) -> 0.81391943 | L24: =-(L18-K18) -> -1.5653215
A25: Δ Accounts Payable (liability ↑ = source) | B25: $M | D25: =D19-C19 -> 10.26937 | E25: =E19-D19 -> 0.5559901 | F25: =F19-E19 -> 4.5446776 | G25: =G19-F19 -> 4.6627098 | H25: =H19-G19 -> 4.3009196 | I25: =I19-H19 -> 3.817445 | J25: =J19-I19 -> 3.3204928 | K25: =K19-J19 -> 2.7537181 | L25: =L19-K19 -> 2.1305333
A26: Δ Other NWC (asset ↑ = use) | B26: $M | D26: =-(D20-C20) -> -7.809 | E26: =-(E20-D20) -> -5.3618546 | F26: =-(F20-E20) -> -6.079364 | G26: =-(G20-F20) -> -6.6001196 | H26: =-(H20-G20) -> -6.5311822 | I26: =-(I20-H20) -> -6.2884211 | J26: =-(J20-I20) -> -6.0022531 | K26: =-(K20-J20) -> -5.5839548 | L26: =-(L20-K20) -> -5.0350485
A27: Total Δ NWC (cash impact) | B27: $M | D27: =SUM(D23:D26) -> 100.42958 | E27: =SUM(E23:E26) -> 172.48867 | F27: =SUM(F23:F26) -> 213.67391 | G27: =SUM(G23:G26) -> 213.48946 | H27: =SUM(H23:H26) -> 210.18254 | I27: =SUM(I23:I26) -> 197.65834 | J27: =SUM(J23:J26) -> 192.11999 | K27: =SUM(K23:K26) -> 170.70588 | L27: =SUM(L23:L26) -> 153.2962
A29: 4. Cash Roll-Forward (pre-IPO; no debt service / dividends / buybacks)
A30: Beginning Cash | B30: $M | D30: =$D$12 -> 75 | E30: =D34 -> 63.500575 | F30: =E34 -> 728.61763 | G30: =F34 -> 838.84744 | H30: =G34 -> 1049.2254 | I30: =H34 -> 1399.6397 | J30: =I34 -> 1823.8941 | K30: =J34 -> 2347.3736 | L30: =K34 -> 2986.0978
A31: + Series G proceeds | B31: $M | D31: =$D$14 -> 0 | E31: =$E$14 -> 575
A32: + Unlevered Free Cash Flow (FCF tab) | B32: $M | D32: =FCF!D18 -> -11.499425 | E32: =FCF!E18 -> 90.117058 | F32: =FCF!F18 -> 110.2298 | G32: =FCF!G18 -> 210.37793 | H32: =FCF!H18 -> 350.41433 | I32: =FCF!I18 -> 424.25439 | J32: =FCF!J18 -> 523.47953 | K32: =FCF!K18 -> 638.72413 | L32: =FCF!L18 -> 758.18441
A34: Ending Cash | B34: $M | D34: =D30+D31+D32 -> 63.500575 | E34: =E30+E31+E32 -> 728.61763 | F34: =F30+F32 -> 838.84744 | G34: =G30+G32 -> 1049.2254 | H34: =H30+H32 -> 1399.6397 | I34: =I30+I32 -> 1823.8941 | J34: =J30+J32 -> 2347.3736 | K34: =K30+K32 -> 2986.0978 | L34: =L30+L32 -> 3744.2822

Sheet WACC Bottom-Up
A1: WHOOP — Bottom-Up WACC Build (Justification)
A2: Cross-check on Damodaran sector approach used in Assumptions!F74. Methodology: 3Y weekly Bloomberg-adjusted betas + Oura tender-anchored liquidity premium. Pure justification — does NOT feed DCF.
A3: Source: research/wacc-bottom-up-build.md (May 5, 2026). Replaces 5Y monthly + Hiive premium methodology.
A5: Executive Summary
A6: • Bottom-up bucket-median unlevered betas (Bloomberg-adj, 3Y weekly): B1 = 1.01, B2 = 1.00 (ex-PTON), B3 = 0.92. Tight clustering.
A7: • WHOOP blended βᵤ = 0.95–0.99 across Bear/Base/Bull; Damodaran sector blended = 0.81–0.85. Delta narrowed from +0.40 (5Y monthly) to +0.10–0.18.
A8: • Revenue-weighted ERP = 4.61% Base (vs. pure US 4.46%); +11bps from ~42% intl mix.
A9: • Liquidity premium = +2.0pp anchored to Oura Jan 2026 tender at 25% discount to Series E (Oct 2025); replaces prior +5pp Hiive figure.
A10: • Bottom-up WACC ~11.6% Base vs. Damodaran sector ~10.4% Base — two methods converge within ~1pp. Triangulation finding.
A13: §1. Per-Comp Inputs & Hamada Unlevered Betas
A14: 3Y weekly OLS regression vs. ^GSPC, 157 obs (May 2023 – May 2026). Bloomberg adj: β_adj = (2/3)×β_raw + (1/3)×1.0. Hamada: βᵤ = βL / [1 + (1−t)×(D/E)].
A16: Comp | B16: Bucket | C16: β_raw | D16: β_adj | E16: R² | F16: Mkt Cap ($M) | G16: Debt ($M) | H16: Cash ($M) | I16: D/E | J16: ETR (3Y agg) | K16: Marg Tax | L16: Tax Used | M16: βᵤ (adj) | N16: βᵤ (raw chk)
A17: Garmin (GRMN) | B17: B1 Hardware | C17: 1.029 | D17: 1.019 | E17: 0.216 | F17: 45250 | G17: 216 | H17: 2700 | I17: =G17/F17 -> 0.0047734807 | J17: 0.111 | K17: 0.21 | L17: =K17 -> 0.21 | M17: =D17/(1+(1-L17)*I17) -> 1.0151717 | N17: =C17/(1+(1-L17)*I17) -> 1.0251342
A18: Peloton (PTON) | B18: B2 Sub (distressed) | C18: 2.283 | D18: 1.855 | E18: 0.185 | F18: 2200 | G18: 1950 | H18: 1180 | I18: =G18/F18 -> 0.88636364 | J18: n/m | K18: 0.25 | L18: =K18 -> 0.25 | M18: =D18/(1+(1-L18)*I18) -> 1.1142662 | N18: =C18/(1+(1-L18)*I18) -> 1.3713584
A19: Spotify (SPOT) | B19: B2 Sub (mature) | C19: 1.014 | D19: 1.01 | E19: 0.134 | F19: 86260 | G19: 549 | H19: 7260 | I19: =G19/F19 -> 0.0063644795 | J19: 0.079 | K19: 0.25 | L19: =K19 -> 0.25 | M19: =D19/(1+(1-L19)*I19) -> 1.0052018 | N19: =C19/(1+(1-L19)*I19) -> 1.0091828
A20: Dexcom (DXCM) | B20: B3 Health Data | C20: 1.08 | D20: 1.054 | E20: 0.119 | F20: 22950 | G20: 1380 | H20: 2420 | I20: =G20/F20 -> 0.060130719 | J20: 0.221 | K20: 0.25 | L20: =K20 -> 0.25 | M20: =D20/(1+(1-L20)*I20) -> 1.0085178 | N20: =C20/(1+(1-L20)*I20) -> 1.0333959
A21: ResMed (RMD) | B21: B3 Health Data | C21: 0.962 | D21: 0.974 | E21: 0.181 | F21: 30150 | G21: 843 | H21: 1660 | I21: =G21/F21 -> 0.027960199 | J21: 0.179 | K21: 0.27 | L21: =K21 -> 0.27 | M21: =D21/(1+(1-L21)*I21) -> 0.9545174 | N21: =C21/(1+(1-L21)*I21) -> 0.94275743
A22: Masimo (MASI) | B22: B3 Health Data | C22: 0.885 | D22: 0.924 | E22: 0.09 | F22: 9310 | G22: 559 | H22: 152 | I22: =G22/F22 -> 0.060042965 | J22: n/m | K22: 0.25 | L22: =K22 -> 0.25 | M22: =D22/(1+(1-L22)*I22) -> 0.88418326 | N22: =C22/(1+(1-L22)*I22) -> 0.84686384
A23: iRhythm (IRTC) | B23: B3 Health Data | C23: 0.816 | D23: 0.877 | E23: 0.057 | F23: 4090 | G23: 729 | H23: 550 | I23: =G23/F23 -> 0.17823961 | J23: n/m | K23: 0.25 | L23: =K23 -> 0.25 | M23: =D23/(1+(1-L23)*I23) -> 0.7735871 | N23: =C23/(1+(1-L23)*I23) -> 0.71978002
A24: R² caveat: range 5.7% (IRTC) to 21.6% (GRMN) — standard error on each β ~±0.20–0.30. Bucket medians of 4 names (B3) more robust than singletons.
A27: §2. Bucket Median Unlevered Betas
A29: Bucket | B29: Comps | C29: Median βᵤ (incl PTON) | D29: Median βᵤ (ex-PTON) | E29: Min | F29: Max | G29: Range
A30: B1 Hardware | B30: GRMN | C30: =MEDIAN(M17) -> 1.0151717 | D30: =MEDIAN(M17) -> 1.0151717 | E30: =MIN(M17) -> 1.0151717 | F30: =MAX(M17) -> 1.0151717 | G30: =F30-E30 -> 0
A31: B2 Subscription | B31: PTON, SPOT | C31: =MEDIAN(M18:M19) -> 1.059734 | D31: =MEDIAN(M19) -> 1.0052018 | E31: =MIN(M18:M19) -> 1.0052018 | F31: =MAX(M18:M19) -> 1.1142662 | G31: =F31-E31 -> 0.1090644
A32: B3 Health Data | B32: DXCM, RMD, MASI, IRTC | C32: =MEDIAN(M20:M23) -> 0.91935033 | D32: =MEDIAN(M20:M23) -> 0.91935033 | E32: =MIN(M20:M23) -> 0.7735871 | F32: =MAX(M20:M23) -> 1.0085178 | G32: =F32-E32 -> 0.23493072
A33: Notes:
A34: • B2 ex-PTON is primary anchor; PTON's Hamada output contaminated by distressed-equity dynamics (D/E 0.89, levered β 1.86 adj).
A35: • B3 4-comp median robust to outliers — anchored by RMD (0.95) and MASI (0.88) as middle two; DXCM (1.01) and IRTC (0.77) are bookends.
A37: §3. Damodaran Sector Cross-Check (Jan 2026)
A39: Bucket | B39: Bottom-up βᵤ (ex-PTON) | C39: Damodaran Sector | D39: Sector βᵤ | E39: # Firms | F39: Delta | G39: 5Y mo Delta (prior)
A40: B1 Hardware | B40: =D30 -> 1.0151717 | C40: Electronics (Consumer & Office) | D40: 0.83 | E40: 8 | F40: =B40-D40 -> 0.18517174 | G40: 0.4
A41: B2 Subscription | B41: =D31 -> 1.0052018 | C41: Software (Entertainment) | D41: 1.01 | E41: 77 | F41: =B41-D41 -> -0.0047981897 | G41: 0.43
A42: B3 Health Data | B42: =D32 -> 0.91935033 | C42: HC Info & Tech | D42: 0.99 | E42: 115 | F42: =B42-D42 -> -0.07064967 | G42: 0.39
A43: Convergence finding: under 3Y weekly methodology, bucket betas converge to within ±0.10 of Damodaran sector medians. Idiosyncratic events filtered out (IRTC 2021 CMS, PTON 2021 collapse); Bloomberg adjustment shrinks toward 1.0.
A46: §4. WHOOP Re-Levered Beta (zero debt → β_L = βᵤ)
A47: Bucket weights pulled live from Assumptions!C84:E86 (Bear/Base/Bull). Damodaran sector blended sourced from Assumptions!C71:E71.
A49: Scenario | B49: B1 Wt | C49: B2 Wt | D49: B3 Wt | E49: B1 βᵤ | F49: B2 βᵤ (ex-PTON) | G49: B3 βᵤ | H49: Blended βᵤ (BU) | I49: Damodaran βᵤ | J49: Delta | K49: Blended βᵤ (PTON-incl)
A50: Bear (40/40/20) | B50: =Assumptions!C83 -> 0.4 | C50: =Assumptions!C84 -> 0.4 | D50: =Assumptions!C85 -> 0.2 | E50: =$D$30 -> 1.0151717 | F50: =$D$31 -> 1.0052018 | G50: =$D$32 -> 0.91935033 | H50: =B50*E50+C50*F50+D50*G50 -> 0.99201948 | I50: =Assumptions!C70 -> 0.85 | J50: =H50-I50 -> 0.14201948 | K50: =B50*$C$30+C50*$C$31+D50*$C$32 -> 1.0138324
A51: Base (20/40/40) | B51: =Assumptions!D83 -> 0.2 | C51: =Assumptions!D84 -> 0.4 | D51: =Assumptions!D85 -> 0.4 | E51: =$D$30 -> 1.0151717 | F51: =$D$31 -> 1.0052018 | G51: =$D$32 -> 0.91935033 | H51: =B51*E51+C51*F51+D51*G51 -> 0.9728552 | I51: =Assumptions!D70 -> 0.83 | J51: =H51-I51 -> 0.1428552 | K51: =B51*$C$30+C51*$C$31+D51*$C$32 -> 0.99466808
A52: Bull (10/30/60) | B52: =Assumptions!E83 -> 0.1 | C52: =Assumptions!E84 -> 0.3 | D52: =Assumptions!E85 -> 0.6 | E52: =$D$30 -> 1.0151717 | F52: =$D$31 -> 1.0052018 | G52: =$D$32 -> 0.91935033 | H52: =B52*E52+C52*F52+D52*G52 -> 0.95468791 | I52: =Assumptions!E70 -> 0.81 | J52: =H52-I52 -> 0.14468791 | K52: =B52*$C$30+C52*$C$31+D52*$C$32 -> 0.97104757
A53: Bloomberg adjustment effect on WHOOP-blended is trivial (<0.02) since blend is already centered near 1.0. Remaining +0.10 to +0.18 vs. Damodaran reflects genuine WHOOP-comp-specific premium over broad sector medians.
A54: Note: Damodaran βᵤ in Assumptions!C71:E71 is bucket-weighted (Bear 0.85/Base 0.83/Bull 0.81 — higher β = more bearish, i.e. B1-heavy hardware mix). Bottom-up bucket-weighted output uses identical weights, so deltas are consistent across all three scenarios.
A57: §5. Revenue-Weighted ERP
A58: WHOOP intl mix ~42% (per stress-test). Intl blend: 50% UK/EU developed, 30% Asia developed, 20% other/GCC.
A60: Country ERPs (Damodaran Jan 2026) | C60: ERP
A61: US | C61: 0.0446
A62: UK / EU developed avg | C62: 0.046
A63: Asia developed avg (JP/AU/SG) | C63: 0.0453
A64: Other / GCC / emerging | C64: 0.057
A66: Blended International ERP | C66: =0.5*C62+0.3*C63+0.2*C64 -> 0.04799
A68: Sensitivity: Intl revenue weight | B68: Intl Wt | C68: US Contrib | D68: Intl Contrib | E68: Blended ERP
A69: Conservative | B69: 0.35 | C69: =(1-B69)*$C$61 -> 0.02899 | D69: =B69*$C$66 -> 0.0167965 | E69: =C69+D69 -> 0.0457865
A70: Base case | B70: 0.42 | C70: =(1-B70)*$C$61 -> 0.025868 | D70: =B70*$C$66 -> 0.0201558 | E70: =C70+D70 -> 0.0460238
A71: Aggressive | B71: 0.5 | C71: =(1-B71)*$C$61 -> 0.0223 | D71: =B71*$C$66 -> 0.023995 | E71: =C71+D71 -> 0.046295
A72: Net effect: +11-19bp vs. pure US ERP. Most intl revenue is developed-market with ERPs near US base — token adjustment, not a swing factor.
A75: §6. Liquidity Premium — Oura Tender Anchor
A76: Oura Jan 2026 tender priced at 25% discount to Oct 2025 Series E (~3-month gap → minimal stale-pricing decay; close to pure DLOM for high-quality wearable comp on credible IPO path).
A78: Translation: DLOM → WACC add-on
A79: Public-comp WACC base (Damodaran sector) | C79: =Assumptions!D73-Assumptions!D72 -> 0.08845
A80: Terminal growth (g) | C80: =Assumptions!D79 -> 0.03
A81: Public (r − g) | C81: =C79-C80 -> 0.05845
A83: DLOM scenario | B83: DLOM % | C83: PV haircut | D83: (r−g) ratio | E83: New (r−g) | F83: Implied add-on
A84: Optimistic (shorter time-to-IPO) | B84: 0.15 | C84: =-B84 -> -0.15 | D84: =1/(1-B84) -> 1.1764706 | E84: =$C$81*D84 -> 0.068764706 | F84: =E84-$C$81 -> 0.010314706
A85: Base (Oura tender) | B85: 0.25 | C85: =-B85 -> -0.25 | D85: =1/(1-B85) -> 1.3333333 | E85: =$C$81*D85 -> 0.077933333 | F85: =E85-$C$81 -> 0.019483333
A86: Conservative (Oura + WHOOP-specific) | B86: 0.35 | C86: =-B86 -> -0.35 | D86: =1/(1-B86) -> 1.5384615 | E86: =$C$81*D86 -> 0.089923077 | F86: =E86-$C$81 -> 0.031473077
A88: Recommended liquidity premium | B88: Bear | C88: Base | D88: Bull
A89: Bottom-up + Oura | B89: 0.025 | C89: 0.02 | D89: 0.015
A90: Existing model (Assumptions!F73) | B90: =Assumptions!C72 -> 0.03 | C90: =Assumptions!D72 -> 0.02 | D90: =Assumptions!E72 -> 0.01
A91: Why not Hiive (-39 to -51%)? Hiive prices common (subordinated to $291M preference stack), captures secondary-market valuation skepticism (not pure DLOM), and reflects thin order-book depth. Oura tender = company-organized, structured price = controlled signal.
A92: Oura's +2.0pp ratifies the existing 1.5% practitioner midpoint with a market anchor.
A95: §7. Synthesis WACC: Bottom-Up vs. Damodaran Sector
A96: Cost of Equity = WACC (zero debt). Build A = current model approach (Assumptions). Build B = bottom-up justification (this tab).
A98: Component | B98: Build A: Damodaran Sector | E98: Build B: Bottom-Up + Oura | H98: Delta (Base)
B99: Bear | C99: Base | D99: Bull | E99: Bear | F99: Base | G99: Bull
A100: Risk-free rate (10Y UST) | B100: =Assumptions!C68 -> 0.043 | C100: =Assumptions!D68 -> 0.043 | D100: =Assumptions!E68 -> 0.043 | E100: =Assumptions!C68 -> 0.043 | F100: =Assumptions!D68 -> 0.043 | G100: =Assumptions!E68 -> 0.043 | H100: =F100-C100 -> 0
A101: Equity Risk Premium | B101: =Assumptions!C69 -> 0.045 | C101: =Assumptions!D69 -> 0.045 | D101: =Assumptions!E69 -> 0.045 | E101: =$E$70 -> 0.0460238 | F101: =$E$70 -> 0.0460238 | G101: =$E$70 -> 0.0460238 | H101: =F101-C101 -> 0.0010238
A102: Unlevered Beta (= levered, no debt) | B102: =Assumptions!C70 -> 0.85 | C102: =Assumptions!D70 -> 0.83 | D102: =Assumptions!E70 -> 0.81 | E102: =$H$50 -> 0.99201948 | F102: =$H$51 -> 0.9728552 | G102: =$H$52 -> 0.95468791 | H102: =F102-C102 -> 0.1428552
A103: Size Premium (CRSP Decile 3) | B103: =Assumptions!C71 -> 0.0081 | C103: =Assumptions!D71 -> 0.0081 | D103: =Assumptions!E71 -> 0.0081 | E103: =Assumptions!C71 -> 0.0081 | F103: =Assumptions!D71 -> 0.0081 | G103: =Assumptions!E71 -> 0.0081 | H103: =F103-C103 -> 0
A104: Liquidity Premium (Oura-anchored vs. CSRP) | B104: =Assumptions!C72 -> 0.03 | C104: =Assumptions!D72 -> 0.02 | D104: =Assumptions!E72 -> 0.01 | E104: =$B$89 -> 0.025 | F104: =$C$89 -> 0.02 | G104: =$D$89 -> 0.015 | H104: =F104-C104 -> 0
A106: Implied WACC | B106: =B100+B101*B102+B103+B104 -> 0.11935 | C106: =C100+C101*C102+C103+C104 -> 0.10845 | D106: =D100+D101*D102+D103+D104 -> 0.09755 | E106: =E100+E101*E102+E103+E104 -> 0.12175651 | F106: =F100+F101*F102+F103+F104 -> 0.11587449 | G106: =G100+G101*G102+G103+G104 -> 0.11003837 | H106: =F106-C106 -> 0.0074244933
A108: Decomposition of Build B − Build A delta (Base case) | C108: Contribution
A109: Beta upgrade (0.83 → 0.97) | C109: =(F102-C102)*F101 -> 0.0065747393
A110: ERP revenue-weighting (4.50% → 4.60%) | C110: =(F101-C101)*C102 -> 0.000849754
A111: Liquidity premium (CSRP 2.00% → Oura 2.00%) | C111: =F104-C104 -> 0
A112: Total | C112: =SUM(C109:C111) -> 0.0074244933
A114: Triangulation: Build A (10.85% Base, current model) and Build B (~11.6% Base, this tab) converge within ~0.7-0.8pp — two independent methods landing close gives the IC committee triangulation confidence. The +0.7pp delta is essentially the bottom-up beta premium (+0.65pp); ERP and liquidity rounding effects are trivial.
A115: Bottoms-Up WACC — By Scenario
A116: CAPM build from raw market data. Bucket-weighted βᵤ, revenue-weighted ERP (42% intl mix), Oura-tender-anchored liquidity premium.
A118: Component | B118: Bear | C118: Base | D118: Bull | E118: Source / Anchor
A119: Risk-free rate (10Y UST) | B119: =F100 -> 0.043 | C119: =F100 -> 0.043 | D119: =F100 -> 0.043 | E119: Bloomberg, May 2026
A120: Bucket-weighted βᵤ | B120: =H50 -> 0.99201948 | C120: =H51 -> 0.9728552 | D120: =H52 -> 0.95468791 | E120: Median of bucket comp betas × scenario weights (see bottom panel)
A121: Revenue-weighted ERP | B121: =E69 -> 0.0457865 | D121: =E71 -> 0.046295
A122: β × ERP contribution | B122: =B120*B121 -> 0.0454211 | D122: =D120*D121 -> 0.044197277
A123: Size premium (CRSP Decile 3) | B123: =F103 -> 0.0081 | D123: =F103 -> 0.0081
A124: Liquidity premium (Oura-anchored) | B124: =B89 -> 0.025 | D124: =D89 -> 0.015
A125: WACC | B125: =E106 -> 0.12175651 | D125: =G106 -> 0.11003837
A128: Bucket-Weighted Unlevered Beta — Industry Mix by Scenario | B128: Public-comp WACC base for Oura translation — if 11% used vs 10%, +2pp → +1.8pp | D128: Documented; the 10% base is itself the Damodaran sector output
A129: Three industry buckets, each with median βᵤ from comparable public peers. Scenario weights reflect business-mix evolution — Bull = healthcare-heavy.
A131: Bucket | B131: βᵤ (median) | C131: Bear wt. | D131: Base wt. | E131: Bull wt. | F131: Comp Set
A132: Consumer hardware | B132: =D30 -> 1.0151717 | C132: =Assumptions!C83 -> 0.4 | D132: =Assumptions!D83 -> 0.2 | E132: =Assumptions!E83 -> 0.1 | F132: Garmin, GoPro, Sonos
...

Sheet DCF
A1: WHOOP — Discounted Cash Flow
A2: ="$M; Calendar Year; Base case (Assumptions!B3 = "&Assumptions!B3&") — WACC "&TEXT(Assumptions!F74,"0.00%")&" / Exit Mult "&TEXT(Assumptions!F77,"0.0\x")&" / Term g "&TEXT(Assumptions!F79,"0.0%")&" → EV "&TEXT(C32/1000,"$0.00\B")&" / Equity "&TEXT(C38/1000,"$0.00\B")&" / "&TEXT(C40,"$0.00")&"/sh. See Sensitivity tab for ranges." -> $M; Calendar Year; Base case (Assumptions!B3 = Base) — WACC 11.59% / Exit Mult 3.5x / Term g 3.0% → EV $6.60B / Equity $7.32B / $17.86/sh. See Sensitivity tab for ranges.
A3: ="⚠ Integrity flags: TV divergence "&TEXT(C24,"0.0%")&" (threshold 25%) — "&IF(C24>0.25,"OVER","OK")&"; TV % EV "&TEXT(C27,"0.0%")&" (threshold 75%) — "&IF(C27>0.75,"OVER","OK")&". See notes on C24, C27." -> ⚠ Integrity flags: TV divergence 34.6% (threshold 25%) — OVER; TV % EV 73.2% (threshold 75%) — OK. See notes on C24, C27.
B5: Units | C5: 2025 | D5: 2026 | E5: 2027 | F5: 2028 | G5: 2029 | H5: 2030 | I5: 2031 | J5: 2032 | K5: 2033
A7: 1. Cash Flow & Discounting
A8: Revenue (memo) | B8: $M | C8: ='P&L'!D8 -> 520.6 | D8: ='P&L'!E8 -> 878.05698 | E8: ='P&L'!F8 -> 1283.3479 | F8: ='P&L'!G8 -> 1723.3559 | G8: ='P&L'!H8 -> 2158.768 | H8: ='P&L'!I8 -> 2577.9961 | I8: ='P&L'!J8 -> 2978.1463 | J8: ='P&L'!K8 -> 3350.41 | K8: ='P&L'!L8 -> 3686.0799 | M8: ← From P&L tab
A9: Unlevered Free Cash Flow | B9: $M | C9: =FCF!D18 -> -11.499425 | D9: =FCF!E18 -> 90.117058 | E9: =FCF!F18 -> 110.2298 | F9: =FCF!G18 -> 210.37793 | G9: =FCF!H18 -> 350.41433 | H9: =FCF!I18 -> 424.25439 | I9: =FCF!J18 -> 523.47953 | J9: =FCF!K18 -> 638.72413 | K9: =FCF!L18 -> 758.18441 | M9: ← From FCF tab (single source of truth)
A10: FCF Margin % | B10: % | C10: =IFERROR(C9/C8,0) -> -0.022088791 | D10: =IFERROR(D9/D8,0) -> 0.10263236 | E10: =IFERROR(E9/E8,0) -> 0.085892378 | F10: =IFERROR(F9/F8,0) -> 0.12207457 | G10: =IFERROR(G9/G8,0) -> 0.16232144 | H10: =IFERROR(H9/H8,0) -> 0.16456751 | I10: =IFERROR(I9/I8,0) -> 0.17577361 | J10: =IFERROR(J9/J8,0) -> 0.19064059 | K10: =IFERROR(K9/K8,0) -> 0.20568855
A12: WACC | B12: % | C12: n/a | D12: =Assumptions!$F$74 -> 0.11587449 | E12: =Assumptions!$F$74 -> 0.11587449 | F12: =Assumptions!$F$74 -> 0.11587449 | G12: =Assumptions!$F$74 -> 0.11587449 | H12: =Assumptions!$F$74 -> 0.11587449 | I12: =Assumptions!$F$74 -> 0.11587449 | J12: =Assumptions!$F$74 -> 0.11587449 | K12: =Assumptions!$F$74 -> 0.11587449 | M12: ← From Assumptions F74
A13: Discount Period (mid-year) | B13: yrs | C13: n/a | D13: 0.5 | E13: 1.5 | F13: 2.5 | G13: 3.5 | H13: 4.5 | I13: 5.5 | J13: 6.5 | K13: 7.5 | M13: Mid-year convention
A14: Discount Factor | B14: x | C14: n/a | D14: =1/(1+D12)^D13 -> 0.94665629 | E14: =1/(1+E12)^E13 -> 0.84835373 | F14: =1/(1+F12)^F13 -> 0.76025909 | G14: =1/(1+G12)^G13 -> 0.68131237 | H14: =1/(1+H12)^H13 -> 0.61056362 | I14: =1/(1+I12)^I13 -> 0.54716155 | J14: =1/(1+J12)^J13 -> 0.49034327 | K14: =1/(1+K12)^K13 -> 0.43942511
A15: PV of Unlevered FCF | B15: $M | C15: n/a | D15: =D9*D14 -> 85.30988 | E15: =E9*E14 -> 93.513866 | F15: =F9*F14 -> 159.94173 | G15: =G9*G14 -> 238.74162 | H15: =H9*H14 -> 259.0343 | I15: =I9*I14 -> 286.42787 | J15: =J9*J14 -> 313.19408 | K15: =K9*K14 -> 333.16527 | M15: = UFCF / (1+WACC)^period
A17: 2. Terminal Value
A18: Terminal Year Revenue | B18: $M | C18: =K8 -> 3686.0799
A19: Terminal Year EBITDA | B19: $M | C19: ='P&L'!L32 -> 1246.1918
A20: Terminal Year FCF | B20: $M | C20: =K9 -> 758.18441
A21: Exit Multiple (EV/Revenue) | B21: x | C21: =Assumptions!$F$77 -> 3.5 | L21: ← From Assumptions F78
A22: Terminal Value (Exit Multiple) | B22: $M | C22: =C18*C21 -> 12901.28
A23: Terminal Value (Gordon Growth) | B23: $M | C23: =C20*(1+Assumptions!$F$79)/(D12-Assumptions!$F$79) -> 9093.8521 | L23: Gordon: =FCF × (1+g) / (WACC − g)
A24: TV Method Divergence | B24: % | C24: =ABS(C22-C23)/((C22+C23)/2) -> 0.34620638 | L24: If >25%, an assumption is inconsistent
A25: Selected Terminal Value | B25: $M | C25: =(C23+C22) / 2 -> 10997.566
A26: PV of Terminal Value | B26: $M | C26: =C25*K14 -> 4832.6066
A27: TV as % of Total EV | B27: % | C27: =C26/(C26+SUM(D15:K15)) -> 0.73199849 | L27: If >75%, explicit forecast doing too little
A29: 3. Enterprise Value Summary
A30: Sum of PV of FCFs (2026-2033) | B30: $M | C30: =SUM(D15:K15) -> 1769.3286
A31: PV of Terminal Value | B31: $M | C31: =C26 -> 4832.6066
A32: Enterprise Value (DCF Base) | B32: $M | C32: =C30+C31 -> 6601.9352
A34: 4. Equity Bridge
A35: Enterprise Value | B35: $M | C35: =C32 -> 6601.9352
A36: Less: Debt | B36: $M | C36: =-Assumptions!$F$61 -> -10 | L36: ~$0 (minimal)
A37: Plus: Cash | B37: $M | C37: ='WC & Cash'!E34 -> 728.61763 | L37: $600-800M est. post-Series G
A38: Equity Value | B38: $M | C38: =C35+C36+C37 -> 7320.5528
A39: Fully Diluted Shares (M) | B39: M | C39: =Assumptions!$F$54 -> 410 | L39: ~900M (PremierAlts est.)
A40: Equity Value per Share | B40: $/sh | C40: =C38/C39 -> 17.855007
A42: 5. Real Options (Additive — healthcare pathway only)
A43: Healthcare option — Bear scenario range ($M) | B43: $M | C43: =RealOptions!B31 -> 164.15584 | L43: ← Probability × Payoff from Assumptions
A44: Healthcare option — Bull scenario range ($M) | B44: $M | C44: =RealOptions!D31 -> 2833.6519
A45: Healthcare option — active scenario ($M) | B45: $M | C45: =RealOptions!B36 -> 940.08677
A46: Expected Option Value | B46: $M | C46: n/a
A47: Total EV (DCF + Options) | B47: $M | C47: n/a
A49: 6. Scenario Comparison vs Series G — Equity Value Basis
A50: DCF Base Case Equity Value | B50: $M | C50: =C38 -> 7320.5528
A51: DCF + Options Equity Value | B51: $M | C51: n/a
A52: Series G Mark | B52: $M | C52: 10100
A53: DCF Premium / (Discount) to Series G | B53: % | C53: =C50/C52-1 -> -0.27519279 | M53: Base case = 'WHOOP executes plan'
A54: DCF + Options Premium / (Discount) to Series G | B54: % | C54: n/a | M54: Options = 'Healthcare reimbursement pathway materializes (probability-weighted, 15-25%)'
A56: 7. Probability-Weighting Diagnostics — Input vs Scenario Weighting Triangulation
A57: Diagnostic block compares input-level weighting (ProbWeighted scenario) vs. scenario-level weighting (independent DCF runs combined). Jensen gap = E[DCF(inputs)] vs P_w · DCF(scenario). Static snapshot — refreshed after bottom-up WACC rewire + shares-out update to 410M. Toggle Assumptions!B3 and refresh manually after material input changes.
A59: Scenario | B59: DCF EV ($M) | C59: Equity ($M) | D59: vs Series G
A60: Bear (after R79 bug fix) | B60: 2048.89 | C60: 2496.75 | D60: =C60/$C$52-1 -> -0.75279703
A61: Base | B61: 6601.94 | C61: 7320.55 | D61: =C61/$C$52-1 -> -0.27519307
A62: Bull | B62: 23635.53 | C62: 24657.67 | D62: =C62/$C$52-1 -> 1.4413535
A63: ProbWeighted (input-level) | B63: 7458.63 | C63: 8185.67 | D63: =C63/$C$52-1 -> -0.18953762
A65: Scenario-weighted bookend (P_Bear=20%, P_Base=50%, P_Bull=30%) | B65: =0.2*B60+0.5*B61+0.3*B62 -> 10801.407 | C65: =0.2*C60+0.5*C61+0.3*C62 -> 11556.926
A67: Jensen Gap Analysis (scenario-weighted minus input-weighted)
A68: EV gap ($M) | B68: =B65-B63 -> 3342.777 | C68: =C65-C63 -> 3371.256
A69: EV gap (%) | B69: =B65/B63-1 -> 0.44817574 | C69: =C65/C63-1 -> 0.41184851
A70: Interpretation:
A71: • Positive gap = DCF is convex in inputs; ProbWeighted UNDERSTATES true E[EV]. Use scenario-weighted as upper anchor.
A72: • Negative gap = DCF is concave; ProbWeighted OVERSTATES. Use input-weighted as conservative anchor.
A73: • Headline = ProbWeighted (row 63). Bookend = scenario-weighted (row 65). Memo should cite both with the gap as the dispersion story.
A74: • Snapshot manually refreshed via validation pass; rerun if any of the 20 ProbWeighted-eligible inputs change materially. Last refresh: ProbWeighted equity = $8,091M (post-rebalance to 20-driver set: dropped 10 low-impact inputs, added 7 SBC/CapEx/NWC/Tax drivers).

Sheet RealOptions
A1: WHOOP — Real Options (Healthcare Pathway)
A2: Single-gate decision tree on reimbursable healthcare platform thesis. Class anchor: Lecture 3B (Arundel) — probability-weighted call option on uncertain future cash flows. Decision tree EV; underlying not tradable, so not Black-Scholes. Same economic logic as Arundel sequel rights.
A4: Section 1 — The Binary Gate
A5: Question: Does WHOOP become a reimbursable healthcare platform within decision window?
B6: Bear | C6: Base | D6: Bull
A7: Probability healthcare materializes | B7: =Assumptions!$C$155 -> 0.15 | C7: =Assumptions!$D$155 -> 0.2 | D7: =Assumptions!$E$155 -> 0.25
A8: Probability of failure / indefinite stall | B8: =1-B7 -> 0.85 | C8: =1-C7 -> 0.8 | D8: =1-D7 -> 0.75
A10: Section 2 — Revenue Impact if Materialized
A11: (Computed three times: Bear / Base / Bull scenarios)
A13: 2033 ending members (M) | B13: =Assumptions!C176 -> 7.4999193 | C13: =Assumptions!D176 -> 10.924108 | D13: =Assumptions!E176 -> 18.106692
A14: × Eligibility % (qualifying conditions) | B14: =Assumptions!$C$156 -> 0.3 | C14: =Assumptions!$D$156 -> 0.4 | D14: =Assumptions!$E$156 -> 0.45
A15: = Eligible members (M) | B15: =B13*B14 -> 2.2499758 | C15: =C13*C14 -> 4.3696432 | D15: =D13*D14 -> 8.1480114
A17: × Payer-paid annual ARPU ($/member) | B17: =Assumptions!$C$157 -> 200 | C17: =Assumptions!$D$157 -> 300 | D17: =Assumptions!$E$157 -> 350
A18: = Incremental annual revenue at maturity ($M) | B18: =B15*B17 -> 449.99516 | C18: =C15*C17 -> 1310.893 | D18: =D15*D17 -> 2851.804
A20: × Healthcare-anchored multiple (x revenue) | B20: =Assumptions!$C$158 -> 5 | C20: =Assumptions!$D$158 -> 6 | D20: =Assumptions!$E$158 -> 6
A21: = Incremental EV at exercise ($M) — undiscounted | B21: =B18*B20 -> 2249.9758 | C21: =C18*C20 -> 7865.3578 | D21: =D18*D20 -> 17110.824
A24: Section 3 — Discounting and Probability Weighting
A25: Years to exercise | B25: =Assumptions!$C$159 -> 7 | C25: =Assumptions!$D$159 -> 5 | D25: =Assumptions!$E$159 -> 4
A26: WACC | B26: =Assumptions!$F$73 -> 0.10845 | C26: =Assumptions!$F$73 -> 0.10845 | D26: =Assumptions!$F$73 -> 0.10845
A27: Discount factor (1/(1+WACC)^t) | B27: =1/(1+B26)^B25 -> 0.48639292 | C27: =1/(1+C26)^C25 -> 0.59761221 | D27: =1/(1+D26)^D25 -> 0.66242325
A28: Discounted incremental EV ($M) | B28: =B21*B27 -> 1094.3723 | C28: =C21*C27 -> 4700.4339 | D28: =D21*D27 -> 11334.608
A30: × Probability of materialization | B30: =B7 -> 0.15 | C30: =C7 -> 0.2 | D30: =D7 -> 0.25
A31: = Expected option value ($M) | B31: =B28*B30 -> 164.15584 | C31: =C28*C30 -> 940.08677 | D31: =D28*D30 -> 2833.6519
A32: = Expected option value ($B) | B32: =B31/1000 -> 0.16415584 | C32: =C31/1000 -> 0.94008677 | D32: =D31/1000 -> 2.8336519
A34: Section 4 — Active Scenario Output
A35: Active scenario | B35: =Assumptions!$B$3 -> Base
A36: Expected option value (active scenario, $M) | B36: =IF($B$35="Bear",B31,IF($B$35="Bull",D31,C31)) -> 940.08677
A37: Expected option value (active scenario, $B) | B37: =B36/1000 -> 0.94008677
A38: Scenario-weighted Expected Option Value (across-scenario, $M) | B38: =Assumptions!$C$2*B31+Assumptions!$E$2*C31+Assumptions!$G$2*D31 -> 1352.9701 | C38: = P_Bear×Bear + P_Base×Base + P_Bull×Bull on B31:D31. Two-layer probability: each scenario already weights by P(materialize) at row 30; this layer weights ACROSS scenarios at the 20/50/30 macro split. Not double-counting — they compound. Asymmetric vs DCF approach: option inputs are coupled at scenario level (eligibility, ARPU, multiple, timing, materialize-prob all move together), so input-weighting cross-scenario would be incoherent. Scenario-weighted is the only valid cross-scenario aggregation for the option.
A39: Scenario-weighted Expected Option Value ($B) | B39: =B38/1000 -> 1.3529701
A40: Section 5 — Justification (memo, not driver)
A41: Honest read on what supports each input. Cite specific comparables and signals.
A43: Probability anchor (RO1 — 15/20/25%)
A44: iRhythm pathway: FDA-cleared cardiac monitoring, took 7+ years from approval to stable national CMS reimbursement. Stock dropped 83% during journey. Base rate evidence for consumer→medical transitions: low and slow.
A45: Dexcom pathway: 15+ year ongoing reimbursement expansion from initial Type 1 diabetes coverage. Each new indication requires separate CMS review.
A46: WHOOP-specific positive signals: CMS Innovation Center Access Program selection (Apr 13, 2026); Abbott + Mayo Clinic as Series G investors; FDA-cleared ECG already shipping; BP Insights with FDA wellness exemptions (Jan 2026).
A47: WHOOP-specific gaps: zero CPT codes filed; no clinical trial data validating diagnostic claims; no disclosed Abbott/Mayo deliverables; no payer revenue projections.
A48: Probability range 15-25% reflects: (a) credible signals justify above pure base rate, (b) absence of clinical/regulatory milestones bounds upside.
A50: Eligibility anchor (RO2 — 30/40/45%)
A51: ~40% of US adults have cardiometabolic risk factors (CDC: 47% HTN, 38% pre-diabetes, 9-12% AFib risk in over-65s, 30% sleep disorders).
A52: WHOOP user base premium-skewed (high health engagement); plausibly overrepresents diagnosable risk factors.
A53: Range 30-45%: bear conservative (only severe cases qualify); bull at calibrated upper end (was 50% wide, tightened to 45% — broad screening eligibility but stops short of aggressive).
... A83: Pushback 1 — "Bull case is consumer-driven, not healthcare-driven"
A84: Acknowledged. Bull case member growth (MG1-MG8 in Assumptions row 169-176) is justified by Series G capital deployment and brand step-function (Peloton-stage IPO mechanics) — NOT by reimbursement assumption. Bull DCF reaches $19.88B equity / $48.49/sh on consumer-only thesis. Healthcare option is layered ON TOP, not embedded IN, the consumer Bull. The two are independent paths: consumer base materializes through ad spend, athlete partnerships, brand awareness; healthcare path materializes through CMS/CPT/clinical work. Conflating them inflates probability — the model treats them as separate (DCF runs on consumer assumptions; option valued discretely; scenario-weighted EV adds them). | B84: Within-Scenario EV ($M) | C84: Macro Weight | D84: Contribution ($M) | E84: % of Total
A85: Bear | B85: =B31 -> 164.15584 | C85: =Assumptions!$C$2 -> 0.2 | D85: =B85*C85 -> 32.831169 | E85: =D85/$D$88 -> 0.024265997
A86: Pushback 2 — "You're already getting an implicit option premium in the comps multiple" | B86: =C31 -> 940.08677 | C86: =Assumptions!$E$2 -> 0.5 | D86: =B86*C86 -> 470.04339 | E86: =D86/$D$88 -> 0.34741594
A87: Partly fair. Consumer wearables comps trade at 3-5x revenue; bucket-3 medtech (Dexcom/ResMed/Masimo/iRhythm) at 5.0-6.4x. WHOOP's blended comp implies the market already prices SOME healthcare optionality — estimating this premium at +0.5-1.0x revenue (= roughly $220-440M EV at 2033 revenue of $3.7B and 12% probability-weighted discount). Recommend interpreting the explicit option value (B36 Base $940M / B38 Scen-Wtd $1,286M) as the FULL PV of the medical pathway, with the comps premium as a CHECK rather than additive layer. If sensitive to double-counting, conservative read: option value PROVES IN at $700-1,000M after netting estimated multiple premium. Memo recommendation: present option value as standalone module; let reader subtract comps premium if they believe it's already priced. | B87: =D31 -> 2833.6519 | C87: =Assumptions!$G$2 -> 0.3 | D87: =B87*C87 -> 850.09558 | E87: =D87/$D$88 -> 0.62831807
A88: Scenario-Weighted Total | C88: =SUM(C85:C87) -> 1 | D88: =SUM(D85:D87) -> 1352.9701 | E88: =SUM(E85:E87) -> 1
A89: Pushback 3 — "What if the medical pathway doesn't materialize — are you overpaying for ARPU?"
A90: Defensible. Consumer ARPU ($338/yr at 2033, blended consumer + B2B) is the primary subscription revenue — NOT contingent on payer reimbursement. WHOOP currently bills $200-300/yr direct-to-consumer at scale. Even if zero medical revenue ever materializes (P(materialize)=0%), the consumer ARPU remains intact. The healthcare option is upside ON TOP of consumer ARPU, not a substitute. The only ARPU at risk is incremental medical-bill ARPU ($200-350/yr from RO3) which only flows in scenarios where the option triggers. Bear case ($164M option) effectively models the "medical doesn't materialize" outcome — still positive because even probability-weighted at 15% × $1.07B intrinsic = $164M residual.
A91: Block B — Total Option Value at Varying Macro Probability Weights ($M)
A92: 5×5 grid: rows = P_Bear, columns = P_Bull. P_Base = 1 - P_Bear - P_Bull. Yellow center = current 20/50/30 macro weights ($1.29B). Cells where P_Bear+P_Bull ≥ 1 return #N/A (invalid).
A94: P_Bear ↓ / P_Bull → | B94: 0.1 | C94: 0.2 | D94: 0.3 | E94: 0.4 | F94: 0.5
A95: 0.1 | B95: =IF($A95+B$94>=1,NA(),$A95*$B$31+(1-$A95-B$94)*$C$31+B$94*$D$31) -> 1051.8502 | C95: =IF($A95+C$94>=1,NA(),$A95*$B$31+(1-$A95-C$94)*$C$31+C$94*$D$31) -> 1241.2067 | D95: =IF($A95+D$94>=1,NA(),$A95*$B$31+(1-$A95-D$94)*$C$31+D$94*$D$31) -> 1430.5632 | E95: =IF($A95+E$94>=1,NA(),$A95*$B$31+(1-$A95-E$94)*$C$31+E$94*$D$31) -> 1619.9197 | F95: =IF($A95+F$94>=1,NA(),$A95*$B$31+(1-$A95-F$94)*$C$31+F$94*$D$31) -> 1809.2763
A96: 0.15 | B96: =IF($A96+B$94>=1,NA(),$A96*$B$31+(1-$A96-B$94)*$C$31+B$94*$D$31) -> 1013.0536 | C96: =IF($A96+C$94>=1,NA(),$A96*$B$31+(1-$A96-C$94)*$C$31+C$94*$D$31) -> 1202.4102 | D96: =IF($A96+D$94>=1,NA(),$A96*$B$31+(1-$A96-D$94)*$C$31+D$94*$D$31) -> 1391.7667 | E96: =IF($A96+E$94>=1,NA(),$A96*$B$31+(1-$A96-E$94)*$C$31+E$94*$D$31) -> 1581.1232 | F96: =IF($A96+F$94>=1,NA(),$A96*$B$31+(1-$A96-F$94)*$C$31+F$94*$D$31) -> 1770.4797
A97: 0.2 | B97: =IF($A97+B$94>=1,NA(),$A97*$B$31+(1-$A97-B$94)*$C$31+B$94*$D$31) -> 974.2571 | C97: =IF($A97+C$94>=1,NA(),$A97*$B$31+(1-$A97-C$94)*$C$31+C$94*$D$31) -> 1163.6136 | D97: =IF($A97+D$94>=1,NA(),$A97*$B$31+(1-$A97-D$94)*$C$31+D$94*$D$31) -> 1352.9701 | E97: =IF($A97+E$94>=1,NA(),$A97*$B$31+(1-$A97-E$94)*$C$31+E$94*$D$31) -> 1542.3266 | F97: =IF($A97+F$94>=1,NA(),$A97*$B$31+(1-$A97-F$94)*$C$31+F$94*$D$31) -> 1731.6832
A98: 0.25 | B98: =IF($A98+B$94>=1,NA(),$A98*$B$31+(1-$A98-B$94)*$C$31+B$94*$D$31) -> 935.46056 | C98: =IF($A98+C$94>=1,NA(),$A98*$B$31+(1-$A98-C$94)*$C$31+C$94*$D$31) -> 1124.8171 | D98: =IF($A98+D$94>=1,NA(),$A98*$B$31+(1-$A98-D$94)*$C$31+D$94*$D$31) -> 1314.1736 | E98: =IF($A98+E$94>=1,NA(),$A98*$B$31+(1-$A98-E$94)*$C$31+E$94*$D$31) -> 1503.5301 | F98: =IF($A98+F$94>=1,NA(),$A98*$B$31+(1-$A98-F$94)*$C$31+F$94*$D$31) -> 1692.8866
A99: 0.3 | B99: =IF($A99+B$94>=1,NA(),$A99*$B$31+(1-$A99-B$94)*$C$31+B$94*$D$31) -> 896.66401 | C99: =IF($A99+C$94>=1,NA(),$A99*$B$31+(1-$A99-C$94)*$C$31+C$94*$D$31) -> 1086.0205 | D99: =IF($A99+D$94>=1,NA(),$A99*$B$31+(1-$A99-D$94)*$C$31+D$94*$D$31) -> 1275.377 | E99: =IF($A99+E$94>=1,NA(),$A99*$B$31+(1-$A99-E$94)*$C$31+E$94*$D$31) -> 1464.7336 | F99: =IF($A99+F$94>=1,NA(),$A99*$B$31+(1-$A99-F$94)*$C$31+F$94*$D$31) -> 1654.0901
A101: Floor / Range / Lever Analysis
A102: Min option value (most conservative) | B102: =B99 -> 896.66401 | C102: P_Bear=30%, P_Bull=10% (extreme bearish weights)
A103: Max option value (most aggressive) | B103: =F95 -> 1809.2763 | C103: P_Bear=10%, P_Bull=50% (extreme bullish weights)
A104: Range (max - min) | B104: =B103-B102 -> 912.61225 | C104: ="Total swing across reasonable bounds = $"&TEXT(B104/1000,"0.00")&"B" -> Total swing across reasonable bounds = $0.91B
A105: Sensitivity to P_Bull (10→50pp shift, holding P_Bear=20%) | B105: =(F97-B97)/4 -> 189.35652 | C105: $ per 10pp P_Bull shift — dominant lever
A106: Sensitivity to P_Bear (10→30pp shift, holding P_Bull=30%) | B106: =(D95-D99)/4 -> 38.796547 | C106: $ per 10pp P_Bear shift — secondary lever
A108: Read
A109: ="At 20/50/30 base weights, scenario-weighted option value is $"&TEXT(D97/1000,"0.00")&"B (yellow center) — "&TEXT(D97/C31-1,"+0%;-0%")&" vs Base DCF active scenario ($"&TEXT(C31/1000,"0.00")&"B). Across the full grid, option value spans $"&TEXT(B102/1000,"0.00")&"B (max-bear: 30% Bear / 10% Bull) to $"&TEXT(B103/1000,"0.00")&"B (max-bull: 10% Bear / 50% Bull) — a $"&TEXT(B104/1000,"0.00")&"B range. P_Bull is the dominant lever ($"&TEXT(B105,"#,##0")&"M per 10pp shift — 4x larger than P_Bear at $"&TEXT(B106,"#,##0")&"M). Under any plausible weighting where P_Bull ≥ 20% AND P_Bear ≤ 25%, option value sits comfortably ABOVE Base DCF $"&TEXT(C31,"#,##0")&"M. Only the extreme bearish corner (30%/10%, $"&TEXT(B102,"#,##0")&"M) drops below — and that scenario implies probabilities materially out of line with management's stated ambition." -> At 20/50/30 base weights, scenario-weighted option value is $1.35B (yellow center) — +44% vs Base DCF active scenario ($0.94B). Across the full grid, option value spans $0.90B (max-bear: 30% Bear / 10% Bull) to $1.81B (max-bull: 10% Bear / 50% Bull) — a $0.91B range. P_Bull is the dominant lever ($189M per 10pp shift — 4x larger than P_Bear at $39M). Under any plausible weighting where P_Bull ≥ 20% AND P_Bear ≤ 25%, option value sits comfortably ABOVE Base DCF $940M. Only the extreme bearish corner (30%/10%, $897M) drops below — and that scenario implies probabilities materially out of line with management's stated ambition.

Sheet Comps
A1: WHOOP — Public Comp Triangulation (Three-Thesis Framework)
A2: Comps grouped by what WHOOP would *become* under each thesis (Failed Pivot / Subscription Executed / Healthcare Platform). Within each thesis comps share economic structure; across theses they don't — so we don't average across them. Composite span feeds Football Field. Oura shown as parallel reference, never blended. Garmin reclassified as form factor reference, doesn't anchor any thesis.
A4: 1. WHOOP Inputs
A6: Recognized revenue (2025, $M) | B6: ='Revenue Build'!D20 -> 520.6
A7: Bookings run-rate ($M) | B7: 1100
A8: Gross margin (model 2026E) | B8: ='P&L'!E16 -> 0.75
A9: Implied gross profit — recognized basis | B9: =B6*B8 -> 390.45
A10: Implied gross profit — bookings basis | B10: =B7*B8 -> 825
A11: LTM bookings growth | B11: 1.03
A12: NTM growth (model) | B12: 0.7
A13: Series G mark ($M) | B13: 10100
A15: 2. Master Comp Table
A16: Multiples per spec (May 5, 2026 refresh). Tier T1=direct comp parallel ref, T2=structural analogue thesis anchor, T3=boundary marker thesis anchor, T4=historical footnote. Thesis tag drives which bracket each comp anchors.
A18: Comp | B18: Ticker | C18: Tier | D18: Thesis | E18: EV/Rev NTM | F18: EV/GP NTM | G18: NTM Growth | H18: Gross Margin | I18: EV/Rev / Growth | J18: Notes
A19: Peloton | B19: PTON | C19: T3 | D19: 1 — Failed Pivot | E19: 1.22 | F19: 2.9 | G19: -0.05 | H19: 0.42 | I19: =IFERROR(E19/(G19*100),"n/m") -> -0.244 | J19: Hardware-sub failed pivot. Bear floor.
A20: Sonos | B20: SONO | C20: T3 | D20: 1 — Failed Pivot | E20: 1.07 | F20: 2.4 | G20: -0.02 | H20: 0.45 | I20: =IFERROR(E20/(G20*100),"n/m") -> -0.535 | J20: Consumer durable in revenue decline.
A21: GoPro | B21: GPRO | C21: T3 | D21: 1 — Failed Pivot | E21: 0.4 | F21: 1.2 | G21: -0.08 | H21: 0.33 | I21: =IFERROR(E21/(G21*100),"n/m") -> -0.05 | J21: Failed subscription pivot, terminal decline.
A22: Spotify | B22: SPOT | C22: T2 | D22: 2 — Subscription Executed | E22: 3.66 | F22: 11.4 | G22: 0.13 | H22: 0.32 | I22: =IFERROR(E22/(G22*100),"n/m") -> 0.28153846 | J22: Mature pure subscription. Profitability proof drove +116% multiple expansion 3yr.
A23: Roku | B23: ROKU | C23: T2 | D23: 2 — Subscription Executed | E23: 3.02 | F23: 6.9 | G23: 0.12 | H23: 0.44 | I23: =IFERROR(E23/(G23*100),"n/m") -> 0.25166667 | J23: Platform with hardware as CAC, profitability inflection.
A24: Dexcom | B24: DXCM | C24: T2 | D24: 3 — Healthcare Platform | E24: 4.24 | F24: 7.1 | G24: 0.11 | H24: 0.6 | I24: =IFERROR(E24/(G24*100),"n/m") -> 0.38545455 | J24: FDA-cleared CGM, reimbursed. Compressed -67% from 13.8x in 2023.
A25: iRhythm | B25: IRTC | C25: T2 | D25: 3 — Healthcare Platform | E25: 4.65 | F25: 6.5 | G25: 0.18 | H25: 0.7 | I25: =IFERROR(E25/(G25*100),"n/m") -> 0.25833333 | J25: Cardiac monitoring, CMS-reimbursed. Closest pathway analog. Compressed -51% from peak.
A26: ResMed | B26: RMD | C26: T3 | D26: 3 — Healthcare Platform | E26: 5.23 | F26: 8.9 | G26: 0.08 | H26: 0.59 | I26: =IFERROR(E26/(G26*100),"n/m") -> 0.65375 | J26: Sleep apnea, reimbursed, mature.
A27: Masimo | B27: MASI | C27: T3 | D27: 3 — Healthcare Platform | E27: 5.96 | F27: 9.5 | G27: 0.1 | H27: 0.63 | I27: =IFERROR(E27/(G27*100),"n/m") -> 0.596 | J27: Hospital monitoring, sensor-first.
A28: Garmin | B28: GRMN | C28: T2 | D28: Form factor ref — not anchored | E28: 5.25 | F28: 9.8 | G28: 0.06 | H28: 0.59 | I28: =IFERROR(E28/(G28*100),"n/m") -> 0.875 | J28: Diversified hardware conglomerate. WHOOP isn't fundamentally hardware. Reference only.
A29: Oura | B29: (private) | C29: T1 | D29: Parallel ref — never blended | E29: 13 | F29: 26 | G29: 1.29 | H29: 0.5 | I29: =IFERROR(E29/(G29*100),"n/m") -> 0.10077519 | J29: Only direct comp; private. Same Gornall/Strebulaev critique applies as Series G.
A30: Fitbit (IPO 2015) | B30: FIT | C30: T4 | D30: Historical footnote | E30: 2.2 | J30: Peak public-market mark before category compression.
A31: Fitbit (Google acquire 2021) | B31: FIT | C31: T4 | D31: Historical footnote | E31: 1.5 | J31: Strategic exit; revenue-declining at sale.
A33: 3. Thesis Summary — Bracketed Implied WHOOP Valuations
A34: Three theses about what WHOOP becomes. Within each, comps share economic structure; across theses they don't. Each bracket shows EV/Rev and EV/GP ranges and computes 4 implied-EV variants × WHOOP financials.
A36: Thesis 1 — Failed Pivot (Bear)
A37: Anchors: Peloton, Sonos, GoPro. Question: what if WHOOP fails to defend subscription economics and reverts to hardware-dependent revenue?
B38: Low | C38: High | D38: Median
A39: EV/Rev NTM | B39: =MIN(E19:E21) -> 0.4 | C39: =MAX(E19:E21) -> 1.22 | D39: =MEDIAN(E19:E21) -> 1.07
A40: EV/GP NTM | B40: =MIN(F19:F21) -> 1.2 | C40: =MAX(F19:F21) -> 2.9 | D40: =MEDIAN(F19:F21) -> 2.4
A41: Implied EV ($M):
A42: Recognized × EV/Rev | B42: =B39*$B$6 -> 208.24 | C42: =C39*$B$6 -> 635.132 | D42: =D39*$B$6 -> 557.042
A43: Bookings × EV/Rev | B43: =B39*$B$7 -> 440 | C43: =C39*$B$7 -> 1342 | D43: =D39*$B$7 -> 1177
A44: Recognized GP × EV/GP | B44: =B40*$B$9 -> 468.54 | C44: =C40*$B$9 -> 1132.305 | D44: =D40*$B$9 -> 937.08
A45: Bookings GP × EV/GP | B45: =B40*$B$10 -> 990 | C45: =C40*$B$10 -> 2392.5 | D45: =D40*$B$10 -> 1980
A47: Thesis 2 — Subscription Executed (Base)
A48: Anchors: Spotify, Roku. Question: what if WHOOP becomes a premium consumer subscription business at scale? EV/GP is the more analytically relevant multiple here — normalizes WHOOP's GM advantage (75% vs Spotify 32% / Roku 44%).
B49: Low | C49: High | D49: Median
A50: EV/Rev NTM | B50: =MIN(E22:E23) -> 3.02 | C50: =MAX(E22:E23) -> 3.66 | D50: =MEDIAN(E22:E23) -> 3.34
A51: EV/GP NTM | B51: =MIN(F22:F23) -> 6.9 | C51: =MAX(F22:F23) -> 11.4 | D51: =MEDIAN(F22:F23) -> 9.15
A52: Implied EV ($M):
A53: Recognized × EV/Rev | B53: =B50*$B$6 -> 1572.212 | C53: =C50*$B$6 -> 1905.396 | D53: =D50*$B$6 -> 1738.804
A54: Bookings × EV/Rev | B54: =B50*$B$7 -> 3322 | C54: =C50*$B$7 -> 4026 | D54: =D50*$B$7 -> 3674
A55: Recognized GP × EV/GP | B55: =B51*$B$9 -> 2694.105 | C55: =C51*$B$9 -> 4451.13 | D55: =D51*$B$9 -> 3572.6175
A56: Bookings GP × EV/GP | B56: =B51*$B$10 -> 5692.5 | C56: =C51*$B$10 -> 9405 | D56: =D51*$B$10 -> 7548.75
A58: Thesis 3 — Healthcare Platform (Bull / Optionality)
A59: Anchors: Dexcom, iRhythm, ResMed, Masimo. Question: what if WHOOP becomes a reimbursable health-data platform with FDA/CMS pathway success? Note multiples have de-rated -51 to -67% from 2023 peaks — bull case more constrained than 2023 multiples would suggest.
B60: Low | C60: High | D60: Median
A61: EV/Rev NTM | B61: =MIN(E24:E27) -> 4.24 | C61: =MAX(E24:E27) -> 5.96 | D61: =MEDIAN(E24:E27) -> 4.94
A62: EV/GP NTM | B62: =MIN(F24:F27) -> 6.5 | C62: =MAX(F24:F27) -> 9.5 | D62: =MEDIAN(F24:F27) -> 8
A63: Implied EV ($M):
A64: Recognized × EV/Rev | B64: =B61*$B$6 -> 2207.344 | C64: =C61*$B$6 -> 3102.776 | D64: =D61*$B$6 -> 2571.764
A65: Bookings × EV/Rev | B65: =B61*$B$7 -> 4664 | C65: =C61*$B$7 -> 6556 | D65: =D61*$B$7 -> 5434
A66: Recognized GP × EV/GP | B66: =B62*$B$9 -> 2537.925 | C66: =C62*$B$9 -> 3709.275 | D66: =D62*$B$9 -> 3123.6
A67: Bookings GP × EV/GP | B67: =B62*$B$10 -> 5362.5 | C67: =C62*$B$10 -> 7837.5 | D67: =D62*$B$10 -> 6600
A69: 4. Composite Span (across all theses)
A71: Lowest defensible (Bear, recognized basis) | B71: =MIN(B42:B45) -> 208.24
A72: Highest defensible (Sub Executed, bookings GP × EV/GP) | B72: =MAX(C56,C67) -> 9405
A73: Most defensible base (T2 median, recognized GP × EV/GP) | B73: =D55 -> 3572.6175
A74: Series G mark | B74: =B13 -> 10100
A76: 5. Oura — Private Market Category Reference (parallel, never blended)
A77: Oura at 13x recognized is a private-market data point on category pricing. Comparison flips between EV/Rev and EV/GP — real analytical content.
A79: Oura TEV ($M) | B79: 12060
A80: Oura TTM revenue ($M) | B80: 927
A81: Oura EV/Rev | B81: =B79/B80 -> 13.009709
A82: Oura EV/GP (est. 50% GM) | B82: =B79/(B80*0.5) -> 26.019417
A83: WHOOP at Series G — EV/Rev (recognized) | B83: =B13/B6 -> 19.400692
A84: WHOOP at Series G — EV/GP (recognized) | B84: =B13/B9 -> 25.867589
A85: Read | B85: WHOOP higher than Oura on EV/Rev, lower on EV/GP. Margin advantage flips it. Both private marks reflect rich category pricing.
A87: 6. Series G Implied Multiples — Back-Solve Diagnostic
A88: What multiple does Series G $10.1B imply on each thesis basis? Compare to thesis medians to see how far above the comp set Series G sits.
B89: Series G implied | C89: T1 median | D89: T2 median | E89: T3 median | F89: Premium (Series G vs T2 median)
A141: Three-Thesis Comp Bracketing — Why Public Multiples Undershoot Series G
A142: WHOOP's four commercial vectors (consumer hardware, subscription, health data, B2B) don't fit one bucket. Three theses bracket the range; spread is the analytical content.
A144: Thesis | B144: Comp Set | C144: EV/Rev | D144: EV/GP | E144: Implied EV | F144: vs Series G | G144: Commentary
A145: T1: Failed Pivot | B145: PTON, SONO, GPRO | C145: 1.07 | D145: 2.4 | E145: =B6*C145 -> 557.042 | F145: =E145/$B$13-1 -> -0.94484733 | G145: Consumer hardware floor; assumes WHOOP fails subscription transition
A146: T2: Subscription Executed | B146: SPOT, ROKU | C146: 3.34 | D146: 9.15 | E146: =B6*C146 -> 1738.804 | F146: =E146/$B$13-1 -> -0.82784119 | G146: Most defensible: WHOOP is a durable consumer subscription
A147: T3: Healthcare Platform | B147: DXCM, IRTC, RMD, MASI | C147: 4.94 | D147: 8 | E147: =B6*C147 -> 2571.764 | F147: =E147/$B$13-1 -> -0.7453699 | G147: Reimbursed-revenue ceiling; assumes healthcare positioning materializes
A148: Series G mark (Mar 2026) | B148: Abbott / Mayo / growth | C148: n/a | D148: n/a | E148: =B13 -> 10100 | F148: — | G148: Sophisticated capital prices ~2.8x the T2 (subscription) median
A151: Implied WHOOP EV — Composite Span (EV/Rev and EV/GP both applied)
A152: Recognized Revenue $520.6M | Gross Profit $390.5M @ 75% GM (both live-linked)
A154: Thesis | B154: EV/Rev Implied | C154: EV/GP Implied | D154: Midpoint | E154: Range Span | F154: Midpoint vs SerG
A155: T1: Failed Pivot | B155: =B6*C145 -> 557.042 | C155: =B10*D145 -> 1980 | D155: =(B155+C155)/2 -> 1268.521 | E155: =C155-B155 -> 1422.958 | F155: =D155/$B$13-1 -> -0.87440386
A156: T2: Subscription Executed | B156: =B6*C146 -> 1738.804 | C156: =B10*D146 -> 7548.75 | D156: =(B156+C156)/2 -> 4643.777 | E156: =C156-B156 -> 5809.946 | F156: =D156/$B$13-1 -> -0.5402201
A157: T3: Healthcare Platform | B157: =B6*C147 -> 2571.764 | C157: =B10*D147 -> 6600 | D157: =(B157+C157)/2 -> 4585.882 | E157: =C157-B157 -> 4028.236 | F157: =D157/$B$13-1 -> -0.54595228
A160: Read
A161: • Even T3 healthcare-platform midpoint prices WHOOP well below Series G — no public bucket reaches $10.1B
A162: • T2 (subscription executed) midpoint is the most defensible public-comp anchor; gap to Series G quantifies the structural premium
A163: • The undershoot IS the thesis — comp methodology can't price platform companies before the platform thesis is publicly visible (a16z American Dynamism)
A164: • Series G investors implicitly price WHOOP at a multiple of T2 — sophisticated capital captures the gap public comps cannot see
A167: Thesis | B167: Midpoint EV ($M)
A168: T1: Failed Pivot | B168: =D155 -> 1268.521
A169: T2: Subscription Executed | B169: =D156 -> 4643.777
A170: T3: Healthcare Platform | B170: =D157 -> 4585.882
A171: Series G (March 2026) | B171: =B13 -> 10100

Sheet Precedents
A1: WHOOP — Precedent Transactions
A2: 2020-2026; $500M+ EV preferred; All USD
A4: Acquirer / Target | B4: Date | C4: EV ($B) | D4: LTM Rev ($B) | E4: EV/Rev | F4: Regime | G4: Bucket | H4: Strategic Rationale
A5: Google / Fitbit | B5: Jan 2021 | C5: 2.1 | D5: 1.43 | E5: 1.5 | F5: ZIRP-peak | G5: B1 | H5: Wearable data acquisition; failed sub pivot
A6: Lululemon / Mirror | B6: Jul 2020 | C6: 0.5 | D6: 0.17 | E6: 2.9 | F6: ZIRP-peak | G6: B2 | H6: Connected fitness content; 89% write-off
A7: Teladoc / Livongo | B7: Oct 2020 | C7: 18.5 | D7: 0.29 | E7: 63.8 | F7: ZIRP-peak | G7: Cross | H7: Digital health mega-deal; massive write-down
A8: Microsoft / Nuance | B8: Mar 2022 | C8: 19.7 | D8: 1.48 | E8: 13.3 | F8: Transition | G8: Cross | H8: Healthcare AI voice/NLP platform
A9: Masimo / Sound United | B9: Apr 2022 | C9: 1.03 | D9: 0.9 | E9: 1.1 | F9: Transition | G9: B1 | H9: Consumer audio pivot; $675M value destruction
A10: CVS / Signify Health | B10: Sep 2022 | C10: 8 | D10: 0.77 | E10: 10.4 | F10: Transition | G10: B3 | H10: Home health + value-based care platform
A11: Amazon / One Medical | B11: Feb 2023 | C11: 3.9 | D11: 1.1 | E11: 3.5 | F11: Transition | G11: Cross | H11: Primary care distribution; strategic access play
A12: J&J / Shockwave Medical | B12: May 2024 | C12: 13.1 | D12: 0.73 | E12: 17.9 | F12: Current | G12: B3 | H12: OUTLIER: IVL synergies drove 2x+ peer median
A13: BSci / Axonics | B13: Nov 2024 | C13: 3.7 | D13: 0.37 | E13: 10.1 | F13: Current | G13: B3 | H13: Neuromodulation bolt-on
A14: Stryker / Inari Medical | B14: Feb 2025 | C14: 4.9 | D14: 0.6 | E14: 8.1 | F14: Current | G14: B3 | H14: Venous thromboembolism devices
A15: Danaher / Masimo | B15: Feb 2026 | C15: 9.9 | D15: 1.51 | E15: 6.6 | F15: Current | G15: B3 | H15: Patient monitoring platform; pending close
A18: Summary by Regime & Bucket
A19: Current-regime B3 medtech: 6.6-10.1x (median ~8.5x)
A20: Connected fitness deals: uniformly value-destructive
A21: Implied WHOOP range: $5-8B (control premium embedded; Series G is minority)

Sheet Cap Table
A1: WHOOP — Cap Table & Waterfall
A2: Sources: Pitchbook + Cap IQ; BUILD WATERFALL FORMULAS
A4: Round | B4: Date | C4: Amount ($M) | D4: Post-Money ($B) | E4: Price/Share ($) | F4: Shares (M) | G4: Ownership % | H4: Pref Terms | I4: Lead Investor(s)
A5: Seed | B5: 2012 | C5: 1 | H5: 1x non-part. | I5: DraftKings founders
A6: Series A | B6: Sep 2014 | C6: 4 | H6: 1x non-part. | I6: Accomplice, Mousse Partners
A7: Series B | B7: Sep 2016 | C7: 12 | H7: 1x non-part. | I7: Foundry Group
A8: Series C | B8: Oct 2018 | C8: 55 | D8: 0.43 | H8: 1x non-part. | I8: IVP
A9: Series D | B9: Oct 2020 | C9: 100 | D9: 1.2 | H9: 1x non-part. | I9: IVP
A10: Series E | B10: Aug 2021 | C10: 200 | D10: 2.4 | H10: 1x non-part. | I10: SoftBank Vision Fund 2
A11: Series F | B11: Aug 2021 | C11: 200 | D11: 3.6 | E11: 4.76 | H11: 1x non-part. | I11: SoftBank Vision Fund 2
A12: Mezz/Bridge | B12: 2022-2024 | C12: 46 | H12: Various | I12: 5 interim rounds (VC + debt)
A13: Series G | B13: Mar 2026 | C13: 575 | D13: 10.1 | E13: 11.23 | G13: 0.057 | H13: 1x non-part. | I13: Collaborative Fund
A15: Total Equity Raised: | C15: 1030
A17: Key Metrics
A18: Authorized Preferred Shares | C18: 537.9M | E18: Pitchbook
A19: Outstanding Common Shares | C19: 361.2M | E19: Pitchbook
A20: Fully Diluted Shares (est.) | C20: ~900M | E20: PremierAlts/Forge
A21: Option Pool (est.) | C21: ~10-15% of FD | E21: Inferred from gap; FLAGGED_GAP
A22: All Preferences | C22: 1x non-participating pari passu | E22: Pitchbook
A23: Total Liquidation Preference | C23: ~$1.03B (floor) | E23: Sum of equity raised × 1x
A26: Waterfall at Exit Scenarios (BUILD FORMULAS)
C27: Bear ($5B) | E27: Base ($10B) | G27: Bull ($20B)
A28: Total Exit Proceeds
A29: Less: Liquidation Preferences
A30: Remaining for Pro-Rata
A31: Preferred Conversion Check (convert or take pref?)
A32: Common Share Proceeds
A33: Common Value per Share
A34: Preferred Value per Share
A35: Founder Equity Value (est. 12-18% FD)

Sheet Football Field
A1: WHOOP — Valuation Football Field
A2: Multi-method synthesis. Each method shown with low/base/high EV. Per-share converts via Assumptions F62 (debt), F63 (cash), F55 (FD shares).
A4: Method | B4: Source | C4: Low EV ($B) | D4: Base EV ($B) | E4: High EV ($B) | F4: Low $/sh | G4: Base $/sh | H4: High $/sh | I4: Weight | J4: Wtd Base | K4: Note
A6: 1. Intrinsic DCF (base case, no options) | B6: DCF!C60:C62 (Equity, Bear/Base/Bull) | C6: =DCF!C60/1000 -> 2.49675 | D6: =DCF!C61/1000 -> 7.32055 | E6: =DCF!C62/1000 -> 24.65767 | F6: =(C6*1000 - Assumptions!$F$61 + Assumptions!$F$62)/Assumptions!$F$54 -> 7.772561 | G6: =(D6*1000 - Assumptions!$F$61 + Assumptions!$F$62)/Assumptions!$F$54 -> 19.537927 | H6: =(E6*1000 - Assumptions!$F$61 + Assumptions!$F$62)/Assumptions!$F$54 -> 61.823585 | I6: 0 | J6: =D6*I6 -> 0 | K6: Bear/Base/Bull DCF Equity sourced from DCF triangulation rows 60-62 (the canonical 4-scenario snapshot, refreshed by validation pass). Replaces prior dependency on Sensitivity!B44:D44 (WACC × Exit Multiple grid endpoints) which was a static slice and got out of sync with the DCF as inputs evolved. Single source of truth: DCF tab Section 7.
A7: 1b. DCF + Real Options (excluded — see RealOptions tab note) | B7: DCF!D60:D62 (Equity + Real Options) | C7: n/a | D7: n/a | E7: n/a | F7: n/a | G7: n/a | H7: n/a | K7: Equity + Real Options sourced directly from DCF!D60:D62. Real options layer (RealOptions!B32:D32) is already baked into the DCF triangulation Equity+Opts column so no double-add needed. Was previously =C6 + RealOptions!B32; now decoupled from row 6 chain so any drift is caught.
A8: 1c. ProbWeighted DCF (input-level, no options) | B8: DCF!C63 (input-weighted single run) | C8: =Scenarios!F16/1000 -> 6.82065 | D8: =Scenarios!F17/1000 -> 8.18567 | E8: =Scenarios!F18/1000 -> 8.66394 | F8: =(C8*1000 - Assumptions!$F$61 + Assumptions!$F$62)/Assumptions!$F$54 -> 18.318659 | G8: =(D8*1000 - Assumptions!$F$61 + Assumptions!$F$62)/Assumptions!$F$54 -> 21.647976 | H8: =(E8*1000 - Assumptions!$F$61 + Assumptions!$F$62)/Assumptions!$F$54 -> 22.814488 | K8: ProbWeighted DCF range = three weight schemes (Pessimistic 35/50/15, Neutral 20/50/30, Optimistic 15/45/40). Each is an input-level ProbWeighted run with that weight scheme. Low = Pessimistic (highest Bear weight), High = Optimistic (highest Bull weight). Captures the range of conservative-anchor estimates under reasonable conviction shifts.
A9: 1d. Scenario-Weighted DCF (P·DCF, no options) | B9: Scenarios!E16:E18 (P·DCF across weight schemes) | C9: =Scenarios!E16/1000 -> 8.232788 | D9: =Scenarios!E17/1000 -> 11.556926 | E9: =Scenarios!E18/1000 -> 13.531828 | F9: =(C9*1000 - Assumptions!$F$61 + Assumptions!$F$62)/Assumptions!$F$54 -> 21.762898 | G9: =(D9*1000 - Assumptions!$F$61 + Assumptions!$F$62)/Assumptions!$F$54 -> 29.870551 | H9: =(E9*1000 - Assumptions!$F$61 + Assumptions!$F$62)/Assumptions!$F$54 -> 34.687385 | I9: 0.4 | J9: =I9*D9 -> 4.6227704 | K9: Scenario-Weighted (P·DCF) range = scenario-level weighted equity across three weight schemes (Pessimistic/Neutral/Optimistic). Computed from the live Bear/Base/Bull equity in DCF!C60:C62 weighted by row-2 schemes. Upper anchor for triangulation under perfect cross-input correlation.
A10: 2. Public Comps (three-thesis bracketing) | B10: Comps tab (three-thesis brackets) | C10: =Comps!D43/1000 -> 1.177 | D10: =Comps!D55/1000 -> 3.5726175 | E10: =Comps!D56/1000 -> 7.54875 | F10: =(C10*1000 - Assumptions!$F$61 + Assumptions!$F$62)/Assumptions!$F$54 -> 4.5536585 | G10: =(D10*1000 - Assumptions!$F$61 + Assumptions!$F$62)/Assumptions!$F$54 -> 10.396628 | H10: =(E10*1000 - Assumptions!$F$61 + Assumptions!$F$62)/Assumptions!$F$54 -> 20.094512 | I10: 0.35 | J10: =D10*I10 -> 1.2504161 | K10: Three-thesis bracketing. Composite span $0.7B-$9.4B; T2 base anchor $4.0B (recognized GP × EV/GP). Implies Series G priced for bull case across drivers.
A12: 3. Precedent Transactions | B12: Not yet populated | C12: n/a | D12: n/a | E12: n/a | K12: Skipped per session decision. 5-10% memo weight max per methodology.
A13: 4. Last-Round Implied (Series G) | B13: DCF C58 | C13: =DCF!C52/1000 -> 10.1 | D13: =DCF!C52/1000 -> 10.1 | E13: =DCF!C52/1000 -> 10.1 | F13: =(C13*1000 - Assumptions!$F$61 + Assumptions!$F$62)/Assumptions!$F$54 -> 26.317073 | G13: =(D13*1000 - Assumptions!$F$61 + Assumptions!$F$62)/Assumptions!$F$54 -> 26.317073 | H13: =(E13*1000 - Assumptions!$F$61 + Assumptions!$F$62)/Assumptions!$F$54 -> 26.317073 | I13: 0.1 | J13: =D13*I13 -> 1.01 | K13: Series G $10.1B post-money mark, March 2026. Single point, not derived value.
A14: 5. Implied IPO Trading Range | B14: Assumptions C94/D94/E94 (Reference Class) | C14: =Assumptions!C94/1000 -> 13.242222 | D14: =Assumptions!D94/1000 -> 14.690909 | E14: =Assumptions!E94/1000 -> 19.713253 | F14: =(C14*1000 - Assumptions!$F$61 + Assumptions!$F$62)/Assumptions!$F$54 -> 33.98103 | G14: =(D14*1000 - Assumptions!$F$61 + Assumptions!$F$62)/Assumptions!$F$54 -> 37.514412 | H14: =(E14*1000 - Assumptions!$F$61 + Assumptions!$F$62)/Assumptions!$F$54 -> 49.764032 | I14: 0.15 | J14: =D14*I14 -> 2.2036364 | K14: Reference-class step-up methodology: Bear/Base/Bull = 25th/50th/75th percentile of last-private→IPO valuation step-up across 5 comparable consumer/health platform IPOs (Peloton, Oscar, GoPro, Hims, Allbirds). Replaces prior IRR-backsolve method which was mechanically tethered to Series G. Empirical anchor; full reference class data in rows 42-70 below.
A16: Weight Check | I16: =I6+I9+I10+I13+I14 -> 1
A18: Weighted Average EV | D18: =J9+J10+J13+J14 -> 9.0868229 | G18: =(D18*1000 - Assumptions!$F$61 + Assumptions!$F$62)/Assumptions!$F$54 -> 23.845909 | K18: = Σ(weight × base EV) per method
A19: Series G Mark | D19: =DCF!C52/1000 -> 10.1 | G19: =(D19*1000 - Assumptions!$F$61 + Assumptions!$F$62)/Assumptions!$F$54 -> 26.317073
A20: Premium / (Discount) to Series G | D20: =D18/D19 - 1 -> -0.10031457 | G20: =G18/G19 - 1 -> -0.09389964 | K20: Positive = methods support a higher mark; negative = Series G is rich.
A22: Method Range Summary
A23: Lowest method base | B23: =INDEX($A$6:$A$14, MATCH(MIN(D6,D10,D13,D14), D6:D14, 0)) -> 2. Public Comps (three-thesis bracketing) | D23: =MIN(D6,D10,D13,D14) -> 3.5726175 | G23: =(D23*1000 - Assumptions!$F$61 + Assumptions!$F$62)/Assumptions!$F$54 -> 10.396628
A24: Highest method base | B24: =INDEX($A$6:$A$14, MATCH(MAX(D6,D10,D13,D14), D6:D14, 0)) -> 5. Implied IPO Trading Range | D24: =MAX(D6,D10,D13,D14) -> 14.690909 | G24: =(D24*1000 - Assumptions!$F$61 + Assumptions!$F$62)/Assumptions!$F$54 -> 37.514412
A25: Range across methods | D25: =D24-D23 -> 11.118292 | G25: =G24-G23 -> 27.117784
A27: Memo Read
A28: ="Multi-method synthesis: weighted average EV "&TEXT(D18,"$0.00\B")&" / "&TEXT(G18,"$0.00")&" per share, "&TEXT(D20,"+0.0%;-0.0%")&" vs Series G "&TEXT(D19,"$0.00\B")&" / "&TEXT(G19,"$0.00")&". DCF Base anchor "&TEXT(D6,"$0.00\B")&" EV / "&TEXT(D6,"$0.00\B")&" equity (Series G premium "&TEXT(D6/D19-1,"+0.0%;-0.0%")&"). Three-thesis comps Low/Base/High: "&TEXT(C10,"$0.0\B")&" / "&TEXT(D10,"$0.0\B")&" / "&TEXT(E10,"$0.0\B")&". IPO implied range "&TEXT(C14,"$0.0\B")&"-"&TEXT(E14,"$0.0\B")&"." -> Multi-method synthesis: weighted average EV $9.09B / $23.85 per share, -10.0% vs Series G $10.10B / $26.32. DCF Base anchor $7.32B EV / $7.32B equity (Series G premium -27.5%). Three-thesis comps Low/Base/High: $1.2B / $3.6B / $7.5B. IPO implied range $13.2B-$19.7B.
A31: Chart Data (helper table for visual)
A32: Method | B32: Low (offset) | C32: Range (visible bar) | D32: Base marker | E32: Series G ref
A33: 1. Intrinsic DCF | B33: =C6 -> 2.49675 | C33: =E6-C6 -> 22.16092 | D33: =D6 -> 7.32055 | E33: =$D$19 -> 10.1
A34: 1b. DCF + Real Options | B34: n/a | C34: n/a | D34: n/a | E34: =$D$19 -> 10.1
A35: 2. Public Comps (Three-Thesis) | B35: =C10 -> 1.177 | C35: =E10-C10 -> 6.37175 | D35: =D10 -> 3.5726175 | E35: =$D$19 -> 10.1
A36: 4. Last-Round Implied (Series G) | B36: =C13 -> 10.1 | C36: 0.001 | D36: =D13 -> 10.1 | E36: =$D$19 -> 10.1
A37: 5. Implied IPO Range | B37: =C14 -> 13.242222 | C37: =E14-C14 -> 6.4710308 | D37: =D14 -> 14.690909 | E37: =$D$19 -> 10.1
A38: 5. IPO Range | B38: =C14 -> 13.242222 | C38: =E14-C14 -> 6.4710308 | D38: =D14 -> 14.690909 | E38: 10.1
A39: Weighted Avg | B39: =D18 -> 9.0868229 | C39: 0.001 | D39: =D18 -> 9.0868229 | E39: 10.1
A41: 1b. DCF + Real Options (excluded) | B41: n/a | C41: n/a | D41: n/a | E41: n/a
A42: Reference Class — Private-to-IPO Step-Up Analysis
A43: Empirical step-ups for 6 consumer/health platform IPOs; replaces 25% IRR assumption with observed distribution. USD billions unless noted.
A45: Company | B45: Last Private Round | C45: Round Date | D45: Post-Money | E45: IPO Date | F45: IPO Val. | G45: Months | H45: Step-Up | I45: Ann. IRR | K45: Commentary
A46: Peloton | B46: Series F | C46: 43313 | D46: 4.15 | E46: 43709 | F46: 8.1 | G46: =DATEDIF(DATE(2018,8,1),DATE(2019,9,27),"m") -> 13 | H46: =F46/D46 -> 1.9518072 | I46: =(F46/D46)^(12/G46)-1 -> 0.85393977 | K46: Connected fitness subscription — closest WHOOP analog
A47: Fitbit | B47: Series F | C47: 41487 | D47: 0.3 | E47: 42156 | F47: 4.1 | G47: =DATEDIF(DATE(2013,8,1),DATE(2015,6,18),"m") -> 22 | H47: =F47/D47 -> 13.666667 | I47: =(F47/D47)^(12/G47)-1 -> 3.1634402 | K47: OUTLIER — last private round was tiny relative to IPO; exclude from median
A48: Oscar Health | B48: Series G | C48: 43313 | D48: 3.2 | E48: 44256 | F48: 7.92 | G48: =DATEDIF(DATE(2018,8,1),DATE(2021,3,3),"m") -> 31 | H48: =F48/D48 -> 2.475 | I48: =(F48/D48)^(12/G48)-1 -> 0.42020714 | K48: Digital health / insurtech — same Series G stage as WHOOP
A49: GoPro | B49: Foxconn corp minority | C49: 41244 | D49: 2.25 | E49: 41791 | F49: 2.95 | G49: =DATEDIF(DATE(2012,12,1),DATE(2014,6,26),"m") -> 18 | H49: =F49/D49 -> 1.3111111 | I49: =(F49/D49)^(12/G49)-1 -> 0.19791591 | K49: Consumer wearable hardware — closest bucket-1 analog
A50: Hims & Hers | B50: Series C | C50: 43466 | D50: 1.1 | E50: 44197 | F50: 1.6 | G50: =DATEDIF(DATE(2019,1,1),DATE(2021,1,20),"m") -> 24 | H50: =F50/D50 -> 1.4545455 | I50: =(F50/D50)^(12/G50)-1 -> 0.20604538 | K50: Consumer health subscription — SPAC vehicle (not traditional IPO)
A51: Allbirds | B51: Series F | C51: 44075 | D51: 1.7 | E51: 44501 | F51: 2.2 | G51: =DATEDIF(DATE(2020,9,1),DATE(2021,11,3),"m") -> 14 | H51: =F51/D51 -> 1.2941176 | I51: =(F51/D51)^(12/G51)-1 -> 0.24731891 | K51: DTC consumer brand
A53: Summary Statistics
A54: Median (all 6 comps) | G54: =MEDIAN(G46:G51) -> 20 | H54: =MEDIAN(H46:H51) -> 1.7031763 | I54: =MEDIAN(I46:I51) -> 0.33376303
A55: Mean (all 6 comps) | G55: =AVERAGE(G46:G51) -> 20.333333 | H55: =AVERAGE(H46:H51) -> 3.692208 | I55: =AVERAGE(I46:I51) -> 0.84814455
A56: Median (ex-Fitbit outlier) | G56: =MEDIAN(G46,G48:G51) -> 18 | H56: =MEDIAN(H46,H48:H51) -> 1.4545455 | I56: =MEDIAN(I46,I48:I51) -> 0.24731891
A57: 25th percentile (ex-Fitbit) | H57: =PERCENTILE(CHOOSE({1;2;3;4;5},H46,H48,H49,H50,H51),0.25) -> 1.3111111
A58: 75th percentile (ex-Fitbit) | H58: =PERCENTILE(CHOOSE({1;2;3;4;5},H46,H48,H49,H50,H51),0.75) -> 1.9518072
A60: Implied WHOOP IPO Valuation (Series G $10.10B × Step-Up) | B60: Series G Anchor ($B) | C60: Step-Up Applied | D60: Implied IPO EV ($B) | E60: vs Current Backsolve ($12.6B)
A61: Bear (25th percentile, 1.31x) | B61: =D13 -> 10.1 | C61: =H57 -> 1.3111111 | D61: =B61*C61 -> 13.242222 | E61: =D61/D14-1 -> -0.098611111
A62: Base (median ex-Fitbit, 1.45x) | B62: =D13 -> 10.1 | C62: =H56 -> 1.4545455 | D62: =B62*C62 -> 14.690909 | E62: =D62/D14-1 -> 0
A63: Bull (75th percentile, 1.95x) | B63: =D13 -> 10.1 | C63: =H58 -> 1.9518072 | D63: =B63*C63 -> 19.713253 | E63: =D63/D14-1 -> 0.34186747
A65: Methodology Notes
A66: 1. Replaces the assumed 25% IRR target in the original 'Implied IPO Range' backsolve with the empirical distribution of last-private → IPO step-ups for reference-class consumer/health platform companies.
A67: 2. Fitbit excluded from median because its 'last private round' (Aug 2013) was small (~$300M) and far pre-platform; not representative of a Series G stage anchor.
A68: 3. SPACs (Hims) and traditional IPOs (Peloton, Oscar, GoPro, Allbirds) treated equivalently — both represent first liquid public price.
A69: 4. Median time-to-IPO ex-Fitbit ≈ 18-22 months, consistent with original 12-18mo assumption. Median annualized IRR ≈ 24-25%, validating the IRR assumption but anchoring it empirically.
A70: 5. To replace assumption-based IPO range in Assumptions!C93:E93, link those cells to D61:D63 here. Doing this would shift the football field weighted average upward (currently $8.78B).

Sheet Scenarios
A1: WHOOP — Scenario Summary
A2: Scenario EV by method (live links). Probability Weight Sensitivity tests how the weighted-average EV moves under different conviction schemes. ProbWeighted (input-level) shown alongside scenario-weighted (P·DCF) to expose the Jensen gap.
A4: Method | B4: Bear ($M) | C4: Base ($M) | D4: Bull ($M) | E4: ProbWeighted ($M) | F4: Notes
A5: 1. Intrinsic DCF (Equity Value) | B5: =DCF!C60 -> 2496.75 | C5: =DCF!C61 -> 7320.55 | D5: =DCF!C62 -> 24657.67 | E5: =DCF!C63 -> 8185.67 | F5: Equity values from DCF triangulation block (rows 60-63). Live snapshot.
A6: + Real Options (excluded from valuation) | B6: n/a | C6: n/a | D6: n/a | E6: n/a | F6: Includes healthcare reimbursement option (binary gate). Real options scenario-aligned.
A7: 2. Trading Comps (3-bucket EV) | B7: =Comps!D43 -> 1177 | C7: =Comps!D55 -> 3572.6175 | D7: =Comps!D56 -> 7548.75 | E7: n/a | F7: Three-thesis bracketing (Failed Pivot / Subscription / Healthcare). Cross-thesis blending not meaningful — ProbWeighted not applicable.
A8: 3. Precedent Transactions | B8: n/a | C8: n/a | D8: n/a | E8: n/a | F8: Skipped per session decision. 5-10% memo weight max.
A9: 4. Last-Round Implied (Series G) | B9: =DCF!C52 -> 10100 | C9: =DCF!C52 -> 10100 | D9: =DCF!C52 -> 10100 | E9: =DCF!C52 -> 10100 | F9: Single point (constant across scenarios). Mar 2026 mark.
A10: 5. Implied IPO Trading Range | B10: =Assumptions!C94 -> 13242.222 | C10: =Assumptions!D94 -> 14690.909 | D10: =Assumptions!E94 -> 19713.253 | E10: =D10-B10 -> 6471.0308 | F10: Back-solve from $10.1B ÷ (1−illiquidity) ÷ (1−IPO discount). Bear=highest discounts, lowest implied.
A12: Probability Weight Sensitivity — DCF Equity ($M)
A13: Tests three conviction schemes against both methods. Scenario-weighted = P_Bear·Bear + P_Base·Base + P_Bull·Bull (joint correlation). ProbWeighted = read from DCF!C63 with row-2 weights set to scheme (input independence). Difference = Jensen gap. | B13: Bear Wt | C13: Base Wt | D13: Bull Wt | E13: Weighted EV ($B)
A14: Pessimistic | B14: 0.35 | C14: 0.5 | D14: 0.15
A15: Weight Scheme | B15: P_Bear | C15: P_Base | D15: P_Bull | E15: Scenario-Wtd Equity | F15: ProbWeighted Equity | G15: Jensen Gap | H15: vs Series G
A16: Pessimistic (high Bear weight) | B16: 0.35 | C16: 0.5 | D16: 0.15 | E16: =B16*B5+C16*C5+D16*D5 -> 8232.788 | F16: 6820.65 | G16: =E16-F16 -> 1412.138 | H16: =E16/DCF!$C$52-1 -> -0.18487248
A17: Neutral (current base case) | B17: =Assumptions!C2 -> 0.2 | C17: =Assumptions!E2 -> 0.5 | D17: =Assumptions!G2 -> 0.3 | E17: =B17*B5+C17*C5+D17*D5 -> 11556.926 | F17: =DCF!C63 -> 8185.67 | G17: =E17-F17 -> 3371.256 | H17: =E17/DCF!$C$52-1 -> 0.1442501
A18: Optimistic (high Bull weight) | B18: 0.15 | C18: 0.45 | D18: 0.4 | E18: =B18*B5+C18*C5+D18*D5 -> 13531.828 | F18: 8663.94 | G18: =E18-F18 -> 4867.888 | H18: =E18/DCF!$C$52-1 -> 0.33978495
A20: Read: Even under Pessimistic weights (35/50/15), scenario-weighted Equity exceeds ProbWeighted by ~$2.0B (Jensen gap). Under Optimistic weights, gap widens to ~$5.5B as Bull's joint upside dominates. Series G premium/discount column shows scenario-weighted hits the mark only under Neutral or Optimistic schemes — Pessimistic implies $2B+ haircut to Series G.

Sheet Sensitivity
A1: WHOOP — Sensitivity Analysis
A2: ="Base case anchored: WACC "&TEXT(Assumptions!F74,"0.00%")&", Exit Mult "&TEXT(Assumptions!F77,"0.0\x")&", Terminal Growth "&TEXT(Assumptions!F79,"0.0%")&", CSRP "&TEXT(Assumptions!F72,"0.0%")&" → EV "&TEXT(DCF!C32/1000,"$0.00\B")&" / Equity "&TEXT(DCF!C38/1000,"$0.00\B")&" / "&TEXT(DCF!C40,"$0.00")&" per share. Yellow cell = base case." -> Base case anchored: WACC 11.59%, Exit Mult 3.5x, Terminal Growth 3.0%, CSRP 2.0% → EV $6.60B / Equity $7.32B / $17.86 per share. Yellow cell = base case.
A4: Grid 1: WACC × Exit Multiple → Enterprise Value ($B)
A5: WACC ↓ / Exit Mult (EV/Rev) → | B5: 2 | C5: 2.5 | D5: 3 | E5: 3.5 | F5: 4 | G5: 4.5 | H5: 5
A6: 0.1009 | B6: {=(SUMPRODUCT(DCF!$D$9:$K$9, 1/(1+$A6)^DCF!$D$13:$K$13) + DCF!$K$8*B$5/(1+$A6)^DCF!$K$13)/1000} -> 5.4764551 | C6: {=(SUMPRODUCT(DCF!$D$9:$K$9, 1/(1+$A6)^DCF!$D$13:$K$13) + DCF!$K$8*C$5/(1+$A6)^DCF!$K$13)/1000} -> 6.3726979 | D6: {=(SUMPRODUCT(DCF!$D$9:$K$9, 1/(1+$A6)^DCF!$D$13:$K$13) + DCF!$K$8*D$5/(1+$A6)^DCF!$K$13)/1000} -> 7.2689408 | E6: {=(SUMPRODUCT(DCF!$D$9:$K$9, 1/(1+$A6)^DCF!$D$13:$K$13) + DCF!$K$8*E$5/(1+$A6)^DCF!$K$13)/1000} -> 8.1651836 | F6: {=(SUMPRODUCT(DCF!$D$9:$K$9, 1/(1+$A6)^DCF!$D$13:$K$13) + DCF!$K$8*F$5/(1+$A6)^DCF!$K$13)/1000} -> 9.0614265 | G6: {=(SUMPRODUCT(DCF!$D$9:$K$9, 1/(1+$A6)^DCF!$D$13:$K$13) + DCF!$K$8*G$5/(1+$A6)^DCF!$K$13)/1000} -> 9.9576693 | H6: {=(SUMPRODUCT(DCF!$D$9:$K$9, 1/(1+$A6)^DCF!$D$13:$K$13) + DCF!$K$8*H$5/(1+$A6)^DCF!$K$13)/1000} -> 10.853912
A7: 0.1059 | B7: {=(SUMPRODUCT(DCF!$D$9:$K$9, 1/(1+$A7)^DCF!$D$13:$K$13) + DCF!$K$8*B$5/(1+$A7)^DCF!$K$13)/1000} -> 5.3146254 | C7: {=(SUMPRODUCT(DCF!$D$9:$K$9, 1/(1+$A7)^DCF!$D$13:$K$13) + DCF!$K$8*C$5/(1+$A7)^DCF!$K$13)/1000} -> 6.1809204 | D7: {=(SUMPRODUCT(DCF!$D$9:$K$9, 1/(1+$A7)^DCF!$D$13:$K$13) + DCF!$K$8*D$5/(1+$A7)^DCF!$K$13)/1000} -> 7.0472154 | E7: {=(SUMPRODUCT(DCF!$D$9:$K$9, 1/(1+$A7)^DCF!$D$13:$K$13) + DCF!$K$8*E$5/(1+$A7)^DCF!$K$13)/1000} -> 7.9135104 | F7: {=(SUMPRODUCT(DCF!$D$9:$K$9, 1/(1+$A7)^DCF!$D$13:$K$13) + DCF!$K$8*F$5/(1+$A7)^DCF!$K$13)/1000} -> 8.7798054 | G7: {=(SUMPRODUCT(DCF!$D$9:$K$9, 1/(1+$A7)^DCF!$D$13:$K$13) + DCF!$K$8*G$5/(1+$A7)^DCF!$K$13)/1000} -> 9.6461004 | H7: {=(SUMPRODUCT(DCF!$D$9:$K$9, 1/(1+$A7)^DCF!$D$13:$K$13) + DCF!$K$8*H$5/(1+$A7)^DCF!$K$13)/1000} -> 10.512395
A8: 0.1109 | B8: {=(SUMPRODUCT(DCF!$D$9:$K$9, 1/(1+$A8)^DCF!$D$13:$K$13) + DCF!$K$8*B$5/(1+$A8)^DCF!$K$13)/1000} -> 5.1585811 | C8: {=(SUMPRODUCT(DCF!$D$9:$K$9, 1/(1+$A8)^DCF!$D$13:$K$13) + DCF!$K$8*C$5/(1+$A8)^DCF!$K$13)/1000} -> 5.9960573 | D8: {=(SUMPRODUCT(DCF!$D$9:$K$9, 1/(1+$A8)^DCF!$D$13:$K$13) + DCF!$K$8*D$5/(1+$A8)^DCF!$K$13)/1000} -> 6.8335335 | E8: {=(SUMPRODUCT(DCF!$D$9:$K$9, 1/(1+$A8)^DCF!$D$13:$K$13) + DCF!$K$8*E$5/(1+$A8)^DCF!$K$13)/1000} -> 7.6710098 | F8: {=(SUMPRODUCT(DCF!$D$9:$K$9, 1/(1+$A8)^DCF!$D$13:$K$13) + DCF!$K$8*F$5/(1+$A8)^DCF!$K$13)/1000} -> 8.508486 | G8: {=(SUMPRODUCT(DCF!$D$9:$K$9, 1/(1+$A8)^DCF!$D$13:$K$13) + DCF!$K$8*G$5/(1+$A8)^DCF!$K$13)/1000} -> 9.3459623 | H8: {=(SUMPRODUCT(DCF!$D$9:$K$9, 1/(1+$A8)^DCF!$D$13:$K$13) + DCF!$K$8*H$5/(1+$A8)^DCF!$K$13)/1000} -> 10.183439
A9: 0.1159 | B9: {=(SUMPRODUCT(DCF!$D$9:$K$9, 1/(1+$A9)^DCF!$D$13:$K$13) + DCF!$K$8*B$5/(1+$A9)^DCF!$K$13)/1000} -> 5.0080867 | C9: {=(SUMPRODUCT(DCF!$D$9:$K$9, 1/(1+$A9)^DCF!$D$13:$K$13) + DCF!$K$8*C$5/(1+$A9)^DCF!$K$13)/1000} -> 5.8178259 | D9: {=(SUMPRODUCT(DCF!$D$9:$K$9, 1/(1+$A9)^DCF!$D$13:$K$13) + DCF!$K$8*D$5/(1+$A9)^DCF!$K$13)/1000} -> 6.6275651 | E9: {=(SUMPRODUCT(DCF!$D$9:$K$9, 1/(1+$A9)^DCF!$D$13:$K$13) + DCF!$K$8*E$5/(1+$A9)^DCF!$K$13)/1000} -> 7.4373043 | F9: {=(SUMPRODUCT(DCF!$D$9:$K$9, 1/(1+$A9)^DCF!$D$13:$K$13) + DCF!$K$8*F$5/(1+$A9)^DCF!$K$13)/1000} -> 8.2470435 | G9: {=(SUMPRODUCT(DCF!$D$9:$K$9, 1/(1+$A9)^DCF!$D$13:$K$13) + DCF!$K$8*G$5/(1+$A9)^DCF!$K$13)/1000} -> 9.0567827 | H9: {=(SUMPRODUCT(DCF!$D$9:$K$9, 1/(1+$A9)^DCF!$D$13:$K$13) + DCF!$K$8*H$5/(1+$A9)^DCF!$K$13)/1000} -> 9.8665219
A10: 0.1209 | B10: {=(SUMPRODUCT(DCF!$D$9:$K$9, 1/(1+$A10)^DCF!$D$13:$K$13) + DCF!$K$8*B$5/(1+$A10)^DCF!$K$13)/1000} -> 4.8629176 | C10: {=(SUMPRODUCT(DCF!$D$9:$K$9, 1/(1+$A10)^DCF!$D$13:$K$13) + DCF!$K$8*C$5/(1+$A10)^DCF!$K$13)/1000} -> 5.6459563 | D10: {=(SUMPRODUCT(DCF!$D$9:$K$9, 1/(1+$A10)^DCF!$D$13:$K$13) + DCF!$K$8*D$5/(1+$A10)^DCF!$K$13)/1000} -> 6.428995 | E10: {=(SUMPRODUCT(DCF!$D$9:$K$9, 1/(1+$A10)^DCF!$D$13:$K$13) + DCF!$K$8*E$5/(1+$A10)^DCF!$K$13)/1000} -> 7.2120337 | F10: {=(SUMPRODUCT(DCF!$D$9:$K$9, 1/(1+$A10)^DCF!$D$13:$K$13) + DCF!$K$8*F$5/(1+$A10)^DCF!$K$13)/1000} -> 7.9950724 | G10: {=(SUMPRODUCT(DCF!$D$9:$K$9, 1/(1+$A10)^DCF!$D$13:$K$13) + DCF!$K$8*G$5/(1+$A10)^DCF!$K$13)/1000} -> 8.7781111 | H10: {=(SUMPRODUCT(DCF!$D$9:$K$9, 1/(1+$A10)^DCF!$D$13:$K$13) + DCF!$K$8*H$5/(1+$A10)^DCF!$K$13)/1000} -> 9.5611498
A11: 0.1259 | B11: {=(SUMPRODUCT(DCF!$D$9:$K$9, 1/(1+$A11)^DCF!$D$13:$K$13) + DCF!$K$8*B$5/(1+$A11)^DCF!$K$13)/1000} -> 4.7228593 | C11: {=(SUMPRODUCT(DCF!$D$9:$K$9, 1/(1+$A11)^DCF!$D$13:$K$13) + DCF!$K$8*C$5/(1+$A11)^DCF!$K$13)/1000} -> 5.480191 | D11: {=(SUMPRODUCT(DCF!$D$9:$K$9, 1/(1+$A11)^DCF!$D$13:$K$13) + DCF!$K$8*D$5/(1+$A11)^DCF!$K$13)/1000} -> 6.2375226 | E11: {=(SUMPRODUCT(DCF!$D$9:$K$9, 1/(1+$A11)^DCF!$D$13:$K$13) + DCF!$K$8*E$5/(1+$A11)^DCF!$K$13)/1000} -> 6.9948543 | F11: {=(SUMPRODUCT(DCF!$D$9:$K$9, 1/(1+$A11)^DCF!$D$13:$K$13) + DCF!$K$8*F$5/(1+$A11)^DCF!$K$13)/1000} -> 7.7521859 | G11: {=(SUMPRODUCT(DCF!$D$9:$K$9, 1/(1+$A11)^DCF!$D$13:$K$13) + DCF!$K$8*G$5/(1+$A11)^DCF!$K$13)/1000} -> 8.5095175 | H11: {=(SUMPRODUCT(DCF!$D$9:$K$9, 1/(1+$A11)^DCF!$D$13:$K$13) + DCF!$K$8*H$5/(1+$A11)^DCF!$K$13)/1000} -> 9.2668492
A12: 0.1309 | B12: {=(SUMPRODUCT(DCF!$D$9:$K$9, 1/(1+$A12)^DCF!$D$13:$K$13) + DCF!$K$8*B$5/(1+$A12)^DCF!$K$13)/1000} -> 4.5877068 | C12: {=(SUMPRODUCT(DCF!$D$9:$K$9, 1/(1+$A12)^DCF!$D$13:$K$13) + DCF!$K$8*C$5/(1+$A12)^DCF!$K$13)/1000} -> 5.3202837 | D12: {=(SUMPRODUCT(DCF!$D$9:$K$9, 1/(1+$A12)^DCF!$D$13:$K$13) + DCF!$K$8*D$5/(1+$A12)^DCF!$K$13)/1000} -> 6.0528606 | E12: {=(SUMPRODUCT(DCF!$D$9:$K$9, 1/(1+$A12)^DCF!$D$13:$K$13) + DCF!$K$8*E$5/(1+$A12)^DCF!$K$13)/1000} -> 6.7854375 | F12: {=(SUMPRODUCT(DCF!$D$9:$K$9, 1/(1+$A12)^DCF!$D$13:$K$13) + DCF!$K$8*F$5/(1+$A12)^DCF!$K$13)/1000} -> 7.5180144 | G12: {=(SUMPRODUCT(DCF!$D$9:$K$9, 1/(1+$A12)^DCF!$D$13:$K$13) + DCF!$K$8*G$5/(1+$A12)^DCF!$K$13)/1000} -> 8.2505913 | H12: {=(SUMPRODUCT(DCF!$D$9:$K$9, 1/(1+$A12)^DCF!$D$13:$K$13) + DCF!$K$8*H$5/(1+$A12)^DCF!$K$13)/1000} -> 8.9831682
A15: Grid 2: WACC × Terminal Growth (Gordon Method) → Enterprise Value ($B)
A16: WACC ↓ / Terminal Growth → | B16: 0.015 | C16: 0.02 | D16: 0.025 | E16: 0.03 | F16: 0.035 | G16: 0.04 | H16: 0.045
A17: 0.1009 | B17: {=(SUMPRODUCT(DCF!$D$9:$K$9, 1/(1+$A17)^DCF!$D$13:$K$13) + DCF!$K$9*(1+B$16)/($A17-B$16)/(1+$A17)^DCF!$K$13)/1000} -> 6.2479934 | C17: {=(SUMPRODUCT(DCF!$D$9:$K$9, 1/(1+$A17)^DCF!$D$13:$K$13) + DCF!$K$9*(1+C$16)/($A17-C$16)/(1+$A17)^DCF!$K$13)/1000} -> 6.5400332 | D17: {=(SUMPRODUCT(DCF!$D$9:$K$9, 1/(1+$A17)^DCF!$D$13:$K$13) + DCF!$K$9*(1+D$16)/($A17-D$16)/(1+$A17)^DCF!$K$13)/1000} -> 6.8705499 | E17: {=(SUMPRODUCT(DCF!$D$9:$K$9, 1/(1+$A17)^DCF!$D$13:$K$13) + DCF!$K$9*(1+E$16)/($A17-E$16)/(1+$A17)^DCF!$K$13)/1000} -> 7.2476838 | F17: {=(SUMPRODUCT(DCF!$D$9:$K$9, 1/(1+$A17)^DCF!$D$13:$K$13) + DCF!$K$9*(1+F$16)/($A17-F$16)/(1+$A17)^DCF!$K$13)/1000} -> 7.6820461 | G17: {=(SUMPRODUCT(DCF!$D$9:$K$9, 1/(1+$A17)^DCF!$D$13:$K$13) + DCF!$K$9*(1+G$16)/($A17-G$16)/(1+$A17)^DCF!$K$13)/1000} -> 8.1877321 | H17: {=(SUMPRODUCT(DCF!$D$9:$K$9, 1/(1+$A17)^DCF!$D$13:$K$13) + DCF!$K$9*(1+H$16)/($A17-H$16)/(1+$A17)^DCF!$K$13)/1000} -> 8.7838808
