Workbook
Name Scenario: Assumptions!$B$3

Sheet Cover
B3: WHOOP Inc.
A4: ARPU Simplification: Option B ($305 anchor) — bottom-up justified. See ARPU tab justification block. | B4: Private Company Valuation
B5: Investment Committee Memo — Supporting Model
B8: Company: | C8: WHOOP Inc.
B9: Ticker: | C9: Private (Pre-IPO)
B10: Last Round: | C10: Series G — $575M at $10.1B post-money (Mar 31, 2026)
B11: Model Date: | C11: April 16, 2026
B12: Analyst: | C12: Landon Brice
B13: Fiscal Year: | C13: Calendar Year (Jan-Dec)
B14: Currency: | C14: USD ($M unless noted)
B17: Valuation Methods:
B18: 1. Intrinsic DCF (scenario-based + real options)
B19: 2. Trading Comps (three-bucket framework)
B20: 3. Precedent Transactions
B21: 4. Last-Round Implied ($10.1B)
B22: 5. Implied IPO Trading Range (back-solved)
B25: Color Convention:
B26: Hard-coded input
B27: Formula / calculation
B28: Cross-sheet link
B29: Needs verification / FLAGGED_GAP
B32: Source Files:
B33: Valuation Summary (live, scenario-driven)
B34: Active Scenario | C34: =Assumptions!$B$3 -> Base
B36: Base DCF — Enterprise Value | C36: =DCF!C32 -> 7308.752
B37: + Cash | C37: =DCF!C37 -> 1008.2226
B38: − Debt | C38: =DCF!C36 -> -10
B39: = Equity Value | C39: =DCF!C38 -> 8306.9745
B40: Per Share (FD) | C40: =DCF!C40 -> 20.260914
B42: Real Options (Expected) | C42: =DCF!C46 -> 704.48043
B43: Total Equity + Options | C43: =DCF!C51 -> 9011.455
B45: Series G Mark | C45: =DCF!C52 -> 10100
B46: Base DCF vs Series G | C46: =DCF!C53 -> -0.17752727
B47: DCF + Options vs Series G | C47: =DCF!C54 -> -0.10777673
B48: Football Field (multi-method synthesis)
B49: Weighted Average EV | C49: ='Football Field'!D16*1000 -> 7306.5144
B50: Per Share (FD) | C50: ='Football Field'!G16 -> 19.503694
B51: vs Series G | C51: ='Football Field'!D18 -> -0.22353726
B53: Model Integrity (Checks tab)
B54: Passing | C54: =Checks!B17 -> 10
B55: Warning | C55: =Checks!B18 -> 0
B56: Failing | C56: =Checks!B19 -> 0
B57: Overall | C57: =Checks!B20 -> PASS
B59: Framing Decision — Base Case vs Real Options
B60: Base DCF reflects WHOOP's subscription-driven unit economics if executed (terminal GM ~80%, FCF margin 27%). Real options are valued separately as a single binary-gate decision tree on the healthcare reimbursement pathway: probability of CMS materialization × incremental eligible-member revenue × medtech multiple × discount factor. Probability range 15-25% reflects iRhythm precedent (7+ year consumer→medical pathway) plus WHOOP-specific signals (CMS Innovation Center selection Apr 2026, Abbott + Mayo Series G investors). International, B2B Unite, women's health, and glucose are NOT separately valued — either captured in base case (international, B2B) or excluded for lack of evidence (glucose).
B61: Memo conclusion: Base DCF $8.3B equity value (-18% vs Series G $10.1B post-money) anchors fair value, after WC schedule wiring + cash sourced from year-end 2026 ($1.0B post-Series G close) + 3.5x exit multiple. DCF + healthcare option $9.0B (-11% vs mark) shows the gap narrows but doesn't close even crediting the bucket-3 thesis at base probability. Football field weighted average $8.4B (-17% vs mark). Series G prices in the Bull case across drivers — defensible only if healthcare materializes (15-25% probability) AND base case overdelivers on member growth + ARPU.

Sheet Assumptions
A1: WHOOP — Master Assumptions
A3: Scenario: | B3: Base | C3: Select Bear / Base / Bull — drives Active column F throughout the model. Other tabs reference Active values only.
A5: ID | B5: Assumption | C5: Bear | D5: Base | E5: Bull | F5: Active | G5: Tier | H5: Status | I5: Notes
A7: Section 1: Revenue & Growth
A8: R3a | B8: 2025 Beginning Members (M) | C8: 1.5 | D8: 1.3 | E8: 1.1 | F8: =IF($B$3="Bear",C8,IF($B$3="Bull",E8,D8)) -> 1.3 | G8: Tier 3 | H8: High | I8: Back-solved to reconcile avg×ARPU ≈ $650M base. Bear slower decel; bull faster acquisition.
A9: R3b | B9: 2025 Ending Members (M) | C9: 2.3 | D9: 2.5 | E9: 2.7 | F9: =IF($B$3="Bear",C9,IF($B$3="Bull",E9,D9)) -> 2.5 | G9: Tier 1 | H9: Critical | I9: Series G press release: 2.5M+ paying members
A10: R3 | B10: 2025 Average Members (M) — DERIVED | C10: =(C8+C9)/2 -> 1.9 | D10: =(D8+D9)/2 -> 1.9 | E10: =(E8+E9)/2 -> 1.9 | F10: =IF($B$3="Bear",C10,IF($B$3="Bull",E10,D10)) -> 1.9 | G10: Derived | H10: Critical | I10: Per methodology: ARPU applies to AVERAGE members during period, NOT year-end.
A11: R4 | B11: 2025 Blended ARPU ($/yr) | C11: 270 | D11: 305 | E11: 340 | F11: =IF($B$3="Bear",C11,IF($B$3="Bull",E11,D11)) -> 305 | G11: Tier 3 | H11: Critical | I11: Updated to Option B (bottom-up justified): consumer ~80% × $278 + Unite ~20% × $260 ≈ $274; with mature attach assumptions ≈ $307. Anchor 305 (Base). See ARPU tab justification block.
A12: R1 | B12: 2025 Recognized Revenue ($M) — DERIVED | C12: =C10*C11 -> 513 | D12: =D10*D11 -> 579.5 | E12: =E10*E11 -> 646 | F12: =IF($B$3="Bear",C12,IF($B$3="Bull",E12,D12)) -> 579.5 | G12: Derived | H12: Critical | I12: DERIVED: Avg Members × Blended ARPU. Target ~$650M base. Methodology consistency check: must reconcile within ±5%.
A13: R2 | B13: 2025 Bookings Run-Rate ($M) | C13: 1100 | D13: 1100 | E13: 1100 | F13: =IF($B$3="Bear",C13,IF($B$3="Bull",E13,D13)) -> 1100 | G13: Tier 1 | H13: Locked | I13: Series G press release; CEO statement (Dec 2025 exit rate × 12)
A14: R5 | B14: Subscription Revenue % | C14: 0.8 | D14: 0.85 | E14: 0.88 | F14: =IF($B$3="Bear",C14,IF($B$3="Bull",E14,D14)) -> 0.85 | G14: Tier 2 | H14: High | I14: Sacra/BMCT: ~80-88% range
A15: R6 | B15: 2025 YoY Subscription Growth | C15: 1.03 | D15: 1.03 | E15: 1.03 | F15: =IF($B$3="Bear",C15,IF($B$3="Bull",E15,D15)) -> 1.03 | G15: Tier 1 | H15: Locked | I15: Series G press release: 103%
A16: R7 | B16: Phase 1 Revenue Growth (2026-27) | C16: 0.5 | D16: 0.7 | E16: 0.9 | F16: =IF($B$3="Bear",C16,IF($B$3="Bull",E16,D16)) -> 0.7 | G16: Tier 3 | H16: Critical | I16: Peer trajectories; Series G deployment & WHOOP 5.0 cycle
A17: R8 | B17: Phase 2 Revenue Growth (2028-30) | C17: 0.15 | D17: 0.25 | E17: 0.4 | F17: =IF($B$3="Bear",C17,IF($B$3="Bull",E17,D17)) -> 0.25 | G17: Tier 3 | H17: Critical | I17: Deceleration shape: Dexcom (bull) / Netflix (base) / Peloton (bear)
A18: R9 | B18: Phase 3 Revenue Growth (2031-33) | C18: 0.05 | D18: 0.12 | E18: 0.2 | F18: =IF($B$3="Bear",C18,IF($B$3="Bull",E18,D18)) -> 0.12 | G18: Tier 3 | H18: High | I18: TAM ceiling; healthcare attach resolution
A19: R10a | B19: Year-1 Cohort Annual Churn | C19: 0.3 | D19: 0.22 | E19: 0.15 | F19: =IF($B$3="Bear",C19,IF($B$3="Bull",E19,D19)) -> 0.22 | G19: Tier 3 | H19: Critical | I19: Highest churn ("try and quit"). Will drive Members tab cohort engine.
A20: R10b | B20: Year-2 Cohort Annual Churn | C20: 0.18 | D20: 0.14 | E20: 0.1 | F20: =IF($B$3="Bear",C20,IF($B$3="Bull",E20,D20)) -> 0.14 | G20: Tier 3 | H20: Critical | I20: Stabilizing cohort
A21: R10c | B21: Year-3+ Cohort Annual Churn | C21: 0.12 | D21: 0.08 | E21: 0.05 | F21: =IF($B$3="Bear",C21,IF($B$3="Bull",E21,D21)) -> 0.08 | G21: Tier 3 | H21: Critical | I21: Retained core; very sticky power users
A22: R11
A23: R12 | B23: B2B Unite Revenue % | C23: 0.12 | D23: 0.18 | E23: 0.25 | F23: =IF($B$3="Bear",C23,IF($B$3="Bull",E23,D23)) -> 0.18 | G23: Tier 2 | H23: Medium | I23: Sacra/BMCT: ~20% recurring revenue; growing rapidly
A24: R14 | B24: Advanced Labs Attach Rate | C24: 0.03 | D24: 0.1 | E24: 0.25 | F24: =IF($B$3="Bear",C24,IF($B$3="Bull",E24,D24)) -> 0.1 | G24: Tier 3 | H24: Critical | I24: BUCKET-3 THESIS VARIABLE. Bear/Base/Bull per methodology Sec 3. Single most important ARPU assumption — swings $80/member.
A25: R15 | B25: Labs Avg Test Price ($) | C25: 250 | D25: 300 | E25: 350 | F25: =IF($B$3="Bear",C25,IF($B$3="Bull",E25,D25)) -> 300 | G25: Tier 3 | H25: High | I25: WHOOP Advanced Labs site: $199-$599. Methodology base: $300.
A26: R16 | B26: Annual Price Inflation | C26: 0.02 | D26: 0.03 | E26: 0.04 | F26: =IF($B$3="Bear",C26,IF($B$3="Bull",E26,D26)) -> 0.03 | G26: Tier 3 | H26: Medium | I26: CPI + premium brand pricing power
A27: R18 | B27: 2026 Gross Adds (M) | C27: 1.5 | D27: 1.9 | E27: 2.3 | F27: =IF($B$3="Bear",C27,IF($B$3="Bull",E27,D27)) -> 1.9 | G27: Tier 3 | H27: Critical | I27: Methodology priors: 1.8-2.0M base. Members tab will use this; per-year gross adds modeled there. CAC × this = S&M consistency check.
A28: R19 | B28: Deferred Revenue Adjustment (% of bookings) | C28: -0.1 | D28: -0.08 | E28: -0.05 | F28: =IF($B$3="Bear",C28,IF($B$3="Bull",E28,D28)) -> -0.08 | G28: Tier 3 | H28: Medium | I28: Drag during growth (recognized < booked); ASC 606. Approaches 0 at steady state.
A30: Section 2: Cost Structure & Margins
A31: C1 | B31: Hardware BOM per Device ($) | C31: 100 | D31: 80 | E31: 60 | F31: =IF($B$3="Bear",C31,IF($B$3="Bull",E31,D31)) -> 80 | G31: Tier 3 | H31: Critical | I31: Est. $50-80 at scale; 2016 BOM was $250-300 per Contrary Research
A32: C2 | B32: Loaded Hardware Cost per Acquisition ($) | C32: 150 | D32: 120 | E32: 90 | F32: =IF($B$3="Bear",C32,IF($B$3="Bull",E32,D32)) -> 120 | G32: Tier 3 | H32: Critical | I32: C1 + assembly, ship, warranty, returns. Drives unit economics.
A33: C4 | B33: Subscription Delivery Cost (% of sub rev) | C33: 0.15 | D33: 0.1 | E33: 0.08 | F33: =IF($B$3="Bear",C33,IF($B$3="Bull",E33,D33)) -> 0.1 | G33: Tier 3 | H33: High | I33: Infra + support; AWS/GCP benchmarks; declining at scale
A34: C5 | B34: Subscription Gross Margin (standalone) | C34: 0.72 | D34: 0.78 | E34: 0.83 | F34: =IF($B$3="Bear",C34,IF($B$3="Bull",E34,D34)) -> 0.78 | G34: Tier 3 | H34: Critical | I34: Peer: pure SaaS ~80%, Dexcom ~64% (incl consumables). WHOOP higher quality recurring.
A35: C6 | B35: Hardware Gross Margin (standalone) | C35: -0.1 | D35: -0.02 | E35: 0.05 | F35: =IF($B$3="Bear",C35,IF($B$3="Bull",E35,D35)) -> -0.02 | G35: Tier 3 | H35: Critical | I35: Subsidized at acquisition; Peloton HW GM trajectory: -18% to +14%
A36: C7a | B36: Blended GM Phase 1 (2026-27) | C36: 0.56 | D36: 0.6 | E36: 0.64 | F36: =IF($B$3="Bear",C36,IF($B$3="Bull",E36,D36)) -> 0.6 | G36: Tier 3 | H36: High | I36: Phase 1 blended GM (legacy decomposed framework, pre-collapse to C7d). No longer drives the model post-ARPU simplification — retained for reference only.
A37: C7b | B37: Blended GM Phase 2 (2028-30) | C37: 0.63 | D37: a | E37: 0.72 | F37: =IF($B$3="Bear",C37,IF($B$3="Bull",E37,D37)) -> a | G37: Tier 3 | H37: High | I37: Margin expansion as growth decelerates
A38: C7c | B38: Blended GM Terminal | C38: 0.72 | D38: 0.76 | E38: 0.8 | F38: =IF($B$3="Bear",C38,IF($B$3="Bull",E38,D38)) -> 0.76 | G38: Tier 3 | H38: High | I38: Peer terminal: Dexcom 60%, Spotify 32%; software-heavy mix at scale
A39: C8a | B39: R&D % of Revenue (current) | C39: 0.25 | D39: 0.22 | E39: 0.2 | F39: =IF($B$3="Bear",C39,IF($B$3="Bull",E39,D39)) -> 0.22 | G39: Tier 3 | H39: High | I39: Peers: Dexcom 13%, Garmin 16%, growth SaaS 20-30%
A40: C8b | B40: R&D % of Revenue (terminal) | C40: 0.12 | D40: 0.15 | E40: 0.18 | F40: =IF($B$3="Bear",C40,IF($B$3="Bull",E40,D40)) -> 0.15 | G40: Tier 3 | H40: Medium | I40: Peer steady-state
A41: C9 | B41: S&M % of Revenue (current) | C41: 0.35 | D41: 0.3 | E41: 0.25 | F41: =IF($B$3="Bear",C41,IF($B$3="Bull",E41,D41)) -> 0.3 | G41: Tier 3 | H41: Critical | I41: Peloton peak 28.4% FY22, current 16.9% FY25. Bear = stuck high.
A42: C9a | B42: Paid CAC per Gross Add ($) | C42: 220 | D42: 175 | E42: 130 | F42: =IF($B$3="Bear",C42,IF($B$3="Bull",E42,D42)) -> 175 | G42: Tier 3 | H42: Critical | I42: 30-50% of first-year ARPU. S&M consistency check on Checks tab.
A43: C9b | B43: Athlete/Brand Spend ($M/yr) | C43: 100 | D43: 60 | E43: 30 | F43: =IF($B$3="Bear",C43,IF($B$3="Bull",E43,D43)) -> 60 | G43: Tier 3 | H43: High | I43: Press, endorsement deals; non-paid S&M floor
A44: C9t | B44: S&M % of Revenue (terminal) | C44: 0.2 | D44: 0.17 | E44: 0.15 | F44: =IF($B$3="Bear",C44,IF($B$3="Bull",E44,D44)) -> 0.17 | G44: Tier 3 | H44: High | I44: Peer steady-state: Garmin SG&A 14-19%
A45: C10 | B45: G&A % of Revenue (current) | C45: 0.18 | D45: 0.15 | E45: 0.12 | F45: =IF($B$3="Bear",C45,IF($B$3="Bull",E45,D45)) -> 0.15 | G45: Tier 3 | H45: Medium | I45: IPO step-up 200-300bps in 2027-28 (SOX, IR, legal)
A46: C10t | B46: G&A % of Revenue (terminal) | C46: 0.13 | D46: 0.11 | E46: 0.09 | F46: =IF($B$3="Bear",C46,IF($B$3="Bull",E46,D46)) -> 0.11 | G46: Tier 3 | H46: Medium | I46: Peer steady-state
A47: C11a | B47: SBC % of Revenue (current, 2026 pre-IPO peak) | C47: 0.16 | D47: 0.14 | E47: 0.12 | F47: =IF($B$3="Bear",C47,IF($B$3="Bull",E47,D47)) -> 0.14 | G47: Tier 3 | H47: High | I47: Peloton: 9.2% FY25; pre-IPO typically higher. SBC is REAL COST in FCF.
A48: C11b | B48: SBC % of Revenue (terminal, 2033 post-IPO normalized) | C48: 0.1 | D48: 0.08 | E48: 0.06 | F48: =IF($B$3="Bear",C48,IF($B$3="Bull",E48,D48)) -> 0.08 | G48: Tier 3 | H48: High | I48: Methodology Sec 6: SBC normalizes to 6-10% post-IPO. Linear taper from F47 (current) to F48 (terminal) by 2033.
A49: C13 | B49: CapEx % of Revenue | C49: 0.05 | D49: 0.04 | E49: 0.03 | F49: =IF($B$3="Bear",C49,IF($B$3="Bull",E49,D49)) -> 0.04 | G49: Tier 3 | H49: Medium | I49: Asset-light; contract manufacturing
... A53: C12 | B53: D&A % of Revenue | C53: 0.045 | D53: 0.035 | E53: 0.025 | F53: =IF($B$3="Bear",C53,IF($B$3="Bull",E53,D53)) -> 0.035 | G53: Tier 2 | H53: Medium | I53: Capex amortization; lower in mature stages as growth slows. Restored after styling pass clobbered row.
A54: Section 3: Capital Structure & Cap Table (incl. cash yield)
A55: S1 | B55: Fully Diluted Shares Outstanding (M) | C55: 420 | D55: 410 | E55: 400 | F55: =IF($B$3="Bear",C55,IF($B$3="Bull",E55,D55)) -> 410 | G55: Tier 3 | H55: Critical | I55: 361.2M common + ~50M option pool est. Pitchbook auth pref 537.9M, outs 361.2M.
A56: S2 | B56: Series G Price per Share ($) | C56: 28 | D56: 28 | E56: 28 | F56: =IF($B$3="Bear",C56,IF($B$3="Bull",E56,D56)) -> 28 | G56: Tier 2 | H56: High | I56: Pitchbook Series G data; back-solve from $575M raise / shares issued
A57: S3 | B57: Liquidation Preference Type | C57: Participating | D57: 1x non-participating | E57: 1x non-participating | F57: =IF($B$3="Bear",C57,IF($B$3="Bull",E57,D57)) -> 1x non-participating | G57: Tier 2 | H57: Locked | I57: Pitchbook: 1x non-participating pari passu. Bear assumes participating ratchet.
A58: S4 | B58: Total Liquidation Preference ($M) | C58: 1400 | D58: 1400 | E58: 1400 | F58: =IF($B$3="Bear",C58,IF($B$3="Bull",E58,D58)) -> 1400 | G58: Tier 2 | H58: High | I58: Sum of preferred raises: ~$1.4B aggregate (Series A through G)
A59: S7 | B59: Option Pool Size (% of FD shares) | C59: 0.15 | D59: 0.12 | E59: 0.1 | F59: =IF($B$3="Bear",C59,IF($B$3="Bull",E59,D59)) -> 0.12 | G59: Tier 3 | H59: High | I59: Typical 10-15% pre-IPO; 600-person hiring surge implies aggressive granting
A60: S8 | B60: Founder Ownership Ahmed (% FD) | C60: 0.1 | D60: 0.14 | E60: 0.18 | F60: =IF($B$3="Bear",C60,IF($B$3="Bull",E60,D60)) -> 0.14 | G60: Tier 3 | H60: Medium | I60: 12-18% est. across 7 rounds + pool refreshes; possibly lower with secondaries
A61: S9 | B61: DLOM (Discount for Lack of Marketability) | C61: 0.3 | D61: 0.22 | E61: 0.15 | F61: =IF($B$3="Bear",C61,IF($B$3="Bull",E61,D61)) -> 0.22 | G61: Tier 2 | H61: High | I61: Oura tender 25%; EquityZen avg 13-29%; Hiive 39-51% deeper discount
A62: S10 | B62: Debt on Balance Sheet ($M) | C62: 50 | D62: 10 | E62: 0 | F62: =IF($B$3="Bear",C62,IF($B$3="Bull",E62,D62)) -> 10 | G62: Tier 2 | H62: Low | I62: Likely minimal/zero; Pitchbook shows $10.13M debt round Mar 2024
A63: S11 | B63: Cash post Series G ($M) | C63: 500 | D63: 700 | E63: 850 | F63: =IF($B$3="Bear",C63,IF($B$3="Bull",E63,D63)) -> 700 | G63: Tier 3 | H63: Medium | I63: Back-solve: $575M raise + operating cash flow positive entering 2026
A64: S12 | B64: EV-to-Equity Bridge ($M) — DERIVED | C64: =C63-C62 -> 450 | D64: =D63-D62 -> 690 | E64: =E63-E62 -> 850 | F64: =IF($B$3="Bear",C64,IF($B$3="Bull",E64,D64)) -> 690 | G64: Derived | H64: High | I64: Cash − Debt: add to EV to bridge to equity value
A65: S15 | B65: Series F Ratchet / IPO Provisions | C65: Live | D65: Likely extinguished | E65: Extinguished | F65: =IF($B$3="Bear",C65,IF($B$3="Bull",E65,D65)) -> Likely extinguished | G65: Tier 3 | H65: High | I65: Likely extinguished at Series G close; SoftBank notably absent from Series G syndicate
A66: S16
A67: C18 | B67: Cash money-market yield (interest income on idle balance) | C67: 0.025 | D67: 0.035 | E67: 0.045 | F67: =IF($B$3="Bear",C67,IF($B$3="Bull",E67,D67)) -> 0.035 | G67: Tier 2 | H67: Medium | I67: Yield on idle Series G cash. Apply to PRIOR-YEAR ending cash balance to avoid circularity (no feedback into current year cash).
A68: Section 4: WACC / Discount Rate (Damodaran Apr 2026)
A69: D1 | B69: Risk-Free Rate (10yr UST) | C69: 0.043 | D69: 0.043 | E69: 0.043 | F69: =IF($B$3="Bear",C69,IF($B$3="Bull",E69,D69)) -> 0.043 | G69: Tier 1 | H69: Locked | I69: Fed H.15, Apr 14 2026: 4.26%; rounded 4.3%
A70: D2 | B70: Equity Risk Premium | C70: 0.045 | D70: 0.045 | E70: 0.045 | F70: =IF($B$3="Bear",C70,IF($B$3="Bull",E70,D70)) -> 0.045 | G70: Tier 1 | H70: Point Est. | I70: Damodaran 4.23% (Jan 2026); Kroll 5.0%; midpoint 4.5%
A71: D3 | B71: Unlevered Beta (bucket-weighted) | C71: 0.85 | D71: 0.83 | E71: 0.81 | F71: =IF($B$3="Bear",C71,IF($B$3="Bull",E71,D71)) -> 0.83 | G71: Tier 1 | H71: Sensitivity | I71: Damodaran sector: Healthcare 0.83, Electronics 0.83. Bucket-weighted.
A72: D4 | B72: Size Premium | C72: 0.0081 | D72: 0.0081 | E72: 0.0081 | F72: =IF($B$3="Bear",C72,IF($B$3="Bull",E72,D72)) -> 0.0081 | G72: Tier 2 | H72: Point Est. | I72: Kroll CRSP Decile 3 ($7.3-13.5B): 0.81%
A73: D5 | B73: Company-Specific Risk Premium (CSRP) | C73: 0.03 | D73: 0.02 | E73: 0.01 | F73: =IF($B$3="Bear",C73,IF($B$3="Bull",E73,D73)) -> 0.02 | G73: Tier 3 | H73: Sensitivity | I73: Pre-IPO execution risk + private illiquidity; 1-3% range
A74: D8 | B74: Implied Cost of Equity / WACC — DERIVED | C74: =C69+C70*C71+C72+C73 -> 0.11935 | D74: =D69+D70*D71+D72+D73 -> 0.10845 | E74: =E69+E70*E71+E72+E73 -> 0.09755 | F74: =IF($B$3="Bear",C74,IF($B$3="Bull",E74,D74)) -> 0.10845 | G74: Derived | H74: Critical
A76: Section 5: Terminal Value
A77: D9 | B77: Terminal Method (primary) | C77: Exit Multiple | D77: Exit Multiple | E77: Exit Multiple | F77: =IF($B$3="Bear",C77,IF($B$3="Bull",E77,D77)) -> Exit Multiple | G77: Design | H77: Locked | I77: Primary: EV/Revenue exit multiple; cross-check: Gordon Growth
A78: D11 | B78: Terminal EV/Revenue Multiple | C78: 3 | D78: 3.5 | E78: 4.5 | F78: =IF($B$3="Bear",D78,IF($B$3="Bull",E78,D78)) -> 3.5 | G78: Tier 3 | H78: Critical | I78: Compressed 40-60% from current comps; reflects terminal growth 10-15%
A79: D12 | B79: Terminal EV/EBITDA Multiple | C79: 12 | D79: 15 | E79: 18 | F79: =IF($B$3="Bear",C79,IF($B$3="Bull",E79,D79)) -> 15 | G79: Tier 3 | H79: High | I79: Cross-check only; more stable than revenue multiple at maturity
A80: D13 | B80: Perpetuity Growth Rate (Gordon) | C80: 0.025 | D80: 0.03 | E80: 0.035 | F80: =IF($B$3="Bear",C80,IF($B$3="Bull",E80,D80)) -> 0.03 | G80: Tier 2 | H80: Critical | I80: GDP growth + inflation; cannot exceed WACC
A81: D28 | B81: Multiple Compression Factor | C81: 0.4 | D81: 0.5 | E81: 0.6 | F81: =IF($B$3="Bear",C81,IF($B$3="Bull",E81,D81)) -> 0.5 | G81: Tier 3 | H81: High | I81: Terminal multiples 40-60% lower than current comps. Applied to derive D11.
A83: Section 6: Comp Bucket Weighting — THIS IS THE THESIS
A84: V11a | B84: Bucket 1 Weight (Consumer Hardware — Garmin) | C84: 0.4 | D84: 0.2 | E84: 0.1 | F84: =IF($B$3="Bear",C84,IF($B$3="Bull",E84,D84)) -> 0.2 | G84: Design | H84: Critical | I84: Higher = more bearish (WHOOP as hardware company)
A85: V11b | B85: Bucket 2 Weight (Consumer Subscription — PTON/SPOT) | C85: 0.4 | D85: 0.4 | E85: 0.3 | F85: =IF($B$3="Bear",C85,IF($B$3="Bull",E85,D85)) -> 0.4 | G85: Design | H85: Critical | I85: Peloton-Spotify range disaggregated; where does WHOOP sit?
A86: V11c | B86: Bucket 3 Weight (Health Data — DXCM/RMD/MASI/IRTC) | C86: 0.2 | D86: 0.4 | E86: 0.6 | F86: =IF($B$3="Bear",C86,IF($B$3="Bull",E86,D86)) -> 0.4 | G86: Design | H86: Critical | I86: Higher = healthcare thesis is believed; Series G implied ~70%
A87: V11_chk | B87: Bucket Weights Sum (must = 100%) | C87: =C84+C85+C86 -> 1 | D87: =D84+D85+D86 -> 1 | E87: =E84+E85+E86 -> 1 | F87: =IF($B$3="Bear",C87,IF($B$3="Bull",E87,D87)) -> 1 | G87: Derived | H87: Check | I87: Sanity check: bucket weights must sum to 100%
A89: Section 7: IPO Trading Range & Discount Framework
A90: I1 | B90: IPO Timing (months from Series G) | C90: 18 | D90: 15 | E90: 12 | F90: =IF($B$3="Bear",C90,IF($B$3="Bull",E90,D90)) -> 15 | G90: Tier 2 | H90: High | I90: Q2 2027 - Q1 2028; "last private round" per Ahmed
A91: I2 | B91: IPO Pricing Discount (to Stage 1 fair value) | C91: 0.25 | D91: 0.2 | E91: 0.15 | F91: =IF($B$3="Bear",C91,IF($B$3="Bull",E91,D91)) -> 0.2 | G91: Tier 2 | H91: Critical | I91: Loughran/Ritter IPO pricing studies; 15-25% standard
A92: I3
A93: I4 | B93: Series G Investor Required IRR | C93: 0.3 | D93: 0.25 | E93: 0.2 | F93: =IF($B$3="Bear",C93,IF($B$3="Bull",E93,D93)) -> 0.25 | G93: Tier 3 | H93: Medium | I93: Late-stage growth equity return expectations (3-5yr hold)
A94: I5 | B94: Implied Stage 1 Public Fair Value ($M) — DERIVED | C94: =10100/(1-C92)/(1-C91) -> 13466.667 | D94: =10100/(1-D92)/(1-D91) -> 12625 | E94: =10100/(1-E92)/(1-E91) -> 11882.353 | F94: =IF($B$3="Bear",C94,IF($B$3="Bull",E94,D94)) -> 12625 | G94: Derived | H94: Critical | I94: Back-solve: $10.1B / (1-illiquidity) / (1-IPO discount) → $13-15B target
A96: Section 8: Precedent Transactions
A97: P1 | B97: Deal Inclusion Window | C97: Last 5 years | D97: Last 5 years | E97: Last 5 years | F97: =IF($B$3="Bear",C97,IF($B$3="Bull",E97,D97)) -> Last 5 years | G97: Design | H97: Locked | I97: 2021-2026 with 3-year primary focus
A98: P3 | B98: Deal Size Threshold ($M EV) | C98: 500 | D98: 500 | E98: 500 | F98: =IF($B$3="Bear",C98,IF($B$3="Bull",E98,D98)) -> 500 | G98: Design | H98: Locked | I98: Below this, synergy math distorts multiples
A99: P5 | B99: Multiple Extraction Method | C99: EV/LTM Rev | D99: EV/LTM Rev | E99: EV/LTM Rev | F99: =IF($B$3="Bear",C99,IF($B$3="Bull",E99,D99)) -> EV/LTM Rev | G99: Design | H99: Locked | I99: EV / LTM revenue at announcement; NTM where available
A100: P_b1 | B100: Bucket 1 Precedent Multiple (median) | C100: 1 | D100: 1.5 | E100: 2.5 | F100: =IF($B$3="Bear",C100,IF($B$3="Bull",E100,D100)) -> 1.5 | G100: Tier 2 | H100: High | I100: Fitbit/Google ~1.3x; Garmin tuck-ins; mostly distressed exits
A101: P_b2 | B101: Bucket 2 Precedent Multiple (median) | C101: 0.8 | D101: 1.5 | E101: 3 | F101: =IF($B$3="Bear",C101,IF($B$3="Bull",E101,D101)) -> 1.5 | G101: Tier 2 | H101: High | I101: Peloton/Precor; connected fitness all value-destructive
A102: P_b3 | B102: Bucket 3 Precedent Multiple (median) | C102: 6 | D102: 8 | E102: 10 | F102: =IF($B$3="Bear",C102,IF($B$3="Bull",E102,D102)) -> 8 | G102: Tier 2 | H102: High | I102: Per research/precedent-transactions.md: B3 medtech 6.6-10.1x range
A104: Section 9: Real Options — see rows 154-161 (binary-gate redesign, supersedes cluster framework)
A105: Healthcare reimbursement pathway is the only separately-valued real option. International, B2B, women's health, glucose moved to base case sensitivities or dropped. Inputs: RO1 (probability), RO2 (eligibility %), RO3 (payer ARPU), RO4 (multiple), RO5 (years). See RealOptions tab Section 5 for full justification.
A107: Legend & Conventions
A108: Blue text | B108: Hard-coded input
A109: Black text | B109: Formula / derived calculation
A110: Green text | B110: Cross-sheet link (wired when other tabs are built)
A111: Yellow fill | B111: FLAGGED_GAP — unsourced critical, needs verification
A112: Active col | B112: Picks Bear/Base/Bull per scenario selector at $B$3
A114: Section 10: Gross Adds Derivation Drivers
...

Sheet Assumptions Audit
A1: Assumptions Tab — Cleanup Audit
A2: Cross-sheet reference scan of every Assumptions row. Categories: WIRED (used downstream), INTERNAL (consumed only by other Assumptions cells), ORPHAN (defined but unreferenced anywhere), ARCHIVED (deprecated section per A126 header). Action column = recommendation.
A4: Summary by section
A5: Section | B5: Total Rows | C5: Wired | D5: Internal Only | E5: Orphan | F5: Notes
A6: Sec 1: Revenue & Growth (rows 8-28) | B6: 19 | C6: 6 | D6: 3 | E6: 10 | F6: Wired: F8, F9, F11, F12, F19, F20, F21. Phase growth & churn rates not used by Members/Revenue Build.
A7: Sec 2: Cost Structure (rows 31-53) | B7: 21 | C7: 8 | D7: 0 | E7: 13 | F7: Wired: F32, F39, F40, F41, F45, F46, F47, F48, F52, F53. Tier-by-tier GM (C7a/b/c) replaced by collapsed C7d_start/end (rows 151-152).
A8: Sec 3: Cap Structure (rows 55-67) | B8: 12 | C8: 4 | D8: 0 | E8: 8 | F8: Wired: F55 (FD shares), F62 (debt), F63 (cash), F67 (cash yield). Cap table detail (LP, ratchets, founder %, DLOM) unused.
A9: Sec 4: WACC (rows 69-74) | B9: 6 | C9: 6 | D9: 0 | E9: 0 | F9: All wired. Sensitivity grids reference C/D/E directly for bottom-up build (intentional).
A10: Sec 5: Terminal Value (rows 77-81) | B10: 5 | C10: 2 | D10: 0 | E10: 3 | F10: Wired: F78 (exit mult), F80 (terminal growth). Method label, EV/EBITDA, multiple compression unused.
A11: Sec 6: Comp Bucket Weights (rows 84-87) | B11: 4 | C11: 4 | D11: 0 | E11: 0 | F11: All wired. Comps tab references C/D/E directly for thesis-anchored brackets (intentional).
A12: Sec 7: IPO Range (rows 90-94) | B12: 5 | C12: 1 | D12: 0 | E12: 4 | F12: Wired: only F94 / C94/D94/E94 (Stage 1 fair value). Timing, discount, IRR — defined but unused.
A13: Sec 8: Precedents (rows 97-102) | B13: 6 | C13: 0 | D13: 0 | E13: 6 | F13: ENTIRE SECTION ORPHAN. Precedents tab does not reference Assumptions.
A14: Sec 9: Real Options (rows 156-161) | B14: 6 | C14: 5 | D14: 1 | E14: 0 | F14: All wired. RealOptions tab references C/D/E directly (intentional, scenario-aligned).
A15: Sec 10: Gross Adds Drivers (rows 117-123) | B15: 5 | C15: 5 | D15: 0 | E15: 0 | F15: All wired. Members tab uses F117, F118, F121, F122, F123.
A16: Sec 11: ARCHIVED ARPU decomp (rows 130-149) | B16: 18 | C16: 0 | D16: 0 | E16: 18 | F16: ARCHIVED per header A126. Replaced by R4g/C7d_start/C7d_end (rows 150-152). DELETE CANDIDATES.
A17: Collapsed Drivers (rows 150-152) | B17: 3 | C17: 3 | D17: 0 | E17: 0 | F17: All wired. R4g (ARPU growth) → ARPU tab. C7d_start/end → P&L.
A18: TOTAL | B18: =SUM(B6:B17) -> 110 | C18: =SUM(C6:C17) -> 44 | D18: =SUM(D6:D17) -> 4 | E18: =SUM(E6:E17) -> 62 | F18: Total assumption rows / wired / internal / orphan + archived
A20: Detailed Orphan List — Delete Candidates
A21: Row | B21: ID | C21: Label | D21: Status | E21: Reason / Replacement | F21: Action
A22: 14 | B22: R5 | C22: Subscription Revenue % | D22: ORPHAN | E22: Members tab tracks subscribers directly; sub % not used. Revenue Build derives from members × ARPU. | F22: DELETE
A23: 15 | B23: R6 | C23: 2025 YoY Subscription Growth | D23: ORPHAN | E23: Not referenced. Growth flows from Members tab cohort math. | F23: DELETE
A24: 16 | B24: R7 | C24: Phase 1 Revenue Growth (2026-27) | D24: ORPHAN | E24: Phase growth replaced by bottom-up Members × ARPU build. R7-R9 are legacy top-down inputs. | F24: DELETE
A25: 17 | B25: R8 | C25: Phase 2 Revenue Growth (2028-30) | D25: ORPHAN | E25: Same — superseded by bottom-up build. | F25: DELETE
A26: 18 | B26: R9 | C26: Phase 3 Revenue Growth (2031-33) | D26: ORPHAN | E26: Same — superseded by bottom-up build. | F26: DELETE
A27: 23 | B27: R11 | C27: B2B Unite Revenue % | D27: ORPHAN | E27: B2B not separately modeled in current build. Revenue Build aggregates. | F27: DELETE
A28: 24 | B28: R12 | C28: Advanced Labs Attach Rate | D28: ORPHAN | E28: Sec 11 ARCHIVED equivalent (R25a, row 137) was wired but archived. | F28: DELETE
A29: 25 | B29: R14 | C29: Labs Avg Test Price | D29: ORPHAN | E29: Sec 11 archived. Labs not currently driving. | F29: DELETE
A30: 26 | B30: R15 | C30: Annual Price Inflation | D30: ORPHAN | E30: Replaced by R4g (row 150) Blended ARPU growth. | F30: DELETE
A31: 27 | B31: R16 | C31: 2026 Gross Adds (M) | D31: ORPHAN | E31: Members tab back-solves gross adds from S&M / CAC (Sec 10 drivers). | F31: DELETE
A33: 31 | B33: C1 | C33: Hardware BOM per Device | D33: ORPHAN | E33: Hardware GM not separately modeled — collapsed into blended C7d_start/end. | F33: DELETE
A34: 33 | B34: C4 | C34: Subscription Delivery Cost % | D34: ORPHAN | E34: Same — collapsed into blended COGS. | F34: DELETE
... A61: 93 | B61: I4 | C61: Investor Required IRR | D61: ORPHAN | E61: F94 derivation uses C92/D92/E92 (the discount factor row, not visible in extract). | F61: VERIFY F93 not used; likely DELETE
A63: 97-102 | B63: P1-Pb3 | C63: Sec 8 Precedents (entire section) | D63: ORPHAN | E63: Precedents tab built independently. None of these inputs flow through. | F63: DELETE entire section
A65: 130-149 | B65: R24a-R27c | C65: Sec 11 ARCHIVED ARPU decomp | D65: ARCHIVED | E65: Header A126 confirms archived. 18 rows of tier-mix / labs / accessories / BP-healthspan decomp — all replaced by R4g (row 150). | F65: DELETE entire section
A67: Recommendations & Cleanup Path
A68: 1. Safe Bulk Delete — Sec 11 ARCHIVED (rows 126-149)
A69: Drop the entire 'Section 11 (ARCHIVED)' block. Header A126 explicitly marks it deprecated. Replaced by R4g/C7d_start/C7d_end (rows 150-152) which ARE wired. Verified zero downstream references. Removes 24 rows of clutter.
A70: 2. Safe Bulk Delete — Sec 8 Precedents (rows 96-102)
A71: Entire section unreferenced. Precedents tab does not pull from Assumptions. If precedents analysis is parked for later, leave inputs on Precedents tab itself, not in master Assumptions.
A72: 3. Sec 1 + Sec 2 Cleanup — Legacy top-down inputs
A73: Phase growth (R7-R9), B2B/Labs/inflation (R11-R15), gross adds anchor (R16), and tier-by-tier GMs (C7a-c) are vestiges of an earlier top-down structure. The bottom-up Members × ARPU build supersedes them. Recommend deleting after a final scan to confirm no notes/comments depend on these row IDs.
A74: 4. Sec 3 Cap Structure — Trim
A75: Keep F55 (FD shares), F62 (debt), F63 (cash), F67 (cash yield). Consider keeping S16 (ratchet provisions) as text documentation. Delete S2-S9, S15. Removes 8 rows.
A76: 5. Sec 5/7 Trim
A77: Sec 5: keep F78 (exit mult) and F80 (terminal growth); delete D9 method label, D11 EV/EBITDA, D28 multiple compression. Sec 7: keep C/D/E values for I2-I3 (used inline in F94 formula); delete F-row pulls for I1, I4 if confirmed unused.
A79: Estimated Net Cleanup
A80: Total rows defined: | B80: ~110 input + label rows
A81: Safe deletes (immediate): | B81: ~18 rows (Sec 11 archived + Sec 8 precedents)
A82: Conditional deletes (after sign-off): | B82: ~30+ rows (legacy Sec 1/2/3/5/7 inputs)
A83: Post-cleanup target: | B83: ~60 rows (45% reduction in Assumptions tab footprint)
A85: IMPORTANT — Read Before Deleting
A86: Some 'orphan' rows are referenced by NOTES on other cells (e.g., 'see C40' in DCF row 32) rather than by formula. Notes preserve audit trail but break if rows shift. Recommend: instead of deleting rows in place, MOVE all orphans to a 'Section X: ARCHIVED' bucket at the bottom of Assumptions, mark them gray, and reclaim the space if desired in a later pass.

Sheet Members
A1: WHOOP — Member Cohort Engine
A2: Members in millions; cohort engine drives revenue. 2025 beginning treated as Y3+ legacy block (simplification — see note).
B5: Units | C5: 2024 | D5: 2025 | E5: 2026 | F5: 2027 | G5: 2028 | H5: 2029 | I5: 2030 | J5: 2031 | K5: 2032 | L5: 2033
C6: Historical | D6: Historical | E6: Phase 1 | F6: Phase 1 | G6: Phase 2 | H6: Phase 2 | I6: Phase 2 | J6: Phase 3 | K6: Phase 3 | L6: Phase 3
A8: 1. Beginning Members (start of year)
A9: Beginning Members (total) | B9: M | C9: 0.7 | D9: =Assumptions!$F$8 -> 1.3 | E9: =D34 -> 2.5 | F9: =E34 -> 2.98669 | G9: =F34 -> 3.6873114 | H9: =G34 -> 4.4220311 | I9: =H34 -> 5.1901123 | J9: =I34 -> 5.9725117 | K9: =J34 -> 6.7474478 | L9: =K34 -> 7.4928859
A10: of which: Year-1 cohort | B10: M | C10: 0.5 | D10: 0 | E10: =D31 -> 1.304 | F10: =E31 -> 0.86925 | G10: =F31 -> 1.1222788 | H10: =G31 -> 1.2275045 | I10: =H31 -> 1.346217 | J10: =I31 -> 1.443526 | K10: =J31 -> 1.5178336 | L10: =K31 -> 1.5652877
A11: of which: Year-2 cohort | B11: M | C11: 0.15 | D11: 0 | E11: =D26 -> 0 | F11: =E26 -> 1.01712 | G11: =F26 -> 0.678015 | H11: =G26 -> 0.87537746 | I11: =H26 -> 0.95745351 | J11: =I26 -> 1.0500492 | K11: =J26 -> 1.1259503 | L11: =K26 -> 1.1839102
A12: of which: Year-3+ cohort | B12: M | C12: 0.05 | D12: =Assumptions!$F$8 -> 1.3 | E12: =D28 -> 1.196 | F12: =E28 -> 1.10032 | G12: =F28 -> 1.8870176 | H12: =G28 -> 2.3191491 | I12: =H28 -> 2.8864418 | J12: =I28 -> 3.4789365 | K12: =J28 -> 4.1036639 | L12: =K28 -> 4.743688
A14: 2. Churn Rates (cohort-aged, from Assumptions)
A15: Year-1 churn rate | B15: % | C15: =Assumptions!$F$19 -> 0.22 | D15: =Assumptions!$F$19 -> 0.22 | E15: =Assumptions!$F$19 -> 0.22 | F15: =Assumptions!$F$19 -> 0.22 | G15: =Assumptions!$F$19 -> 0.22 | H15: =Assumptions!$F$19 -> 0.22 | I15: =Assumptions!$F$19 -> 0.22 | J15: =Assumptions!$F$19 -> 0.22 | ... L15: =Assumptions!$F$19 -> 0.22
A16: Year-2 churn rate | B16: % | C16: =Assumptions!$F$20 -> 0.14 | D16: =Assumptions!$F$20 -> 0.14 | E16: =Assumptions!$F$20 -> 0.14 | F16: =Assumptions!$F$20 -> 0.14 | G16: =Assumptions!$F$20 -> 0.14 | H16: =Assumptions!$F$20 -> 0.14 | I16: =Assumptions!$F$20 -> 0.14 | J16: =Assumptions!$F$20 -> 0.14 | ... L16: =Assumptions!$F$20 -> 0.14
A17: Year-3+ churn rate | B17: % | C17: =Assumptions!$F$21 -> 0.08 | D17: =Assumptions!$F$21 -> 0.08 | E17: =Assumptions!$F$21 -> 0.08 | F17: =Assumptions!$F$21 -> 0.08 | G17: =Assumptions!$F$21 -> 0.08 | H17: =Assumptions!$F$21 -> 0.08 | I17: =Assumptions!$F$21 -> 0.08 | J17: =Assumptions!$F$21 -> 0.08 | ... L17: =Assumptions!$F$21 -> 0.08
A19: 3. Churned Members
A20: Y1 churned | B20: M | C20: =C10*C15 -> 0.11 | D20: =D10*D15 -> 0 | E20: =E10*E15 -> 0.28688 | F20: =F10*F15 -> 0.191235 | G20: =G10*G15 -> 0.24690133 | H20: =H10*H15 -> 0.27005099 | I20: =I10*I15 -> 0.29616773 | J20: =J10*J15 -> 0.31757572 | ... L20: =L10*L15 -> 0.34436329
A21: Y2 churned | B21: M | C21: =C11*C16 -> 0.021 | D21: =D11*D16 -> 0 | E21: =E11*E16 -> 0 | F21: =F11*F16 -> 0.1423968 | G21: =G11*G16 -> 0.0949221 | H21: =H11*H16 -> 0.12255284 | I21: =I11*I16 -> 0.13404349 | J21: =J11*J16 -> 0.14700689 | ... L21: =L11*L16 -> 0.16574743
A22: Y3+ churned | B22: M | C22: =C12*C17 -> 0.004 | D22: =D12*D17 -> 0.104 | E22: =E12*E17 -> 0.09568 | F22: =F12*F17 -> 0.0880256 | G22: =G12*G17 -> 0.15096141 | H22: =H12*H17 -> 0.18553193 | I22: =I12*I17 -> 0.23091534 | J22: =J12*J17 -> 0.27831492 | ... L22: =L12*L17 -> 0.37949504
A23: Total churned | B23: M | C23: =SUM(C20:C22) -> 0.135 | D23: =SUM(D20:D22) -> 0.104 | E23: =SUM(E20:E22) -> 0.38256 | F23: =SUM(F20:F22) -> 0.4216574 | G23: =SUM(G20:G22) -> 0.49278484 | H23: =SUM(H20:H22) -> 0.57813576 | I23: =SUM(I20:I22) -> 0.66112657 | J23: =SUM(J20:J22) -> 0.74289753 | ... L23: =SUM(L20:L22) -> 0.88960576
A25: 4. Surviving Members (end of year, before new adds)
A26: Y1 survivors | B26: M | C26: =C10-C20 -> 0.39 | D26: =D10-D20 -> 0 | E26: =E10-E20 -> 1.01712 | F26: =F10-F20 -> 0.678015 | G26: =G10-G20 -> 0.87537746 | H26: =H10-H20 -> 0.95745351 | I26: =I10-I20 -> 1.0500492 | J26: =J10-J20 -> 1.1259503 | ... L26: =L10-L20 -> 1.2209244
A27: Y2 survivors | B27: M | C27: =C11-C21 -> 0.129 | D27: =D11-D21 -> 0 | E27: =E11-E21 -> 0 | F27: =F11-F21 -> 0.8747232 | G27: =G11-G21 -> 0.5830929 | H27: =H11-H21 -> 0.75282461 | I27: =I11-I21 -> 0.82341002 | J27: =J11-J21 -> 0.90304235 | ... L27: =L11-L21 -> 1.0181628
A28: Y3+ end state (incl. Y2 graduates) | B28: M | C28: =C12-C22+C27 -> 0.175 | D28: =D12-D22+D27 -> 1.196 | E28: =E12-E22+E27 -> 1.10032 | F28: =F12-F22+F27 -> 1.8870176 | G28: =G12-G22+G27 -> 2.3191491 | H28: =H12-H22+H27 -> 2.8864418 | I28: =I12-I22+I27 -> 3.4789365 | J28: =J12-J22+J27 -> 4.1036639 | ... L28: =L12-L22+L27 -> 5.3823558
A30: 5. New Members (Gross Adds — input per year)
A31: Gross Adds | B31: M | C31: 0.6 | D31: =Assumptions!$F$9-D28 -> 1.304 | E31: =E51 -> 0.86925 | F31: =F51 -> 1.1222788 | G31: =G51 -> 1.2275045 | H31: =H51 -> 1.346217 | I31: =I51 -> 1.443526 | J31: =J51 -> 1.5178336 | K31: =K51 -> 1.5652877 | L31: =L51 -> 1.5830071
A33: 6. Ending & Average Members
A34: Ending Members | B34: M | C34: =C26+C28+C31 -> 1.165 | D34: =D26+D28+D31 -> 2.5 | E34: =E26+E28+E31 -> 2.98669 | F34: =F26+F28+F31 -> 3.6873114 | G34: =G26+G28+G31 -> 4.4220311 | H34: =H26+H28+H31 -> 5.1901123 | I34: =I26+I28+I31 -> 5.9725117 | J34: =J26+J28+J31 -> 6.7474478 | ... L34: =L26+L28+L31 -> 8.1862873
A35: Average Members | B35: M | C35: =(C9+C34)/2 -> 0.9325 | D35: =(D9+D34)/2 -> 1.9 | E35: =(E9+E34)/2 -> 2.743345 | F35: =(F9+F34)/2 -> 3.3370007 | G35: =(G9+G34)/2 -> 4.0546712 | H35: =(H9+H34)/2 -> 4.8060717 | I35: =(I9+I34)/2 -> 5.581312 | J35: =(J9+J34)/2 -> 6.3599798 | ... L35: =(L9+L34)/2 -> 7.8395866
A37: 7. Diagnostics (output, not input)
A38: Net Adds (Gross - Churned) | B38: M | C38: =C31-C23 -> 0.465 | D38: =D31-D23 -> 1.2 | E38: =E31-E23 -> 0.48669 | F38: =F31-F23 -> 0.70062139 | G38: =G31-G23 -> 0.73471966 | H38: =H31-H23 -> 0.76808121 | I38: =I31-I23 -> 0.78239945 | J38: =J31-J23 -> 0.77493607 | ... L38: =L31-L23 -> 0.69340135
A39: Net Member Growth % | B39: % | D39: =D34/C34-1 -> 1.1459227 | E39: =E34/D34-1 -> 0.194676 | F39: =F34/E34-1 -> 0.23458122 | G39: =G34/F34-1 -> 0.1992562 | H39: =H34/G34-1 -> 0.17369422 | I39: =I34/H34-1 -> 0.15074808 | J39: =J34/I34-1 -> 0.12975045 | K39: =K34/J34-1 -> 0.11047705 | L39: =L34/K34-1 -> 0.092541293
A40: Blended Annual Churn Rate (output) | B40: % | C40: =IFERROR(C23/C9,0) -> 0.19285714 | D40: =IFERROR(D23/D9,0) -> 0.08 | E40: =IFERROR(E23/E9,0) -> 0.153024 | F40: =IFERROR(F23/F9,0) -> 0.14117883 | G40: =IFERROR(G23/G9,0) -> 0.1336434 | H40: =IFERROR(H23/H9,0) -> 0.13073987 | I40: =IFERROR(I23/I9,0) -> 0.12738194 | J40: =IFERROR(J23/J9,0) -> 0.12438612 | ... L40: =IFERROR(L23/L9,0) -> 0.11872672
A41: 2025 ending vs Assumptions R3b (consistency) | B41: % | D41: =D34/Assumptions!$F$9-1 -> 0
A43: NOTE: 2025 beginning is treated as Y3+ legacy block (simplification). Replace with audited cohort splits when S-1 data is available. 2024 column is historical reference; engine fully runs 2025 onwards.
A45: 8. Gross Adds Build (DERIVED — S&M / CAC, with TAM diagnostic)
A46: Phase # (DEPRECATED — replaced by linear interpolation) | B46: # | C46: Hist | D46: Hist
A47: S&M Budget ($M = prior-yr rev × interpolated S&M%) | B47: $M | D47: 195 | E47: ='Revenue Build'!D20*(Assumptions!$F$117 + (Assumptions!$F$118-Assumptions!$F$117)*(E$5-2026)/7) -> 173.85 | F47: ='Revenue Build'!E20*(Assumptions!$F$117 + (Assumptions!$F$118-Assumptions!$F$117)*(F$5-2026)/7) -> 247.38231 | G47: ='Revenue Build'!F20*(Assumptions!$F$117 + (Assumptions!$F$118-Assumptions!$F$117)*(G$5-2026)/7) -> 295.65323 | H47: ='Revenue Build'!G20*(Assumptions!$F$117 + (Assumptions!$F$118-Assumptions!$F$117)*(H$5-2026)/7) -> 351.74726 | I47: ='Revenue Build'!H20*(Assumptions!$F$117 + (Assumptions!$F$118-Assumptions!$F$117)*(I$5-2026)/7) -> 406.6619 | J47: ='Revenue Build'!I20*(Assumptions!$F$117 + (Assumptions!$F$118-Assumptions!$F$117)*(J$5-2026)/7) -> 458.60258 | K47: ='Revenue Build'!J20*(Assumptions!$F$117 + (Assumptions!$F$118-Assumptions!$F$117)*(K$5-2026)/7) -> 504.91708 | L47: ='Revenue Build'!K20*(Assumptions!$F$117 + (Assumptions!$F$118-Assumptions!$F$117)*(L$5-2026)/7) -> 542.97144
A48: Blended CAC ($, linearly interpolated F121→F122) | B48: $ | D48: 130 | E48: =Assumptions!$F$121 + (Assumptions!$F$122-Assumptions!$F$121)*(E$5-2026)/7 -> 200 | F48: =Assumptions!$F$121 + (Assumptions!$F$122-Assumptions!$F$121)*(F$5-2026)/7 -> 220.42857 | G48: =Assumptions!$F$121 + (Assumptions!$F$122-Assumptions!$F$121)*(G$5-2026)/7 -> 240.85714 | H48: =Assumptions!$F$121 + (Assumptions!$F$122-Assumptions!$F$121)*(H$5-2026)/7 -> 261.28571 | I48: =Assumptions!$F$121 + (Assumptions!$F$122-Assumptions!$F$121)*(I$5-2026)/7 -> 281.71429 | J48: =Assumptions!$F$121 + (Assumptions!$F$122-Assumptions!$F$121)*(J$5-2026)/7 -> 302.14286 | K48: =Assumptions!$F$121 + (Assumptions!$F$122-Assumptions!$F$121)*(K$5-2026)/7 -> 322.57143 | L48: =Assumptions!$F$121 + (Assumptions!$F$122-Assumptions!$F$121)*(L$5-2026)/7 -> 343
A49: Unconstrained Gross Adds (M) = S&M / CAC | B49: M | D49: =D47/D48 -> 1.5 | E49: =E47/E48 -> 0.86925 | F49: =F47/F48 -> 1.1222788 | G49: =G47/G48 -> 1.2275045 | H49: =H47/H48 -> 1.346217 | I49: =I47/I48 -> 1.443526 | J49: =J47/J48 -> 1.5178336 | K49: =K47/K48 -> 1.5652877 | L49: =L47/L48 -> 1.5830071
A50: TAM Penetration % (diagnostic — flag if >40%) | B50: % | D50: n/a | E50: =D34/Assumptions!$F$123 -> 0.1 | F50: =E34/Assumptions!$F$123 -> 0.1194676 | G50: =F34/Assumptions!$F$123 -> 0.14749246 | H50: =G34/Assumptions!$F$123 -> 0.17688124 | I50: =H34/Assumptions!$F$123 -> 0.20760449 | J50: =I34/Assumptions!$F$123 -> 0.23890047 | K50: =J34/Assumptions!$F$123 -> 0.26989791 | L50: =K34/Assumptions!$F$123 -> 0.29971544
A51: Final Gross Adds (M) | B51: M | D51: =D49 -> 1.5 | E51: =E49 -> 0.86925 | F51: =F49 -> 1.1222788 | G51: =G49 -> 1.2275045 | H51: =H49 -> 1.346217 | I51: =I49 -> 1.443526 | J51: =J49 -> 1.5178336 | K51: =K49 -> 1.5652877 | L51: =L49 -> 1.5830071

Sheet ARPU
A1: ARPU — Single-Line Blended Driver (collapsed from 5-component build)
A2: Active driver: Assumptions R4 (anchor) compounded by R4g (annual growth). Bottom-up justification preserved as memo block below — does not feed model. Consistency check at row 38 verifies Members × ARPU ≈ Methodology rev anchor.
A5: Year | B5: Unit | C5: 2024 | D5: 2025 | E5: 2026 | F5: 2027 | G5: 2028 | H5: 2029 | I5: 2030 | J5: 2031 | K5: 2032 | L5: 2033
A7: Blended ARPU (driver)
A8: 2025 Anchor (Assumptions R4) | B8: $/yr | D8: =Assumptions!$F$11 -> 305
A9: Annual growth rate (Assumptions R4g) | B9: % | D9: =Assumptions!$F$150 -> 0.04
A10: Blended ARPU | B10: $/yr | C10: 0 | D10: =D8 -> 305 | E10: =D10*(1+$D$9) -> 317.2 | F10: =E10*(1+$D$9) -> 329.888 | G10: =F10*(1+$D$9) -> 343.08352 | H10: =G10*(1+$D$9) -> 356.80686 | I10: =H10*(1+$D$9) -> 371.07914 | J10: =I10*(1+$D$9) -> 385.9223 | K10: =J10*(1+$D$9) -> 401.35919 | L10: =K10*(1+$D$9) -> 417.41356
A13: ARPU Justification (memo — does not drive model)
A14: Bottom-up reconciliation showing how blended ARPU reflects consumer + B2B mix. Numbers below are reference; active driver is Section 1 R4 above.
A16: Consumer per-member ARPU components:
A17: Subscription tier-weighted average | B17: $/yr | D17: 258 | E17: Tier mix 30/45/25 × $199/$239/$359 = $257; +$1.68 monthly premium
A18: Labs ARPU at maturity (10% attach × $250 × 1.5 tests) | B18: $/yr | D18: 38
A19: Accessories ARPU | B19: $/yr | D19: 18
A20: BP/Healthspan ARPU at 5% attach (post-launch) | B20: $/yr | D20: 5
A21: Consumer ARPU (mature, 2026+) | B21: $/yr | D21: =SUM(D17:D20) -> 319
A22: Consumer ARPU (2025, partial Labs only) | B22: $/yr | D22: 278
A24: B2B Unite per-seat:
A25: Per-seat employer-rate ARPU | B25: $/yr | D25: 260 | E25: B2B health platforms with bundled hardware: $200-350; standalone software: $100-180. Estimate $260 mid-range.
A27: Mix assumption (% of paying members):
A28: Consumer share | B28: % | D28: 0.8 | E28: BMCT estimate: Unite ~20% of recurring revenue
A29: Unite share | B29: % | D29: 0.2
A30: Mix sum check | D30: =D28+D29 -> 1 | E30: Must = 100%
A32: Implied blended ARPU 2025 (memo): | D32: =D28*D22 + D29*D25 -> 274.4
A33: Implied blended ARPU 2026 mature (memo): | D33: =D28*D21 + D29*D25 -> 307.2
A34: Anchor used in driver (R4) | D34: =Assumptions!$F$11 -> 305
A35: Variance vs implied (mature) | D35: =(D34-D33)/D33 -> -0.0071614583
A36: Status | D36: =IF(ABS(D35)<=0.1,"✓ within ±10% of justification","⚠ anchor diverges from justification — review") -> ✓ within ±10% of justification
A38: Consistency Check: Members × ARPU = Revenue
A39: 2025 Avg Members × Blended ARPU | B39: $M | D39: =Members!D35*D10 -> 579.5
A40: Methodology revenue prior (Assumptions R1 / F12) | B40: $M | D40: =Assumptions!$F$12 -> 579.5
A41: Variance | D41: =(D39-D40)/D40 -> 0
A42: Status | D42: =IF(ABS(D41)<=0.05,"✓ within ±5%","⚠ outside ±5% — reconcile") -> ✓ within ±5%

Sheet Revenue Build
A1: WHOOP — Revenue Build-Up
A2: $M unless noted; Calendar Year
B5: Units | C5: 2024 | D5: 2025 | E5: 2026 | F5: 2027 | G5: 2028 | H5: 2029 | I5: 2030 | J5: 2031 | K5: 2032 | L5: 2033
C6: Historical | D6: Historical | E6: Phase 1 | F6: Phase 1 | G6: Phase 2 | H6: Phase 2 | I6: Phase 2 | J6: Phase 3 | K6: Phase 3 | L6: Phase 3
A8: 1. Member Economics (linked from Members tab)
A9: Beginning Members | B9: M | C9: =Members!C9 -> 0.7 | D9: =Members!D9 -> 1.3 | E9: =Members!E9 -> 2.5 | F9: =Members!F9 -> 2.98669 | G9: =Members!G9 -> 3.6873114 | H9: =Members!H9 -> 4.4220311 | I9: =Members!I9 -> 5.1901123 | J9: =Members!J9 -> 5.9725117 | ... L9: =Members!L9 -> 7.4928859
A10: Gross Adds | B10: M | C10: =Members!C31 -> 0.6 | D10: =Members!D31 -> 1.304 | E10: =Members!E31 -> 0.86925 | F10: =Members!F31 -> 1.1222788 | G10: =Members!G31 -> 1.2275045 | H10: =Members!H31 -> 1.346217 | I10: =Members!I31 -> 1.443526 | J10: =Members!J31 -> 1.5178336 | ... L10: =Members!L31 -> 1.5830071
A11: Churned Members | B11: M | C11: =Members!C23 -> 0.135 | D11: =Members!D23 -> 0.104 | E11: =Members!E23 -> 0.38256 | F11: =Members!F23 -> 0.4216574 | G11: =Members!G23 -> 0.49278484 | H11: =Members!H23 -> 0.57813576 | I11: =Members!I23 -> 0.66112657 | J11: =Members!J23 -> 0.74289753 | ... L11: =Members!L23 -> 0.88960576
A12: Ending Members | B12: M | C12: =Members!C34 -> 1.165 | D12: =Members!D34 -> 2.5 | E12: =Members!E34 -> 2.98669 | F12: =Members!F34 -> 3.6873114 | G12: =Members!G34 -> 4.4220311 | H12: =Members!H34 -> 5.1901123 | I12: =Members!I34 -> 5.9725117 | J12: =Members!J34 -> 6.7474478 | ... L12: =Members!L34 -> 8.1862873
A13: Avg Members | B13: M | C13: =Members!C35 -> 0.9325 | D13: =Members!D35 -> 1.9 | E13: =Members!E35 -> 2.743345 | F13: =Members!F35 -> 3.3370007 | G13: =Members!G35 -> 4.0546712 | H13: =Members!H35 -> 4.8060717 | I13: =Members!I35 -> 5.581312 | J13: =Members!J35 -> 6.3599798 | ... L13: =Members!L35 -> 7.8395866
A14: Blended Annual Churn (output) | B14: % | C14: =IFERROR(Members!C23/Members!C9, 0) -> 0.19285714 | D14: =IFERROR(Members!D23/Members!D9, 0) -> 0.08 | E14: =IFERROR(Members!E23/Members!E9, 0) -> 0.153024 | F14: =IFERROR(Members!F23/Members!F9, 0) -> 0.14117883 | G14: =IFERROR(Members!G23/Members!G9, 0) -> 0.1336434 | H14: =IFERROR(Members!H23/Members!H9, 0) -> 0.13073987 | I14: =IFERROR(Members!I23/Members!I9, 0) -> 0.12738194 | J14: =IFERROR(Members!J23/Members!J9, 0) -> 0.12438612 | ... L14: =IFERROR(Members!L23/Members!L9, 0) -> 0.11872672
A16: 2. ARPU (linked from ARPU tab)
A17: Blended ARPU | B17: $/yr | C17: =ARPU!C10 -> 0 | D17: =ARPU!D10 -> 305 | E17: =ARPU!E10 -> 317.2 | F17: =ARPU!F10 -> 329.888 | G17: =ARPU!G10 -> 343.08352 | H17: =ARPU!H10 -> 356.80686 | I17: =ARPU!I10 -> 371.07914 | J17: =ARPU!J10 -> 385.9223 | ... L17: =ARPU!L10 -> 417.41356
A19: 3. Revenue Build
A20: Recognized Revenue (Total) | B20: $M | C20: =C13*C17 -> 0 | D20: =D13*D17 -> 579.5 | E20: =E13*E17 -> 870.18903 | F20: =F13*F17 -> 1100.8365 | G20: =G13*G17 -> 1391.0909 | H20: =H13*H17 -> 1714.8393 | I20: =I13*I17 -> 2071.1084 | J20: =J13*J17 -> 2454.458 | ... L20: =L13*L17 -> 3272.3497
A21: Memo: Δ Deferred Rev Balance (flows to NWC, not P&L) | B21: $M | C21: =C20*Assumptions!$F$28 -> 0 | D21: =D20*Assumptions!$F$28 -> -46.36 | E21: =E20*Assumptions!$F$28 -> -69.615123 | F21: =F20*Assumptions!$F$28 -> -88.066919 | G21: =G20*Assumptions!$F$28 -> -111.28727 | H21: =H20*Assumptions!$F$28 -> -137.18715 | I21: =I20*Assumptions!$F$28 -> -165.68867 | J21: =J20*Assumptions!$F$28 -> -196.35664 | ... L21: =L20*Assumptions!$F$28 -> -261.78798
A22: YoY Revenue Growth | B22: % | D22: =IFERROR(D20/C20-1,0) -> 0 | E22: =E20/D20-1 -> 0.50162042 | F22: =F20/E20-1 -> 0.26505442 | G22: =G20/F20-1 -> 0.26366712 | H22: =H20/G20-1 -> 0.23272992 | I22: =I20/H20-1 -> 0.20775654 | J22: =J20/I20-1 -> 0.18509393 | K22: =K20/J20-1 -> 0.16430772 | L22: =L20/K20-1 -> 0.14508132
A24: 4. Bookings Reconciliation
A25: Implied Bookings (End × ARPU) | B25: $M | C25: =C12*C17 -> 0 | D25: =D12*D17 -> 762.5 | E25: =E12*E17 -> 947.37807 | F25: =F12*F17 -> 1216.3998 | G25: =G12*G17 -> 1517.126 | H25: =H12*H17 -> 1851.8677 | I25: =I12*I17 -> 2216.2745 | J25: =J12*J17 -> 2603.9906 | ... L25: =L12*L17 -> 3417.0673
A26: Bookings/Revenue Ratio | B26: x | C26: =IFERROR(C25/C20, 0) -> 0 | D26: =IFERROR(D25/D20, 0) -> 1.3157895 | E26: =IFERROR(E25/E20, 0) -> 1.0887038 | F26: =IFERROR(F25/F20, 0) -> 1.1049777 | G26: =IFERROR(G25/G20, 0) -> 1.0906016 | H26: =IFERROR(H25/H20, 0) -> 1.0799074 | I26: =IFERROR(I25/I20, 0) -> 1.070091 | J26: =IFERROR(J25/J20, 0) -> 1.0609228 | ... L26: =IFERROR(L25/L20, 0) -> 1.0442244
A27: 2025 Recognized vs Assumptions R1 (consistency) | B27: % | D27: =D20/Assumptions!$F$12-1 -> 0

Sheet P&L
A1: WHOOP — Projected Income Statement
A2: $M; Calendar Year; Scenario per Assumptions toggle
A3: Calibration items: see notes on F31 (2027 dip), L23 (S&M architecture). Margin tapers and NOL wired; refer to CalibrationLog for status.
B5: Units | C5: 2024 | D5: 2025 | E5: 2026 | F5: 2027 | G5: 2028 | H5: 2029 | I5: 2030 | J5: 2031 | K5: 2032 | L5: 2033
A7: Revenue
A8: Total Revenue | B8: $M | C8: ='Revenue Build'!C20 -> 0 | D8: ='Revenue Build'!D20 -> 579.5 | E8: ='Revenue Build'!E20 -> 870.18903 | F8: ='Revenue Build'!F20 -> 1100.8365 | G8: ='Revenue Build'!G20 -> 1391.0909 | H8: ='Revenue Build'!H20 -> 1714.8393 | I8: ='Revenue Build'!I20 -> 2071.1084 | J8: ='Revenue Build'!J20 -> 2454.458 | ... L8: ='Revenue Build'!L20 -> 3272.3497 | M8: ← From Revenue Build tab
A9: YoY Growth | B9: % | D9: =IFERROR(D8/C8-1,0) -> 0 | E9: =E8/D8-1 -> 0.50162042 | F9: =F8/E8-1 -> 0.26505442 | G9: =G8/F8-1 -> 0.26366712 | H9: =H8/G8-1 -> 0.23272992 | I9: =I8/H8-1 -> 0.20775654 | J9: =J8/I8-1 -> 0.18509393 | K9: =K8/J8-1 -> 0.16430772 | L9: =L8/K8-1 -> 0.14508132
A11: Cost of Revenue
A12: Total COGS (Blended COGS% × Revenue, linearly interpolated) | B12: $M | D12: =D8*0.4 -> 231.8 | E12: =E8*(Assumptions!$F$151 + (Assumptions!$F$152-Assumptions!$F$151)*(E$5-2026)/7) -> 217.54726 | F12: =F8*(Assumptions!$F$151 + (Assumptions!$F$152-Assumptions!$F$151)*(F$5-2026)/7) -> 267.346 | G12: =G8*(Assumptions!$F$151 + (Assumptions!$F$152-Assumptions!$F$151)*(G$5-2026)/7) -> 327.89999 | H12: =H8*(Assumptions!$F$151 + (Assumptions!$F$152-Assumptions!$F$151)*(H$5-2026)/7) -> 391.96328 | I12: =I8*(Assumptions!$F$151 + (Assumptions!$F$152-Assumptions!$F$151)*(I$5-2026)/7) -> 458.60258 | J12: =J8*(Assumptions!$F$151 + (Assumptions!$F$152-Assumptions!$F$151)*(J$5-2026)/7) -> 525.95529 | K12: =K8*(Assumptions!$F$151 + (Assumptions!$F$152-Assumptions!$F$151)*(K$5-2026)/7) -> 591.96134 | L12: =L8*(Assumptions!$F$151 + (Assumptions!$F$152-Assumptions!$F$151)*(L$5-2026)/7) -> 654.46995
A13: Hardware COGS (MEMO ONLY — embedded in blended COGS%; used for WC inventory only) | B13: $M | D13: =Members!D31 * Assumptions!$F$32 -> 156.48 | E13: =Members!E31 * Assumptions!$F$32 -> 104.31 | F13: =Members!F31 * Assumptions!$F$32 -> 134.67346 | G13: =Members!G31 * Assumptions!$F$32 -> 147.30054 | H13: =Members!H31 * Assumptions!$F$32 -> 161.54604 | I13: =Members!I31 * Assumptions!$F$32 -> 173.22312 | J13: =Members!J31 * Assumptions!$F$32 -> 182.14003 | K13: =Members!K31 * Assumptions!$F$32 -> 187.83452 | L13: =Members!L31 * Assumptions!$F$32 -> 189.96085
A14: Total COGS (= row 12) | B14: $M | D14: =D12 -> 231.8 | E14: =E12 -> 217.54726 | F14: =F12 -> 267.346 | G14: =G12 -> 327.89999 | H14: =H12 -> 391.96328 | I14: =I12 -> 458.60258 | J14: =J12 -> 525.95529 | K14: =K12 -> 591.96134 | L14: =L12 -> 654.46995
A15: Gross Profit | B15: $M | D15: =D8-D12 -> 347.7 | E15: =E8-E12 -> 652.64178 | F15: =F8-F12 -> 833.49048 | G15: =G8-G12 -> 1063.1909 | H15: =H8-H12 -> 1322.8761 | I15: =I8-I12 -> 1612.5058 | J15: =J8-J12 -> 1928.5027 | K15: =K8-K12 -> 2265.7831 | L15: =L8-L12 -> 2617.8798
A16: Gross Margin | B16: % | D16: =D15/D8 -> 0.6 | E16: =E15/E8 -> 0.75 | F16: =F15/F8 -> 0.75714286 | G16: =G15/G8 -> 0.76428571 | H16: =H15/H8 -> 0.77142857 | I16: =I15/I8 -> 0.77857143 | J16: =J15/J8 -> 0.78571429 | K16: =K15/K8 -> 0.79285714 | L16: =L15/L8 -> 0.8
A20: Operating Expenses
A21: R&D | B21: $M | D21: =D8*Assumptions!$F$39 -> 127.49 | E21: =E8*(Assumptions!$F$39 + (Assumptions!$F$40-Assumptions!$F$39)*(E$5-2026)/7) -> 191.44159 | F21: =F8*(Assumptions!$F$39 + (Assumptions!$F$40-Assumptions!$F$39)*(F$5-2026)/7) -> 231.17566 | G21: =G8*(Assumptions!$F$39 + (Assumptions!$F$40-Assumptions!$F$39)*(G$5-2026)/7) -> 278.21818 | H21: =H8*(Assumptions!$F$39 + (Assumptions!$F$40-Assumptions!$F$39)*(H$5-2026)/7) -> 325.81948 | I21: =I8*(Assumptions!$F$39 + (Assumptions!$F$40-Assumptions!$F$39)*(I$5-2026)/7) -> 372.79952 | J21: =J8*(Assumptions!$F$39 + (Assumptions!$F$40-Assumptions!$F$39)*(J$5-2026)/7) -> 417.25786 | K21: =K8*(Assumptions!$F$39 + (Assumptions!$F$40-Assumptions!$F$39)*(K$5-2026)/7) -> 457.23911 | L21: =L8*(Assumptions!$F$39 + (Assumptions!$F$40-Assumptions!$F$39)*(L$5-2026)/7) -> 490.85246
A22: R&D % Revenue | B22: % | D22: =D21/D8 -> 0.22 | E22: =E21/E8 -> 0.22 | F22: =F21/F8 -> 0.21 | G22: =G21/G8 -> 0.2 | H22: =H21/H8 -> 0.19 | I22: =I21/I8 -> 0.18 | J22: =J21/J8 -> 0.17 | K22: =K21/K8 -> 0.16 | L22: =L21/L8 -> 0.15 | M22: ← From Assumptions F39/F40 (R&D phase % linearly interpolated)
A23: Sales & Marketing | B23: $M | D23: =D8*Assumptions!$F$41 -> 173.85 | E23: =Members!E47 -> 173.85 | F23: =Members!F47 -> 247.38231 | G23: =Members!G47 -> 295.65323 | H23: =Members!H47 -> 351.74726 | I23: =Members!I47 -> 406.6619 | J23: =Members!J47 -> 458.60258 | K23: =Members!K47 -> 504.91708 | L23: =Members!L47 -> 542.97144
A24: S&M % Revenue | B24: % | D24: =D23/D8 -> 0.3 | E24: =E23/E8 -> 0.19978418 | F24: =F23/F8 -> 0.22472212 | G24: =G23/G8 -> 0.21253337 | H24: =H23/H8 -> 0.20511966 | I24: =I23/I8 -> 0.19634988 | J24: =J23/J8 -> 0.18684474 | K24: =K23/K8 -> 0.17668378 | L24: =L23/L8 -> 0.16592708 | M24: ← From Members tab S&M build (= prior-yr revenue × GA1/GA2 endpoint)
A25: General & Administrative | B25: $M | D25: =D8*Assumptions!$F$45 -> 86.925 | E25: =E8*(Assumptions!$F$45 + (Assumptions!$F$46-Assumptions!$F$45)*(E$5-2026)/7) -> 130.52836 | F25: =F8*(Assumptions!$F$45 + (Assumptions!$F$46-Assumptions!$F$45)*(F$5-2026)/7) -> 158.83498 | G25: =G8*(Assumptions!$F$45 + (Assumptions!$F$46-Assumptions!$F$45)*(G$5-2026)/7) -> 192.76545 | H25: =H8*(Assumptions!$F$45 + (Assumptions!$F$46-Assumptions!$F$45)*(H$5-2026)/7) -> 227.82866 | I25: =I8*(Assumptions!$F$45 + (Assumptions!$F$46-Assumptions!$F$45)*(I$5-2026)/7) -> 263.32664 | J25: =J8*(Assumptions!$F$45 + (Assumptions!$F$46-Assumptions!$F$45)*(J$5-2026)/7) -> 298.04133 | K25: =K8*(Assumptions!$F$45 + (Assumptions!$F$46-Assumptions!$F$45)*(K$5-2026)/7) -> 330.68185 | L25: =L8*(Assumptions!$F$45 + (Assumptions!$F$46-Assumptions!$F$45)*(L$5-2026)/7) -> 359.95847
A26: G&A % Revenue | B26: % | D26: =D25/D8 -> 0.15 | E26: =E25/E8 -> 0.15 | F26: =F25/F8 -> 0.14428571 | G26: =G25/G8 -> 0.13857143 | H26: =H25/H8 -> 0.13285714 | I26: =I25/I8 -> 0.12714286 | J26: =J25/J8 -> 0.12142857 | K26: =K25/K8 -> 0.11571429 | L26: =L25/L8 -> 0.11 | M26: ← From Assumptions F45/F46 (G&A phase % linearly interpolated)
A27: Stock-Based Compensation | B27: $M | D27: =D8*Assumptions!$F$47 -> 81.13 | E27: =E8*(Assumptions!$F$47 + (Assumptions!$F$48-Assumptions!$F$47)*(E$5-2026)/7) -> 121.82646 | F27: =F8*(Assumptions!$F$47 + (Assumptions!$F$48-Assumptions!$F$47)*(F$5-2026)/7) -> 144.68137 | G27: =G8*(Assumptions!$F$47 + (Assumptions!$F$48-Assumptions!$F$47)*(G$5-2026)/7) -> 170.90545 | H27: =H8*(Assumptions!$F$47 + (Assumptions!$F$48-Assumptions!$F$47)*(H$5-2026)/7) -> 195.98164 | I27: =I8*(Assumptions!$F$47 + (Assumptions!$F$48-Assumptions!$F$47)*(I$5-2026)/7) -> 218.94575 | J27: =J8*(Assumptions!$F$47 + (Assumptions!$F$48-Assumptions!$F$47)*(J$5-2026)/7) -> 238.43306 | K27: =K8*(Assumptions!$F$47 + (Assumptions!$F$48-Assumptions!$F$47)*(K$5-2026)/7) -> 253.11451 | L27: =L8*(Assumptions!$F$47 + (Assumptions!$F$48-Assumptions!$F$47)*(L$5-2026)/7) -> 261.78798
A28: SBC % Revenue | B28: % | D28: =D27/D8 -> 0.14 | E28: =E27/E8 -> 0.14 | F28: =F27/F8 -> 0.13142857 | G28: =G27/G8 -> 0.12285714 | H28: =H27/H8 -> 0.11428571 | I28: =I27/I8 -> 0.10571429 | J28: =J27/J8 -> 0.097142857 | K28: =K27/K8 -> 0.088571429 | L28: =L27/L8 -> 0.08 | M28: ← From Assumptions F47/F48 (SBC phase % linearly interpolated)
A29: Total OpEx | B29: $M | D29: =D21+D23+D25+D27 -> 469.395 | E29: =E21+E23+E25+E27 -> 617.64641 | F29: =F21+F23+F25+F27 -> 782.07432 | G29: =G21+G23+G25+G27 -> 937.5423 | H29: =H21+H23+H25+H27 -> 1101.377 | I29: =I21+I23+I25+I27 -> 1261.7338 | J29: =J21+J23+J25+J27 -> 1412.3348 | K29: =K21+K23+K25+K27 -> 1545.9525 | L29: =L21+L23+L25+L27 -> 1655.5704
A31: Profitability
A32: EBITDA | B32: $M | D32: =D15-D29+D27 -> -40.565 | E32: =E15-E29+E27 -> 156.82183 | F32: =F15-F29+F27 -> 196.09753 | G32: =G15-G29+G27 -> 296.55403 | H32: =H15-H29+H27 -> 417.48067 | I32: =I15-I29+I27 -> 569.71779 | J32: =J15-J29+J27 -> 754.60095 | K32: =K15-K29+K27 -> 972.94503 | L32: =L15-L29+L27 -> 1224.0974
A33: EBITDA Margin | B33: % | D33: =D32/D8 -> -0.07 | E33: =E32/E8 -> 0.18021582 | F33: =F32/F8 -> 0.17813502 | G33: =G32/G8 -> 0.21318092 | H33: =H32/H8 -> 0.24345177 | I33: =I32/I8 -> 0.27507869 | J33: =J32/J8 -> 0.30744097 | K33: =K32/K8 -> 0.34045908 | L33: =L32/L8 -> 0.37407292
A34: EBIT / Operating Income | B34: $M | D34: =D15-D29 -> -121.695 | E34: =E15-E29 -> 34.995368 | F34: =F15-F29 -> 51.416164 | G34: =G15-G29 -> 125.64858 | H34: =H15-H29 -> 221.49903 | I34: =I15-I29 -> 350.77204 | J34: =J15-J29 -> 516.16789 | K34: =K15-K29 -> 719.83053 | L34: =L15-L29 -> 962.30944
A35: Operating Margin | B35: % | D35: =D34/D8 -> -0.21 | E35: =E34/E8 -> 0.040215823 | F35: =F34/F8 -> 0.046706449 | G35: =G34/G8 -> 0.090323776 | H35: =H34/H8 -> 0.12916605 | I35: =I34/I8 -> 0.1693644 | J35: =J34/J8 -> 0.21029811 | K35: =K34/K8 -> 0.25188765 | L35: =L34/L8 -> 0.29407292
A36: Rule of 40 Score | B36: # | D36: =(D9+D33)*100 -> -7 | E36: =(E9+E33)*100 -> 68.183624 | F36: =(F9+F33)*100 -> 44.318944 | G36: =(G9+G33)*100 -> 47.684804 | H36: =(H9+H33)*100 -> 47.618169 | I36: =(I9+I33)*100 -> 48.283523 | J36: =(J9+J33)*100 -> 49.25349 | K36: =(K9+K33)*100 -> 50.47668 | L36: =(L9+L33)*100 -> 51.915424 | M36: = Revenue Growth % + EBITDA Margin %
A38: Below the Line
A39: Interest Income / (Expense) | B39: $M | D39: ='WC & Cash'!$D$12*Assumptions!$F$67 -> 2.625 | E39: =('WC & Cash'!D33 + 'WC & Cash'!E13*0.5)*Assumptions!$F$67 -> 21.316263 | F39: ='WC & Cash'!E33*Assumptions!$F$67 -> 35.28779 | G39: ='WC & Cash'!F33*Assumptions!$F$67 -> 41.373373 | H39: ='WC & Cash'!G33*Assumptions!$F$67 -> 49.373971 | I39: ='WC & Cash'!H33*Assumptions!$F$67 -> 60.394012 | J39: ='WC & Cash'!I33*Assumptions!$F$67 -> 75.265325 | K39: ='WC & Cash'!J33*Assumptions!$F$67 -> 94.816087 | L39: ='WC & Cash'!K33*Assumptions!$F$67 -> 119.90376
A40: Pre-Tax Income | B40: $M | D40: =D34+D39 -> -119.07 | E40: =E34+E39 -> 56.311632 | F40: =F34+F39 -> 86.703953 | G40: =G34+G39 -> 167.02195 | H40: =H34+H39 -> 270.873 | I40: =I34+I39 -> 411.16605 | J40: =J34+J39 -> 591.43321 | K40: =K34+K39 -> 814.64662 | L40: =L34+L39 -> 1082.2132
A41: Taxes | B41: $M | D41: =MAX(0, D40-D48)*Assumptions!$F$52 -> 0 | E41: =MAX(0, E40-E48)*Assumptions!$F$52 -> 2.590335 | F41: =MAX(0, F40-F48)*Assumptions!$F$52 -> 3.9883819 | G41: =MAX(0, G40-G48)*Assumptions!$F$52 -> 37.343817 | H41: =MAX(0, H40-H48)*Assumptions!$F$52 -> 62.30079 | I41: =MAX(0, I40-I48)*Assumptions!$F$52 -> 94.568192 | J41: =MAX(0, J40-J48)*Assumptions!$F$52 -> 136.02964 | K41: =MAX(0, K40-K48)*Assumptions!$F$52 -> 187.36872 | L41: =MAX(0, L40-L48)*Assumptions!$F$52 -> 248.90904
A42: Net Income | B42: $M | D42: =D40-D41 -> -119.07 | E42: =E40-E41 -> 53.721296 | F42: =F40-F41 -> 82.715572 | G42: =G40-G41 -> 129.67814 | H42: =H40-H41 -> 208.57221 | I42: =I40-I41 -> 316.59786 | J42: =J40-J41 -> 455.40357 | K42: =K40-K41 -> 627.27789 | L42: =L40-L41 -> 833.30417
A43: Net Margin | B43: % | D43: =D42/D8 -> -0.20547023 | E43: =E42/E8 -> 0.061735203 | F43: =F42/F8 -> 0.075138836 | G43: =G42/G8 -> 0.093220464 | H43: =H42/H8 -> 0.12162784 | I43: =I42/I8 -> 0.15286397 | J43: =J42/J8 -> 0.1855414 | K43: =K42/K8 -> 0.21950105 | L43: =L42/L8 -> 0.25465009
A45: NOL Carryforward Schedule (post-TCJA, 80% utilization cap)
A46: Beginning NOL Balance | B46: $M | C46: 0 | D46: =C49 -> 0 | E46: =D49 -> 119.07 | F46: =E49 -> 74.020695 | G46: =F49 -> 4.657532 | H46: =G49 -> 0 | I46: =H49 -> 0 | J46: =I49 -> 0 | K46: =J49 -> 0 | L46: =K49 -> 0
A47: + Current Year Loss Added (if pretax < 0) | B47: $M | C47: 0 | D47: =MAX(0,-D40) -> 119.07 | E47: =MAX(0,-E40) -> 0 | F47: =MAX(0,-F40) -> 0 | G47: =MAX(0,-G40) -> 0 | H47: =MAX(0,-H40) -> 0 | I47: =MAX(0,-I40) -> 0 | J47: =MAX(0,-J40) -> 0 | K47: =MAX(0,-K40) -> 0 | L47: =MAX(0,-L40) -> 0
A48: − NOL Utilized Against Current Income | B48: $M | C48: 0 | D48: =MIN(D46, MAX(0,D40)*0.8) -> 0 | E48: =MIN(E46, MAX(0,E40)*0.8) -> 45.049305 | F48: =MIN(F46, MAX(0,F40)*0.8) -> 69.363163 | G48: =MIN(G46, MAX(0,G40)*0.8) -> 4.657532 | H48: =MIN(H46, MAX(0,H40)*0.8) -> 0 | I48: =MIN(I46, MAX(0,I40)*0.8) -> 0 | J48: =MIN(J46, MAX(0,J40)*0.8) -> 0 | K48: =MIN(K46, MAX(0,K40)*0.8) -> 0 | L48: =MIN(L46, MAX(0,L40)*0.8) -> 0
A49: Ending NOL Balance | B49: $M | C49: =C46+C47-C48 -> 0 | D49: =D46+D47-D48 -> 119.07 | E49: =E46+E47-E48 -> 74.020695 | F49: =F46+F47-F48 -> 4.657532 | G49: =G46+G47-G48 -> 0 | H49: =H46+H47-H48 -> 0 | I49: =I46+I47-I48 -> 0 | J49: =J46+J47-J48 -> 0 | ... L49: =L46+L47-L48 -> 0

Sheet FCF
A1: WHOOP — FCF
A2: Free cash flow build. ΔNWC sourced from WC & Cash tab (detailed deferred-rev schedule).
B5: Units | C5: 2024 | D5: 2025 | E5: 2026 | F5: 2027 | G5: 2028 | H5: 2029 | I5: 2030 | J5: 2031 | K5: 2032 | L5: 2033
C6: Historical | D6: Historical | E6: Phase 1 | F6: Phase 1 | G6: Phase 2 | H6: Phase 2 | I6: Phase 2 | J6: Phase 3 | K6: Phase 3 | L6: Phase 3
A8: 1. EBIT to NOPAT
A9: EBIT | B9: $M | D9: ='P&L'!D34 -> -121.695 | E9: ='P&L'!E34 -> 34.995368 | F9: ='P&L'!F34 -> 51.416164 | G9: ='P&L'!G34 -> 125.64858 | H9: ='P&L'!H34 -> 221.49903 | I9: ='P&L'!I34 -> 350.77204 | J9: ='P&L'!J34 -> 516.16789 | K9: ='P&L'!K34 -> 719.83053 | L9: ='P&L'!L34 -> 962.30944 | M9: = P&L EBIT (row 33)
A10: Less: Cash taxes on EBIT | B10: $M | D10: ='P&L'!D41 -> 0 | E10: ='P&L'!E41 -> 2.590335 | F10: ='P&L'!F41 -> 3.9883819 | G10: ='P&L'!G41 -> 37.343817 | H10: ='P&L'!H41 -> 62.30079 | I10: ='P&L'!I41 -> 94.568192 | J10: ='P&L'!J41 -> 136.02964 | K10: ='P&L'!K41 -> 187.36872 | L10: ='P&L'!L41 -> 248.90904 | M10: = P&L Cash Taxes (row 40), tax-affected at effective rate
A11: NOPAT | B11: $M | D11: =D9-D10 -> -121.695 | E11: =E9-E10 -> 32.405033 | F11: =F9-F10 -> 47.427782 | G11: =G9-G10 -> 88.304764 | H11: =H9-H10 -> 159.19824 | I11: =I9-I10 -> 256.20385 | J11: =J9-J10 -> 380.13825 | K11: =K9-K10 -> 532.46181 | L11: =L9-L10 -> 713.40041 | M11: = EBIT − Cash Taxes
A13: 2. NOPAT to Unlevered FCF
A14: Plus: D&A | B14: $M | D14: ='P&L'!D8*Assumptions!$F$53 -> 20.2825 | E14: ='P&L'!E8*Assumptions!$F$53 -> 30.456616 | F14: ='P&L'!F8*Assumptions!$F$53 -> 38.529277 | G14: ='P&L'!G8*Assumptions!$F$53 -> 48.688181 | H14: ='P&L'!H8*Assumptions!$F$53 -> 60.019377 | I14: ='P&L'!I8*Assumptions!$F$53 -> 72.488795 | J14: ='P&L'!J8*Assumptions!$F$53 -> 85.906031 | K14: ='P&L'!K8*Assumptions!$F$53 -> 100.02105 | L14: ='P&L'!L8*Assumptions!$F$53 -> 114.53224 | M14: = Revenue × D&A % (Assumptions F52)
A15: Less: CapEx | B15: $M | D15: =-'P&L'!D8*Assumptions!$F$49 -> -23.18 | E15: =-'P&L'!E8*Assumptions!$F$49 -> -34.807561 | F15: =-'P&L'!F8*Assumptions!$F$49 -> -44.033459 | G15: =-'P&L'!G8*Assumptions!$F$49 -> -55.643635 | H15: =-'P&L'!H8*Assumptions!$F$49 -> -68.593574 | I15: =-'P&L'!I8*Assumptions!$F$49 -> -82.844337 | J15: =-'P&L'!J8*Assumptions!$F$49 -> -98.178321 | K15: =-'P&L'!K8*Assumptions!$F$49 -> -114.30978 | L15: =-'P&L'!L8*Assumptions!$F$49 -> -130.89399 | M15: = −(Revenue × CapEx %) (Assumptions F48)
A16: Less: Change in NWC | B16: $M | D16: ='WC & Cash'!D26 -> 371.1286 | E16: ='WC & Cash'!E26 -> 83.632384 | F16: ='WC & Cash'!F26 -> 131.95021 | G16: ='WC & Cash'!G26 -> 147.23921 | H16: ='WC & Cash'!H26 -> 164.23426 | I16: ='WC & Cash'!I26 -> 179.04635 | J16: ='WC & Cash'!J26 -> 190.72724 | K16: ='WC & Cash'!K26 -> 198.61768 | L16: ='WC & Cash'!L26 -> 200.55688 | M16: = From WC & Cash tab (Section 3, Total ΔNWC)
A17: Note: SBC is REAL COST in P&L — do NOT add back | M17: Per methodology Sec 6 — SBC stays in P&L as cash-equivalent expense
A18: Unlevered Free Cash Flow | B18: $M | D18: =D11+D14+D15+D16 -> 246.5361 | E18: =E11+E14+E15+E16 -> 111.68647 | F18: =F11+F14+F15+F16 -> 173.87381 | G18: =G11+G14+G15+G16 -> 228.58852 | H18: =H11+H14+H15+H16 -> 314.8583 | I18: =I11+I14+I15+I16 -> 424.89465 | J18: =J11+J14+J15+J16 -> 558.5932 | K18: =K11+K14+K15+K16 -> 716.79076 | L18: =L11+L14+L15+L16 -> 897.59554 | M18: = NOPAT + D&A + CapEx + ΔNWC
A20: 3. FCF Diagnostics
A21: FCF Margin % | B21: % | D21: =IFERROR(D18/'P&L'!D8,0) -> 0.42542898 | E21: =IFERROR(E18/'P&L'!E8,0) -> 0.12834737 | F21: =IFERROR(F18/'P&L'!F8,0) -> 0.15794699 | G21: =IFERROR(G18/'P&L'!G8,0) -> 0.16432321 | H21: =IFERROR(H18/'P&L'!H8,0) -> 0.18360805 | I21: =IFERROR(I18/'P&L'!I8,0) -> 0.20515326 | J21: =IFERROR(J18/'P&L'!J8,0) -> 0.22758312 | K21: =IFERROR(K18/'P&L'!K8,0) -> 0.25082396 | L21: =IFERROR(L18/'P&L'!L8,0) -> 0.27429695 | M21: FCF / Revenue
A22: Rule of 40 (Growth + FCF Margin) | B22: % | E22: =IFERROR(('P&L'!E8/'P&L'!D8-1)*100 + E21*100,0) -> 62.996779 | F22: =IFERROR(('P&L'!F8/'P&L'!E8-1)*100 + F21*100,0) -> 42.300141 | G22: =IFERROR(('P&L'!G8/'P&L'!F8-1)*100 + G21*100,0) -> 42.799034 | H22: =IFERROR(('P&L'!H8/'P&L'!G8-1)*100 + H21*100,0) -> 41.633797 | I22: =IFERROR(('P&L'!I8/'P&L'!H8-1)*100 + I21*100,0) -> 41.29098 | J22: =IFERROR(('P&L'!J8/'P&L'!I8-1)*100 + J21*100,0) -> 41.267704 | K22: =IFERROR(('P&L'!K8/'P&L'!J8-1)*100 + K21*100,0) -> 41.513168 | L22: =IFERROR(('P&L'!L8/'P&L'!K8-1)*100 + L21*100,0) -> 41.937826 | M22: Revenue Growth % + FCF Margin %

Sheet WC & Cash
A1: WHOOP — Working Capital & Cash Roll-Forward
A2: $M; pre-IPO (no debt service / dividends / buybacks). Replaces FCF-tab ΔNWC plug with explicit WC build.
A3: Detailed WC schedule wired into FCF tab as of this session. DCF EV impact: +$813M.
B5: Units | C5: 2024 | D5: 2025 | E5: 2026 | F5: 2027 | G5: 2028 | H5: 2029 | I5: 2030 | J5: 2031 | K5: 2032 | L5: 2033
A7: 1. Drivers
A8: Avg months remaining on annual sub (deferred rev) | B8: mo | D8: 6
A9: Inventory days (gross adds device cost) | B9: days | D9: 45
A10: Accounts payable days (% of total COGS) | B10: days | D10: 18
A11: Other NWC (% of revenue) | B11: % | D11: 0.015
A12: Pre-existing cash balance (start 2025) | B12: $M | D12: 75
A13: Series G proceeds (closed Mar 2026) | B13: $M | D13: 0 | E13: 575
A15: 2. Working Capital Balances (Liabilities = Source / Assets = Use)
A16: Deferred Revenue (= End Members × ARPU × mo/12) | B16: $M | C16: 0 | D16: =Members!D34*ARPU!D10*$D$8/12 -> 381.25 | E16: =Members!E34*ARPU!E10*$D$8/12 -> 473.68903 | F16: =Members!F34*ARPU!F10*$D$8/12 -> 608.19989 | G16: =Members!G34*ARPU!G10*$D$8/12 -> 758.56299 | H16: =Members!H34*ARPU!H10*$D$8/12 -> 925.93383 | I16: =Members!I34*ARPU!I10*$D$8/12 -> 1108.1372 | J16: =Members!J34*ARPU!J10*$D$8/12 -> 1301.9953 | K16: =Members!K34*ARPU!K10*$D$8/12 -> 1503.6693 | L16: =Members!L34*ARPU!L10*$D$8/12 -> 1708.5337
A17: Inventory (= ~45 days of NEXT-yr hardware COGS) | B17: $M | C17: 0 | D17: ='P&L'!E13*$D$9/365 -> 12.860137 | E17: ='P&L'!F13*$D$9/365 -> 16.603577 | F17: ='P&L'!G13*$D$9/365 -> 18.160341 | G17: ='P&L'!H13*$D$9/365 -> 19.916635 | H17: ='P&L'!I13*$D$9/365 -> 21.356275 | I17: ='P&L'!J13*$D$9/365 -> 22.45562 | J17: ='P&L'!K13*$D$9/365 -> 23.157681 | K17: ='P&L'!L13*$D$9/365 -> 23.419831 | L17: =K17*1.05 -> 24.590823
A18: Accounts Payable (= ~18 days of total COGS) | B18: $M | C18: 0 | D18: ='P&L'!D14*$D$10/365 -> 11.431233 | E18: ='P&L'!E14*$D$10/365 -> 10.728358 | F18: ='P&L'!F14*$D$10/365 -> 13.184186 | G18: ='P&L'!G14*$D$10/365 -> 16.170411 | H18: ='P&L'!H14*$D$10/365 -> 19.329696 | I18: ='P&L'!I14*$D$10/365 -> 22.616018 | J18: ='P&L'!J14*$D$10/365 -> 25.937521 | K18: ='P&L'!K14*$D$10/365 -> 29.192614 | L18: ='P&L'!L14*$D$10/365 -> 32.27523
A19: Other NWC (= 1.5% of revenue) | B19: $M | C19: 0 | D19: ='P&L'!D8*$D$11 -> 8.6925 | E19: ='P&L'!E8*$D$11 -> 13.052836 | F19: ='P&L'!F8*$D$11 -> 16.512547 | G19: ='P&L'!G8*$D$11 -> 20.866363 | H19: ='P&L'!H8*$D$11 -> 25.72259 | I19: ='P&L'!I8*$D$11 -> 31.066626 | J19: ='P&L'!J8*$D$11 -> 36.81687 | K19: ='P&L'!K8*$D$11 -> 42.866166 | L19: ='P&L'!L8*$D$11 -> 49.085246
A21: 3. Change in WC (positive = cash source)
A22: Δ Deferred Revenue (liability ↑ = source) | B22: $M | D22: =D16-C16 -> 381.25 | E22: =E16-D16 -> 92.439034 | F22: =F16-E16 -> 134.51086 | G22: =G16-F16 -> 150.3631 | H22: =H16-G16 -> 167.37084 | I22: =I16-H16 -> 182.20341 | J22: =J16-I16 -> 193.85804 | K22: =K16-J16 -> 201.67403 | L22: =L16-K16 -> 204.86434
A23: Δ Inventory (asset ↑ = use) | B23: $M | D23: =-(D17-C17) -> -12.860137 | E23: =-(E17-D17) -> -3.7434397 | F23: =-(F17-E17) -> -1.5567639 | G23: =-(G17-F17) -> -1.7562941 | H23: =-(H17-G17) -> -1.4396406 | I23: =-(I17-H17) -> -1.099345 | J23: =-(J17-I17) -> -0.70206013 | K23: =-(K17-J17) -> -0.26215072 | L23: =-(L17-K17) -> -1.1709916
A24: Δ Accounts Payable (liability ↑ = source) | B24: $M | D24: =D18-C18 -> 11.431233 | E24: =E18-D18 -> -0.70287492 | F24: =F18-E18 -> 2.4558285 | G24: =G18-F18 -> 2.9862241 | H24: =H18-G18 -> 3.1592853 | I24: =I18-H18 -> 3.2863218 | J24: =J18-I18 -> 3.3215035 | K24: =K18-J18 -> 3.2550931 | L24: =L18-K18 -> 3.0826162
A25: Δ Other NWC (asset ↑ = use) | B25: $M | D25: =-(D19-C19) -> -8.6925 | E25: =-(E19-D19) -> -4.3603355 | F25: =-(F19-E19) -> -3.4597118 | G25: =-(G19-F19) -> -4.3538159 | H25: =-(H19-G19) -> -4.856227 | I25: =-(I19-H19) -> -5.3440363 | J25: =-(J19-I19) -> -5.7502438 | K25: =-(K19-J19) -> -6.049296 | L25: =-(L19-K19) -> -6.21908
A26: Total Δ NWC (cash impact) | B26: $M | D26: =SUM(D22:D25) -> 371.1286 | E26: =SUM(E22:E25) -> 83.632384 | F26: =SUM(F22:F25) -> 131.95021 | G26: =SUM(G22:G25) -> 147.23921 | H26: =SUM(H22:H25) -> 164.23426 | I26: =SUM(I22:I25) -> 179.04635 | J26: =SUM(J22:J25) -> 190.72724 | K26: =SUM(K22:K25) -> 198.61768 | L26: =SUM(L22:L25) -> 200.55688
A28: 4. Cash Roll-Forward (pre-IPO; no debt service / dividends / buybacks)
A29: Beginning Cash | B29: $M | D29: =$D$12 -> 75 | E29: =D33 -> 321.5361 | F29: =E33 -> 1008.2226 | G29: =F33 -> 1182.0964 | H29: =G33 -> 1410.6849 | I29: =H33 -> 1725.5432 | J29: =I33 -> 2150.4379 | K29: =J33 -> 2709.0311 | L29: =K33 -> 3425.8218
A30: + Series G proceeds | B30: $M | D30: =$D$13 -> 0 | E30: =$E$13 -> 575 | F30: 0 | G30: 0 | H30: 0 | I30: 0 | J30: 0 | K30: 0 | L30: 0
A31: + Unlevered Free Cash Flow (FCF tab) | B31: $M | D31: =FCF!D18 -> 246.5361 | E31: =FCF!E18 -> 111.68647 | F31: =FCF!F18 -> 173.87381 | G31: =FCF!G18 -> 228.58852 | H31: =FCF!H18 -> 314.8583 | I31: =FCF!I18 -> 424.89465 | J31: =FCF!J18 -> 558.5932 | K31: =FCF!K18 -> 716.79076 | L31: =FCF!L18 -> 897.59554
A33: Ending Cash | B33: $M | D33: =D29+D30+D31 -> 321.5361 | E33: =E29+E30+E31 -> 1008.2226 | F33: =F29+F30+F31 -> 1182.0964 | G33: =G29+G30+G31 -> 1410.6849 | H33: =H29+H30+H31 -> 1725.5432 | I33: =I29+I30+I31 -> 2150.4379 | J33: =J29+J30+J31 -> 2709.0311 | K33: =K29+K30+K31 -> 3425.8218 | L33: =L29+L30+L31 -> 4323.4174

Sheet DCF
A1: WHOOP — Discounted Cash Flow
A2: $M; Calendar Year; Base case below — see Sensitivity tab for ranges
A3: ✓ Integrity flags clear: TV divergence 2.9% (<25% threshold), TV % EV 72% (<75% threshold). Both passed after exit-multiple tightening to 3.5x and WC schedule wiring.
B5: Units | C5: 2025 | D5: 2026 | E5: 2027 | F5: 2028 | G5: 2029 | H5: 2030 | I5: 2031 | J5: 2032 | K5: 2033
A7: 1. Cash Flow & Discounting
A8: Revenue (memo) | B8: $M | C8: ='P&L'!D8 -> 579.5 | D8: ='P&L'!E8 -> 870.18903 | E8: ='P&L'!F8 -> 1100.8365 | F8: ='P&L'!G8 -> 1391.0909 | G8: ='P&L'!H8 -> 1714.8393 | H8: ='P&L'!I8 -> 2071.1084 | I8: ='P&L'!J8 -> 2454.458 | J8: ='P&L'!K8 -> 2857.7444 | K8: ='P&L'!L8 -> 3272.3497 | M8: ← From P&L tab
A9: Unlevered Free Cash Flow | B9: $M | C9: =FCF!D18 -> 246.5361 | D9: =FCF!E18 -> 111.68647 | E9: =FCF!F18 -> 173.87381 | F9: =FCF!G18 -> 228.58852 | G9: =FCF!H18 -> 314.8583 | H9: =FCF!I18 -> 424.89465 | I9: =FCF!J18 -> 558.5932 | J9: =FCF!K18 -> 716.79076 | K9: =FCF!L18 -> 897.59554 | M9: ← From FCF tab (single source of truth)
A10: FCF Margin % | B10: % | C10: =IFERROR(C9/C8,0) -> 0.42542898 | D10: =IFERROR(D9/D8,0) -> 0.12834737 | E10: =IFERROR(E9/E8,0) -> 0.15794699 | F10: =IFERROR(F9/F8,0) -> 0.16432321 | G10: =IFERROR(G9/G8,0) -> 0.18360805 | H10: =IFERROR(H9/H8,0) -> 0.20515326 | I10: =IFERROR(I9/I8,0) -> 0.22758312 | J10: =IFERROR(J9/J8,0) -> 0.25082396 | K10: =IFERROR(K9/K8,0) -> 0.27429695
A12: WACC | B12: % | C12: n/a | D12: =Assumptions!$F$74 -> 0.10845 | E12: =Assumptions!$F$74 -> 0.10845 | F12: =Assumptions!$F$74 -> 0.10845 | G12: =Assumptions!$F$74 -> 0.10845 | H12: =Assumptions!$F$74 -> 0.10845 | I12: =Assumptions!$F$74 -> 0.10845 | J12: =Assumptions!$F$74 -> 0.10845 | K12: =Assumptions!$F$74 -> 0.10845 | M12: ← From Assumptions F74
A13: Discount Period (mid-year) | B13: yrs | C13: n/a | D13: 0.5 | E13: 1.5 | F13: 2.5 | G13: 3.5 | H13: 4.5 | I13: 5.5 | J13: 6.5 | K13: 7.5 | M13: Mid-year convention
A14: Discount Factor | B14: x | C14: n/a | D14: =1/(1+D12)^D13 -> 0.94982139 | E14: =1/(1+E12)^E13 -> 0.85689151 | F14: =1/(1+F12)^F13 -> 0.77305382 | G14: =1/(1+G12)^G13 -> 0.69741876 | H14: =1/(1+H12)^H13 -> 0.62918378 | I14: =1/(1+I12)^I13 -> 0.56762486 | J14: =1/(1+J12)^J13 -> 0.51208883 | K14: =1/(1+K12)^K13 -> 0.4619864
A15: PV of Unlevered FCF | B15: $M | C15: n/a | D15: =D9*D14 -> 106.0822 | E15: =E9*E14 -> 148.99099 | F15: =F9*F14 -> 176.71123 | G15: =G9*G14 -> 219.58809 | H15: =H9*H14 -> 267.33682 | I15: =I9*I14 -> 317.07139 | J15: =J9*J14 -> 367.06054 | K15: =K9*K14 -> 414.67693 | M15: = UFCF / (1+WACC)^period
A17: 2. Terminal Value
A18: Terminal Year Revenue | B18: $M | C18: =K8 -> 3272.3497
A19: Terminal Year EBITDA | B19: $M | C19: ='P&L'!L32 -> 1224.0974
A20: Terminal Year FCF | B20: $M | C20: =K9 -> 897.59554
A21: Exit Multiple (EV/Revenue) | B21: x | C21: =Assumptions!$F$78 -> 3.5 | L21: ← From Assumptions F78
A22: Terminal Value (Exit Multiple) | B22: $M | C22: =C18*C21 -> 11453.224
A23: Terminal Value (Gordon Growth) | B23: $M | C23: =C20*(1+Assumptions!$F$80)/(D12-Assumptions!$F$80) -> 11784.875 | L23: Gordon: =FCF × (1+g) / (WACC − g)
A24: TV Method Divergence | B24: % | C24: =ABS(C22-C23)/((C22+C23)/2) -> 0.028543677 | L24: If >25%, an assumption is inconsistent
A25: Selected Terminal Value | B25: $M | C25: =C22 -> 11453.224
A26: PV of Terminal Value | B26: $M | C26: =C25*K14 -> 5291.2338
A27: TV as % of Total EV | B27: % | C27: =C26/(C26+SUM(D15:K15)) -> 0.72395859 | L27: If >75%, explicit forecast doing too little
A29: 3. Enterprise Value Summary
A30: Sum of PV of FCFs (2026-2033) | B30: $M | C30: =SUM(D15:K15) -> 2017.5182
A31: PV of Terminal Value | B31: $M | C31: =C26 -> 5291.2338
A32: Enterprise Value (DCF Base) | B32: $M | C32: =C30+C31 -> 7308.752
A34: 4. Equity Bridge
A35: Enterprise Value | B35: $M | C35: =C32 -> 7308.752
A36: Less: Debt | B36: $M | C36: =-Assumptions!$F$62 -> -10 | L36: ~$0 (minimal)
A37: Plus: Cash | B37: $M | C37: ='WC & Cash'!E33 -> 1008.2226 | L37: $600-800M est. post-Series G
A38: Equity Value | B38: $M | C38: =C35+C36+C37 -> 8306.9745
A39: Fully Diluted Shares (M) | B39: M | C39: =Assumptions!$F$55 -> 410 | L39: ~900M (PremierAlts est.)
A40: Equity Value per Share | B40: $/sh | C40: =C38/C39 -> 20.260914
A42: 5. Real Options (Additive — healthcare pathway only)
A43: Healthcare option — Bear scenario range ($M) | B43: $M | C43: =RealOptions!B31 -> 179.17885 | L43: ← Probability × Payoff from Assumptions
A44: Healthcare option — Bull scenario range ($M) | B44: $M | C44: =RealOptions!D31 -> 1281.1334
A45: Healthcare option — active scenario ($M) | B45: $M | C45: =RealOptions!B36 -> 704.48043
A46: Expected Option Value | B46: $M | C46: =C45 -> 704.48043
A47: Total EV (DCF + Options) | B47: $M | C47: =C32+C46 -> 8013.2324
A49: 6. Scenario Comparison vs Series G — Equity Value Basis
A50: DCF Base Case Equity Value | B50: $M | C50: =C38 -> 8306.9745
A51: DCF + Options Equity Value | B51: $M | C51: =C38+C46 -> 9011.455
A52: Series G Mark | B52: $M | C52: 10100
A53: DCF Premium / (Discount) to Series G | B53: % | C53: =C50/C52-1 -> -0.17752727 | M53: Base case = 'WHOOP executes plan'
A54: DCF + Options Premium / (Discount) to Series G | B54: % | C54: =C51/C52-1 -> -0.10777673 | M54: Options = 'Healthcare reimbursement pathway materializes (probability-weighted, 15-25%)'

Sheet WACC Bottom-Up
A1: WHOOP — Bottom-Up WACC Build (Justification)
A2: Cross-check on Damodaran sector approach used in Assumptions!F74. Methodology: 3Y weekly Bloomberg-adjusted betas + Oura tender-anchored liquidity premium. Pure justification — does NOT feed DCF.
A3: Source: research/wacc-bottom-up-build.md (May 5, 2026). Replaces 5Y monthly + Hiive premium methodology.
A5: Executive Summary
A6: • Bottom-up bucket-median unlevered betas (Bloomberg-adj, 3Y weekly): B1 = 1.01, B2 = 1.00 (ex-PTON), B3 = 0.92. Tight clustering.
A7: • WHOOP blended βᵤ = 0.95–0.99 across Bear/Base/Bull; Damodaran sector blended = 0.81–0.85. Delta narrowed from +0.40 (5Y monthly) to +0.10–0.18.
A8: • Revenue-weighted ERP = 4.61% Base (vs. pure US 4.46%); +11bps from ~42% intl mix.
A9: • Liquidity premium = +2.0pp anchored to Oura Jan 2026 tender at 25% discount to Series E (Oct 2025); replaces prior +5pp Hiive figure.
A10: • Bottom-up WACC ~11.6% Base vs. Damodaran sector ~10.4% Base — two methods converge within ~1pp. Triangulation finding.
A13: §1. Per-Comp Inputs & Hamada Unlevered Betas
A14: 3Y weekly OLS regression vs. ^GSPC, 157 obs (May 2023 – May 2026). Bloomberg adj: β_adj = (2/3)×β_raw + (1/3)×1.0. Hamada: βᵤ = βL / [1 + (1−t)×(D/E)].
A16: Comp | B16: Bucket | C16: β_raw | D16: β_adj | E16: R² | F16: Mkt Cap ($M) | G16: Debt ($M) | H16: Cash ($M) | I16: D/E | J16: ETR (3Y agg) | K16: Marg Tax | L16: Tax Used | M16: βᵤ (adj) | N16: βᵤ (raw chk)
A17: Garmin (GRMN) | B17: B1 Hardware | C17: 1.029 | D17: 1.019 | E17: 0.216 | F17: 45250 | G17: 216 | H17: 2700 | I17: =G17/F17 -> 0.0047734807 | J17: 0.111 | K17: 0.21 | L17: =J17 -> 0.111 | M17: =D17/(1+(1-L17)*I17) -> 1.014694 | N17: =C17/(1+(1-L17)*I17) -> 1.0246518
A18: Peloton (PTON) | B18: B2 Sub (distressed) | C18: 2.283 | D18: 1.855 | E18: 0.185 | F18: 2200 | G18: 1950 | H18: 1180 | I18: =G18/F18 -> 0.88636364 | J18: n/m | K18: 0.25 | L18: =K18 -> 0.25 | M18: =D18/(1+(1-L18)*I18) -> 1.1142662 | N18: =C18/(1+(1-L18)*I18) -> 1.3713584
A19: Spotify (SPOT) | B19: B2 Sub (mature) | C19: 1.014 | D19: 1.01 | E19: 0.134 | F19: 86260 | G19: 549 | H19: 7260 | I19: =G19/F19 -> 0.0063644795 | J19: 0.079 | K19: 0.25 | L19: =J19 -> 0.079 | M19: =D19/(1+(1-L19)*I19) -> 1.0041142 | N19: =C19/(1+(1-L19)*I19) -> 1.0080909
A20: Dexcom (DXCM) | B20: B3 Health Data | C20: 1.08 | D20: 1.054 | E20: 0.119 | F20: 22950 | G20: 1380 | H20: 2420 | I20: =G20/F20 -> 0.060130719 | J20: 0.221 | K20: 0.25 | L20: =J20 -> 0.221 | M20: =D20/(1+(1-L20)*I20) -> 1.0068379 | N20: =C20/(1+(1-L20)*I20) -> 1.0316745
A21: ResMed (RMD) | B21: B3 Health Data | C21: 0.962 | D21: 0.974 | E21: 0.181 | F21: 30150 | G21: 843 | H21: 1660 | I21: =G21/F21 -> 0.027960199 | J21: 0.179 | K21: 0.27 | L21: =J21 -> 0.179 | M21: =D21/(1+(1-L21)*I21) -> 0.95214324 | N21: =C21/(1+(1-L21)*I21) -> 0.94041253
A22: Masimo (MASI) | B22: B3 Health Data | C22: 0.885 | D22: 0.924 | E22: 0.09 | F22: 9310 | G22: 559 | H22: 152 | I22: =G22/F22 -> 0.060042965 | J22: n/m | K22: 0.25 | L22: =K22 -> 0.25 | M22: =D22/(1+(1-L22)*I22) -> 0.88418326 | N22: =C22/(1+(1-L22)*I22) -> 0.84686384
A23: iRhythm (IRTC) | B23: B3 Health Data | C23: 0.816 | D23: 0.877 | E23: 0.057 | F23: 4090 | G23: 729 | H23: 550 | I23: =G23/F23 -> 0.17823961 | J23: n/m | K23: 0.25 | L23: =K23 -> 0.25 | M23: =D23/(1+(1-L23)*I23) -> 0.7735871 | N23: =C23/(1+(1-L23)*I23) -> 0.71978002
A24: R² caveat: range 5.7% (IRTC) to 21.6% (GRMN) — standard error on each β ~±0.20–0.30. Bucket medians of 4 names (B3) more robust than singletons.
A27: §2. Bucket Median Unlevered Betas
A29: Bucket | B29: Comps | C29: Median βᵤ (incl PTON) | D29: Median βᵤ (ex-PTON) | E29: Min | F29: Max | G29: Range
A30: B1 Hardware | B30: GRMN | C30: =MEDIAN(M17) -> 1.014694 | D30: =MEDIAN(M17) -> 1.014694 | E30: =MIN(M17) -> 1.014694 | F30: =MAX(M17) -> 1.014694 | G30: =F30-E30 -> 0
A31: B2 Subscription | B31: PTON, SPOT | C31: =MEDIAN(M18:M19) -> 1.0591902 | D31: =MEDIAN(M19) -> 1.0041142 | E31: =MIN(M18:M19) -> 1.0041142 | F31: =MAX(M18:M19) -> 1.1142662 | G31: =F31-E31 -> 0.11015201
A32: B3 Health Data | B32: DXCM, RMD, MASI, IRTC | C32: =MEDIAN(M20:M23) -> 0.91816325 | D32: =MEDIAN(M20:M23) -> 0.91816325 | E32: =MIN(M20:M23) -> 0.7735871 | F32: =MAX(M20:M23) -> 1.0068379 | G32: =F32-E32 -> 0.23325077
A33: Notes:
A34: • B2 ex-PTON is primary anchor; PTON's Hamada output contaminated by distressed-equity dynamics (D/E 0.89, levered β 1.86 adj).
A35: • B3 4-comp median robust to outliers — anchored by RMD (0.95) and MASI (0.88) as middle two; DXCM (1.01) and IRTC (0.77) are bookends.
A37: §3. Damodaran Sector Cross-Check (Jan 2026)
A39: Bucket | B39: Bottom-up βᵤ (ex-PTON) | C39: Damodaran Sector | D39: Sector βᵤ | E39: # Firms | F39: Delta | G39: 5Y mo Delta (prior)
A40: B1 Hardware | B40: =D30 -> 1.014694 | C40: Electronics (Consumer & Office) | D40: 0.83 | E40: 8 | F40: =B40-D40 -> 0.18469402 | G40: 0.4
A41: B2 Subscription | B41: =D31 -> 1.0041142 | C41: Software (Entertainment) | D41: 1.01 | E41: 77 | F41: =B41-D41 -> -0.0058858017 | G41: 0.43
A42: B3 Health Data | B42: =D32 -> 0.91816325 | C42: HC Info & Tech | D42: 0.99 | E42: 115 | F42: =B42-D42 -> -0.071836747 | G42: 0.39
A43: Convergence finding: under 3Y weekly methodology, bucket betas converge to within ±0.10 of Damodaran sector medians. Idiosyncratic events filtered out (IRTC 2021 CMS, PTON 2021 collapse); Bloomberg adjustment shrinks toward 1.0.
A46: §4. WHOOP Re-Levered Beta (zero debt → β_L = βᵤ)
A47: Bucket weights pulled live from Assumptions!C84:E86 (Bear/Base/Bull). Damodaran sector blended sourced from Assumptions!C71:E71.
A49: Scenario | B49: B1 Wt | C49: B2 Wt | D49: B3 Wt | E49: B1 βᵤ | F49: B2 βᵤ (ex-PTON) | G49: B3 βᵤ | H49: Blended βᵤ (BU) | I49: Damodaran βᵤ | J49: Delta | K49: Blended βᵤ (PTON-incl)
A50: Bear (40/40/20) | B50: =Assumptions!C84 -> 0.4 | C50: =Assumptions!C85 -> 0.4 | D50: =Assumptions!C86 -> 0.2 | E50: =$D$30 -> 1.014694 | F50: =$D$31 -> 1.0041142 | G50: =$D$32 -> 0.91816325 | H50: =B50*E50+C50*F50+D50*G50 -> 0.99115594 | I50: =Assumptions!C71 -> 0.85 | J50: =H50-I50 -> 0.14115594 | K50: =B50*$C$30+C50*$C$31+D50*$C$32 -> 1.0131863
A51: Base (20/40/40) | B51: =Assumptions!D84 -> 0.2 | C51: =Assumptions!D85 -> 0.4 | D51: =Assumptions!D86 -> 0.4 | E51: =$D$30 -> 1.014694 | F51: =$D$31 -> 1.0041142 | G51: =$D$32 -> 0.91816325 | H51: =B51*E51+C51*F51+D51*G51 -> 0.97184978 | I51: =Assumptions!D71 -> 0.83 | J51: =H51-I51 -> 0.14184978 | K51: =B51*$C$30+C51*$C$31+D51*$C$32 -> 0.99388019
A52: Bull (10/30/60) | B52: =Assumptions!E84 -> 0.1 | C52: =Assumptions!E85 -> 0.3 | D52: =Assumptions!E86 -> 0.6 | E52: =$D$30 -> 1.014694 | F52: =$D$31 -> 1.0041142 | G52: =$D$32 -> 0.91816325 | H52: =B52*E52+C52*F52+D52*G52 -> 0.95360161 | I52: =Assumptions!E71 -> 0.81 | J52: =H52-I52 -> 0.14360161 | K52: =B52*$C$30+C52*$C$31+D52*$C$32 -> 0.97012442
A53: Bloomberg adjustment effect on WHOOP-blended is trivial (<0.02) since blend is already centered near 1.0. Remaining +0.10 to +0.18 vs. Damodaran reflects genuine WHOOP-comp-specific premium over broad sector medians.
A54: Note: Damodaran βᵤ in Assumptions!C71:E71 is bucket-weighted (Bear 0.85/Base 0.83/Bull 0.81 — higher β = more bearish, i.e. B1-heavy hardware mix). Bottom-up bucket-weighted output uses identical weights, so deltas are consistent across all three scenarios.
A57: §5. Revenue-Weighted ERP
A58: WHOOP intl mix ~42% (per stress-test). Intl blend: 50% UK/EU developed, 30% Asia developed, 20% other/GCC.
A60: Country ERPs (Damodaran Jan 2026) | C60: ERP
A61: US | C61: 0.0446
A62: UK / EU developed avg | C62: 0.046
A63: Asia developed avg (JP/AU/SG) | C63: 0.0453
A64: Other / GCC / emerging | C64: 0.057
A66: Blended International ERP | C66: =0.5*C62+0.3*C63+0.2*C64 -> 0.04799
A68: Sensitivity: Intl revenue weight | B68: Intl Wt | C68: US Contrib | D68: Intl Contrib | E68: Blended ERP
A69: Conservative | B69: 0.35 | C69: =(1-B69)*$C$61 -> 0.02899 | D69: =B69*$C$66 -> 0.0167965 | E69: =C69+D69 -> 0.0457865
A70: Base case | B70: 0.42 | C70: =(1-B70)*$C$61 -> 0.025868 | D70: =B70*$C$66 -> 0.0201558 | E70: =C70+D70 -> 0.0460238
A71: Aggressive | B71: 0.5 | C71: =(1-B71)*$C$61 -> 0.0223 | D71: =B71*$C$66 -> 0.023995 | E71: =C71+D71 -> 0.046295
A72: Net effect: +11-19bp vs. pure US ERP. Most intl revenue is developed-market with ERPs near US base — token adjustment, not a swing factor.
A75: §6. Liquidity Premium — Oura Tender Anchor
A76: Oura Jan 2026 tender priced at 25% discount to Oct 2025 Series E (~3-month gap → minimal stale-pricing decay; close to pure DLOM for high-quality wearable comp on credible IPO path).
A78: Translation: DLOM → WACC add-on
A79: Public-comp WACC base (Damodaran sector) | C79: =Assumptions!D74-Assumptions!D73 -> 0.08845
A80: Terminal growth (g) | C80: =Assumptions!D80 -> 0.03
A81: Public (r − g) | C81: =C79-C80 -> 0.05845
A83: DLOM scenario | B83: DLOM % | C83: PV haircut | D83: (r−g) ratio | E83: New (r−g) | F83: Implied add-on
A84: Optimistic (shorter time-to-IPO) | B84: 0.15 | C84: =-B84 -> -0.15 | D84: =1/(1-B84) -> 1.1764706 | E84: =$C$81*D84 -> 0.068764706 | F84: =E84-$C$81 -> 0.010314706
A85: Base (Oura tender) | B85: 0.25 | C85: =-B85 -> -0.25 | D85: =1/(1-B85) -> 1.3333333 | E85: =$C$81*D85 -> 0.077933333 | F85: =E85-$C$81 -> 0.019483333
A86: Conservative (Oura + WHOOP-specific) | B86: 0.35 | C86: =-B86 -> -0.35 | D86: =1/(1-B86) -> 1.5384615 | E86: =$C$81*D86 -> 0.089923077 | F86: =E86-$C$81 -> 0.031473077
A88: Recommended liquidity premium | B88: Bear | C88: Base | D88: Bull
A89: Bottom-up + Oura | B89: 0.025 | C89: 0.02 | D89: 0.015
A90: Existing model (Assumptions!F73) | B90: =Assumptions!C73 -> 0.03 | C90: =Assumptions!D73 -> 0.02 | D90: =Assumptions!E73 -> 0.01
A91: Why not Hiive (-39 to -51%)? Hiive prices common (subordinated to $291M preference stack), captures secondary-market valuation skepticism (not pure DLOM), and reflects thin order-book depth. Oura tender = company-organized, structured price = controlled signal.
A92: Oura's +2.0pp ratifies the existing 1.5% practitioner midpoint with a market anchor.
A95: §7. Synthesis WACC: Bottom-Up vs. Damodaran Sector
A96: Cost of Equity = WACC (zero debt). Build A = current model approach (Assumptions). Build B = bottom-up justification (this tab).
A98: Component | B98: Build A: Damodaran Sector | E98: Build B: Bottom-Up + Oura | H98: Delta (Base)
B99: Bear | C99: Base | D99: Bull | E99: Bear | F99: Base | G99: Bull
A100: Risk-free rate (10Y UST) | B100: =Assumptions!C69 -> 0.043 | C100: =Assumptions!D69 -> 0.043 | D100: =Assumptions!E69 -> 0.043 | E100: =Assumptions!C69 -> 0.043 | F100: =Assumptions!D69 -> 0.043 | G100: =Assumptions!E69 -> 0.043 | H100: =F100-C100 -> 0
A101: Equity Risk Premium | B101: =Assumptions!C70 -> 0.045 | C101: =Assumptions!D70 -> 0.045 | D101: =Assumptions!E70 -> 0.045 | E101: =$E$70 -> 0.0460238 | F101: =$E$70 -> 0.0460238 | G101: =$E$70 -> 0.0460238 | H101: =F101-C101 -> 0.0010238
A102: Unlevered Beta (= levered, no debt) | B102: =Assumptions!C71 -> 0.85 | C102: =Assumptions!D71 -> 0.83 | D102: =Assumptions!E71 -> 0.81 | E102: =$H$50 -> 0.99115594 | F102: =$H$51 -> 0.97184978 | G102: =$H$52 -> 0.95360161 | H102: =F102-C102 -> 0.14184978
A103: Size Premium (CRSP Decile 3) | B103: =Assumptions!C72 -> 0.0081 | C103: =Assumptions!D72 -> 0.0081 | D103: =Assumptions!E72 -> 0.0081 | E103: =Assumptions!C72 -> 0.0081 | F103: =Assumptions!D72 -> 0.0081 | G103: =Assumptions!E72 -> 0.0081 | H103: =F103-C103 -> 0
A104: Liquidity Premium (Oura-anchored vs. CSRP) | B104: =Assumptions!C73 -> 0.03 | C104: =Assumptions!D73 -> 0.02 | D104: =Assumptions!E73 -> 0.01 | E104: =$B$89 -> 0.025 | F104: =$C$89 -> 0.02 | G104: =$D$89 -> 0.015 | H104: =F104-C104 -> 0
A106: Implied WACC | B106: =B100+B101*B102+B103+B104 -> 0.11935 | C106: =C100+C101*C102+C103+C104 -> 0.10845 | D106: =D100+D101*D102+D103+D104 -> 0.09755 | E106: =E100+E101*E102+E103+E104 -> 0.12171676 | F106: =F100+F101*F102+F103+F104 -> 0.11582822 | G106: =G100+G101*G102+G103+G104 -> 0.10998837 | H106: =F106-C106 -> 0.0073782201
A108: Decomposition of Build B − Build A delta (Base case) | C108: Contribution
A109: Beta upgrade (0.83 → 0.97) | C109: =(F102-C102)*F101 -> 0.0065284661
A110: ERP revenue-weighting (4.50% → 4.60%) | C110: =(F101-C101)*C102 -> 0.000849754
A111: Liquidity premium (CSRP 2.00% → Oura 2.00%) | C111: =F104-C104 -> 0
A112: Total | C112: =SUM(C109:C111) -> 0.0073782201
A114: Triangulation: Build A (10.85% Base, current model) and Build B (~11.6% Base, this tab) converge within ~0.7-0.8pp — two independent methods landing close gives the IC committee triangulation confidence. The +0.7pp delta is essentially the bottom-up beta premium (+0.65pp); ERP and liquidity rounding effects are trivial.
A115: DCF tab continues to reference Assumptions!F74 (Build A). This sheet is justification only.
A118: §8. Flagged Gaps & Caveats
A120: # | B120: Gap | D120: Path Forward
A121: 1 | B121: WHOOP actual ETR / NOL position unknown — forecast tax 5-15% range fully estimated | D121: Wait for S-1; sensitivity in Excel
A122: 2 | B122: Oura tender details (preferred vs. common) not fully disclosed | D122: Sacra paywall has more detail; not blocking
A123: 3 | B123: PTON βᵤ still distorted by distress dynamics even under 3Y weekly | D123: Use ex-PTON as primary; PTON-incl as overlay (col K, Section 4)
A124: 4 | B124: IRTC convertible debt treatment: βᵤ = 0.774 (debt) vs 0.877 (equity) | D124: B3 median essentially unchanged either way; use 0.774 primary
A125: 5 | B125: MASI deal-pending compression: stock pinned to $180 since Feb 2026; vol artificially low | D125: MASI exits comp set at H2 2026 close — flag and move on
A126: 6 | B126: R² on per-comp regressions weak (5.7-21.6%); single-name β std error ±0.20-0.30 | D126: Bucket medians smooth; Bloomberg adj is partial correction
A127: 7 | B127: B2 ex-PTON has only SPOT (n=1); SPOT 1.01 β reflects post-2024 phase-change | D127: Sensitivity: try B2 = 1.20; spec recommends current β as forward-looking proxy
A128: 8 | B128: Public-comp WACC base for Oura translation — if 11% used vs 10%, +2pp → +1.8pp | D128: Documented; the 10% base is itself the Damodaran sector output
A129: 9 | B129: S&P 500 as sole benchmark; SPOT's true reference could be MSCI World | D129: Sensitivity: re-run vs MSCI ACWI; expected impact <0.05 on β
A130: 10 | B130: 3Y weekly window excludes COVID-recovery dynamics; forward β in 2027+ may differ | D130: Acknowledge — current-state estimate by design
A132: Sources & Methodology
...

Sheet RealOptions
A1: WHOOP — Real Options (Healthcare Pathway)
A2: Single-gate decision tree on reimbursable healthcare platform thesis. Class anchor: Lecture 3B (Arundel) — probability-weighted call option on uncertain future cash flows. Decision tree EV; underlying not tradable, so not Black-Scholes. Same economic logic as Arundel sequel rights.
A4: Section 1 — The Binary Gate
A5: Question: Does WHOOP become a reimbursable healthcare platform within decision window?
B6: Bear | C6: Base | D6: Bull
A7: Probability healthcare materializes | B7: =Assumptions!$C$156 -> 0.15 | C7: =Assumptions!$D$156 -> 0.2 | D7: =Assumptions!$E$156 -> 0.25
A8: Probability of failure / indefinite stall | B8: =1-B7 -> 0.85 | C8: =1-C7 -> 0.8 | D8: =1-D7 -> 0.75
A10: Section 2 — Revenue Impact if Materialized
A11: (Computed three times: Bear / Base / Bull scenarios)
A13: 2033 ending members (M) | B13: =Members!L34 -> 8.1862873 | C13: =Members!L34 -> 8.1862873 | D13: =Members!L34 -> 8.1862873
A14: × Eligibility % (qualifying conditions) | B14: =Assumptions!$C$157 -> 0.3 | C14: =Assumptions!$D$157 -> 0.4 | D14: =Assumptions!$E$157 -> 0.45
A15: = Eligible members (M) | B15: =B13*B14 -> 2.4558862 | C15: =C13*C14 -> 3.2745149 | D15: =D13*D14 -> 3.6838293
A17: × Payer-paid annual ARPU ($/member) | B17: =Assumptions!$C$158 -> 200 | C17: =Assumptions!$D$158 -> 300 | D17: =Assumptions!$E$158 -> 350
A18: = Incremental annual revenue at maturity ($M) | B18: =B15*B17 -> 491.17724 | C18: =C15*C17 -> 982.35447 | D18: =D15*D17 -> 1289.3402
A20: × Healthcare-anchored multiple (x revenue) | B20: =Assumptions!$C$159 -> 5 | C20: =Assumptions!$D$159 -> 6 | D20: =Assumptions!$E$159 -> 6
A21: = Incremental EV at exercise ($M) — undiscounted | B21: =B18*B20 -> 2455.8862 | C21: =C18*C20 -> 5894.1268 | D21: =D18*D20 -> 7736.0415
A24: Section 3 — Discounting and Probability Weighting
A25: Years to exercise | B25: =Assumptions!$C$160 -> 7 | C25: =Assumptions!$D$160 -> 5 | D25: =Assumptions!$E$160 -> 4
A26: WACC | B26: =Assumptions!$F$74 -> 0.10845 | C26: =Assumptions!$F$74 -> 0.10845 | D26: =Assumptions!$F$74 -> 0.10845
A27: Discount factor (1/(1+WACC)^t) | B27: =1/(1+B26)^B25 -> 0.48639292 | C27: =1/(1+C26)^C25 -> 0.59761221 | D27: =1/(1+D26)^D25 -> 0.66242325
A28: Discounted incremental EV ($M) | B28: =B21*B27 -> 1194.5257 | C28: =C21*C27 -> 3522.4022 | D28: =D21*D27 -> 5124.5337
A30: × Probability of materialization | B30: =B7 -> 0.15 | C30: =C7 -> 0.2 | D30: =D7 -> 0.25
A31: = Expected option value ($M) | B31: =B28*B30 -> 179.17885 | C31: =C28*C30 -> 704.48043 | D31: =D28*D30 -> 1281.1334
A32: = Expected option value ($B) | B32: =B31/1000 -> 0.17917885 | C32: =C31/1000 -> 0.70448043 | D32: =D31/1000 -> 1.2811334
A34: Section 4 — Active Scenario Output
A35: Active scenario | B35: =Assumptions!$B$3 -> Base
A36: Expected option value (active scenario, $M) | B36: =IF($B$35="Bear",B31,IF($B$35="Bull",D31,C31)) -> 704.48043
A37: Expected option value (active scenario, $B) | B37: =B36/1000 -> 0.70448043
A40: Section 5 — Justification (memo, not driver)
A41: Honest read on what supports each input. Cite specific comparables and signals.
A43: Probability anchor (RO1 — 15/20/25%)
A44: iRhythm pathway: FDA-cleared cardiac monitoring, took 7+ years from approval to stable national CMS reimbursement. Stock dropped 83% during journey. Base rate evidence for consumer→medical transitions: low and slow.
A45: Dexcom pathway: 15+ year ongoing reimbursement expansion from initial Type 1 diabetes coverage. Each new indication requires separate CMS review.
A46: WHOOP-specific positive signals: CMS Innovation Center Access Program selection (Apr 13, 2026); Abbott + Mayo Clinic as Series G investors; FDA-cleared ECG already shipping; BP Insights with FDA wellness exemptions (Jan 2026).
A47: WHOOP-specific gaps: zero CPT codes filed; no clinical trial data validating diagnostic claims; no disclosed Abbott/Mayo deliverables; no payer revenue projections.
A48: Probability range 15-25% reflects: (a) credible signals justify above pure base rate, (b) absence of clinical/regulatory milestones bounds upside.
A50: Eligibility anchor (RO2 — 30/40/45%)
A51: ~40% of US adults have cardiometabolic risk factors (CDC: 47% HTN, 38% pre-diabetes, 9-12% AFib risk in over-65s, 30% sleep disorders).
A52: WHOOP user base premium-skewed (high health engagement); plausibly overrepresents diagnosable risk factors.
A53: Range 30-45%: bear conservative (only severe cases qualify); bull at calibrated upper end (was 50% wide, tightened to 45% — broad screening eligibility but stops short of aggressive).
... A78: If audience asks 'why not value these separately': these options either (a) generate revenue already partially in base case, leading to double-counting risk, OR (b) lack any sourced evidence base for probability/payoff inputs. Healthcare is the only option with both signal AND comparable structure (iRhythm).

Sheet Comps
A1: WHOOP — Public Comp Triangulation (Three-Thesis Framework)
A2: Comps grouped by what WHOOP would *become* under each thesis (Failed Pivot / Subscription Executed / Healthcare Platform). Within each thesis comps share economic structure; across theses they don't — so we don't average across them. Composite span feeds Football Field. Oura shown as parallel reference, never blended. Garmin reclassified as form factor reference, doesn't anchor any thesis.
A4: 1. WHOOP Inputs
A6: Recognized revenue (2025, $M) | B6: ='Revenue Build'!D20 -> 579.5
A7: Bookings run-rate ($M) | B7: 1100
A8: Gross margin (model 2026E) | B8: ='P&L'!E16 -> 0.75
A9: Implied gross profit — recognized basis | B9: =B6*B8 -> 434.625
A10: Implied gross profit — bookings basis | B10: =B7*B8 -> 825
A11: LTM bookings growth | B11: 1.03
A12: NTM growth (model) | B12: 0.7
A13: Series G mark ($M) | B13: 10100
A15: 2. Master Comp Table
A16: Multiples per spec (May 5, 2026 refresh). Tier T1=direct comp parallel ref, T2=structural analogue thesis anchor, T3=boundary marker thesis anchor, T4=historical footnote. Thesis tag drives which bracket each comp anchors.
A18: Comp | B18: Ticker | C18: Tier | D18: Thesis | E18: EV/Rev NTM | F18: EV/GP NTM | G18: NTM Growth | H18: Gross Margin | I18: EV/Rev / Growth | J18: Notes
A19: Peloton | B19: PTON | C19: T3 | D19: 1 — Failed Pivot | E19: 1.22 | F19: 2.9 | G19: -0.05 | H19: 0.42 | I19: =IFERROR(E19/(G19*100),"n/m") -> -0.244 | J19: Hardware-sub failed pivot. Bear floor.
A20: Sonos | B20: SONO | C20: T3 | D20: 1 — Failed Pivot | E20: 1.07 | F20: 2.4 | G20: -0.02 | H20: 0.45 | I20: =IFERROR(E20/(G20*100),"n/m") -> -0.535 | J20: Consumer durable in revenue decline.
A21: GoPro | B21: GPRO | C21: T3 | D21: 1 — Failed Pivot | E21: 0.4 | F21: 1.2 | G21: -0.08 | H21: 0.33 | I21: =IFERROR(E21/(G21*100),"n/m") -> -0.05 | J21: Failed subscription pivot, terminal decline.
A22: Spotify | B22: SPOT | C22: T2 | D22: 2 — Subscription Executed | E22: 3.66 | F22: 11.4 | G22: 0.13 | H22: 0.32 | I22: =IFERROR(E22/(G22*100),"n/m") -> 0.28153846 | J22: Mature pure subscription. Profitability proof drove +116% multiple expansion 3yr.
A23: Roku | B23: ROKU | C23: T2 | D23: 2 — Subscription Executed | E23: 3.02 | F23: 6.9 | G23: 0.12 | H23: 0.44 | I23: =IFERROR(E23/(G23*100),"n/m") -> 0.25166667 | J23: Platform with hardware as CAC, profitability inflection.
A24: Dexcom | B24: DXCM | C24: T2 | D24: 3 — Healthcare Platform | E24: 4.24 | F24: 7.1 | G24: 0.11 | H24: 0.6 | I24: =IFERROR(E24/(G24*100),"n/m") -> 0.38545455 | J24: FDA-cleared CGM, reimbursed. Compressed -67% from 13.8x in 2023.
A25: iRhythm | B25: IRTC | C25: T2 | D25: 3 — Healthcare Platform | E25: 4.65 | F25: 6.5 | G25: 0.18 | H25: 0.7 | I25: =IFERROR(E25/(G25*100),"n/m") -> 0.25833333 | J25: Cardiac monitoring, CMS-reimbursed. Closest pathway analog. Compressed -51% from peak.
A26: ResMed | B26: RMD | C26: T3 | D26: 3 — Healthcare Platform | E26: 5.23 | F26: 8.9 | G26: 0.08 | H26: 0.59 | I26: =IFERROR(E26/(G26*100),"n/m") -> 0.65375 | J26: Sleep apnea, reimbursed, mature.
A27: Masimo | B27: MASI | C27: T3 | D27: 3 — Healthcare Platform | E27: 5.96 | F27: 9.5 | G27: 0.1 | H27: 0.63 | I27: =IFERROR(E27/(G27*100),"n/m") -> 0.596 | J27: Hospital monitoring, sensor-first.
A28: Garmin | B28: GRMN | C28: T2 | D28: Form factor ref — not anchored | E28: 5.25 | F28: 9.8 | G28: 0.06 | H28: 0.59 | I28: =IFERROR(E28/(G28*100),"n/m") -> 0.875 | J28: Diversified hardware conglomerate. WHOOP isn't fundamentally hardware. Reference only.
A29: Oura | B29: (private) | C29: T1 | D29: Parallel ref — never blended | E29: 13 | F29: 26 | G29: 1.29 | H29: 0.5 | I29: =IFERROR(E29/(G29*100),"n/m") -> 0.10077519 | J29: Only direct comp; private. Same Gornall/Strebulaev critique applies as Series G.
A30: Fitbit (IPO 2015) | B30: FIT | C30: T4 | D30: Historical footnote | E30: 2.2 | J30: Peak public-market mark before category compression.
A31: Fitbit (Google acquire 2021) | B31: FIT | C31: T4 | D31: Historical footnote | E31: 1.5 | J31: Strategic exit; revenue-declining at sale.
A33: 3. Thesis Summary — Bracketed Implied WHOOP Valuations
A34: Three theses about what WHOOP becomes. Within each, comps share economic structure; across theses they don't. Each bracket shows EV/Rev and EV/GP ranges and computes 4 implied-EV variants × WHOOP financials.
A36: Thesis 1 — Failed Pivot (Bear)
A37: Anchors: Peloton, Sonos, GoPro. Question: what if WHOOP fails to defend subscription economics and reverts to hardware-dependent revenue?
B38: Low | C38: High | D38: Median
A39: EV/Rev NTM | B39: =MIN(E19:E21) -> 0.4 | C39: =MAX(E19:E21) -> 1.22 | D39: =MEDIAN(E19:E21) -> 1.07
A40: EV/GP NTM | B40: =MIN(F19:F21) -> 1.2 | C40: =MAX(F19:F21) -> 2.9 | D40: =MEDIAN(F19:F21) -> 2.4
A41: Implied EV ($M):
A42: Recognized × EV/Rev | B42: =B39*$B$6 -> 231.8 | C42: =C39*$B$6 -> 706.99 | D42: =D39*$B$6 -> 620.065
A43: Bookings × EV/Rev | B43: =B39*$B$7 -> 440 | C43: =C39*$B$7 -> 1342 | D43: =D39*$B$7 -> 1177
A44: Recognized GP × EV/GP | B44: =B40*$B$9 -> 521.55 | C44: =C40*$B$9 -> 1260.4125 | D44: =D40*$B$9 -> 1043.1
A45: Bookings GP × EV/GP | B45: =B40*$B$10 -> 990 | C45: =C40*$B$10 -> 2392.5 | D45: =D40*$B$10 -> 1980
A47: Thesis 2 — Subscription Executed (Base)
A48: Anchors: Spotify, Roku. Question: what if WHOOP becomes a premium consumer subscription business at scale? EV/GP is the more analytically relevant multiple here — normalizes WHOOP's GM advantage (75% vs Spotify 32% / Roku 44%).
B49: Low | C49: High | D49: Median
A50: EV/Rev NTM | B50: =MIN(E22:E23) -> 3.02 | C50: =MAX(E22:E23) -> 3.66 | D50: =MEDIAN(E22:E23) -> 3.34
A51: EV/GP NTM | B51: =MIN(F22:F23) -> 6.9 | C51: =MAX(F22:F23) -> 11.4 | D51: =MEDIAN(F22:F23) -> 9.15
A52: Implied EV ($M):
A53: Recognized × EV/Rev | B53: =B50*$B$6 -> 1750.09 | C53: =C50*$B$6 -> 2120.97 | D53: =D50*$B$6 -> 1935.53
A54: Bookings × EV/Rev | B54: =B50*$B$7 -> 3322 | C54: =C50*$B$7 -> 4026 | D54: =D50*$B$7 -> 3674
A55: Recognized GP × EV/GP | B55: =B51*$B$9 -> 2998.9125 | C55: =C51*$B$9 -> 4954.725 | D55: =D51*$B$9 -> 3976.8188
A56: Bookings GP × EV/GP | B56: =B51*$B$10 -> 5692.5 | C56: =C51*$B$10 -> 9405 | D56: =D51*$B$10 -> 7548.75
A58: Thesis 3 — Healthcare Platform (Bull / Optionality)
A59: Anchors: Dexcom, iRhythm, ResMed, Masimo. Question: what if WHOOP becomes a reimbursable health-data platform with FDA/CMS pathway success? Note multiples have de-rated -51 to -67% from 2023 peaks — bull case more constrained than 2023 multiples would suggest.
B60: Low | C60: High | D60: Median
A61: EV/Rev NTM | B61: =MIN(E24:E27) -> 4.24 | C61: =MAX(E24:E27) -> 5.96 | D61: =MEDIAN(E24:E27) -> 4.94
A62: EV/GP NTM | B62: =MIN(F24:F27) -> 6.5 | C62: =MAX(F24:F27) -> 9.5 | D62: =MEDIAN(F24:F27) -> 8
A63: Implied EV ($M):
A64: Recognized × EV/Rev | B64: =B61*$B$6 -> 2457.08 | C64: =C61*$B$6 -> 3453.82 | D64: =D61*$B$6 -> 2862.73
A65: Bookings × EV/Rev | B65: =B61*$B$7 -> 4664 | C65: =C61*$B$7 -> 6556 | D65: =D61*$B$7 -> 5434
A66: Recognized GP × EV/GP | B66: =B62*$B$9 -> 2825.0625 | C66: =C62*$B$9 -> 4128.9375 | D66: =D62*$B$9 -> 3477
A67: Bookings GP × EV/GP | B67: =B62*$B$10 -> 5362.5 | C67: =C62*$B$10 -> 7837.5 | D67: =D62*$B$10 -> 6600
A69: 4. Composite Span (across all theses)
A71: Lowest defensible (Bear, recognized basis) | B71: =MIN(B42:B45) -> 231.8
A72: Highest defensible (Sub Executed, bookings GP × EV/GP) | B72: =MAX(C56,C67) -> 9405
A73: Most defensible base (T2 median, recognized GP × EV/GP) | B73: =D55 -> 3976.8188
A74: Series G mark | B74: =B13 -> 10100
A76: 5. Oura — Private Market Category Reference (parallel, never blended)
A77: Oura at 13x recognized is a private-market data point on category pricing. Comparison flips between EV/Rev and EV/GP — real analytical content.
A79: Oura TEV ($M) | B79: 12060
A80: Oura TTM revenue ($M) | B80: 927
A81: Oura EV/Rev | B81: =B79/B80 -> 13.009709
A82: Oura EV/GP (est. 50% GM) | B82: =B79/(B80*0.5) -> 26.019417
A83: WHOOP at Series G — EV/Rev (recognized) | B83: =B13/B6 -> 17.428818
A84: WHOOP at Series G — EV/GP (recognized) | B84: =B13/B9 -> 23.238424
A85: Read | B85: WHOOP higher than Oura on EV/Rev, lower on EV/GP. Margin advantage flips it. Both private marks reflect rich category pricing.
A87: 6. Series G Implied Multiples — Back-Solve Diagnostic
A88: What multiple does Series G $10.1B imply on each thesis basis? Compare to thesis medians to see how far above the comp set Series G sits.
B89: Series G implied | C89: T1 median | D89: T2 median | E89: T3 median | F89: Premium (Series G vs T2 median)
A90: EV/Rev (recognized basis) | B90: =$B$13/$B$6 -> 17.428818 | C90: =D39 -> 1.07 | D90: =D50 -> 3.34 | E90: =D61 -> 4.94 | F90: =B90/D50-1 -> 4.218209
A91: EV/Rev (bookings basis) | B91: =$B$13/$B$7 -> 9.1818182 | C91: =D39 -> 1.07 | D91: =D50 -> 3.34 | E91: =D61 -> 4.94 | F91: =B91/D50-1 -> 1.7490474
A92: EV/GP (recognized basis) | B92: =$B$13/$B$9 -> 23.238424 | C92: =D40 -> 2.4 | D92: =D51 -> 9.15 | E92: =D62 -> 8 | F92: =B92/D51-1 -> 1.5397185
A93: EV/GP (bookings basis) | B93: =$B$13/$B$10 -> 12.242424 | C93: =D40 -> 2.4 | D93: =D51 -> 9.15 | E93: =D62 -> 8 | F93: =B93/D51-1 -> 0.33796986
A95: 7. Historical Regime (V19) — Multiple Compression in Health Data
A96: Health-data multiples have structurally compressed (Dexcom -67%, iRhythm -51% over 3yr). Spotify shows the inverse: profitability proof drove +116% expansion. WHOOP's path runs through Spotify's template, not Dexcom's. Series G investors may have anchored to 2023-era multiples that no longer exist.
A98: Company | B98: 46143 | C98: 45931 | D98: 45748 | E98: 45017 | F98: 3yr Change
A99: Garmin | B99: 5.6 | C99: 6.5 | D99: 5.5 | E99: 3.5 | F99: =B99/E99-1 -> 0.6
A100: Spotify | B100: 4.1 | C100: 6 | D100: 4.9 | E100: 1.9 | F100: =B100/E100-1 -> 1.1578947
A101: Dexcom | B101: 4.6 | C101: 5.9 | D101: 5.8 | E101: 13.8 | F101: =B101/E101-1 -> -0.66666667
A102: iRhythm | B102: 5.2 | C102: 10 | D102: 6.9 | E102: 10.7 | F102: =B102/E102-1 -> -0.51401869
A104: 8. Growth-Adjusted Scatter Data (regression input — visual built separately)
A105: X = NTM growth, Y = EV/GP NTM. T2 anchors used for regression line. WHOOP plotted at NTM growth (~70%) and Series G implied EV/GP. Linear extrapolation produces nonsense at extreme growth (concave relationship), so this is narrative-only — no $ output.
B107: X: NTM Growth | C107: Y: EV/GP NTM | D107: Tier | E107: In Regression?
A108: Peloton | B108: =G19 -> -0.05 | C108: =F19 -> 2.9 | D108: =C19 -> T3 | E108: No (T3)
A109: Sonos | B109: =G20 -> -0.02 | C109: =F20 -> 2.4 | D109: =C20 -> T3 | E109: No (T3)
A110: GoPro | B110: =G21 -> -0.08 | C110: =F21 -> 1.2 | D110: =C21 -> T3 | E110: No (T3)
A111: Spotify | B111: =G22 -> 0.13 | C111: =F22 -> 11.4 | D111: =C22 -> T2 | E111: Yes (T2)
A112: Roku | B112: =G23 -> 0.12 | C112: =F23 -> 6.9 | D112: =C23 -> T2 | E112: Yes (T2)
A113: Dexcom | B113: =G24 -> 0.11 | C113: =F24 -> 7.1 | D113: =C24 -> T2 | E113: Yes (T2)
A114: iRhythm | B114: =G25 -> 0.18 | C114: =F25 -> 6.5 | D114: =C25 -> T2 | E114: Yes (T2)
A115: ResMed | B115: =G26 -> 0.08 | C115: =F26 -> 8.9 | D115: =C26 -> T3 | E115: No (T3)
A116: Masimo | B116: =G27 -> 0.1 | C116: =F27 -> 9.5 | D116: =C27 -> T3 | E116: No (T3)
A117: WHOOP at Series G | B117: =B12 -> 0.7 | C117: =B92 -> 23.238424 | D117: WHOOP | E117: Plotted, not in regression
...

Sheet Precedents
A1: WHOOP — Precedent Transactions
A2: 2020-2026; $500M+ EV preferred; All USD
A4: Acquirer / Target | B4: Date | C4: EV ($B) | D4: LTM Rev ($B) | E4: EV/Rev | F4: Regime | G4: Bucket | H4: Strategic Rationale
A5: Google / Fitbit | B5: Jan 2021 | C5: 2.1 | D5: 1.43 | E5: 1.5 | F5: ZIRP-peak | G5: B1 | H5: Wearable data acquisition; failed sub pivot
A6: Lululemon / Mirror | B6: Jul 2020 | C6: 0.5 | D6: 0.17 | E6: 2.9 | F6: ZIRP-peak | G6: B2 | H6: Connected fitness content; 89% write-off
A7: Teladoc / Livongo | B7: Oct 2020 | C7: 18.5 | D7: 0.29 | E7: 63.8 | F7: ZIRP-peak | G7: Cross | H7: Digital health mega-deal; massive write-down
A8: Microsoft / Nuance | B8: Mar 2022 | C8: 19.7 | D8: 1.48 | E8: 13.3 | F8: Transition | G8: Cross | H8: Healthcare AI voice/NLP platform
A9: Masimo / Sound United | B9: Apr 2022 | C9: 1.03 | D9: 0.9 | E9: 1.1 | F9: Transition | G9: B1 | H9: Consumer audio pivot; $675M value destruction
A10: CVS / Signify Health | B10: Sep 2022 | C10: 8 | D10: 0.77 | E10: 10.4 | F10: Transition | G10: B3 | H10: Home health + value-based care platform
A11: Amazon / One Medical | B11: Feb 2023 | C11: 3.9 | D11: 1.1 | E11: 3.5 | F11: Transition | G11: Cross | H11: Primary care distribution; strategic access play
A12: J&J / Shockwave Medical | B12: May 2024 | C12: 13.1 | D12: 0.73 | E12: 17.9 | F12: Current | G12: B3 | H12: OUTLIER: IVL synergies drove 2x+ peer median
A13: BSci / Axonics | B13: Nov 2024 | C13: 3.7 | D13: 0.37 | E13: 10.1 | F13: Current | G13: B3 | H13: Neuromodulation bolt-on
A14: Stryker / Inari Medical | B14: Feb 2025 | C14: 4.9 | D14: 0.6 | E14: 8.1 | F14: Current | G14: B3 | H14: Venous thromboembolism devices
A15: Danaher / Masimo | B15: Feb 2026 | C15: 9.9 | D15: 1.51 | E15: 6.6 | F15: Current | G15: B3 | H15: Patient monitoring platform; pending close
A18: Summary by Regime & Bucket
A19: Current-regime B3 medtech: 6.6-10.1x (median ~8.5x)
A20: Connected fitness deals: uniformly value-destructive
A21: Implied WHOOP range: $5-8B (control premium embedded; Series G is minority)

Sheet Cap Table
A1: WHOOP — Cap Table & Waterfall
A2: Sources: Pitchbook + Cap IQ; BUILD WATERFALL FORMULAS
A4: Round | B4: Date | C4: Amount ($M) | D4: Post-Money ($B) | E4: Price/Share ($) | F4: Shares (M) | G4: Ownership % | H4: Pref Terms | I4: Lead Investor(s)
A5: Seed | B5: 2012 | C5: 1 | H5: 1x non-part. | I5: DraftKings founders
A6: Series A | B6: Sep 2014 | C6: 4 | H6: 1x non-part. | I6: Accomplice, Mousse Partners
A7: Series B | B7: Sep 2016 | C7: 12 | H7: 1x non-part. | I7: Foundry Group
A8: Series C | B8: Oct 2018 | C8: 55 | D8: 0.43 | H8: 1x non-part. | I8: IVP
A9: Series D | B9: Oct 2020 | C9: 100 | D9: 1.2 | H9: 1x non-part. | I9: IVP
A10: Series E | B10: Aug 2021 | C10: 200 | D10: 2.4 | H10: 1x non-part. | I10: SoftBank Vision Fund 2
A11: Series F | B11: Aug 2021 | C11: 200 | D11: 3.6 | E11: 4.76 | H11: 1x non-part. | I11: SoftBank Vision Fund 2
A12: Mezz/Bridge | B12: 2022-2024 | C12: 46 | H12: Various | I12: 5 interim rounds (VC + debt)
A13: Series G | B13: Mar 2026 | C13: 575 | D13: 10.1 | E13: 11.23 | G13: 0.057 | H13: 1x non-part. | I13: Collaborative Fund
A15: Total Equity Raised: | C15: 1030
A17: Key Metrics
A18: Authorized Preferred Shares | C18: 537.9M | E18: Pitchbook
A19: Outstanding Common Shares | C19: 361.2M | E19: Pitchbook
A20: Fully Diluted Shares (est.) | C20: ~900M | E20: PremierAlts/Forge
A21: Option Pool (est.) | C21: ~10-15% of FD | E21: Inferred from gap; FLAGGED_GAP
A22: All Preferences | C22: 1x non-participating pari passu | E22: Pitchbook
A23: Total Liquidation Preference | C23: ~$1.03B (floor) | E23: Sum of equity raised × 1x
A26: Waterfall at Exit Scenarios (BUILD FORMULAS)
C27: Bear ($5B) | E27: Base ($10B) | G27: Bull ($20B)
A28: Total Exit Proceeds
A29: Less: Liquidation Preferences
A30: Remaining for Pro-Rata
A31: Preferred Conversion Check (convert or take pref?)
A32: Common Share Proceeds
A33: Common Value per Share
A34: Preferred Value per Share
A35: Founder Equity Value (est. 12-18% FD)

Sheet Football Field
A1: WHOOP — Valuation Football Field
A2: Multi-method synthesis. Each method shown with low/base/high EV. Per-share converts via Assumptions F62 (debt), F63 (cash), F55 (FD shares).
A4: Method | B4: Source | C4: Low EV ($B) | D4: Base EV ($B) | E4: High EV ($B) | F4: Low $/sh | G4: Base $/sh | H4: High $/sh | I4: Weight | J4: Wtd Base | K4: Note
A6: 1. Intrinsic DCF (base case, no options) | B6: Sensitivity Grid 1 | C6: =Sensitivity!B29 -> 4.6214298 | D6: =Sensitivity!C29 -> 7.3065144 | E6: =Sensitivity!D29 -> 10.527152 | F6: =(C6*1000 - Assumptions!$F$62 + Assumptions!$F$63)/Assumptions!$F$55 -> 12.954707 | G6: =(D6*1000 - Assumptions!$F$62 + Assumptions!$F$63)/Assumptions!$F$55 -> 19.503694 | H6: =(E6*1000 - Assumptions!$F$62 + Assumptions!$F$63)/Assumptions!$F$55 -> 27.358907 | I6: 1 | J6: =D6*I6 -> 7.3065144 | K6: Primary fundamental method. WACC × Exit Mult range.
A7: 1b. DCF + Real Options (probability-wtd) | B7: DCF Base + RO Active | C7: =C6 + RealOptions!B32 -> 4.8006086 | D7: =D6 + RealOptions!C32 -> 8.0109948 | E7: =E6 + RealOptions!D32 -> 11.808285 | F7: =(C7*1000 - Assumptions!$F$62 + Assumptions!$F$63)/Assumptions!$F$55 -> 13.391728 | G7: =(D7*1000 - Assumptions!$F$62 + Assumptions!$F$63)/Assumptions!$F$55 -> 21.221939 | H7: =(E7*1000 - Assumptions!$F$62 + Assumptions!$F$63)/Assumptions!$F$55 -> 30.483622 | K7: Binary-gate decision tree on healthcare reimbursement pathway. Additive to DCF. Replaces prior 3-cluster correlated framework (success/mixed/failure).
A8: 2. Public Comps (three-thesis bracketing) | B8: Comps tab (three-thesis brackets) | C8: =Comps!D43/1000 -> 1.177 | D8: =Comps!D55/1000 -> 3.9768188 | E8: =Comps!D56/1000 -> 7.54875 | F8: =(C8*1000 - Assumptions!$F$62 + Assumptions!$F$63)/Assumptions!$F$55 -> 4.5536585 | G8: =(D8*1000 - Assumptions!$F$62 + Assumptions!$F$63)/Assumptions!$F$55 -> 11.382485 | H8: =(E8*1000 - Assumptions!$F$62 + Assumptions!$F$63)/Assumptions!$F$55 -> 20.094512 | I8: 0 | J8: =D8*I8 -> 0 | K8: Three-thesis bracketing. Composite span $0.7B-$9.4B; T2 base anchor $4.0B (recognized GP × EV/GP). Implies Series G priced for bull case across drivers.
A10: 3. Precedent Transactions | B10: Not yet populated | C10: n/a | D10: n/a | E10: n/a | K10: Skipped per session decision. 5-10% memo weight max per methodology.
A11: 4. Last-Round Implied (Series G) | B11: DCF C58 | C11: =$D$19 -> 9.41 | D11: =$D$19 -> 9.41 | E11: =$D$19 -> 9.41 | F11: =(C11*1000 - Assumptions!$F$62 + Assumptions!$F$63)/Assumptions!$F$55 -> 24.634146 | G11: =(D11*1000 - Assumptions!$F$62 + Assumptions!$F$63)/Assumptions!$F$55 -> 24.634146 | H11: =(E11*1000 - Assumptions!$F$62 + Assumptions!$F$63)/Assumptions!$F$55 -> 24.634146 | I11: 0 | J11: =D11*I11 -> 0 | K11: Series G $10.1B post-money mark, March 2026. Single point, not derived value.
A12: 5. Implied IPO Trading Range | B12: Assumptions C94/D94/E94 | C12: =Assumptions!E94/1000 -> 11.882353 | D12: =Assumptions!D94/1000 -> 12.625 | E12: =Assumptions!C94/1000 -> 13.466667 | F12: =(C12*1000 - Assumptions!$F$62 + Assumptions!$F$63)/Assumptions!$F$55 -> 30.664275 | G12: =(D12*1000 - Assumptions!$F$62 + Assumptions!$F$63)/Assumptions!$F$55 -> 32.47561 | H12: =(E12*1000 - Assumptions!$F$62 + Assumptions!$F$63)/Assumptions!$F$55 -> 34.528455 | I12: 0 | J12: =D12*I12 -> 0 | K12: Back-solve: $10.1B ÷ (1−illiquidity) ÷ (1−IPO discount). Bull = lower discounts, lower implied; Bear = higher discounts, higher implied.
A14: Weight Check | I14: =I6+I8+I11+I12 -> 1
A16: Weighted Average EV | D16: =J6+J8+J11+J12 -> 7.3065144 | G16: =(D16*1000 - Assumptions!$F$62 + Assumptions!$F$63)/Assumptions!$F$55 -> 19.503694 | K16: = Σ(weight × base EV) per method
A17: Series G Mark (Equity, post-money) | D17: =DCF!C52/1000 -> 10.1 | G17: =(D17*1000 - Assumptions!$F$62 + Assumptions!$F$63)/Assumptions!$F$55 -> 26.317073
A18: Premium / (Discount) to Series G | D18: =D16/D19 - 1 -> -0.22353726 | G18: =G16/((D19*1000 - Assumptions!$F$62 + Assumptions!$F$63)/Assumptions!$F$55) - 1 -> -0.2082659 | K18: Positive = methods support a higher mark; negative = Series G is rich.
A19: Series G EV equivalent | D19: =D17 - Assumptions!F63/1000 + Assumptions!F62/1000 -> 9.41 | K19: Equity − Cash + Debt. EV-basis comparable for premium/(discount) calc.
A20: Method Range Summary
A21: Lowest method base | B21: =INDEX($A$6:$A$12, MATCH(MIN(D6,D8,D11,D12), D6:D12, 0)) -> 2. Public Comps (three-thesis bracketing) | D21: =MIN(D6,D8,D11,D12) -> 3.9768188 | G21: =(D21*1000 - Assumptions!$F$62 + Assumptions!$F$63)/Assumptions!$F$55 -> 11.382485
A22: Highest method base | B22: =INDEX($A$6:$A$12, MATCH(MAX(D6,D8,D11,D12), D6:D12, 0)) -> 5. Implied IPO Trading Range | D22: =MAX(D6,D8,D11,D12) -> 12.625 | G22: =(D22*1000 - Assumptions!$F$62 + Assumptions!$F$63)/Assumptions!$F$55 -> 32.47561
A23: Range across methods | D23: =D22-D21 -> 8.6481813 | G23: =G22-G21 -> 21.093125
A25: Memo Read
A26: Multi-method synthesis lands at $7.2B / $19.29 per share, -28.5% below Series G $10.1B / $26.32. Methods range $4.0B (Comps T2 base, recognized GP × EV/GP) to $12.6B (IPO Base implied). DCF is the analytical anchor at $7.3B EV / $8.0B equity (3.5x exit, full WC schedule); the +healthcare-option bridge adds $0.7B at base probability, lifting to $8.0B (-21% vs Series G). Three-thesis comps undershoot Series G across every basis: Failed Pivot $1.2B, Subscription Executed $4.0B median (recognized GP × EV/GP), Healthcare Platform bracketed within. Even the most flattering comp combo (T2 bookings GP × EV/GP at $7.5B) sits 25% below mark. IPO range $11.9-13.5B implied is consistent with Series G investors targeting 25%+ IRR over 12-18 month hold. Bottom line: independent triangulation centers $7.2-8.0B; Series G prices in the bull case across multiple drivers.
A27: Cross-Check | D27: EV ($B) | G27: $/sh | K27: Note
A28: Median of independent methods (DCF, Comps, DCF+RO) | D28: =MEDIAN(D6, D7, D8) -> 7.3065144 | G28: =(D28*1000 - Assumptions!$F$62 + Assumptions!$F$63)/Assumptions!$F$55 -> 19.503694 | K28: Cross-check on the DCF anchor.
A29: Chart Data (helper table for visual)
A30: Method | B30: Low (offset) | C30: Range (visible bar) | D30: Base marker | E30: Series G ref
A31: 1. Intrinsic DCF | B31: =C6 -> 4.6214298 | C31: =E6-C6 -> 5.9057219 | D31: =D6 -> 7.3065144 | E31: =$D$17 -> 10.1
A32: 1b. DCF + Real Options | B32: =C7 -> 4.8006086 | C32: =E7-C7 -> 7.0076765 | D32: =D7 -> 8.0109948 | E32: =$D$17 -> 10.1
A33: 2. Public Comps (Three-Thesis) | B33: =C8 -> 1.177 | C33: =E8-C8 -> 6.37175 | D33: =D8 -> 3.9768188 | E33: =$D$17 -> 10.1
A34: 4. Last-Round Implied (Series G) | B34: =C11 -> 9.41 | C34: 0.001 | D34: =D11 -> 9.41 | E34: =$D$17 -> 10.1
A35: 5. Implied IPO Range | B35: =C12 -> 11.882353 | C35: =E12-C12 -> 1.5843137 | D35: =D12 -> 12.625 | E35: =$D$17 -> 10.1
A36: Weighted Avg | B36: =D16 -> 7.3065144 | C36: 0.001 | D36: =D16 -> 7.3065144 | E36: =$D$17 -> 10.1

Sheet Scenarios
A1: WHOOP — Scenario Summary
A2: Scenario EV by method; weight sensitivity grid. Populate after DCF + Comps are wired.
A4: Method | B4: Bear ($B) | C4: Base ($B) | D4: Bull ($B) | E4: Notes
A5: 1. Intrinsic DCF (base) | E5: Link from DCF tab
A6: + Real Options | E6: Link from RealOptions tab
A7: 2. Trading Comps (3-bucket) | E7: Link from Comps tab
A8: 3. Precedent Transactions | E8: Link from Precedents tab
A9: 4. Last-Round Implied | E9: Series G mark = $10.1B (constant)
A10: 5. Implied IPO Trading Range | E10: Link from Assumptions I5
A12: Probability Weight Sensitivity
A13: Weight Scheme | B13: Bear Wt | C13: Base Wt | D13: Bull Wt | E13: Weighted EV ($B)
A14: Pessimistic | B14: 0.35 | C14: 0.5 | D14: 0.15
A15: Neutral (base) | B15: 0.25 | C15: 0.5 | D15: 0.25
A16: Optimistic | B16: 0.15 | C16: 0.55 | D16: 0.3

Sheet Sensitivity
A1: WHOOP — Sensitivity Analysis
A2: Base case anchored: WACC 10.85%, Exit Mult 3.5x, Terminal Growth 3.0% → EV $7.31B / Equity $8.00B / $19.50 per share. Yellow cell = base case (E9).
A4: Grid 1: WACC × Exit Multiple → Enterprise Value ($B)
A5: WACC ↓ / Exit Mult (EV/Rev) → | B5: 2 | C5: 2.5 | D5: 3 | E5: 3.5 | F5: 4 | G5: 4.5 | H5: 5
A6: 0.0935 | B6: {=(SUMPRODUCT(DCF!$D$9:$K$9, 1/(1+$A6)^DCF!$D$13:$K$13) + DCF!$K$8*B$5/(1+$A6)^DCF!$K$13)/1000} -> 5.5055754 | C6: {=(SUMPRODUCT(DCF!$D$9:$K$9, 1/(1+$A6)^DCF!$D$13:$K$13) + DCF!$K$8*C$5/(1+$A6)^DCF!$K$13)/1000} -> 6.3425048 | D6: {=(SUMPRODUCT(DCF!$D$9:$K$9, 1/(1+$A6)^DCF!$D$13:$K$13) + DCF!$K$8*D$5/(1+$A6)^DCF!$K$13)/1000} -> 7.1794342 | E6: {=(SUMPRODUCT(DCF!$D$9:$K$9, 1/(1+$A6)^DCF!$D$13:$K$13) + DCF!$K$8*E$5/(1+$A6)^DCF!$K$13)/1000} -> 8.0163636 | F6: {=(SUMPRODUCT(DCF!$D$9:$K$9, 1/(1+$A6)^DCF!$D$13:$K$13) + DCF!$K$8*F$5/(1+$A6)^DCF!$K$13)/1000} -> 8.8532929 | G6: {=(SUMPRODUCT(DCF!$D$9:$K$9, 1/(1+$A6)^DCF!$D$13:$K$13) + DCF!$K$8*G$5/(1+$A6)^DCF!$K$13)/1000} -> 9.6902223 | H6: {=(SUMPRODUCT(DCF!$D$9:$K$9, 1/(1+$A6)^DCF!$D$13:$K$13) + DCF!$K$8*H$5/(1+$A6)^DCF!$K$13)/1000} -> 10.527152
A7: 0.0985 | B7: {=(SUMPRODUCT(DCF!$D$9:$K$9, 1/(1+$A7)^DCF!$D$13:$K$13) + DCF!$K$8*B$5/(1+$A7)^DCF!$K$13)/1000} -> 5.3445695 | C7: {=(SUMPRODUCT(DCF!$D$9:$K$9, 1/(1+$A7)^DCF!$D$13:$K$13) + DCF!$K$8*C$5/(1+$A7)^DCF!$K$13)/1000} -> 6.1533474 | D7: {=(SUMPRODUCT(DCF!$D$9:$K$9, 1/(1+$A7)^DCF!$D$13:$K$13) + DCF!$K$8*D$5/(1+$A7)^DCF!$K$13)/1000} -> 6.9621252 | E7: {=(SUMPRODUCT(DCF!$D$9:$K$9, 1/(1+$A7)^DCF!$D$13:$K$13) + DCF!$K$8*E$5/(1+$A7)^DCF!$K$13)/1000} -> 7.7709031 | F7: {=(SUMPRODUCT(DCF!$D$9:$K$9, 1/(1+$A7)^DCF!$D$13:$K$13) + DCF!$K$8*F$5/(1+$A7)^DCF!$K$13)/1000} -> 8.579681 | G7: {=(SUMPRODUCT(DCF!$D$9:$K$9, 1/(1+$A7)^DCF!$D$13:$K$13) + DCF!$K$8*G$5/(1+$A7)^DCF!$K$13)/1000} -> 9.3884588 | H7: {=(SUMPRODUCT(DCF!$D$9:$K$9, 1/(1+$A7)^DCF!$D$13:$K$13) + DCF!$K$8*H$5/(1+$A7)^DCF!$K$13)/1000} -> 10.197237
A8: 0.1035 | B8: {=(SUMPRODUCT(DCF!$D$9:$K$9, 1/(1+$A8)^DCF!$D$13:$K$13) + DCF!$K$8*B$5/(1+$A8)^DCF!$K$13)/1000} -> 5.189326 | C8: {=(SUMPRODUCT(DCF!$D$9:$K$9, 1/(1+$A8)^DCF!$D$13:$K$13) + DCF!$K$8*C$5/(1+$A8)^DCF!$K$13)/1000} -> 5.9710208 | D8: {=(SUMPRODUCT(DCF!$D$9:$K$9, 1/(1+$A8)^DCF!$D$13:$K$13) + DCF!$K$8*D$5/(1+$A8)^DCF!$K$13)/1000} -> 6.7527155 | E8: {=(SUMPRODUCT(DCF!$D$9:$K$9, 1/(1+$A8)^DCF!$D$13:$K$13) + DCF!$K$8*E$5/(1+$A8)^DCF!$K$13)/1000} -> 7.5344102 | F8: {=(SUMPRODUCT(DCF!$D$9:$K$9, 1/(1+$A8)^DCF!$D$13:$K$13) + DCF!$K$8*F$5/(1+$A8)^DCF!$K$13)/1000} -> 8.316105 | G8: {=(SUMPRODUCT(DCF!$D$9:$K$9, 1/(1+$A8)^DCF!$D$13:$K$13) + DCF!$K$8*G$5/(1+$A8)^DCF!$K$13)/1000} -> 9.0977997 | H8: {=(SUMPRODUCT(DCF!$D$9:$K$9, 1/(1+$A8)^DCF!$D$13:$K$13) + DCF!$K$8*H$5/(1+$A8)^DCF!$K$13)/1000} -> 9.8794944
A9: 0.1085 | B9: {=(SUMPRODUCT(DCF!$D$9:$K$9, 1/(1+$A9)^DCF!$D$13:$K$13) + DCF!$K$8*B$5/(1+$A9)^DCF!$K$13)/1000} -> 5.0396098 | C9: {=(SUMPRODUCT(DCF!$D$9:$K$9, 1/(1+$A9)^DCF!$D$13:$K$13) + DCF!$K$8*C$5/(1+$A9)^DCF!$K$13)/1000} -> 5.7952447 | D9: {=(SUMPRODUCT(DCF!$D$9:$K$9, 1/(1+$A9)^DCF!$D$13:$K$13) + DCF!$K$8*D$5/(1+$A9)^DCF!$K$13)/1000} -> 6.5508795 | E9: {=(SUMPRODUCT(DCF!$D$9:$K$9, 1/(1+$A9)^DCF!$D$13:$K$13) + DCF!$K$8*E$5/(1+$A9)^DCF!$K$13)/1000} -> 7.3065144 | F9: {=(SUMPRODUCT(DCF!$D$9:$K$9, 1/(1+$A9)^DCF!$D$13:$K$13) + DCF!$K$8*F$5/(1+$A9)^DCF!$K$13)/1000} -> 8.0621493 | G9: {=(SUMPRODUCT(DCF!$D$9:$K$9, 1/(1+$A9)^DCF!$D$13:$K$13) + DCF!$K$8*G$5/(1+$A9)^DCF!$K$13)/1000} -> 8.8177841 | H9: {=(SUMPRODUCT(DCF!$D$9:$K$9, 1/(1+$A9)^DCF!$D$13:$K$13) + DCF!$K$8*H$5/(1+$A9)^DCF!$K$13)/1000} -> 9.573419
A10: 0.1135 | B10: {=(SUMPRODUCT(DCF!$D$9:$K$9, 1/(1+$A10)^DCF!$D$13:$K$13) + DCF!$K$8*B$5/(1+$A10)^DCF!$K$13)/1000} -> 4.8951963 | C10: {=(SUMPRODUCT(DCF!$D$9:$K$9, 1/(1+$A10)^DCF!$D$13:$K$13) + DCF!$K$8*C$5/(1+$A10)^DCF!$K$13)/1000} -> 5.6257516 | D10: {=(SUMPRODUCT(DCF!$D$9:$K$9, 1/(1+$A10)^DCF!$D$13:$K$13) + DCF!$K$8*D$5/(1+$A10)^DCF!$K$13)/1000} -> 6.3563068 | E10: {=(SUMPRODUCT(DCF!$D$9:$K$9, 1/(1+$A10)^DCF!$D$13:$K$13) + DCF!$K$8*E$5/(1+$A10)^DCF!$K$13)/1000} -> 7.086862 | F10: {=(SUMPRODUCT(DCF!$D$9:$K$9, 1/(1+$A10)^DCF!$D$13:$K$13) + DCF!$K$8*F$5/(1+$A10)^DCF!$K$13)/1000} -> 7.8174173 | G10: {=(SUMPRODUCT(DCF!$D$9:$K$9, 1/(1+$A10)^DCF!$D$13:$K$13) + DCF!$K$8*G$5/(1+$A10)^DCF!$K$13)/1000} -> 8.5479725 | H10: {=(SUMPRODUCT(DCF!$D$9:$K$9, 1/(1+$A10)^DCF!$D$13:$K$13) + DCF!$K$8*H$5/(1+$A10)^DCF!$K$13)/1000} -> 9.2785277
A11: 0.1185 | B11: {=(SUMPRODUCT(DCF!$D$9:$K$9, 1/(1+$A11)^DCF!$D$13:$K$13) + DCF!$K$8*B$5/(1+$A11)^DCF!$K$13)/1000} -> 4.7558712 | C11: {=(SUMPRODUCT(DCF!$D$9:$K$9, 1/(1+$A11)^DCF!$D$13:$K$13) + DCF!$K$8*C$5/(1+$A11)^DCF!$K$13)/1000} -> 5.462286 | D11: {=(SUMPRODUCT(DCF!$D$9:$K$9, 1/(1+$A11)^DCF!$D$13:$K$13) + DCF!$K$8*D$5/(1+$A11)^DCF!$K$13)/1000} -> 6.1687009 | E11: {=(SUMPRODUCT(DCF!$D$9:$K$9, 1/(1+$A11)^DCF!$D$13:$K$13) + DCF!$K$8*E$5/(1+$A11)^DCF!$K$13)/1000} -> 6.8751157 | F11: {=(SUMPRODUCT(DCF!$D$9:$K$9, 1/(1+$A11)^DCF!$D$13:$K$13) + DCF!$K$8*F$5/(1+$A11)^DCF!$K$13)/1000} -> 7.5815305 | G11: {=(SUMPRODUCT(DCF!$D$9:$K$9, 1/(1+$A11)^DCF!$D$13:$K$13) + DCF!$K$8*G$5/(1+$A11)^DCF!$K$13)/1000} -> 8.2879453 | H11: {=(SUMPRODUCT(DCF!$D$9:$K$9, 1/(1+$A11)^DCF!$D$13:$K$13) + DCF!$K$8*H$5/(1+$A11)^DCF!$K$13)/1000} -> 8.9943602
A12: 0.1235 | B12: {=(SUMPRODUCT(DCF!$D$9:$K$9, 1/(1+$A12)^DCF!$D$13:$K$13) + DCF!$K$8*B$5/(1+$A12)^DCF!$K$13)/1000} -> 4.6214298 | C12: {=(SUMPRODUCT(DCF!$D$9:$K$9, 1/(1+$A12)^DCF!$D$13:$K$13) + DCF!$K$8*C$5/(1+$A12)^DCF!$K$13)/1000} -> 5.3046043 | D12: {=(SUMPRODUCT(DCF!$D$9:$K$9, 1/(1+$A12)^DCF!$D$13:$K$13) + DCF!$K$8*D$5/(1+$A12)^DCF!$K$13)/1000} -> 5.9877787 | E12: {=(SUMPRODUCT(DCF!$D$9:$K$9, 1/(1+$A12)^DCF!$D$13:$K$13) + DCF!$K$8*E$5/(1+$A12)^DCF!$K$13)/1000} -> 6.6709532 | F12: {=(SUMPRODUCT(DCF!$D$9:$K$9, 1/(1+$A12)^DCF!$D$13:$K$13) + DCF!$K$8*F$5/(1+$A12)^DCF!$K$13)/1000} -> 7.3541277 | G12: {=(SUMPRODUCT(DCF!$D$9:$K$9, 1/(1+$A12)^DCF!$D$13:$K$13) + DCF!$K$8*G$5/(1+$A12)^DCF!$K$13)/1000} -> 8.0373022 | H12: {=(SUMPRODUCT(DCF!$D$9:$K$9, 1/(1+$A12)^DCF!$D$13:$K$13) + DCF!$K$8*H$5/(1+$A12)^DCF!$K$13)/1000} -> 8.7204767
A15: Grid 2: WACC × Terminal Growth (Gordon Method) → Enterprise Value ($B)
A16: WACC ↓ / Terminal Growth → | B16: 0.015 | C16: 0.02 | D16: 0.025 | E16: 0.03 | F16: 0.035 | G16: 0.04 | H16: 0.045
A17: 0.0935 | B17: {=(SUMPRODUCT(DCF!$D$9:$K$9, 1/(1+$A17)^DCF!$D$13:$K$13) + DCF!$K$9*(1+B$16)/($A17-B$16)/(1+$A17)^DCF!$K$13)/1000} -> 8.0944357 | C17: {=(SUMPRODUCT(DCF!$D$9:$K$9, 1/(1+$A17)^DCF!$D$13:$K$13) + DCF!$K$9*(1+C$16)/($A17-C$16)/(1+$A17)^DCF!$K$13)/1000} -> 8.5295182 | D17: {=(SUMPRODUCT(DCF!$D$9:$K$9, 1/(1+$A17)^DCF!$D$13:$K$13) + DCF!$K$9*(1+D$16)/($A17-D$16)/(1+$A17)^DCF!$K$13)/1000} -> 9.0281163 | E17: {=(SUMPRODUCT(DCF!$D$9:$K$9, 1/(1+$A17)^DCF!$D$13:$K$13) + DCF!$K$9*(1+E$16)/($A17-E$16)/(1+$A17)^DCF!$K$13)/1000} -> 9.6052339 | F17: {=(SUMPRODUCT(DCF!$D$9:$K$9, 1/(1+$A17)^DCF!$D$13:$K$13) + DCF!$K$9*(1+F$16)/($A17-F$16)/(1+$A17)^DCF!$K$13)/1000} -> 10.281004 | G17: {=(SUMPRODUCT(DCF!$D$9:$K$9, 1/(1+$A17)^DCF!$D$13:$K$13) + DCF!$K$9*(1+G$16)/($A17-G$16)/(1+$A17)^DCF!$K$13)/1000} -> 11.083086 | H17: {=(SUMPRODUCT(DCF!$D$9:$K$9, 1/(1+$A17)^DCF!$D$13:$K$13) + DCF!$K$9*(1+H$16)/($A17-H$16)/(1+$A17)^DCF!$K$13)/1000} -> 12.050546
A18: 0.0985 | B18: {=(SUMPRODUCT(DCF!$D$9:$K$9, 1/(1+$A18)^DCF!$D$13:$K$13) + DCF!$K$9*(1+B$16)/($A18-B$16)/(1+$A18)^DCF!$K$13)/1000} -> 7.5028228 | C18: {=(SUMPRODUCT(DCF!$D$9:$K$9, 1/(1+$A18)^DCF!$D$13:$K$13) + DCF!$K$9*(1+C$16)/($A18-C$16)/(1+$A18)^DCF!$K$13)/1000} -> 7.8746097 | D18: {=(SUMPRODUCT(DCF!$D$9:$K$9, 1/(1+$A18)^DCF!$D$13:$K$13) + DCF!$K$9*(1+D$16)/($A18-D$16)/(1+$A18)^DCF!$K$13)/1000} -> 8.29698 | E18: {=(SUMPRODUCT(DCF!$D$9:$K$9, 1/(1+$A18)^DCF!$D$13:$K$13) + DCF!$K$9*(1+E$16)/($A18-E$16)/(1+$A18)^DCF!$K$13)/1000} -> 8.7810101 | F18: {=(SUMPRODUCT(DCF!$D$9:$K$9, 1/(1+$A18)^DCF!$D$13:$K$13) + DCF!$K$9*(1+F$16)/($A18-F$16)/(1+$A18)^DCF!$K$13)/1000} -> 9.3412654 | G18: {=(SUMPRODUCT(DCF!$D$9:$K$9, 1/(1+$A18)^DCF!$D$13:$K$13) + DCF!$K$9*(1+G$16)/($A18-G$16)/(1+$A18)^DCF!$K$13)/1000} -> 9.9972909 | H18: {=(SUMPRODUCT(DCF!$D$9:$K$9, 1/(1+$A18)^DCF!$D$13:$K$13) + DCF!$K$9*(1+H$16)/($A18-H$16)/(1+$A18)^DCF!$K$13)/1000} -> 10.775938
A19: 0.1035 | B19: {=(SUMPRODUCT(DCF!$D$9:$K$9, 1/(1+$A19)^DCF!$D$13:$K$13) + DCF!$K$9*(1+B$16)/($A19-B$16)/(1+$A19)^DCF!$K$13)/1000} -> 6.9808008 | C19: {=(SUMPRODUCT(DCF!$D$9:$K$9, 1/(1+$A19)^DCF!$D$13:$K$13) + DCF!$K$9*(1+C$16)/($A19-C$16)/(1+$A19)^DCF!$K$13)/1000} -> 7.3009856 | D19: {=(SUMPRODUCT(DCF!$D$9:$K$9, 1/(1+$A19)^DCF!$D$13:$K$13) + DCF!$K$9*(1+D$16)/($A19-D$16)/(1+$A19)^DCF!$K$13)/1000} -> 7.6619583 | E19: {=(SUMPRODUCT(DCF!$D$9:$K$9, 1/(1+$A19)^DCF!$D$13:$K$13) + DCF!$K$9*(1+E$16)/($A19-E$16)/(1+$A19)^DCF!$K$13)/1000} -> 8.0720429 | F19: {=(SUMPRODUCT(DCF!$D$9:$K$9, 1/(1+$A19)^DCF!$D$13:$K$13) + DCF!$K$9*(1+F$16)/($A19-F$16)/(1+$A19)^DCF!$K$13)/1000} -> 8.5419939 | G19: {=(SUMPRODUCT(DCF!$D$9:$K$9, 1/(1+$A19)^DCF!$D$13:$K$13) + DCF!$K$9*(1+G$16)/($A19-G$16)/(1+$A19)^DCF!$K$13)/1000} -> 9.085953 | H19: {=(SUMPRODUCT(DCF!$D$9:$K$9, 1/(1+$A19)^DCF!$D$13:$K$13) + DCF!$K$9*(1+H$16)/($A19-H$16)/(1+$A19)^DCF!$K$13)/1000} -> 9.7228965
A20: 0.1085 | B20: {=(SUMPRODUCT(DCF!$D$9:$K$9, 1/(1+$A20)^DCF!$D$13:$K$13) + DCF!$K$9*(1+B$16)/($A20-B$16)/(1+$A20)^DCF!$K$13)/1000} -> 6.5171208 | C20: {=(SUMPRODUCT(DCF!$D$9:$K$9, 1/(1+$A20)^DCF!$D$13:$K$13) + DCF!$K$9*(1+C$16)/($A20-C$16)/(1+$A20)^DCF!$K$13)/1000} -> 6.7947811 | D20: {=(SUMPRODUCT(DCF!$D$9:$K$9, 1/(1+$A20)^DCF!$D$13:$K$13) + DCF!$K$9*(1+D$16)/($A20-D$16)/(1+$A20)^DCF!$K$13)/1000} -> 7.1056941 | E20: {=(SUMPRODUCT(DCF!$D$9:$K$9, 1/(1+$A20)^DCF!$D$13:$K$13) + DCF!$K$9*(1+E$16)/($A20-E$16)/(1+$A20)^DCF!$K$13)/1000} -> 7.4562139 | F20: {=(SUMPRODUCT(DCF!$D$9:$K$9, 1/(1+$A20)^DCF!$D$13:$K$13) + DCF!$K$9*(1+F$16)/($A20-F$16)/(1+$A20)^DCF!$K$13)/1000} -> 7.8544235 | G20: {=(SUMPRODUCT(DCF!$D$9:$K$9, 1/(1+$A20)^DCF!$D$13:$K$13) + DCF!$K$9*(1+G$16)/($A20-G$16)/(1+$A20)^DCF!$K$13)/1000} -> 8.3107658 | H20: {=(SUMPRODUCT(DCF!$D$9:$K$9, 1/(1+$A20)^DCF!$D$13:$K$13) + DCF!$K$9*(1+H$16)/($A20-H$16)/(1+$A20)^DCF!$K$13)/1000} -> 8.838973
A21: 0.1135 | B21: {=(SUMPRODUCT(DCF!$D$9:$K$9, 1/(1+$A21)^DCF!$D$13:$K$13) + DCF!$K$9*(1+B$16)/($A21-B$16)/(1+$A21)^DCF!$K$13)/1000} -> 6.1028212 | C21: {=(SUMPRODUCT(DCF!$D$9:$K$9, 1/(1+$A21)^DCF!$D$13:$K$13) + DCF!$K$9*(1+C$16)/($A21-C$16)/(1+$A21)^DCF!$K$13)/1000} -> 6.3451005 | D21: {=(SUMPRODUCT(DCF!$D$9:$K$9, 1/(1+$A21)^DCF!$D$13:$K$13) + DCF!$K$9*(1+D$16)/($A21-D$16)/(1+$A21)^DCF!$K$13)/1000} -> 6.6147561 | E21: {=(SUMPRODUCT(DCF!$D$9:$K$9, 1/(1+$A21)^DCF!$D$13:$K$13) + DCF!$K$9*(1+E$16)/($A21-E$16)/(1+$A21)^DCF!$K$13)/1000} -> 6.9167057 | F21: {=(SUMPRODUCT(DCF!$D$9:$K$9, 1/(1+$A21)^DCF!$D$13:$K$13) + DCF!$K$9*(1+F$16)/($A21-F$16)/(1+$A21)^DCF!$K$13)/1000} -> 7.2571203 | G21: {=(SUMPRODUCT(DCF!$D$9:$K$9, 1/(1+$A21)^DCF!$D$13:$K$13) + DCF!$K$9*(1+G$16)/($A21-G$16)/(1+$A21)^DCF!$K$13)/1000} -> 7.6438497 | H21: {=(SUMPRODUCT(DCF!$D$9:$K$9, 1/(1+$A21)^DCF!$D$13:$K$13) + DCF!$K$9*(1+H$16)/($A21-H$16)/(1+$A21)^DCF!$K$13)/1000} -> 8.087036
A22: 0.1185 | B22: {=(SUMPRODUCT(DCF!$D$9:$K$9, 1/(1+$A22)^DCF!$D$13:$K$13) + DCF!$K$9*(1+B$16)/($A22-B$16)/(1+$A22)^DCF!$K$13)/1000} -> 5.7306745 | C22: {=(SUMPRODUCT(DCF!$D$9:$K$9, 1/(1+$A22)^DCF!$D$13:$K$13) + DCF!$K$9*(1+C$16)/($A22-C$16)/(1+$A22)^DCF!$K$13)/1000} -> 5.9432632 | D22: {=(SUMPRODUCT(DCF!$D$9:$K$9, 1/(1+$A22)^DCF!$D$13:$K$13) + DCF!$K$9*(1+D$16)/($A22-D$16)/(1+$A22)^DCF!$K$13)/1000} -> 6.1785887 | E22: {=(SUMPRODUCT(DCF!$D$9:$K$9, 1/(1+$A22)^DCF!$D$13:$K$13) + DCF!$K$9*(1+E$16)/($A22-E$16)/(1+$A22)^DCF!$K$13)/1000} -> 6.4405046 | F22: {=(SUMPRODUCT(DCF!$D$9:$K$9, 1/(1+$A22)^DCF!$D$13:$K$13) + DCF!$K$9*(1+F$16)/($A22-F$16)/(1+$A22)^DCF!$K$13)/1000} -> 6.7337877 | G22: {=(SUMPRODUCT(DCF!$D$9:$K$9, 1/(1+$A22)^DCF!$D$13:$K$13) + DCF!$K$9*(1+G$16)/($A22-G$16)/(1+$A22)^DCF!$K$13)/1000} -> 7.0644317 | H22: {=(SUMPRODUCT(DCF!$D$9:$K$9, 1/(1+$A22)^DCF!$D$13:$K$13) + DCF!$K$9*(1+H$16)/($A22-H$16)/(1+$A22)^DCF!$K$13)/1000} -> 7.4400612
A23: 0.1235 | B23: {=(SUMPRODUCT(DCF!$D$9:$K$9, 1/(1+$A23)^DCF!$D$13:$K$13) + DCF!$K$9*(1+B$16)/($A23-B$16)/(1+$A23)^DCF!$K$13)/1000} -> 5.3947883 | C23: {=(SUMPRODUCT(DCF!$D$9:$K$9, 1/(1+$A23)^DCF!$D$13:$K$13) + DCF!$K$9*(1+C$16)/($A23-C$16)/(1+$A23)^DCF!$K$13)/1000} -> 5.5822686 | D23: {=(SUMPRODUCT(DCF!$D$9:$K$9, 1/(1+$A23)^DCF!$D$13:$K$13) + DCF!$K$9*(1+D$16)/($A23-D$16)/(1+$A23)^DCF!$K$13)/1000} -> 5.7887824 | E23: {=(SUMPRODUCT(DCF!$D$9:$K$9, 1/(1+$A23)^DCF!$D$13:$K$13) + DCF!$K$9*(1+E$16)/($A23-E$16)/(1+$A23)^DCF!$K$13)/1000} -> 6.0173833 | F23: {=(SUMPRODUCT(DCF!$D$9:$K$9, 1/(1+$A23)^DCF!$D$13:$K$13) + DCF!$K$9*(1+F$16)/($A23-F$16)/(1+$A23)^DCF!$K$13)/1000} -> 6.2718147 | G23: {=(SUMPRODUCT(DCF!$D$9:$K$9, 1/(1+$A23)^DCF!$D$13:$K$13) + DCF!$K$9*(1+G$16)/($A23-G$16)/(1+$A23)^DCF!$K$13)/1000} -> 6.556717 | H23: {=(SUMPRODUCT(DCF!$D$9:$K$9, 1/(1+$A23)^DCF!$D$13:$K$13) + DCF!$K$9*(1+H$16)/($A23-H$16)/(1+$A23)^DCF!$K$13)/1000} -> 6.8779126
A27: Summary — Equity Value per Share Range
A28: Method | B28: Low EV ($B) | C28: Base EV ($B) | D28: High EV ($B) | E28: Per Share Range ($)
A29: Grid 1: WACC × Exit Multiple | B29: =MIN(B6:H12) -> 4.6214298 | C29: =E9 -> 7.3065144 | D29: =MAX(B6:H12) -> 10.527152 | E29: =ROUND((B29*1000-Assumptions!$F$62+Assumptions!$F$63)/Assumptions!$F$55,1) & " — " & ROUND((D29*1000-Assumptions!$F$62+Assumptions!$F$63)/Assumptions!$F$55,1) -> 13 — 27.4
A30: Grid 2: WACC × Terminal Growth (Gordon) | B30: =MIN(B17:H23) -> 5.3947883 | C30: =E20 -> 7.4562139 | D30: =MAX(B17:H23) -> 12.050546 | E30: =ROUND((B30*1000-Assumptions!$F$62+Assumptions!$F$63)/Assumptions!$F$55,1) & " — " & ROUND((D30*1000-Assumptions!$F$62+Assumptions!$F$63)/Assumptions!$F$55,1) -> 14.8 — 31.1
A33: Series G mark $10.1B post-money = $24.63 implied per share. Base DCF base case = $19.50 (-20.8% discount to Series G).

Sheet Checks
A1: WHOOP — Diagnostic Checks
A2: Automated integrity checks per methodology Sec 9. ANY red FAIL must be resolved before output is trusted.
A4: Check | B4: Computed | C4: Threshold | D4: Status | E4: Notes
A5: 1. Members × ARPU ≈ Revenue (2025) | B5: =ABS(Members!D35*ARPU!D10/'Revenue Build'!D20-1) -> 0 | C5: <5% | D5: =IF(B5<0.05,"PASS","FAIL") -> PASS | E5: Avg members × blended ARPU should reconcile to consumer revenue
A6: 2. S&M coverage: Members.S&M$ ≤ P&L.S&M (2026) | B6: =ABS('P&L'!E23-Members!E47) -> 0 | C6: <$1M | D6: =IF(B6<1,"PASS","FAIL") -> PASS | E6: P&L S&M = Members.row 46 (single source); should match exactly
A7: 3. Comp bucket weights sum = 100% | B7: =Assumptions!$F$87 -> 1 | C7: =100% | D7: =IF(ABS(B7-1)<0.001,"PASS","FAIL") -> PASS | E7: B1+B2+B3 weights must total 1.0
A8: 4. TV < 75% of total EV (DCF) | B8: =DCF!C27 -> 0.72395859 | C8: <75% | D8: =IF(B8<0.75,"PASS",IF(B8<0.8,"WARN","FAIL")) -> PASS | E8: Methodology Sec 4: TV >75% means explicit forecast doing too little
A9: 5. Exit Multiple ↔ Gordon TV divergence | B9: =DCF!C24 -> 0.028543677 | C9: <25% | D9: =IF(B9<0.25,"PASS",IF(B9<0.35,"WARN","FAIL")) -> PASS | E9: Methodology Sec 4: divergence >25% means assumption inconsistency
A10: 6. Real options probability sum = 100% | B10: =Assumptions!$F$161 -> 1 | C10: =100% | D10: =IF(ABS(B10-1)<0.001,"PASS","FAIL") -> PASS | E10: Materialize + fail must = 1.0 (binary gate, by construction). Updated post-RO redesign — was cluster sum (success/mixed/failure).
A11: 7. WACC > Perpetuity growth (Gordon validity) | B11: =Assumptions!$F$74-Assumptions!$F$80 -> 0.07845 | C11: >0% | D11: =IF(B11>0,"PASS","FAIL") -> PASS | E11: Required for Gordon Growth perpetuity to converge; safer if >3pp
A12: 8. Gross adds vs historical peak (any year) | B12: =MAX(Members!E31:L31)/Members!D31 -> 1.2139625 | C12: <2.0x | D12: =IF(B12<2,"PASS",IF(B12<3,"WARN","FAIL")) -> PASS | E12: Methodology Sec 9: peak gross adds shouldn't exceed 2x base year
A13: 9. Rule of 40 ≥ 20 by Phase 3 | B13: =MIN(FCF!J22:L22) -> 41.267704 | C13: ≥20 | D13: =IF(B13>=20,"PASS","FAIL") -> PASS | E13: Min Rule of 40 across 2031-2033 forecast
A14: 10. ARPU Justification consistency | B14: =ARPU!D36 -> ✓ within ±10% of justification | C14: ✓ or ⚠ | D14: =IF(LEFT(B14,1)="✓","PASS","WARN") -> PASS | E14: Verifies blended ARPU anchor is within ±10% of bottom-up justification
A15: Summary
A16: Total checks | B16: =COUNTA(D5:D14) -> 10
A17: Passing | B17: =COUNTIF(D5:D14,"PASS") -> 10
A18: Warning | B18: =COUNTIF(D5:D14,"WARN") -> 0
A19: Failing | B19: =COUNTIF(D5:D14,"FAIL") -> 0
A20: Overall | B20: =IF(B19>0,"FAIL",IF(B18>0,"WARN","PASS")) -> PASS

Sheet Sources
A1: Research File Index
A3: File | B3: Contents | C3: Session
A4: research/whoop-research-brief.md | B4: Structured research brief | C4: S0
A5: research/whoop-pitchbook-data.md | B5: Pitchbook: cap table, funding, financials | C5: S1
A6: research/whoop-capiq-data.md | B6: Cap IQ: dilution waterfall, investors | C6: S1
A7: research/oura-pitchbook-data.md | B7: Oura private comp profile ($11B) | C7: S1
A8: research/peloton-10k-analysis.md | B8: Peloton deep dive (revenue, margins, subs) | C8: S1
A9: research/web-research-sweep.md | B9: Market data, Forge, Garmin, Strava | C9: S1
A10: research/revenue-bookings-reconciliation.md | B10: $1.1B bookings vs revenue, ARPU, churn grids | C10: S1
A11: research/investor-deep-research.md | B11: Series G investor analysis | C11: S1
A12: research/stress-test-international-revenue.md | B12: 60% intl claim verification | C12: S1
A13: research/stress-test-revenue-reconciliation.md | B13: Revenue stress test (base: $650M) | C13: S1
A14: research/comp-dexcom-dxcm.md | B14: Dexcom 10-K (5yr financials) | C14: S2
... A26: research/precedent-transactions.md | B26: 14 deals, 3-bucket M&A analysis | C26: S2
A28: Web Sources (this build)
A29: Source | B29: Used For | C29: URL / Reference | D29: Date Accessed
A30: BusinessWire (WHOOP press release) | B30: Advanced Labs pricing: $199/$349/$599 (1/2/4 tests/yr); 350K waitlist on launch | C30: businesswire.com/news/home/20250930178710/ | D30: Sept 30, 2025 launch
A31: Boston Globe | B31: Women's blood test add-on $299; 150% YoY women membership growth; staff +75% | C31: bostonglobe.com/2026/03/10/business/whoop-299-blood-testing-service-women/ | D31: 46092
A32: WHOOP Membership page | B32: Tier pricing: One ~$199, Peak ~$239-279, Life ~$359; BP & Healthspan bundled in Peak/Life | C32: whoop.com/us/en/membership/ | D32: 46113
A33: WHOOP BP Insights page | B33: BP Insights bundled in Peak & Life (NOT separate paid feature) | C33: whoop.com/us/en/thelocker/blood-pressure-insights/ | D33: 46113
A34: Bloomberg | B34: May 2025 hardware launch: WHOOP 5.0 + WHOOP MG (medical grade); subscription from $199 | C34: bloomberg.com/news/features/2025-05-08/review-whoop-5-0-whoop-mg | D34: 45785
A35: TechCrunch | B35: Function Health $500/yr quarterly (comp price point); Fountain Life $20K/yr | C35: techcrunch.com/2025/09/30/whoop-opens-its-blood-testing-service/ | D35: 45930

Sheet CalibrationLog
A1: WHOOP Valuation — Calibration & Open Items Log
A2: Items deferred for next session. Each is non-blocking but should be addressed before relying on numbers for IC/memo. Sorted by priority.
A4: Tab | B4: Cell / Area | C4: Issue | D4: Suggested fix | E4: Priority | F4: Status
A5: DCF | B5: C30 | C5: TV divergence 55% (Exit Mult $16.1B vs Gordon $9.1B); methodology threshold 25% | D5: Lower exit mult to ~3.0x for Gordon equivalence, OR accept divergence as bull bias on terminal multiple compression | E5: High | F5: Open
A6: DCF | B6: C33 | C6: TV is 85% of total EV; methodology threshold 75%; explicit forecast doing only 15% of work | D6: Tighten R&D/G&A tapers (raises FCF in forecast period), OR extend horizon from 8 to 10 years | E6: High | F6: Open
A7: P&L | B7: L31 | C7: Margin tapers calibrated against bucket-3 peer benchmarks. R&D scenarios spread (Bear 12% / Base 15% / Bull 18%) reflect platform thesis. G&A 13/11/9 per Dexcom/ResMed anchors. SBC restructured: now interpolates from F47 (current) to F48 (terminal), 14%→8% Base. Terminal EBITDA: 36% → 33%. | D7: DONE — Assumptions C40/D40/E40 (R&D), C46/D46/E46 (G&A), C47-E47 (SBC current), C48-E48 (SBC terminal, NEW row inserted). P&L row 26 SBC formula updated to interpolate. | E7: Done | F7: RESOLVED
A8: P&L | B8: D38 | C8: Interest income wired — prior-yr cash × yield (Assumptions F66, 3.5% base). 2026-2033 NI uplift ~$300M cumulative. Non-circular: does NOT flow into UFCF. | D8: DONE — P&L D38:L38 wired to WC & Cash row 32 × Assumptions F66 | E8: Done | F8: RESOLVED
A9: P&L | B9: F31 | C9: 2027 EBITDA margin dips 22→12% from gross adds bulge (1.24M units → hardware COGS spike) | D9: Smooth Members E50:F50 to even gross adds across Phase 1, OR accept as Phase 1 deployment shape | E9: Medium | F9: Open
A10: P&L | B10: L23 | C10: S&M as % current revenue runs 16-20% vs methodology stated 30% | D10: Architecture-driven gap from prior-yr-rev basis. Either restate methodology, OR raise Members S&M phase % inputs | E10: Medium | F10: Open
A11: P&L | B11: D40 | C11: NOL carryforward wired — P&L rows 44-48. Begin/Add/Util/End schedule with 80% TCJA utilization cap. Self-balancing: any future losses auto-flow to NOL pool. | D11: DONE — P&L D40:L40 tax formula updated to MAX(0, Pretax − NOL_Util) × 23%. 2026/2027 NI uplift modest (~$14M, $7M) at current pretax. | E11: Done | F11: RESOLVED
A12: Revenue Build | B12: Row 19 | C12: $528M 2025 revenue vs $650M methodology target; gap is Unite B2B + Coach | D12: Add Unite B2B as separate revenue line on Revenue Build (Path C). $80-120M anchor. | E12: Medium | F12: Open
A13: ARPU | B13: D34 | C13: Derived ARPU $278 vs methodology anchor $338 (-17.7% gap) | D13: Largely resolved by Unite B2B path above. Revisit anchor language in methodology after. | E13: Low | F13: Linked
A14: FCF | B14: L17 | C14: FCF margin 19% in 2033, ~5pp below methodology terminal prior of 25-28% | D14: Will resolve when EBITDA tapers tightened (linked to L31). Or lower CapEx % from 4% to 3%. | E14: Low | F14: Linked
A16: Open Tabs / Builds Pending
A17: Balance Sheet | C17: Not yet built. Unlocks interest income wiring, NWC validation, cash build through forecast. | E17: Next
A18: Sensitivity | C18: Three grids built and live: WACC × Exit Mult, WACC × Terminal Growth (Gordon), Beta × CSRP → EV. Per-share range $14.8-33.7 across method combinations. | E18: Done | F18: RESOLVED
A19: Football Field | C19: Multi-method synthesis live with chart visualization. 5 methods wired to live sources. Weighted avg $8.6B / $22.75 per share, ~14.5% below Series G. Range bar chart added at A29 helper table; Series G $10.1B reference line overlay. Methods range $4.4B (forward comps) to $14.0B (IPO range). | D19: DONE — Football Field tab fully wired. All cells formula-driven from DCF / Sensitivity / Comps / Assumptions / RealOptions. | E19: Done | F19: RESOLVED
A20: Comps | C20: Three-bucket framework wired. Per-comp data placeholder (verify vs SEC/Bloomberg). Bucket summary stats (median + range), implied valuation table by scenario, dual back-solve (naive vs growth-adjusted) all live. Implied EVs: Bear $4.7B, Base $5.4B, Bull $6.3B vs Series G $10.1B. | D20: DONE — Comps tab fully wired. Data placeholder; refresh with current trading multiples before relying on output. | E20: Done | F20: WIRED (data needs refresh)
A21: Precedents | C21: Tab exists; needs deals populated per Assumptions Sec 8. | E21: Later
A22: ΔNWC | B22: FCF row 15 | C22: FCF tab now uses detailed WC schedule (was 8% plug). DCF EV +$813M to $9.54B; per share +$1.98 to $24.95. | D22: DONE — FCF!D15:L15 wired to 'WC & Cash'!D25:L25 | E22: High | F22: RESOLVED
A23: Framing | B23: Cover B56:B58, DCF A55 | C23: Discussed and decided: bucket-3 weight is expressed via 4.5x exit multiple (50% compressed from B3 ~9x), NOT via P&L margin compression. Base case 33% terminal EBITDA reflects WHOOP's natural subscription economics if executed. Real options carry the bucket-3-becoming-true upside as separate value source. No double-counting risk verified. | D23: DONE — Framing documented on Cover B56:B58 and DCF A55. Base case held; options held. No further OpEx changes. | E23: Done | F23: RESOLVED
A24: Real Options | B24: RealOptions C5:D7 | C24: Cluster probabilities (18/45/37) and values ($5.5/$2.5/$0.75B) are methodology-anchored priors, NOT derived from research. Highest-leverage, lowest-rigor input. $2.4B option value swings $1.5-3.5B across reasonable probability ranges. The +18% premium of DCF+Options to Series G is sensitive to this judgment. | D24: Acknowledged in memo as judgment input. Notes added to RealOptions C5:D7 and A18:A22. No model change; flagged for memo discussion of sensitivity. | E24: Memo flag | F24: DOCUMENTED
