Workbook
Name Scenario: Assumptions!$B$3

Sheet Claude Log
A1: Turn | B1: Date | C1: User Request | D1: Action Taken | E1: Details | F1: Outcome
A2: 1 | B2: 46149 | C2: Continue Member Thesis full rebuild in Comps idiom (sections 2-11). | D2: Built Sections 2-11 from scratch with Comps style fingerprint applied throughout. Wiped sheet, rebuilt with calculator-panel anchors, navy banners, alt zebra rows, peach/blue/green lens tints, horizontal Lens C, composite span, trajectory build, cross-checks, Series G back-solve, key findings. | E2: Lens tints: A=peach #FCE4D6 (aggressive), B/C=blue #DDEBF7 (base), D=green #E2EFDA (disciplined floor). Math chain reproduces all prior values: B16=11.954 (Lens A), B17=11.209 (B), B18=10.625 (C), B19=8.379 (D), B20=10.917 (median), J93=10.918 (trajectory), B103=+0.06% (cross-check). New diagnostic: B112=15.03M Series G implied members (proxy), B113=+25.7% above Lens A ceiling. | F2: Member Thesis fully rebuilt: 11 sections, 125 rows. DCF unchanged ($17.89/sh). Memo-ready. Awaiting user review.
A3: 2 | B3: 46149 | C3: Get sizes equivalent from Comps to Member Thesis — heights, zoom, columns don't look parallel. | D3: Read actual Comps column widths + row heights via Office.js. Decoded the 4-tier row height pattern (title 28pt / subtitle 36pt / banners 22pt / intros 30pt / body 15pt). Applied Comps-equivalent sizing to Member Thesis. Also fixed broken §2 Convergence formulas (B16:B19 were empty) and downstream Assumptions!F179 reference (was pointing at obsolete B11, now B20). | E3: Comps col widths: A=320, B-F=95 uniform, J=380 (wide notes). Member Thesis adapted: A=320, B=95, C/D=75, E/G/I/K=160 (Lens C horizontal blocks), H/L=15 gutters, M=380 (mirrors Comps J wide notes). Row tiers: 28/36/22/30/22/15. Wire-ups: B16=B30, B17=B43, B18=B67, B19=B78. Repointed Assumptions!F179 from B11 to B20. | F3: Sheets now parallel in size rhythm. Math chain restored: B20=10.917M lens median, F179=+0.06% triangulation, DCF $17.89/sh.
A4: 3 | B4: 46149 | C4: Build probability-weighted DCF capability: add ProbWeighted scenario as 4th option that weights 16 high-leverage inputs at the input level (P_Bear×Bear + P_Base×Base + P_Bull×Bull) rather than at scenario level, to avoid joint-extreme overstatement of tail dispersion. Also fix R79 Bear-branch bug. | D4: Unmerged Assumptions!A2:N2 (was a single merged cell blocking writes). Built probability weight cells in row 2 (B2-I2: P_Bear=20%, P_Base=50%, P_Bull=30%, sum check with red-fill conditional format if ≠1). Added ProbWeighted column at J for 16 inputs (R19-21 churn, R36-38 GMs, R73 CSRP, R79 terminal multiple, R169-176 MG1-MG8). Fixed R79 Bear-branch bug (was pointing to D79 Base 3.5x; now correctly C79 Bear 3.0x). Updated Active formulas on all 16 rows to handle ProbWeighted branch. Extended B3 dropdown to 4 options (Bear/Base/Bull/ProbWeighted). Added DCF tab guardrail block at rows 56-74: 4-scenario EV snapshot, scenario-weighted bookend (P-weighted DCF runs), and Jensen gap analysis. | E4: ProbWeighted formula: =$C$2*C[row]+$E$2*D[row]+$G$2*E[row] (absolute refs on weight cells). Active formula: =IF($B$3="Bear",C[r],IF($B$3="Bull",E[r],IF($B$3="ProbWeighted",J[r],D[r]))). 16 cells touched: F19,F20,F21,F36,F37,F38,F73,F79,F169-F176. R79 bug delta on Bear: -$191M EV (terminal multiple correctly 3.0x not 3.5x). Notes column at I preserved untouched — used column J instead to avoid disturbing audit trail. DCF guardrails snapshot is STATIC values — refresh manually if any of the 16 inputs change materially. | F4: All 4 scenarios run cleanly. Bear=$2.50B equity / $2.66B w/opts, Base=$7.34B / $8.28B, Bull=$19.88B / $22.60B, ProbWeighted=$7.96B / $8.90B (closes ~$626M of $1.82B gap to Series G). Major finding: Jensen gap = +$2.15B (29.7%) — DCF strongly convex in inputs. Scenario-weighted equity ($10.13B) hits Series G ($10.10B) almost exactly. Memo narrative now: input-weighted = central tendency under independence, scenario-weighted = E[EV] under perfect correlation, Series G sits between (partial correlation). The Jensen gap IS the optionality premium. R79 bug fix dropped Bear EV by $191M as expected. No #REF/#VALUE/#NAME errors introduced. F179 #DIV/0! preserved as expected (Member Thesis B20 blank during rebuild).
A5: 4 | B5: 46149 | C5: Push ProbWeighted scenario through entire memo — documentation, Cover, Football Field, Sensitivity, Scenarios, Checks. Style anchor to Comps + WACC Bottom-Up. Cover snapshot live on B3 toggle. | D5: (1) Assumptions Section 13 doc at row 181 (header banner, weights table linked to row 2, eligible-inputs table, Jensen caveat, refresh protocol). (2) Cover triangulation block at B63-C77 (live deps to DCF rows 60-65, Bear/Base/Bull/ProbWeighted/Scenario-Wtd/Series G/Jensen Gap; memo read narrative). (3) Cover B60/B61 narrative updated for new outputs. (4) Football Field K6 footnote on DCF row — NOT a new method line. (5) Sensitivity Section 5 prob-weight grid (5×5 P_Bear×P_Bull, base case yellow center, range $7.27-8.36B). (6) Scenarios fully populated: 6-method table with live links (DCF, Comps, Series G, IPO range), ProbWeighted column, Probability Weight Sensitivity block (3 schemes × Scenario-Wtd vs ProbWeighted vs Jensen Gap vs Series G). (7) Checks row 16: Check 12 weight-sum integrity, summary formulas expanded D5:D16. (8) Retried C3 description (had not persisted previously) — success on second attempt. | E5: Style fingerprint applied uniformly: Title bold 14-16pt white on #2F5496/#1F4E78; Subtitle italic 9-11pt #595959; Section banner bold 12pt white on #1F4E78; Table header bold 11pt black on #D9E1F2; Data 11pt black with #0000FF for inputs; Number formats $#,##0 / 0.0%/ 0.0"x" / +0.00;-0.00;0.00 deltas; Yellow #FFF2CC base case; #E2EFDA scenario-wtd; #FCE4D6 Jensen gap. Cover triangulation cells C67-C73 = LIVE formulas reading DCF!C60-C63 (single source of truth, refresh DCF and everything updates). DCF rows 60-63 themselves are STATIC — manually refreshed via validation pass. Sensitivity grid B67:F71 generated via Office.js auto-toggling P_Bear/P_Bull/P_Base across 5×5 grid (running ProbWeighted + recalc each time), base case D69 yellow. | F5: All decisions executed. ProbWeighted now end-to-end: docs (Assumptions row 181), Cover narrative + triangulation, Football Field footnote, Sensitivity grid, Scenarios full table, Checks weight-sum. Live test confirms toggling B3 to ProbWeighted updates Cover C34, C39 ($7.96B), C40 per-share. Memo narrative locked: input-weighted ($7.96B) = conservative anchor under input independence; scenario-weighted ($10.13B) = upper anchor at perfect correlation hits Series G almost exactly; Series G ($10.10B) reflects partial correlation; Jensen gap ($2.17B / +27%) IS the optionality premium. Checks 12/12 (11 PASS, 1 WARN). Open items flagged: Cover C43 has pre-existing label/formula mismatch (says 'Total Equity + Options' but formula reads DCF!C47 = EV+Options); RealOptions tab does not differentiate Base from ProbWeighted (both return $940M).
A6: 6 | B6: 46149 | C6: Full sweep audit of WHOOP valuation model — flag inconsistencies, errors, stale content, formatting issues across all 22 sheets. | D6: Read & analyzed all 22 sheets. Compiled prioritized issue list across 4 tiers: (1) real bugs, (2) documented-but-unfixed gaps in CalibrationLog, (3) cosmetic cruft/orphans, (4) structural improvements. | E6: Tier-1 bugs: Cover B43 label/formula mismatch (=DCF!C47 EV+Options $7,557 but labeled 'Total Equity + Options' — should be =DCF!C51 $8,276); Football Field B11 stale source text 'DCF C58' (live formula C52 OK); DCF!A3 stale TV diagnostic (says TV%EV 78%, Checks reports 73.2%). Tier-2: 6 Open items in CalibrationLog (TV divergence, TV%, S&M architecture, EBITDA dip, ARPU/Revenue gap, FCF margin). Tier-3 cruft: Assumptions D120/D121 ORPHANED but still drive F120/F121; A44='x' stray; Section 9 duplicate header A105+A155; Section 11 ARCHIVED; Cap Table A26:G35 waterfall unbuilt ('BUILD FORMULAS'); DCF rows 56-74 ProbWeighted snapshot static. Tier-4 structural: ProbWeighted only blends 8 Member Growth inputs not the 16 documented (Cover memo overstates scope); Cap Table key metrics (C18:C22) are text strings; Sources Web Sources section sparse. | F6: Audit complete, written report delivered to user. No model changes made — awaiting user direction on which fixes to prioritize.
A8: 7 | B8: 46149 | C8: Reviewed Sensitivity tab: validity of formulaic approach, accuracy of F54-F58 churn approximation tooltip, whether Grid 4 should recompute against live DCF, whether ±100bps WACC range is wide enough | D8: Audited Sensitivity tab against live DCF and Cover; identified two real reconciliation issues | E8: Confirmed: (1) formulaic SUMPRODUCT-based grids are correct architecture (live DCF would lock all cells to one scenario); (2) F54-F58 'directional only' tooltip is accurate — formula is linear approx scaled 5x, doesn't capture compounding; (3) Grid 4 should add EV column for IC relevance; (4) WACC range too narrow on the low side (Series G implied WACC <10.85% can't be reached). Found Cover!C43 still pulling DCF!C47 ($7,557M EV) but labeled 'Total Equity + Options' (should be DCF!C51 = $8,276M). Found Sensitivity!E9 = $9.51B EV at base, but DCF base equity = $7.34B — narrative in A2 says $10.23B equity, which doesn't tie to live DCF. | F8: Findings delivered to user with P1/P2/P3 prioritization. Awaiting decision on whether to execute fixes (Cover C43 ref change, Sensitivity A2 reconciliation, Grid 1 WACC range extension, Grid 4 EV column).
A9: 8 | B9: 46149 | C9: Approved Sensitivity tab rework: Grids stale with WACC/exit, Section 5 base wrong (showed 11.24M instead of 10.92M base members). Asked to rework Section 5 to match Grid 1-3 conventional (label-row + label-column + grid) format used by other grids. | D9: Full rebuild of Sensitivity rows 5-86: Grid 1/2/3/3b headers re-centered on live base values (WACC 11.59%, Exit Mult 3.5x, Term Growth 2.5%, Beta 0.83, CSRP 2%); base cells highlighted yellow. Grid 4 expanded with EV columns and live formulas. Section 5 (Probability Weighting + Members Lens) completely rebuilt as conventional grids with live DCF ties. | E9: Grid 1 (WACC×Exit Mult): A6:A12 = 10.09-13.09% step 50bps base 11.59% at A9 yellow; B5:H5 = 2.0-5.0x step 0.5x base 3.5x at E5 yellow. Grid 1 base E9 = $7.45B (pure Exit Mult). Grid 2 (WACC×Term Growth): A16:A22 same WACC; B16:F16 = 1.5-4.5% base 2.5% at D16. Grid 2 base D20 = $5.54B (pure Gordon). Grid 3 (Beta×CSRP top-down WACC) and Grid 3b (EV at top-down WACC × 3.5x exit): A28-A32 = 0.70/0.83/1.00/1.20/1.40 base 0.83; B27:F27 = 1.0-3.0% base 2% at D27. Grid 3 base D29 = 10.85% (top-down). Grid 3b base D37 = $7.80B EV. Grid 4 summary: B43:D43 EV columns (Low/Base/High by method using all three grid bases). Section 5 Block 1 (rows 63-72): 5×5 P_Bear×P_Bull grid using formula =$A66*DCF!$C$60+B$65*DCF!$C$62+(1-$A66-B$65)*DCF!$C$61. Base D68 = $10.13B = scenario-weighted bookend, NOT input-weighted $7.96B (caveat in A64). Section 5 Block 2 (rows 73-83): 6 rows of member counts centered on Members!L34=10.92M base at row 80 yellow (range 8.4-14.5M = -23%/+33% vs base). Block A: EV from FCF margin held constant. Block B: margin coupled ±60bps per ±10% members from base. Base D80=E80=$7,336M = DCF!C38. G80=$17.89/sh = DCF!C40. Coupled-bull G83=$25.22 (ONLY path > Series G $24.63). All formulas live: pull from DCF!K8/K9/K10/C32/C36/C37/C38/C39/C60/C61/C62 and Members!L34. Methodology footnote at A88. Section 5 narrative A85 reads live ($9.0/sh swing, coupling adds $2.04 at bull, subtracts $0.84 at floor). | F9: Sensitivity tab live and audit-clean. Tie-out: E9=$7.45B (Grid 1 Exit Mult @ live WACC/Mult), D20=$5.54B (Grid 2 Gordon), D37=$7.80B (Grid 3b top-down), D68=$10.13B (Block 1 scenario-weighted bookend), D80=$7,336M = DCF!C38, G80=$17.89=DCF!C40. Methodology gaps documented in caveats. Open: Cover!C43 label/formula mismatch (deferred, low priority). Awaiting next direction.
A10: 9 | B10: 46149 | C10: Reviewer (committee/IC) pushed back on RealOptions: Bull case is consumer-driven not healthcare-driven, comps multiple already prices implicit option premium (double-counting risk), and what if medical pathway doesn't materialize — ARPU defense needed. Asked to (a) add scenario-weighted line, (b) sensitivity grid scenario × probability weight, (c) memo sentences on three pushbacks, (d) elevate Bull timing logic, (e) hold multiple at 6x flat. | D10: Built scenario-weighted aggregation, sensitivity grid (Section 7), memo additions (Section 5b), and elevated Bull timing logic with explicit conditions. | E10: (1) Section 4 Scenario-weighted EV: B38 = =P_Bear*B31+P_Base*C31+P_Bull*D31 = $1,286M ($1.29B vs Base scenario $940M); C38 caveat explains two-layer probability is not double-counting (within-scenario P(materialize) at row 30 already weights by trigger probability; cross-scenario weights weight outcome distributions — they compound). (2) Section 7 Block A: per-scenario contribution decomposition Bear $33M/2.6%, Base $470M/36.6%, Bull $783M/60.9% (Bull dominates despite only 30% weight — reflects $2.6B Bull intrinsic value). (3) Section 7 Block B: 5×5 P_Bear×P_Bull grid centered on D97=$1,286M; floor max-bear=$874M, ceiling max-bull=$1,697M, range=$823M. P_Bull lever=$167M per 10pp, P_Bear lever=$39M per 10pp — Bull weight is dominant lever. Read narrative at A109 with live TEXT formulas reading B38, D97, B96/F98 floor/ceiling, B98/F96 corner cases. (4) Section 5b Pushback responses (rows 80-90): consumer-only Bull (clean separation — DCF runs consumer assumptions, option valued discretely, scenario-weighted EV adds them), implicit option premium ($220-440M estimated comps premium; recommend reading explicit option as standalone module — reader can subtract premium if they believe it's already priced; or keep $700-1,000M proves-in floor), ARPU defense ($338/yr blended consumer+B2B is intact regardless of medical materialization — only incremental medical-bill ARPU is at risk; Bear $164M residual = 15% prob × $1.07B intrinsic still positive). (5) Bull timing elevated (row 68 yellow callout): 4yr requires three conditions ALL to break right (CMS Innovation Center accelerates 7-10yr review, CPT code filing within 18 months, Abbott/Mayo co-published study by Y2). Probability of all three = 25% = P_Bull. 1 extra year = ~11% PV drag (multiplicative discount). (6) Multiple held at 6x flat per user direction. (7) Style: scenario-weighted line uses #E2EFDA mint. Block A and B narratives at A109 fully live. | F10: RealOptions tab now Series A: Section 4 dual reads (active scenario $940M Base + scenario-weighted $1,286M cross-scenario), Section 7 sensitivity grid live, Section 5b pushback responses memo-quality. Tie-outs: B38=$1,286M, D97=$1,286M, F98=$1,697M ceiling, B96=$874M floor. Awaiting next direction.

Sheet Cover
B3: WHOOP Inc.
A4: ARPU Simplification: Option B ($305 anchor) — bottom-up justified. See ARPU tab justification block. | B4: Private Company Valuation
B5: Investment Committee Memo — Supporting Model
B8: Company: | C8: WHOOP Inc.
B9: Ticker: | C9: Private (Pre-IPO)
B10: Last Round: | C10: Series G — $575M at $10.1B post-money (Mar 31, 2026)
B11: Model Date: | C11: April 16, 2026
B12: Analyst: | C12: Landon Brice
B13: Fiscal Year: | C13: Calendar Year (Jan-Dec)
B14: Currency: | C14: USD ($M unless noted)
B17: Valuation Methods:
B18: 1. Intrinsic DCF (scenario-based + real options)
B19: 2. Trading Comps (three-bucket framework)
B20: 3. Precedent Transactions
B21: 4. Last-Round Implied ($10.1B)
B22: 5. Implied IPO Trading Range (back-solved)
B25: Color Convention:
B26: Hard-coded input
B27: Formula / calculation
B28: Cross-sheet link
B29: Needs verification / FLAGGED_GAP
B32: Source Files:
B33: Valuation Summary (live, scenario-driven)
B34: Active Scenario | C34: =Assumptions!$B$3 -> Base
B36: Base DCF — Enterprise Value | C36: =DCF!C32 -> 6616.6418
B37: + Cash | C37: =DCF!C37 -> 729.51888
B38: − Debt | C38: =DCF!C36 -> -10
B39: = Equity Value | C39: =DCF!C38 -> 7336.1607
B40: Per Share (FD) | C40: =DCF!C40 -> 17.893075
B42: Real Options (Expected) | C42: =DCF!C46 -> 940.08677
B43: Total Equity + Options | C43: =DCF!C47 -> 7556.7286
B45: Series G Mark | C45: =DCF!C52 -> 10100
B46: Base DCF vs Series G | C46: =DCF!C53 -> -0.27364746
B47: DCF + Options vs Series G | C47: =DCF!C54 -> -0.18056956
B48: Football Field (multi-method synthesis)
B49: Weighted Average EV | C49: ='Football Field'!D16*1000 -> 7136.4713
B50: Per Share (FD) | C50: ='Football Field'!G16 -> 19.088954
B51: vs Series G | C51: ='Football Field'!D18 -> -0.29341868
B53: Model Integrity (Checks tab)
B54: Passing | C54: =Checks!B19 -> 11
B55: Warning | C55: =Checks!B20 -> 1
B56: Failing | C56: =Checks!B21 -> 0
B57: Overall | C57: =Checks!B22 -> WARN
B59: Framing Decision — Base Case vs Real Options
B60: Base DCF reflects WHOOP's subscription-driven unit economics if executed (terminal GM ~80%, FCF margin 27%). Real options are valued separately as a single binary-gate decision tree on the healthcare reimbursement pathway: probability of CMS materialization × incremental eligible-member revenue × medtech multiple × discount factor. Probability range 15-25% reflects iRhythm precedent (7+ year consumer→medical pathway) plus WHOOP-specific signals (CMS Innovation Center selection Apr 2026, Abbott + Mayo Series G investors). NEW: Probability-weighted scenario added to triangulate Bear/Base/Bull at the input level (ProbWeighted) alongside scenario level (P·DCF) — see triangulation block below.
B61: Memo conclusion: Base DCF $7.34B equity (-27% vs Series G $10.10B). DCF + healthcare option $8.28B (-18%). ProbWeighted (input-level, P_Bear 20% / P_Base 50% / P_Bull 30%) $7.96B equity (-21%) — the conservative anchor under input independence. Scenario-weighted (P·DCF, same weights) $10.13B equity — hits the Series G mark almost exactly, telling us investors are pricing the model under perfect cross-input correlation. The Jensen gap (~$2.2B, +27%) is the joint-optionality premium. Series G defensible only if (a) healthcare materializes (15-25% prob), AND (b) bull case drivers correlate jointly across member growth, ARPU, churn, and multiple expansion.
B63: Probability-Weighting Triangulation (input-level vs scenario-level)
B64: Two ways to combine Bear/Base/Bull into a single number. Input-level (ProbWeighted) is the central tendency under input independence; scenario-level (P·DCF(scenario) summed) is E[EV] under perfect cross-input correlation. The gap = the optionality premium investors price.
B66: Method | C66: Equity ($M)
B67: Bear (full bear scenario) | C67: =DCF!C60 -> 2504.21
B68: Base (full base scenario) | C68: =DCF!C61 -> 7336.16
B69: Bull (full bull scenario) | C69: =DCF!C62 -> 19882
B70: ProbWeighted (input-level) — conservative anchor | C70: =DCF!C63 -> 7961.86
B71: Scenario-weighted (P·DCF) — upper anchor | C71: =DCF!C65 -> 10133.522
B72: Series G mark (March 2026) | C72: =DCF!C52 -> 10100
B73: Jensen Gap (Scenario-weighted minus ProbWeighted) | C73: =C71-C70 -> 2171.662
B74: Jensen Gap % | C74: =C71/C70-1 -> 0.27275812
B76: Memo Read:
B77: Series G ($10.1B) lands almost exactly at the scenario-weighted Equity ($10.13B). Read this as: investors are pricing the model under perfect cross-input correlation — the 'story holds together' assumption (high member growth AND tight churn AND multiple expansion AND CSRP compression all jointly). Input-level ProbWeighted ($7.96B) is the conservative anchor under input independence — 16% below the mark. The gap (~$2.2B) IS the joint-optionality premium. Healthcare option (separate) layers on top.

Sheet Assumptions
A1: WHOOP — Master Assumptions
A2: Probability Weights (ProbWeighted scenario): | B2: P_Bear | C2: 0.2 | D2: P_Base | E2: 0.5 | F2: P_Bull | G2: 0.3 | H2: Sum check: | I2: =C2+E2+G2 -> 1
A3: Scenario: | B3: Base | C3: Select Bear / Base / Bull / ProbWeighted — drives Active column F throughout the model. ProbWeighted = P_Bear×Bear + P_Base×Base + P_Bull×Bull on 16 high-leverage inputs (see row 2 weights, Section 13 doc at row 181).
A5: ID | B5: Assumption | C5: Bear | D5: Base | E5: Bull | F5: Active | G5: Tier | H5: Status | I5: Notes | J5: ProbWeighted
A7: Section 1: Revenue & Growth
A8: R3a | B8: 2025 Beginning Members (M) | C8: 1.5 | D8: 1.3 | E8: 1.1 | F8: =IF($B$3="Bear",C8,IF($B$3="Bull",E8,D8)) -> 1.3 | G8: Tier 3 | H8: High | I8: Back-solved to reconcile avg×ARPU ≈ $650M base. Bear slower decel; bull faster acquisition.
A9: R3b | B9: 2025 Ending Members (M) | C9: 2.3 | D9: 2.5 | E9: 2.7 | F9: =IF($B$3="Bear",C9,IF($B$3="Bull",E9,D9)) -> 2.5 | G9: Tier 1 | H9: Critical | I9: Series G press release: 2.5M+ paying members
A10: R3 | B10: 2025 Average Members (M) — DERIVED | C10: =(C8+C9)/2 -> 1.9 | D10: =(D8+D9)/2 -> 1.9 | E10: =(E8+E9)/2 -> 1.9 | F10: =IF($B$3="Bear",C10,IF($B$3="Bull",E10,D10)) -> 1.9 | G10: Derived | H10: Critical | I10: Per methodology: ARPU applies to AVERAGE members during period, NOT year-end.
A11: R4 | B11: 2025 Blended ARPU ($/yr) | C11: 270 | D11: =ARPU!D10 -> 274.4 | E11: 340 | F11: =IF($B$3="Bear",C11,IF($B$3="Bull",E11,D11)) -> 274.4 | G11: Tier 3 | H11: Critical | I11: Base linked to ARPU!D10 = $274 (year-specific bottoms-up: consumer 80% × $278 + Unite 20% × $260). 2026 steps to $307 (mature build w/ Labs + BP at 5% attach). Bear/Bull still hardcoded $ overrides — TODO: rebuild from tier-mix scenarios. See ARPU tab.
A12: R1 | B12: 2025 Recognized Revenue ($M) — DERIVED | C12: =C10*C11 -> 513 | D12: =D10*D11 -> 521.36 | E12: =E10*E11 -> 646 | F12: =IF($B$3="Bear",C12,IF($B$3="Bull",E12,D12)) -> 521.36 | G12: Derived | H12: Critical | I12: DERIVED: Avg Members × Blended ARPU. 2025 reconciles to $1.1B Series G run-rate as Dec exit-rate annualized, NOT full-year recognized. Gap = ramp through year (free-hardware pivot 9/2025). Memo material.
A13: R2 | B13: 2025 Bookings Run-Rate ($M) | C13: 1100 | D13: 1100 | E13: 1100 | F13: =IF($B$3="Bear",C13,IF($B$3="Bull",E13,D13)) -> 1100 | G13: Tier 1 | H13: Locked | I13: Series G press release; CEO statement (Dec 2025 exit-rate × 12). NOT full-year recognized — see I12 reconciliation note.
A14: R5 | B14: Subscription Revenue % | C14: 0.8 | D14: 0.85 | E14: 0.88 | F14: =IF($B$3="Bear",C14,IF($B$3="Bull",E14,D14)) -> 0.85 | G14: Tier 2 | H14: High | I14: Sacra/BMCT: ~80-88% range
A15: R6 | B15: 2025 YoY Subscription Growth | C15: 1.03 | D15: 1.03 | E15: 1.03 | F15: =IF($B$3="Bear",C15,IF($B$3="Bull",E15,D15)) -> 1.03 | G15: Tier 1 | H15: Locked | I15: Series G press release: 103%
A16: R7 | B16: Phase 1 Revenue Growth (2026-27) | C16: 0.5 | D16: 0.7 | E16: 0.9 | F16: =IF($B$3="Bear",C16,IF($B$3="Bull",E16,D16)) -> 0.7 | G16: Tier 3 | H16: Critical | I16: Peer trajectories; Series G deployment & WHOOP 5.0 cycle
A17: R8 | B17: Phase 2 Revenue Growth (2028-30) | C17: 0.15 | D17: 0.25 | E17: 0.4 | F17: =IF($B$3="Bear",C17,IF($B$3="Bull",E17,D17)) -> 0.25 | G17: Tier 3 | H17: Critical | I17: Deceleration shape: Dexcom (bull) / Netflix (base) / Peloton (bear)
A18: R9 | B18: Phase 3 Revenue Growth (2031-33) | C18: 0.05 | D18: 0.12 | E18: 0.2 | F18: =IF($B$3="Bear",C18,IF($B$3="Bull",E18,D18)) -> 0.12 | G18: Tier 3 | H18: High | I18: TAM ceiling; healthcare attach resolution
A19: R10a | B19: Year-1 Cohort Annual Churn | C19: 0.3 | D19: 0.22 | E19: 0.15 | F19: =IF($B$3="Bear",C19,IF($B$3="Bull",E19,IF($B$3="ProbWeighted",J19,D19))) -> 0.22 | G19: Tier 3 | H19: Critical | I19: Highest churn ("try and quit"). Will drive Members tab cohort engine. | J19: =$C$2*C19+$E$2*D19+$G$2*E19 -> 0.215
A20: R10b | B20: Year-2 Cohort Annual Churn | C20: 0.18 | D20: 0.15 | E20: 0.1 | F20: =IF($B$3="Bear",C20,IF($B$3="Bull",E20,IF($B$3="ProbWeighted",J20,D20))) -> 0.15 | G20: Tier 3 | H20: Critical | I20: Stabilizing cohort | J20: =$C$2*C20+$E$2*D20+$G$2*E20 -> 0.141
A21: R10c | B21: Year-3+ Cohort Annual Churn | C21: 0.12 | D21: 0.12 | E21: 0.05 | F21: =IF($B$3="Bear",C21,IF($B$3="Bull",E21,IF($B$3="ProbWeighted",J21,D21))) -> 0.12 | G21: Tier 3 | H21: Critical | I21: Retained core; very sticky power users | J21: =$C$2*C21+$E$2*D21+$G$2*E21 -> 0.099
A22: R11
A23: R12 | B23: B2B Unite Revenue % | C23: 0.12 | D23: 0.18 | E23: 0.25 | F23: =IF($B$3="Bear",C23,IF($B$3="Bull",E23,D23)) -> 0.18 | G23: Tier 2 | H23: Medium | I23: Sacra/BMCT: ~20% recurring revenue; growing rapidly
A24: R14 | B24: Advanced Labs Attach Rate | C24: 0.03 | D24: 0.1 | E24: 0.25 | F24: =IF($B$3="Bear",C24,IF($B$3="Bull",E24,D24)) -> 0.1 | G24: Tier 3 | H24: Critical | I24: BUCKET-3 THESIS VARIABLE. Bear/Base/Bull per methodology Sec 3. Single most important ARPU assumption — swings $80/member.
A25: R15 | B25: Labs Avg Test Price ($) | C25: 250 | D25: 300 | E25: 350 | F25: =IF($B$3="Bear",C25,IF($B$3="Bull",E25,D25)) -> 300 | G25: Tier 3 | H25: High | I25: WHOOP Advanced Labs site: $199-$599. Methodology base: $300.
A26: R16 | B26: Annual Price Inflation | C26: 0.02 | D26: 0.03 | E26: 0.04 | F26: =IF($B$3="Bear",C26,IF($B$3="Bull",E26,D26)) -> 0.03 | G26: Tier 3 | H26: Medium | I26: CPI + premium brand pricing power
A27: R18 | B27: 2026 Gross Adds (M) | C27: 1.5 | D27: 1.9 | E27: 2.3 | F27: =IF($B$3="Bear",C27,IF($B$3="Bull",E27,D27)) -> 1.9 | G27: Tier 3 | H27: Critical | I27: Methodology priors: 1.8-2.0M base. Members tab will use this; per-year gross adds modeled there. CAC × this = S&M consistency check.
A28: R19 | B28: Deferred Revenue Adjustment (% of bookings) | C28: -0.1 | D28: -0.08 | E28: -0.05 | F28: =IF($B$3="Bear",C28,IF($B$3="Bull",E28,D28)) -> -0.08 | G28: Tier 3 | H28: Medium | I28: Drag during growth (recognized < booked); ASC 606. Approaches 0 at steady state.
A30: Section 2: Cost Structure & Margins
A31: C1 | B31: Hardware BOM per Device ($) | C31: 100 | D31: 80 | E31: 60 | F31: =IF($B$3="Bear",C31,IF($B$3="Bull",E31,D31)) -> 80 | G31: Tier 3 | H31: Critical | I31: Est. $50-80 at scale; 2016 BOM was $250-300 per Contrary Research
A32: C2 | B32: Loaded Hardware Cost per Acquisition ($) | C32: 150 | D32: 120 | E32: 90 | F32: =IF($B$3="Bear",C32,IF($B$3="Bull",E32,D32)) -> 120 | G32: Tier 3 | H32: Critical | I32: C1 + assembly, ship, warranty, returns. Drives unit economics.
A33: C4 | B33: Subscription Delivery Cost (% of sub rev) | C33: 0.15 | D33: 0.1 | E33: 0.08 | F33: =IF($B$3="Bear",C33,IF($B$3="Bull",E33,D33)) -> 0.1 | G33: Tier 3 | H33: High | I33: Infra + support; AWS/GCP benchmarks; declining at scale
A34: C5 | B34: Subscription Gross Margin (standalone) | C34: 0.72 | D34: 0.78 | E34: 0.83 | F34: =IF($B$3="Bear",C34,IF($B$3="Bull",E34,D34)) -> 0.78 | G34: Tier 3 | H34: Critical | I34: Peer: pure SaaS ~80%, Dexcom ~64% (incl consumables). WHOOP higher quality recurring.
A35: C6 | B35: Hardware Gross Margin (standalone) | C35: -0.1 | D35: -0.02 | E35: 0.05 | F35: =IF($B$3="Bear",C35,IF($B$3="Bull",E35,D35)) -> -0.02 | G35: Tier 3 | H35: Critical | I35: Subsidized at acquisition; Peloton HW GM trajectory: -18% to +14%
A36: C7a | B36: Blended GM Phase 1 (2026-27) | C36: 0.56 | D36: 0.6 | E36: 0.64 | F36: =IF($B$3="Bear",C36,IF($B$3="Bull",E36,IF($B$3="ProbWeighted",J36,D36))) -> 0.6 | G36: Tier 3 | H36: High | I36: Phase 1 blended GM (legacy decomposed framework, pre-collapse to C7d). No longer drives the model post-ARPU simplification — retained for reference only. | J36: =$C$2*C36+$E$2*D36+$G$2*E36 -> 0.604
A37: C7b | B37: Blended GM Phase 2 (2028-30) | C37: 0.63 | D37: 0.67 | E37: 0.72 | F37: =IF($B$3="Bear",C37,IF($B$3="Bull",E37,IF($B$3="ProbWeighted",J37,D37))) -> 0.67 | G37: Tier 3 | H37: High | I37: Margin expansion as growth decelerates | J37: =$C$2*C37+$E$2*D37+$G$2*E37 -> 0.677
A38: C7c | B38: Blended GM Terminal | C38: 0.72 | D38: 0.76 | E38: 0.8 | F38: =IF($B$3="Bear",C38,IF($B$3="Bull",E38,IF($B$3="ProbWeighted",J38,D38))) -> 0.76 | G38: Tier 3 | H38: High | I38: Peer terminal: Dexcom 60%, Spotify 32%; software-heavy mix at scale | J38: =$C$2*C38+$E$2*D38+$G$2*E38 -> 0.764
A39: C8a | B39: R&D % of Revenue (current) | C39: 0.25 | D39: 0.22 | E39: 0.2 | F39: =IF($B$3="Bear",C39,IF($B$3="Bull",E39,D39)) -> 0.22 | G39: Tier 3 | H39: High | I39: Peers: Dexcom 13%, Garmin 16%, growth SaaS 20-30%
A40: C8b | B40: R&D % of Revenue (terminal) | C40: 0.13 | D40: 0.16 | E40: 0.19 | F40: =IF($B$3="Bear",C40,IF($B$3="Bull",E40,D40)) -> 0.16 | G40: Tier 3 | H40: Medium | I40: Peer steady-state
A41: C9 | B41: S&M % of Revenue (current) | C41: 0.35 | D41: 0.3 | E41: 0.25 | F41: =IF($B$3="Bear",C41,IF($B$3="Bull",E41,D41)) -> 0.3 | G41: Tier 3 | H41: Critical | I41: Peloton peak 28.4% FY22, current 16.9% FY25. Bear = stuck high.
A42: C9a | B42: Paid CAC per Gross Add ($) | C42: 220 | D42: 175 | E42: 130 | F42: =IF($B$3="Bear",C42,IF($B$3="Bull",E42,D42)) -> 175 | G42: Tier 3 | H42: Critical | I42: 30-50% of first-year ARPU. S&M consistency check on Checks tab.
A43: C9b | B43: Athlete/Brand Spend ($M/yr) | C43: 100 | D43: 60 | E43: 30 | F43: =IF($B$3="Bear",C43,IF($B$3="Bull",E43,D43)) -> 60 | G43: Tier 3 | H43: High | I43: Press, endorsement deals; non-paid S&M floor
A44: C9t | B44: x | C44: 0.2 | D44: 0.17 | E44: 0.15 | F44: =IF($B$3="Bear",C44,IF($B$3="Bull",E44,D44)) -> 0.17 | G44: Tier 3 | H44: High | I44: Peer steady-state: Garmin SG&A 14-19%
A45: C10 | B45: G&A % of Revenue (current) | C45: 0.18 | D45: 0.15 | E45: 0.12 | F45: =IF($B$3="Bear",C45,IF($B$3="Bull",E45,D45)) -> 0.15 | G45: Tier 3 | H45: Medium | I45: IPO step-up 200-300bps in 2027-28 (SOX, IR, legal)
A46: C10t | B46: G&A % of Revenue (terminal) | C46: 0.13 | D46: 0.11 | E46: 0.09 | F46: =IF($B$3="Bear",C46,IF($B$3="Bull",E46,D46)) -> 0.11 | G46: Tier 3 | H46: Medium | I46: Peer steady-state
A47: C11a | B47: SBC % of Revenue (current, 2026 pre-IPO peak) | C47: 0.16 | D47: 0.14 | E47: 0.12 | F47: =IF($B$3="Bear",C47,IF($B$3="Bull",E47,D47)) -> 0.14 | G47: Tier 3 | H47: High | I47: Peloton: 9.2% FY25; pre-IPO typically higher. SBC is REAL COST in FCF.
A48: C11b | B48: SBC % of Revenue (terminal, 2033 post-IPO normalized) | C48: 0.13 | D48: 0.11 | E48: 0.08 | F48: =IF($B$3="Bear",C48,IF($B$3="Bull",E48,D48)) -> 0.11 | G48: Tier 3 | H48: High | I48: Methodology Sec 6: SBC normalizes to 6-10% post-IPO. Linear taper from F47 (current) to F48 (terminal) by 2033.
A49: C13 | B49: CapEx % of Revenue | C49: 0.05 | D49: 0.04 | E49: 0.03 | F49: =IF($B$3="Bear",C49,IF($B$3="Bull",E49,D49)) -> 0.04 | G49: Tier 3 | H49: Medium | I49: Asset-light; contract manufacturing
A50: C16 | B50: NWC % of Incremental Revenue | C50: -0.05 | D50: -0.08 | E50: -0.1 | F50: =IF($B$3="Bear",C50,IF($B$3="Bull",E50,D50)) -> -0.08 | G50: Tier 3 | H50: High | I50: Negative = WC benefit (deferred rev > inventory drag during growth)
... A53: C12 | B53: D&A % of Revenue | C53: 0.045 | D53: 0.035 | E53: 0.025 | F53: =IF($B$3="Bear",C53,IF($B$3="Bull",E53,D53)) -> 0.035 | G53: Tier 2 | H53: Medium | I53: Capex amortization; lower in mature stages as growth slows. Restored after styling pass clobbered row.
A54: Section 3: Capital Structure & Cap Table (incl. cash yield)
A55: S1 | B55: Fully Diluted Shares Outstanding (M) | C55: 420 | D55: 410 | E55: 400 | F55: =IF($B$3="Bear",C55,IF($B$3="Bull",E55,D55)) -> 410 | G55: Tier 3 | H55: Critical | I55: 361.2M common + ~50M option pool est. Pitchbook auth pref 537.9M, outs 361.2M.
A56: S2 | B56: Series G Price per Share ($) | C56: 28 | D56: 28 | E56: 28 | F56: =IF($B$3="Bear",C56,IF($B$3="Bull",E56,D56)) -> 28 | G56: Tier 2 | H56: High | I56: Pitchbook Series G data; back-solve from $575M raise / shares issued
A57: S3 | B57: Liquidation Preference Type | C57: Participating | D57: 1x non-participating | E57: 1x non-participating | F57: =IF($B$3="Bear",C57,IF($B$3="Bull",E57,D57)) -> 1x non-participating | G57: Tier 2 | H57: Locked | I57: Pitchbook: 1x non-participating pari passu. Bear assumes participating ratchet.
A58: S4 | B58: Total Liquidation Preference ($M) | C58: 1400 | D58: 1400 | E58: 1400 | F58: =IF($B$3="Bear",C58,IF($B$3="Bull",E58,D58)) -> 1400 | G58: Tier 2 | H58: High | I58: Sum of preferred raises: ~$1.4B aggregate (Series A through G)
A59: S7 | B59: Option Pool Size (% of FD shares) | C59: 0.15 | D59: 0.12 | E59: 0.1 | F59: =IF($B$3="Bear",C59,IF($B$3="Bull",E59,D59)) -> 0.12 | G59: Tier 3 | H59: High | I59: Typical 10-15% pre-IPO; 600-person hiring surge implies aggressive granting
A60: S8 | B60: Founder Ownership Ahmed (% FD) | C60: 0.1 | D60: 0.14 | E60: 0.18 | F60: =IF($B$3="Bear",C60,IF($B$3="Bull",E60,D60)) -> 0.14 | G60: Tier 3 | H60: Medium | I60: 12-18% est. across 7 rounds + pool refreshes; possibly lower with secondaries
A61: S9 | B61: DLOM (Discount for Lack of Marketability) | C61: 0.3 | D61: 0.22 | E61: 0.15 | F61: =IF($B$3="Bear",C61,IF($B$3="Bull",E61,D61)) -> 0.22 | G61: Tier 2 | H61: High | I61: Oura tender 25%; EquityZen avg 13-29%; Hiive 39-51% deeper discount
A62: S10 | B62: Debt on Balance Sheet ($M) | C62: 50 | D62: 10 | E62: 0 | F62: =IF($B$3="Bear",C62,IF($B$3="Bull",E62,D62)) -> 10 | G62: Tier 2 | H62: Low | I62: Likely minimal/zero; Pitchbook shows $10.13M debt round Mar 2024
A63: S11 | B63: Cash post Series G ($M) | C63: 500 | D63: 700 | E63: 850 | F63: =IF($B$3="Bear",C63,IF($B$3="Bull",E63,D63)) -> 700 | G63: Tier 3 | H63: Medium | I63: Back-solve: $575M raise + operating cash flow positive entering 2026
A64: S12 | B64: EV-to-Equity Bridge ($M) — DERIVED | C64: =C63-C62 -> 450 | D64: =D63-D62 -> 690 | E64: =E63-E62 -> 850 | F64: =IF($B$3="Bear",C64,IF($B$3="Bull",E64,D64)) -> 690 | G64: Derived | H64: High | I64: Cash − Debt: add to EV to bridge to equity value
A65: S15 | B65: Series F Ratchet / IPO Provisions | C65: Live | D65: Likely extinguished | E65: Extinguished | F65: =IF($B$3="Bear",C65,IF($B$3="Bull",E65,D65)) -> Likely extinguished | G65: Tier 3 | H65: High | I65: Likely extinguished at Series G close; SoftBank notably absent from Series G syndicate
A66: S16
A67: C18 | B67: Cash money-market yield (interest income on idle balance) | C67: 0.025 | D67: 0.035 | E67: 0.045 | F67: =IF($B$3="Bear",C67,IF($B$3="Bull",E67,D67)) -> 0.035 | G67: Tier 2 | H67: Medium | I67: Yield on idle Series G cash. Apply to PRIOR-YEAR ending cash balance to avoid circularity (no feedback into current year cash).
A68: Section 4: WACC / Discount Rate (Damodaran Apr 2026)
A69: D1 | B69: Risk-Free Rate (10yr UST) | C69: 0.043 | D69: 0.043 | E69: 0.043 | F69: =IF($B$3="Bear",C69,IF($B$3="Bull",E69,D69)) -> 0.043 | G69: Tier 1 | H69: Locked | I69: Fed H.15, Apr 14 2026: 4.26%; rounded 4.3%
A70: D2 | B70: Equity Risk Premium | C70: 0.045 | D70: 0.045 | E70: 0.045 | F70: =IF($B$3="Bear",C70,IF($B$3="Bull",E70,D70)) -> 0.045 | G70: Tier 1 | H70: Point Est. | I70: Damodaran 4.23% (Jan 2026); Kroll 5.0%; midpoint 4.5%
A71: D3 | B71: Unlevered Beta (bucket-weighted) | C71: 0.85 | D71: 0.83 | E71: 0.81 | F71: =IF($B$3="Bear",C71,IF($B$3="Bull",E71,D71)) -> 0.83 | G71: Tier 1 | H71: Sensitivity | I71: Damodaran sector: Healthcare 0.83, Electronics 0.83. Bucket-weighted.
A72: D4 | B72: Size Premium | C72: 0.0081 | D72: 0.0081 | E72: 0.0081 | F72: =IF($B$3="Bear",C72,IF($B$3="Bull",E72,D72)) -> 0.0081 | G72: Tier 2 | H72: Point Est. | I72: Kroll CRSP Decile 3 ($7.3-13.5B): 0.81%
A73: D5 | B73: Company-Specific Risk Premium (CSRP) | C73: 0.03 | D73: 0.02 | E73: 0.01 | F73: =IF($B$3="Bear",C73,IF($B$3="Bull",E73,IF($B$3="ProbWeighted",J73,D73))) -> 0.02 | G73: Tier 3 | H73: Sensitivity | I73: Pre-IPO execution risk + private illiquidity; 1-3% range | J73: =$C$2*C73+$E$2*D73+$G$2*E73 -> 0.019
A74: D8 | B74: Implied Cost of Equity / WACC — DERIVED | C74: =C69+C70*C71+C72+C73 -> 0.11935 | D74: =D69+D70*D71+D72+D73 -> 0.10845 | E74: =E69+E70*E71+E72+E73 -> 0.09755 | F74: =IF($B$3="Bear",C74,IF($B$3="Bull",E74,D74)) -> 0.10845 | G74: Derived | H74: Critical
B75: Bottoms Up WACC | C75: ='WACC Bottom-Up'!E106 -> 0.12175651 | D75: ='WACC Bottom-Up'!F106 -> 0.11587449 | E75: ='WACC Bottom-Up'!G106 -> 0.11003837 | F75: =IF($B$3="Bear",C75,IF($B$3="Bull",E75,D75)) -> 0.11587449
A77: Section 5: Terminal Value
A78: D9 | B78: Terminal Method (primary) | C78: Exit Multiple | D78: Exit Multiple | E78: Exit Multiple | F78: =IF($B$3="Bear",C78,IF($B$3="Bull",E78,D78)) -> Exit Multiple | G78: Design | H78: Locked | I78: Primary: EV/Revenue exit multiple; cross-check: Gordon Growth
A79: D11 | B79: Terminal EV/Revenue Multiple | C79: 3 | D79: 3.5 | E79: 4.5 | F79: =IF($B$3="Bear",C79,IF($B$3="Bull",E79,IF($B$3="ProbWeighted",J79,D79))) -> 3.5 | G79: Tier 3 | H79: Critical | I79: Compressed 40-60% from current comps; reflects terminal growth 10-15% | J79: =$C$2*C79+$E$2*D79+$G$2*E79 -> 3.7
A80: D12 | B80: Terminal EV/EBITDA Multiple | C80: 12 | D80: 15 | E80: 18 | F80: =IF($B$3="Bear",C80,IF($B$3="Bull",E80,D80)) -> 15 | G80: Tier 3 | H80: High | I80: Cross-check only; more stable than revenue multiple at maturity
A81: D13 | B81: Perpetuity Growth Rate (Gordon) | C81: 0.025 | D81: 0.03 | E81: 0.035 | F81: =IF($B$3="Bear",C81,IF($B$3="Bull",E81,D81)) -> 0.03 | G81: Tier 2 | H81: Critical | I81: GDP growth + inflation; cannot exceed WACC
A82: D28 | B82: Multiple Compression Factor | C82: 0.4 | D82: 0.5 | E82: 0.6 | F82: =IF($B$3="Bear",C82,IF($B$3="Bull",E82,D82)) -> 0.5 | G82: Tier 3 | H82: High | I82: Terminal multiples 40-60% lower than current comps. Applied to derive D11.
A84: Section 6: Comp Bucket Weighting — THIS IS THE THESIS
A85: V11a | B85: Bucket 1 Weight (Consumer Hardware — Garmin) | C85: 0.4 | D85: 0.2 | E85: 0.1 | F85: =IF($B$3="Bear",C85,IF($B$3="Bull",E85,D85)) -> 0.2 | G85: Design | H85: Critical | I85: Higher = more bearish (WHOOP as hardware company)
A86: V11b | B86: Bucket 2 Weight (Consumer Subscription — PTON/SPOT) | C86: 0.4 | D86: 0.4 | E86: 0.3 | F86: =IF($B$3="Bear",C86,IF($B$3="Bull",E86,D86)) -> 0.4 | G86: Design | H86: Critical | I86: Peloton-Spotify range disaggregated; where does WHOOP sit?
A87: V11c | B87: Bucket 3 Weight (Health Data — DXCM/RMD/MASI/IRTC) | C87: 0.2 | D87: 0.4 | E87: 0.6 | F87: =IF($B$3="Bear",C87,IF($B$3="Bull",E87,D87)) -> 0.4 | G87: Design | H87: Critical | I87: Higher = healthcare thesis is believed; Series G implied ~70%
A88: V11_chk | B88: Bucket Weights Sum (must = 100%) | C88: =C85+C86+C87 -> 1 | D88: =D85+D86+D87 -> 1 | E88: =E85+E86+E87 -> 1 | F88: =IF($B$3="Bear",C88,IF($B$3="Bull",E88,D88)) -> 1 | G88: Derived | H88: Check | I88: Sanity check: bucket weights must sum to 100%
A90: Section 7: IPO Trading Range & Discount Framework
A91: I1 | B91: IPO Timing (months from Series G) | C91: 18 | D91: 15 | E91: 12 | F91: =IF($B$3="Bear",C91,IF($B$3="Bull",E91,D91)) -> 15 | G91: Tier 2 | H91: High | I91: Q2 2027 - Q1 2028; "last private round" per Ahmed
A92: I2 | B92: IPO Pricing Discount (to Stage 1 fair value) | C92: 0.25 | D92: 0.2 | E92: 0.15 | F92: =IF($B$3="Bear",C92,IF($B$3="Bull",E92,D92)) -> 0.2 | G92: Tier 2 | H92: Critical | I92: Loughran/Ritter IPO pricing studies; 15-25% standard
A93: I3
A94: I4 | B94: Series G Investor Required IRR | C94: 0.3 | D94: 0.25 | E94: 0.2 | F94: =IF($B$3="Bear",C94,IF($B$3="Bull",E94,D94)) -> 0.25 | G94: Tier 3 | H94: Medium | I94: Late-stage growth equity return expectations (3-5yr hold)
A95: I5 | B95: Implied Stage 1 Public Fair Value ($M) — DERIVED | C95: =10100/(1-C93)/(1-C92) -> 13466.667 | D95: =10100/(1-D93)/(1-D92) -> 12625 | E95: =10100/(1-E93)/(1-E92) -> 11882.353 | F95: =IF($B$3="Bear",C95,IF($B$3="Bull",E95,D95)) -> 12625 | G95: Derived | H95: Critical | I95: Back-solve: $10.1B / (1-illiquidity) / (1-IPO discount) → $13-15B target
A97: Section 8: Precedent Transactions
A98: P1 | B98: Deal Inclusion Window | C98: Last 5 years | D98: Last 5 years | E98: Last 5 years | F98: =IF($B$3="Bear",C98,IF($B$3="Bull",E98,D98)) -> Last 5 years | G98: Design | H98: Locked | I98: 2021-2026 with 3-year primary focus
A99: P3 | B99: Deal Size Threshold ($M EV) | C99: 500 | D99: 500 | E99: 500 | F99: =IF($B$3="Bear",C99,IF($B$3="Bull",E99,D99)) -> 500 | G99: Design | H99: Locked | I99: Below this, synergy math distorts multiples
A100: P5 | B100: Multiple Extraction Method | C100: EV/LTM Rev | D100: EV/LTM Rev | E100: EV/LTM Rev | F100: =IF($B$3="Bear",C100,IF($B$3="Bull",E100,D100)) -> EV/LTM Rev | G100: Design | H100: Locked | I100: EV / LTM revenue at announcement; NTM where available
A101: P_b1 | B101: Bucket 1 Precedent Multiple (median) | C101: 1 | D101: 1.5 | E101: 2.5 | F101: =IF($B$3="Bear",C101,IF($B$3="Bull",E101,D101)) -> 1.5 | G101: Tier 2 | H101: High | I101: Fitbit/Google ~1.3x; Garmin tuck-ins; mostly distressed exits
A102: P_b2 | B102: Bucket 2 Precedent Multiple (median) | C102: 0.8 | D102: 1.5 | E102: 3 | F102: =IF($B$3="Bear",C102,IF($B$3="Bull",E102,D102)) -> 1.5 | G102: Tier 2 | H102: High | I102: Peloton/Precor; connected fitness all value-destructive
A103: P_b3 | B103: Bucket 3 Precedent Multiple (median) | C103: 6 | D103: 8 | E103: 10 | F103: =IF($B$3="Bear",C103,IF($B$3="Bull",E103,D103)) -> 8 | G103: Tier 2 | H103: High | I103: Per research/precedent-transactions.md: B3 medtech 6.6-10.1x range
A105: Section 9: Real Options — see rows 154-161 (binary-gate redesign, supersedes cluster framework)
A106: Healthcare reimbursement pathway is the only separately-valued real option. International, B2B, women's health, glucose moved to base case sensitivities or dropped. Inputs: RO1 (probability), RO2 (eligibility %), RO3 (payer ARPU), RO4 (multiple), RO5 (years). See RealOptions tab Section 5 for full justification.
A108: Legend & Conventions
A109: Blue text | B109: Hard-coded input
A110: Black text | B110: Formula / derived calculation
A111: Green text | B111: Cross-sheet link (wired when other tabs are built)
...

Sheet Member Thesis
A1: WHOOP — Member Trajectory Triangulation (Four-Lens Framework)
A2: Four independent lenses converge on a 2033 ending member range. Each lens uses a different methodology; convergence is emergent, not curve-fit. Median feeds Trajectory Build (Oura-shape calibrated). Triangulation distance vs live model = audit check (±15% target).
A4: 1. Member Anchors
A6: 2025E starting members (M) | B6: 2.5
A7: ARPU ($/yr) | B7: =Assumptions!F11 -> 274.4
A8: Series G post-money valuation ($M) | B8: 10100
A9: Series G implied $/share ($) | B9: 24.63
A10: DCF base $/share (live model) | B10: =DCF!C40 -> 17.893075
A12: 2. Convergence Summary
A13: Each lens uses an independent methodology. Convergence is emergent, not curve-fit. Median feeds Trajectory Build. ✓ = within ±15% of median; ⚠ = 15-25%; ✗ = >25%. | M13: Methodology
M14: TAM 25M × 6%/yr growth × 30% terminal share. Apple-style category-defining product precedent.
A15: Lens | B15: 2033 End (M) | C15: Δ vs Median | D15: Status | M15: Peloton Connected Fitness subs IPO+10 hypothetical × free-hardware advantage × ARPU drag.
A16: Lens A — TAM × Terminal Share | B16: =B30 -> 11.953861 | C16: =B16/$B$20-1 -> 0.094960645 | D16: =IF(ABS(C16)<=0.15,"✓",IF(ABS(C16)<=0.25,"⚠","✗")) -> ✓ | M16: Median of three independently-derived comp endpoints (Apple Watch shape / Oura forward-extrap / Garmin timeline-compressed).
A17: Lens B — Peloton Stage-Shifted Comp | B17: =B43 -> 11.20932 | C17: =B17/$B$20-1 -> 0.026761539 | D17: =IF(ABS(C17)<=0.15,"✓",IF(ABS(C17)<=0.25,"⚠","✗")) -> ✓ | M17: Cumulative S&M $ ÷ weighted CAC, less churn drag. Capital-bounded floor.
A18: Lens C — Comps Triangulation | B18: =B67 -> 10.625 | C18: =B18/$B$20-1 -> -0.026761539 | D18: =IF(ABS(C18)<=0.15,"✓",IF(ABS(C18)<=0.25,"⚠","✗")) -> ✓ | M18: COV across the four lenses; flags whether triangulation is tight enough to feed Trajectory Build.
A19: Lens D — SAM/SOM Bottoms-Up | B19: =B78 -> 8.379 | C19: =B19/$B$20-1 -> -0.2324927 | D19: =IF(ABS(C19)<=0.15,"✓",IF(ABS(C19)<=0.25,"⚠","✗")) -> ⚠
A20: → Median across lenses | B20: =MEDIAN(B16:B19) -> 10.91716 | C20: =STDEV(B16:B19)/B20 -> 0.14115473 | D20: =IF(C20<0.1,"✓ tight",IF(C20<0.2,"⚠ wide","✗ diverge")) -> ⚠ wide
A22: 3. Lens A — TAM × Terminal Share
A23: Lens character — aggressive, assumption-heavy
A24: Premium continuous physiological monitoring at $200-400/yr WTP. Apple-at-30%-smartphone-share precedent supports 25-45% terminal share for category-defining product. Highest output of the four lenses — most upside-leaning by construction. | M24: Source
M25: mHealth Intelligence (2023). Oura+WHOOP combined ~4.5M paying 2025 = ~18% penetration of WTP filter.
A26: Input | B26: Value | C26: Note | M26: MarketsandMarkets ($84.5B→$176.8B, 15.9% CAGR). Grand View Research ($92.9B→$230B by 2033, 12.1% CAGR).
A27: TAM 2025 (M) | B27: 25 | C27: Premium continuous monitoring; ~130M US adults × $200-400/yr WTP filter ≈ 20-30M globally. | M27: IDC: Oura already >80% smart ring share (2024). Apple smartphone share precedent for category-defining products.
A28: TAM growth rate (%/yr) | B28: 0.06 | C28: Conservative vs broader wearable CAGR 12-16%. Captures WTP filter narrowing the base. | M28: Memo: TAM 2033 = 25 × 1.06⁸ ≈ 39.8M.
A29: Terminal share 2033 (%) | B29: 0.3 | C29: Apple precedent: 30% global smartphone share. WHOOP at 25-30% in defined WTP TAM defensible.
A30: → Implied 2033 ending (M) | B30: =B27*((1+B28)^8)*B29 -> 11.953861 | C30: = TAM 2025 × (1 + growth)⁸ × terminal share
A32: 4. Lens B — Peloton Stage-Shifted Comp
A33: Lens character — base, structural analogue
A34: WHOOP at 2.5M pre-IPO ≈ Peloton at IPO+2 (~2.6M CF subs end-2020). WHOOP 2033 ≈ Peloton IPO+10 hypothetical extrapolation, adjusted for free-hardware advantage and ARPU drag. | M34: Source
M35: Peloton 10-K FY2019.
A36: Input | B36: Value | C36: Note | M36: Peloton 10-K FY2021.
A37: Peloton CF subs at IPO (Sep 2019) | B37: 0.563 | C37: 10-K FY2019 disclosed Connected Fitness Subscribers. | M37: Peloton 10-K FY2023.
A38: Peloton CF subs IPO+2 (FY2021) | B38: 2.49 | C38: Peak; aligns roughly with WHOOP 2025 anchor of 2.5M. | M38: Spec: extrapolated curve.
A39: Peloton CF peak (FY2023) | B39: 3.08 | C39: Peloton stalled ~3M post-COVID unwind — not a clean 8yr extrapolation, useful floor. | M39: Industry data on hardware-cost elasticity in subscription conversion.
A40: Stage-shifted base case 8yr ahead (M) | B40: 10.7 | C40: Hypothetical Peloton trajectory absent COVID unwind: 4x stage-2 base. Industry S-curve anchored. | M40: Peloton ARPU/churn comp; WHOOP retention disclosure.
A41: Free-hardware acquisition advantage (×) | B41: 1.08 | C41: WHOOP $0 hw vs Peloton $2k bike unlocks step-fn in trial-to-paid; +5-10% sustained gross adds. | M41: = 10.7 × 1.08 × 0.97 = 11.21M.
A42: Lower ARPU drag (marketing capacity, ×) | B42: 0.97 | C42: WHOOP $307 ARPU vs Peloton $500: less CAC headroom but offset by lower churn (12% vs 24%).
A43: → Implied 2033 ending (M) | B43: =B40*B41*B42 -> 11.20932 | C43: = stage-shifted base × free-hw advantage × ARPU drag
A45: 5. Lens C — Comps Triangulation
A46: Lens character — base, methodologically strongest (3 independent paths converge within 3%)
A47: Three independently-derived 2033 endpoints, each using a different analytical method. Apple Watch shape-projects from a smaller scale-anchored base. Oura forward-extrapolates from current trajectory. Garmin compresses a 12-year timeline to 8 years. Convergence is emergent, not curve-fit.
A49: 5a. Apple Watch — Shape Projection | E49: 5b. Oura — Forward Extrapolation | I49: 5c. Garmin — Timeline Compression
A50: Stage-shift WHOOP 2.5M to AW 2017 (10M base), apply AW 8yr multiple, TAM-adjust. | E50: Forward-extrapolate WHOOP 2M anchor with Oura-style decel curve (50/40/30/22/17/13/10/8% YoY). | I50: Compress Garmin's 12yr to ~8yr (digital CAC), TAM-expand, premium-tier offset.
A52: Input | B52: Value | C52: Note | E52: Input | F52: Value | G52: Note | I52: Input | J52: Value | K52: Note
A53: AW base 2017 (M) | B53: 10 | C53: Counterpoint Research / analyst consensus. | E53: WHOOP 2025 anchor (M) | F53: 2 | G53: Conservative; Series G implies 2.4-2.5M. | I53: Garmin yrs to stable wearable subs | J53: 12 | K53: Garmin Fitness segment scale (2008-2020).
A54: AW base 2025 (M) | B54: 170 | C54: Counterpoint/IDC midpoint of 150-200M cumulative shipments through 2025. | E54: 8yr compounded multiple | F54: =(1.5)*(1.4)*(1.3)*(1.22)*(1.17)*(1.13)*(1.1)*(1.08) -> 5.2312229 | G54: = ∏(1+rates) for the 8 YoY values (50/40/30/22/17/13/10/8%). | I54: Garmin terminal premium subs (M) | J54: 10 | K54: Mid-tier wearables active subs base.
A55: 8yr growth multiple | B55: =B54/B53 -> 17 | C55: = 170 / 10 = 17x. | I55: Compression factor (digital-native) | J55: 0.8 | K55: $0 hardware + mandatory sub vs. $300-900 upfront. 80% of Garmin timeline.
A56: WHOOP 2025 anchor (M) | B56: 2.5 | C56: Stage-matched to AW 2017 (4x scale). | I56: TAM expansion factor (2025→2033) | J56: 1.2 | K56: Wearable TAM grows ~20% over 8yrs.
A57: Raw projected 2033 (M) | B57: =B56*B55 -> 42.5 | C57: WHOOP × AW multiple. | I57: Premium-tier offset (subset adj) | J57: 0.9 | K57: Narrower TAM offset by higher retention. 90% of Garmin terminal.
A58: TAM adjustment | B58: 4 | C58: AW 50% buyers vs WHOOP 5-7%; offset for stickiness.
A60: → Apple endpoint (M) | B60: =B57/B58 -> 10.625 | C60: = raw ÷ TAM adj | E60: → Oura endpoint (M) | F60: =F53*F54 -> 10.462446 | G60: = anchor × 8yr mult | I60: → Garmin endpoint (M) | J60: =J54*J56*J57 -> 10.8 | K60: = terminal × TAM × offset
A62: 5d. Lens C Synthesis
A64: Method | B64: Apple | C64: Oura | D64: Garmin | E64: Median | F64: Range
A65: 2033 Endpoint (M) | B65: =B60 -> 10.625 | C65: =F60 -> 10.462446 | D65: =J60 -> 10.8 | E65: =MEDIAN(B65:D65) -> 10.625 | F65: =MAX(B65:D65)-MIN(B65:D65) -> 0.33755425
A67: → Lens C endpoint (M) | B67: =E65 -> 10.625 | C67: = median of 3 methods. Range 0.34M (±3%); convergence is emergent.
A69: 6. Lens D — SAM/SOM Bottoms-Up
A70: Lens character — disciplined floor, most defensible
A71: TAM → SAM → SOM stack. Most conservative lens (8.39M) by design — disciplined market sizing without comp-borrowed shape assumptions. Acts as floor of the four-lens range, not point estimate.
A73: Input | B73: Value | C73: Note | M73: Source
A74: Global TAM — health-conscious consumers (M) | B74: 3500 | C74: Global adults w/ disposable income + health interest. | M74: Pew Research / McKinsey wellness reports.
A75: SAM — premium continuous-biometric subscribers | B75: 245 | C75: Variable + brand allocated. P1 ~$200, P2 ~$240, P3 ~$300; weighted by gross-adds shape. | M75: 7% TAM penetration. Excludes occasional users; targets WTP $25+/mo.
A76: SOM share — WHOOP capture | B76: 0.15 | C76: Steady-state blended; cohort mix shifts to Y3+ over time. | M76: Premium positioning between AW (volume) and Oura (style/wellness).
A77: Maturity factor — 2033 penetration of theoretical max | B77: 0.228 | C77: Approx midpoint 2.5M start → ~11M end. Penetration ramps; 2033 ~23% of full saturation (2040+). | M77: Theoretical max 36.75M (SAM × SOM share) — long-term ceiling, not 2033 expectation.
A78: → Lens D bottoms-up endpoint (M) | B78: =B75*B76*B77 -> 8.379 | C78: = SAM × SOM share × maturity factor. Conservative by construction — floor of the four-lens range. | M78: = 245 × 15% × 22.8% = 8.379M.
A80: 7. Composite Span (across all four lenses)
A82: Lowest defensible (Lens D — SAM/SOM floor) | B82: =MIN(B16:B19) -> 8.379 | C82: Disciplined bottoms-up; comp-shape free.
A83: Highest defensible (Lens A — TAM × share) | B83: =MAX(B16:B19) -> 11.953861 | C83: Top-down; assumption-heavy ceiling.
A84: Most defensible base (lens median) | B84: =B20 -> 10.91716 | C84: Trajectory Build is calibrated to land here.
A85: Span (range across lenses) | B85: =B83-B82 -> 3.5748606 | C85: Span 3.6M = Lens D floor to Lens A ceiling.
A87: 8. Trajectory Build — Oura-Shape Calibrated to Lens Median
A88: Anchors: 2.5M start (2025) → lens median (B20). Shape borrowed from Oura forward-extrapolation (5b): aggressive Y1–2 reflecting unconverted-demand punch (free hardware + GLP-1/CGM/employer wellness tailwinds), decelerating to single-digits as TAM saturates. Per-year rate scaled by k so compounded endpoint matches lens median.
A90: Year | B90: 2025E | C90: 2026E | D90: 2027E | E90: 2028E | F90: 2029E | G90: 2030E | H90: 2031E | I90: 2032E | J90: 2033E | K90: CAGR
A91: Raw Oura shape (%) | C91: 0.5 | D91: 0.38 | E91: 0.26 | F91: 0.19 | G91: 0.14 | H91: 0.11 | I91: 0.08 | J91: 0.06
A92: Calibration multiplier k | B92: 0.9781
A93: Members (M), end of year | B93: 2.5 | C93: =B93*(1+C$91*$B$92) -> 3.722625 | D93: =C93*(1+D$91*$B$92) -> 5.1062428 | E93: =D93*(1+E$91*$B$92) -> 6.404791 | F93: =E93*(1+F$91*$B$92) -> 7.595051 | G93: =F93*(1+G$91*$B$92) -> 8.6350717 | H93: =G93*(1+H$91*$B$92) -> 9.5641277 | I93: =H93*(1+I$91*$B$92) -> 10.312502 | J93: =I93*(1+J$91*$B$92) -> 10.917701 | K93: =(J93/B93)^(1/8)-1 -> 0.20233059
A94: Calibrated YoY % | C94: =C93/B93-1 -> 0.48905 | D94: =D93/C93-1 -> 0.371678 | E94: =E93/D93-1 -> 0.254306 | F94: =F93/E93-1 -> 0.185839 | G94: =G93/F93-1 -> 0.136934 | H94: =H93/G93-1 -> 0.107591 | I94: =I93/H93-1 -> 0.078248 | J94: =J93/I93-1 -> 0.058686
A96: 9. Cross-Checks vs Live Model
A97: Audit chain: lens median → trajectory build → live Assumptions Base → DCF. Distance metric should be <±15% to confirm triangulation holds.
A99: Cross-check | B99: Members (M) | C99: Note
A100: Live Base (Assumptions!F178) | B100: =Assumptions!F178 -> 10.924108 | C100: Live model Base scenario, compounded ending.
A101: Lens median (B20) | B101: =B20 -> 10.91716 | C101: Triangulated four-lens median — the target.
A102: Trajectory build endpoint (J93) | B102: =J93 -> 10.917701 | C102: Calibrated endpoint (k=0.9781).
A103: → Distance (Live vs Triangulation) | B103: =B100/B101-1 -> 0.00063643908 | C103: ✓ Triangulated within tolerance (target: ±15%).
A105: 10. Series G Back-Solve Diagnostic
A106: What member trajectory does Series G $24.63/sh imply? Compare to four-lens triangulation to see how far above the lens range Series G prices.
A108: Metric | B108: Value | C108: Note
A109: Series G $/sh | B109: =B9 -> 24.63 | C109: From Member Anchors (B9).
A110: DCF base $/sh (lens median trajectory) | B110: =B10 -> 17.893075 | C110: From Member Anchors (B10) — live link to DCF C40.
A111: Series G premium to DCF base | B111: =B109/B110-1 -> 0.3765102 | C111: Series G prices in members beyond the lens range OR upside on margins / pricing / multiples.
A112: Implied 2033 members at Series G (proxy) | B112: =B101*(B109/B110) -> 15.027582 | C112: First-order linear scaling: lens median × (Series G / DCF). Approximate — ignores nonlinearity in margin/scale.
A113: → Implied vs Lens A ceiling (max defensible) | B113: =B112/B83-1 -> 0.25713213 | C113: If positive: Series G prices in members beyond what any lens defends.
A115: 11. Key Findings (carry to memo)
A117: 1. Four lenses converge tightly (median 10.92M, COV 14%). Three of four lenses sit within ±3% of the median; only Lens D's bottoms-up SAM/SOM (8.38M) drags the range. Convergence is emergent — each lens uses an independent methodology, none is calibrated to the others.
A118: 2. Lens C (comps triangulation) is the methodologically strongest single lens. Three sub-methods (Apple Watch shape projection, Oura forward extrapolation, Garmin timeline compression) land within 0.34M (±3%) of each other — the tightest internal consistency of any lens.
A119: 3. Lens D anchors the bear floor at 8.38M. Disciplined bottoms-up sizing (TAM→SAM→SOM) without comp-borrowed shape. The 14% COV across lenses is wide because Lens D pulls down — not because the upside lenses disagree.
A120: 4. Trajectory build calibrates exactly to lens median. Oura-shape decel curve scaled by k=0.9781 lands the 8-year compounded endpoint at 10.92M. Implied CAGR 20.2% — aggressive Y1–2 (49%/37%) easing to single-digits Y6–8.
A121: 5. Live model Base scenario reproduces the lens median within 0.06%. Assumptions D169:D176 retuned to (49%/37%/25%/19%/14%/11%/8%/6%) — the trajectory the model now uses is the trajectory the four lenses triangulate to.
A122: 6. Series G implies ~15.0M members (proxy, linear scaling) — 26% above Lens A's most aggressive defensible ceiling (11.95M). Series G is not pricing in even the most upside-leaning lens; the gap to the comp set requires upside on margins, pricing, OR member count beyond what any methodology defends.
A123: 7. Verdict: Member triangulation supports DCF base $17.89/sh. Series G $24.63/sh requires multiple things to break right simultaneously — not a binary member-count argument, but stacked margin + multiple + member upside relative to lens median.
A125: Source: Member triangulation built from independent methodologies — mHealth Intelligence (TAM), Counterpoint/IDC (Apple Watch), Pew/McKinsey (SAM/SOM). Trajectory shape borrowed from Oura forward extrapolation. Calibration k solved to land compounded endpoint exactly on lens median.

Sheet Members
A1: WHOOP — Member Cohort Engine
A2: Members in millions; cohort engine drives revenue. 2025 beginning treated as Y3+ legacy block (simplification — see note).
B5: Units | C5: 2024 | D5: 2025 | E5: 2026 | F5: 2027 | G5: 2028 | H5: 2029 | I5: 2030 | J5: 2031 | K5: 2032 | L5: 2033
C6: Historical | D6: Historical | E6: Phase 1 | F6: Phase 1 | G6: Phase 2 | H6: Phase 2 | I6: Phase 2 | J6: Phase 3 | K6: Phase 3 | L6: Phase 3
A8: 1. Beginning Members (start of year)
A9: Beginning Members (total) | B9: M | C9: 0.7 | D9: =Assumptions!$F$8 -> 1.3 | E9: =D34 -> 2.5 | F9: =E34 -> 3.7225 | G9: =F34 -> 5.10727 | H9: =G34 -> 6.4045166 | I9: =H34 -> 7.5957567 | J9: =I34 -> 8.6363753 | K9: =J34 -> 9.5691039 | L9: =K34 -> 10.315494
A10: of which: Year-1 cohort | B10: M | C10: 0.5 | D10: 0 | E10: =D31 -> 1.356 | F10: =E31 -> 1.6581 | G10: =F31 -> 2.0290104 | H10: =G31 -> 2.1518196 | I10: =H31 -> 2.2224429 | J10: =I31 -> 2.2247063 | K10: =J31 -> 2.2435694 | L10: =K31 -> 2.1710976
A11: of which: Year-2 cohort | B11: M | C11: 0.15 | D11: 0 | E11: =D26 -> 0 | F11: =E26 -> 1.05768 | G11: =F26 -> 1.293318 | H11: =G26 -> 1.5826281 | I11: =H26 -> 1.6784193 | J11: =I26 -> 1.7335054 | K11: =J26 -> 1.7352709 | L11: =K26 -> 1.7499841
A12: of which: Year-3+ cohort | B12: M | C12: 0.05 | D12: =Assumptions!$F$8 -> 1.3 | E12: =D28 -> 1.144 | F12: =E28 -> 1.00672 | G12: =F28 -> 1.7849416 | H12: =G28 -> 2.6700689 | I12: =H28 -> 3.6948945 | J12: =I28 -> 4.6781636 | K12: =J28 -> 5.5902636 | L12: =K28 -> 6.3944122
A14: 2. Churn Rates (cohort-aged, from Assumptions)
A15: Year-1 churn rate | B15: % | C15: =Assumptions!$F$19 -> 0.22 | D15: =Assumptions!$F$19 -> 0.22 | E15: =Assumptions!$F$19 -> 0.22 | F15: =Assumptions!$F$19 -> 0.22 | G15: =Assumptions!$F$19 -> 0.22 | H15: =Assumptions!$F$19 -> 0.22 | I15: =Assumptions!$F$19 -> 0.22 | J15: =Assumptions!$F$19 -> 0.22 | ... L15: =Assumptions!$F$19 -> 0.22
A16: Year-2 churn rate | B16: % | C16: =Assumptions!$F$20 -> 0.15 | D16: =Assumptions!$F$20 -> 0.15 | E16: =Assumptions!$F$20 -> 0.15 | F16: =Assumptions!$F$20 -> 0.15 | G16: =Assumptions!$F$20 -> 0.15 | H16: =Assumptions!$F$20 -> 0.15 | I16: =Assumptions!$F$20 -> 0.15 | J16: =Assumptions!$F$20 -> 0.15 | ... L16: =Assumptions!$F$20 -> 0.15
A17: Year-3+ churn rate | B17: % | C17: =Assumptions!$F$21 -> 0.12 | D17: =Assumptions!$F$21 -> 0.12 | E17: =Assumptions!$F$21 -> 0.12 | F17: =Assumptions!$F$21 -> 0.12 | G17: =Assumptions!$F$21 -> 0.12 | H17: =Assumptions!$F$21 -> 0.12 | I17: =Assumptions!$F$21 -> 0.12 | J17: =Assumptions!$F$21 -> 0.12 | ... L17: =Assumptions!$F$21 -> 0.12
A19: 3. Churned Members
A20: Y1 churned | B20: M | C20: =C10*C15 -> 0.11 | D20: =D10*D15 -> 0 | E20: =E10*E15 -> 0.29832 | F20: =F10*F15 -> 0.364782 | G20: =G10*G15 -> 0.44638229 | H20: =H10*H15 -> 0.4734003 | I20: =I10*I15 -> 0.48893743 | J20: =J10*J15 -> 0.48943539 | ... L20: =L10*L15 -> 0.47764148
A21: Y2 churned | B21: M | C21: =C11*C16 -> 0.0225 | D21: =D11*D16 -> 0 | E21: =E11*E16 -> 0 | F21: =F11*F16 -> 0.158652 | G21: =G11*G16 -> 0.1939977 | H21: =H11*H16 -> 0.23739422 | I21: =I11*I16 -> 0.25176289 | J21: =J11*J16 -> 0.26002582 | ... L21: =L11*L16 -> 0.26249762
A22: Y3+ churned | B22: M | C22: =C12*C17 -> 0.006 | D22: =D12*D17 -> 0.156 | E22: =E12*E17 -> 0.13728 | F22: =F12*F17 -> 0.1208064 | G22: =G12*G17 -> 0.21419299 | H22: =H12*H17 -> 0.32040827 | I22: =I12*I17 -> 0.44338734 | J22: =J12*J17 -> 0.56137963 | ... L22: =L12*L17 -> 0.76732947
A23: Total churned | B23: M | C23: =SUM(C20:C22) -> 0.1385 | D23: =SUM(D20:D22) -> 0.156 | E23: =SUM(E20:E22) -> 0.4356 | F23: =SUM(F20:F22) -> 0.6442404 | G23: =SUM(G20:G22) -> 0.85457298 | H23: =SUM(H20:H22) -> 1.0312028 | I23: =SUM(I20:I22) -> 1.1840877 | J23: =SUM(J20:J22) -> 1.3108408 | ... L23: =SUM(L20:L22) -> 1.5074686
A25: 4. Surviving Members (end of year, before new adds)
A26: Y1 survivors | B26: M | C26: =C10-C20 -> 0.39 | D26: =D10-D20 -> 0 | E26: =E10-E20 -> 1.05768 | F26: =F10-F20 -> 1.293318 | G26: =G10-G20 -> 1.5826281 | H26: =H10-H20 -> 1.6784193 | I26: =I10-I20 -> 1.7335054 | J26: =J10-J20 -> 1.7352709 | ... L26: =L10-L20 -> 1.6934562
A27: Y2 survivors | B27: M | C27: =C11-C21 -> 0.1275 | D27: =D11-D21 -> 0 | E27: =E11-E21 -> 0 | F27: =F11-F21 -> 0.899028 | G27: =G11-G21 -> 1.0993203 | H27: =H11-H21 -> 1.3452339 | I27: =I11-I21 -> 1.4266564 | J27: =J11-J21 -> 1.4734796 | ... L27: =L11-L21 -> 1.4874865
A28: Y3+ end state (incl. Y2 graduates) | B28: M | C28: =C12-C22+C27 -> 0.1715 | D28: =D12-D22+D27 -> 1.144 | E28: =E12-E22+E27 -> 1.00672 | F28: =F12-F22+F27 -> 1.7849416 | G28: =G12-G22+G27 -> 2.6700689 | H28: =H12-H22+H27 -> 3.6948945 | I28: =I12-I22+I27 -> 4.6781636 | J28: =J12-J22+J27 -> 5.5902636 | ... L28: =L12-L22+L27 -> 7.1145693
A30: 5. New Members (Gross Adds — DERIVED via membership identity)
A31: Gross Adds (= Δ Ending + Total Churned) | B31: M | C31: 0.6 | D31: =Assumptions!$F$9-D28 -> 1.356 | E31: =E34-E9+E23 -> 1.6581 | F31: =F34-F9+F23 -> 2.0290104 | G31: =G34-G9+G23 -> 2.1518196 | H31: =H34-H9+H23 -> 2.2224429 | I31: =I34-I9+I23 -> 2.2247063 | J31: =J34-J9+J23 -> 2.2435694 | K31: =K34-K9+K23 -> 2.1710976 | L31: =L34-L9+L23 -> 2.1160827
A33: 6. Ending & Average Members
A34: Ending Members | B34: M | C34: =C26+C28+C31 -> 1.1615 | D34: =D26+D28+D31 -> 2.5 | E34: =MIN(D34*(1+Assumptions!$F$169),0.45*Assumptions!$F$124) -> 3.7225 | F34: =MIN(E34*(1+Assumptions!$F$170),0.45*Assumptions!$F$124) -> 5.10727 | G34: =MIN(F34*(1+Assumptions!$F$171),0.45*Assumptions!$F$124) -> 6.4045166 | H34: =MIN(G34*(1+Assumptions!$F$172),0.45*Assumptions!$F$124) -> 7.5957567 | I34: =MIN(H34*(1+Assumptions!$F$173),0.45*Assumptions!$F$124) -> 8.6363753 | J34: =MIN(I34*(1+Assumptions!$F$174),0.45*Assumptions!$F$124) -> 9.5691039 | K34: =MIN(J34*(1+Assumptions!$F$175),0.45*Assumptions!$F$124) -> 10.315494 | L34: =MIN(K34*(1+Assumptions!$F$176),0.45*Assumptions!$F$124) -> 10.924108
A35: Average Members | B35: M | C35: =(C9+C34)/2 -> 0.93075 | D35: =(D9+D34)/2 -> 1.9 | E35: =(E9+E34)/2 -> 3.11125 | F35: =(F9+F34)/2 -> 4.414885 | G35: =(G9+G34)/2 -> 5.7558933 | H35: =(H9+H34)/2 -> 7.0001366 | I35: =(I9+I34)/2 -> 8.116066 | J35: =(J9+J34)/2 -> 9.1027396 | ... L35: =(L9+L34)/2 -> 10.619801
A37: 7. Diagnostics (output, not input)
A38: Net Adds (Gross - Churned) | B38: M | C38: =C31-C23 -> 0.4615 | D38: =D31-D23 -> 1.2 | E38: =E31-E23 -> 1.2225 | F38: =F31-F23 -> 1.38477 | G38: =G31-G23 -> 1.2972466 | H38: =H31-H23 -> 1.1912401 | I38: =I31-I23 -> 1.0406187 | J38: =J31-J23 -> 0.93272854 | ... L38: =L31-L23 -> 0.60861414
A39: Net Member Growth % | B39: % | D39: =D34/C34-1 -> 1.1523892 | E39: =E34/D34-1 -> 0.489 | F39: =F34/E34-1 -> 0.372 | G39: =G34/F34-1 -> 0.254 | H39: =H34/G34-1 -> 0.186 | I39: =I34/H34-1 -> 0.137 | J39: =J34/I34-1 -> 0.108 | K39: =K34/J34-1 -> 0.078 | L39: =L34/K34-1 -> 0.059
A40: Blended Annual Churn Rate (output) | B40: % | C40: =IFERROR(C23/C9,0) -> 0.19785714 | D40: =IFERROR(D23/D9,0) -> 0.12 | E40: =IFERROR(E23/E9,0) -> 0.17424 | F40: =IFERROR(F23/F9,0) -> 0.1730666 | G40: =IFERROR(G23/G9,0) -> 0.16732481 | H40: =IFERROR(H23/H9,0) -> 0.16101181 | I40: =IFERROR(I23/I9,0) -> 0.15588805 | J40: =IFERROR(J23/J9,0) -> 0.15178136 | ... L40: =IFERROR(L23/L9,0) -> 0.14613634
A41: 2025 ending vs Assumptions R3b (consistency) | B41: % | D41: =D34/Assumptions!$F$9-1 -> 0
A44: 8. S&M Build (Variable + Brand decomposition; member-anchored)
A45: Framework: Total S&M = (Gross Adds × Variable CAC) + Brand $. P&L pulls Total. Brand split exposes true variable acquisition economics. | B45: # | C45: Hist | D45: Hist | E45: Adds→S&M | F45: Adds→S&M | G45: Rev→Adds | H45: Rev→Adds | I45: Rev→Adds | J45: Rev→Adds | K45: Rev→Adds | L45: Rev→Adds
A46: Total S&M $ (= Variable + Brand) [P&L feeder] | B46: $M | D46: 195 | E46: =E53+E54 -> 288.715 | F46: =F53+F54 -> 394.03074 | G46: =G53+G54 -> 463.04359 | H46: =H53+H54 -> 524.55937 | I46: =I53+I54 -> 575.33016 | J46: =J53+J54 -> 628.91598 | K46: =K53+K54 -> 666.90625 | L46: =L53+L54 -> 707.43056
A47: Variable CAC $ (paid acquisition only, excl. brand) | B47: $ | D47: 130 | E47: =Assumptions!$F$122 + (Assumptions!$F$123-Assumptions!$F$122)*(E$5-2026)/7 -> 150 | F47: =Assumptions!$F$122 + (Assumptions!$F$123-Assumptions!$F$122)*(F$5-2026)/7 -> 153.71429 | G47: =Assumptions!$F$122 + (Assumptions!$F$123-Assumptions!$F$122)*(G$5-2026)/7 -> 157.42857 | H47: =Assumptions!$F$122 + (Assumptions!$F$123-Assumptions!$F$122)*(H$5-2026)/7 -> 161.14286 | I47: =Assumptions!$F$122 + (Assumptions!$F$123-Assumptions!$F$122)*(I$5-2026)/7 -> 164.85714 | J47: =Assumptions!$F$122 + (Assumptions!$F$123-Assumptions!$F$122)*(J$5-2026)/7 -> 168.57143 | K47: =Assumptions!$F$122 + (Assumptions!$F$123-Assumptions!$F$122)*(K$5-2026)/7 -> 172.28571 | L47: =Assumptions!$F$122 + (Assumptions!$F$123-Assumptions!$F$122)*(L$5-2026)/7 -> 176
A48: Memo: Total S&M ÷ CAC (legacy diagnostic) | B48: M | D48: =D46/D47 -> 1.5 | E48: =E46/E47 -> 1.9247667 | F48: =F46/F47 -> 2.563397 | G48: =G46/G47 -> 2.9412932 | H48: =H46/H47 -> 3.2552443 | I48: =I46/I47 -> 3.489871 | J48: =J46/J47 -> 3.7308575 | K48: =K46/K47 -> 3.8709318 | L48: =L46/L47 -> 4.0194918
A49: TAM Penetration % (diagnostic — flag if >40%) | B49: % | D49: n/a | E49: =D34/Assumptions!$F$124 -> 0.1 | F49: =E34/Assumptions!$F$124 -> 0.1489 | G49: =F34/Assumptions!$F$124 -> 0.2042908 | H49: =G34/Assumptions!$F$124 -> 0.25618066 | I49: =H34/Assumptions!$F$124 -> 0.30383027 | J49: =I34/Assumptions!$F$124 -> 0.34545501 | K49: =J34/Assumptions!$F$124 -> 0.38276415 | L49: =K34/Assumptions!$F$124 -> 0.41261976
A50: Final Gross Adds (= row 31, derived) | B50: M | D50: =D48 -> 1.5 | E50: =E31 -> 1.6581 | F50: =F31 -> 2.0290104 | G50: =G31 -> 2.1518196 | H50: =H31 -> 2.2224429 | I50: =I31 -> 2.2247063 | J50: =J31 -> 2.2435694 | K50: =K31 -> 2.1710976 | L50: =L31 -> 2.1160827
A51: Implied S&M % of prior-yr revenue (diagnostic by phase) | B51: % | E51: =E46/'Revenue Build'!D20 -> 0.55377282 | F51: =F46/'Revenue Build'!E20 -> 0.44809889 | G51: =G46/'Revenue Build'!F20 -> 0.36028313 | H51: =H46/'Revenue Build'!G20 -> 0.30393879 | I51: =I46/'Revenue Build'!H20 -> 0.26612006 | J51: =J46/'Revenue Build'!I20 -> 0.24359974 | K51: =K46/'Revenue Build'!J20 -> 0.22360691 | L51: =L46/'Revenue Build'!K20 -> 0.21083967
A52: Memo: 2027→2028 implied step (informational) | B52: pp | G52: =(G46/'Revenue Build'!F20)-F51 -> -0.087815756
A53: Variable S&M $ (= Gross Adds × Variable CAC) | B53: $M | E53: =E50*E47 -> 248.715 | F53: =F50*F47 -> 311.88788 | G53: =G50*G47 -> 338.75788 | H53: =H50*H47 -> 358.13079 | I53: =I50*I47 -> 366.75873 | J53: =J50*J47 -> 378.20169 | K53: =K50*K47 -> 374.04911 | L53: =L50*L47 -> 372.43056
A54: Brand S&M $ (= linearly interp Assumptions!F124→F125) | B54: $M | E54: =Assumptions!$F$125+(Assumptions!$F$126-Assumptions!$F$125)*(E$5-2026)/7 -> 40 | F54: =Assumptions!$F$125+(Assumptions!$F$126-Assumptions!$F$125)*(F$5-2026)/7 -> 82.142857 | G54: =Assumptions!$F$125+(Assumptions!$F$126-Assumptions!$F$125)*(G$5-2026)/7 -> 124.28571 | H54: =Assumptions!$F$125+(Assumptions!$F$126-Assumptions!$F$125)*(H$5-2026)/7 -> 166.42857 | I54: =Assumptions!$F$125+(Assumptions!$F$126-Assumptions!$F$125)*(I$5-2026)/7 -> 208.57143 | J54: =Assumptions!$F$125+(Assumptions!$F$126-Assumptions!$F$125)*(J$5-2026)/7 -> 250.71429 | K54: =Assumptions!$F$125+(Assumptions!$F$126-Assumptions!$F$125)*(K$5-2026)/7 -> 292.85714 | L54: =Assumptions!$F$125+(Assumptions!$F$126-Assumptions!$F$125)*(L$5-2026)/7 -> 335
A55: All-in CAC $ (= Total S&M / Gross Adds) [diagnostic] | B55: $ | E55: =E46/E50 -> 174.124 | F55: =F46/F50 -> 194.19848 | G55: =G46/G50 -> 215.187 | H55: =H46/H50 -> 236.02828 | I55: =I46/I50 -> 258.60948 | J55: =J46/J50 -> 280.31938 | K55: =K46/K50 -> 307.17469 | L55: =L46/L50 -> 334.31139
A56: LTV $ (= ARPU × GM% / blended churn) | B56: $ | E56: =Assumptions!$F$11*Assumptions!$F$36/Members!E40 -> 944.90358 | F56: =Assumptions!$F$11*Assumptions!$F$36/Members!F40 -> 951.3101 | G56: =Assumptions!$F$11*Assumptions!$F$37/Members!G40 -> 1098.7492 | H56: =Assumptions!$F$11*Assumptions!$F$37/Members!H40 -> 1141.8293 | I56: =Assumptions!$F$11*Assumptions!$F$37/Members!I40 -> 1179.3592 | J56: =Assumptions!$F$11*Assumptions!$F$38/Members!J40 -> 1373.9763 | K56: =Assumptions!$F$11*Assumptions!$F$38/Members!K40 -> 1400.6939 | L56: =Assumptions!$F$11*Assumptions!$F$38/Members!L40 -> 1427.0509
A57: LTV / All-in CAC (≥3x healthy, <2x flag) | B57: x | E57: =E56/E55 -> 5.4266132 | F57: =F56/F55 -> 4.8986485 | G57: =G56/G55 -> 5.1060204 | H57: =H56/H55 -> 4.8376801 | I57: =I56/I55 -> 4.5603865 | J57: =J56/J55 -> 4.9014674 | K57: =K56/K55 -> 4.5599262 | L57: =L56/L55 -> 4.2686278
A58: LTV / Variable CAC (≥5x healthy, what acquisition really earns) | B58: x | E58: =E56/E47 -> 6.2993572 | F58: =F56/F47 -> 6.1888204 | G58: =G56/G47 -> 6.9793506 | H58: =H56/H47 -> 7.0858202 | I58: =I56/I47 -> 7.1538253 | J58: =J56/J47 -> 8.1507069 | K58: =K56/K47 -> 8.1300643 | L58: =L56/L47 -> 8.1082438
A59: 9. Guardrails (Layer 5: phase-aware bands & coherence) | M59: Notes
A60: Implied S&M % within band (P1 35-55%, P2 20-30%, P3 12-18%) | B60: ✓/⚠/✗ | E60: =IF(E$5<=2027,IF(AND(E51>=0.35,E51<=0.55),"✓",IF(AND(E51>=0.3,E51<=0.6),"⚠","✗")),IF(E$5<=2030,IF(AND(E51>=0.2,E51<=0.3),"✓",IF(AND(E51>=0.17,E51<=0.33),"⚠","✗")),IF(AND(E51>=0.12,E51<=0.18),"✓",IF(AND(E51>=0.1,E51<=0.2),"⚠","✗")))) -> ⚠ | F60: =IF(F$5<=2027,IF(AND(F51>=0.35,F51<=0.55),"✓",IF(AND(F51>=0.3,F51<=0.6),"⚠","✗")),IF(F$5<=2030,IF(AND(F51>=0.2,F51<=0.3),"✓",IF(AND(F51>=0.17,F51<=0.33),"⚠","✗")),IF(AND(F51>=0.12,F51<=0.18),"✓",IF(AND(F51>=0.1,F51<=0.2),"⚠","✗")))) -> ✓ | G60: =IF(G$5<=2027,IF(AND(G51>=0.35,G51<=0.55),"✓",IF(AND(G51>=0.3,G51<=0.6),"⚠","✗")),IF(G$5<=2030,IF(AND(G51>=0.2,G51<=0.3),"✓",IF(AND(G51>=0.17,G51<=0.33),"⚠","✗")),IF(AND(G51>=0.12,G51<=0.18),"✓",IF(AND(G51>=0.1,G51<=0.2),"⚠","✗")))) -> ✗ | H60: =IF(H$5<=2027,IF(AND(H51>=0.35,H51<=0.55),"✓",IF(AND(H51>=0.3,H51<=0.6),"⚠","✗")),IF(H$5<=2030,IF(AND(H51>=0.2,H51<=0.3),"✓",IF(AND(H51>=0.17,H51<=0.33),"⚠","✗")),IF(AND(H51>=0.12,H51<=0.18),"✓",IF(AND(H51>=0.1,H51<=0.2),"⚠","✗")))) -> ⚠ | I60: =IF(I$5<=2027,IF(AND(I51>=0.35,I51<=0.55),"✓",IF(AND(I51>=0.3,I51<=0.6),"⚠","✗")),IF(I$5<=2030,IF(AND(I51>=0.2,I51<=0.3),"✓",IF(AND(I51>=0.17,I51<=0.33),"⚠","✗")),IF(AND(I51>=0.12,I51<=0.18),"✓",IF(AND(I51>=0.1,I51<=0.2),"⚠","✗")))) -> ✓ | J60: =IF(J$5<=2027,IF(AND(J51>=0.35,J51<=0.55),"✓",IF(AND(J51>=0.3,J51<=0.6),"⚠","✗")),IF(J$5<=2030,IF(AND(J51>=0.2,J51<=0.3),"✓",IF(AND(J51>=0.17,J51<=0.33),"⚠","✗")),IF(AND(J51>=0.12,J51<=0.18),"✓",IF(AND(J51>=0.1,J51<=0.2),"⚠","✗")))) -> ✗ | K60: =IF(K$5<=2027,IF(AND(K51>=0.35,K51<=0.55),"✓",IF(AND(K51>=0.3,K51<=0.6),"⚠","✗")),IF(K$5<=2030,IF(AND(K51>=0.2,K51<=0.3),"✓",IF(AND(K51>=0.17,K51<=0.33),"⚠","✗")),IF(AND(K51>=0.12,K51<=0.18),"✓",IF(AND(K51>=0.1,K51<=0.2),"⚠","✗")))) -> ✗ | L60: =IF(L$5<=2027,IF(AND(L51>=0.35,L51<=0.55),"✓",IF(AND(L51>=0.3,L51<=0.6),"⚠","✗")),IF(L$5<=2030,IF(AND(L51>=0.2,L51<=0.3),"✓",IF(AND(L51>=0.17,L51<=0.33),"⚠","✗")),IF(AND(L51>=0.12,L51<=0.18),"✓",IF(AND(L51>=0.1,L51<=0.2),"⚠","✗")))) -> ✗ | M60: 2030 ✗ accepted as P2/P3 transition flag — model is authentically between regimes; not a band-design fix. 2033 ⚠ resolved by Brand $ bump to $130M terminal.
A61: Variable CAC ≤ 50% × ARPU | B61: ✓/⚠/✗ | E61: =IF(E47<=0.5*ARPU!E$10,"✓",IF(E47<=0.6*ARPU!E$10,"⚠","✗")) -> ⚠ | F61: =IF(F47<=0.5*ARPU!F$10,"✓",IF(F47<=0.6*ARPU!F$10,"⚠","✗")) -> ⚠ | G61: =IF(G47<=0.5*ARPU!G$10,"✓",IF(G47<=0.6*ARPU!G$10,"⚠","✗")) -> ⚠ | H61: =IF(H47<=0.5*ARPU!H$10,"✓",IF(H47<=0.6*ARPU!H$10,"⚠","✗")) -> ⚠ | I61: =IF(I47<=0.5*ARPU!I$10,"✓",IF(I47<=0.6*ARPU!I$10,"⚠","✗")) -> ⚠ | J61: =IF(J47<=0.5*ARPU!J$10,"✓",IF(J47<=0.6*ARPU!J$10,"⚠","✗")) -> ⚠ | K61: =IF(K47<=0.5*ARPU!K$10,"✓",IF(K47<=0.6*ARPU!K$10,"⚠","✗")) -> ⚠ | L61: =IF(L47<=0.5*ARPU!L$10,"✓",IF(L47<=0.6*ARPU!L$10,"⚠","✗")) -> ⚠
A62: LTV / All-in CAC ≥ 3.0x | B62: ✓/⚠/✗ | E62: =IF(E57>=3,"✓",IF(E57>=2,"⚠","✗")) -> ✓ | F62: =IF(F57>=3,"✓",IF(F57>=2,"⚠","✗")) -> ✓ | G62: =IF(G57>=3,"✓",IF(G57>=2,"⚠","✗")) -> ✓ | H62: =IF(H57>=3,"✓",IF(H57>=2,"⚠","✗")) -> ✓ | I62: =IF(I57>=3,"✓",IF(I57>=2,"⚠","✗")) -> ✓ | J62: =IF(J57>=3,"✓",IF(J57>=2,"⚠","✗")) -> ✓ | K62: =IF(K57>=3,"✓",IF(K57>=2,"⚠","✗")) -> ✓ | L62: =IF(L57>=3,"✓",IF(L57>=2,"⚠","✗")) -> ✓
A63: LTV / Variable CAC ≥ 5.0x | B63: ✓/⚠/✗ | E63: =IF(E58>=5,"✓",IF(E58>=3,"⚠","✗")) -> ✓ | F63: =IF(F58>=5,"✓",IF(F58>=3,"⚠","✗")) -> ✓ | G63: =IF(G58>=5,"✓",IF(G58>=3,"⚠","✗")) -> ✓ | H63: =IF(H58>=5,"✓",IF(H58>=3,"⚠","✗")) -> ✓ | I63: =IF(I58>=5,"✓",IF(I58>=3,"⚠","✗")) -> ✓ | J63: =IF(J58>=5,"✓",IF(J58>=3,"⚠","✗")) -> ✓ | K63: =IF(K58>=5,"✓",IF(K58>=3,"⚠","✗")) -> ✓ | L63: =IF(L58>=5,"✓",IF(L58>=3,"⚠","✗")) -> ✓
A64: TAM penetration ≤ 45% (hard-cap if breached) | B64: ✓/⚠/✗ | E64: =IF(E49<=0.45,"✓",IF(E49<=0.55,"⚠","✗")) -> ✓ | F64: =IF(F49<=0.45,"✓",IF(F49<=0.55,"⚠","✗")) -> ✓ | G64: =IF(G49<=0.45,"✓",IF(G49<=0.55,"⚠","✗")) -> ✓ | H64: =IF(H49<=0.45,"✓",IF(H49<=0.55,"⚠","✗")) -> ✓ | I64: =IF(I49<=0.45,"✓",IF(I49<=0.55,"⚠","✗")) -> ✓ | J64: =IF(J49<=0.45,"✓",IF(J49<=0.55,"⚠","✗")) -> ✓ | K64: =IF(K49<=0.45,"✓",IF(K49<=0.55,"⚠","✗")) -> ✓ | L64: =IF(L49<=0.45,"✓",IF(L49<=0.55,"⚠","✗")) -> ✓
A65: Capital coherence: 2026-27 cumul. S&M ≤ $700M Series G | B65: ✓/⚠/✗ | E65: =IF(E46+F46<=700,"✓",IF(E46+F46<=800,"⚠","✗")) -> ✓
A66: Roll-up status (worst across rows 61-65) | B66: ✓/⚠/✗ | E66: =IF(COUNTIF(E60:E64,"✗")>0,"✗",IF(COUNTIF(E60:E64,"⚠")>0,"⚠","✓")) -> ⚠ | F66: =IF(COUNTIF(F60:F64,"✗")>0,"✗",IF(COUNTIF(F60:F64,"⚠")>0,"⚠","✓")) -> ⚠ | G66: =IF(COUNTIF(G60:G64,"✗")>0,"✗",IF(COUNTIF(G60:G64,"⚠")>0,"⚠","✓")) -> ✗ | H66: =IF(COUNTIF(H60:H64,"✗")>0,"✗",IF(COUNTIF(H60:H64,"⚠")>0,"⚠","✓")) -> ⚠ | I66: =IF(COUNTIF(I60:I64,"✗")>0,"✗",IF(COUNTIF(I60:I64,"⚠")>0,"⚠","✓")) -> ⚠ | J66: =IF(COUNTIF(J60:J64,"✗")>0,"✗",IF(COUNTIF(J60:J64,"⚠")>0,"⚠","✓")) -> ✗ | K66: =IF(COUNTIF(K60:K64,"✗")>0,"✗",IF(COUNTIF(K60:K64,"⚠")>0,"⚠","✓")) -> ✗ | L66: =IF(COUNTIF(L60:L64,"✗")>0,"✗",IF(COUNTIF(L60:L64,"⚠")>0,"⚠","✓")) -> ✗
A67: Triangulation flag (vs Member Thesis median) | B67: Δ% | E67: =IF(ABS(Assumptions!$F$179)<=0.15,"✓ triang.",IF(ABS(Assumptions!$F$179)<=0.25,"⚠ wide","✗ diverged")) -> ✓ triang.

Sheet ARPU
A1: ARPU — Single-Line Blended Driver (collapsed from 5-component build)
A2: Active driver: ARPU tab bottoms-up build. 2025 driver = D32 (year-specific implied: partial Labs, no BP). 2026 driver = D33 (mature build: full Labs + BP at 5% attach). 2027+ grows at R4g. Assumptions!F11 reads from D10. Consistency check at row 38 verifies Members × ARPU ≈ Methodology rev anchor.
A5: Year | B5: Unit | C5: 2024 | D5: 2025 | E5: 2026 | F5: 2027 | G5: 2028 | H5: 2029 | I5: 2030 | J5: 2031 | K5: 2032 | L5: 2033
A7: Blended ARPU (driver)
A8: 2025 Anchor (Assumptions R4) | B8: $/yr | D8: =D32 -> 274.4
A9: Annual growth rate (Assumptions R4g) | B9: % | D9: =Assumptions!$F$151 -> 0.03
A10: Blended ARPU | B10: $/yr | C10: 0 | D10: =D8 -> 274.4 | E10: =D10*(1+$D$9) -> 282.632 | F10: =E10*(1+$D$9) -> 291.11096 | G10: =F10*(1+$D$9) -> 299.84429 | H10: =G10*(1+$D$9) -> 308.83962 | I10: =H10*(1+$D$9) -> 318.10481 | J10: =I10*(1+$D$9) -> 327.64795 | K10: =J10*(1+$D$9) -> 337.47739 | L10: =K10*(1+$D$9) -> 347.60171
A13: ARPU Justification (memo — does not drive model)
A14: Bottom-up reconciliation showing how blended ARPU reflects consumer + B2B mix. Numbers below are reference; active driver is Section 1 R4 above.
A16: Consumer per-member ARPU components:
A17: Subscription tier-weighted average | B17: $/yr | D17: 258 | E17: Tier mix 30/45/25 × $199/$239/$359 = $257; +$1.68 monthly premium
A18: Labs ARPU at maturity (10% attach × $250 × 1.5 tests) | B18: $/yr | D18: 38
A19: Accessories ARPU | B19: $/yr | D19: 18
A20: BP/Healthspan ARPU at 5% attach (post-launch) | B20: $/yr | D20: 5
A21: Consumer ARPU (mature, 2026+) | B21: $/yr | D21: =SUM(D17:D20) -> 319
A22: Consumer ARPU (2025, partial Labs only) | B22: $/yr | D22: 278
A24: B2B Unite per-seat:
A25: Per-seat employer-rate ARPU | B25: $/yr | D25: 260 | E25: B2B health platforms with bundled hardware: $200-350; standalone software: $100-180. Estimate $260 mid-range.
A27: Mix assumption (% of paying members):
A28: Consumer share | B28: % | D28: 0.8 | E28: BMCT estimate: Unite ~20% of recurring revenue
A29: Unite share | B29: % | D29: 0.2
A30: Mix sum check | D30: =D28+D29 -> 1 | E30: Must = 100%
A32: Implied blended ARPU 2025 (memo): | D32: =D28*D22 + D29*D25 -> 274.4
A33: Implied blended ARPU 2026 mature (memo): | D33: =D28*D21 + D29*D25 -> 307.2
A34: Anchor used in driver (D10) | D34: =D10 -> 274.4
A35: Variance vs year-specific implied (D32) | D35: =(D34-D32)/D32 -> 0
A36: Status | D36: =IF(ABS(D35)<=0.05,"✓ matches year-specific build","⚠ driver diverges from year-specific build — review") -> ✓ matches year-specific build
A37: Memo: 2026 mature check (E10 vs D33) | E37: =(E10-D33)/D33 -> -0.079973958
A38: Consistency Check: Members × ARPU = Revenue
A39: 2025 Avg Members × Blended ARPU | B39: $M | D39: =Members!D35*D10 -> 521.36
A40: Methodology revenue prior (Assumptions R1 / F12) | B40: $M | D40: =Assumptions!$F$12 -> 521.36
A41: Variance | D41: =(D39-D40)/D40 -> 0
A42: Status | D42: =IF(ABS(D41)<=0.05,"✓ within ±5%","⚠ outside ±5% — reconcile") -> ✓ within ±5%

Sheet Revenue Build
A1: WHOOP — Revenue Build-Up
A2: $M unless noted; Calendar Year
B5: Units | C5: 2024 | D5: 2025 | E5: 2026 | F5: 2027 | G5: 2028 | H5: 2029 | I5: 2030 | J5: 2031 | K5: 2032 | L5: 2033
C6: Historical | D6: Historical | E6: Phase 1 | F6: Phase 1 | G6: Phase 2 | H6: Phase 2 | I6: Phase 2 | J6: Phase 3 | K6: Phase 3 | L6: Phase 3
A8: 1. Member Economics (linked from Members tab)
A9: Beginning Members | B9: M | C9: =Members!C9 -> 0.7 | D9: =Members!D9 -> 1.3 | E9: =Members!E9 -> 2.5 | F9: =Members!F9 -> 3.7225 | G9: =Members!G9 -> 5.10727 | H9: =Members!H9 -> 6.4045166 | I9: =Members!I9 -> 7.5957567 | J9: =Members!J9 -> 8.6363753 | ... L9: =Members!L9 -> 10.315494
A10: Gross Adds | B10: M | C10: =Members!C31 -> 0.6 | D10: =Members!D31 -> 1.356 | E10: =Members!E31 -> 1.6581 | F10: =Members!F31 -> 2.0290104 | G10: =Members!G31 -> 2.1518196 | H10: =Members!H31 -> 2.2224429 | I10: =Members!I31 -> 2.2247063 | J10: =Members!J31 -> 2.2435694 | ... L10: =Members!L31 -> 2.1160827
A11: Churned Members | B11: M | C11: =Members!C23 -> 0.1385 | D11: =Members!D23 -> 0.156 | E11: =Members!E23 -> 0.4356 | F11: =Members!F23 -> 0.6442404 | G11: =Members!G23 -> 0.85457298 | H11: =Members!H23 -> 1.0312028 | I11: =Members!I23 -> 1.1840877 | J11: =Members!J23 -> 1.3108408 | ... L11: =Members!L23 -> 1.5074686
A12: Ending Members | B12: M | C12: =Members!C34 -> 1.1615 | D12: =Members!D34 -> 2.5 | E12: =Members!E34 -> 3.7225 | F12: =Members!F34 -> 5.10727 | G12: =Members!G34 -> 6.4045166 | H12: =Members!H34 -> 7.5957567 | I12: =Members!I34 -> 8.6363753 | J12: =Members!J34 -> 9.5691039 | ... L12: =Members!L34 -> 10.924108
A13: Avg Members | B13: M | C13: =Members!C35 -> 0.93075 | D13: =Members!D35 -> 1.9 | E13: =Members!E35 -> 3.11125 | F13: =Members!F35 -> 4.414885 | G13: =Members!G35 -> 5.7558933 | H13: =Members!H35 -> 7.0001366 | I13: =Members!I35 -> 8.116066 | J13: =Members!J35 -> 9.1027396 | ... L13: =Members!L35 -> 10.619801
A14: Blended Annual Churn (output) | B14: % | C14: =IFERROR(Members!C23/Members!C9, 0) -> 0.19785714 | D14: =IFERROR(Members!D23/Members!D9, 0) -> 0.12 | E14: =IFERROR(Members!E23/Members!E9, 0) -> 0.17424 | F14: =IFERROR(Members!F23/Members!F9, 0) -> 0.1730666 | G14: =IFERROR(Members!G23/Members!G9, 0) -> 0.16732481 | H14: =IFERROR(Members!H23/Members!H9, 0) -> 0.16101181 | I14: =IFERROR(Members!I23/Members!I9, 0) -> 0.15588805 | J14: =IFERROR(Members!J23/Members!J9, 0) -> 0.15178136 | ... L14: =IFERROR(Members!L23/Members!L9, 0) -> 0.14613634
A16: 2. ARPU (linked from ARPU tab)
A17: Blended ARPU | B17: $/yr | C17: =ARPU!C10 -> 0 | D17: =ARPU!D10 -> 274.4 | E17: =ARPU!E10 -> 282.632 | F17: =ARPU!F10 -> 291.11096 | G17: =ARPU!G10 -> 299.84429 | H17: =ARPU!H10 -> 308.83962 | I17: =ARPU!I10 -> 318.10481 | J17: =ARPU!J10 -> 327.64795 | ... L17: =ARPU!L10 -> 347.60171
A19: 3. Revenue Build
A20: Recognized Revenue (Total) | B20: $M | C20: =C13*C17 -> 0 | D20: =D13*D17 -> 521.36 | E20: =E13*E17 -> 879.33881 | F20: =F13*F17 -> 1285.2214 | G20: =G13*G17 -> 1725.8717 | H20: =H13*H17 -> 2161.9195 | I20: =I13*I17 -> 2581.7596 | J20: =J13*J17 -> 2982.494 | ... L20: =L13*L17 -> 3691.461
A21: Memo: Δ Deferred Rev Balance (flows to NWC, not P&L) | B21: $M | C21: =C20*Assumptions!$F$28 -> 0 | D21: =D20*Assumptions!$F$28 -> -41.7088 | E21: =E20*Assumptions!$F$28 -> -70.347105 | F21: =F20*Assumptions!$F$28 -> -102.81771 | G21: =G20*Assumptions!$F$28 -> -138.06974 | H21: =H20*Assumptions!$F$28 -> -172.95356 | I21: =I20*Assumptions!$F$28 -> -206.54077 | J21: =J20*Assumptions!$F$28 -> -238.59952 | ... L21: =L20*Assumptions!$F$28 -> -295.31688
A22: YoY Revenue Growth | B22: % | D22: =IFERROR(D20/C20-1,0) -> 0 | E22: =E20/D20-1 -> 0.686625 | F22: =F20/E20-1 -> 0.46157703 | G22: =G20/F20-1 -> 0.34285946 | H22: =H20/G20-1 -> 0.25265365 | I22: =I20/H20-1 -> 0.19419783 | J22: =J20/I20-1 -> 0.15521754 | K22: =K20/J20-1 -> 0.12499844 | L22: =L20/K20-1 -> 0.10018771
A24: 4. Bookings Reconciliation
A25: Implied Bookings (End × ARPU) | B25: $M | C25: =C12*C17 -> 0 | D25: =D12*D17 -> 686 | E25: =E12*E17 -> 1052.0976 | F25: =F12*F17 -> 1486.7823 | G25: =G12*G17 -> 1920.3577 | H25: =H12*H17 -> 2345.8706 | I25: =I12*I17 -> 2747.2725 | J25: =J12*J17 -> 3135.2973 | ... L25: =L12*L17 -> 3797.2387
A26: Bookings/Revenue Ratio (memo: Ending × ARPU vs Avg × ARPU) | B26: x | C26: =IFERROR(C25/C20, 0) -> 0 | D26: =IFERROR(D25/D20, 0) -> 1.3157895 | E26: =IFERROR(E25/E20, 0) -> 1.1964644 | F26: =IFERROR(F25/F20, 0) -> 1.1568297 | G26: =IFERROR(G25/G20, 0) -> 1.1126886 | H26: =IFERROR(H25/H20, 0) -> 1.0850869 | I26: =IFERROR(I25/I20, 0) -> 1.0641086 | J26: =IFERROR(J25/J20, 0) -> 1.0512334 | ... L26: =IFERROR(L25/L20, 0) -> 1.0286547
A27: 2025 Recognized vs Assumptions F12 (consistency) | B27: % | D27: =D20/Assumptions!$F$12-1 -> 0

Sheet P&L
A1: WHOOP — Projected Income Statement
A2: $M; Calendar Year; Scenario per Assumptions toggle
A3: Calibration items: see notes on F31 (2027 dip), L23 (S&M architecture). Margin tapers and NOL wired; refer to CalibrationLog for status.
B5: Units | C5: 2024 | D5: 2025 | E5: 2026 | F5: 2027 | G5: 2028 | H5: 2029 | I5: 2030 | J5: 2031 | K5: 2032 | L5: 2033
A7: Revenue
A8: Total Revenue | B8: $M | C8: ='Revenue Build'!C20 -> 0 | D8: ='Revenue Build'!D20 -> 521.36 | E8: ='Revenue Build'!E20 -> 879.33881 | F8: ='Revenue Build'!F20 -> 1285.2214 | G8: ='Revenue Build'!G20 -> 1725.8717 | H8: ='Revenue Build'!H20 -> 2161.9195 | I8: ='Revenue Build'!I20 -> 2581.7596 | J8: ='Revenue Build'!J20 -> 2982.494 | ... L8: ='Revenue Build'!L20 -> 3691.461 | M8: ← From Revenue Build tab
A9: YoY Growth | B9: % | D9: =IFERROR(D8/C8-1,0) -> 0 | E9: =E8/D8-1 -> 0.686625 | F9: =F8/E8-1 -> 0.46157703 | G9: =G8/F8-1 -> 0.34285946 | H9: =H8/G8-1 -> 0.25265365 | I9: =I8/H8-1 -> 0.19419783 | J9: =J8/I8-1 -> 0.15521754 | K9: =K8/J8-1 -> 0.12499844 | L9: =L8/K8-1 -> 0.10018771
A11: Cost of Revenue
A12: Total COGS (Blended COGS% × Revenue, linearly interpolated) | B12: $M | D12: =D8*0.4 -> 208.544 | E12: =E8*(Assumptions!$F$152 + (Assumptions!$F$153-Assumptions!$F$152)*(E$5-2026)/7) -> 219.8347 | F12: =F8*(Assumptions!$F$152 + (Assumptions!$F$153-Assumptions!$F$152)*(F$5-2026)/7) -> 312.1252 | G12: =G8*(Assumptions!$F$152 + (Assumptions!$F$153-Assumptions!$F$152)*(G$5-2026)/7) -> 406.81262 | H12: =H8*(Assumptions!$F$152 + (Assumptions!$F$153-Assumptions!$F$152)*(H$5-2026)/7) -> 494.15303 | I12: =I8*(Assumptions!$F$152 + (Assumptions!$F$153-Assumptions!$F$152)*(I$5-2026)/7) -> 571.67534 | J12: =J8*(Assumptions!$F$152 + (Assumptions!$F$153-Assumptions!$F$152)*(J$5-2026)/7) -> 639.10585 | K12: =K8*(Assumptions!$F$152 + (Assumptions!$F$153-Assumptions!$F$152)*(K$5-2026)/7) -> 695.02665 | L12: =L8*(Assumptions!$F$152 + (Assumptions!$F$153-Assumptions!$F$152)*(L$5-2026)/7) -> 738.2922
A13: Hardware COGS (MEMO ONLY — embedded in blended COGS%; used for WC inventory only) | B13: $M | D13: =Members!D31 * Assumptions!$F$32 -> 162.72 | E13: =Members!E31 * Assumptions!$F$32 -> 198.972 | F13: =Members!F31 * Assumptions!$F$32 -> 243.48125 | G13: =Members!G31 * Assumptions!$F$32 -> 258.21835 | H13: =Members!H31 * Assumptions!$F$32 -> 266.69314 | I13: =Members!I31 * Assumptions!$F$32 -> 266.96476 | J13: =Members!J31 * Assumptions!$F$32 -> 269.22832 | K13: =Members!K31 * Assumptions!$F$32 -> 260.53172 | L13: =Members!L31 * Assumptions!$F$32 -> 253.92992
A14: Total COGS (= row 12) | B14: $M | D14: =D12 -> 208.544 | E14: =E12 -> 219.8347 | F14: =F12 -> 312.1252 | G14: =G12 -> 406.81262 | H14: =H12 -> 494.15303 | I14: =I12 -> 571.67534 | J14: =J12 -> 639.10585 | K14: =K12 -> 695.02665 | L14: =L12 -> 738.2922
A15: Gross Profit | B15: $M | D15: =D8-D12 -> 312.816 | E15: =E8-E12 -> 659.50411 | F15: =F8-F12 -> 973.09621 | G15: =G8-G12 -> 1319.0591 | H15: =H8-H12 -> 1667.7665 | I15: =I8-I12 -> 2010.0843 | J15: =J8-J12 -> 2343.3881 | K15: =K8-K12 -> 2660.2744 | L15: =L8-L12 -> 2953.1688
A16: Gross Margin | B16: % | D16: =D15/D8 -> 0.6 | E16: =E15/E8 -> 0.75 | F16: =F15/F8 -> 0.75714286 | G16: =G15/G8 -> 0.76428571 | H16: =H15/H8 -> 0.77142857 | I16: =I15/I8 -> 0.77857143 | J16: =J15/J8 -> 0.78571429 | K16: =K15/K8 -> 0.79285714 | L16: =L15/L8 -> 0.8
A20: Operating Expenses
A21: R&D | B21: $M | D21: =D8*Assumptions!$F$39 -> 114.6992 | E21: =E8*(Assumptions!$F$39 + (Assumptions!$F$40-Assumptions!$F$39)*(E$5-2026)/7) -> 193.45454 | F21: =F8*(Assumptions!$F$39 + (Assumptions!$F$40-Assumptions!$F$39)*(F$5-2026)/7) -> 271.73253 | G21: =G8*(Assumptions!$F$39 + (Assumptions!$F$40-Assumptions!$F$39)*(G$5-2026)/7) -> 350.10541 | H21: =H8*(Assumptions!$F$39 + (Assumptions!$F$40-Assumptions!$F$39)*(H$5-2026)/7) -> 420.03008 | I21: =I8*(Assumptions!$F$39 + (Assumptions!$F$40-Assumptions!$F$39)*(I$5-2026)/7) -> 479.46964 | J21: =J8*(Assumptions!$F$39 + (Assumptions!$F$40-Assumptions!$F$39)*(J$5-2026)/7) -> 528.3275 | K21: =K8*(Assumptions!$F$39 + (Assumptions!$F$40-Assumptions!$F$39)*(K$5-2026)/7) -> 565.6079 | L21: =L8*(Assumptions!$F$39 + (Assumptions!$F$40-Assumptions!$F$39)*(L$5-2026)/7) -> 590.63376
A22: R&D % Revenue | B22: % | D22: =D21/D8 -> 0.22 | E22: =E21/E8 -> 0.22 | F22: =F21/F8 -> 0.21142857 | G22: =G21/G8 -> 0.20285714 | H22: =H21/H8 -> 0.19428571 | I22: =I21/I8 -> 0.18571429 | J22: =J21/J8 -> 0.17714286 | K22: =K21/K8 -> 0.16857143 | L22: =L21/L8 -> 0.16 | M22: ← From Assumptions C7/C8
A23: Sales & Marketing | B23: $M | D23: =D8*Assumptions!$F$41 -> 156.408 | E23: =Members!E46 -> 288.715 | F23: =Members!F46 -> 394.03074 | G23: =Members!G46 -> 463.04359 | H23: =Members!H46 -> 524.55937 | I23: =Members!I46 -> 575.33016 | J23: =Members!J46 -> 628.91598 | K23: =Members!K46 -> 666.90625 | L23: =Members!L46 -> 707.43056
A24: S&M % Revenue | B24: % | D24: =D23/D8 -> 0.3 | E24: =E23/E8 -> 0.32833192 | F24: =F23/F8 -> 0.30658588 | G24: =G23/G8 -> 0.26829549 | H24: =H23/H8 -> 0.24263594 | I24: =I23/I8 -> 0.2228442 | J24: =J23/J8 -> 0.21086915 | K24: =K23/K8 -> 0.19876197 | L24: =L23/L8 -> 0.19163972 | M24: ← From Assumptions C9/C10
A25: General & Administrative | B25: $M | D25: =D8*Assumptions!$F$45 -> 78.204 | E25: =E8*(Assumptions!$F$45 + (Assumptions!$F$46-Assumptions!$F$45)*(E$5-2026)/7) -> 131.90082 | F25: =F8*(Assumptions!$F$45 + (Assumptions!$F$46-Assumptions!$F$45)*(F$5-2026)/7) -> 185.43909 | G25: =G8*(Assumptions!$F$45 + (Assumptions!$F$46-Assumptions!$F$45)*(G$5-2026)/7) -> 239.15651 | H25: =H8*(Assumptions!$F$45 + (Assumptions!$F$46-Assumptions!$F$45)*(H$5-2026)/7) -> 287.22645 | I25: =I8*(Assumptions!$F$45 + (Assumptions!$F$46-Assumptions!$F$45)*(I$5-2026)/7) -> 328.25229 | J25: =J8*(Assumptions!$F$45 + (Assumptions!$F$46-Assumptions!$F$45)*(J$5-2026)/7) -> 362.15998 | K25: =K8*(Assumptions!$F$45 + (Assumptions!$F$46-Assumptions!$F$45)*(K$5-2026)/7) -> 388.25627 | L25: =L8*(Assumptions!$F$45 + (Assumptions!$F$46-Assumptions!$F$45)*(L$5-2026)/7) -> 406.06071
A26: G&A % Revenue | B26: % | D26: =D25/D8 -> 0.15 | E26: =E25/E8 -> 0.15 | F26: =F25/F8 -> 0.14428571 | G26: =G25/G8 -> 0.13857143 | H26: =H25/H8 -> 0.13285714 | I26: =I25/I8 -> 0.12714286 | J26: =J25/J8 -> 0.12142857 | K26: =K25/K8 -> 0.11571429 | L26: =L25/L8 -> 0.11 | M26: ← From Assumptions C11/C12
A27: Stock-Based Compensation | B27: $M | D27: =D8*Assumptions!$F$47 -> 72.9904 | E27: =E8*(Assumptions!$F$47 + (Assumptions!$F$48-Assumptions!$F$47)*(E$5-2026)/7) -> 123.10743 | F27: =F8*Assumptions!$F$164 -> 218.48764 | G27: =G8*Assumptions!$F$165 -> 258.88076 | H27: =H8*(Assumptions!$F$47 + (Assumptions!$F$48-Assumptions!$F$47)*(H$5-2026)/7) -> 274.87262 | I27: =I8*(Assumptions!$F$47 + (Assumptions!$F$48-Assumptions!$F$47)*(I$5-2026)/7) -> 317.18761 | J27: =J8*(Assumptions!$F$47 + (Assumptions!$F$48-Assumptions!$F$47)*(J$5-2026)/7) -> 353.63857 | K27: =K8*(Assumptions!$F$47 + (Assumptions!$F$48-Assumptions!$F$47)*(K$5-2026)/7) -> 383.46298 | L27: =L8*(Assumptions!$F$47 + (Assumptions!$F$48-Assumptions!$F$47)*(L$5-2026)/7) -> 406.06071
A28: SBC % Revenue | B28: % | D28: =D27/D8 -> 0.14 | E28: =E27/E8 -> 0.14 | F28: =F27/F8 -> 0.17 | G28: =G27/G8 -> 0.15 | H28: =H27/H8 -> 0.12714286 | I28: =I27/I8 -> 0.12285714 | J28: =J27/J8 -> 0.11857143 | K28: =K27/K8 -> 0.11428571 | L28: =L27/L8 -> 0.11 | M28: ← From Assumptions C13
A29: Total OpEx | B29: $M | D29: =D21+D23+D25+D27 -> 422.3016 | E29: =E21+E23+E25+E27 -> 737.17779 | F29: =F21+F23+F25+F27 -> 1069.69 | G29: =G21+G23+G25+G27 -> 1311.1863 | H29: =H21+H23+H25+H27 -> 1506.6885 | I29: =I21+I23+I25+I27 -> 1700.2397 | J29: =J21+J23+J25+J27 -> 1873.042 | K29: =K21+K23+K25+K27 -> 2004.2334 | L29: =L21+L23+L25+L27 -> 2110.1857
A31: Profitability
A32: EBITDA | B32: $M | D32: =D15-D29+D27 -> -36.4952 | E32: =E15-E29+E27 -> 45.433748 | F32: =F15-F29+F27 -> 121.89385 | G32: =G15-G29+G27 -> 266.7536 | H32: =H15-H29+H27 -> 435.95059 | I32: =I15-I29+I27 -> 627.03217 | J32: =J15-J29+J27 -> 823.98465 | K32: =K15-K29+K27 -> 1039.504 | L32: =L15-L29+L27 -> 1249.0438
A33: EBITDA Margin | B33: % | D33: =D32/D8 -> -0.07 | E33: =E32/E8 -> 0.05166808 | F33: =F32/F8 -> 0.094842688 | G33: =G32/G8 -> 0.15456166 | H33: =H32/H8 -> 0.20164978 | I33: =I32/I8 -> 0.24287008 | J33: =J32/J8 -> 0.2762737 | K33: =K32/K8 -> 0.30980946 | L33: =L32/L8 -> 0.33836028
A34: EBIT / Operating Income | B34: $M | D34: =D15-D29 -> -109.4856 | E34: =E15-E29 -> -77.673686 | F34: =F15-F29 -> -96.593786 | G34: =G15-G29 -> 7.8728356 | H34: =H15-H29 -> 161.07797 | I34: =I15-I29 -> 309.84456 | J34: =J15-J29 -> 470.34608 | K34: =K15-K29 -> 656.04103 | L34: =L15-L29 -> 842.98307
A35: Operating Margin | B35: % | D35: =D34/D8 -> -0.21 | E35: =E34/E8 -> -0.08833192 | F35: =F34/F8 -> -0.075157312 | G35: =G34/G8 -> 0.0045616574 | H35: =H34/H8 -> 0.074506921 | I35: =I34/I8 -> 0.12001294 | J35: =J34/J8 -> 0.15770227 | K35: =K34/K8 -> 0.19552375 | L35: =L34/L8 -> 0.22836028
A36: Rule of 40 Score | B36: # | D36: =(D9+D33)*100 -> -7 | E36: =(E9+E33)*100 -> 73.829308 | F36: =(F9+F33)*100 -> 55.641972 | G36: =(G9+G33)*100 -> 49.742112 | H36: =(H9+H33)*100 -> 45.430342 | I36: =(I9+I33)*100 -> 43.706792 | J36: =(J9+J33)*100 -> 43.149124 | K36: =(K9+K33)*100 -> 43.48079 | L36: =(L9+L33)*100 -> 43.854799 | M36: = Revenue Growth % + EBITDA Margin %
A38: Below the Line
A39: Interest Income / (Expense) | B39: $M | D39: ='WC & Cash'!$D$12*Assumptions!$F$67 -> 2.625 | E39: =('WC & Cash'!D34 + 'WC & Cash'!E14*0.5)*Assumptions!$F$67 -> 12.296927 | F39: ='WC & Cash'!E34*Assumptions!$F$67 -> 25.533161 | G39: ='WC & Cash'!F34*Assumptions!$F$67 -> 29.417062 | H39: ='WC & Cash'!G34*Assumptions!$F$67 -> 36.813639 | I39: ='WC & Cash'!H34*Assumptions!$F$67 -> 49.121557 | J39: ='WC & Cash'!I34*Assumptions!$F$67 -> 63.996767 | K39: ='WC & Cash'!J34*Assumptions!$F$67 -> 82.369445 | L39: ='WC & Cash'!K34*Assumptions!$F$67 -> 104.78289
A40: Pre-Tax Income | B40: $M | D40: =D34+D39 -> -106.8606 | E40: =E34+E39 -> -65.376759 | F40: =F34+F39 -> -71.060626 | G40: =G34+G39 -> 37.289897 | H40: =H34+H39 -> 197.89161 | I40: =I34+I39 -> 358.96612 | J40: =J34+J39 -> 534.34285 | K40: =K34+K39 -> 738.41048 | L40: =L34+L39 -> 947.76595
A41: Taxes | B41: $M | D41: =MAX(0, D40-D48)*Assumptions!$F$52 -> 0 | E41: =MAX(0, E40-E48)*Assumptions!$F$52 -> 0 | F41: =MAX(0, F40-F48)*Assumptions!$F$52 -> 0 | G41: =MAX(0, G40-G48)*Assumptions!$F$52 -> 1.7153353 | H41: =MAX(0, H40-H48)*Assumptions!$F$52 -> 9.1030139 | I41: =MAX(0, I40-I48)*Assumptions!$F$52 -> 69.877068 | J41: =MAX(0, J40-J48)*Assumptions!$F$52 -> 122.89886 | K41: =MAX(0, K40-K48)*Assumptions!$F$52 -> 169.83441 | L41: =MAX(0, L40-L48)*Assumptions!$F$52 -> 217.98617
A42: Net Income | B42: $M | D42: =D40-D41 -> -106.8606 | E42: =E40-E41 -> -65.376759 | F42: =F40-F41 -> -71.060626 | G42: =G40-G41 -> 35.574562 | H42: =H40-H41 -> 188.78859 | I42: =I40-I41 -> 289.08905 | J42: =J40-J41 -> 411.44399 | K42: =K40-K41 -> 568.57607 | L42: =L40-L41 -> 729.77978
A43: Net Margin | B43: % | D43: =D42/D8 -> -0.20496509 | E43: =E42/E8 -> -0.074347633 | F43: =F42/F8 -> -0.055290571 | G43: =G42/G8 -> 0.020612518 | H43: =H42/H8 -> 0.087324524 | I43: =I42/I8 -> 0.11197365 | J43: =J42/J8 -> 0.137953 | K43: =K42/K8 -> 0.16945605 | L43: =L42/L8 -> 0.19769402
A45: NOL Carryforward Schedule (post-TCJA, 80% utilization cap)
A46: Beginning NOL Balance | B46: $M | C46: 0 | D46: =C49 -> 0 | E46: =D49 -> 106.8606 | F46: =E49 -> 172.23736 | G46: =F49 -> 243.29798 | H46: =G49 -> 213.46607 | I46: =H49 -> 55.152782 | J46: =I49 -> 0 | K46: =J49 -> 0 | L46: =K49 -> 0
A47: + Current Year Loss Added (if pretax < 0) | B47: $M | C47: 0 | D47: =MAX(0,-D40) -> 106.8606 | E47: =MAX(0,-E40) -> 65.376759 | F47: =MAX(0,-F40) -> 71.060626 | G47: =MAX(0,-G40) -> 0 | H47: =MAX(0,-H40) -> 0 | I47: =MAX(0,-I40) -> 0 | J47: =MAX(0,-J40) -> 0 | K47: =MAX(0,-K40) -> 0 | L47: =MAX(0,-L40) -> 0
A48: − NOL Utilized Against Current Income | B48: $M | C48: 0 | D48: =MIN(D46, MAX(0,D40)*0.8) -> 0 | E48: =MIN(E46, MAX(0,E40)*0.8) -> 0 | F48: =MIN(F46, MAX(0,F40)*0.8) -> 0 | G48: =MIN(G46, MAX(0,G40)*0.8) -> 29.831918 | H48: =MIN(H46, MAX(0,H40)*0.8) -> 158.31328 | I48: =MIN(I46, MAX(0,I40)*0.8) -> 55.152782 | J48: =MIN(J46, MAX(0,J40)*0.8) -> 0 | K48: =MIN(K46, MAX(0,K40)*0.8) -> 0 | L48: =MIN(L46, MAX(0,L40)*0.8) -> 0
A49: Ending NOL Balance | B49: $M | C49: =C46+C47-C48 -> 0 | D49: =D46+D47-D48 -> 106.8606 | E49: =E46+E47-E48 -> 172.23736 | F49: =F46+F47-F48 -> 243.29798 | G49: =G46+G47-G48 -> 213.46607 | H49: =H46+H47-H48 -> 55.152782 | I49: =I46+I47-I48 -> 0 | J49: =J46+J47-J48 -> 0 | ... L49: =L46+L47-L48 -> 0

Sheet FCF
A1: WHOOP — FCF
A2: Free cash flow build. ΔNWC sourced from WC & Cash tab (detailed deferred-rev schedule).
B5: Units | C5: 2024 | D5: 2025 | E5: 2026 | F5: 2027 | G5: 2028 | H5: 2029 | I5: 2030 | J5: 2031 | K5: 2032 | L5: 2033
C6: Historical | D6: Historical | E6: Phase 1 | F6: Phase 1 | G6: Phase 2 | H6: Phase 2 | I6: Phase 2 | J6: Phase 3 | K6: Phase 3 | L6: Phase 3
A8: 1. EBIT to NOPAT
A9: EBIT | B9: $M | D9: ='P&L'!D34 -> -109.4856 | E9: ='P&L'!E34 -> -77.673686 | F9: ='P&L'!F34 -> -96.593786 | G9: ='P&L'!G34 -> 7.8728356 | H9: ='P&L'!H34 -> 161.07797 | I9: ='P&L'!I34 -> 309.84456 | J9: ='P&L'!J34 -> 470.34608 | K9: ='P&L'!K34 -> 656.04103 | L9: ='P&L'!L34 -> 842.98307 | M9: = P&L EBIT (row 33)
A10: Less: Cash taxes on EBIT | B10: $M | D10: ='P&L'!D41 -> 0 | E10: ='P&L'!E41 -> 0 | F10: ='P&L'!F41 -> 0 | G10: ='P&L'!G41 -> 1.7153353 | H10: ='P&L'!H41 -> 9.1030139 | I10: ='P&L'!I41 -> 69.877068 | J10: ='P&L'!J41 -> 122.89886 | K10: ='P&L'!K41 -> 169.83441 | L10: ='P&L'!L41 -> 217.98617 | M10: = P&L Cash Taxes (row 40), tax-affected at effective rate
A11: NOPAT | B11: $M | D11: =D9-D10 -> -109.4856 | E11: =E9-E10 -> -77.673686 | F11: =F9-F10 -> -96.593786 | G11: =G9-G10 -> 6.1575003 | H11: =H9-H10 -> 151.97495 | I11: =I9-I10 -> 239.96749 | J11: =J9-J10 -> 347.44723 | K11: =K9-K10 -> 486.20662 | L11: =L9-L10 -> 624.9969 | M11: = EBIT − Cash Taxes
A13: 2. NOPAT to Unlevered FCF
A14: Plus: D&A | B14: $M | D14: ='P&L'!D8*Assumptions!$F$53 -> 18.2476 | E14: ='P&L'!E8*Assumptions!$F$53 -> 30.776858 | F14: ='P&L'!F8*Assumptions!$F$53 -> 44.982749 | G14: ='P&L'!G8*Assumptions!$F$53 -> 60.405511 | H14: ='P&L'!H8*Assumptions!$F$53 -> 75.667183 | I14: ='P&L'!I8*Assumptions!$F$53 -> 90.361586 | J14: ='P&L'!J8*Assumptions!$F$53 -> 104.38729 | K14: ='P&L'!K8*Assumptions!$F$53 -> 117.43554 | L14: ='P&L'!L8*Assumptions!$F$53 -> 129.20114 | M14: = Revenue × D&A % (Assumptions F52)
A15: Less: CapEx | B15: $M | D15: =-'P&L'!D8*Assumptions!$F$49 -> -20.8544 | E15: =-'P&L'!E8*Assumptions!$F$49 -> -35.173552 | F15: =-'P&L'!F8*Assumptions!$F$49 -> -51.408856 | G15: =-'P&L'!G8*Assumptions!$F$49 -> -69.034869 | H15: =-'P&L'!H8*Assumptions!$F$49 -> -86.476781 | I15: =-'P&L'!I8*Assumptions!$F$49 -> -103.27038 | J15: =-'P&L'!J8*Assumptions!$F$49 -> -119.29976 | K15: =-'P&L'!K8*Assumptions!$F$49 -> -134.21204 | L15: =-'P&L'!L8*Assumptions!$F$49 -> -147.65844 | M15: = −(Revenue × CapEx %) (Assumptions F48)
A16: Less: Change in NWC | B16: $M | D16: ='WC & Cash'!D27 -> 100.93317 | E16: ='WC & Cash'!E27 -> 172.74849 | F16: ='WC & Cash'!F27 -> 213.9885 | G16: ='WC & Cash'!G27 -> 213.80265 | H16: ='WC & Cash'!H27 -> 210.48943 | I16: ='WC & Cash'!I27 -> 197.9473 | J16: ='WC & Cash'!J27 -> 192.39889 | K16: ='WC & Cash'!K27 -> 170.9539 | L16: ='WC & Cash'!L27 -> 153.52227 | M16: = From WC & Cash tab (Section 3, Total ΔNWC)
A17: Note: SBC is REAL COST in P&L — do NOT add back | M17: Per methodology Sec 6 — SBC stays in P&L as cash-equivalent expense
A18: Unlevered Free Cash Flow | B18: $M | D18: =D11+D14+D15+D16 -> -11.159233 | E18: =E11+E14+E15+E16 -> 90.678108 | F18: =F11+F14+F15+F16 -> 110.9686 | G18: =G11+G14+G15+G16 -> 211.33079 | H18: =H11+H14+H15+H16 -> 351.65478 | I18: =I11+I14+I15+I16 -> 425.006 | J18: =J11+J14+J15+J16 -> 524.93365 | K18: =K11+K14+K15+K16 -> 640.38402 | L18: =L11+L14+L15+L16 -> 760.06186 | M18: = NOPAT + D&A + CapEx + ΔNWC
A20: 3. FCF Diagnostics
A21: FCF Margin % | B21: % | D21: =IFERROR(D18/'P&L'!D8,0) -> -0.021404083 | E21: =IFERROR(E18/'P&L'!E8,0) -> 0.10312079 | F21: =IFERROR(F18/'P&L'!F8,0) -> 0.086342013 | G21: =IFERROR(G18/'P&L'!G8,0) -> 0.12244872 | H21: =IFERROR(H18/'P&L'!H8,0) -> 0.16265859 | I21: =IFERROR(I18/'P&L'!I8,0) -> 0.16461874 | J21: =IFERROR(J18/'P&L'!J8,0) -> 0.17600493 | K21: =IFERROR(K18/'P&L'!K8,0) -> 0.19085739 | L21: =IFERROR(L18/'P&L'!L8,0) -> 0.2058973 | M21: FCF / Revenue
A22: Rule of 40 (Growth + FCF Margin) | B22: % | E22: =IFERROR(('P&L'!E8/'P&L'!D8-1)*100 + E21*100,0) -> 78.974579 | F22: =IFERROR(('P&L'!F8/'P&L'!E8-1)*100 + F21*100,0) -> 54.791905 | G22: =IFERROR(('P&L'!G8/'P&L'!F8-1)*100 + G21*100,0) -> 46.530818 | H22: =IFERROR(('P&L'!H8/'P&L'!G8-1)*100 + H21*100,0) -> 41.531224 | I22: =IFERROR(('P&L'!I8/'P&L'!H8-1)*100 + I21*100,0) -> 35.881657 | J22: =IFERROR(('P&L'!J8/'P&L'!I8-1)*100 + J21*100,0) -> 33.122247 | K22: =IFERROR(('P&L'!K8/'P&L'!J8-1)*100 + K21*100,0) -> 31.585584 | L22: =IFERROR(('P&L'!L8/'P&L'!K8-1)*100 + L21*100,0) -> 30.608501 | M22: Revenue Growth % + FCF Margin %

Sheet WC & Cash
A1: WHOOP — Working Capital & Cash Roll-Forward
A2: $M; pre-IPO (no debt service / dividends / buybacks). Replaces FCF-tab ΔNWC plug with explicit WC build.
A3: Detailed WC schedule wired into FCF tab as of this session. DCF EV impact: +$813M.
B5: Units | C5: 2024 | D5: 2025 | E5: 2026 | F5: 2027 | G5: 2028 | H5: 2029 | I5: 2030 | J5: 2031 | K5: 2032 | L5: 2033
A7: 1. Drivers
A8: Avg months remaining on annual sub (deferred rev) | B8: mo | D8: 6
A9: Inventory days (gross adds device cost) | B9: days | D9: 45
A10: Accounts payable days (% of total COGS) | B10: days | D10: 18
A11: Other NWC (% of revenue) | B11: % | D11: 0.015
A12: Pre-existing cash balance (start 2025) | B12: $M | D12: 75
A13: 2024 Deferred Revenue Balance | B13: $M | D13: 220
A14: Series G proceeds (closed Mar 2026) | B14: $M | D14: 0 | E14: 575
A16: 2. Working Capital Balances (Liabilities = Source / Assets = Use)
A17: Deferred Revenue (= End Members × ARPU × mo/12) | B17: $M | C17: =D13 -> 220 | D17: =Members!D34*ARPU!D10*$D$8/12 -> 343 | E17: =Members!E34*ARPU!E10*$D$8/12 -> 526.04881 | F17: =Members!F34*ARPU!F10*$D$8/12 -> 743.39114 | G17: =Members!G34*ARPU!G10*$D$8/12 -> 960.17886 | H17: =Members!H34*ARPU!H10*$D$8/12 -> 1172.9353 | I17: =Members!I34*ARPU!I10*$D$8/12 -> 1373.6362 | J17: =Members!J34*ARPU!J10*$D$8/12 -> 1567.6486 | K17: =Members!K34*ARPU!K10*$D$8/12 -> 1740.623 | L17: =Members!L34*ARPU!L10*$D$8/12 -> 1898.6193
A18: Inventory (= ~45 days of NEXT-yr hardware COGS) | B18: $M | C18: 0 | D18: ='P&L'!E13*$D$9/365 -> 24.530795 | E18: ='P&L'!F13*$D$9/365 -> 30.018236 | F18: ='P&L'!G13*$D$9/365 -> 31.835139 | G18: ='P&L'!H13*$D$9/365 -> 32.879977 | H18: ='P&L'!I13*$D$9/365 -> 32.913463 | I18: ='P&L'!J13*$D$9/365 -> 33.192533 | J18: ='P&L'!K13*$D$9/365 -> 32.120348 | K18: ='P&L'!L13*$D$9/365 -> 31.306429 | L18: =K18*1.05 -> 32.871751
A19: Accounts Payable (= ~18 days of total COGS) | B19: $M | C19: 0 | D19: ='P&L'!D14*$D$10/365 -> 10.284362 | E19: ='P&L'!E14*$D$10/365 -> 10.841163 | F19: ='P&L'!F14*$D$10/365 -> 15.392476 | G19: ='P&L'!G14*$D$10/365 -> 20.061992 | H19: ='P&L'!H14*$D$10/365 -> 24.369191 | I19: ='P&L'!I14*$D$10/365 -> 28.192209 | J19: ='P&L'!J14*$D$10/365 -> 31.517549 | K19: ='P&L'!K14*$D$10/365 -> 34.275287 | L19: ='P&L'!L14*$D$10/365 -> 36.40893
A20: Other NWC (= 1.5% of revenue) | B20: $M | C20: 0 | D20: ='P&L'!D8*$D$11 -> 7.8204 | E20: ='P&L'!E8*$D$11 -> 13.190082 | F20: ='P&L'!F8*$D$11 -> 19.278321 | G20: ='P&L'!G8*$D$11 -> 25.888076 | H20: ='P&L'!H8*$D$11 -> 32.428793 | I20: ='P&L'!I8*$D$11 -> 38.726394 | J20: ='P&L'!J8*$D$11 -> 44.73741 | K20: ='P&L'!K8*$D$11 -> 50.329516 | L20: ='P&L'!L8*$D$11 -> 55.371915
A22: 3. Change in WC (positive = cash source)
A23: Δ Deferred Revenue (liability ↑ = source) | B23: $M | D23: =D17-C17 -> 123 | E23: =E17-D17 -> 183.04881 | F23: =F17-E17 -> 217.34233 | G23: =G17-F17 -> 216.78772 | H23: =H17-G17 -> 212.75643 | I23: =I17-H17 -> 200.70096 | J23: =J17-I17 -> 194.01238 | K23: =K17-J17 -> 172.97435 | L23: =L17-K17 -> 157.99635
A24: Δ Inventory (asset ↑ = use) | B24: $M | D24: =-(D18-C18) -> -24.530795 | E24: =-(E18-D18) -> -5.4874415 | F24: =-(F18-E18) -> -1.8169026 | G24: =-(G18-F18) -> -1.0448381 | H24: =-(H18-G18) -> -0.033486728 | I24: =-(I18-H18) -> -0.27906968 | J24: =-(J18-I18) -> 1.0721847 | K24: =-(K18-J18) -> 0.81391943 | L24: =-(L18-K18) -> -1.5653215
A25: Δ Accounts Payable (liability ↑ = source) | B25: $M | D25: =D19-C19 -> 10.284362 | E25: =E19-D19 -> 0.55680177 | F25: =F19-E19 -> 4.5513122 | G25: =G19-F19 -> 4.6695167 | H25: =H19-G19 -> 4.3071983 | I25: =I19-H19 -> 3.8230179 | J25: =J19-I19 -> 3.3253403 | K25: =K19-J19 -> 2.7577381 | L25: =L19-K19 -> 2.1336435
A26: Δ Other NWC (asset ↑ = use) | B26: $M | D26: =-(D20-C20) -> -7.8204 | E26: =-(E20-D20) -> -5.3696822 | F26: =-(F20-E20) -> -6.088239 | G26: =-(G20-F20) -> -6.6097548 | H26: =-(H20-G20) -> -6.5407168 | I26: =-(I20-H20) -> -6.2976012 | J26: =-(J20-I20) -> -6.0110156 | K26: =-(K20-J20) -> -5.5921066 | L26: =-(L20-K20) -> -5.0423989
A27: Total Δ NWC (cash impact) | B27: $M | D27: =SUM(D23:D26) -> 100.93317 | E27: =SUM(E23:E26) -> 172.74849 | F27: =SUM(F23:F26) -> 213.9885 | G27: =SUM(G23:G26) -> 213.80265 | H27: =SUM(H23:H26) -> 210.48943 | I27: =SUM(I23:I26) -> 197.9473 | J27: =SUM(J23:J26) -> 192.39889 | K27: =SUM(K23:K26) -> 170.9539 | L27: =SUM(L23:L26) -> 153.52227
A29: 4. Cash Roll-Forward (pre-IPO; no debt service / dividends / buybacks)
A30: Beginning Cash | B30: $M | D30: =$D$12 -> 75 | E30: =D34 -> 63.840767 | F30: =E34 -> 729.51888 | G30: =F34 -> 840.48748 | H30: =G34 -> 1051.8183 | I30: =H34 -> 1403.473 | J30: =I34 -> 1828.4791 | K30: =J34 -> 2353.4127 | L30: =K34 -> 2993.7967
A31: + Series G proceeds | B31: $M | D31: =$D$14 -> 0 | E31: =$E$14 -> 575
A32: + Unlevered Free Cash Flow (FCF tab) | B32: $M | D32: =FCF!D18 -> -11.159233 | E32: =FCF!E18 -> 90.678108 | F32: =FCF!F18 -> 110.9686 | G32: =FCF!G18 -> 211.33079 | H32: =FCF!H18 -> 351.65478 | I32: =FCF!I18 -> 425.006 | J32: =FCF!J18 -> 524.93365 | K32: =FCF!K18 -> 640.38402 | L32: =FCF!L18 -> 760.06186
A34: Ending Cash | B34: $M | D34: =D30+D31+D32 -> 63.840767 | E34: =E30+E31+E32 -> 729.51888 | F34: =F30+F32 -> 840.48748 | G34: =G30+G32 -> 1051.8183 | H34: =H30+H32 -> 1403.473 | I34: =I30+I32 -> 1828.4791 | J34: =J30+J32 -> 2353.4127 | K34: =K30+K32 -> 2993.7967 | L34: =L30+L32 -> 3753.8586

Sheet WACC Bottom-Up
A1: WHOOP — Bottom-Up WACC Build (Justification)
A2: Cross-check on Damodaran sector approach used in Assumptions!F74. Methodology: 3Y weekly Bloomberg-adjusted betas + Oura tender-anchored liquidity premium. Pure justification — does NOT feed DCF.
A3: Source: research/wacc-bottom-up-build.md (May 5, 2026). Replaces 5Y monthly + Hiive premium methodology.
A5: Executive Summary
A6: • Bottom-up bucket-median unlevered betas (Bloomberg-adj, 3Y weekly): B1 = 1.01, B2 = 1.00 (ex-PTON), B3 = 0.92. Tight clustering.
A7: • WHOOP blended βᵤ = 0.95–0.99 across Bear/Base/Bull; Damodaran sector blended = 0.81–0.85. Delta narrowed from +0.40 (5Y monthly) to +0.10–0.18.
A8: • Revenue-weighted ERP = 4.61% Base (vs. pure US 4.46%); +11bps from ~42% intl mix.
A9: • Liquidity premium = +2.0pp anchored to Oura Jan 2026 tender at 25% discount to Series E (Oct 2025); replaces prior +5pp Hiive figure.
A10: • Bottom-up WACC ~11.6% Base vs. Damodaran sector ~10.4% Base — two methods converge within ~1pp. Triangulation finding.
A13: §1. Per-Comp Inputs & Hamada Unlevered Betas
A14: 3Y weekly OLS regression vs. ^GSPC, 157 obs (May 2023 – May 2026). Bloomberg adj: β_adj = (2/3)×β_raw + (1/3)×1.0. Hamada: βᵤ = βL / [1 + (1−t)×(D/E)].
A16: Comp | B16: Bucket | C16: β_raw | D16: β_adj | E16: R² | F16: Mkt Cap ($M) | G16: Debt ($M) | H16: Cash ($M) | I16: D/E | J16: ETR (3Y agg) | K16: Marg Tax | L16: Tax Used | M16: βᵤ (adj) | N16: βᵤ (raw chk)
A17: Garmin (GRMN) | B17: B1 Hardware | C17: 1.029 | D17: 1.019 | E17: 0.216 | F17: 45250 | G17: 216 | H17: 2700 | I17: =G17/F17 -> 0.0047734807 | J17: 0.111 | K17: 0.21 | L17: =K17 -> 0.21 | M17: =D17/(1+(1-L17)*I17) -> 1.0151717 | N17: =C17/(1+(1-L17)*I17) -> 1.0251342
A18: Peloton (PTON) | B18: B2 Sub (distressed) | C18: 2.283 | D18: 1.855 | E18: 0.185 | F18: 2200 | G18: 1950 | H18: 1180 | I18: =G18/F18 -> 0.88636364 | J18: n/m | K18: 0.25 | L18: =K18 -> 0.25 | M18: =D18/(1+(1-L18)*I18) -> 1.1142662 | N18: =C18/(1+(1-L18)*I18) -> 1.3713584
A19: Spotify (SPOT) | B19: B2 Sub (mature) | C19: 1.014 | D19: 1.01 | E19: 0.134 | F19: 86260 | G19: 549 | H19: 7260 | I19: =G19/F19 -> 0.0063644795 | J19: 0.079 | K19: 0.25 | L19: =K19 -> 0.25 | M19: =D19/(1+(1-L19)*I19) -> 1.0052018 | N19: =C19/(1+(1-L19)*I19) -> 1.0091828
A20: Dexcom (DXCM) | B20: B3 Health Data | C20: 1.08 | D20: 1.054 | E20: 0.119 | F20: 22950 | G20: 1380 | H20: 2420 | I20: =G20/F20 -> 0.060130719 | J20: 0.221 | K20: 0.25 | L20: =K20 -> 0.25 | M20: =D20/(1+(1-L20)*I20) -> 1.0085178 | N20: =C20/(1+(1-L20)*I20) -> 1.0333959
A21: ResMed (RMD) | B21: B3 Health Data | C21: 0.962 | D21: 0.974 | E21: 0.181 | F21: 30150 | G21: 843 | H21: 1660 | I21: =G21/F21 -> 0.027960199 | J21: 0.179 | K21: 0.27 | L21: =K21 -> 0.27 | M21: =D21/(1+(1-L21)*I21) -> 0.9545174 | N21: =C21/(1+(1-L21)*I21) -> 0.94275743
A22: Masimo (MASI) | B22: B3 Health Data | C22: 0.885 | D22: 0.924 | E22: 0.09 | F22: 9310 | G22: 559 | H22: 152 | I22: =G22/F22 -> 0.060042965 | J22: n/m | K22: 0.25 | L22: =K22 -> 0.25 | M22: =D22/(1+(1-L22)*I22) -> 0.88418326 | N22: =C22/(1+(1-L22)*I22) -> 0.84686384
A23: iRhythm (IRTC) | B23: B3 Health Data | C23: 0.816 | D23: 0.877 | E23: 0.057 | F23: 4090 | G23: 729 | H23: 550 | I23: =G23/F23 -> 0.17823961 | J23: n/m | K23: 0.25 | L23: =K23 -> 0.25 | M23: =D23/(1+(1-L23)*I23) -> 0.7735871 | N23: =C23/(1+(1-L23)*I23) -> 0.71978002
A24: R² caveat: range 5.7% (IRTC) to 21.6% (GRMN) — standard error on each β ~±0.20–0.30. Bucket medians of 4 names (B3) more robust than singletons.
A27: §2. Bucket Median Unlevered Betas
A29: Bucket | B29: Comps | C29: Median βᵤ (incl PTON) | D29: Median βᵤ (ex-PTON) | E29: Min | F29: Max | G29: Range
A30: B1 Hardware | B30: GRMN | C30: =MEDIAN(M17) -> 1.0151717 | D30: =MEDIAN(M17) -> 1.0151717 | E30: =MIN(M17) -> 1.0151717 | F30: =MAX(M17) -> 1.0151717 | G30: =F30-E30 -> 0
A31: B2 Subscription | B31: PTON, SPOT | C31: =MEDIAN(M18:M19) -> 1.059734 | D31: =MEDIAN(M19) -> 1.0052018 | E31: =MIN(M18:M19) -> 1.0052018 | F31: =MAX(M18:M19) -> 1.1142662 | G31: =F31-E31 -> 0.1090644
A32: B3 Health Data | B32: DXCM, RMD, MASI, IRTC | C32: =MEDIAN(M20:M23) -> 0.91935033 | D32: =MEDIAN(M20:M23) -> 0.91935033 | E32: =MIN(M20:M23) -> 0.7735871 | F32: =MAX(M20:M23) -> 1.0085178 | G32: =F32-E32 -> 0.23493072
A33: Notes:
A34: • B2 ex-PTON is primary anchor; PTON's Hamada output contaminated by distressed-equity dynamics (D/E 0.89, levered β 1.86 adj).
A35: • B3 4-comp median robust to outliers — anchored by RMD (0.95) and MASI (0.88) as middle two; DXCM (1.01) and IRTC (0.77) are bookends.
A37: §3. Damodaran Sector Cross-Check (Jan 2026)
A39: Bucket | B39: Bottom-up βᵤ (ex-PTON) | C39: Damodaran Sector | D39: Sector βᵤ | E39: # Firms | F39: Delta | G39: 5Y mo Delta (prior)
A40: B1 Hardware | B40: =D30 -> 1.0151717 | C40: Electronics (Consumer & Office) | D40: 0.83 | E40: 8 | F40: =B40-D40 -> 0.18517174 | G40: 0.4
A41: B2 Subscription | B41: =D31 -> 1.0052018 | C41: Software (Entertainment) | D41: 1.01 | E41: 77 | F41: =B41-D41 -> -0.0047981897 | G41: 0.43
A42: B3 Health Data | B42: =D32 -> 0.91935033 | C42: HC Info & Tech | D42: 0.99 | E42: 115 | F42: =B42-D42 -> -0.07064967 | G42: 0.39
A43: Convergence finding: under 3Y weekly methodology, bucket betas converge to within ±0.10 of Damodaran sector medians. Idiosyncratic events filtered out (IRTC 2021 CMS, PTON 2021 collapse); Bloomberg adjustment shrinks toward 1.0.
A46: §4. WHOOP Re-Levered Beta (zero debt → β_L = βᵤ)
A47: Bucket weights pulled live from Assumptions!C84:E86 (Bear/Base/Bull). Damodaran sector blended sourced from Assumptions!C71:E71.
A49: Scenario | B49: B1 Wt | C49: B2 Wt | D49: B3 Wt | E49: B1 βᵤ | F49: B2 βᵤ (ex-PTON) | G49: B3 βᵤ | H49: Blended βᵤ (BU) | I49: Damodaran βᵤ | J49: Delta | K49: Blended βᵤ (PTON-incl)
A50: Bear (40/40/20) | B50: =Assumptions!C85 -> 0.4 | C50: =Assumptions!C86 -> 0.4 | D50: =Assumptions!C87 -> 0.2 | E50: =$D$30 -> 1.0151717 | F50: =$D$31 -> 1.0052018 | G50: =$D$32 -> 0.91935033 | H50: =B50*E50+C50*F50+D50*G50 -> 0.99201948 | I50: =Assumptions!C71 -> 0.85 | J50: =H50-I50 -> 0.14201948 | K50: =B50*$C$30+C50*$C$31+D50*$C$32 -> 1.0138324
A51: Base (20/40/40) | B51: =Assumptions!D85 -> 0.2 | C51: =Assumptions!D86 -> 0.4 | D51: =Assumptions!D87 -> 0.4 | E51: =$D$30 -> 1.0151717 | F51: =$D$31 -> 1.0052018 | G51: =$D$32 -> 0.91935033 | H51: =B51*E51+C51*F51+D51*G51 -> 0.9728552 | I51: =Assumptions!D71 -> 0.83 | J51: =H51-I51 -> 0.1428552 | K51: =B51*$C$30+C51*$C$31+D51*$C$32 -> 0.99466808
A52: Bull (10/30/60) | B52: =Assumptions!E85 -> 0.1 | C52: =Assumptions!E86 -> 0.3 | D52: =Assumptions!E87 -> 0.6 | E52: =$D$30 -> 1.0151717 | F52: =$D$31 -> 1.0052018 | G52: =$D$32 -> 0.91935033 | H52: =B52*E52+C52*F52+D52*G52 -> 0.95468791 | I52: =Assumptions!E71 -> 0.81 | J52: =H52-I52 -> 0.14468791 | K52: =B52*$C$30+C52*$C$31+D52*$C$32 -> 0.97104757
A53: Bloomberg adjustment effect on WHOOP-blended is trivial (<0.02) since blend is already centered near 1.0. Remaining +0.10 to +0.18 vs. Damodaran reflects genuine WHOOP-comp-specific premium over broad sector medians.
A54: Note: Damodaran βᵤ in Assumptions!C71:E71 is bucket-weighted (Bear 0.85/Base 0.83/Bull 0.81 — higher β = more bearish, i.e. B1-heavy hardware mix). Bottom-up bucket-weighted output uses identical weights, so deltas are consistent across all three scenarios.
A57: §5. Revenue-Weighted ERP
A58: WHOOP intl mix ~42% (per stress-test). Intl blend: 50% UK/EU developed, 30% Asia developed, 20% other/GCC.
A60: Country ERPs (Damodaran Jan 2026) | C60: ERP
A61: US | C61: 0.0446
A62: UK / EU developed avg | C62: 0.046
A63: Asia developed avg (JP/AU/SG) | C63: 0.0453
A64: Other / GCC / emerging | C64: 0.057
A66: Blended International ERP | C66: =0.5*C62+0.3*C63+0.2*C64 -> 0.04799
A68: Sensitivity: Intl revenue weight | B68: Intl Wt | C68: US Contrib | D68: Intl Contrib | E68: Blended ERP
A69: Conservative | B69: 0.35 | C69: =(1-B69)*$C$61 -> 0.02899 | D69: =B69*$C$66 -> 0.0167965 | E69: =C69+D69 -> 0.0457865
A70: Base case | B70: 0.42 | C70: =(1-B70)*$C$61 -> 0.025868 | D70: =B70*$C$66 -> 0.0201558 | E70: =C70+D70 -> 0.0460238
A71: Aggressive | B71: 0.5 | C71: =(1-B71)*$C$61 -> 0.0223 | D71: =B71*$C$66 -> 0.023995 | E71: =C71+D71 -> 0.046295
A72: Net effect: +11-19bp vs. pure US ERP. Most intl revenue is developed-market with ERPs near US base — token adjustment, not a swing factor.
A75: §6. Liquidity Premium — Oura Tender Anchor
A76: Oura Jan 2026 tender priced at 25% discount to Oct 2025 Series E (~3-month gap → minimal stale-pricing decay; close to pure DLOM for high-quality wearable comp on credible IPO path).
A78: Translation: DLOM → WACC add-on
A79: Public-comp WACC base (Damodaran sector) | C79: =Assumptions!D74-Assumptions!D73 -> 0.08845
A80: Terminal growth (g) | C80: =Assumptions!D81 -> 0.03
A81: Public (r − g) | C81: =C79-C80 -> 0.05845
A83: DLOM scenario | B83: DLOM % | C83: PV haircut | D83: (r−g) ratio | E83: New (r−g) | F83: Implied add-on
A84: Optimistic (shorter time-to-IPO) | B84: 0.15 | C84: =-B84 -> -0.15 | D84: =1/(1-B84) -> 1.1764706 | E84: =$C$81*D84 -> 0.068764706 | F84: =E84-$C$81 -> 0.010314706
A85: Base (Oura tender) | B85: 0.25 | C85: =-B85 -> -0.25 | D85: =1/(1-B85) -> 1.3333333 | E85: =$C$81*D85 -> 0.077933333 | F85: =E85-$C$81 -> 0.019483333
A86: Conservative (Oura + WHOOP-specific) | B86: 0.35 | C86: =-B86 -> -0.35 | D86: =1/(1-B86) -> 1.5384615 | E86: =$C$81*D86 -> 0.089923077 | F86: =E86-$C$81 -> 0.031473077
A88: Recommended liquidity premium | B88: Bear | C88: Base | D88: Bull
A89: Bottom-up + Oura | B89: 0.025 | C89: 0.02 | D89: 0.015
A90: Existing model (Assumptions!F73) | B90: =Assumptions!C73 -> 0.03 | C90: =Assumptions!D73 -> 0.02 | D90: =Assumptions!E73 -> 0.01
A91: Why not Hiive (-39 to -51%)? Hiive prices common (subordinated to $291M preference stack), captures secondary-market valuation skepticism (not pure DLOM), and reflects thin order-book depth. Oura tender = company-organized, structured price = controlled signal.
A92: Oura's +2.0pp ratifies the existing 1.5% practitioner midpoint with a market anchor.
A95: §7. Synthesis WACC: Bottom-Up vs. Damodaran Sector
A96: Cost of Equity = WACC (zero debt). Build A = current model approach (Assumptions). Build B = bottom-up justification (this tab).
A98: Component | B98: Build A: Damodaran Sector | E98: Build B: Bottom-Up + Oura | H98: Delta (Base)
B99: Bear | C99: Base | D99: Bull | E99: Bear | F99: Base | G99: Bull
A100: Risk-free rate (10Y UST) | B100: =Assumptions!C69 -> 0.043 | C100: =Assumptions!D69 -> 0.043 | D100: =Assumptions!E69 -> 0.043 | E100: =Assumptions!C69 -> 0.043 | F100: =Assumptions!D69 -> 0.043 | G100: =Assumptions!E69 -> 0.043 | H100: =F100-C100 -> 0
A101: Equity Risk Premium | B101: =Assumptions!C70 -> 0.045 | C101: =Assumptions!D70 -> 0.045 | D101: =Assumptions!E70 -> 0.045 | E101: =$E$70 -> 0.0460238 | F101: =$E$70 -> 0.0460238 | G101: =$E$70 -> 0.0460238 | H101: =F101-C101 -> 0.0010238
A102: Unlevered Beta (= levered, no debt) | B102: =Assumptions!C71 -> 0.85 | C102: =Assumptions!D71 -> 0.83 | D102: =Assumptions!E71 -> 0.81 | E102: =$H$50 -> 0.99201948 | F102: =$H$51 -> 0.9728552 | G102: =$H$52 -> 0.95468791 | H102: =F102-C102 -> 0.1428552
A103: Size Premium (CRSP Decile 3) | B103: =Assumptions!C72 -> 0.0081 | C103: =Assumptions!D72 -> 0.0081 | D103: =Assumptions!E72 -> 0.0081 | E103: =Assumptions!C72 -> 0.0081 | F103: =Assumptions!D72 -> 0.0081 | G103: =Assumptions!E72 -> 0.0081 | H103: =F103-C103 -> 0
A104: Liquidity Premium (Oura-anchored vs. CSRP) | B104: =Assumptions!C73 -> 0.03 | C104: =Assumptions!D73 -> 0.02 | D104: =Assumptions!E73 -> 0.01 | E104: =$B$89 -> 0.025 | F104: =$C$89 -> 0.02 | G104: =$D$89 -> 0.015 | H104: =F104-C104 -> 0
A106: Implied WACC | B106: =B100+B101*B102+B103+B104 -> 0.11935 | C106: =C100+C101*C102+C103+C104 -> 0.10845 | D106: =D100+D101*D102+D103+D104 -> 0.09755 | E106: =E100+E101*E102+E103+E104 -> 0.12175651 | F106: =F100+F101*F102+F103+F104 -> 0.11587449 | G106: =G100+G101*G102+G103+G104 -> 0.11003837 | H106: =F106-C106 -> 0.0074244933
A108: Decomposition of Build B − Build A delta (Base case) | C108: Contribution
A109: Beta upgrade (0.83 → 0.97) | C109: =(F102-C102)*F101 -> 0.0065747393
A110: ERP revenue-weighting (4.50% → 4.60%) | C110: =(F101-C101)*C102 -> 0.000849754
A111: Liquidity premium (CSRP 2.00% → Oura 2.00%) | C111: =F104-C104 -> 0
A112: Total | C112: =SUM(C109:C111) -> 0.0074244933
A114: Triangulation: Build A (10.85% Base, current model) and Build B (~11.6% Base, this tab) converge within ~0.7-0.8pp — two independent methods landing close gives the IC committee triangulation confidence. The +0.7pp delta is essentially the bottom-up beta premium (+0.65pp); ERP and liquidity rounding effects are trivial.
A115: DCF tab continues to reference Assumptions!F74 (Build A). This sheet is justification only.
A118: §8. Flagged Gaps & Caveats
A120: # | B120: Gap | D120: Path Forward
A121: 1 | B121: WHOOP actual ETR / NOL position unknown — forecast tax 5-15% range fully estimated | D121: Wait for S-1; sensitivity in Excel
A122: 2 | B122: Oura tender details (preferred vs. common) not fully disclosed | D122: Sacra paywall has more detail; not blocking
A123: 3 | B123: PTON βᵤ still distorted by distress dynamics even under 3Y weekly | D123: Use ex-PTON as primary; PTON-incl as overlay (col K, Section 4)
A124: 4 | B124: IRTC convertible debt treatment: βᵤ = 0.774 (debt) vs 0.877 (equity) | D124: B3 median essentially unchanged either way; use 0.774 primary
A125: 5 | B125: MASI deal-pending compression: stock pinned to $180 since Feb 2026; vol artificially low | D125: MASI exits comp set at H2 2026 close — flag and move on
A126: 6 | B126: R² on per-comp regressions weak (5.7-21.6%); single-name β std error ±0.20-0.30 | D126: Bucket medians smooth; Bloomberg adj is partial correction
A127: 7 | B127: B2 ex-PTON has only SPOT (n=1); SPOT 1.01 β reflects post-2024 phase-change | D127: Sensitivity: try B2 = 1.20; spec recommends current β as forward-looking proxy
A128: 8 | B128: Public-comp WACC base for Oura translation — if 11% used vs 10%, +2pp → +1.8pp | D128: Documented; the 10% base is itself the Damodaran sector output
A129: 9 | B129: S&P 500 as sole benchmark; SPOT's true reference could be MSCI World | D129: Sensitivity: re-run vs MSCI ACWI; expected impact <0.05 on β
A130: 10 | B130: 3Y weekly window excludes COVID-recovery dynamics; forward β in 2027+ may differ | D130: Acknowledge — current-state estimate by design
A132: Sources & Methodology
...

Sheet DCF
A1: WHOOP — Discounted Cash Flow
A2: $M; Calendar Year; Base case below — see Sensitivity tab for ranges
A3: ⚠ Integrity flags: TV divergence 30% (>25% threshold), TV % EV 78% (>75% threshold) — both improved materially after WC wiring. See notes on C30, C33
B5: Units | C5: 2025 | D5: 2026 | E5: 2027 | F5: 2028 | G5: 2029 | H5: 2030 | I5: 2031 | J5: 2032 | K5: 2033
A7: 1. Cash Flow & Discounting
A8: Revenue (memo) | B8: $M | C8: ='P&L'!D8 -> 521.36 | D8: ='P&L'!E8 -> 879.33881 | E8: ='P&L'!F8 -> 1285.2214 | F8: ='P&L'!G8 -> 1725.8717 | G8: ='P&L'!H8 -> 2161.9195 | H8: ='P&L'!I8 -> 2581.7596 | I8: ='P&L'!J8 -> 2982.494 | J8: ='P&L'!K8 -> 3355.3011 | K8: ='P&L'!L8 -> 3691.461 | M8: ← From P&L tab
A9: Unlevered Free Cash Flow | B9: $M | C9: =FCF!D18 -> -11.159233 | D9: =FCF!E18 -> 90.678108 | E9: =FCF!F18 -> 110.9686 | F9: =FCF!G18 -> 211.33079 | G9: =FCF!H18 -> 351.65478 | H9: =FCF!I18 -> 425.006 | I9: =FCF!J18 -> 524.93365 | J9: =FCF!K18 -> 640.38402 | K9: =FCF!L18 -> 760.06186 | M9: ← From FCF tab (single source of truth)
A10: FCF Margin % | B10: % | C10: =IFERROR(C9/C8,0) -> -0.021404083 | D10: =IFERROR(D9/D8,0) -> 0.10312079 | E10: =IFERROR(E9/E8,0) -> 0.086342013 | F10: =IFERROR(F9/F8,0) -> 0.12244872 | G10: =IFERROR(G9/G8,0) -> 0.16265859 | H10: =IFERROR(H9/H8,0) -> 0.16461874 | I10: =IFERROR(I9/I8,0) -> 0.17600493 | J10: =IFERROR(J9/J8,0) -> 0.19085739 | K10: =IFERROR(K9/K8,0) -> 0.2058973
A12: WACC | B12: % | C12: n/a | D12: =Assumptions!$F$75 -> 0.11587449 | E12: =Assumptions!$F$75 -> 0.11587449 | F12: =Assumptions!$F$75 -> 0.11587449 | G12: =Assumptions!$F$75 -> 0.11587449 | H12: =Assumptions!$F$75 -> 0.11587449 | I12: =Assumptions!$F$75 -> 0.11587449 | J12: =Assumptions!$F$75 -> 0.11587449 | K12: =Assumptions!$F$75 -> 0.11587449 | M12: ← From Assumptions F74
A13: Discount Period (mid-year) | B13: yrs | C13: n/a | D13: 0.5 | E13: 1.5 | F13: 2.5 | G13: 3.5 | H13: 4.5 | I13: 5.5 | J13: 6.5 | K13: 7.5 | M13: Mid-year convention
A14: Discount Factor | B14: x | C14: n/a | D14: =1/(1+D12)^D13 -> 0.94665629 | E14: =1/(1+E12)^E13 -> 0.84835373 | F14: =1/(1+F12)^F13 -> 0.76025909 | G14: =1/(1+G12)^G13 -> 0.68131237 | H14: =1/(1+H12)^H13 -> 0.61056362 | I14: =1/(1+I12)^I13 -> 0.54716155 | J14: =1/(1+J12)^J13 -> 0.49034327 | K14: =1/(1+K12)^K13 -> 0.43942511
A15: PV of Unlevered FCF | B15: $M | C15: n/a | D15: =D9*D14 -> 85.841002 | E15: =E9*E14 -> 94.140629 | F15: =F9*F14 -> 160.66615 | G15: =G9*G14 -> 239.58675 | H15: =H9*H14 -> 259.4932 | I15: =I9*I14 -> 287.22351 | J15: =J9*J14 -> 314.008 | K15: =K9*K14 -> 333.99027 | M15: = UFCF / (1+WACC)^period
A17: 2. Terminal Value
A18: Terminal Year Revenue | B18: $M | C18: =K8 -> 3691.461
A19: Terminal Year EBITDA | B19: $M | C19: ='P&L'!L32 -> 1249.0438
A20: Terminal Year FCF | B20: $M | C20: =K9 -> 760.06186
A21: Exit Multiple (EV/Revenue) | B21: x | C21: =Assumptions!$F$79 -> 3.5 | L21: ← From Assumptions F78
A22: Terminal Value (Exit Multiple) | B22: $M | C22: =C18*C21 -> 12920.114
A23: Terminal Value (Gordon Growth) | B23: $M | C23: =C20*(1+Assumptions!$F$81)/(D12-Assumptions!$F$81) -> 9116.3707 | L23: Gordon: =FCF × (1+g) / (WACC − g)
A24: TV Method Divergence | B24: % | C24: =ABS(C22-C23)/((C22+C23)/2) -> 0.34522229 | L24: If >25%, an assumption is inconsistent
A25: Selected Terminal Value | B25: $M | C25: =(C23+C22) / 2 -> 11018.242
A26: PV of Terminal Value | B26: $M | C26: =C25*K14 -> 4841.6923
A27: TV as % of Total EV | B27: % | C27: =C26/(C26+SUM(D15:K15)) -> 0.73174466 | L27: If >75%, explicit forecast doing too little
A29: 3. Enterprise Value Summary
A30: Sum of PV of FCFs (2026-2033) | B30: $M | C30: =SUM(D15:K15) -> 1774.9495
A31: PV of Terminal Value | B31: $M | C31: =C26 -> 4841.6923
A32: Enterprise Value (DCF Base) | B32: $M | C32: =C30+C31 -> 6616.6418
A34: 4. Equity Bridge
A35: Enterprise Value | B35: $M | C35: =C32 -> 6616.6418
A36: Less: Debt | B36: $M | C36: =-Assumptions!$F$62 -> -10 | L36: ~$0 (minimal)
A37: Plus: Cash | B37: $M | C37: ='WC & Cash'!E34 -> 729.51888 | L37: $600-800M est. post-Series G
A38: Equity Value | B38: $M | C38: =C35+C36+C37 -> 7336.1607
A39: Fully Diluted Shares (M) | B39: M | C39: =Assumptions!$F$55 -> 410 | L39: ~900M (PremierAlts est.)
A40: Equity Value per Share | B40: $/sh | C40: =C38/C39 -> 17.893075
A42: 5. Real Options (Additive — healthcare pathway only)
A43: Healthcare option — Bear scenario range ($M) | B43: $M | C43: =RealOptions!B31 -> 164.15584 | L43: ← Probability × Payoff from Assumptions
A44: Healthcare option — Bull scenario range ($M) | B44: $M | C44: =RealOptions!D31 -> 2609.1236
A45: Healthcare option — active scenario ($M) | B45: $M | C45: =RealOptions!B36 -> 940.08677
A46: Expected Option Value | B46: $M | C46: =C45 -> 940.08677
A47: Total EV (DCF + Options) | B47: $M | C47: =C32+C46 -> 7556.7286
A49: 6. Scenario Comparison vs Series G — Equity Value Basis
A50: DCF Base Case Equity Value | B50: $M | C50: =C38 -> 7336.1607
A51: DCF + Options Equity Value | B51: $M | C51: =C38+C46 -> 8276.2474
A52: Series G Mark | B52: $M | C52: 10100
A53: DCF Premium / (Discount) to Series G | B53: % | C53: =C50/C52-1 -> -0.27364746 | M53: Base case = 'WHOOP executes plan'
A54: DCF + Options Premium / (Discount) to Series G | B54: % | C54: =C51/C52-1 -> -0.18056956 | M54: Options = 'Healthcare reimbursement pathway materializes (probability-weighted, 15-25%)'
A56: 7. Probability-Weighting Diagnostics — Input vs Scenario Weighting Triangulation
A57: Diagnostic block compares input-level weighting (ProbWeighted scenario) vs. scenario-level weighting (independent DCF runs combined). Jensen gap = E[DCF(inputs)] vs P_w · DCF(scenario). Static snapshot — refresh manually after material input changes.
A59: Scenario | B59: DCF EV ($M) | C59: Equity ($M) | D59: Equity + Opts ($M) | E59: Real Opts Active ($M) | F59: vs Series G
A60: Bear (after R79 bug fix) | B60: 2055.85 | C60: 2504.21 | D60: 2657.5 | E60: 153.29 | F60: =D60/$C$52-1 -> -0.73688119
A61: Base | B61: 6616.64 | C61: 7336.16 | D61: 8276.25 | E61: 940.09 | F61: =D61/$C$52-1 -> -0.18056931
A62: Bull | B62: 18877.82 | C62: 19882 | D62: 22596.33 | E62: 2714.32 | F62: =D62/$C$52-1 -> 1.2372604
A63: ProbWeighted (input-level) | B63: 7236.6 | C63: 7961.86 | D63: 8901.95 | E63: 940.09 | F63: =D63/$C$52-1 -> -0.11861881
A65: Scenario-weighted bookend (P_Bear=20%, P_Base=50%, P_Bull=30%) | B65: =0.2*B60+0.5*B61+0.3*B62 -> 9382.836 | C65: =0.2*C60+0.5*C61+0.3*C62 -> 10133.522 | D65: =0.2*D60+0.5*D61+0.3*D62 -> 11448.524 | E65: =0.2*E60+0.5*E61+0.3*E62 -> 1314.999 | F65: =D65/$C$52-1 -> 0.13351723
A67: Jensen Gap Analysis (scenario-weighted minus input-weighted)
A68: EV gap ($M) | B68: =B65-B63 -> 2146.236 | C68: =C65-C63 -> 2171.662 | D68: =D65-D63 -> 2546.574
A69: EV gap (%) | B69: =B65/B63-1 -> 0.29658071 | C69: =C65/C63-1 -> 0.27275812 | D69: =D65/D63-1 -> 0.28606923
A70: Interpretation:
A71: • Positive gap = DCF is convex in inputs; ProbWeighted UNDERSTATES true E[EV]. Use scenario-weighted as upper anchor.
A72: • Negative gap = DCF is concave; ProbWeighted OVERSTATES. Use input-weighted as conservative anchor.
A73: • Headline = ProbWeighted (row 63). Bookend = scenario-weighted (row 65). Memo should cite both with the gap as the dispersion story.
A74: • Snapshot manually refreshed via validation pass; rerun if any of the 16 ProbWeighted-eligible inputs change materially.

Sheet RealOptions
A1: WHOOP — Real Options (Healthcare Pathway)
A2: Single-gate decision tree on reimbursable healthcare platform thesis. Class anchor: Lecture 3B (Arundel) — probability-weighted call option on uncertain future cash flows. Decision tree EV; underlying not tradable, so not Black-Scholes. Same economic logic as Arundel sequel rights.
A4: Section 1 — The Binary Gate
A5: Question: Does WHOOP become a reimbursable healthcare platform within decision window?
B6: Bear | C6: Base | D6: Bull
A7: Probability healthcare materializes | B7: =Assumptions!$C$157 -> 0.15 | C7: =Assumptions!$D$157 -> 0.2 | D7: =Assumptions!$E$157 -> 0.25
A8: Probability of failure / indefinite stall | B8: =1-B7 -> 0.85 | C8: =1-C7 -> 0.8 | D8: =1-D7 -> 0.75
A10: Section 2 — Revenue Impact if Materialized
A11: (Computed three times: Bear / Base / Bull scenarios)
A13: 2033 ending members (M) | B13: =Assumptions!C178 -> 7.4999193 | C13: =Assumptions!D178 -> 10.924108 | D13: =Assumptions!E178 -> 16.671983
A14: × Eligibility % (qualifying conditions) | B14: =Assumptions!$C$158 -> 0.3 | C14: =Assumptions!$D$158 -> 0.4 | D14: =Assumptions!$E$158 -> 0.45
A15: = Eligible members (M) | B15: =B13*B14 -> 2.2499758 | C15: =C13*C14 -> 4.3696432 | D15: =D13*D14 -> 7.5023925
A17: × Payer-paid annual ARPU ($/member) | B17: =Assumptions!$C$159 -> 200 | C17: =Assumptions!$D$159 -> 300 | D17: =Assumptions!$E$159 -> 350
A18: = Incremental annual revenue at maturity ($M) | B18: =B15*B17 -> 449.99516 | C18: =C15*C17 -> 1310.893 | D18: =D15*D17 -> 2625.8374
A20: × Healthcare-anchored multiple (x revenue) | B20: =Assumptions!$C$160 -> 5 | C20: =Assumptions!$D$160 -> 6 | D20: =Assumptions!$E$160 -> 6
A21: = Incremental EV at exercise ($M) — undiscounted | B21: =B18*B20 -> 2249.9758 | C21: =C18*C20 -> 7865.3578 | D21: =D18*D20 -> 15755.024
A24: Section 3 — Discounting and Probability Weighting
A25: Years to exercise | B25: =Assumptions!$C$161 -> 7 | C25: =Assumptions!$D$161 -> 5 | D25: =Assumptions!$E$161 -> 4
A26: WACC | B26: =Assumptions!$F$74 -> 0.10845 | C26: =Assumptions!$F$74 -> 0.10845 | D26: =Assumptions!$F$74 -> 0.10845
A27: Discount factor (1/(1+WACC)^t) | B27: =1/(1+B26)^B25 -> 0.48639292 | C27: =1/(1+C26)^C25 -> 0.59761221 | D27: =1/(1+D26)^D25 -> 0.66242325
A28: Discounted incremental EV ($M) | B28: =B21*B27 -> 1094.3723 | C28: =C21*C27 -> 4700.4339 | D28: =D21*D27 -> 10436.494
A30: × Probability of materialization | B30: =B7 -> 0.15 | C30: =C7 -> 0.2 | D30: =D7 -> 0.25
A31: = Expected option value ($M) | B31: =B28*B30 -> 164.15584 | C31: =C28*C30 -> 940.08677 | D31: =D28*D30 -> 2609.1236
A32: = Expected option value ($B) | B32: =B31/1000 -> 0.16415584 | C32: =C31/1000 -> 0.94008677 | D32: =D31/1000 -> 2.6091236
A34: Section 4 — Active Scenario Output
A35: Active scenario | B35: =Assumptions!$B$3 -> Base
A36: Expected option value (active scenario, $M) | B36: =IF($B$35="Bear",B31,IF($B$35="Bull",D31,C31)) -> 940.08677
A37: Expected option value (active scenario, $B) | B37: =B36/1000 -> 0.94008677
A38: Scenario-weighted Expected Option Value (across-scenario, $M) | B38: =Assumptions!$C$2*B31+Assumptions!$E$2*C31+Assumptions!$G$2*D31 -> 1285.6116 | C38: = P_Bear×Bear + P_Base×Base + P_Bull×Bull on B31:D31. Two-layer probability: each scenario already weights by P(materialize) at row 30; this layer weights ACROSS scenarios at the 20/50/30 macro split. Not double-counting — they compound. Asymmetric vs DCF approach: option inputs are coupled at scenario level (eligibility, ARPU, multiple, timing, materialize-prob all move together), so input-weighting cross-scenario would be incoherent. Scenario-weighted is the only valid cross-scenario aggregation for the option.
A39: Scenario-weighted Expected Option Value ($B) | B39: =B38/1000 -> 1.2856116
A40: Section 5 — Justification (memo, not driver)
A41: Honest read on what supports each input. Cite specific comparables and signals.
A43: Probability anchor (RO1 — 15/20/25%)
A44: iRhythm pathway: FDA-cleared cardiac monitoring, took 7+ years from approval to stable national CMS reimbursement. Stock dropped 83% during journey. Base rate evidence for consumer→medical transitions: low and slow.
A45: Dexcom pathway: 15+ year ongoing reimbursement expansion from initial Type 1 diabetes coverage. Each new indication requires separate CMS review.
A46: WHOOP-specific positive signals: CMS Innovation Center Access Program selection (Apr 13, 2026); Abbott + Mayo Clinic as Series G investors; FDA-cleared ECG already shipping; BP Insights with FDA wellness exemptions (Jan 2026).
A47: WHOOP-specific gaps: zero CPT codes filed; no clinical trial data validating diagnostic claims; no disclosed Abbott/Mayo deliverables; no payer revenue projections.
A48: Probability range 15-25% reflects: (a) credible signals justify above pure base rate, (b) absence of clinical/regulatory milestones bounds upside.
A50: Eligibility anchor (RO2 — 30/40/45%)
A51: ~40% of US adults have cardiometabolic risk factors (CDC: 47% HTN, 38% pre-diabetes, 9-12% AFib risk in over-65s, 30% sleep disorders).
A52: WHOOP user base premium-skewed (high health engagement); plausibly overrepresents diagnosable risk factors.
A53: Range 30-45%: bear conservative (only severe cases qualify); bull at calibrated upper end (was 50% wide, tightened to 45% — broad screening eligibility but stops short of aggressive).
... A83: Pushback 1 — "Bull case is consumer-driven, not healthcare-driven"
A84: Acknowledged. Bull case member growth (MG1-MG8 in Assumptions row 169-176) is justified by Series G capital deployment and brand step-function (Peloton-stage IPO mechanics) — NOT by reimbursement assumption. Bull DCF reaches $19.88B equity / $48.49/sh on consumer-only thesis. Healthcare option is layered ON TOP, not embedded IN, the consumer Bull. The two are independent paths: consumer base materializes through ad spend, athlete partnerships, brand awareness; healthcare path materializes through CMS/CPT/clinical work. Conflating them inflates probability — the model treats them as separate (DCF runs on consumer assumptions; option valued discretely; scenario-weighted EV adds them). | B84: Within-Scenario EV ($M) | C84: Macro Weight | D84: Contribution ($M) | E84: % of Total
A85: Bear | B85: =B31 -> 164.15584 | C85: =Assumptions!$C$2 -> 0.2 | D85: =B85*C85 -> 32.831169 | E85: =D85/$D$88 -> 0.025537392
A86: Pushback 2 — "You're already getting an implicit option premium in the comps multiple" | B86: =C31 -> 940.08677 | C86: =Assumptions!$E$2 -> 0.5 | D86: =B86*C86 -> 470.04339 | E86: =D86/$D$88 -> 0.36561849
A87: Partly fair. Consumer wearables comps trade at 3-5x revenue; bucket-3 medtech (Dexcom/ResMed/Masimo/iRhythm) at 5.0-6.4x. WHOOP's blended comp implies the market already prices SOME healthcare optionality — estimating this premium at +0.5-1.0x revenue (= roughly $220-440M EV at 2033 revenue of $3.7B and 12% probability-weighted discount). Recommend interpreting the explicit option value (B36 Base $940M / B38 Scen-Wtd $1,286M) as the FULL PV of the medical pathway, with the comps premium as a CHECK rather than additive layer. If sensitive to double-counting, conservative read: option value PROVES IN at $700-1,000M after netting estimated multiple premium. Memo recommendation: present option value as standalone module; let reader subtract comps premium if they believe it's already priced. | B87: =D31 -> 2609.1236 | C87: =Assumptions!$G$2 -> 0.3 | D87: =B87*C87 -> 782.73708 | E87: =D87/$D$88 -> 0.60884412
A88: Scenario-Weighted Total | C88: =SUM(C85:C87) -> 1 | D88: =SUM(D85:D87) -> 1285.6116 | E88: =SUM(E85:E87) -> 1
A89: Pushback 3 — "What if the medical pathway doesn't materialize — are you overpaying for ARPU?"
A90: Defensible. Consumer ARPU ($338/yr at 2033, blended consumer + B2B) is the primary subscription revenue — NOT contingent on payer reimbursement. WHOOP currently bills $200-300/yr direct-to-consumer at scale. Even if zero medical revenue ever materializes (P(materialize)=0%), the consumer ARPU remains intact. The healthcare option is upside ON TOP of consumer ARPU, not a substitute. The only ARPU at risk is incremental medical-bill ARPU ($200-350/yr from RO3) which only flows in scenarios where the option triggers. Bear case ($164M option) effectively models the "medical doesn't materialize" outcome — still positive because even probability-weighted at 15% × $1.07B intrinsic = $164M residual.
A91: Block B — Total Option Value at Varying Macro Probability Weights ($M)
A92: 5×5 grid: rows = P_Bear, columns = P_Bull. P_Base = 1 - P_Bear - P_Bull. Yellow center = current 20/50/30 macro weights ($1.29B). Cells where P_Bear+P_Bull ≥ 1 return #N/A (invalid).
A94: P_Bear ↓ / P_Bull → | B94: 0.1 | C94: 0.2 | D94: 0.3 | E94: 0.4 | F94: 0.5
A95: 0.1 | B95: =IF($A95+B$94>=1,NA(),$A95*$B$31+(1-$A95-B$94)*$C$31+B$94*$D$31) -> 1029.3974 | C95: =IF($A95+C$94>=1,NA(),$A95*$B$31+(1-$A95-C$94)*$C$31+C$94*$D$31) -> 1196.301 | D95: =IF($A95+D$94>=1,NA(),$A95*$B$31+(1-$A95-D$94)*$C$31+D$94*$D$31) -> 1363.2047 | E95: =IF($A95+E$94>=1,NA(),$A95*$B$31+(1-$A95-E$94)*$C$31+E$94*$D$31) -> 1530.1084 | F95: =IF($A95+F$94>=1,NA(),$A95*$B$31+(1-$A95-F$94)*$C$31+F$94*$D$31) -> 1697.0121
A96: 0.15 | B96: =IF($A96+B$94>=1,NA(),$A96*$B$31+(1-$A96-B$94)*$C$31+B$94*$D$31) -> 990.60082 | C96: =IF($A96+C$94>=1,NA(),$A96*$B$31+(1-$A96-C$94)*$C$31+C$94*$D$31) -> 1157.5045 | D96: =IF($A96+D$94>=1,NA(),$A96*$B$31+(1-$A96-D$94)*$C$31+D$94*$D$31) -> 1324.4082 | E96: =IF($A96+E$94>=1,NA(),$A96*$B$31+(1-$A96-E$94)*$C$31+E$94*$D$31) -> 1491.3119 | F96: =IF($A96+F$94>=1,NA(),$A96*$B$31+(1-$A96-F$94)*$C$31+F$94*$D$31) -> 1658.2156
A97: 0.2 | B97: =IF($A97+B$94>=1,NA(),$A97*$B$31+(1-$A97-B$94)*$C$31+B$94*$D$31) -> 951.80427 | C97: =IF($A97+C$94>=1,NA(),$A97*$B$31+(1-$A97-C$94)*$C$31+C$94*$D$31) -> 1118.708 | D97: =IF($A97+D$94>=1,NA(),$A97*$B$31+(1-$A97-D$94)*$C$31+D$94*$D$31) -> 1285.6116 | E97: =IF($A97+E$94>=1,NA(),$A97*$B$31+(1-$A97-E$94)*$C$31+E$94*$D$31) -> 1452.5153 | F97: =IF($A97+F$94>=1,NA(),$A97*$B$31+(1-$A97-F$94)*$C$31+F$94*$D$31) -> 1619.419
A98: 0.25 | B98: =IF($A98+B$94>=1,NA(),$A98*$B$31+(1-$A98-B$94)*$C$31+B$94*$D$31) -> 913.00773 | C98: =IF($A98+C$94>=1,NA(),$A98*$B$31+(1-$A98-C$94)*$C$31+C$94*$D$31) -> 1079.9114 | D98: =IF($A98+D$94>=1,NA(),$A98*$B$31+(1-$A98-D$94)*$C$31+D$94*$D$31) -> 1246.8151 | E98: =IF($A98+E$94>=1,NA(),$A98*$B$31+(1-$A98-E$94)*$C$31+E$94*$D$31) -> 1413.7188 | F98: =IF($A98+F$94>=1,NA(),$A98*$B$31+(1-$A98-F$94)*$C$31+F$94*$D$31) -> 1580.6225
A99: 0.3 | B99: =IF($A99+B$94>=1,NA(),$A99*$B$31+(1-$A99-B$94)*$C$31+B$94*$D$31) -> 874.21118 | C99: =IF($A99+C$94>=1,NA(),$A99*$B$31+(1-$A99-C$94)*$C$31+C$94*$D$31) -> 1041.1149 | D99: =IF($A99+D$94>=1,NA(),$A99*$B$31+(1-$A99-D$94)*$C$31+D$94*$D$31) -> 1208.0185 | E99: =IF($A99+E$94>=1,NA(),$A99*$B$31+(1-$A99-E$94)*$C$31+E$94*$D$31) -> 1374.9222 | F99: =IF($A99+F$94>=1,NA(),$A99*$B$31+(1-$A99-F$94)*$C$31+F$94*$D$31) -> 1541.8259
A101: Floor / Range / Lever Analysis
A102: Min option value (most conservative) | B102: =B99 -> 874.21118 | C102: P_Bear=30%, P_Bull=10% (extreme bearish weights)
A103: Max option value (most aggressive) | B103: =F95 -> 1697.0121 | C103: P_Bear=10%, P_Bull=50% (extreme bullish weights)
A104: Range (max - min) | B104: =B103-B102 -> 822.80092 | C104: ="Total swing across reasonable bounds = $"&TEXT(B104/1000,"0.00")&"B" -> Total swing across reasonable bounds = $0.82B
A105: Sensitivity to P_Bull (10→50pp shift, holding P_Bear=20%) | B105: =(F97-B97)/4 -> 166.90368 | C105: $ per 10pp P_Bull shift — dominant lever
A106: Sensitivity to P_Bear (10→30pp shift, holding P_Bull=30%) | B106: =(D95-D99)/4 -> 38.796547 | C106: $ per 10pp P_Bear shift — secondary lever
A108: Read
A109: ="At 20/50/30 base weights, scenario-weighted option value is $"&TEXT(D97/1000,"0.00")&"B (yellow center) — "&TEXT(D97/C31-1,"+0%;-0%")&" vs Base DCF active scenario ($"&TEXT(C31/1000,"0.00")&"B). Across the full grid, option value spans $"&TEXT(B102/1000,"0.00")&"B (max-bear: 30% Bear / 10% Bull) to $"&TEXT(B103/1000,"0.00")&"B (max-bull: 10% Bear / 50% Bull) — a $"&TEXT(B104/1000,"0.00")&"B range. P_Bull is the dominant lever ($"&TEXT(B105,"#,##0")&"M per 10pp shift — 4x larger than P_Bear at $"&TEXT(B106,"#,##0")&"M). Under any plausible weighting where P_Bull ≥ 20% AND P_Bear ≤ 25%, option value sits comfortably ABOVE Base DCF $"&TEXT(C31,"#,##0")&"M. Only the extreme bearish corner (30%/10%, $"&TEXT(B102,"#,##0")&"M) drops below — and that scenario implies probabilities materially out of line with management's stated ambition." -> At 20/50/30 base weights, scenario-weighted option value is $1.29B (yellow center) — +37% vs Base DCF active scenario ($0.94B). Across the full grid, option value spans $0.87B (max-bear: 30% Bear / 10% Bull) to $1.70B (max-bull: 10% Bear / 50% Bull) — a $0.82B range. P_Bull is the dominant lever ($167M per 10pp shift — 4x larger than P_Bear at $39M). Under any plausible weighting where P_Bull ≥ 20% AND P_Bear ≤ 25%, option value sits comfortably ABOVE Base DCF $940M. Only the extreme bearish corner (30%/10%, $874M) drops below — and that scenario implies probabilities materially out of line with management's stated ambition.

Sheet Comps
A1: WHOOP — Public Comp Triangulation (Three-Thesis Framework)
A2: Comps grouped by what WHOOP would *become* under each thesis (Failed Pivot / Subscription Executed / Healthcare Platform). Within each thesis comps share economic structure; across theses they don't — so we don't average across them. Composite span feeds Football Field. Oura shown as parallel reference, never blended. Garmin reclassified as form factor reference, doesn't anchor any thesis.
A4: 1. WHOOP Inputs
A6: Recognized revenue (2025, $M) | B6: ='Revenue Build'!D20 -> 521.36
A7: Bookings run-rate ($M) | B7: 1100
A8: Gross margin (model 2026E) | B8: ='P&L'!E16 -> 0.75
A9: Implied gross profit — recognized basis | B9: =B6*B8 -> 391.02
A10: Implied gross profit — bookings basis | B10: =B7*B8 -> 825
A11: LTM bookings growth | B11: 1.03
A12: NTM growth (model) | B12: 0.7
A13: Series G mark ($M) | B13: 1100
A15: 2. Master Comp Table
A16: Multiples per spec (May 5, 2026 refresh). Tier T1=direct comp parallel ref, T2=structural analogue thesis anchor, T3=boundary marker thesis anchor, T4=historical footnote. Thesis tag drives which bracket each comp anchors.
A18: Comp | B18: Ticker | C18: Tier | D18: Thesis | E18: EV/Rev NTM | F18: EV/GP NTM | G18: NTM Growth | H18: Gross Margin | I18: EV/Rev / Growth | J18: Notes
A19: Peloton | B19: PTON | C19: T3 | D19: 1 — Failed Pivot | E19: 1.22 | F19: 2.9 | G19: -0.05 | H19: 0.42 | I19: =IFERROR(E19/(G19*100),"n/m") -> -0.244 | J19: Hardware-sub failed pivot. Bear floor.
A20: Sonos | B20: SONO | C20: T3 | D20: 1 — Failed Pivot | E20: 1.07 | F20: 2.4 | G20: -0.02 | H20: 0.45 | I20: =IFERROR(E20/(G20*100),"n/m") -> -0.535 | J20: Consumer durable in revenue decline.
A21: GoPro | B21: GPRO | C21: T3 | D21: 1 — Failed Pivot | E21: 0.4 | F21: 1.2 | G21: -0.08 | H21: 0.33 | I21: =IFERROR(E21/(G21*100),"n/m") -> -0.05 | J21: Failed subscription pivot, terminal decline.
A22: Spotify | B22: SPOT | C22: T2 | D22: 2 — Subscription Executed | E22: 3.66 | F22: 11.4 | G22: 0.13 | H22: 0.32 | I22: =IFERROR(E22/(G22*100),"n/m") -> 0.28153846 | J22: Mature pure subscription. Profitability proof drove +116% multiple expansion 3yr.
A23: Roku | B23: ROKU | C23: T2 | D23: 2 — Subscription Executed | E23: 3.02 | F23: 6.9 | G23: 0.12 | H23: 0.44 | I23: =IFERROR(E23/(G23*100),"n/m") -> 0.25166667 | J23: Platform with hardware as CAC, profitability inflection.
A24: Dexcom | B24: DXCM | C24: T2 | D24: 3 — Healthcare Platform | E24: 4.24 | F24: 7.1 | G24: 0.11 | H24: 0.6 | I24: =IFERROR(E24/(G24*100),"n/m") -> 0.38545455 | J24: FDA-cleared CGM, reimbursed. Compressed -67% from 13.8x in 2023.
A25: iRhythm | B25: IRTC | C25: T2 | D25: 3 — Healthcare Platform | E25: 4.65 | F25: 6.5 | G25: 0.18 | H25: 0.7 | I25: =IFERROR(E25/(G25*100),"n/m") -> 0.25833333 | J25: Cardiac monitoring, CMS-reimbursed. Closest pathway analog. Compressed -51% from peak.
A26: ResMed | B26: RMD | C26: T3 | D26: 3 — Healthcare Platform | E26: 5.23 | F26: 8.9 | G26: 0.08 | H26: 0.59 | I26: =IFERROR(E26/(G26*100),"n/m") -> 0.65375 | J26: Sleep apnea, reimbursed, mature.
A27: Masimo | B27: MASI | C27: T3 | D27: 3 — Healthcare Platform | E27: 5.96 | F27: 9.5 | G27: 0.1 | H27: 0.63 | I27: =IFERROR(E27/(G27*100),"n/m") -> 0.596 | J27: Hospital monitoring, sensor-first.
A28: Garmin | B28: GRMN | C28: T2 | D28: Form factor ref — not anchored | E28: 5.25 | F28: 9.8 | G28: 0.06 | H28: 0.59 | I28: =IFERROR(E28/(G28*100),"n/m") -> 0.875 | J28: Diversified hardware conglomerate. WHOOP isn't fundamentally hardware. Reference only.
A29: Oura | B29: (private) | C29: T1 | D29: Parallel ref — never blended | E29: 13 | F29: 26 | G29: 1.29 | H29: 0.5 | I29: =IFERROR(E29/(G29*100),"n/m") -> 0.10077519 | J29: Only direct comp; private. Same Gornall/Strebulaev critique applies as Series G.
A30: Fitbit (IPO 2015) | B30: FIT | C30: T4 | D30: Historical footnote | E30: 2.2 | J30: Peak public-market mark before category compression.
A31: Fitbit (Google acquire 2021) | B31: FIT | C31: T4 | D31: Historical footnote | E31: 1.5 | J31: Strategic exit; revenue-declining at sale.
A33: 3. Thesis Summary — Bracketed Implied WHOOP Valuations
A34: Three theses about what WHOOP becomes. Within each, comps share economic structure; across theses they don't. Each bracket shows EV/Rev and EV/GP ranges and computes 4 implied-EV variants × WHOOP financials.
A36: Thesis 1 — Failed Pivot (Bear)
A37: Anchors: Peloton, Sonos, GoPro. Question: what if WHOOP fails to defend subscription economics and reverts to hardware-dependent revenue?
B38: Low | C38: High | D38: Median
A39: EV/Rev NTM | B39: =MIN(E19:E21) -> 0.4 | C39: =MAX(E19:E21) -> 1.22 | D39: =MEDIAN(E19:E21) -> 1.07
A40: EV/GP NTM | B40: =MIN(F19:F21) -> 1.2 | C40: =MAX(F19:F21) -> 2.9 | D40: =MEDIAN(F19:F21) -> 2.4
A41: Implied EV ($M):
A42: Recognized × EV/Rev | B42: =B39*$B$6 -> 208.544 | C42: =C39*$B$6 -> 636.0592 | D42: =D39*$B$6 -> 557.8552
A43: Bookings × EV/Rev | B43: =B39*$B$7 -> 440 | C43: =C39*$B$7 -> 1342 | D43: =D39*$B$7 -> 1177
A44: Recognized GP × EV/GP | B44: =B40*$B$9 -> 469.224 | C44: =C40*$B$9 -> 1133.958 | D44: =D40*$B$9 -> 938.448
A45: Bookings GP × EV/GP | B45: =B40*$B$10 -> 990 | C45: =C40*$B$10 -> 2392.5 | D45: =D40*$B$10 -> 1980
A47: Thesis 2 — Subscription Executed (Base)
A48: Anchors: Spotify, Roku. Question: what if WHOOP becomes a premium consumer subscription business at scale? EV/GP is the more analytically relevant multiple here — normalizes WHOOP's GM advantage (75% vs Spotify 32% / Roku 44%).
B49: Low | C49: High | D49: Median
A50: EV/Rev NTM | B50: =MIN(E22:E23) -> 3.02 | C50: =MAX(E22:E23) -> 3.66 | D50: =MEDIAN(E22:E23) -> 3.34
A51: EV/GP NTM | B51: =MIN(F22:F23) -> 6.9 | C51: =MAX(F22:F23) -> 11.4 | D51: =MEDIAN(F22:F23) -> 9.15
A52: Implied EV ($M):
A53: Recognized × EV/Rev | B53: =B50*$B$6 -> 1574.5072 | C53: =C50*$B$6 -> 1908.1776 | D53: =D50*$B$6 -> 1741.3424
A54: Bookings × EV/Rev | B54: =B50*$B$7 -> 3322 | C54: =C50*$B$7 -> 4026 | D54: =D50*$B$7 -> 3674
A55: Recognized GP × EV/GP | B55: =B51*$B$9 -> 2698.038 | C55: =C51*$B$9 -> 4457.628 | D55: =D51*$B$9 -> 3577.833
A56: Bookings GP × EV/GP | B56: =B51*$B$10 -> 5692.5 | C56: =C51*$B$10 -> 9405 | D56: =D51*$B$10 -> 7548.75
A58: Thesis 3 — Healthcare Platform (Bull / Optionality)
A59: Anchors: Dexcom, iRhythm, ResMed, Masimo. Question: what if WHOOP becomes a reimbursable health-data platform with FDA/CMS pathway success? Note multiples have de-rated -51 to -67% from 2023 peaks — bull case more constrained than 2023 multiples would suggest.
B60: Low | C60: High | D60: Median
A61: EV/Rev NTM | B61: =MIN(E24:E27) -> 4.24 | C61: =MAX(E24:E27) -> 5.96 | D61: =MEDIAN(E24:E27) -> 4.94
A62: EV/GP NTM | B62: =MIN(F24:F27) -> 6.5 | C62: =MAX(F24:F27) -> 9.5 | D62: =MEDIAN(F24:F27) -> 8
A63: Implied EV ($M):
A64: Recognized × EV/Rev | B64: =B61*$B$6 -> 2210.5664 | C64: =C61*$B$6 -> 3107.3056 | D64: =D61*$B$6 -> 2575.5184
A65: Bookings × EV/Rev | B65: =B61*$B$7 -> 4664 | C65: =C61*$B$7 -> 6556 | D65: =D61*$B$7 -> 5434
A66: Recognized GP × EV/GP | B66: =B62*$B$9 -> 2541.63 | C66: =C62*$B$9 -> 3714.69 | D66: =D62*$B$9 -> 3128.16
A67: Bookings GP × EV/GP | B67: =B62*$B$10 -> 5362.5 | C67: =C62*$B$10 -> 7837.5 | D67: =D62*$B$10 -> 6600
A69: 4. Composite Span (across all theses)
A71: Lowest defensible (Bear, recognized basis) | B71: =MIN(B42:B45) -> 208.544
A72: Highest defensible (Sub Executed, bookings GP × EV/GP) | B72: =MAX(C56,C67) -> 9405
A73: Most defensible base (T2 median, recognized GP × EV/GP) | B73: =D55 -> 3577.833
A74: Series G mark | B74: =B13 -> 1100
A76: 5. Oura — Private Market Category Reference (parallel, never blended)
A77: Oura at 13x recognized is a private-market data point on category pricing. Comparison flips between EV/Rev and EV/GP — real analytical content.
A79: Oura TEV ($M) | B79: 12060
A80: Oura TTM revenue ($M) | B80: 927
A81: Oura EV/Rev | B81: =B79/B80 -> 13.009709
A82: Oura EV/GP (est. 50% GM) | B82: =B79/(B80*0.5) -> 26.019417
A83: WHOOP at Series G — EV/Rev (recognized) | B83: =B13/B6 -> 2.1098665
A84: WHOOP at Series G — EV/GP (recognized) | B84: =B13/B9 -> 2.8131553
A85: Read | B85: WHOOP higher than Oura on EV/Rev, lower on EV/GP. Margin advantage flips it. Both private marks reflect rich category pricing.
A87: 6. Series G Implied Multiples — Back-Solve Diagnostic
A88: What multiple does Series G $10.1B imply on each thesis basis? Compare to thesis medians to see how far above the comp set Series G sits.
B89: Series G implied | C89: T1 median | D89: T2 median | E89: T3 median | F89: Premium (Series G vs T2 median)
A90: EV/Rev (recognized basis) | B90: =$B$13/$B$6 -> 2.1098665 | C90: =D39 -> 1.07 | D90: =D50 -> 3.34 | E90: =D61 -> 4.94 | F90: =B90/D50-1 -> -0.36830344
A91: EV/Rev (bookings basis) | B91: =$B$13/$B$7 -> 1 | C91: =D39 -> 1.07 | D91: =D50 -> 3.34 | E91: =D61 -> 4.94 | F91: =B91/D50-1 -> -0.7005988
A92: EV/GP (recognized basis) | B92: =$B$13/$B$9 -> 2.8131553 | C92: =D40 -> 2.4 | D92: =D51 -> 9.15 | E92: =D62 -> 8 | F92: =B92/D51-1 -> -0.69255133
A93: EV/GP (bookings basis) | B93: =$B$13/$B$10 -> 1.3333333 | C93: =D40 -> 2.4 | D93: =D51 -> 9.15 | E93: =D62 -> 8 | F93: =B93/D51-1 -> -0.85428051
A95: 7. Historical Regime (V19) — Multiple Compression in Health Data
A96: Health-data multiples have structurally compressed (Dexcom -67%, iRhythm -51% over 3yr). Spotify shows the inverse: profitability proof drove +116% expansion. WHOOP's path runs through Spotify's template, not Dexcom's. Series G investors may have anchored to 2023-era multiples that no longer exist.
A98: Company | B98: 46143 | C98: 45931 | D98: 45748 | E98: 45017 | F98: 3yr Change
A99: Garmin | B99: 5.6 | C99: 6.5 | D99: 5.5 | E99: 3.5 | F99: =B99/E99-1 -> 0.6
A100: Spotify | B100: 4.1 | C100: 6 | D100: 4.9 | E100: 1.9 | F100: =B100/E100-1 -> 1.1578947
A101: Dexcom | B101: 4.6 | C101: 5.9 | D101: 5.8 | E101: 13.8 | F101: =B101/E101-1 -> -0.66666667
A102: iRhythm | B102: 5.2 | C102: 10 | D102: 6.9 | E102: 10.7 | F102: =B102/E102-1 -> -0.51401869
A104: 8. Growth-Adjusted Scatter Data (regression input — visual built separately)
A105: X = NTM growth, Y = EV/GP NTM. T2 anchors used for regression line. WHOOP plotted at NTM growth (~70%) and Series G implied EV/GP. Linear extrapolation produces nonsense at extreme growth (concave relationship), so this is narrative-only — no $ output.
B107: X: NTM Growth | C107: Y: EV/GP NTM | D107: Tier | E107: In Regression?
A108: Peloton | B108: =G19 -> -0.05 | C108: =F19 -> 2.9 | D108: =C19 -> T3 | E108: No (T3)
A109: Sonos | B109: =G20 -> -0.02 | C109: =F20 -> 2.4 | D109: =C20 -> T3 | E109: No (T3)
A110: GoPro | B110: =G21 -> -0.08 | C110: =F21 -> 1.2 | D110: =C21 -> T3 | E110: No (T3)
A111: Spotify | B111: =G22 -> 0.13 | C111: =F22 -> 11.4 | D111: =C22 -> T2 | E111: Yes (T2)
A112: Roku | B112: =G23 -> 0.12 | C112: =F23 -> 6.9 | D112: =C23 -> T2 | E112: Yes (T2)
A113: Dexcom | B113: =G24 -> 0.11 | C113: =F24 -> 7.1 | D113: =C24 -> T2 | E113: Yes (T2)
A114: iRhythm | B114: =G25 -> 0.18 | C114: =F25 -> 6.5 | D114: =C25 -> T2 | E114: Yes (T2)
A115: ResMed | B115: =G26 -> 0.08 | C115: =F26 -> 8.9 | D115: =C26 -> T3 | E115: No (T3)
A116: Masimo | B116: =G27 -> 0.1 | C116: =F27 -> 9.5 | D116: =C27 -> T3 | E116: No (T3)
A117: WHOOP at Series G | B117: =B12 -> 0.7 | C117: =B92 -> 2.8131553 | D117: WHOOP | E117: Plotted, not in regression
...

Sheet Precedents
A1: WHOOP — Precedent Transactions
A2: 2020-2026; $500M+ EV preferred; All USD
A4: Acquirer / Target | B4: Date | C4: EV ($B) | D4: LTM Rev ($B) | E4: EV/Rev | F4: Regime | G4: Bucket | H4: Strategic Rationale
A5: Google / Fitbit | B5: Jan 2021 | C5: 2.1 | D5: 1.43 | E5: 1.5 | F5: ZIRP-peak | G5: B1 | H5: Wearable data acquisition; failed sub pivot
A6: Lululemon / Mirror | B6: Jul 2020 | C6: 0.5 | D6: 0.17 | E6: 2.9 | F6: ZIRP-peak | G6: B2 | H6: Connected fitness content; 89% write-off
A7: Teladoc / Livongo | B7: Oct 2020 | C7: 18.5 | D7: 0.29 | E7: 63.8 | F7: ZIRP-peak | G7: Cross | H7: Digital health mega-deal; massive write-down
A8: Microsoft / Nuance | B8: Mar 2022 | C8: 19.7 | D8: 1.48 | E8: 13.3 | F8: Transition | G8: Cross | H8: Healthcare AI voice/NLP platform
A9: Masimo / Sound United | B9: Apr 2022 | C9: 1.03 | D9: 0.9 | E9: 1.1 | F9: Transition | G9: B1 | H9: Consumer audio pivot; $675M value destruction
A10: CVS / Signify Health | B10: Sep 2022 | C10: 8 | D10: 0.77 | E10: 10.4 | F10: Transition | G10: B3 | H10: Home health + value-based care platform
A11: Amazon / One Medical | B11: Feb 2023 | C11: 3.9 | D11: 1.1 | E11: 3.5 | F11: Transition | G11: Cross | H11: Primary care distribution; strategic access play
A12: J&J / Shockwave Medical | B12: May 2024 | C12: 13.1 | D12: 0.73 | E12: 17.9 | F12: Current | G12: B3 | H12: OUTLIER: IVL synergies drove 2x+ peer median
A13: BSci / Axonics | B13: Nov 2024 | C13: 3.7 | D13: 0.37 | E13: 10.1 | F13: Current | G13: B3 | H13: Neuromodulation bolt-on
A14: Stryker / Inari Medical | B14: Feb 2025 | C14: 4.9 | D14: 0.6 | E14: 8.1 | F14: Current | G14: B3 | H14: Venous thromboembolism devices
A15: Danaher / Masimo | B15: Feb 2026 | C15: 9.9 | D15: 1.51 | E15: 6.6 | F15: Current | G15: B3 | H15: Patient monitoring platform; pending close
A18: Summary by Regime & Bucket
A19: Current-regime B3 medtech: 6.6-10.1x (median ~8.5x)
A20: Connected fitness deals: uniformly value-destructive
A21: Implied WHOOP range: $5-8B (control premium embedded; Series G is minority)

Sheet Cap Table
A1: WHOOP — Cap Table & Waterfall
A2: Sources: Pitchbook + Cap IQ; BUILD WATERFALL FORMULAS
A4: Round | B4: Date | C4: Amount ($M) | D4: Post-Money ($B) | E4: Price/Share ($) | F4: Shares (M) | G4: Ownership % | H4: Pref Terms | I4: Lead Investor(s)
A5: Seed | B5: 2012 | C5: 1 | H5: 1x non-part. | I5: DraftKings founders
A6: Series A | B6: Sep 2014 | C6: 4 | H6: 1x non-part. | I6: Accomplice, Mousse Partners
A7: Series B | B7: Sep 2016 | C7: 12 | H7: 1x non-part. | I7: Foundry Group
A8: Series C | B8: Oct 2018 | C8: 55 | D8: 0.43 | H8: 1x non-part. | I8: IVP
A9: Series D | B9: Oct 2020 | C9: 100 | D9: 1.2 | H9: 1x non-part. | I9: IVP
A10: Series E | B10: Aug 2021 | C10: 200 | D10: 2.4 | H10: 1x non-part. | I10: SoftBank Vision Fund 2
A11: Series F | B11: Aug 2021 | C11: 200 | D11: 3.6 | E11: 4.76 | H11: 1x non-part. | I11: SoftBank Vision Fund 2
A12: Mezz/Bridge | B12: 2022-2024 | C12: 46 | H12: Various | I12: 5 interim rounds (VC + debt)
A13: Series G | B13: Mar 2026 | C13: 575 | D13: 10.1 | E13: 11.23 | G13: 0.057 | H13: 1x non-part. | I13: Collaborative Fund
A15: Total Equity Raised: | C15: 1030
A17: Key Metrics
A18: Authorized Preferred Shares | C18: 537.9M | E18: Pitchbook
A19: Outstanding Common Shares | C19: 361.2M | E19: Pitchbook
A20: Fully Diluted Shares (est.) | C20: ~900M | E20: PremierAlts/Forge
A21: Option Pool (est.) | C21: ~10-15% of FD | E21: Inferred from gap; FLAGGED_GAP
A22: All Preferences | C22: 1x non-participating pari passu | E22: Pitchbook
A23: Total Liquidation Preference | C23: ~$1.03B (floor) | E23: Sum of equity raised × 1x
A26: Waterfall at Exit Scenarios (BUILD FORMULAS)
C27: Bear ($5B) | E27: Base ($10B) | G27: Bull ($20B)
A28: Total Exit Proceeds
A29: Less: Liquidation Preferences
A30: Remaining for Pro-Rata
A31: Preferred Conversion Check (convert or take pref?)
A32: Common Share Proceeds
A33: Common Value per Share
A34: Preferred Value per Share
A35: Founder Equity Value (est. 12-18% FD)

Sheet Football Field
A1: WHOOP — Valuation Football Field
A2: Multi-method synthesis. Each method shown with low/base/high EV. Per-share converts via Assumptions F62 (debt), F63 (cash), F55 (FD shares).
A4: Method | B4: Source | C4: Low EV ($B) | D4: Base EV ($B) | E4: High EV ($B) | F4: Low $/sh | G4: Base $/sh | H4: High $/sh | I4: Weight | J4: Wtd Base | K4: Note
A6: 1. Intrinsic DCF (base case, no options) | B6: Sensitivity Grid 1 | C6: =Sensitivity!B44 -> 4.5972973 | D6: =Sensitivity!C44 -> 7.4511993 | E6: =Sensitivity!D44 -> 10.872952 | F6: =(C6*1000 - Assumptions!$F$62 + Assumptions!$F$63)/Assumptions!$F$55 -> 12.895847 | G6: =(D6*1000 - Assumptions!$F$62 + Assumptions!$F$63)/Assumptions!$F$55 -> 19.856584 | H6: =(E6*1000 - Assumptions!$F$62 + Assumptions!$F$63)/Assumptions!$F$55 -> 28.202322 | I6: 0.4 | J6: =D6*I6 -> 2.9804797 | K6: Primary fundamental method. WACC × Exit Mult range. NEW: Probability-weighted variant available — see Cover triangulation block (B63-C77) for ProbWeighted (input-level) and Scenario-weighted (P·DCF) bookends. Football Field uses Bear/Base/Bull endpoints from Sensitivity!B44:D44; ProbWeighted reading sits between Base and Scenario-weighted. Not added as a separate method line per session decision — same fundamental method, different aggregation.
A7: 1b. DCF + Real Options (probability-wtd) | B7: DCF Base + RO Active | C7: =C6 + RealOptions!B32 -> 4.7614532 | D7: =D6 + RealOptions!C32 -> 8.3912861 | E7: =E6 + RealOptions!D32 -> 13.482076 | F7: =(C7*1000 - Assumptions!$F$62 + Assumptions!$F$63)/Assumptions!$F$55 -> 13.296227 | G7: =(D7*1000 - Assumptions!$F$62 + Assumptions!$F$63)/Assumptions!$F$55 -> 22.149478 | H7: =(E7*1000 - Assumptions!$F$62 + Assumptions!$F$63)/Assumptions!$F$55 -> 34.566038 | K7: Binary-gate decision tree on healthcare reimbursement pathway. Additive to DCF. Replaces prior 3-cluster correlated framework (success/mixed/failure).
A8: 2. Public Comps (three-thesis bracketing) | B8: Comps tab (three-thesis brackets) | C8: =Comps!D43/1000 -> 1.177 | D8: =Comps!D55/1000 -> 3.577833 | E8: =Comps!D56/1000 -> 7.54875 | F8: =(C8*1000 - Assumptions!$F$62 + Assumptions!$F$63)/Assumptions!$F$55 -> 4.5536585 | G8: =(D8*1000 - Assumptions!$F$62 + Assumptions!$F$63)/Assumptions!$F$55 -> 10.409349 | H8: =(E8*1000 - Assumptions!$F$62 + Assumptions!$F$63)/Assumptions!$F$55 -> 20.094512 | I8: 0.35 | J8: =D8*I8 -> 1.2522415 | K8: Three-thesis bracketing. Composite span $0.7B-$9.4B; T2 base anchor $4.0B (recognized GP × EV/GP). Implies Series G priced for bull case across drivers.
A10: 3. Precedent Transactions | B10: Not yet populated | C10: n/a | D10: n/a | E10: n/a | K10: Skipped per session decision. 5-10% memo weight max per methodology.
A11: 4. Last-Round Implied (Series G) | B11: DCF C58 | C11: =DCF!C52/1000 -> 10.1 | D11: =DCF!C52/1000 -> 10.1 | E11: =DCF!C52/1000 -> 10.1 | F11: =(C11*1000 - Assumptions!$F$62 + Assumptions!$F$63)/Assumptions!$F$55 -> 26.317073 | G11: =(D11*1000 - Assumptions!$F$62 + Assumptions!$F$63)/Assumptions!$F$55 -> 26.317073 | H11: =(E11*1000 - Assumptions!$F$62 + Assumptions!$F$63)/Assumptions!$F$55 -> 26.317073 | I11: 0.1 | J11: =D11*I11 -> 1.01 | K11: Series G $10.1B post-money mark, March 2026. Single point, not derived value.
A12: 5. Implied IPO Trading Range | B12: Assumptions C94/D94/E94 | C12: =Assumptions!E95/1000 -> 11.882353 | D12: =Assumptions!D95/1000 -> 12.625 | E12: =Assumptions!C95/1000 -> 13.466667 | F12: =(C12*1000 - Assumptions!$F$62 + Assumptions!$F$63)/Assumptions!$F$55 -> 30.664275 | G12: =(D12*1000 - Assumptions!$F$62 + Assumptions!$F$63)/Assumptions!$F$55 -> 32.47561 | H12: =(E12*1000 - Assumptions!$F$62 + Assumptions!$F$63)/Assumptions!$F$55 -> 34.528455 | I12: 0.15 | J12: =D12*I12 -> 1.89375 | K12: Back-solve: $10.1B ÷ (1−illiquidity) ÷ (1−IPO discount). Bull = lower discounts, lower implied; Bear = higher discounts, higher implied.
A14: Weight Check | I14: =I6+I8+I11+I12 -> 1
A16: Weighted Average EV | D16: =J6+J8+J11+J12 -> 7.1364713 | G16: =(D16*1000 - Assumptions!$F$62 + Assumptions!$F$63)/Assumptions!$F$55 -> 19.088954 | K16: = Σ(weight × base EV) per method
A17: Series G Mark | D17: =DCF!C52/1000 -> 10.1 | G17: =(D17*1000 - Assumptions!$F$62 + Assumptions!$F$63)/Assumptions!$F$55 -> 26.317073
A18: Premium / (Discount) to Series G | D18: =D16/D17 - 1 -> -0.29341868 | G18: =G16/G17 - 1 -> -0.27465512 | K18: Positive = methods support a higher mark; negative = Series G is rich.
A20: Method Range Summary
A21: Lowest method base | B21: =INDEX($A$6:$A$12, MATCH(MIN(D6,D8,D11,D12), D6:D12, 0)) -> 2. Public Comps (three-thesis bracketing) | D21: =MIN(D6,D8,D11,D12) -> 3.577833 | G21: =(D21*1000 - Assumptions!$F$62 + Assumptions!$F$63)/Assumptions!$F$55 -> 10.409349
A22: Highest method base | B22: =INDEX($A$6:$A$12, MATCH(MAX(D6,D8,D11,D12), D6:D12, 0)) -> 5. Implied IPO Trading Range | D22: =MAX(D6,D8,D11,D12) -> 12.625 | G22: =(D22*1000 - Assumptions!$F$62 + Assumptions!$F$63)/Assumptions!$F$55 -> 32.47561
A23: Range across methods | D23: =D22-D21 -> 9.047167 | G23: =G22-G21 -> 22.066261
A25: Memo Read
A26: Multi-method synthesis lands at $8.0B / $21.28 per share, -20.5% below Series G $10.1B / $26.32. Methods range $4.0B (Comps T2 base) to $14.0B (IPO Bull range). DCF is the analytical anchor at $7.3B EV / $8.3B equity (post-3.5x exit multiple, post-WC schedule wiring); the +healthcare-option bridge adds $0.7B at base probability, lifting to $9.0B (-11% vs Series G). Three-thesis comps undershoot Series G across every basis: Failed Pivot $1.2B, Subscription Executed $4.0B median (recognized GP × EV/GP), Healthcare Platform $3.5-6.6B median. Even the most flattering comp combo (T2 bookings GP × EV/GP at $7.6B) sits 25% below mark. IPO range $13-15B implied is consistent with Series G investors targeting 25%+ IRR over 12-18 month hold to IPO. Bottom line: independent triangulation centers $8-9B; Series G prices in the bull case across multiple drivers.
A29: Chart Data (helper table for visual)
A30: Method | B30: Low (offset) | C30: Range (visible bar) | D30: Base marker | E30: Series G ref
A31: 1. Intrinsic DCF | B31: =C6 -> 4.5972973 | C31: =E6-C6 -> 6.2756547 | D31: =D6 -> 7.4511993 | E31: =$D$17 -> 10.1
A32: 1b. DCF + Real Options | B32: =C7 -> 4.7614532 | C32: =E7-C7 -> 8.7206224 | D32: =D7 -> 8.3912861 | E32: =$D$17 -> 10.1
A33: 2. Public Comps (Three-Thesis) | B33: =C8 -> 1.177 | C33: =E8-C8 -> 6.37175 | D33: =D8 -> 3.577833 | E33: =$D$17 -> 10.1
A34: 4. Last-Round Implied (Series G) | B34: =C11 -> 10.1 | C34: 0.001 | D34: =D11 -> 10.1 | E34: =$D$17 -> 10.1
A35: 5. Implied IPO Range | B35: =C12 -> 11.882353 | C35: =E12-C12 -> 1.5843137 | D35: =D12 -> 12.625 | E35: =$D$17 -> 10.1
A36: 5. IPO Range | B36: =C12 -> 11.882353 | C36: =E12-C12 -> 1.5843137 | D36: =D12 -> 12.625 | E36: 10.1
A37: Weighted Avg | B37: =D16 -> 7.1364713 | C37: 0.001 | D37: =D16 -> 7.1364713 | E37: 10.1

Sheet Scenarios
A1: WHOOP — Scenario Summary
A2: Scenario EV by method (live links). Probability Weight Sensitivity tests how the weighted-average EV moves under different conviction schemes. ProbWeighted (input-level) shown alongside scenario-weighted (P·DCF) to expose the Jensen gap.
A4: Method | B4: Bear ($M) | C4: Base ($M) | D4: Bull ($M) | E4: ProbWeighted ($M) | F4: Notes
A5: 1. Intrinsic DCF (Equity Value) | B5: =DCF!C60 -> 2504.21 | C5: =DCF!C61 -> 7336.16 | D5: =DCF!C62 -> 19882 | E5: =DCF!C63 -> 7961.86 | F5: Equity values from DCF triangulation block (rows 60-63). Live snapshot.
A6: + Real Options (Equity + Options) | B6: =DCF!D60 -> 2657.5 | C6: =DCF!D61 -> 8276.25 | D6: =DCF!D62 -> 22596.33 | E6: =DCF!D63 -> 8901.95 | F6: Includes healthcare reimbursement option (binary gate). Real options scenario-aligned.
A7: 2. Trading Comps (3-bucket EV) | B7: =Comps!D43 -> 1177 | C7: 83.5977 | D7: =Comps!D56 -> 7548.75 | E7: n/a | F7: Three-thesis bracketing (Failed Pivot / Subscription / Healthcare). Cross-thesis blending not meaningful — ProbWeighted not applicable.
A8: 3. Precedent Transactions | B8: n/a | C8: n/a | D8: n/a | E8: n/a | F8: Skipped per session decision. 5-10% memo weight max.
A9: 4. Last-Round Implied (Series G) | B9: =DCF!C52 -> 10100 | C9: =DCF!C52 -> 10100 | D9: =DCF!C52 -> 10100 | E9: =DCF!C52 -> 10100 | F9: Single point (constant across scenarios). Mar 2026 mark.
A10: 5. Implied IPO Trading Range | B10: =Assumptions!E95 -> 11882.353 | C10: =Assumptions!D95 -> 12625 | D10: =Assumptions!C95 -> 13466.667 | E10: n/a | F10: Back-solve from $10.1B ÷ (1−illiquidity) ÷ (1−IPO discount). Bear=highest discounts, lowest implied.
A12: Probability Weight Sensitivity — DCF Equity ($M)
A13: Tests three conviction schemes against both methods. Scenario-weighted = P_Bear·Bear + P_Base·Base + P_Bull·Bull (joint correlation). ProbWeighted = read from DCF!C63 with row-2 weights set to scheme (input independence). Difference = Jensen gap. | B13: Bear Wt | C13: Base Wt | D13: Bull Wt | E13: Weighted EV ($B)
A14: Pessimistic | B14: 0.35 | C14: 0.5 | D14: 0.15
A15: Weight Scheme | B15: P_Bear | C15: P_Base | D15: P_Bull | E15: Scenario-Wtd Equity | F15: ProbWeighted Equity | G15: Jensen Gap | H15: vs Series G
A16: Pessimistic (high Bear weight) | B16: 0.35 | C16: 0.5 | D16: 0.15 | E16: =B16*B5+C16*C5+D16*D5 -> 7526.8535 | F16: 7269.61 | G16: =E16-F16 -> 257.2435 | H16: =E16/DCF!$C$52-1 -> -0.25476698
A17: Neutral (current base case) | B17: =Assumptions!C2 -> 0.2 | C17: =Assumptions!E2 -> 0.5 | D17: =Assumptions!G2 -> 0.3 | E17: =B17*B5+C17*C5+D17*D5 -> 10133.522 | F17: =DCF!C63 -> 7961.86 | G17: =E17-F17 -> 2171.662 | H17: =E17/DCF!$C$52-1 -> 0.0033190099
A18: Optimistic (high Bull weight) | B18: 0.15 | C18: 0.45 | D18: 0.4 | E18: =B18*B5+C18*C5+D18*D5 -> 11629.703 | F18: 8359.77 | G18: =E18-F18 -> 3269.9335 | H18: =E18/DCF!$C$52-1 -> 0.15145579
A20: Read: Even under Pessimistic weights (35/50/15), scenario-weighted Equity exceeds ProbWeighted by ~$2.0B (Jensen gap). Under Optimistic weights, gap widens to ~$5.5B as Bull's joint upside dominates. Series G premium/discount column shows scenario-weighted hits the mark only under Neutral or Optimistic schemes — Pessimistic implies $2B+ haircut to Series G.

Sheet Sensitivity
A1: WHOOP — Sensitivity Analysis
A2: Base case anchored: WACC 10.85%, Exit Mult 4.5x, Terminal Growth 3.0%, CSRP 2.0% → EV $9.54B / Equity $10.23B / $24.95 per share. Yellow cell = base case.
A4: Grid 1: WACC × Exit Multiple → Enterprise Value ($B)
A5: WACC ↓ / Exit Mult (EV/Rev) → | B5: 2 | C5: 2.5 | D5: 3 | E5: 3.5 | F5: 4 | G5: 4.5 | H5: 5
A6: 0.1009 | B6: {=(SUMPRODUCT(DCF!$D$9:$K$9, 1/(1+$A6)^DCF!$D$13:$K$13) + DCF!$K$8*B$5/(1+$A6)^DCF!$K$13)/1000} -> 5.4876446 | C6: {=(SUMPRODUCT(DCF!$D$9:$K$9, 1/(1+$A6)^DCF!$D$13:$K$13) + DCF!$K$8*C$5/(1+$A6)^DCF!$K$13)/1000} -> 6.3851958 | D6: {=(SUMPRODUCT(DCF!$D$9:$K$9, 1/(1+$A6)^DCF!$D$13:$K$13) + DCF!$K$8*D$5/(1+$A6)^DCF!$K$13)/1000} -> 7.282747 | E6: {=(SUMPRODUCT(DCF!$D$9:$K$9, 1/(1+$A6)^DCF!$D$13:$K$13) + DCF!$K$8*E$5/(1+$A6)^DCF!$K$13)/1000} -> 8.1802983 | F6: {=(SUMPRODUCT(DCF!$D$9:$K$9, 1/(1+$A6)^DCF!$D$13:$K$13) + DCF!$K$8*F$5/(1+$A6)^DCF!$K$13)/1000} -> 9.0778495 | G6: {=(SUMPRODUCT(DCF!$D$9:$K$9, 1/(1+$A6)^DCF!$D$13:$K$13) + DCF!$K$8*G$5/(1+$A6)^DCF!$K$13)/1000} -> 9.9754008 | H6: {=(SUMPRODUCT(DCF!$D$9:$K$9, 1/(1+$A6)^DCF!$D$13:$K$13) + DCF!$K$8*H$5/(1+$A6)^DCF!$K$13)/1000} -> 10.872952
A7: 0.1059 | B7: {=(SUMPRODUCT(DCF!$D$9:$K$9, 1/(1+$A7)^DCF!$D$13:$K$13) + DCF!$K$8*B$5/(1+$A7)^DCF!$K$13)/1000} -> 5.3255249 | C7: {=(SUMPRODUCT(DCF!$D$9:$K$9, 1/(1+$A7)^DCF!$D$13:$K$13) + DCF!$K$8*C$5/(1+$A7)^DCF!$K$13)/1000} -> 6.1930845 | D7: {=(SUMPRODUCT(DCF!$D$9:$K$9, 1/(1+$A7)^DCF!$D$13:$K$13) + DCF!$K$8*D$5/(1+$A7)^DCF!$K$13)/1000} -> 7.0606442 | E7: {=(SUMPRODUCT(DCF!$D$9:$K$9, 1/(1+$A7)^DCF!$D$13:$K$13) + DCF!$K$8*E$5/(1+$A7)^DCF!$K$13)/1000} -> 7.9282039 | F7: {=(SUMPRODUCT(DCF!$D$9:$K$9, 1/(1+$A7)^DCF!$D$13:$K$13) + DCF!$K$8*F$5/(1+$A7)^DCF!$K$13)/1000} -> 8.7957635 | G7: {=(SUMPRODUCT(DCF!$D$9:$K$9, 1/(1+$A7)^DCF!$D$13:$K$13) + DCF!$K$8*G$5/(1+$A7)^DCF!$K$13)/1000} -> 9.6633232 | H7: {=(SUMPRODUCT(DCF!$D$9:$K$9, 1/(1+$A7)^DCF!$D$13:$K$13) + DCF!$K$8*H$5/(1+$A7)^DCF!$K$13)/1000} -> 10.530883
A8: 0.1109 | B8: {=(SUMPRODUCT(DCF!$D$9:$K$9, 1/(1+$A8)^DCF!$D$13:$K$13) + DCF!$K$8*B$5/(1+$A8)^DCF!$K$13)/1000} -> 5.1692004 | C8: {=(SUMPRODUCT(DCF!$D$9:$K$9, 1/(1+$A8)^DCF!$D$13:$K$13) + DCF!$K$8*C$5/(1+$A8)^DCF!$K$13)/1000} -> 6.0078992 | D8: {=(SUMPRODUCT(DCF!$D$9:$K$9, 1/(1+$A8)^DCF!$D$13:$K$13) + DCF!$K$8*D$5/(1+$A8)^DCF!$K$13)/1000} -> 6.8465981 | E8: {=(SUMPRODUCT(DCF!$D$9:$K$9, 1/(1+$A8)^DCF!$D$13:$K$13) + DCF!$K$8*E$5/(1+$A8)^DCF!$K$13)/1000} -> 7.6852969 | F8: {=(SUMPRODUCT(DCF!$D$9:$K$9, 1/(1+$A8)^DCF!$D$13:$K$13) + DCF!$K$8*F$5/(1+$A8)^DCF!$K$13)/1000} -> 8.5239957 | G8: {=(SUMPRODUCT(DCF!$D$9:$K$9, 1/(1+$A8)^DCF!$D$13:$K$13) + DCF!$K$8*G$5/(1+$A8)^DCF!$K$13)/1000} -> 9.3626946 | H8: {=(SUMPRODUCT(DCF!$D$9:$K$9, 1/(1+$A8)^DCF!$D$13:$K$13) + DCF!$K$8*H$5/(1+$A8)^DCF!$K$13)/1000} -> 10.201393
A9: 0.1159 | B9: {=(SUMPRODUCT(DCF!$D$9:$K$9, 1/(1+$A9)^DCF!$D$13:$K$13) + DCF!$K$8*B$5/(1+$A9)^DCF!$K$13)/1000} -> 5.0184355 | C9: {=(SUMPRODUCT(DCF!$D$9:$K$9, 1/(1+$A9)^DCF!$D$13:$K$13) + DCF!$K$8*C$5/(1+$A9)^DCF!$K$13)/1000} -> 5.8293568 | D9: {=(SUMPRODUCT(DCF!$D$9:$K$9, 1/(1+$A9)^DCF!$D$13:$K$13) + DCF!$K$8*D$5/(1+$A9)^DCF!$K$13)/1000} -> 6.640278 | E9: {=(SUMPRODUCT(DCF!$D$9:$K$9, 1/(1+$A9)^DCF!$D$13:$K$13) + DCF!$K$8*E$5/(1+$A9)^DCF!$K$13)/1000} -> 7.4511993 | F9: {=(SUMPRODUCT(DCF!$D$9:$K$9, 1/(1+$A9)^DCF!$D$13:$K$13) + DCF!$K$8*F$5/(1+$A9)^DCF!$K$13)/1000} -> 8.2621206 | G9: {=(SUMPRODUCT(DCF!$D$9:$K$9, 1/(1+$A9)^DCF!$D$13:$K$13) + DCF!$K$8*G$5/(1+$A9)^DCF!$K$13)/1000} -> 9.0730419 | H9: {=(SUMPRODUCT(DCF!$D$9:$K$9, 1/(1+$A9)^DCF!$D$13:$K$13) + DCF!$K$8*H$5/(1+$A9)^DCF!$K$13)/1000} -> 9.8839632
A10: 0.1209 | B10: {=(SUMPRODUCT(DCF!$D$9:$K$9, 1/(1+$A10)^DCF!$D$13:$K$13) + DCF!$K$8*B$5/(1+$A10)^DCF!$K$13)/1000} -> 4.873005 | C10: {=(SUMPRODUCT(DCF!$D$9:$K$9, 1/(1+$A10)^DCF!$D$13:$K$13) + DCF!$K$8*C$5/(1+$A10)^DCF!$K$13)/1000} -> 5.6571868 | D10: {=(SUMPRODUCT(DCF!$D$9:$K$9, 1/(1+$A10)^DCF!$D$13:$K$13) + DCF!$K$8*D$5/(1+$A10)^DCF!$K$13)/1000} -> 6.4413686 | E10: {=(SUMPRODUCT(DCF!$D$9:$K$9, 1/(1+$A10)^DCF!$D$13:$K$13) + DCF!$K$8*E$5/(1+$A10)^DCF!$K$13)/1000} -> 7.2255504 | F10: {=(SUMPRODUCT(DCF!$D$9:$K$9, 1/(1+$A10)^DCF!$D$13:$K$13) + DCF!$K$8*F$5/(1+$A10)^DCF!$K$13)/1000} -> 8.0097322 | G10: {=(SUMPRODUCT(DCF!$D$9:$K$9, 1/(1+$A10)^DCF!$D$13:$K$13) + DCF!$K$8*G$5/(1+$A10)^DCF!$K$13)/1000} -> 8.7939141 | H10: {=(SUMPRODUCT(DCF!$D$9:$K$9, 1/(1+$A10)^DCF!$D$13:$K$13) + DCF!$K$8*H$5/(1+$A10)^DCF!$K$13)/1000} -> 9.5780959
A11: 0.1259 | B11: {=(SUMPRODUCT(DCF!$D$9:$K$9, 1/(1+$A11)^DCF!$D$13:$K$13) + DCF!$K$8*B$5/(1+$A11)^DCF!$K$13)/1000} -> 4.732694 | C11: {=(SUMPRODUCT(DCF!$D$9:$K$9, 1/(1+$A11)^DCF!$D$13:$K$13) + DCF!$K$8*C$5/(1+$A11)^DCF!$K$13)/1000} -> 5.4911313 | D11: {=(SUMPRODUCT(DCF!$D$9:$K$9, 1/(1+$A11)^DCF!$D$13:$K$13) + DCF!$K$8*D$5/(1+$A11)^DCF!$K$13)/1000} -> 6.2495685 | E11: {=(SUMPRODUCT(DCF!$D$9:$K$9, 1/(1+$A11)^DCF!$D$13:$K$13) + DCF!$K$8*E$5/(1+$A11)^DCF!$K$13)/1000} -> 7.0080057 | F11: {=(SUMPRODUCT(DCF!$D$9:$K$9, 1/(1+$A11)^DCF!$D$13:$K$13) + DCF!$K$8*F$5/(1+$A11)^DCF!$K$13)/1000} -> 7.766443 | G11: {=(SUMPRODUCT(DCF!$D$9:$K$9, 1/(1+$A11)^DCF!$D$13:$K$13) + DCF!$K$8*G$5/(1+$A11)^DCF!$K$13)/1000} -> 8.5248802 | H11: {=(SUMPRODUCT(DCF!$D$9:$K$9, 1/(1+$A11)^DCF!$D$13:$K$13) + DCF!$K$8*H$5/(1+$A11)^DCF!$K$13)/1000} -> 9.2833174
A12: 0.1309 | B12: {=(SUMPRODUCT(DCF!$D$9:$K$9, 1/(1+$A12)^DCF!$D$13:$K$13) + DCF!$K$8*B$5/(1+$A12)^DCF!$K$13)/1000} -> 4.5972973 | C12: {=(SUMPRODUCT(DCF!$D$9:$K$9, 1/(1+$A12)^DCF!$D$13:$K$13) + DCF!$K$8*C$5/(1+$A12)^DCF!$K$13)/1000} -> 5.3309437 | D12: {=(SUMPRODUCT(DCF!$D$9:$K$9, 1/(1+$A12)^DCF!$D$13:$K$13) + DCF!$K$8*D$5/(1+$A12)^DCF!$K$13)/1000} -> 6.06459 | E12: {=(SUMPRODUCT(DCF!$D$9:$K$9, 1/(1+$A12)^DCF!$D$13:$K$13) + DCF!$K$8*E$5/(1+$A12)^DCF!$K$13)/1000} -> 6.7982364 | F12: {=(SUMPRODUCT(DCF!$D$9:$K$9, 1/(1+$A12)^DCF!$D$13:$K$13) + DCF!$K$8*F$5/(1+$A12)^DCF!$K$13)/1000} -> 7.5318827 | G12: {=(SUMPRODUCT(DCF!$D$9:$K$9, 1/(1+$A12)^DCF!$D$13:$K$13) + DCF!$K$8*G$5/(1+$A12)^DCF!$K$13)/1000} -> 8.2655291 | H12: {=(SUMPRODUCT(DCF!$D$9:$K$9, 1/(1+$A12)^DCF!$D$13:$K$13) + DCF!$K$8*H$5/(1+$A12)^DCF!$K$13)/1000} -> 8.9991754
A15: Grid 2: WACC × Terminal Growth (Gordon Method) → Enterprise Value ($B)
A16: WACC ↓ / Terminal Growth → | B16: 0.015 | C16: 0.02 | D16: 0.025 | E16: 0.03 | F16: 0.035 | G16: 0.04 | H16: 0.045
A17: 0.1009 | B17: {=(SUMPRODUCT(DCF!$D$9:$K$9, 1/(1+$A17)^DCF!$D$13:$K$13) + DCF!$K$9*(1+B$16)/($A17-B$16)/(1+$A17)^DCF!$K$13)/1000} -> 6.2647372 | C17: {=(SUMPRODUCT(DCF!$D$9:$K$9, 1/(1+$A17)^DCF!$D$13:$K$13) + DCF!$K$9*(1+C$16)/($A17-C$16)/(1+$A17)^DCF!$K$13)/1000} -> 6.5575001 | D17: {=(SUMPRODUCT(DCF!$D$9:$K$9, 1/(1+$A17)^DCF!$D$13:$K$13) + DCF!$K$9*(1+D$16)/($A17-D$16)/(1+$A17)^DCF!$K$13)/1000} -> 6.8888352 | E17: {=(SUMPRODUCT(DCF!$D$9:$K$9, 1/(1+$A17)^DCF!$D$13:$K$13) + DCF!$K$9*(1+E$16)/($A17-E$16)/(1+$A17)^DCF!$K$13)/1000} -> 7.2669031 | F17: {=(SUMPRODUCT(DCF!$D$9:$K$9, 1/(1+$A17)^DCF!$D$13:$K$13) + DCF!$K$9*(1+F$16)/($A17-F$16)/(1+$A17)^DCF!$K$13)/1000} -> 7.7023409 | G17: {=(SUMPRODUCT(DCF!$D$9:$K$9, 1/(1+$A17)^DCF!$D$13:$K$13) + DCF!$K$9*(1+G$16)/($A17-G$16)/(1+$A17)^DCF!$K$13)/1000} -> 8.2092792 | H17: {=(SUMPRODUCT(DCF!$D$9:$K$9, 1/(1+$A17)^DCF!$D$13:$K$13) + DCF!$K$9*(1+H$16)/($A17-H$16)/(1+$A17)^DCF!$K$13)/1000} -> 8.806904
A18: 0.1059 | B18: {=(SUMPRODUCT(DCF!$D$9:$K$9, 1/(1+$A18)^DCF!$D$13:$K$13) + DCF!$K$9*(1+B$16)/($A18-B$16)/(1+$A18)^DCF!$K$13)/1000} -> 5.8444527 | C18: {=(SUMPRODUCT(DCF!$D$9:$K$9, 1/(1+$A18)^DCF!$D$13:$K$13) + DCF!$K$9*(1+C$16)/($A18-C$16)/(1+$A18)^DCF!$K$13)/1000} -> 6.0974459 | D18: {=(SUMPRODUCT(DCF!$D$9:$K$9, 1/(1+$A18)^DCF!$D$13:$K$13) + DCF!$K$9*(1+D$16)/($A18-D$16)/(1+$A18)^DCF!$K$13)/1000} -> 6.3817114 | E18: {=(SUMPRODUCT(DCF!$D$9:$K$9, 1/(1+$A18)^DCF!$D$13:$K$13) + DCF!$K$9*(1+E$16)/($A18-E$16)/(1+$A18)^DCF!$K$13)/1000} -> 6.7034296 | F18: {=(SUMPRODUCT(DCF!$D$9:$K$9, 1/(1+$A18)^DCF!$D$13:$K$13) + DCF!$K$9*(1+F$16)/($A18-F$16)/(1+$A18)^DCF!$K$13)/1000} -> 7.0705241 | G18: {=(SUMPRODUCT(DCF!$D$9:$K$9, 1/(1+$A18)^DCF!$D$13:$K$13) + DCF!$K$9*(1+G$16)/($A18-G$16)/(1+$A18)^DCF!$K$13)/1000} -> 7.4933233 | H18: {=(SUMPRODUCT(DCF!$D$9:$K$9, 1/(1+$A18)^DCF!$D$13:$K$13) + DCF!$K$9*(1+H$16)/($A18-H$16)/(1+$A18)^DCF!$K$13)/1000} -> 7.9855477
A19: 0.1109 | B19: {=(SUMPRODUCT(DCF!$D$9:$K$9, 1/(1+$A19)^DCF!$D$13:$K$13) + DCF!$K$9*(1+B$16)/($A19-B$16)/(1+$A19)^DCF!$K$13)/1000} -> 5.4697985 | C19: {=(SUMPRODUCT(DCF!$D$9:$K$9, 1/(1+$A19)^DCF!$D$13:$K$13) + DCF!$K$9*(1+C$16)/($A19-C$16)/(1+$A19)^DCF!$K$13)/1000} -> 5.6898626 | D19: {=(SUMPRODUCT(DCF!$D$9:$K$9, 1/(1+$A19)^DCF!$D$13:$K$13) + DCF!$K$9*(1+D$16)/($A19-D$16)/(1+$A19)^DCF!$K$13)/1000} -> 5.9355453 | E19: {=(SUMPRODUCT(DCF!$D$9:$K$9, 1/(1+$A19)^DCF!$D$13:$K$13) + DCF!$K$9*(1+E$16)/($A19-E$16)/(1+$A19)^DCF!$K$13)/1000} -> 6.2115967 | F19: {=(SUMPRODUCT(DCF!$D$9:$K$9, 1/(1+$A19)^DCF!$D$13:$K$13) + DCF!$K$9*(1+F$16)/($A19-F$16)/(1+$A19)^DCF!$K$13)/1000} -> 6.5240185 | G19: {=(SUMPRODUCT(DCF!$D$9:$K$9, 1/(1+$A19)^DCF!$D$13:$K$13) + DCF!$K$9*(1+G$16)/($A19-G$16)/(1+$A19)^DCF!$K$13)/1000} -> 6.8805055 | H19: {=(SUMPRODUCT(DCF!$D$9:$K$9, 1/(1+$A19)^DCF!$D$13:$K$13) + DCF!$K$9*(1+H$16)/($A19-H$16)/(1+$A19)^DCF!$K$13)/1000} -> 7.2910876
A20: 0.1159 | B20: {=(SUMPRODUCT(DCF!$D$9:$K$9, 1/(1+$A20)^DCF!$D$13:$K$13) + DCF!$K$9*(1+B$16)/($A20-B$16)/(1+$A20)^DCF!$K$13)/1000} -> 5.1339377 | C20: {=(SUMPRODUCT(DCF!$D$9:$K$9, 1/(1+$A20)^DCF!$D$13:$K$13) + DCF!$K$9*(1+C$16)/($A20-C$16)/(1+$A20)^DCF!$K$13)/1000} -> 5.3264883 | D20: {=(SUMPRODUCT(DCF!$D$9:$K$9, 1/(1+$A20)^DCF!$D$13:$K$13) + DCF!$K$9*(1+D$16)/($A20-D$16)/(1+$A20)^DCF!$K$13)/1000} -> 5.5402216 | E20: {=(SUMPRODUCT(DCF!$D$9:$K$9, 1/(1+$A20)^DCF!$D$13:$K$13) + DCF!$K$9*(1+E$16)/($A20-E$16)/(1+$A20)^DCF!$K$13)/1000} -> 5.7788365 | F20: {=(SUMPRODUCT(DCF!$D$9:$K$9, 1/(1+$A20)^DCF!$D$13:$K$13) + DCF!$K$9*(1+F$16)/($A20-F$16)/(1+$A20)^DCF!$K$13)/1000} -> 6.0469464 | G20: {=(SUMPRODUCT(DCF!$D$9:$K$9, 1/(1+$A20)^DCF!$D$13:$K$13) + DCF!$K$9*(1+G$16)/($A20-G$16)/(1+$A20)^DCF!$K$13)/1000} -> 6.3503805 | H20: {=(SUMPRODUCT(DCF!$D$9:$K$9, 1/(1+$A20)^DCF!$D$13:$K$13) + DCF!$K$9*(1+H$16)/($A20-H$16)/(1+$A20)^DCF!$K$13)/1000} -> 6.6966121
A21: 0.1209 | B21: {=(SUMPRODUCT(DCF!$D$9:$K$9, 1/(1+$A21)^DCF!$D$13:$K$13) + DCF!$K$9*(1+B$16)/($A21-B$16)/(1+$A21)^DCF!$K$13)/1000} -> 4.8313265 | C21: {=(SUMPRODUCT(DCF!$D$9:$K$9, 1/(1+$A21)^DCF!$D$13:$K$13) + DCF!$K$9*(1+C$16)/($A21-C$16)/(1+$A21)^DCF!$K$13)/1000} -> 5.0007007 | D21: {=(SUMPRODUCT(DCF!$D$9:$K$9, 1/(1+$A21)^DCF!$D$13:$K$13) + DCF!$K$9*(1+D$16)/($A21-D$16)/(1+$A21)^DCF!$K$13)/1000} -> 5.1877364 | E21: {=(SUMPRODUCT(DCF!$D$9:$K$9, 1/(1+$A21)^DCF!$D$13:$K$13) + DCF!$K$9*(1+E$16)/($A21-E$16)/(1+$A21)^DCF!$K$13)/1000} -> 5.3953481 | F21: {=(SUMPRODUCT(DCF!$D$9:$K$9, 1/(1+$A21)^DCF!$D$13:$K$13) + DCF!$K$9*(1+F$16)/($A21-F$16)/(1+$A21)^DCF!$K$13)/1000} -> 5.6271288 | G21: {=(SUMPRODUCT(DCF!$D$9:$K$9, 1/(1+$A21)^DCF!$D$13:$K$13) + DCF!$K$9*(1+G$16)/($A21-G$16)/(1+$A21)^DCF!$K$13)/1000} -> 5.8875597 | H21: {=(SUMPRODUCT(DCF!$D$9:$K$9, 1/(1+$A21)^DCF!$D$13:$K$13) + DCF!$K$9*(1+H$16)/($A21-H$16)/(1+$A21)^DCF!$K$13)/1000} -> 6.1823031
A22: 0.1259 | B22: {=(SUMPRODUCT(DCF!$D$9:$K$9, 1/(1+$A22)^DCF!$D$13:$K$13) + DCF!$K$9*(1+B$16)/($A22-B$16)/(1+$A22)^DCF!$K$13)/1000} -> 4.5574227 | C22: {=(SUMPRODUCT(DCF!$D$9:$K$9, 1/(1+$A22)^DCF!$D$13:$K$13) + DCF!$K$9*(1+C$16)/($A22-C$16)/(1+$A22)^DCF!$K$13)/1000} -> 4.7071299 | D22: {=(SUMPRODUCT(DCF!$D$9:$K$9, 1/(1+$A22)^DCF!$D$13:$K$13) + DCF!$K$9*(1+D$16)/($A22-D$16)/(1+$A22)^DCF!$K$13)/1000} -> 4.8716742 | E22: {=(SUMPRODUCT(DCF!$D$9:$K$9, 1/(1+$A22)^DCF!$D$13:$K$13) + DCF!$K$9*(1+E$16)/($A22-E$16)/(1+$A22)^DCF!$K$13)/1000} -> 5.0533765 | F22: {=(SUMPRODUCT(DCF!$D$9:$K$9, 1/(1+$A22)^DCF!$D$13:$K$13) + DCF!$K$9*(1+F$16)/($A22-F$16)/(1+$A22)^DCF!$K$13)/1000} -> 5.255068 | G22: {=(SUMPRODUCT(DCF!$D$9:$K$9, 1/(1+$A22)^DCF!$D$13:$K$13) + DCF!$K$9*(1+G$16)/($A22-G$16)/(1+$A22)^DCF!$K$13)/1000} -> 5.4802393 | H22: {=(SUMPRODUCT(DCF!$D$9:$K$9, 1/(1+$A22)^DCF!$D$13:$K$13) + DCF!$K$9*(1+H$16)/($A22-H$16)/(1+$A22)^DCF!$K$13)/1000} -> 5.7332439
A23: 0.1309 | B23: {=(SUMPRODUCT(DCF!$D$9:$K$9, 1/(1+$A23)^DCF!$D$13:$K$13) + DCF!$K$9*(1+B$16)/($A23-B$16)/(1+$A23)^DCF!$K$13)/1000} -> 4.3084693 | C23: {=(SUMPRODUCT(DCF!$D$9:$K$9, 1/(1+$A23)^DCF!$D$13:$K$13) + DCF!$K$9*(1+C$16)/($A23-C$16)/(1+$A23)^DCF!$K$13)/1000} -> 4.441376 | D23: {=(SUMPRODUCT(DCF!$D$9:$K$9, 1/(1+$A23)^DCF!$D$13:$K$13) + DCF!$K$9*(1+D$16)/($A23-D$16)/(1+$A23)^DCF!$K$13)/1000} -> 4.5868328 | E23: {=(SUMPRODUCT(DCF!$D$9:$K$9, 1/(1+$A23)^DCF!$D$13:$K$13) + DCF!$K$9*(1+E$16)/($A23-E$16)/(1+$A23)^DCF!$K$13)/1000} -> 4.7467056 | F23: {=(SUMPRODUCT(DCF!$D$9:$K$9, 1/(1+$A23)^DCF!$D$13:$K$13) + DCF!$K$9*(1+F$16)/($A23-F$16)/(1+$A23)^DCF!$K$13)/1000} -> 4.9232491 | G23: {=(SUMPRODUCT(DCF!$D$9:$K$9, 1/(1+$A23)^DCF!$D$13:$K$13) + DCF!$K$9*(1+G$16)/($A23-G$16)/(1+$A23)^DCF!$K$13)/1000} -> 5.1192144 | H23: {=(SUMPRODUCT(DCF!$D$9:$K$9, 1/(1+$A23)^DCF!$D$13:$K$13) + DCF!$K$9*(1+H$16)/($A23-H$16)/(1+$A23)^DCF!$K$13)/1000} -> 5.3379929
A26: Grid 3: Beta × CSRP → Top-Down WACC (CAPM, Methodology Sec 8)
A27: Beta ↓ / CSRP → | B27: 0.01 | C27: 0.015 | D27: 0.02 | E27: 0.025 | F27: 0.03
A28: 0.7 | B28: =Assumptions!$F$69 + Assumptions!$F$70*$A28 + Assumptions!$F$72 + B$27 -> 0.0926 | C28: =Assumptions!$F$69 + Assumptions!$F$70*$A28 + Assumptions!$F$72 + C$27 -> 0.0976 | D28: =Assumptions!$F$69 + Assumptions!$F$70*$A28 + Assumptions!$F$72 + D$27 -> 0.1026 | E28: =Assumptions!$F$69 + Assumptions!$F$70*$A28 + Assumptions!$F$72 + E$27 -> 0.1076 | F28: =Assumptions!$F$69 + Assumptions!$F$70*$A28 + Assumptions!$F$72 + F$27 -> 0.1126
A29: 0.83 | B29: =Assumptions!$F$69 + Assumptions!$F$70*$A29 + Assumptions!$F$72 + B$27 -> 0.09845 | C29: =Assumptions!$F$69 + Assumptions!$F$70*$A29 + Assumptions!$F$72 + C$27 -> 0.10345 | D29: =Assumptions!$F$69 + Assumptions!$F$70*$A29 + Assumptions!$F$72 + D$27 -> 0.10845 | E29: =Assumptions!$F$69 + Assumptions!$F$70*$A29 + Assumptions!$F$72 + E$27 -> 0.11345 | F29: =Assumptions!$F$69 + Assumptions!$F$70*$A29 + Assumptions!$F$72 + F$27 -> 0.11845
A30: 1 | B30: =Assumptions!$F$69 + Assumptions!$F$70*$A30 + Assumptions!$F$72 + B$27 -> 0.1061 | C30: =Assumptions!$F$69 + Assumptions!$F$70*$A30 + Assumptions!$F$72 + C$27 -> 0.1111 | D30: =Assumptions!$F$69 + Assumptions!$F$70*$A30 + Assumptions!$F$72 + D$27 -> 0.1161 | E30: =Assumptions!$F$69 + Assumptions!$F$70*$A30 + Assumptions!$F$72 + E$27 -> 0.1211 | F30: =Assumptions!$F$69 + Assumptions!$F$70*$A30 + Assumptions!$F$72 + F$27 -> 0.1261
A31: 1.2 | B31: =Assumptions!$F$69 + Assumptions!$F$70*$A31 + Assumptions!$F$72 + B$27 -> 0.1151 | C31: =Assumptions!$F$69 + Assumptions!$F$70*$A31 + Assumptions!$F$72 + C$27 -> 0.1201 | D31: =Assumptions!$F$69 + Assumptions!$F$70*$A31 + Assumptions!$F$72 + D$27 -> 0.1251 | E31: =Assumptions!$F$69 + Assumptions!$F$70*$A31 + Assumptions!$F$72 + E$27 -> 0.1301 | F31: =Assumptions!$F$69 + Assumptions!$F$70*$A31 + Assumptions!$F$72 + F$27 -> 0.1351
A32: 1.4 | B32: =Assumptions!$F$69 + Assumptions!$F$70*$A32 + Assumptions!$F$72 + B$27 -> 0.1241 | C32: =Assumptions!$F$69 + Assumptions!$F$70*$A32 + Assumptions!$F$72 + C$27 -> 0.1291 | D32: =Assumptions!$F$69 + Assumptions!$F$70*$A32 + Assumptions!$F$72 + D$27 -> 0.1341 | E32: =Assumptions!$F$69 + Assumptions!$F$70*$A32 + Assumptions!$F$72 + E$27 -> 0.1391 | F32: =Assumptions!$F$69 + Assumptions!$F$70*$A32 + Assumptions!$F$72 + F$27 -> 0.1441
A34: Grid 3b: Same Beta × CSRP applied to DCF (top-down WACC) → EV ($B) at base 3.5x exit
A35: Beta ↓ / CSRP → | B35: 0.01 | C35: 0.015 | D35: 0.02 | E35: 0.025 | F35: 0.03
A36: 0.7 | B36: {=(SUMPRODUCT(DCF!$D$9:$K$9, 1/(1+(Assumptions!$F$69+Assumptions!$F$70*$A36+Assumptions!$F$72+B$35))^DCF!$D$13:$K$13) + DCF!$K$8*Assumptions!$F$79/(1+(Assumptions!$F$69+Assumptions!$F$70*$A36+Assumptions!$F$72+B$35))^DCF!$K$13)/1000} -> 8.6201346 | C36: {=(SUMPRODUCT(DCF!$D$9:$K$9, 1/(1+(Assumptions!$F$69+Assumptions!$F$70*$A36+Assumptions!$F$72+C$35))^DCF!$D$13:$K$13) + DCF!$K$8*Assumptions!$F$79/(1+(Assumptions!$F$69+Assumptions!$F$70*$A36+Assumptions!$F$72+C$35))^DCF!$K$13)/1000} -> 8.3519051 | D36: {=(SUMPRODUCT(DCF!$D$9:$K$9, 1/(1+(Assumptions!$F$69+Assumptions!$F$70*$A36+Assumptions!$F$72+D$35))^DCF!$D$13:$K$13) + DCF!$K$8*Assumptions!$F$79/(1+(Assumptions!$F$69+Assumptions!$F$70*$A36+Assumptions!$F$72+D$35))^DCF!$K$13)/1000} -> 8.0935311 | E36: {=(SUMPRODUCT(DCF!$D$9:$K$9, 1/(1+(Assumptions!$F$69+Assumptions!$F$70*$A36+Assumptions!$F$72+E$35))^DCF!$D$13:$K$13) + DCF!$K$8*Assumptions!$F$79/(1+(Assumptions!$F$69+Assumptions!$F$70*$A36+Assumptions!$F$72+E$35))^DCF!$K$13)/1000} -> 7.844604 | F36: {=(SUMPRODUCT(DCF!$D$9:$K$9, 1/(1+(Assumptions!$F$69+Assumptions!$F$70*$A36+Assumptions!$F$72+F$35))^DCF!$D$13:$K$13) + DCF!$K$8*Assumptions!$F$79/(1+(Assumptions!$F$69+Assumptions!$F$70*$A36+Assumptions!$F$72+F$35))^DCF!$K$13)/1000} -> 7.6047337
A37: 0.83 | B37: {=(SUMPRODUCT(DCF!$D$9:$K$9, 1/(1+(Assumptions!$F$69+Assumptions!$F$70*$A37+Assumptions!$F$72+B$35))^DCF!$D$13:$K$13) + DCF!$K$8*Assumptions!$F$79/(1+(Assumptions!$F$69+Assumptions!$F$70*$A37+Assumptions!$F$72+B$35))^DCF!$K$13)/1000} -> 8.3072977 | C37: {=(SUMPRODUCT(DCF!$D$9:$K$9, 1/(1+(Assumptions!$F$69+Assumptions!$F$70*$A37+Assumptions!$F$72+C$35))^DCF!$D$13:$K$13) + DCF!$K$8*Assumptions!$F$79/(1+(Assumptions!$F$69+Assumptions!$F$70*$A37+Assumptions!$F$72+C$35))^DCF!$K$13)/1000} -> 8.050558 | D37: {=(SUMPRODUCT(DCF!$D$9:$K$9, 1/(1+(Assumptions!$F$69+Assumptions!$F$70*$A37+Assumptions!$F$72+D$35))^DCF!$D$13:$K$13) + DCF!$K$8*Assumptions!$F$79/(1+(Assumptions!$F$69+Assumptions!$F$70*$A37+Assumptions!$F$72+D$35))^DCF!$K$13)/1000} -> 7.8031975 | E37: {=(SUMPRODUCT(DCF!$D$9:$K$9, 1/(1+(Assumptions!$F$69+Assumptions!$F$70*$A37+Assumptions!$F$72+E$35))^DCF!$D$13:$K$13) + DCF!$K$8*Assumptions!$F$79/(1+(Assumptions!$F$69+Assumptions!$F$70*$A37+Assumptions!$F$72+E$35))^DCF!$K$13)/1000} -> 7.5648295 | F37: {=(SUMPRODUCT(DCF!$D$9:$K$9, 1/(1+(Assumptions!$F$69+Assumptions!$F$70*$A37+Assumptions!$F$72+F$35))^DCF!$D$13:$K$13) + DCF!$K$8*Assumptions!$F$79/(1+(Assumptions!$F$69+Assumptions!$F$70*$A37+Assumptions!$F$72+F$35))^DCF!$K$13)/1000} -> 7.3350848
A38: 1 | B38: {=(SUMPRODUCT(DCF!$D$9:$K$9, 1/(1+(Assumptions!$F$69+Assumptions!$F$70*$A38+Assumptions!$F$72+B$35))^DCF!$D$13:$K$13) + DCF!$K$8*Assumptions!$F$79/(1+(Assumptions!$F$69+Assumptions!$F$70*$A38+Assumptions!$F$72+B$35))^DCF!$K$13)/1000} -> 7.9183138 | C38: {=(SUMPRODUCT(DCF!$D$9:$K$9, 1/(1+(Assumptions!$F$69+Assumptions!$F$70*$A38+Assumptions!$F$72+C$35))^DCF!$D$13:$K$13) + DCF!$K$8*Assumptions!$F$79/(1+(Assumptions!$F$69+Assumptions!$F$70*$A38+Assumptions!$F$72+C$35))^DCF!$K$13)/1000} -> 7.6757663 | D38: {=(SUMPRODUCT(DCF!$D$9:$K$9, 1/(1+(Assumptions!$F$69+Assumptions!$F$70*$A38+Assumptions!$F$72+D$35))^DCF!$D$13:$K$13) + DCF!$K$8*Assumptions!$F$79/(1+(Assumptions!$F$69+Assumptions!$F$70*$A38+Assumptions!$F$72+D$35))^DCF!$K$13)/1000} -> 7.4420135 | E38: {=(SUMPRODUCT(DCF!$D$9:$K$9, 1/(1+(Assumptions!$F$69+Assumptions!$F$70*$A38+Assumptions!$F$72+E$35))^DCF!$D$13:$K$13) + DCF!$K$8*Assumptions!$F$79/(1+(Assumptions!$F$69+Assumptions!$F$70*$A38+Assumptions!$F$72+E$35))^DCF!$K$13)/1000} -> 7.2166953 | F38: {=(SUMPRODUCT(DCF!$D$9:$K$9, 1/(1+(Assumptions!$F$69+Assumptions!$F$70*$A38+Assumptions!$F$72+F$35))^DCF!$D$13:$K$13) + DCF!$K$8*Assumptions!$F$79/(1+(Assumptions!$F$69+Assumptions!$F$70*$A38+Assumptions!$F$72+F$35))^DCF!$K$13)/1000} -> 6.9994678
A39: 1.2 | B39: {=(SUMPRODUCT(DCF!$D$9:$K$9, 1/(1+(Assumptions!$F$69+Assumptions!$F$70*$A39+Assumptions!$F$72+B$35))^DCF!$D$13:$K$13) + DCF!$K$8*Assumptions!$F$79/(1+(Assumptions!$F$69+Assumptions!$F$70*$A39+Assumptions!$F$72+B$35))^DCF!$K$13)/1000} -> 7.488078 | C39: {=(SUMPRODUCT(DCF!$D$9:$K$9, 1/(1+(Assumptions!$F$69+Assumptions!$F$70*$A39+Assumptions!$F$72+C$35))^DCF!$D$13:$K$13) + DCF!$K$8*Assumptions!$F$79/(1+(Assumptions!$F$69+Assumptions!$F$70*$A39+Assumptions!$F$72+C$35))^DCF!$K$13)/1000} -> 7.2611009 | D39: {=(SUMPRODUCT(DCF!$D$9:$K$9, 1/(1+(Assumptions!$F$69+Assumptions!$F$70*$A39+Assumptions!$F$72+D$35))^DCF!$D$13:$K$13) + DCF!$K$8*Assumptions!$F$79/(1+(Assumptions!$F$69+Assumptions!$F$70*$A39+Assumptions!$F$72+D$35))^DCF!$K$13)/1000} -> 7.042282 | E39: {=(SUMPRODUCT(DCF!$D$9:$K$9, 1/(1+(Assumptions!$F$69+Assumptions!$F$70*$A39+Assumptions!$F$72+E$35))^DCF!$D$13:$K$13) + DCF!$K$8*Assumptions!$F$79/(1+(Assumptions!$F$69+Assumptions!$F$70*$A39+Assumptions!$F$72+E$35))^DCF!$K$13)/1000} -> 6.8312901 | F39: {=(SUMPRODUCT(DCF!$D$9:$K$9, 1/(1+(Assumptions!$F$69+Assumptions!$F$70*$A39+Assumptions!$F$72+F$35))^DCF!$D$13:$K$13) + DCF!$K$8*Assumptions!$F$79/(1+(Assumptions!$F$69+Assumptions!$F$70*$A39+Assumptions!$F$72+F$35))^DCF!$K$13)/1000} -> 6.6278087
A40: 1.4 | B40: {=(SUMPRODUCT(DCF!$D$9:$K$9, 1/(1+(Assumptions!$F$69+Assumptions!$F$70*$A40+Assumptions!$F$72+B$35))^DCF!$D$13:$K$13) + DCF!$K$8*Assumptions!$F$79/(1+(Assumptions!$F$69+Assumptions!$F$70*$A40+Assumptions!$F$72+B$35))^DCF!$K$13)/1000} -> 7.0854092 | C40: {=(SUMPRODUCT(DCF!$D$9:$K$9, 1/(1+(Assumptions!$F$69+Assumptions!$F$70*$A40+Assumptions!$F$72+C$35))^DCF!$D$13:$K$13) + DCF!$K$8*Assumptions!$F$79/(1+(Assumptions!$F$69+Assumptions!$F$70*$A40+Assumptions!$F$72+C$35))^DCF!$K$13)/1000} -> 6.8728777 | D40: {=(SUMPRODUCT(DCF!$D$9:$K$9, 1/(1+(Assumptions!$F$69+Assumptions!$F$70*$A40+Assumptions!$F$72+D$35))^DCF!$D$13:$K$13) + DCF!$K$8*Assumptions!$F$79/(1+(Assumptions!$F$69+Assumptions!$F$70*$A40+Assumptions!$F$72+D$35))^DCF!$K$13)/1000} -> 6.6679189 | E40: {=(SUMPRODUCT(DCF!$D$9:$K$9, 1/(1+(Assumptions!$F$69+Assumptions!$F$70*$A40+Assumptions!$F$72+E$35))^DCF!$D$13:$K$13) + DCF!$K$8*Assumptions!$F$79/(1+(Assumptions!$F$69+Assumptions!$F$70*$A40+Assumptions!$F$72+E$35))^DCF!$K$13)/1000} -> 6.4702277 | F40: {=(SUMPRODUCT(DCF!$D$9:$K$9, 1/(1+(Assumptions!$F$69+Assumptions!$F$70*$A40+Assumptions!$F$72+F$35))^DCF!$D$13:$K$13) + DCF!$K$8*Assumptions!$F$79/(1+(Assumptions!$F$69+Assumptions!$F$70*$A40+Assumptions!$F$72+F$35))^DCF!$K$13)/1000} -> 6.2795129
A42: Summary — Equity Value per Share Range
A43: Method | B43: Low EV ($B) | C43: Base EV ($B) | D43: High EV ($B) | E43: Per Share Range ($)
A44: Grid 1: WACC × Exit Multiple | B44: =MIN(B6:H12) -> 4.5972973 | C44: =E9 -> 7.4511993 | D44: =MAX(B6:H12) -> 10.872952 | E44: =ROUND((B44*1000-Assumptions!$F$62+Assumptions!$F$63)/Assumptions!$F$55,1) & " — " & ROUND((D44*1000-Assumptions!$F$62+Assumptions!$F$63)/Assumptions!$F$55,1) -> 12.9 — 28.2
A45: Grid 2: WACC × Terminal Growth (Gordon) | B45: =MIN(B17:H23) -> 4.3084693 | C45: =E20 -> 5.7788365 | D45: =MAX(B17:H23) -> 8.806904 | E45: =ROUND((B45*1000-Assumptions!$F$62+Assumptions!$F$63)/Assumptions!$F$55,1) & " — " & ROUND((D45*1000-Assumptions!$F$62+Assumptions!$F$63)/Assumptions!$F$55,1) -> 12.2 — 23.2
A46: Grid 3b: Beta × CSRP → EV | B46: =MIN(B36:F40) -> 6.2795129 | C46: =D37 -> 7.8031975 | D46: =MAX(B36:F40) -> 8.6201346 | E46: =ROUND((B46*1000-Assumptions!$F$62+Assumptions!$F$63)/Assumptions!$F$55,1) & " — " & ROUND((D46*1000-Assumptions!$F$62+Assumptions!$F$63)/Assumptions!$F$55,1) -> 17 — 22.7
A48: ="Live DCF base = "&TEXT(DCF!$C$38/Assumptions!$F$55,"$0.00")&"/sh ("&TEXT(DCF!$C$38/1000,"$0.00")&"B equity). Series G mark $10.10B = $24.63/sh (40% premium to live DCF). Sensitivity grids show pure-method dispersion; live DCF blends Exit Mult & Gordon (avg of $12.92B + $9.12B = $11.02B TV)." -> Live DCF base = $17.89/sh ($7.34B equity). Series G mark $10.10B = $24.63/sh (40% premium to live DCF). Sensitivity grids show pure-method dispersion; live DCF blends Exit Mult & Gordon (avg of $12.92B + $9.12B = $11.02B TV).
A50: 5. Y3+ Churn Cohort Sensitivity (Item 5)
A51: Tests Y3+ churn assumption (Assumptions!F21 Base = 12%) at 8%/10%/12%/14%/16%. The 2025 free-hardware pivot removed hardware sunk-cost stickiness — historical retention curves no longer cleanly extrapolate. This is the single biggest swing factor on terminal value because Y3+ is the dominant cohort by 2033.
A53: Y3+ Churn | B53: Scenario | C53: Blended Churn (steady-state) | D53: LTV ($) | E53: LTV/All-in CAC | F53: 2033 Members (M) | G53: Δ vs Base | H53: 2033 Revenue ($M) | I53: Implied Equity/Share | J53: Δ vs Base
A54: 0.08 | B54: Super-bull (Spotify-like) | C54: =(Members!$L$10/Members!$L$34)*Members!$L$15+(Members!$L$11/Members!$L$34)*Members!$L$16+(Members!$L$12/Members!$L$34)*A54 -> 0.11458071 | D54: =Assumptions!$F$11*Assumptions!$F$38/C54 -> 1820.062 | E54: =D54/Members!$L$55 -> 5.4442118 | F54: =Members!$L$34*(1-(A54-Assumptions!$F$21)*5) -> 13.10893 | G54: =F54/Members!$L$34-1 -> 0.2 | H54: =F54*((Members!$L$34/Members!$L$35)+1)/2*Assumptions!$F$11*(1+Assumptions!$D$9)^7/(1+Assumptions!$D$9)^7 -> 3648.6271 | I54: =DCF!$C$40*(F54/Members!$L$34) -> 21.47169 | J54: =I54/DCF!$C$40-1 -> 0.2
A55: 0.1 | B55: Bull (improvement) | C55: =(Members!$L$10/Members!$L$34)*Members!$L$15+(Members!$L$11/Members!$L$34)*Members!$L$16+(Members!$L$12/Members!$L$34)*A55 -> 0.12628768 | D55: =Assumptions!$F$11*Assumptions!$F$38/C55 -> 1651.3408 | E55: =D55/Members!$L$55 -> 4.9395288 | F55: =Members!$L$34*(1-(A55-Assumptions!$F$21)*5) -> 12.016519 | G55: =F55/Members!$L$34-1 -> 0.1 | H55: =F55*((Members!$L$34/Members!$L$35)+1)/2*Assumptions!$F$11*(1+Assumptions!$D$9)^7/(1+Assumptions!$D$9)^7 -> 3344.5748 | I55: =DCF!$C$40*(F55/Members!$L$34) -> 19.682382 | J55: =I55/DCF!$C$40-1 -> 0.1
A56: 0.12 | B56: Base (current) | C56: =(Members!$L$10/Members!$L$34)*Members!$L$15+(Members!$L$11/Members!$L$34)*Members!$L$16+(Members!$L$12/Members!$L$34)*A56 -> 0.13799466 | D56: =Assumptions!$F$11*Assumptions!$F$38/C56 -> 1511.2469 | E56: =D56/Members!$L$55 -> 4.5204768 | F56: =Members!$L$34*(1-(A56-Assumptions!$F$21)*5) -> 10.924108 | G56: =F56/Members!$L$34-1 -> 0 | H56: =F56*((Members!$L$34/Members!$L$35)+1)/2*Assumptions!$F$11*(1+Assumptions!$D$9)^7/(1+Assumptions!$D$9)^7 -> 3040.5226 | I56: =DCF!$C$40*(F56/Members!$L$34) -> 17.893075 | J56: =I56/DCF!$C$40-1 -> 0
A57: 0.14 | B57: Bear (degradation) | C57: =(Members!$L$10/Members!$L$34)*Members!$L$15+(Members!$L$11/Members!$L$34)*Members!$L$16+(Members!$L$12/Members!$L$34)*A57 -> 0.14970163 | D57: =Assumptions!$F$11*Assumptions!$F$38/C57 -> 1393.0643 | E57: =D57/Members!$L$55 -> 4.1669663 | F57: =Members!$L$34*(1-(A57-Assumptions!$F$21)*5) -> 9.8316973 | G57: =F57/Members!$L$34-1 -> -0.1 | H57: =F57*((Members!$L$34/Members!$L$35)+1)/2*Assumptions!$F$11*(1+Assumptions!$D$9)^7/(1+Assumptions!$D$9)^7 -> 2736.4703 | I57: =DCF!$C$40*(F57/Members!$L$34) -> 16.103767 | J57: =I57/DCF!$C$40-1 -> -0.1
A58: 0.16 | B58: Severe bear | C58: =(Members!$L$10/Members!$L$34)*Members!$L$15+(Members!$L$11/Members!$L$34)*Members!$L$16+(Members!$L$12/Members!$L$34)*A58 -> 0.16140861 | D58: =Assumptions!$F$11*Assumptions!$F$38/C58 -> 1292.0253 | E58: =D58/Members!$L$55 -> 3.8647361 | F58: =Members!$L$34*(1-(A58-Assumptions!$F$21)*5) -> 8.7392865 | G58: =F58/Members!$L$34-1 -> -0.2 | H58: =F58*((Members!$L$34/Members!$L$35)+1)/2*Assumptions!$F$11*(1+Assumptions!$D$9)^7/(1+Assumptions!$D$9)^7 -> 2432.418 | I58: =DCF!$C$40*(F58/Members!$L$34) -> 14.31446 | J58: =I58/DCF!$C$40-1 -> -0.2
A60: Note: Grids 1-3b use single-method TV (Exit Mult OR Gordon). Live DCF blends both at 50/50, yielding intermediate EV. Don't expect Grid base cells to tie to DCF!C32 — they show methodology dispersion, not central case. | B60: Y3+ churn is the single biggest swing on terminal equity. Moving from 8% → 12% (Spotify-like → mid-Peloton) costs $5.56/share, or ~20% of base equity. The 2025 free-hardware pivot removed hardware sunk-cost stickiness — historical retention curves don't extrapolate.
A61: Bear thesis | B61: Recommended: revise Bear case Y3+ churn from 12% to 14% (severe-bear). Bear/Base/Bull spans at 14%/8%/5% = wider, more honest range than current 12%/8%/5%. The Bear case should be a thesis about the world (free-hw pivot fails to lock retention), not a 1.5x multiplier on Base.
A63: 6. Probability Weighting Sensitivity — ProbWeighted Equity ($M)
A64: Tests robustness of input-weighted equity to choice of probability weights. P_Base = 1 − P_Bear − P_Bull. Yellow = base case (P_Bear=20%, P_Bull=30%, P_Base=50%). Cell value = P_Bear×Bear_Equity + P_Base×Base_Equity + P_Bull×Bull_Equity, where Bear/Base/Bull equities pull live from DCF!C60:C62. NOTE: This grid uses scenario-weighted decomposition (linear approximation); true input-weighted equity (DCF!C63 = $7,962M) differs by Jensen gap.
A65: P_Bear ↓ / P_Bull → | B65: 0.2 | C65: 0.25 | D65: 0.3 | E65: 0.35 | F65: 0.4
A66: 0.1 | B66: =$A66*DCF!$C$60+B$65*DCF!$C$62+(1-$A66-B$65)*DCF!$C$61 -> 9362.133 | C66: =$A66*DCF!$C$60+C$65*DCF!$C$62+(1-$A66-C$65)*DCF!$C$61 -> 9989.425 | D66: =$A66*DCF!$C$60+D$65*DCF!$C$62+(1-$A66-D$65)*DCF!$C$61 -> 10616.717 | E66: =$A66*DCF!$C$60+E$65*DCF!$C$62+(1-$A66-E$65)*DCF!$C$61 -> 11244.009 | F66: =$A66*DCF!$C$60+F$65*DCF!$C$62+(1-$A66-F$65)*DCF!$C$61 -> 11871.301
A67: 0.15 | B67: =$A67*DCF!$C$60+B$65*DCF!$C$62+(1-$A67-B$65)*DCF!$C$61 -> 9120.5355 | C67: =$A67*DCF!$C$60+C$65*DCF!$C$62+(1-$A67-C$65)*DCF!$C$61 -> 9747.8275 | D67: =$A67*DCF!$C$60+D$65*DCF!$C$62+(1-$A67-D$65)*DCF!$C$61 -> 10375.12 | E67: =$A67*DCF!$C$60+E$65*DCF!$C$62+(1-$A67-E$65)*DCF!$C$61 -> 11002.412 | F67: =$A67*DCF!$C$60+F$65*DCF!$C$62+(1-$A67-F$65)*DCF!$C$61 -> 11629.703
A68: 0.2 | B68: =$A68*DCF!$C$60+B$65*DCF!$C$62+(1-$A68-B$65)*DCF!$C$61 -> 8878.938 | C68: =$A68*DCF!$C$60+C$65*DCF!$C$62+(1-$A68-C$65)*DCF!$C$61 -> 9506.23 | D68: =$A68*DCF!$C$60+D$65*DCF!$C$62+(1-$A68-D$65)*DCF!$C$61 -> 10133.522 | E68: =$A68*DCF!$C$60+E$65*DCF!$C$62+(1-$A68-E$65)*DCF!$C$61 -> 10760.814 | F68: =$A68*DCF!$C$60+F$65*DCF!$C$62+(1-$A68-F$65)*DCF!$C$61 -> 11388.106
A69: 0.25 | B69: =$A69*DCF!$C$60+B$65*DCF!$C$62+(1-$A69-B$65)*DCF!$C$61 -> 8637.3405 | C69: =$A69*DCF!$C$60+C$65*DCF!$C$62+(1-$A69-C$65)*DCF!$C$61 -> 9264.6325 | D69: =$A69*DCF!$C$60+D$65*DCF!$C$62+(1-$A69-D$65)*DCF!$C$61 -> 9891.9245 | E69: =$A69*DCF!$C$60+E$65*DCF!$C$62+(1-$A69-E$65)*DCF!$C$61 -> 10519.216 | F69: =$A69*DCF!$C$60+F$65*DCF!$C$62+(1-$A69-F$65)*DCF!$C$61 -> 11146.508
A70: 0.3 | B70: =$A70*DCF!$C$60+B$65*DCF!$C$62+(1-$A70-B$65)*DCF!$C$61 -> 8395.743 | C70: =$A70*DCF!$C$60+C$65*DCF!$C$62+(1-$A70-C$65)*DCF!$C$61 -> 9023.035 | D70: =$A70*DCF!$C$60+D$65*DCF!$C$62+(1-$A70-D$65)*DCF!$C$61 -> 9650.327 | E70: =$A70*DCF!$C$60+E$65*DCF!$C$62+(1-$A70-E$65)*DCF!$C$61 -> 10277.619 | F70: =$A70*DCF!$C$60+F$65*DCF!$C$62+(1-$A70-F$65)*DCF!$C$61 -> 10904.911
A72: ="Read: ProbWeighted Equity ranges "&TEXT(MIN(B66:F70)/1000,"$0.00")&"B (most pessimistic) to "&TEXT(MAX(B66:F70)/1000,"$0.00")&"B (most optimistic). Span = "&TEXT((MAX(B66:F70)-MIN(B66:F70))/1000,"$0.00")&"B; base case D68 = "&TEXT(D68/1000,"$0.00")&"B. Bookend: scenario-weighted DCF!C65 = "&TEXT(DCF!$C$65/1000,"$0.00")&"B (Jensen-adjusted upper anchor)." -> Read: ProbWeighted Equity ranges $8.40B (most pessimistic) to $11.87B (most optimistic). Span = $3.48B; base case D68 = $10.13B. Bookend: scenario-weighted DCF!C65 = $10.13B (Jensen-adjusted upper anchor).
B73: 0.3
A74: 7. Members Lens — Triangulating Bottom-Up Members to DCF Equity ($/Share)
A75: Tests sensitivity of DCF equity to 2033 ending member count. Yellow = base case (Members!L34 = 10.92M). Block A holds 2033 FCF margin constant at base; Block B couples margin to scale (±60 bps per ±10% members) reflecting fixed-cost leverage. EV scales with terminal-year FCF; equity bridge held constant.
A77: Lens / Scenario | B77: 2033 Members (M) | C77: 2033 Revenue ($M) | D77: Block A: Margin Constant | E77: Block B: Margin Coupled | F77: Coupling Δ ($/sh) | G77: $/Share (Coupled)
A78: Lens D — Bottoms-up cohort | B78: 8.39 | C78: =B78*DCF!$K$8/Members!$L$34 -> 2835.1383 | D78: =((C78*DCF!$K$10)/DCF!$K$9)*DCF!$C$32+DCF!$C$36+DCF!$C$37 -> 5801.2724 | E78: =((C78*(DCF!$K$10+0.06*(B78/Members!$L$34-1)))/DCF!$K$9)*DCF!$C$32+DCF!$C$36+DCF!$C$37 -> 5457.7513 | F78: =(E78-D78)/DCF!$C$39 -> -0.83785619 | G78: =E78/DCF!$C$39 -> 13.311589
A79: Stress — Below median | B79: 9.5 | C79: =B79*DCF!$K$8/Members!$L$34 -> 3210.2282 | D79: =((C79*DCF!$K$10)/DCF!$K$9)*DCF!$C$32+DCF!$C$36+DCF!$C$37 -> 6473.5902 | E79: =((C79*(DCF!$K$10+0.06*(B79/Members!$L$34-1)))/DCF!$K$9)*DCF!$C$32+DCF!$C$36+DCF!$C$37 -> 6254.9989 | F79: =(E79-D79)/DCF!$C$39 -> -0.53314942 | G79: =E79/DCF!$C$39 -> 15.256095
A80: BASE — Lens B/C median (live) | B80: =Members!L34 -> 10.924108 | C80: =B80*DCF!$K$8/Members!$L$34 -> 3691.461 | D80: =((C80*DCF!$K$10)/DCF!$K$9)*DCF!$C$32+DCF!$C$36+DCF!$C$37 -> 7336.1607 | E80: =((C80*(DCF!$K$10+0.06*(B80/Members!$L$34-1)))/DCF!$K$9)*DCF!$C$32+DCF!$C$36+DCF!$C$37 -> 7336.1607 | F80: =(E80-D80)/DCF!$C$39 -> 0 | G80: =E80/DCF!$C$39 -> 17.893075
A81: Lens A — TAM × Penetration | B81: 11.95 | C81: =B81*DCF!$K$8/Members!$L$34 -> 4038.1291 | D81: =((C81*DCF!$K$10)/DCF!$K$9)*DCF!$C$32+DCF!$C$36+DCF!$C$37 -> 7957.5349 | E81: =((C81*(DCF!$K$10+0.06*(B81/Members!$L$34-1)))/DCF!$K$9)*DCF!$C$32+DCF!$C$36+DCF!$C$37 -> 8155.6126 | F81: =(E81-D81)/DCF!$C$39 -> 0.48311652 | G81: =E81/DCF!$C$39 -> 19.891738
A82: Stretch — Above lenses | B82: 13 | C82: =B82*DCF!$K$8/Members!$L$34 -> 4392.9438 | D82: =((C82*DCF!$K$10)/DCF!$K$9)*DCF!$C$32+DCF!$C$36+DCF!$C$37 -> 8593.5112 | E82: =((C82*(DCF!$K$10+0.06*(B82/Members!$L$34-1)))/DCF!$K$9)*DCF!$C$32+DCF!$C$36+DCF!$C$37 -> 9029.5391 | F82: =(E82-D82)/DCF!$C$39 -> 1.0634828 | G82: =E82/DCF!$C$39 -> 22.023266
A83: Bull — Hypergrowth | B83: 14.5 | C83: =B83*DCF!$K$8/Members!$L$34 -> 4899.8219 | D83: =((C83*DCF!$K$10)/DCF!$K$9)*DCF!$C$32+DCF!$C$36+DCF!$C$37 -> 9502.0487 | E83: =((C83*(DCF!$K$10+0.06*(B83/Members!$L$34-1)))/DCF!$K$9)*DCF!$C$32+DCF!$C$36+DCF!$C$37 -> 10339.807 | F83: =(E83-D83)/DCF!$C$39 -> 2.0433124 | G83: =E83/DCF!$C$39 -> 25.219041
